Workbook
Name DescMap_Description: Description_Map!$A$5:INDEX(Description_Map!$A:$A, MAX(5, COUNTA(Description_Map!$A:$A)+4))
Name DescMap_Label: Description_Map!$B$5:INDEX(Description_Map!$B:$B, MAX(5, COUNTA(Description_Map!$A:$A)+4))
Name RR_Period_Date: 'Rent Roll Recon'!$B$2
Name T12_Period_Date: 'T12 Analytics'!$E$2
Name RR_Input_Data: 'Rent Roll Input'!$A$7:$S$606
Name T12_Input_Data: 'T12 Input'!$A$12:$O$511
Name Property_Name: Cover!$B$5

Sheet Cover
A1: ALF Financial Analyzer | AZ1: Workbook landing — versions, links, orientation
A2: Senior-housing underwriting workbook — RR + T12 reconciliation, UW-ready output | AZ2: reference
AZ3: visible
A4: Property | AZ4: v0.2.7
A5: Property name
A7: Versions
A8: Substrate template | B8: v0.2.7
A9: Rent Roll Normalizer (app) | B9: v1.12.0
A10: T12 Normalizer | B10: v0.1.0
A12: Links
A13: GitHub | B13: https://github.com/<your-repo>/rent-roll-normalizer
A14: App URL | B14: https://rrnormalizer.streamlit.app/
A16: About
A17: This workbook is the underwriting destination for the Rent Roll Normalizer and T12 Normalizer pipeline. Paste normalized rent roll data into 'Rent Roll Input', T12 data into 'T12 Input', and the analytical sheets recalculate automatically.
A18: Visible tabs flow left to right: T12 inputs → RR inputs → reconciliation → UW Output. The 'Workbook Health' sheet is hidden by default — right-click any tab and choose 'Unhide' to access it for diagnostics, validation checks, and version pills.
A19: Property name entered at B5 above propagates to T12 Analytics via the Property_Name named range.

Sheet Dashboard
O1: Care Type | P1: Property | Q1: Market | AZ1: Underwriting at-a-glance KPI dashboard with embedded charts
B2: ="UNDERWRITING DASHBOARD"&IF(AND(ISTEXT(Cover!B5),Cover!B5<>"")," — "&Cover!B5,"") | O2: Independent Living | P2: =IFERROR(IF('T12 Analytics'!B6>0,'T12 Analytics'!B11/'T12 Analytics'!B6,NA()),NA()) | Q2: 0.91 | AZ2: Analytical (handoff)
B3: ="Period: "&IF(AND(ISTEXT('T12 Analytics'!E2),'T12 Analytics'!E2<>""),'T12 Analytics'!E2,"T12")&" | Basis: "&IF(AND(ISTEXT('T12 Analytics'!H2),'T12 Analytics'!H2<>""),'T12 Analytics'!H2,"As-Reported")&" | Refreshed: "&TEXT(TODAY(),"mmm d, yyyy") | O3: Assisted Living | P3: =IFERROR(IF('T12 Analytics'!C6>0,'T12 Analytics'!C11/'T12 Analytics'!C6,NA()),NA()) | Q3: 0.879 | AZ3: visible
O4: Memory Care | P4: =IFERROR(IF('T12 Analytics'!D6>0,'T12 Analytics'!D11/'T12 Analytics'!D6,NA()),NA()) | Q4: 0.88 | AZ4: v0.2.7
B5: OCCUPANCY | E5: EBITDARM MARGIN | H5: GOING-IN CAP RATE | K5: REVPOR | O5: Blended | P5: =IFERROR('T12 Analytics'!F134,NA()) | Q5: 0.895 | AZ5: All value cells are formula references into T12 Analytics, Rent Roll Recon, Monthly Trending, and Cover. 6 native Excel charts embedded. No source-of-truth data lives here. Supersedes the v0.2.4-v0.2.6 Investment Dashboard.
B6: =IFERROR(IF(ISNUMBER('T12 Analytics'!F134),TEXT('T12 Analytics'!F134,"0.0%"),"—"),"—") | E6: =IFERROR(IF(ISNUMBER('T12 Analytics'!F162),TEXT('T12 Analytics'!F162,"0.0%"),"—"),"—") | H6: =IFERROR(IF(ISNUMBER('T12 Analytics'!F118),TEXT('T12 Analytics'!F118,"0.00%"),"—"),"—") | K6: =IFERROR(IF(ISNUMBER('T12 Analytics'!F143),TEXT('T12 Analytics'!F143,"$#,##0"),"—"),"—")
B7: Normalized community occupancy | E7: Normalized (pre-mgmt fee) | H7: Normalized NOI / Purchase Price | K7: Normalized RevPOR per resident | O7: Payer | P7: Revenue
B8: =IF(ISNUMBER('T12 Analytics'!F134),IF('T12 Analytics'!F134>=0.9,"✓ At/above 90% stabilized hurdle",IF('T12 Analytics'!F134>=0.85,"⚠ Below stabilized, lease-up risk","✗ Distressed occupancy")),"— Source not populated") | E8: =IF(ISNUMBER('T12 Analytics'!F162),IF('T12 Analytics'!F162>=0.27,"✓ In-line with REIT SHOP avg ~27%",IF('T12 Analytics'!F162>=0.22,"⚠ Below institutional median","✗ Margin distressed")),"— Source not populated") | H8: =IF(ISNUMBER('T12 Analytics'!F118),IF('T12 Analytics'!F118>=0.07,"✓ Above 6.2% market avg",IF('T12 Analytics'!F118>=0.055,"⚠ At market, modest yield","✗ Below market, aggressive")),"— Source not populated") | K8: =IF(ISNUMBER('T12 Analytics'!F143),"vs blended market $5,500-$6,500","— Source not populated") | O8: Private Pay | P8: =IFERROR(IF(ISNUMBER(E43),E43,0),0)
B10: EFFECTIVE GROSS INCOME | E10: EBITDAR | H10: PRICE / BED
B11: =IFERROR(IF(ISNUMBER('T12 Analytics'!F52),TEXT('T12 Analytics'!F52,"$#,##0"),"—"),"—") | E11: =IFERROR(IF(ISNUMBER('T12 Analytics'!F163),TEXT('T12 Analytics'!F163,"$#,##0"),"—"),"—") | H11: =IFERROR(IF(AND(ISNUMBER('T12 Analytics'!F117),ISNUMBER('T12 Analytics'!E6),'T12 Analytics'!E6>0),TEXT('T12 Analytics'!F117/'T12 Analytics'!E6,"$#,##0"),"—"),"—")
B12: Annual revenue (T12) | E12: After mgmt fee (lender NOI) | H12: Purchase price / licensed bed
B13: =IF(ISNUMBER('T12 Analytics'!F52),"✓ EGI captured","— Source not populated") | E13: =IFERROR(IF(ISNUMBER('T12 Analytics'!F164),"Margin: "&TEXT('T12 Analytics'!F164,"0.0%"),"— Margin n/a"),"—") | H13: =IFERROR(IF(AND(ISNUMBER('T12 Analytics'!F117),ISNUMBER('T12 Analytics'!E6),'T12 Analytics'!E6>0),"on "&TEXT('T12 Analytics'!E6,"#,##0")&" licensed beds","— Source not populated"),"—")
O14: Medicaid | P14: =IFERROR(IF(ISNUMBER(E44),E44,0),0)
B15: OPERATING PERFORMANCE | O15: LTC Insurance | P15: =IFERROR(IF(ISNUMBER(E45),E45,0),0)
O16: VA | P16: =IFERROR(IF(ISNUMBER(E46),E46,0),0)
B17: CAPACITY & OCCUPANCY | E17: REVENUE & RATE | H17: PROFITABILITY | K17: COST STRUCTURE & LABOR | O17: Managed Care | P17: =IFERROR(IF(ISNUMBER(E47),E47,0),0)
B18: Licensed beds (total) | C18: =IFERROR(IF(ISNUMBER('T12 Analytics'!E6),'T12 Analytics'!E6,"—"),"—") | E18: Gross potential rent | F18: =IFERROR(IF(ISNUMBER('T12 Analytics'!F37),'T12 Analytics'!F37,"—"),"—") | H18: EBITDARM $ | I18: =IFERROR(IF(ISNUMBER('T12 Analytics'!F161),'T12 Analytics'!F161,"—"),"—") | K18: Total labor % EGI | L18: =IFERROR(IF(ISNUMBER('T12 Analytics'!F148),'T12 Analytics'!F148,"—"),"—") | O18: Self-Pay | P18: =IFERROR(IF(ISNUMBER(E48),E48,0),0)
B19: IL / AL / MC | C19: =IFERROR(IF(ISNUMBER('T12 Analytics'!B6),TEXT('T12 Analytics'!B6,"0")&" / "&TEXT('T12 Analytics'!C6,"0")&" / "&TEXT('T12 Analytics'!D6,"0"),"—"),"—") | E19: Effective gross income | F19: =IFERROR(IF(ISNUMBER('T12 Analytics'!F52),'T12 Analytics'!F52,"—"),"—") | H19: EBITDARM margin | I19: =IFERROR(IF(ISNUMBER('T12 Analytics'!F162),'T12 Analytics'!F162,"—"),"—") | K19: Direct labor % EGI | L19: =IFERROR(IF(ISNUMBER('T12 Analytics'!F149),'T12 Analytics'!F149,"—"),"—") | O19: Other | P19: =IFERROR(IF(ISNUMBER(E49),E49,0),0)
B20: Avg occupied beds | C20: =IFERROR(IF(ISNUMBER('T12 Analytics'!E11),'T12 Analytics'!E11,"—"),"—") | E20: Blended ADR / day | F20: =IFERROR(IF(ISNUMBER('T12 Analytics'!F140),'T12 Analytics'!F140,"—"),"—") | H20: EBITDAR $ (post mgmt fee) | I20: =IFERROR(IF(ISNUMBER('T12 Analytics'!F163),'T12 Analytics'!F163,"—"),"—") | K20: Overtime % | L20: =IFERROR(IF(ISNUMBER('T12 Analytics'!F150),'T12 Analytics'!F150,"—"),"—")
B21: Community occupancy % | C21: =IFERROR(IF(ISNUMBER('T12 Analytics'!F134),'T12 Analytics'!F134,"—"),"—") | E21: RevPOR (blended) | F21: =IFERROR(IF(ISNUMBER('T12 Analytics'!F143),'T12 Analytics'!F143,"—"),"—") | H21: EBITDAR margin | I21: =IFERROR(IF(ISNUMBER('T12 Analytics'!F164),'T12 Analytics'!F164,"—"),"—") | K21: Agency labor % | L21: =IFERROR(IF(ISNUMBER('T12 Analytics'!F152),'T12 Analytics'!F152,"—"),"—")
B22: Economic occupancy % | C22: =IFERROR(IF(ISNUMBER('Rent Roll Recon'!E13),'Rent Roll Recon'!E13,"—"),"—") | E22: RevPAB | F22: =IFERROR(IF(ISNUMBER('T12 Analytics'!F145),'T12 Analytics'!F145,"—"),"—") | H22: EGI / occupied bed | I22: =IFERROR(IF(ISNUMBER('T12 Analytics'!F144),'T12 Analytics'!F144,"—"),"—") | K22: Food PPD | L22: =IFERROR(IF(ISNUMBER('T12 Analytics'!F154),'T12 Analytics'!F154,"—"),"—")
B23: Loss to lease % | C23: =IFERROR(IF(AND(ISNUMBER('T12 Analytics'!F41),ISNUMBER('T12 Analytics'!F37),'T12 Analytics'!F37<>0),ABS('T12 Analytics'!F41)/'T12 Analytics'!F37,"—"),"—") | E23: Level of care % | F23: =IFERROR(IF(ISNUMBER('T12 Analytics'!F146),'T12 Analytics'!F146,"—"),"—") | H23: Opex / occupied bed | I23: =IFERROR(IF(ISNUMBER('T12 Analytics'!F160),'T12 Analytics'!F160,"—"),"—") | K23: Mgmt fee % | L23: =IFERROR(IF(ISNUMBER('T12 Analytics'!F157),'T12 Analytics'!F157,"—"),"—")
B24: Vacancy % | C24: =IFERROR(IF(AND(ISNUMBER('T12 Analytics'!F38),ISNUMBER('T12 Analytics'!F37),'T12 Analytics'!F37<>0),ABS('T12 Analytics'!F38)/'T12 Analytics'!F37,"—"),"—") | E24: Bad debt % | F24: =IFERROR(IF(ISNUMBER('T12 Analytics'!F158),'T12 Analytics'!F158,"—"),"—") | H24: Total opex $ | I24: =IFERROR(IF(ISNUMBER('T12 Analytics'!F105),'T12 Analytics'!F105,"—"),"—") | K24: Insurance (P&C) % | L24: =IFERROR(IF(ISNUMBER('T12 Analytics'!F159),'T12 Analytics'!F159,"—"),"—")
B26: VALUATION & MARKET BENCHMARKING
B28: DEAL ECONOMICS | H28: OCCUPANCY vs MARKET (NIC MAP Q1 2026)
B29: Metric | D29: Property | E29: Market | F29: Read
B30: Purchase price | D30: =IFERROR(IF(ISNUMBER('T12 Analytics'!F117),'T12 Analytics'!F117,"—"),"—") | E30: n/a | F30: —
B31: Price / total bed | D31: =IFERROR(IF(AND(ISNUMBER('T12 Analytics'!F117),ISNUMBER('T12 Analytics'!E6),'T12 Analytics'!E6>0),'T12 Analytics'!F117/'T12 Analytics'!E6,"—"),"—") | E31: $220-280k | F31: =IF(ISNUMBER(D31),IF(D31<=280000,"✓",IF(D31<=350000,"⚠","✗")),"—")
B32: Going-in cap rate | D32: =IFERROR(IF(ISNUMBER('T12 Analytics'!F118),'T12 Analytics'!F118,"—"),"—") | E32: 0.062 | F32: =IF(ISNUMBER(D32),IF(D32>=0.07,"✓",IF(D32>=0.055,"⚠","✗")),"—")
B33: EBITDAR cap rate | D33: =IFERROR(IF(ISNUMBER('T12 Analytics'!F120),'T12 Analytics'!F120,"—"),"—") | E33: 5.7-6.5% | F33: =IF(ISNUMBER(D33),IF(D33>=0.065,"✓",IF(D33>=0.055,"⚠","✗")),"—")
B34: EBITDARM margin | D34: =IFERROR(IF(ISNUMBER('T12 Analytics'!F162),'T12 Analytics'!F162,"—"),"—") | E34: 0.27 | F34: =IF(ISNUMBER(D34),IF(D34>=0.27,"✓",IF(D34>=0.22,"⚠","✗")),"—")
B35: Community occupancy | D35: =IFERROR(IF(ISNUMBER('T12 Analytics'!F134),'T12 Analytics'!F134,"—"),"—") | E35: 0.895 | F35: =IF(ISNUMBER(D35),IF(D35>=0.9,"✓",IF(D35>=0.85,"⚠","✗")),"—")
B36: Labor % EGI | D36: =IFERROR(IF(ISNUMBER('T12 Analytics'!F148),'T12 Analytics'!F148,"—"),"—") | E36: 43-45% | F36: =IF(ISNUMBER(D36),IF(D36<=0.45,"✓",IF(D36<=0.5,"⚠","✗")),"—")
B37: Agency labor % | D37: =IFERROR(IF(ISNUMBER('T12 Analytics'!F152),'T12 Analytics'!F152,"—"),"—") | E37: <3% | F37: =IF(ISNUMBER(D37),IF(D37<=0.03,"✓",IF(D37<=0.06,"⚠","✗")),"—")
B39: PAYER MIX
B41: Payer Mix — Revenue & Census | H41: Payer Mix — Revenue Share
B42: Payer Type | C42: Resident Count | D42: % of Census | E42: Revenue (T12) | F42: % of Revenue
B43: Private Pay | C43: =IFERROR(IF(ISNUMBER('Rent Roll Recon'!B40),'Rent Roll Recon'!B40,"—"),"—") | D43: =IFERROR(IF(ISNUMBER('Rent Roll Recon'!C40),'Rent Roll Recon'!C40,"—"),"—") | E43: =IFERROR(IF(ISNUMBER('Rent Roll Recon'!H40),'Rent Roll Recon'!H40,"—"),"—") | F43: =IFERROR(IF(ISNUMBER('Rent Roll Recon'!I40),'Rent Roll Recon'!I40,"—"),"—")
B44: Medicaid | C44: =IFERROR(IF(ISNUMBER('Rent Roll Recon'!B41),'Rent Roll Recon'!B41,"—"),"—") | D44: =IFERROR(IF(ISNUMBER('Rent Roll Recon'!C41),'Rent Roll Recon'!C41,"—"),"—") | E44: =IFERROR(IF(ISNUMBER('Rent Roll Recon'!H41),'Rent Roll Recon'!H41,"—"),"—") | F44: =IFERROR(IF(ISNUMBER('Rent Roll Recon'!I41),'Rent Roll Recon'!I41,"—"),"—")
B45: LTC Insurance | C45: =IFERROR(IF(ISNUMBER('Rent Roll Recon'!B42),'Rent Roll Recon'!B42,"—"),"—") | D45: =IFERROR(IF(ISNUMBER('Rent Roll Recon'!C42),'Rent Roll Recon'!C42,"—"),"—") | E45: =IFERROR(IF(ISNUMBER('Rent Roll Recon'!H42),'Rent Roll Recon'!H42,"—"),"—") | F45: =IFERROR(IF(ISNUMBER('Rent Roll Recon'!I42),'Rent Roll Recon'!I42,"—"),"—")
B46: VA | C46: =IFERROR(IF(ISNUMBER('Rent Roll Recon'!B43),'Rent Roll Recon'!B43,"—"),"—") | D46: =IFERROR(IF(ISNUMBER('Rent Roll Recon'!C43),'Rent Roll Recon'!C43,"—"),"—") | E46: =IFERROR(IF(ISNUMBER('Rent Roll Recon'!H43),'Rent Roll Recon'!H43,"—"),"—") | F46: =IFERROR(IF(ISNUMBER('Rent Roll Recon'!I43),'Rent Roll Recon'!I43,"—"),"—")
B47: Managed Care | C47: =IFERROR(IF(ISNUMBER('Rent Roll Recon'!B44),'Rent Roll Recon'!B44,"—"),"—") | D47: =IFERROR(IF(ISNUMBER('Rent Roll Recon'!C44),'Rent Roll Recon'!C44,"—"),"—") | E47: =IFERROR(IF(ISNUMBER('Rent Roll Recon'!H44),'Rent Roll Recon'!H44,"—"),"—") | F47: =IFERROR(IF(ISNUMBER('Rent Roll Recon'!I44),'Rent Roll Recon'!I44,"—"),"—")
B48: Self-Pay | C48: =IFERROR(IF(ISNUMBER('Rent Roll Recon'!B45),'Rent Roll Recon'!B45,"—"),"—") | D48: =IFERROR(IF(ISNUMBER('Rent Roll Recon'!C45),'Rent Roll Recon'!C45,"—"),"—") | E48: =IFERROR(IF(ISNUMBER('Rent Roll Recon'!H45),'Rent Roll Recon'!H45,"—"),"—") | F48: =IFERROR(IF(ISNUMBER('Rent Roll Recon'!I45),'Rent Roll Recon'!I45,"—"),"—")
B49: Other | C49: =IFERROR(IF(ISNUMBER('Rent Roll Recon'!B46),'Rent Roll Recon'!B46,"—"),"—") | D49: =IFERROR(IF(ISNUMBER('Rent Roll Recon'!C46),'Rent Roll Recon'!C46,"—"),"—") | E49: =IFERROR(IF(ISNUMBER('Rent Roll Recon'!H46),'Rent Roll Recon'!H46,"—"),"—") | F49: =IFERROR(IF(ISNUMBER('Rent Roll Recon'!I46),'Rent Roll Recon'!I46,"—"),"—")
B50: Total | C50: =SUM(C43:C49) | D50: 1 | E50: =SUM(E43:E49) | F50: 1
B52: RISK FLAGS & UNDERWRITING CHECKS
B54: Risk Indicator | E54: Property | F54: Threshold | G54: Flag | H54: Read
B55: Occupancy gap to market | E55: =IFERROR(IF(ISNUMBER('T12 Analytics'!F134),'T12 Analytics'!F134-0.895,"—"),"—") | F55: ≥ 0 ppt | G55: =IFERROR(IF(NOT(ISNUMBER('T12 Analytics'!F134)),"⚪",IF('T12 Analytics'!F134>=0.895,"✅",IF('T12 Analytics'!F134>=0.85,"⚠️","❌"))),"⚪") | H55: =IFERROR(IF(NOT(ISNUMBER('T12 Analytics'!F134)),"No data",IF('T12 Analytics'!F134>=0.895,"At or above NIC MAP",IF('T12 Analytics'!F134>=0.85,"Below market — lease-up risk","Significantly below market"))),"")
B56: Agency labor reliance | E56: =IFERROR(IF(ISNUMBER('T12 Analytics'!F152),'T12 Analytics'!F152,"—"),"—") | F56: < 3% of labor | G56: =IFERROR(IF(NOT(ISNUMBER('T12 Analytics'!F152)),"⚪",IF('T12 Analytics'!F152<0.03,"✅",IF('T12 Analytics'!F152<0.06,"⚠️","❌"))),"⚪") | H56: =IFERROR(IF(NOT(ISNUMBER('T12 Analytics'!F152)),"No data",IF('T12 Analytics'!F152<0.03,"Healthy in-house staffing",IF('T12 Analytics'!F152<0.06,"Moderate agency reliance","Heavy agency — staffing crisis"))),"")
B57: Overtime burden | E57: =IFERROR(IF(ISNUMBER('T12 Analytics'!F150),'T12 Analytics'!F150,"—"),"—") | F57: < 5% of labor | G57: =IFERROR(IF(NOT(ISNUMBER('T12 Analytics'!F150)),"⚪",IF('T12 Analytics'!F150<0.05,"✅",IF('T12 Analytics'!F150<0.08,"⚠️","❌"))),"⚪") | H57: =IFERROR(IF(NOT(ISNUMBER('T12 Analytics'!F150)),"No data",IF('T12 Analytics'!F150<0.05,"Schedule well-managed",IF('T12 Analytics'!F150<0.08,"Elevated OT","Severe OT — understaffed"))),"")
B58: Medicaid concentration | E58: =IFERROR(IF(ISNUMBER('Rent Roll Recon'!I41),'Rent Roll Recon'!I41,"—"),"—") | F58: < 20% of rev | G58: =IFERROR(IF(NOT(ISNUMBER('Rent Roll Recon'!I41)),"⚪",IF('Rent Roll Recon'!I41<0.2,"✅",IF('Rent Roll Recon'!I41<0.35,"⚠️","❌"))),"⚪") | H58: =IFERROR(IF(NOT(ISNUMBER('Rent Roll Recon'!I41)),"No data",IF('Rent Roll Recon'!I41<0.2,"Private-pay dominant",IF('Rent Roll Recon'!I41<0.35,"Material reimbursement risk","Heavy reimbursement exposure"))),"")
B59: Bad debt expense | E59: =IFERROR(IF(ISNUMBER('T12 Analytics'!F158),'T12 Analytics'!F158,"—"),"—") | F59: < 1% of rev | G59: =IFERROR(IF(NOT(ISNUMBER('T12 Analytics'!F158)),"⚪",IF('T12 Analytics'!F158<0.01,"✅",IF('T12 Analytics'!F158<0.025,"⚠️","❌"))),"⚪") | H59: =IFERROR(IF(NOT(ISNUMBER('T12 Analytics'!F158)),"No data",IF('T12 Analytics'!F158<0.01,"Strong collections",IF('T12 Analytics'!F158<0.025,"Watch AR aging","Collections issue"))),"")
B60: EBITDARM margin | E60: =IFERROR(IF(ISNUMBER('T12 Analytics'!F162),'T12 Analytics'!F162,"—"),"—") | F60: ≥ 25% | G60: =IFERROR(IF(NOT(ISNUMBER('T12 Analytics'!F162)),"⚪",IF('T12 Analytics'!F162>=0.25,"✅",IF('T12 Analytics'!F162>=0.18,"⚠️","❌"))),"⚪") | H60: =IFERROR(IF(NOT(ISNUMBER('T12 Analytics'!F162)),"No data",IF('T12 Analytics'!F162>=0.25,"Institutional-quality margin",IF('T12 Analytics'!F162>=0.18,"Sub-institutional margin","Significant margin compression"))),"")
B61: Going-in cap rate vs market | E61: =IFERROR(IF(ISNUMBER('T12 Analytics'!F118),'T12 Analytics'!F118,"—"),"—") | F61: ≥ 6.5% | G61: =IFERROR(IF(NOT(ISNUMBER('T12 Analytics'!F118)),"⚪",IF('T12 Analytics'!F118>=0.065,"✅",IF('T12 Analytics'!F118>=0.055,"⚠️","❌"))),"⚪") | H61: =IFERROR(IF(NOT(ISNUMBER('T12 Analytics'!F118)),"No data",IF('T12 Analytics'!F118>=0.065,"Wide of 6.2% market avg",IF('T12 Analytics'!F118>=0.055,"In line with market","Tight pricing — reaching"))),"")
B62: Loss to lease | E62: =IFERROR(IF(ISNUMBER('T12 Analytics'!F41),IFERROR('T12 Analytics'!F41/'T12 Analytics'!F37,0),"—"),"—") | F62: < 5% of GPR | G62: =IFERROR(IF(NOT(ISNUMBER('T12 Analytics'!F41)),"⚪",IF(IFERROR('T12 Analytics'!F41/'T12 Analytics'!F37,0)<0.05,"✅",IF(IFERROR('T12 Analytics'!F41/'T12 Analytics'!F37,0)<0.1,"⚠️","❌"))),"⚪") | H62: =IFERROR(IF(NOT(ISNUMBER('T12 Analytics'!F41)),"No data",IF(IFERROR('T12 Analytics'!F41/'T12 Analytics'!F37,0)<0.05,"Rate near market",IF(IFERROR('T12 Analytics'!F41/'T12 Analytics'!F37,0)<0.1,"Mark-to-market upside","Material rate compression"))),"")
B64: CAPACITY & OCCUPANCY — IL / AL / MC | H64: REVENUE QUALITY — ADR, RevPOR & ACUITY
B66: Care Type | C66: Licensed | D66: Occupied | E66: Occ % | F66: Target | H66: Metric | I66: IL | J66: AL | K66: MC | L66: Blended
B67: Independent Living | C67: =IFERROR(IF(ISNUMBER('T12 Analytics'!B6),'T12 Analytics'!B6,"—"),"—") | D67: =IFERROR(IF(ISNUMBER('T12 Analytics'!B11),'T12 Analytics'!B11,"—"),"—") | E67: =IFERROR(IF(AND(ISNUMBER(C67),ISNUMBER(D67),C67>0),D67/C67,"—"),"—") | F67: 90%+ | H67: ADR ($/bed/mo) | I67: =IFERROR(IF(AND(ISNUMBER('T12 Analytics'!B16),ISNUMBER('T12 Analytics'!B11),'T12 Analytics'!B11>0),'T12 Analytics'!B16/('T12 Analytics'!B11*12),"—"),"—") | J67: =IFERROR(IF(AND(ISNUMBER('T12 Analytics'!C16),ISNUMBER('T12 Analytics'!C11),'T12 Analytics'!C11>0),'T12 Analytics'!C16/('T12 Analytics'!C11*12),"—"),"—") | K67: =IFERROR(IF(AND(ISNUMBER('T12 Analytics'!D16),ISNUMBER('T12 Analytics'!D11),'T12 Analytics'!D11>0),'T12 Analytics'!D16/('T12 Analytics'!D11*12),"—"),"—") | L67: =IFERROR(IF(AND(ISNUMBER('T12 Analytics'!E16),ISNUMBER('T12 Analytics'!E11),'T12 Analytics'!E11>0),'T12 Analytics'!E16/('T12 Analytics'!E11*12),"—"),"—")
B68: Assisted Living | C68: =IFERROR(IF(ISNUMBER('T12 Analytics'!C6),'T12 Analytics'!C6,"—"),"—") | D68: =IFERROR(IF(ISNUMBER('T12 Analytics'!C11),'T12 Analytics'!C11,"—"),"—") | E68: =IFERROR(IF(AND(ISNUMBER(C68),ISNUMBER(D68),C68>0),D68/C68,"—"),"—") | F68: 87–92% | H68: RevPOR (base + LOC) | I68: =IFERROR(IF(AND(ISNUMBER('T12 Analytics'!B16),ISNUMBER('T12 Analytics'!B11),'T12 Analytics'!B11>0),('T12 Analytics'!B16+IFERROR('T12 Analytics'!B23,0))/('T12 Analytics'!B11*12),"—"),"—") | J68: =IFERROR(IF(AND(ISNUMBER('T12 Analytics'!C16),ISNUMBER('T12 Analytics'!C11),'T12 Analytics'!C11>0),('T12 Analytics'!C16+IFERROR('T12 Analytics'!C23,0))/('T12 Analytics'!C11*12),"—"),"—") | K68: =IFERROR(IF(AND(ISNUMBER('T12 Analytics'!D16),ISNUMBER('T12 Analytics'!D11),'T12 Analytics'!D11>0),('T12 Analytics'!D16+IFERROR('T12 Analytics'!D23,0))/('T12 Analytics'!D11*12),"—"),"—") | L68: =IFERROR(IF(AND(ISNUMBER('T12 Analytics'!E16),ISNUMBER('T12 Analytics'!E11),'T12 Analytics'!E11>0),('T12 Analytics'!E16+IFERROR('T12 Analytics'!E23,0))/('T12 Analytics'!E11*12),"—"),"—")
B69: Memory Care | C69: =IFERROR(IF(ISNUMBER('T12 Analytics'!D6),'T12 Analytics'!D6,"—"),"—") | D69: =IFERROR(IF(ISNUMBER('T12 Analytics'!D11),'T12 Analytics'!D11,"—"),"—") | E69: =IFERROR(IF(AND(ISNUMBER(C69),ISNUMBER(D69),C69>0),D69/C69,"—"),"—") | F69: 85–90% | H69: LOC as % of base rent | I69: =IFERROR(IF(AND(ISNUMBER('T12 Analytics'!B23),ISNUMBER('T12 Analytics'!B16),'T12 Analytics'!B16<>0),'T12 Analytics'!B23/'T12 Analytics'!B16,"—"),"—") | J69: =IFERROR(IF(AND(ISNUMBER('T12 Analytics'!C23),ISNUMBER('T12 Analytics'!C16),'T12 Analytics'!C16<>0),'T12 Analytics'!C23/'T12 Analytics'!C16,"—"),"—") | K69: =IFERROR(IF(AND(ISNUMBER('T12 Analytics'!D23),ISNUMBER('T12 Analytics'!D16),'T12 Analytics'!D16<>0),'T12 Analytics'!D23/'T12 Analytics'!D16,"—"),"—") | L69: =IFERROR(IF(AND(ISNUMBER('T12 Analytics'!E23),ISNUMBER('T12 Analytics'!E16),'T12 Analytics'!E16<>0),'T12 Analytics'!E23/'T12 Analytics'!E16,"—"),"—")
B70: Blended | C70: =IFERROR(IF(ISNUMBER('T12 Analytics'!E6),'T12 Analytics'!E6,"—"),"—") | D70: =IFERROR(IF(ISNUMBER('T12 Analytics'!E11),'T12 Analytics'!E11,"—"),"—") | E70: =IFERROR(IF(AND(ISNUMBER(C70),ISNUMBER(D70),C70>0),D70/C70,"—"),"—") | F70: — | H70: EGI / occupied bed / mo | I70: — | J70: — | K70: — | L70: =IFERROR(IF(AND(ISNUMBER('T12 Analytics'!F52),ISNUMBER('T12 Analytics'!E11),'T12 Analytics'!E11>0),'T12 Analytics'!F52/('T12 Analytics'!E11*12),"—"),"—")
B72: OPERATING MARGIN — T12 vs. INSTITUTIONAL BENCHMARK | H72: VALUATION — CAP RATE & PER-BED PRICING
B74: Line item | C74: T12 $ | D74: % EGI | E74: Benchmark | F74: Status | H74: Metric | I74: T12 Actual | K74: Normalized
B75: Effective Gross Income | C75: =IFERROR(IF(ISNUMBER('T12 Analytics'!F52),'T12 Analytics'!F52,"—"),"—") | D75: 1 | E75: 1 | H75: Purchase price (input) | I75: =IFERROR(IF(ISNUMBER('T12 Analytics'!F117),'T12 Analytics'!F117,"—"),"—") | K75: =IFERROR(IF(ISNUMBER('T12 Analytics'!F117),'T12 Analytics'!F117,"—"),"—")
B76: Labor & burden | C76: =IFERROR(IF(ISNUMBER('T12 Analytics'!F76),'T12 Analytics'!F76,"—"),"—") | D76: =IFERROR(IF(AND(ISNUMBER(C76),ISNUMBER($C$75),$C$75<>0),C76/$C$75,"—"),"—") | E76: 55–65% | F76: =IF(NOT(ISNUMBER(D76)),"—",IF(D76=0,"—",IF(D76>0.65,"⚠ HIGH",IF(D76<0.55,"✓ LOW","✓ OK")))) | H76: Going-in cap (EBITDARM) | I76: =IFERROR(IF(AND(ISNUMBER('T12 Analytics'!F161),ISNUMBER('T12 Analytics'!F117),'T12 Analytics'!F117<>0),'T12 Analytics'!F161/'T12 Analytics'!F117,"—"),"—") | K76: =IFERROR(IF(AND(ISNUMBER('T12 Analytics'!F161),ISNUMBER('T12 Analytics'!F117),'T12 Analytics'!F117<>0),'T12 Analytics'!F161/'T12 Analytics'!F117,"—"),"—")
B77: Non-labor opex | C77: =IFERROR(IF(ISNUMBER('T12 Analytics'!F103),'T12 Analytics'!F103,"—"),"—") | D77: =IFERROR(IF(AND(ISNUMBER(C77),ISNUMBER($C$75),$C$75<>0),C77/$C$75,"—"),"—") | E77: 25–35% | F77: =IF(NOT(ISNUMBER(D77)),"—",IF(D77=0,"—",IF(D77>0.35,"⚠ HIGH",IF(D77<0.25,"✓ LOW","✓ OK")))) | H77: Going-in cap (EBITDAR) | I77: =IFERROR(IF(AND(ISNUMBER('T12 Analytics'!F163),ISNUMBER('T12 Analytics'!F117),'T12 Analytics'!F117<>0),'T12 Analytics'!F163/'T12 Analytics'!F117,"—"),"—") | K77: =IFERROR(IF(AND(ISNUMBER('T12 Analytics'!F163),ISNUMBER('T12 Analytics'!F117),'T12 Analytics'!F117<>0),'T12 Analytics'!F163/'T12 Analytics'!F117,"—"),"—")
B78: EBITDARM (NOI) | C78: =IFERROR(IF(ISNUMBER('T12 Analytics'!F161),'T12 Analytics'!F161,"—"),"—") | D78: =IFERROR(IF(AND(ISNUMBER(C78),ISNUMBER($C$75),$C$75<>0),C78/$C$75,"—"),"—") | E78: 20–30%+ | F78: =IF(NOT(ISNUMBER(D78)),"—",IF(D78=0,"—",IF(D78<0.2,"⚠ LOW",IF(D78>0.3,"✓ STRONG","✓ OK")))) | H78: Price / licensed bed | I78: =IFERROR(IF(AND(ISNUMBER('T12 Analytics'!F117),ISNUMBER('T12 Analytics'!E6),'T12 Analytics'!E6>0),'T12 Analytics'!F117/'T12 Analytics'!E6,"—"),"—") | K78: =IFERROR(IF(AND(ISNUMBER('T12 Analytics'!F117),ISNUMBER('T12 Analytics'!E6),'T12 Analytics'!E6>0),'T12 Analytics'!F117/'T12 Analytics'!E6,"—"),"—")
B79: EBITDAR (after mgmt fee) | C79: =IFERROR(IF(ISNUMBER('T12 Analytics'!F163),'T12 Analytics'!F163,"—"),"—") | D79: =IFERROR(IF(AND(ISNUMBER(C79),ISNUMBER($C$75),$C$75<>0),C79/$C$75,"—"),"—") | E79: 15–25%+ | F79: =IF(NOT(ISNUMBER(D79)),"—",IF(D79=0,"—",IF(D79<0.15,"⚠ LOW",IF(D79>0.25,"✓ STRONG","✓ OK")))) | H79: EBITDARM multiple | I79: =IFERROR(IF(AND(ISNUMBER('T12 Analytics'!F117),ISNUMBER('T12 Analytics'!F161),'T12 Analytics'!F161<>0),'T12 Analytics'!F117/'T12 Analytics'!F161,"—"),"—") | K79: =IFERROR(IF(AND(ISNUMBER('T12 Analytics'!F117),ISNUMBER('T12 Analytics'!F161),'T12 Analytics'!F161<>0),'T12 Analytics'!F117/'T12 Analytics'!F161,"—"),"—")
B81: INSTITUTIONAL RISK CHECKLIST — ADDITIONAL CHECKS
B83: Risk factor | E83: Reading | F83: Threshold | G83: Flag
B84: RR vs T12 revenue gap | C84: Material variance between rent roll annualized revenue and T12 actual indicates restatement risk. | E84: =IFERROR(IF(AND(ISNUMBER('Rent Roll Recon'!E18),ISNUMBER('Rent Roll Recon'!E19),'Rent Roll Recon'!E19<>0),'Rent Roll Recon'!E18/'Rent Roll Recon'!E19,"—"),"—") | F84: ≤ ±3% | G84: =IF(NOT(ISNUMBER(E84)),"⚪",IF(ABS(E84)<=0.03,"✅",IF(ABS(E84)<=0.05,"⚠️","❌")))
B86: CHARTS — OCCUPANCY, MONTHLY EGI, PAYER MIX, P&L WATERFALL
B88: Chart 1 — Occupancy by Unit Type | E88: Chart 3 — Payer Mix (Revenue Share)
B89: Unit Type | C89: Occupancy | E89: Payer | F89: Share
B90: Independent Living | C90: =IFERROR(IF(AND(ISNUMBER('T12 Analytics'!B6),ISNUMBER('T12 Analytics'!B11),'T12 Analytics'!B6>0),'T12 Analytics'!B11/'T12 Analytics'!B6,0),0) | E90: Private Pay | F90: =IFERROR(IF(ISNUMBER('Rent Roll Recon'!B40),'Rent Roll Recon'!B40,0),0)
B91: Assisted Living | C91: =IFERROR(IF(AND(ISNUMBER('T12 Analytics'!C6),ISNUMBER('T12 Analytics'!C11),'T12 Analytics'!C6>0),'T12 Analytics'!C11/'T12 Analytics'!C6,0),0) | E91: Medicaid | F91: =IFERROR(IF(ISNUMBER('Rent Roll Recon'!B41),'Rent Roll Recon'!B41,0),0)
B92: Memory Care | C92: =IFERROR(IF(AND(ISNUMBER('T12 Analytics'!D6),ISNUMBER('T12 Analytics'!D11),'T12 Analytics'!D6>0),'T12 Analytics'!D11/'T12 Analytics'!D6,0),0) | E92: LTC Insurance | F92: =IFERROR(IF(ISNUMBER('Rent Roll Recon'!B42),'Rent Roll Recon'!B42,0),0)
B93: Blended | C93: =IFERROR(IF(AND(ISNUMBER('T12 Analytics'!E6),ISNUMBER('T12 Analytics'!E11),'T12 Analytics'!E6>0),'T12 Analytics'!E11/'T12 Analytics'!E6,0),0) | E93: VA | F93: =IFERROR(IF(ISNUMBER('Rent Roll Recon'!B43),'Rent Roll Recon'!B43,0),0)
E94: Managed Care | F94: =IFERROR(IF(ISNUMBER('Rent Roll Recon'!B44),'Rent Roll Recon'!B44,0),0)
B95: Chart 2 — Monthly EGI Trend | E95: Self-Pay | F95: =IFERROR(IF(ISNUMBER('Rent Roll Recon'!B45),'Rent Roll Recon'!B45,0),0)
B96: Month | C96: EGI | E96: Other | F96: =IFERROR(IF(ISNUMBER('Rent Roll Recon'!B46),'Rent Roll Recon'!B46,0),0)
B97: M01 | C97: =IFERROR('Monthly Trending'!B21,0)
B98: M02 | C98: =IFERROR('Monthly Trending'!C21,0) | E98: Chart 4 — P&L Waterfall
B99: M03 | C99: =IFERROR('Monthly Trending'!D21,0) | E99: Line | F99: T12
B100: M04 | C100: =IFERROR('Monthly Trending'!E21,0) | E100: EGI | F100: =IFERROR('T12 Analytics'!F52,0)
B101: M05 | C101: =IFERROR('Monthly Trending'!F21,0) | E101: Direct Labor | F101: =-IFERROR('T12 Analytics'!F65,0)
B102: M06 | C102: =IFERROR('Monthly Trending'!G21,0) | E102: Payroll Burden | F102: =-IFERROR('T12 Analytics'!F68+'T12 Analytics'!F69+'T12 Analytics'!F70,0)
B103: M07 | C103: =IFERROR('Monthly Trending'!H21,0) | E103: Non-Labor Opex | F103: =-IFERROR('T12 Analytics'!F103,0)
B104: M08 | C104: =IFERROR('Monthly Trending'!I21,0) | E104: Mgmt Fee | F104: =-IFERROR('T12 Analytics'!F106,0)
B105: M09 | C105: =IFERROR('Monthly Trending'!J21,0) | E105: EBITDAR | F105: =IFERROR('T12 Analytics'!F163,0)
B106: M10 | C106: =IFERROR('Monthly Trending'!K21,0)
B107: M11 | C107: =IFERROR('Monthly Trending'!L21,0)
B108: M12 | C108: =IFERROR('Monthly Trending'!M21,0)

Sheet T12 Analytics
A1: ALF T12 Analytics — Underwriting Supplement | AZ1: Per-Label T12 aggregation; main feed for UW Output
A2: Property Name: | B2: =IFERROR(IF(LEN(TRIM('Rent Roll Input'!A3))>0,'Rent Roll Input'!A3,IF(LEN(TRIM('T12 Input'!A10))>0,'T12 Input'!A10,Property_Name)),Property_Name) | D2: T12 Period Ending: | E2: =IFERROR(LOOKUP(2,1/('T12 Input'!$C$11:$N$11<>""),'T12 Input'!$C$11:$N$11),"") | G2: Basis: | H2: ACCRUAL | AZ2: aggregator
AZ3: visible
A4: SECTION 1 · PROPERTY CAPACITY — IL / AL / MC | AZ4: v0.2.7
B5: Independent Living (IL) | C5: Assisted Living (AL) | D5: Memory Care (MC) | E5: Total | H5: Notes
A6: Licensed beds (total) | B6: ='Rent Roll Recon'!B7 | C6: ='Rent Roll Recon'!C7 | D6: ='Rent Roll Recon'!D7 | E6: =SUM(B6:D6) | H6: Licensed / available beds per certificate
A7: Avg occupied beds (T12) | B7: =IFERROR(IF('Rent Roll Recon'!B34>0,'Rent Roll Recon'!B34,0),0) | C7: =IFERROR(IF('Rent Roll Recon'!C35>0,'Rent Roll Recon'!C35,0),0) | D7: =IFERROR(IF('Rent Roll Recon'!D36>0,'Rent Roll Recon'!D36,0),0) | E7: =SUM(B7:D7) | H7: Auto-filled from Rent Roll Recon when period selected (Sections E). Override directly if needed.
A8: Physical occupancy % (T12) | B8: =IFERROR(B7/B6,"-") | C8: =IFERROR(C7/C6,"-") | D8: =IFERROR(D7/D6,"-") | E8: =IFERROR(E7/E6,"-") | H8: Avg occ. beds ÷ licensed beds
A10: Target occupancy % (stabilized) | C10: 0 | E10: =IFERROR((B6*B10+C6*C10+D6*D10)/E6,"-") | H10: Target: 87–92% stabilized for AL/MC; 90%+ for IL
A11: Stabilized occupied beds | B11: =IFERROR(B6*B10,"-") | C11: =IFERROR(C6*C10,"-") | D11: =IFERROR(D6*D10,"-") | E11: =IFERROR(SUM(B11:D11),"-") | H11: Licensed beds × target occupancy %
A13: SECTION 2 · REVENUE ANALYSIS — T12 ACTUAL → NORMALIZED
B14: IL | C14: AL | D14: MC | E14: T12 Total | F14: Normalized | G14: Delta | H14: Notes / Flag
A15: Base Rent | K15: =IF(OR('Rent Roll Recon'!B12<0.85,'Rent Roll Recon'!C12<0.85,'Rent Roll Recon'!D12<0.85),"⚠ One or more care types below 85% physical occupancy — investigate stabilization assumptions.","✓ All care types ≥ 85% physical occupancy.") | P15: =IF('Rent Roll Recon'!E41>0.3,"⚠ Medicaid revenue share "&TEXT('Rent Roll Recon'!E41,"0.0%")&" — reimbursement rate risk; verify stabilized assumption.",IF('Rent Roll Recon'!E44>0.25,"⚠ Managed Care revenue share "&TEXT('Rent Roll Recon'!E44,"0.0%")&" — verify per-diem rates vs. private pay.","✓ Payer mix dominated by private pay / low reimbursement risk."))
A16: T12 base rent (actual) | B16: =IFERROR(INDEX('T12 Raw Data'!R:R,MATCH("Base rent — IL",'T12 Raw Data'!B:B,0)),0) | C16: =IFERROR(INDEX('T12 Raw Data'!R:R,MATCH("Base rent — AL",'T12 Raw Data'!B:B,0)),0) | D16: =IFERROR(INDEX('T12 Raw Data'!R:R,MATCH("Base rent — MC",'T12 Raw Data'!B:B,0)),0) | E16: =SUM(B16:D16) | H16: Gross base rent from T12 Raw Data
A17: Avg daily rate (T12 back-calc) | B17: =IFERROR(B16/(B7*12),"-") | C17: =IFERROR(C16/(C7*12),"-") | D17: =IFERROR(D16/(D7*12),"-") | E17: =IFERROR(E16/(E7*12),"-") | H17: T12 base rent ÷ avg occ. beds ÷ 12 months
A19: Stabilized monthly rate / bed | B19: =B17 | C19: =C17 | D19: =D17 | E19: =IFERROR((B11*B19+C11*C19+D11*D19)/E11,"-") | H19: Blended stabilized rate weighted by occupied beds
A20: Stabilized annual base rent | B20: =IFERROR(B6*B10*B19*12,0) | C20: =IFERROR(C6*C10*C19*12,0) | D20: =IFERROR(D6*D10*D19*12,0) | E20: =SUM(B20:D20) | F20: =E20 | G20: =F20-E16 | H20: Beds × occ% × monthly rate × 12 (per care type)
A22: Level of Care (LOC) Revenue
A23: T12 LOC revenue (actual) | B23: =IFERROR(INDEX('T12 Raw Data'!R:R,MATCH("LOC revenue — IL",'T12 Raw Data'!B:B,0)),0) | C23: =IFERROR(INDEX('T12 Raw Data'!R:R,MATCH("LOC revenue — AL",'T12 Raw Data'!B:B,0)),0) | D23: =IFERROR(INDEX('T12 Raw Data'!R:R,MATCH("LOC revenue — MC",'T12 Raw Data'!B:B,0)),0) | E23: =SUM(B23:D23) | H23: Care rate / level of care charges from T12
A24: LOC per occ. bed / month (T12) | B24: =IFERROR(B23/(B7*12),"-") | C24: =IFERROR(C23/(C7*12),"-") | D24: =IFERROR(D23/(D7*12),"-") | E24: =IFERROR(E23/(E7*12),"-") | H24: Validate vs. care level assessments; MC should be highest
A26: Stabilized LOC / occ. bed / month | C26: =C24 | E26: =IFERROR((B11*B26+C11*C26+D11*D26)/E11,"-") | H26: =IF(E24<>"-","T12 actual LOC/occ bed: "&TEXT(E24,"$#,##0.00")&"/mo blended (AL: "&TEXT(C24,"$#,##0.00")&"). Enter stabilized rate in B26/C26/D26. Default to T12 unless acuity mix change is justified.","Enter stabilized LOC/bed in B26/C26/D26.")
A27: Stabilized LOC revenue | B27: =IFERROR(B6*B10*B26*12,0) | C27: =IFERROR(C6*C10*C26*12,0) | D27: =IFERROR(D6*D10*D26*12,0) | E27: =SUM(B27:D27) | F27: =E27 | G27: =F27-E23
A29: Revenue Quality Ratios
A30: LOC as % of base rent (T12) | B30: =IFERROR(B23/B16,"-") | C30: =IFERROR(C23/C16,"-") | D30: =IFERROR(D23/D16,"-") | E30: =IFERROR(E23/E16,"-") | H30: Higher = higher acuity mix; validate vs. care assessments | K30: =IF(LEN('Rent Roll Recon'!B96)=0,"-",IF(IFERROR(VALUE(SUBSTITUTE('Rent Roll Recon'!B96,"%",""))/100,0)>0.25,"⚠ IL rate dispersion CV "&TEXT(IFERROR(VALUE(SUBSTITUTE('Rent Roll Recon'!B96,"%",""))/100,0),"0.0%")&" — wide spread may indicate legacy in-place rates.","✓ IL rate dispersion within normal band.")) | P30: =IFERROR(IF(AVERAGE(T54:V54)>AVERAGE(K54:M54)*1.05,"↑ Revenue trending up — latest 3-mo avg "&TEXT(AVERAGE(T54:V54),"$#,##0")&" vs prior 3-mo "&TEXT(AVERAGE(K54:M54),"$#,##0"),IF(AVERAGE(T54:V54)<AVERAGE(K54:M54)*0.95,"↓ Revenue trending down — latest 3-mo avg "&TEXT(AVERAGE(T54:V54),"$#,##0")&" vs prior 3-mo "&TEXT(AVERAGE(K54:M54),"$#,##0"),"→ Revenue stable — within ±5% of prior 3-mo.")),"Insufficient T12 data for trend.")
A31: RevPOR (T12 actual) — base + LOC | B31: =IFERROR((B16+B23)/(B7*12),"-") | C31: =IFERROR((C16+C23)/(C7*12),"-") | D31: =IFERROR((D16+D23)/(D7*12),"-") | E31: =IFERROR((E16+E23)/(E7*12),"-") | H31: Revenue per occupied room per month (base + LOC)
A32: RevPOR (normalized) — base + LOC | B32: =IFERROR((B20+B27)/(B11*12),"-") | C32: =IFERROR((C20+C27)/(C11*12),"-") | D32: =IFERROR((D20+D27)/(D11*12),"-") | E32: =IFERROR((E20+E27)/(E11*12),"-") | H32: Normalized RevPOR — stabilized beds and rates
A34: GPR Revenue Waterfall — Rent Roll projection vs. T12 reported
B35: IL | C35: AL | D35: MC | E35: T12 Reported | F35: RR Projection | G35: Delta | H35: Notes
A36: Market rate / bed / month (from rent roll col G, occupied beds) | B36: =IFERROR(AVERAGEIFS('Rent Roll Input'!$G$7:$G$606,'Rent Roll Input'!$S$7:$S$606,'Rent Roll Recon'!$B$2,'Rent Roll Input'!$E$7:$E$606,"Occupied",'Rent Roll Input'!$D$7:$D$606,"IL"),0) | C36: =IFERROR(AVERAGEIFS('Rent Roll Input'!$G$7:$G$606,'Rent Roll Input'!$S$7:$S$606,'Rent Roll Recon'!$B$2,'Rent Roll Input'!$E$7:$E$606,"Occupied",'Rent Roll Input'!$D$7:$D$606,"AL"),0) | D36: =IFERROR(AVERAGEIFS('Rent Roll Input'!$G$7:$G$606,'Rent Roll Input'!$S$7:$S$606,'Rent Roll Recon'!$B$2,'Rent Roll Input'!$E$7:$E$606,"Occupied",'Rent Roll Input'!$D$7:$D$606,"MC"),0) | E36: — | F36: =IFERROR((B6*B36+C6*C36+D6*D36)/E6,"-") | G36: — | H36: Avg market rate for occupied beds from Rent Roll col G, selected period. Override B–D directly. T12 does not report market rates — col E blank by design.
A37: Gross Potential Rent (GPR) — base rent, 100% occupied at market rate | B37: =IFERROR(B6*B36*12,0) | C37: =IFERROR(C6*C36*12,0) | D37: =IFERROR(D6*D36*12,0) | E37: =IFERROR(IF(INDEX('T12 Raw Data'!R:R,MATCH("Gross Rent Revenue",'T12 Raw Data'!B:B,0))=0,"",INDEX('T12 Raw Data'!R:R,MATCH("Gross Rent Revenue",'T12 Raw Data'!B:B,0))),"") | F37: =SUM(B37:D37) | G37: =IFERROR(IF(E37="","",E37-F37),"") | H37: T12 col: pulled from T12 Raw Data — blank if no GPR line reported. RR Projection: licensed beds × avg market rate (rent roll) × 12. Delta: T12 minus RR.
A38: Less: Physical vacancy loss | B38: =IFERROR((B6-B7)*B36*12,0) | C38: =IFERROR((C6-C7)*C36*12,0) | D38: =IFERROR((D6-D7)*D36*12,0) | E38: =IFERROR(IF(ABS('T12 Raw Data'!$R$61)>0,ABS('T12 Raw Data'!$R$61),F38),F38) | F38: =SUM(B38:D38) | G38: =IFERROR(IF(E38="","",E38-F38),"") | H38: =IF(AND(E37<>"",ABS('T12 Raw Data'!$R$61)>0),"T12 check: GPR−Vacancy−Collected = "&TEXT(E37-E38-E16,"$#,##0")&" (0=clean)","T12 vacancy not reported — using RR projection")
A39: Physical vacancy rate % | B39: =IFERROR((B6-B7)/B6,"-") | C39: =IFERROR((C6-C7)/C6,"-") | D39: =IFERROR((D6-D7)/D6,"-") | E39: =IFERROR(IF(AND(E37<>"",ABS('T12 Raw Data'!$R$61)>0),E38/E37,IFERROR((E6-E7)/E6,"-")),IFERROR((E6-E7)/E6,"-")) | F39: =IFERROR((E6-E11)/E6,"-") | G39: =IFERROR(IF(ISNUMBER(E39),F39-E39,"-"),"-") | H39: T12: (licensed − avg occupied) / licensed. RR Projection: (licensed − stabilized target) / licensed. Flag if >20%.
A40: Less: Loss to lease (occupied beds priced below market rate) | B40: =IFERROR(B37-B38-B16,0) | C40: =IFERROR(C37-C38-C16,0) | D40: =IFERROR(D37-D38-D16,0) | E40: =IFERROR(IF(ABS('T12 Raw Data'!$R$62)>0,ABS('T12 Raw Data'!$R$62),F37-F38-E16),F37-F38-E16) | F40: =SUM(B40:D40) | G40: =IFERROR(IF(E40="","",E40-F40),"") | H40: ⚠ RR: occupied beds × market rate × 12 minus T12 collected base rent. Captures concessions, rate-lock, and below-market pricing. T12 col requires GPR line.
A41: Loss to lease as % of GPR | B41: =IFERROR(B40/B37,"-") | C41: =IFERROR(C40/C37,"-") | D41: =IFERROR(D40/D37,"-") | E41: =IFERROR(IF(E37<>"",E40/E37,IF(F37>0,E40/F37,"-")),"-") | F41: =IFERROR(F40/F37,"-") | G41: =IFERROR(E41-F41,"") | H41: ⚠ Flag if RR projection >5% — below-market pricing or heavy concessions. T12 col requires GPR line.
A45: Other Revenue — Normalization Bridge | K45: =IF('Rent Roll Recon'!D67=0,"Property has no AL acuity data — flat-rate AL or unpopulated.",IF(MAX('Rent Roll Recon'!D59:D66)/'Rent Roll Recon'!D67>0.5,"⚠ Acuity skewed: top tier > 50% of AL care charges — verify staffing model.","✓ Acuity distribution within normal range."))
A46: Revenue Item | E46: T12 Actual | F46: Normalized | G46: Delta | H46: Flag / Note | K46: (hidden helper — rate buckets for V2 chart)
A47: Community / move-in fees | E47: =IFERROR(INDEX('T12 Raw Data'!R:R,MATCH("Community / move-in fees",'T12 Raw Data'!B:B,0)),0) | F47: 0 | G47: =F47-E47 | H47: ⚠ ONE-TIME — normalize to $0; model separately if absorption schedule exists | K47: Bucket | L47: IL | M47: AL | N47: MC
A48: Concessions & move-in specials | E48: =IFERROR(INDEX('T12 Raw Data'!R:R,MATCH("Concessions & specials",'T12 Raw Data'!B:B,0)),0) | F48: 0 | G48: =F48-E48 | H48: ⚠ BURN-OFF — normalize to $0 at stabilized occupancy | K48: $0 – $1,999 | L48: =COUNTIFS('Rent Roll Input'!$S$7:$S$606,'Rent Roll Recon'!$B$2,'Rent Roll Input'!$E$7:$E$606,"<>Vacant",'Rent Roll Input'!$E$7:$E$606,"<>Eviction",'Rent Roll Input'!$H$7:$H$606,">="&0,'Rent Roll Input'!$H$7:$H$606,"<="&1999.99,'Rent Roll Input'!$D$7:$D$606,"IL") | M48: =COUNTIFS('Rent Roll Input'!$S$7:$S$606,'Rent Roll Recon'!$B$2,'Rent Roll Input'!$E$7:$E$606,"<>Vacant",'Rent Roll Input'!$E$7:$E$606,"<>Eviction",'Rent Roll Input'!$H$7:$H$606,">="&0,'Rent Roll Input'!$H$7:$H$606,"<="&1999.99,'Rent Roll Input'!$D$7:$D$606,"AL") | N48: =COUNTIFS('Rent Roll Input'!$S$7:$S$606,'Rent Roll Recon'!$B$2,'Rent Roll Input'!$E$7:$E$606,"<>Vacant",'Rent Roll Input'!$E$7:$E$606,"<>Eviction",'Rent Roll Input'!$H$7:$H$606,">="&0,'Rent Roll Input'!$H$7:$H$606,"<="&1999.99,'Rent Roll Input'!$D$7:$D$606,"MC")
A49: Respite care | E49: =IFERROR(INDEX('T12 Raw Data'!R:R,MATCH("Respite care",'T12 Raw Data'!B:B,0)),0) | F49: 0 | G49: =F49-E49 | H49: ⚠ VOLATILE — assess program; include only if documented & consistent | K49: $2,000 – $3,999 | L49: =COUNTIFS('Rent Roll Input'!$S$7:$S$606,'Rent Roll Recon'!$B$2,'Rent Roll Input'!$E$7:$E$606,"<>Vacant",'Rent Roll Input'!$E$7:$E$606,"<>Eviction",'Rent Roll Input'!$H$7:$H$606,">="&2000,'Rent Roll Input'!$H$7:$H$606,"<="&3999.99,'Rent Roll Input'!$D$7:$D$606,"IL") | M49: =COUNTIFS('Rent Roll Input'!$S$7:$S$606,'Rent Roll Recon'!$B$2,'Rent Roll Input'!$E$7:$E$606,"<>Vacant",'Rent Roll Input'!$E$7:$E$606,"<>Eviction",'Rent Roll Input'!$H$7:$H$606,">="&2000,'Rent Roll Input'!$H$7:$H$606,"<="&3999.99,'Rent Roll Input'!$D$7:$D$606,"AL") | N49: =COUNTIFS('Rent Roll Input'!$S$7:$S$606,'Rent Roll Recon'!$B$2,'Rent Roll Input'!$E$7:$E$606,"<>Vacant",'Rent Roll Input'!$E$7:$E$606,"<>Eviction",'Rent Roll Input'!$H$7:$H$606,">="&2000,'Rent Roll Input'!$H$7:$H$606,"<="&3999.99,'Rent Roll Input'!$D$7:$D$606,"MC")
A50: Other community revenue | E50: =IFERROR(INDEX('T12 Raw Data'!R:R,MATCH("Other community revenue",'T12 Raw Data'!B:B,0)),0) | F50: 0 | G50: =F50-E50 | H50: Beautician, utility reimbursement, admin fees, finance charges | K50: $4,000 – $5,999 | L50: =COUNTIFS('Rent Roll Input'!$S$7:$S$606,'Rent Roll Recon'!$B$2,'Rent Roll Input'!$E$7:$E$606,"<>Vacant",'Rent Roll Input'!$E$7:$E$606,"<>Eviction",'Rent Roll Input'!$H$7:$H$606,">="&4000,'Rent Roll Input'!$H$7:$H$606,"<="&5999.99,'Rent Roll Input'!$D$7:$D$606,"IL") | M50: =COUNTIFS('Rent Roll Input'!$S$7:$S$606,'Rent Roll Recon'!$B$2,'Rent Roll Input'!$E$7:$E$606,"<>Vacant",'Rent Roll Input'!$E$7:$E$606,"<>Eviction",'Rent Roll Input'!$H$7:$H$606,">="&4000,'Rent Roll Input'!$H$7:$H$606,"<="&5999.99,'Rent Roll Input'!$D$7:$D$606,"AL") | N50: =COUNTIFS('Rent Roll Input'!$S$7:$S$606,'Rent Roll Recon'!$B$2,'Rent Roll Input'!$E$7:$E$606,"<>Vacant",'Rent Roll Input'!$E$7:$E$606,"<>Eviction",'Rent Roll Input'!$H$7:$H$606,">="&4000,'Rent Roll Input'!$H$7:$H$606,"<="&5999.99,'Rent Roll Input'!$D$7:$D$606,"MC")
K51: $6,000 – $7,999 | L51: =COUNTIFS('Rent Roll Input'!$S$7:$S$606,'Rent Roll Recon'!$B$2,'Rent Roll Input'!$E$7:$E$606,"<>Vacant",'Rent Roll Input'!$E$7:$E$606,"<>Eviction",'Rent Roll Input'!$H$7:$H$606,">="&6000,'Rent Roll Input'!$H$7:$H$606,"<="&7999.99,'Rent Roll Input'!$D$7:$D$606,"IL") | M51: =COUNTIFS('Rent Roll Input'!$S$7:$S$606,'Rent Roll Recon'!$B$2,'Rent Roll Input'!$E$7:$E$606,"<>Vacant",'Rent Roll Input'!$E$7:$E$606,"<>Eviction",'Rent Roll Input'!$H$7:$H$606,">="&6000,'Rent Roll Input'!$H$7:$H$606,"<="&7999.99,'Rent Roll Input'!$D$7:$D$606,"AL") | N51: =COUNTIFS('Rent Roll Input'!$S$7:$S$606,'Rent Roll Recon'!$B$2,'Rent Roll Input'!$E$7:$E$606,"<>Vacant",'Rent Roll Input'!$E$7:$E$606,"<>Eviction",'Rent Roll Input'!$H$7:$H$606,">="&6000,'Rent Roll Input'!$H$7:$H$606,"<="&7999.99,'Rent Roll Input'!$D$7:$D$606,"MC")
A52: EFFECTIVE GROSS INCOME (EGI) | E52: =E16+E23+E47+E48+E49+E50 | F52: =E20+E27+F47+F48+F49+F50 | G52: =F52-E52 | H52: 100% of EGI | K52: $8,000+ | L52: =COUNTIFS('Rent Roll Input'!$S$7:$S$606,'Rent Roll Recon'!$B$2,'Rent Roll Input'!$E$7:$E$606,"<>Vacant",'Rent Roll Input'!$E$7:$E$606,"<>Eviction",'Rent Roll Input'!$H$7:$H$606,">="&8000,'Rent Roll Input'!$H$7:$H$606,"<="&99999999,'Rent Roll Input'!$D$7:$D$606,"IL") | M52: =COUNTIFS('Rent Roll Input'!$S$7:$S$606,'Rent Roll Recon'!$B$2,'Rent Roll Input'!$E$7:$E$606,"<>Vacant",'Rent Roll Input'!$E$7:$E$606,"<>Eviction",'Rent Roll Input'!$H$7:$H$606,">="&8000,'Rent Roll Input'!$H$7:$H$606,"<="&99999999,'Rent Roll Input'!$D$7:$D$606,"AL") | N52: =COUNTIFS('Rent Roll Input'!$S$7:$S$606,'Rent Roll Recon'!$B$2,'Rent Roll Input'!$E$7:$E$606,"<>Vacant",'Rent Roll Input'!$E$7:$E$606,"<>Eviction",'Rent Roll Input'!$H$7:$H$606,">="&8000,'Rent Roll Input'!$H$7:$H$606,"<="&99999999,'Rent Roll Input'!$D$7:$D$606,"MC")
K53: (hidden helper — T12 monthly revenue for V4)
A54: SECTION 3 · EXPENSE ANALYSIS — T12 ACTUAL → NORMALIZED | K54: =SUMIFS('T12 Raw Data'!F:F,'T12 Raw Data'!$A:$A,"Revenue") | L54: =SUMIFS('T12 Raw Data'!G:G,'T12 Raw Data'!$A:$A,"Revenue") | M54: =SUMIFS('T12 Raw Data'!H:H,'T12 Raw Data'!$A:$A,"Revenue") | N54: =SUMIFS('T12 Raw Data'!I:I,'T12 Raw Data'!$A:$A,"Revenue") | O54: =SUMIFS('T12 Raw Data'!J:J,'T12 Raw Data'!$A:$A,"Revenue") | P54: =SUMIFS('T12 Raw Data'!K:K,'T12 Raw Data'!$A:$A,"Revenue") | Q54: =SUMIFS('T12 Raw Data'!L:L,'T12 Raw Data'!$A:$A,"Revenue") | R54: =SUMIFS('T12 Raw Data'!M:M,'T12 Raw Data'!$A:$A,"Revenue") | S54: =SUMIFS('T12 Raw Data'!N:N,'T12 Raw Data'!$A:$A,"Revenue") | T54: =SUMIFS('T12 Raw Data'!O:O,'T12 Raw Data'!$A:$A,"Revenue") | U54: =SUMIFS('T12 Raw Data'!P:P,'T12 Raw Data'!$A:$A,"Revenue") | V54: =SUMIFS('T12 Raw Data'!Q:Q,'T12 Raw Data'!$A:$A,"Revenue")
A55: Expense Category | E55: T12 Actual | F55: Normalized | G55: Delta | H55: Benchmark / Flag
A56: DIRECT LABOR
A57: Care staff labor (AL / MC / IL) | E57: =IFERROR(INDEX('T12 Raw Data'!R:R,MATCH("Care staff labor",'T12 Raw Data'!B:B,0)),0) | F57: =E57 | G57: =F57-E57 | H57: Direct care staff — CNAs, caregivers, med techs
A58: Wellness / care coordinators | E58: =IFERROR(INDEX('T12 Raw Data'!R:R,MATCH("Wellness / care coordinators",'T12 Raw Data'!B:B,0)),0) | F58: =E58 | G58: =F58-E58 | H58: RN, LPN, DON — validate licensure requirements by state
A59: Contract / agency labor | E59: =IFERROR(INDEX('T12 Raw Data'!R:R,MATCH("Contract / agency labor",'T12 Raw Data'!B:B,0)),0) | F59: =E59 | G59: =F59-E59 | H59: ⚠ ELEVATED at distress Normalize to $0 at stabilization; add back if planned
A60: Activities labor | E60: =IFERROR(INDEX('T12 Raw Data'!R:R,MATCH("Activities labor",'T12 Raw Data'!B:B,0)),0) | F60: =E60 | G60: =F60-E60
A61: Dining / food service labor | E61: =IFERROR(INDEX('T12 Raw Data'!R:R,MATCH("Dining / food service labor",'T12 Raw Data'!B:B,0)),0) | F61: =E61 | G61: =F61-E61 | H61: All kitchen and dining room staff
A62: Maintenance & housekeeping labor | E62: =IFERROR(INDEX('T12 Raw Data'!R:R,MATCH("Maint. & housekeeping labor",'T12 Raw Data'!B:B,0)),0) | F62: =E62 | G62: =F62-E62
A63: Administrative labor | E63: =IFERROR(INDEX('T12 Raw Data'!R:R,MATCH("Administrative labor",'T12 Raw Data'!B:B,0)),0) | F63: =E63 | G63: =F63-E63 | H63: ED, business office, marketing / sales FTEs
A64: Bonus wages | E64: =IFERROR(INDEX('T12 Raw Data'!R:R,MATCH("Bonus wages",'T12 Raw Data'!B:B,0)),0) | F64: =E64 | G64: =F64-E64 | H64: ⚠ VARIABLE Normalize to stabilized annual bonus assumption
A65: Total direct labor | E65: =SUM(E57:E64) | F65: =SUM(F57:F64) | G65: =F65-E65
A67: PAYROLL BURDEN
A68: Overtime wages | E68: =IFERROR(INDEX('T12 Raw Data'!R:R,MATCH("Overtime wages",'T12 Raw Data'!B:B,0)),0) | F68: =E68 | G68: =F68-E68 | H68: ⚠ EXCESS OT Normalize to ≤5% of direct wages; flag gap vs. T12
A69: PTO wages | E69: =IFERROR(INDEX('T12 Raw Data'!R:R,MATCH("PTO wages",'T12 Raw Data'!B:B,0)),0) | F69: =E69 | G69: =F69-E69 | H69: ⚠ LUMPY Annualize; normalize to steady-state accrual rate
A70: Payroll taxes | E70: =IFERROR(INDEX('T12 Raw Data'!R:R,MATCH("Payroll taxes",'T12 Raw Data'!B:B,0)),0) | F70: =E70 | G70: =F70-E70 | H70: FICA, SUTA, FUTA, UI — track at ~8–10% of gross wages
A71: Employee benefits (health / dental / vision) | E71: =IFERROR(INDEX('T12 Raw Data'!R:R,MATCH("Employee benefits",'T12 Raw Data'!B:B,0)),0) | F71: =E71 | G71: =F71-E71 | H71: Validate per-FTE cost; check enrollment changes
A72: Workers’ comp insurance | E72: =IFERROR(INDEX('T12 Raw Data'!R:R,MATCH("Workers' comp insurance",'T12 Raw Data'!B:B,0)),0) | F72: =E72 | G72: =F72-E72 | H72: Check experience mod; elevated at distressed facilities
A73: Employee 401(k) / retirement | E73: =IFERROR(INDEX('T12 Raw Data'!R:R,MATCH("Employee 401(k)",'T12 Raw Data'!B:B,0)),0) | F73: =E73 | G73: =F73-E73 | H73: Typically 1–3% of eligible wages
A74: Total payroll burden | E74: =SUM(E68:E73) | F74: =SUM(F68:F73) | G74: =F74-E74
A76: TOTAL LABOR & BURDEN | E76: =E65+E74 | F76: =F65+F74 | G76: =F76-E76 | H76: Target: 55–65% of EGI
A78: NON-LABOR OPERATING EXPENSES
A79: Food cost | E79: =IFERROR(INDEX('T12 Raw Data'!R:R,MATCH("Food cost",'T12 Raw Data'!B:B,0)),0) | F79: =E79 | G79: =F79-E79 | H79: Benchmark: $8–12 PPD for AL; $10–14 for MC; $10–16 for IL
A80: Dining & kitchen supplies | E80: =IFERROR(INDEX('T12 Raw Data'!R:R,MATCH("Dining & kitchen supplies",'T12 Raw Data'!B:B,0)),0) | F80: =E80 | G80: =F80-E80 | H80: Dietary + kitchen supplies combined
A81: Nursing & care supplies | E81: =IFERROR(INDEX('T12 Raw Data'!R:R,MATCH("Nursing & care supplies",'T12 Raw Data'!B:B,0)),0) | F81: =E81 | G81: =F81-E81 | H81: Incontinence, medications, PPE, clinical supplies
A82: Recreation & activity supplies | E82: =IFERROR(INDEX('T12 Raw Data'!R:R,MATCH("Recreation & activity suppl.",'T12 Raw Data'!B:B,0)),0) | F82: =E82 | G82: =F82-E82
A83: R&M — fixed (contracts) | E83: =IFERROR(INDEX('T12 Raw Data'!R:R,MATCH("R&M fixed",'T12 Raw Data'!B:B,0)),0) | F83: =E83 | G83: =F83-E83 | H83: Elevator, HVAC, generator, fire suppression contracts
A84: R&M — variable (repairs) | E84: =IFERROR(INDEX('T12 Raw Data'!R:R,MATCH("R&M variable",'T12 Raw Data'!B:B,0)),0) | F84: =E84 | G84: =F84-E84 | H84: Variable repairs; flag spikes indicating deferred maintenance
A85: Housekeeping & laundry supplies | E85: =IFERROR(INDEX('T12 Raw Data'!R:R,MATCH("HK & laundry supplies",'T12 Raw Data'!B:B,0)),0) | F85: =E85 | G85: =F85-E85 | H85: Includes external linen service if outsourced
A86: Sales, advertising & marketing | E86: =IFERROR(INDEX('T12 Raw Data'!R:R,MATCH("Sales, adv. & marketing",'T12 Raw Data'!B:B,0)),0) | F86: =E86 | G86: =F86-E86 | H86: Benchmark: 2–5% of revenue; includes digital + events
A87: Referral fees | E87: =IFERROR(INDEX('T12 Raw Data'!R:R,MATCH("Referral fees",'T12 Raw Data'!B:B,0)),0) | F87: =E87 | G87: =F87-E87 | H87: ⚠ STABILIZE Normalize to $0 at steady occupancy; include ramp-up schedule
A88: Utilities (electric, gas, water, trash) | E88: =IFERROR(INDEX('T12 Raw Data'!R:R,MATCH("Utilities",'T12 Raw Data'!B:B,0)),0) | F88: =E88 | G88: =F88-E88
A89: Telephone / IT / technology | E89: =IFERROR(INDEX('T12 Raw Data'!R:R,MATCH("Telephone / IT",'T12 Raw Data'!B:B,0)),0) | F89: =E89 | G89: =F89-E89 | H89: Review for one-time credits or service changes; include EHR/EMR
A90: P&C insurance (bundled) | E90: =IFERROR(INDEX('T12 Raw Data'!R:R,MATCH("P&C insurance (bundled)",'T12 Raw Data'!B:B,0)),0) | F90: =E90 | G90: =F90-E90 | H90: Confirm policy year / renewal; check for mid-year adjustments
A91: Auto insurance | E91: =IFERROR(INDEX('T12 Raw Data'!R:R,MATCH("Auto insurance",'T12 Raw Data'!B:B,0)),0) | F91: =E91 | G91: =F91-E91
A92: Fire / security monitoring | E92: =IFERROR(INDEX('T12 Raw Data'!R:R,MATCH("Fire / security monitoring",'T12 Raw Data'!B:B,0)),0) | F92: =E92 | G92: =F92-E92 | H92: Contract-based; confirm annual cost
A93: Pest elimination | E93: =IFERROR(INDEX('T12 Raw Data'!R:R,MATCH("Pest elimination",'T12 Raw Data'!B:B,0)),0) | F93: =E93 | G93: =F93-E93
A94: Real estate taxes | E94: =IFERROR(INDEX('T12 Raw Data'!R:R,MATCH("Real estate taxes",'T12 Raw Data'!B:B,0)),0) | F94: =E94 | G94: =F94-E94 | H94: ⚠ VERIFY Confirm assessed value post-acquisition; exclude reversals
A95: Personal property taxes | E95: =IFERROR(INDEX('T12 Raw Data'!R:R,MATCH("Personal property taxes",'T12 Raw Data'!B:B,0)),0) | F95: =E95 | G95: =F95-E95
A96: Legal expenses | E96: =IFERROR(INDEX('T12 Raw Data'!R:R,MATCH("Legal expenses",'T12 Raw Data'!B:B,0)),0) | F96: =E96 | G96: =F96-E96
A97: Professional services (accounting / consulting) | E97: =IFERROR(INDEX('T12 Raw Data'!R:R,MATCH("Professional services",'T12 Raw Data'!B:B,0)),0) | F97: =E97 | G97: =F97-E97 | H97: Includes dietary consultant, audit, accounting
A98: Bad debt expense | E98: =IFERROR(INDEX('T12 Raw Data'!R:R,MATCH("Bad debt expense",'T12 Raw Data'!B:B,0)),0) | F98: =E98 | G98: =F98-E98 | H98: ⚠ ELEVATED Normalize to 1–2% of gross revenue at stabilization
A99: Permits, licenses & dues | E99: =IFERROR(INDEX('T12 Raw Data'!R:R,MATCH("Permits, licenses & dues",'T12 Raw Data'!B:B,0)),0) | F99: =E99 | G99: =F99-E99 | H99: State survey fees, DOH, association dues, clinical licenses
A100: Office, admin & G&A | E100: =IFERROR(INDEX('T12 Raw Data'!R:R,MATCH("Office, admin & G&A",'T12 Raw Data'!B:B,0)),0) | F100: =E100 | G100: =F100-E100 | H100: Postage, printing, copier, bank charges, pre-employment, auto expenses
A101: Other / miscellaneous | E101: =IFERROR(INDEX('T12 Raw Data'!R:R,MATCH("Other / miscellaneous",'T12 Raw Data'!B:B,0)),0) | F101: =E101 | G101: =F101-E101
A102: Lease / ground lease (if applicable) | E102: =IFERROR(INDEX('T12 Raw Data'!R:R,MATCH("Lease / ground lease",'T12 Raw Data'!B:B,0)),0) | F102: =E102 | G102: =F102-E102 | H102: ⚠ MANUAL ENTRY — enter lease expense if facility is leased; excluded from Raw Data auto-mapping
A103: Total non-labor opex | E103: =SUM(E79:E102) | F103: =SUM(F79:F102) | G103: =F103-E103
A105: TOTAL OPERATING EXPENSES (excl. mgmt fee) | E105: =E76+E103 | F105: =F76+F103 | G105: =F105-E105
A106: Management fee | E106: =IFERROR(INDEX('T12 Raw Data'!R:R,MATCH("Management fee",'T12 Raw Data'!B:B,0)),0) | F106: =E106 | G106: =F106-E106 | H106: EXCLUDED from EBITDARM Evaluate operator separately from real estate; typically 5–7% of revenue
A108: EBITDARM | E108: =E52-E105 | F108: =F52-F105 | G108: =F108-E108 | H108: =IFERROR("DARM margin: "&TEXT(F108/F52,"0.0%"),"")
A110: EBITDAR (after mgmt fee) | E110: =E108-E106 | F110: =F108-F106 | G110: =F110-E110 | H110: =IFERROR("DAR margin: "&TEXT(F110/F52,"0.0%"),"")
A112: Depreciation (non-cash, excluded from EBITDA calc) | E112: =0 | F112: 0 | G112: =F112-E112 | H112: T12 depreciation from income statement (non-operating)
A113: EBITDA | E113: =E110-E112 | F113: =F110-F112 | G113: =F113-E113
A115: SECTION 4 · NOI & CAP RATE ANALYSIS — ACQUISITION METRICS
A116: Metric | E116: T12 Actual | F116: Normalized | H116: Notes
A117: Purchase price (input) | F117: =E117 | H117: Total acquisition price including closing costs
A118: Going-in cap rate (T12 EBITDARM / price) | E118: =IFERROR(E108/E117,"-") | F118: =IFERROR(F108/F117,"-") | H118: T12 EBITDARM ÷ purchase price
...

Sheet T12 Input
A1: T12 Input — Paste T12 data here | AZ1: T12 raw paste area (MRI / Yardi / normalizer output)
AZ2: input
A3: How to use — no setup, no refresh, instant results | AZ3: visible
A4: 1. Upload this Analyzer + your raw T12 to the Streamlit app. | AZ4: v0.2.7
A5: 2. Map any UNMATCHED descriptions in-app before downloading.
A6: 3. Open the populated Analyzer — Coverage Check (col P) confirms all rows mapped.
A7: 4. Mappings persist in Description_Map for next upload.
A9: Layout: Account # (col A, optional, populated for Yardi-style T12s only), Description (col B, required), 12 months (cols C-N), T12 Total (col O). Headers in row 11 reflect the source T12 period.
A11: Account # | B11: Description | O11: T12 Total | P11: Coverage Check
P12: =IF(TRIM(B12)<>"",IFERROR(INDEX(DescMap_Label,MATCH(TRIM(B12),DescMap_Description,0)),"UNMATCHED"),"")
P13: =IF(TRIM(B13)<>"",IFERROR(INDEX(DescMap_Label,MATCH(TRIM(B13),DescMap_Description,0)),"UNMATCHED"),"")
P14: =IF(TRIM(B14)<>"",IFERROR(INDEX(DescMap_Label,MATCH(TRIM(B14),DescMap_Description,0)),"UNMATCHED"),"")
P15: =IF(TRIM(B15)<>"",IFERROR(INDEX(DescMap_Label,MATCH(TRIM(B15),DescMap_Description,0)),"UNMATCHED"),"")
P16: =IF(TRIM(B16)<>"",IFERROR(INDEX(DescMap_Label,MATCH(TRIM(B16),DescMap_Description,0)),"UNMATCHED"),"")
P17: =IF(TRIM(B17)<>"",IFERROR(INDEX(DescMap_Label,MATCH(TRIM(B17),DescMap_Description,0)),"UNMATCHED"),"")
P18: =IF(TRIM(B18)<>"",IFERROR(INDEX(DescMap_Label,MATCH(TRIM(B18),DescMap_Description,0)),"UNMATCHED"),"")
P19: =IF(TRIM(B19)<>"",IFERROR(INDEX(DescMap_Label,MATCH(TRIM(B19),DescMap_Description,0)),"UNMATCHED"),"")
P20: =IF(TRIM(B20)<>"",IFERROR(INDEX(DescMap_Label,MATCH(TRIM(B20),DescMap_Description,0)),"UNMATCHED"),"")
P21: =IF(TRIM(B21)<>"",IFERROR(INDEX(DescMap_Label,MATCH(TRIM(B21),DescMap_Description,0)),"UNMATCHED"),"")
P22: =IF(TRIM(B22)<>"",IFERROR(INDEX(DescMap_Label,MATCH(TRIM(B22),DescMap_Description,0)),"UNMATCHED"),"")
P23: =IF(TRIM(B23)<>"",IFERROR(INDEX(DescMap_Label,MATCH(TRIM(B23),DescMap_Description,0)),"UNMATCHED"),"")
... P511: =IF(TRIM(B511)<>"",IFERROR(INDEX(DescMap_Label,MATCH(TRIM(B511),DescMap_Description,0)),"UNMATCHED"),"")

Sheet T12 Raw Data
A1: T12 Raw Data — auto-calculated from T12 Input descriptions | AZ1: Description→Label rollup with monthly trending
A2: Matches T12 Input col B descriptions against Description_Map. UNMATCHED rows in T12 Input col P are not included here. Add missing descriptions to Description_Map tab to capture them. | AZ2: aggregator
AZ3: visible
A4: Section | B4: Label | C4: Care | D4: Flag | E4: Matched Descriptions | F4: M01 | G4: M02 | H4: M03 | I4: M04 | J4: M05 | K4: M06 | L4: M07 | M4: M08 | N4: M09 | O4: M10 | P4: M11 | Q4: M12 | R4: T12_Total | AZ4: v0.2.7
A6: Revenue | B6: Base rent — IL | C6: IL | E6: IL Base Rate Income | Independent Living Base Rate | F6: =SUMIF(T12_Calc!$N$1:$N$505,"Base rent — IL",T12_Calc!$B$1:$B$505) | G6: =SUMIF(T12_Calc!$N$1:$N$505,"Base rent — IL",T12_Calc!$C$1:$C$505) | H6: =SUMIF(T12_Calc!$N$1:$N$505,"Base rent — IL",T12_Calc!$D$1:$D$505) | I6: =SUMIF(T12_Calc!$N$1:$N$505,"Base rent — IL",T12_Calc!$E$1:$E$505) | J6: =SUMIF(T12_Calc!$N$1:$N$505,"Base rent — IL",T12_Calc!$F$1:$F$505) | K6: =SUMIF(T12_Calc!$N$1:$N$505,"Base rent — IL",T12_Calc!$G$1:$G$505) | L6: =SUMIF(T12_Calc!$N$1:$N$505,"Base rent — IL",T12_Calc!$H$1:$H$505) | M6: =SUMIF(T12_Calc!$N$1:$N$505,"Base rent — IL",T12_Calc!$I$1:$I$505) | N6: =SUMIF(T12_Calc!$N$1:$N$505,"Base rent — IL",T12_Calc!$J$1:$J$505) | O6: =SUMIF(T12_Calc!$N$1:$N$505,"Base rent — IL",T12_Calc!$K$1:$K$505) | P6: =SUMIF(T12_Calc!$N$1:$N$505,"Base rent — IL",T12_Calc!$L$1:$L$505) | Q6: =SUMIF(T12_Calc!$N$1:$N$505,"Base rent — IL",T12_Calc!$M$1:$M$505) | R6: =SUM(F6:Q6)
A7: Revenue | B7: Base rent — AL | C7: AL | E7: AL Base Rate Income | AL Base Rate | Assisted Living Base Rate | Assisted Living Revenue | F7: =SUMIF(T12_Calc!$N$1:$N$505,"Base rent — AL",T12_Calc!$B$1:$B$505) | G7: =SUMIF(T12_Calc!$N$1:$N$505,"Base rent — AL",T12_Calc!$C$1:$C$505) | H7: =SUMIF(T12_Calc!$N$1:$N$505,"Base rent — AL",T12_Calc!$D$1:$D$505) | I7: =SUMIF(T12_Calc!$N$1:$N$505,"Base rent — AL",T12_Calc!$E$1:$E$505) | J7: =SUMIF(T12_Calc!$N$1:$N$505,"Base rent — AL",T12_Calc!$F$1:$F$505) | K7: =SUMIF(T12_Calc!$N$1:$N$505,"Base rent — AL",T12_Calc!$G$1:$G$505) | L7: =SUMIF(T12_Calc!$N$1:$N$505,"Base rent — AL",T12_Calc!$H$1:$H$505) | M7: =SUMIF(T12_Calc!$N$1:$N$505,"Base rent — AL",T12_Calc!$I$1:$I$505) | N7: =SUMIF(T12_Calc!$N$1:$N$505,"Base rent — AL",T12_Calc!$J$1:$J$505) | O7: =SUMIF(T12_Calc!$N$1:$N$505,"Base rent — AL",T12_Calc!$K$1:$K$505) | P7: =SUMIF(T12_Calc!$N$1:$N$505,"Base rent — AL",T12_Calc!$L$1:$L$505) | Q7: =SUMIF(T12_Calc!$N$1:$N$505,"Base rent — AL",T12_Calc!$M$1:$M$505) | R7: =SUM(F7:Q7)
A8: Revenue | B8: Base rent — MC | C8: MC | E8: ALZ Base Rate Income | Memory Care Base Rate Income | MC Base Rate Income | Memory Care Revenue | F8: =SUMIF(T12_Calc!$N$1:$N$505,"Base rent — MC",T12_Calc!$B$1:$B$505) | G8: =SUMIF(T12_Calc!$N$1:$N$505,"Base rent — MC",T12_Calc!$C$1:$C$505) | H8: =SUMIF(T12_Calc!$N$1:$N$505,"Base rent — MC",T12_Calc!$D$1:$D$505) | I8: =SUMIF(T12_Calc!$N$1:$N$505,"Base rent — MC",T12_Calc!$E$1:$E$505) | J8: =SUMIF(T12_Calc!$N$1:$N$505,"Base rent — MC",T12_Calc!$F$1:$F$505) | K8: =SUMIF(T12_Calc!$N$1:$N$505,"Base rent — MC",T12_Calc!$G$1:$G$505) | L8: =SUMIF(T12_Calc!$N$1:$N$505,"Base rent — MC",T12_Calc!$H$1:$H$505) | M8: =SUMIF(T12_Calc!$N$1:$N$505,"Base rent — MC",T12_Calc!$I$1:$I$505) | N8: =SUMIF(T12_Calc!$N$1:$N$505,"Base rent — MC",T12_Calc!$J$1:$J$505) | O8: =SUMIF(T12_Calc!$N$1:$N$505,"Base rent — MC",T12_Calc!$K$1:$K$505) | P8: =SUMIF(T12_Calc!$N$1:$N$505,"Base rent — MC",T12_Calc!$L$1:$L$505) | Q8: =SUMIF(T12_Calc!$N$1:$N$505,"Base rent — MC",T12_Calc!$M$1:$M$505) | R8: =SUM(F8:Q8)
A9: Revenue | B9: LOC revenue — IL | C9: IL | E9: IL Care Rate Income | IL Level of Care Income | F9: =SUMIF(T12_Calc!$N$1:$N$505,"LOC revenue — IL",T12_Calc!$B$1:$B$505) | G9: =SUMIF(T12_Calc!$N$1:$N$505,"LOC revenue — IL",T12_Calc!$C$1:$C$505) | H9: =SUMIF(T12_Calc!$N$1:$N$505,"LOC revenue — IL",T12_Calc!$D$1:$D$505) | I9: =SUMIF(T12_Calc!$N$1:$N$505,"LOC revenue — IL",T12_Calc!$E$1:$E$505) | J9: =SUMIF(T12_Calc!$N$1:$N$505,"LOC revenue — IL",T12_Calc!$F$1:$F$505) | K9: =SUMIF(T12_Calc!$N$1:$N$505,"LOC revenue — IL",T12_Calc!$G$1:$G$505) | L9: =SUMIF(T12_Calc!$N$1:$N$505,"LOC revenue — IL",T12_Calc!$H$1:$H$505) | M9: =SUMIF(T12_Calc!$N$1:$N$505,"LOC revenue — IL",T12_Calc!$I$1:$I$505) | N9: =SUMIF(T12_Calc!$N$1:$N$505,"LOC revenue — IL",T12_Calc!$J$1:$J$505) | O9: =SUMIF(T12_Calc!$N$1:$N$505,"LOC revenue — IL",T12_Calc!$K$1:$K$505) | P9: =SUMIF(T12_Calc!$N$1:$N$505,"LOC revenue — IL",T12_Calc!$L$1:$L$505) | Q9: =SUMIF(T12_Calc!$N$1:$N$505,"LOC revenue — IL",T12_Calc!$M$1:$M$505) | R9: =SUM(F9:Q9)
A10: Revenue | B10: LOC revenue — AL | C10: AL | E10: AL Care Rate Income | AL Level of Care Income | AL Care Level Income | F10: =SUMIF(T12_Calc!$N$1:$N$505,"LOC revenue — AL",T12_Calc!$B$1:$B$505) | G10: =SUMIF(T12_Calc!$N$1:$N$505,"LOC revenue — AL",T12_Calc!$C$1:$C$505) | H10: =SUMIF(T12_Calc!$N$1:$N$505,"LOC revenue — AL",T12_Calc!$D$1:$D$505) | I10: =SUMIF(T12_Calc!$N$1:$N$505,"LOC revenue — AL",T12_Calc!$E$1:$E$505) | J10: =SUMIF(T12_Calc!$N$1:$N$505,"LOC revenue — AL",T12_Calc!$F$1:$F$505) | K10: =SUMIF(T12_Calc!$N$1:$N$505,"LOC revenue — AL",T12_Calc!$G$1:$G$505) | L10: =SUMIF(T12_Calc!$N$1:$N$505,"LOC revenue — AL",T12_Calc!$H$1:$H$505) | M10: =SUMIF(T12_Calc!$N$1:$N$505,"LOC revenue — AL",T12_Calc!$I$1:$I$505) | N10: =SUMIF(T12_Calc!$N$1:$N$505,"LOC revenue — AL",T12_Calc!$J$1:$J$505) | O10: =SUMIF(T12_Calc!$N$1:$N$505,"LOC revenue — AL",T12_Calc!$K$1:$K$505) | P10: =SUMIF(T12_Calc!$N$1:$N$505,"LOC revenue — AL",T12_Calc!$L$1:$L$505) | Q10: =SUMIF(T12_Calc!$N$1:$N$505,"LOC revenue — AL",T12_Calc!$M$1:$M$505) | R10: =SUM(F10:Q10)
A11: Revenue | B11: LOC revenue — MC | C11: MC | E11: ALZ Care Rate Income | Memory Care Level of Care | MC Care Rate Income | F11: =SUMIF(T12_Calc!$N$1:$N$505,"LOC revenue — MC",T12_Calc!$B$1:$B$505) | G11: =SUMIF(T12_Calc!$N$1:$N$505,"LOC revenue — MC",T12_Calc!$C$1:$C$505) | H11: =SUMIF(T12_Calc!$N$1:$N$505,"LOC revenue — MC",T12_Calc!$D$1:$D$505) | I11: =SUMIF(T12_Calc!$N$1:$N$505,"LOC revenue — MC",T12_Calc!$E$1:$E$505) | J11: =SUMIF(T12_Calc!$N$1:$N$505,"LOC revenue — MC",T12_Calc!$F$1:$F$505) | K11: =SUMIF(T12_Calc!$N$1:$N$505,"LOC revenue — MC",T12_Calc!$G$1:$G$505) | L11: =SUMIF(T12_Calc!$N$1:$N$505,"LOC revenue — MC",T12_Calc!$H$1:$H$505) | M11: =SUMIF(T12_Calc!$N$1:$N$505,"LOC revenue — MC",T12_Calc!$I$1:$I$505) | N11: =SUMIF(T12_Calc!$N$1:$N$505,"LOC revenue — MC",T12_Calc!$J$1:$J$505) | O11: =SUMIF(T12_Calc!$N$1:$N$505,"LOC revenue — MC",T12_Calc!$K$1:$K$505) | P11: =SUMIF(T12_Calc!$N$1:$N$505,"LOC revenue — MC",T12_Calc!$L$1:$L$505) | Q11: =SUMIF(T12_Calc!$N$1:$N$505,"LOC revenue — MC",T12_Calc!$M$1:$M$505) | R11: =SUM(F11:Q11)
A12: Revenue | B12: Community / move-in fees | C12: - | D12: Normalize to $0 | E12: Community Fees | Move-In Fees | F12: =SUMIF(T12_Calc!$N$1:$N$505,"Community / move-in fees",T12_Calc!$B$1:$B$505) | G12: =SUMIF(T12_Calc!$N$1:$N$505,"Community / move-in fees",T12_Calc!$C$1:$C$505) | H12: =SUMIF(T12_Calc!$N$1:$N$505,"Community / move-in fees",T12_Calc!$D$1:$D$505) | I12: =SUMIF(T12_Calc!$N$1:$N$505,"Community / move-in fees",T12_Calc!$E$1:$E$505) | J12: =SUMIF(T12_Calc!$N$1:$N$505,"Community / move-in fees",T12_Calc!$F$1:$F$505) | K12: =SUMIF(T12_Calc!$N$1:$N$505,"Community / move-in fees",T12_Calc!$G$1:$G$505) | L12: =SUMIF(T12_Calc!$N$1:$N$505,"Community / move-in fees",T12_Calc!$H$1:$H$505) | M12: =SUMIF(T12_Calc!$N$1:$N$505,"Community / move-in fees",T12_Calc!$I$1:$I$505) | N12: =SUMIF(T12_Calc!$N$1:$N$505,"Community / move-in fees",T12_Calc!$J$1:$J$505) | O12: =SUMIF(T12_Calc!$N$1:$N$505,"Community / move-in fees",T12_Calc!$K$1:$K$505) | P12: =SUMIF(T12_Calc!$N$1:$N$505,"Community / move-in fees",T12_Calc!$L$1:$L$505) | Q12: =SUMIF(T12_Calc!$N$1:$N$505,"Community / move-in fees",T12_Calc!$M$1:$M$505) | R12: =SUM(F12:Q12)
A13: Revenue | B13: Concessions & specials | C13: - | D13: Normalize to $0 | E13: Concessions | Move In Specials and Discounts | Move-In Specials | F13: =SUMIF(T12_Calc!$N$1:$N$505,"Concessions & specials",T12_Calc!$B$1:$B$505) | G13: =SUMIF(T12_Calc!$N$1:$N$505,"Concessions & specials",T12_Calc!$C$1:$C$505) | H13: =SUMIF(T12_Calc!$N$1:$N$505,"Concessions & specials",T12_Calc!$D$1:$D$505) | I13: =SUMIF(T12_Calc!$N$1:$N$505,"Concessions & specials",T12_Calc!$E$1:$E$505) | J13: =SUMIF(T12_Calc!$N$1:$N$505,"Concessions & specials",T12_Calc!$F$1:$F$505) | K13: =SUMIF(T12_Calc!$N$1:$N$505,"Concessions & specials",T12_Calc!$G$1:$G$505) | L13: =SUMIF(T12_Calc!$N$1:$N$505,"Concessions & specials",T12_Calc!$H$1:$H$505) | M13: =SUMIF(T12_Calc!$N$1:$N$505,"Concessions & specials",T12_Calc!$I$1:$I$505) | N13: =SUMIF(T12_Calc!$N$1:$N$505,"Concessions & specials",T12_Calc!$J$1:$J$505) | O13: =SUMIF(T12_Calc!$N$1:$N$505,"Concessions & specials",T12_Calc!$K$1:$K$505) | P13: =SUMIF(T12_Calc!$N$1:$N$505,"Concessions & specials",T12_Calc!$L$1:$L$505) | Q13: =SUMIF(T12_Calc!$N$1:$N$505,"Concessions & specials",T12_Calc!$M$1:$M$505) | R13: =SUM(F13:Q13)
A14: Revenue | B14: Respite care | C14: - | D14: Volatile | E14: Respite Care Income | Respite Care | F14: =SUMIF(T12_Calc!$N$1:$N$505,"Respite care",T12_Calc!$B$1:$B$505) | G14: =SUMIF(T12_Calc!$N$1:$N$505,"Respite care",T12_Calc!$C$1:$C$505) | H14: =SUMIF(T12_Calc!$N$1:$N$505,"Respite care",T12_Calc!$D$1:$D$505) | I14: =SUMIF(T12_Calc!$N$1:$N$505,"Respite care",T12_Calc!$E$1:$E$505) | J14: =SUMIF(T12_Calc!$N$1:$N$505,"Respite care",T12_Calc!$F$1:$F$505) | K14: =SUMIF(T12_Calc!$N$1:$N$505,"Respite care",T12_Calc!$G$1:$G$505) | L14: =SUMIF(T12_Calc!$N$1:$N$505,"Respite care",T12_Calc!$H$1:$H$505) | M14: =SUMIF(T12_Calc!$N$1:$N$505,"Respite care",T12_Calc!$I$1:$I$505) | N14: =SUMIF(T12_Calc!$N$1:$N$505,"Respite care",T12_Calc!$J$1:$J$505) | O14: =SUMIF(T12_Calc!$N$1:$N$505,"Respite care",T12_Calc!$K$1:$K$505) | P14: =SUMIF(T12_Calc!$N$1:$N$505,"Respite care",T12_Calc!$L$1:$L$505) | Q14: =SUMIF(T12_Calc!$N$1:$N$505,"Respite care",T12_Calc!$M$1:$M$505) | R14: =SUM(F14:Q14)
A15: Revenue | B15: 2nd Person Revenue | F15: =SUMIF(T12_Calc!$N$1:$N$505,"2nd Person Revenue",T12_Calc!$B$1:$B$505) | G15: =SUMIF(T12_Calc!$N$1:$N$505,"2nd Person Revenue",T12_Calc!$C$1:$C$505) | H15: =SUMIF(T12_Calc!$N$1:$N$505,"2nd Person Revenue",T12_Calc!$D$1:$D$505) | I15: =SUMIF(T12_Calc!$N$1:$N$505,"2nd Person Revenue",T12_Calc!$E$1:$E$505) | J15: =SUMIF(T12_Calc!$N$1:$N$505,"2nd Person Revenue",T12_Calc!$F$1:$F$505) | K15: =SUMIF(T12_Calc!$N$1:$N$505,"2nd Person Revenue",T12_Calc!$G$1:$G$505) | L15: =SUMIF(T12_Calc!$N$1:$N$505,"2nd Person Revenue",T12_Calc!$H$1:$H$505) | M15: =SUMIF(T12_Calc!$N$1:$N$505,"2nd Person Revenue",T12_Calc!$I$1:$I$505) | N15: =SUMIF(T12_Calc!$N$1:$N$505,"2nd Person Revenue",T12_Calc!$J$1:$J$505) | O15: =SUMIF(T12_Calc!$N$1:$N$505,"2nd Person Revenue",T12_Calc!$K$1:$K$505) | P15: =SUMIF(T12_Calc!$N$1:$N$505,"2nd Person Revenue",T12_Calc!$L$1:$L$505) | Q15: =SUMIF(T12_Calc!$N$1:$N$505,"2nd Person Revenue",T12_Calc!$M$1:$M$505) | R15: =SUM(F15:Q15)
A16: Revenue | B16: Meal Income | F16: =SUMIF(T12_Calc!$N$1:$N$505,"Meal Income",T12_Calc!$B$1:$B$505) | G16: =SUMIF(T12_Calc!$N$1:$N$505,"Meal Income",T12_Calc!$C$1:$C$505) | H16: =SUMIF(T12_Calc!$N$1:$N$505,"Meal Income",T12_Calc!$D$1:$D$505) | I16: =SUMIF(T12_Calc!$N$1:$N$505,"Meal Income",T12_Calc!$E$1:$E$505) | J16: =SUMIF(T12_Calc!$N$1:$N$505,"Meal Income",T12_Calc!$F$1:$F$505) | K16: =SUMIF(T12_Calc!$N$1:$N$505,"Meal Income",T12_Calc!$G$1:$G$505) | L16: =SUMIF(T12_Calc!$N$1:$N$505,"Meal Income",T12_Calc!$H$1:$H$505) | M16: =SUMIF(T12_Calc!$N$1:$N$505,"Meal Income",T12_Calc!$I$1:$I$505) | N16: =SUMIF(T12_Calc!$N$1:$N$505,"Meal Income",T12_Calc!$J$1:$J$505) | O16: =SUMIF(T12_Calc!$N$1:$N$505,"Meal Income",T12_Calc!$K$1:$K$505) | P16: =SUMIF(T12_Calc!$N$1:$N$505,"Meal Income",T12_Calc!$L$1:$L$505) | Q16: =SUMIF(T12_Calc!$N$1:$N$505,"Meal Income",T12_Calc!$M$1:$M$505) | R16: =SUM(F16:Q16)
A17: Revenue | B17: Housekeeping Income | F17: =SUMIF(T12_Calc!$N$1:$N$505,"Housekeeping Income",T12_Calc!$B$1:$B$505) | G17: =SUMIF(T12_Calc!$N$1:$N$505,"Housekeeping Income",T12_Calc!$C$1:$C$505) | H17: =SUMIF(T12_Calc!$N$1:$N$505,"Housekeeping Income",T12_Calc!$D$1:$D$505) | I17: =SUMIF(T12_Calc!$N$1:$N$505,"Housekeeping Income",T12_Calc!$E$1:$E$505) | J17: =SUMIF(T12_Calc!$N$1:$N$505,"Housekeeping Income",T12_Calc!$F$1:$F$505) | K17: =SUMIF(T12_Calc!$N$1:$N$505,"Housekeeping Income",T12_Calc!$G$1:$G$505) | L17: =SUMIF(T12_Calc!$N$1:$N$505,"Housekeeping Income",T12_Calc!$H$1:$H$505) | M17: =SUMIF(T12_Calc!$N$1:$N$505,"Housekeeping Income",T12_Calc!$I$1:$I$505) | N17: =SUMIF(T12_Calc!$N$1:$N$505,"Housekeeping Income",T12_Calc!$J$1:$J$505) | O17: =SUMIF(T12_Calc!$N$1:$N$505,"Housekeeping Income",T12_Calc!$K$1:$K$505) | P17: =SUMIF(T12_Calc!$N$1:$N$505,"Housekeeping Income",T12_Calc!$L$1:$L$505) | Q17: =SUMIF(T12_Calc!$N$1:$N$505,"Housekeeping Income",T12_Calc!$M$1:$M$505) | R17: =SUM(F17:Q17)
A18: Revenue | B18: Laundry Income | F18: =SUMIF(T12_Calc!$N$1:$N$505,"Laundry Income",T12_Calc!$B$1:$B$505) | G18: =SUMIF(T12_Calc!$N$1:$N$505,"Laundry Income",T12_Calc!$C$1:$C$505) | H18: =SUMIF(T12_Calc!$N$1:$N$505,"Laundry Income",T12_Calc!$D$1:$D$505) | I18: =SUMIF(T12_Calc!$N$1:$N$505,"Laundry Income",T12_Calc!$E$1:$E$505) | J18: =SUMIF(T12_Calc!$N$1:$N$505,"Laundry Income",T12_Calc!$F$1:$F$505) | K18: =SUMIF(T12_Calc!$N$1:$N$505,"Laundry Income",T12_Calc!$G$1:$G$505) | L18: =SUMIF(T12_Calc!$N$1:$N$505,"Laundry Income",T12_Calc!$H$1:$H$505) | M18: =SUMIF(T12_Calc!$N$1:$N$505,"Laundry Income",T12_Calc!$I$1:$I$505) | N18: =SUMIF(T12_Calc!$N$1:$N$505,"Laundry Income",T12_Calc!$J$1:$J$505) | O18: =SUMIF(T12_Calc!$N$1:$N$505,"Laundry Income",T12_Calc!$K$1:$K$505) | P18: =SUMIF(T12_Calc!$N$1:$N$505,"Laundry Income",T12_Calc!$L$1:$L$505) | Q18: =SUMIF(T12_Calc!$N$1:$N$505,"Laundry Income",T12_Calc!$M$1:$M$505) | R18: =SUM(F18:Q18)
A19: Revenue | B19: Scooter Fee Revenue | F19: =SUMIF(T12_Calc!$N$1:$N$505,"Scooter Fee Revenue",T12_Calc!$B$1:$B$505) | G19: =SUMIF(T12_Calc!$N$1:$N$505,"Scooter Fee Revenue",T12_Calc!$C$1:$C$505) | H19: =SUMIF(T12_Calc!$N$1:$N$505,"Scooter Fee Revenue",T12_Calc!$D$1:$D$505) | I19: =SUMIF(T12_Calc!$N$1:$N$505,"Scooter Fee Revenue",T12_Calc!$E$1:$E$505) | J19: =SUMIF(T12_Calc!$N$1:$N$505,"Scooter Fee Revenue",T12_Calc!$F$1:$F$505) | K19: =SUMIF(T12_Calc!$N$1:$N$505,"Scooter Fee Revenue",T12_Calc!$G$1:$G$505) | L19: =SUMIF(T12_Calc!$N$1:$N$505,"Scooter Fee Revenue",T12_Calc!$H$1:$H$505) | M19: =SUMIF(T12_Calc!$N$1:$N$505,"Scooter Fee Revenue",T12_Calc!$I$1:$I$505) | N19: =SUMIF(T12_Calc!$N$1:$N$505,"Scooter Fee Revenue",T12_Calc!$J$1:$J$505) | O19: =SUMIF(T12_Calc!$N$1:$N$505,"Scooter Fee Revenue",T12_Calc!$K$1:$K$505) | P19: =SUMIF(T12_Calc!$N$1:$N$505,"Scooter Fee Revenue",T12_Calc!$L$1:$L$505) | Q19: =SUMIF(T12_Calc!$N$1:$N$505,"Scooter Fee Revenue",T12_Calc!$M$1:$M$505) | R19: =SUM(F19:Q19)
A20: Revenue | B20: Transfer Fee Revenue | F20: =SUMIF(T12_Calc!$N$1:$N$505,"Transfer Fee Revenue",T12_Calc!$B$1:$B$505) | G20: =SUMIF(T12_Calc!$N$1:$N$505,"Transfer Fee Revenue",T12_Calc!$C$1:$C$505) | H20: =SUMIF(T12_Calc!$N$1:$N$505,"Transfer Fee Revenue",T12_Calc!$D$1:$D$505) | I20: =SUMIF(T12_Calc!$N$1:$N$505,"Transfer Fee Revenue",T12_Calc!$E$1:$E$505) | J20: =SUMIF(T12_Calc!$N$1:$N$505,"Transfer Fee Revenue",T12_Calc!$F$1:$F$505) | K20: =SUMIF(T12_Calc!$N$1:$N$505,"Transfer Fee Revenue",T12_Calc!$G$1:$G$505) | L20: =SUMIF(T12_Calc!$N$1:$N$505,"Transfer Fee Revenue",T12_Calc!$H$1:$H$505) | M20: =SUMIF(T12_Calc!$N$1:$N$505,"Transfer Fee Revenue",T12_Calc!$I$1:$I$505) | N20: =SUMIF(T12_Calc!$N$1:$N$505,"Transfer Fee Revenue",T12_Calc!$J$1:$J$505) | O20: =SUMIF(T12_Calc!$N$1:$N$505,"Transfer Fee Revenue",T12_Calc!$K$1:$K$505) | P20: =SUMIF(T12_Calc!$N$1:$N$505,"Transfer Fee Revenue",T12_Calc!$L$1:$L$505) | Q20: =SUMIF(T12_Calc!$N$1:$N$505,"Transfer Fee Revenue",T12_Calc!$M$1:$M$505) | R20: =SUM(F20:Q20)
A21: Revenue | B21: Other community revenue | C21: - | E21: Guest Meals | Beautician Income | Utility Income | Incontinence Supplies Income | Personal Purchases | Administrative Fees | Finance Charges Revenue | F21: =SUMIF(T12_Calc!$N$1:$N$505,"Other community revenue",T12_Calc!$B$1:$B$505) | G21: =SUMIF(T12_Calc!$N$1:$N$505,"Other community revenue",T12_Calc!$C$1:$C$505) | H21: =SUMIF(T12_Calc!$N$1:$N$505,"Other community revenue",T12_Calc!$D$1:$D$505) | I21: =SUMIF(T12_Calc!$N$1:$N$505,"Other community revenue",T12_Calc!$E$1:$E$505) | J21: =SUMIF(T12_Calc!$N$1:$N$505,"Other community revenue",T12_Calc!$F$1:$F$505) | K21: =SUMIF(T12_Calc!$N$1:$N$505,"Other community revenue",T12_Calc!$G$1:$G$505) | L21: =SUMIF(T12_Calc!$N$1:$N$505,"Other community revenue",T12_Calc!$H$1:$H$505) | M21: =SUMIF(T12_Calc!$N$1:$N$505,"Other community revenue",T12_Calc!$I$1:$I$505) | N21: =SUMIF(T12_Calc!$N$1:$N$505,"Other community revenue",T12_Calc!$J$1:$J$505) | O21: =SUMIF(T12_Calc!$N$1:$N$505,"Other community revenue",T12_Calc!$K$1:$K$505) | P21: =SUMIF(T12_Calc!$N$1:$N$505,"Other community revenue",T12_Calc!$L$1:$L$505) | Q21: =SUMIF(T12_Calc!$N$1:$N$505,"Other community revenue",T12_Calc!$M$1:$M$505) | R21: =SUM(F21:Q21)
A22: Labor | B22: Care staff labor | C22: - | E22: Care Staff Labor | Direct Care Labor | Other Labor | F22: =SUMIF(T12_Calc!$N$1:$N$505,"Care staff labor",T12_Calc!$B$1:$B$505) | G22: =SUMIF(T12_Calc!$N$1:$N$505,"Care staff labor",T12_Calc!$C$1:$C$505) | H22: =SUMIF(T12_Calc!$N$1:$N$505,"Care staff labor",T12_Calc!$D$1:$D$505) | I22: =SUMIF(T12_Calc!$N$1:$N$505,"Care staff labor",T12_Calc!$E$1:$E$505) | J22: =SUMIF(T12_Calc!$N$1:$N$505,"Care staff labor",T12_Calc!$F$1:$F$505) | K22: =SUMIF(T12_Calc!$N$1:$N$505,"Care staff labor",T12_Calc!$G$1:$G$505) | L22: =SUMIF(T12_Calc!$N$1:$N$505,"Care staff labor",T12_Calc!$H$1:$H$505) | M22: =SUMIF(T12_Calc!$N$1:$N$505,"Care staff labor",T12_Calc!$I$1:$I$505) | N22: =SUMIF(T12_Calc!$N$1:$N$505,"Care staff labor",T12_Calc!$J$1:$J$505) | O22: =SUMIF(T12_Calc!$N$1:$N$505,"Care staff labor",T12_Calc!$K$1:$K$505) | P22: =SUMIF(T12_Calc!$N$1:$N$505,"Care staff labor",T12_Calc!$L$1:$L$505) | Q22: =SUMIF(T12_Calc!$N$1:$N$505,"Care staff labor",T12_Calc!$M$1:$M$505) | R22: =SUM(F22:Q22)
A23: Labor | B23: Wellness / care coordinators | C23: - | E23: Wellness/Care Coordinators Labor | Wellness/Care Coordinator Labor | Care Coordinator Labor | F23: =SUMIF(T12_Calc!$N$1:$N$505,"Wellness / care coordinators",T12_Calc!$B$1:$B$505) | G23: =SUMIF(T12_Calc!$N$1:$N$505,"Wellness / care coordinators",T12_Calc!$C$1:$C$505) | H23: =SUMIF(T12_Calc!$N$1:$N$505,"Wellness / care coordinators",T12_Calc!$D$1:$D$505) | I23: =SUMIF(T12_Calc!$N$1:$N$505,"Wellness / care coordinators",T12_Calc!$E$1:$E$505) | J23: =SUMIF(T12_Calc!$N$1:$N$505,"Wellness / care coordinators",T12_Calc!$F$1:$F$505) | K23: =SUMIF(T12_Calc!$N$1:$N$505,"Wellness / care coordinators",T12_Calc!$G$1:$G$505) | L23: =SUMIF(T12_Calc!$N$1:$N$505,"Wellness / care coordinators",T12_Calc!$H$1:$H$505) | M23: =SUMIF(T12_Calc!$N$1:$N$505,"Wellness / care coordinators",T12_Calc!$I$1:$I$505) | N23: =SUMIF(T12_Calc!$N$1:$N$505,"Wellness / care coordinators",T12_Calc!$J$1:$J$505) | O23: =SUMIF(T12_Calc!$N$1:$N$505,"Wellness / care coordinators",T12_Calc!$K$1:$K$505) | P23: =SUMIF(T12_Calc!$N$1:$N$505,"Wellness / care coordinators",T12_Calc!$L$1:$L$505) | Q23: =SUMIF(T12_Calc!$N$1:$N$505,"Wellness / care coordinators",T12_Calc!$M$1:$M$505) | R23: =SUM(F23:Q23)
A24: Labor | B24: Contract / agency labor | C24: - | D24: Normalize at stabilization | E24: Contract Labor - Care | Contract Labor | Agency Labor | F24: =SUMIF(T12_Calc!$N$1:$N$505,"Contract / agency labor",T12_Calc!$B$1:$B$505) | G24: =SUMIF(T12_Calc!$N$1:$N$505,"Contract / agency labor",T12_Calc!$C$1:$C$505) | H24: =SUMIF(T12_Calc!$N$1:$N$505,"Contract / agency labor",T12_Calc!$D$1:$D$505) | I24: =SUMIF(T12_Calc!$N$1:$N$505,"Contract / agency labor",T12_Calc!$E$1:$E$505) | J24: =SUMIF(T12_Calc!$N$1:$N$505,"Contract / agency labor",T12_Calc!$F$1:$F$505) | K24: =SUMIF(T12_Calc!$N$1:$N$505,"Contract / agency labor",T12_Calc!$G$1:$G$505) | L24: =SUMIF(T12_Calc!$N$1:$N$505,"Contract / agency labor",T12_Calc!$H$1:$H$505) | M24: =SUMIF(T12_Calc!$N$1:$N$505,"Contract / agency labor",T12_Calc!$I$1:$I$505) | N24: =SUMIF(T12_Calc!$N$1:$N$505,"Contract / agency labor",T12_Calc!$J$1:$J$505) | O24: =SUMIF(T12_Calc!$N$1:$N$505,"Contract / agency labor",T12_Calc!$K$1:$K$505) | P24: =SUMIF(T12_Calc!$N$1:$N$505,"Contract / agency labor",T12_Calc!$L$1:$L$505) | Q24: =SUMIF(T12_Calc!$N$1:$N$505,"Contract / agency labor",T12_Calc!$M$1:$M$505) | R24: =SUM(F24:Q24)
A25: Labor | B25: Activities labor | C25: - | E25: Activities Labor | F25: =SUMIF(T12_Calc!$N$1:$N$505,"Activities labor",T12_Calc!$B$1:$B$505) | G25: =SUMIF(T12_Calc!$N$1:$N$505,"Activities labor",T12_Calc!$C$1:$C$505) | H25: =SUMIF(T12_Calc!$N$1:$N$505,"Activities labor",T12_Calc!$D$1:$D$505) | I25: =SUMIF(T12_Calc!$N$1:$N$505,"Activities labor",T12_Calc!$E$1:$E$505) | J25: =SUMIF(T12_Calc!$N$1:$N$505,"Activities labor",T12_Calc!$F$1:$F$505) | K25: =SUMIF(T12_Calc!$N$1:$N$505,"Activities labor",T12_Calc!$G$1:$G$505) | L25: =SUMIF(T12_Calc!$N$1:$N$505,"Activities labor",T12_Calc!$H$1:$H$505) | M25: =SUMIF(T12_Calc!$N$1:$N$505,"Activities labor",T12_Calc!$I$1:$I$505) | N25: =SUMIF(T12_Calc!$N$1:$N$505,"Activities labor",T12_Calc!$J$1:$J$505) | O25: =SUMIF(T12_Calc!$N$1:$N$505,"Activities labor",T12_Calc!$K$1:$K$505) | P25: =SUMIF(T12_Calc!$N$1:$N$505,"Activities labor",T12_Calc!$L$1:$L$505) | Q25: =SUMIF(T12_Calc!$N$1:$N$505,"Activities labor",T12_Calc!$M$1:$M$505) | R25: =SUM(F25:Q25)
A26: Labor | B26: Dining / food service labor | C26: - | E26: Food Service Labor | Dietary Labor | Dining Labor | F26: =SUMIF(T12_Calc!$N$1:$N$505,"Dining / food service labor",T12_Calc!$B$1:$B$505) | G26: =SUMIF(T12_Calc!$N$1:$N$505,"Dining / food service labor",T12_Calc!$C$1:$C$505) | H26: =SUMIF(T12_Calc!$N$1:$N$505,"Dining / food service labor",T12_Calc!$D$1:$D$505) | I26: =SUMIF(T12_Calc!$N$1:$N$505,"Dining / food service labor",T12_Calc!$E$1:$E$505) | J26: =SUMIF(T12_Calc!$N$1:$N$505,"Dining / food service labor",T12_Calc!$F$1:$F$505) | K26: =SUMIF(T12_Calc!$N$1:$N$505,"Dining / food service labor",T12_Calc!$G$1:$G$505) | L26: =SUMIF(T12_Calc!$N$1:$N$505,"Dining / food service labor",T12_Calc!$H$1:$H$505) | M26: =SUMIF(T12_Calc!$N$1:$N$505,"Dining / food service labor",T12_Calc!$I$1:$I$505) | N26: =SUMIF(T12_Calc!$N$1:$N$505,"Dining / food service labor",T12_Calc!$J$1:$J$505) | O26: =SUMIF(T12_Calc!$N$1:$N$505,"Dining / food service labor",T12_Calc!$K$1:$K$505) | P26: =SUMIF(T12_Calc!$N$1:$N$505,"Dining / food service labor",T12_Calc!$L$1:$L$505) | Q26: =SUMIF(T12_Calc!$N$1:$N$505,"Dining / food service labor",T12_Calc!$M$1:$M$505) | R26: =SUM(F26:Q26)
A27: Labor | B27: Maint. & housekeeping labor | C27: - | E27: Maintenance/Housekeeping Labor | Maintenance Labor | Housekeeping Labor | F27: =SUMIF(T12_Calc!$N$1:$N$505,"Maint. & housekeeping labor",T12_Calc!$B$1:$B$505) | G27: =SUMIF(T12_Calc!$N$1:$N$505,"Maint. & housekeeping labor",T12_Calc!$C$1:$C$505) | H27: =SUMIF(T12_Calc!$N$1:$N$505,"Maint. & housekeeping labor",T12_Calc!$D$1:$D$505) | I27: =SUMIF(T12_Calc!$N$1:$N$505,"Maint. & housekeeping labor",T12_Calc!$E$1:$E$505) | J27: =SUMIF(T12_Calc!$N$1:$N$505,"Maint. & housekeeping labor",T12_Calc!$F$1:$F$505) | K27: =SUMIF(T12_Calc!$N$1:$N$505,"Maint. & housekeeping labor",T12_Calc!$G$1:$G$505) | L27: =SUMIF(T12_Calc!$N$1:$N$505,"Maint. & housekeeping labor",T12_Calc!$H$1:$H$505) | M27: =SUMIF(T12_Calc!$N$1:$N$505,"Maint. & housekeeping labor",T12_Calc!$I$1:$I$505) | N27: =SUMIF(T12_Calc!$N$1:$N$505,"Maint. & housekeeping labor",T12_Calc!$J$1:$J$505) | O27: =SUMIF(T12_Calc!$N$1:$N$505,"Maint. & housekeeping labor",T12_Calc!$K$1:$K$505) | P27: =SUMIF(T12_Calc!$N$1:$N$505,"Maint. & housekeeping labor",T12_Calc!$L$1:$L$505) | Q27: =SUMIF(T12_Calc!$N$1:$N$505,"Maint. & housekeeping labor",T12_Calc!$M$1:$M$505) | R27: =SUM(F27:Q27)
A28: Labor | B28: Administrative labor | C28: - | E28: Administration Labor | Administrative Labor | F28: =SUMIF(T12_Calc!$N$1:$N$505,"Administrative labor",T12_Calc!$B$1:$B$505) | G28: =SUMIF(T12_Calc!$N$1:$N$505,"Administrative labor",T12_Calc!$C$1:$C$505) | H28: =SUMIF(T12_Calc!$N$1:$N$505,"Administrative labor",T12_Calc!$D$1:$D$505) | I28: =SUMIF(T12_Calc!$N$1:$N$505,"Administrative labor",T12_Calc!$E$1:$E$505) | J28: =SUMIF(T12_Calc!$N$1:$N$505,"Administrative labor",T12_Calc!$F$1:$F$505) | K28: =SUMIF(T12_Calc!$N$1:$N$505,"Administrative labor",T12_Calc!$G$1:$G$505) | L28: =SUMIF(T12_Calc!$N$1:$N$505,"Administrative labor",T12_Calc!$H$1:$H$505) | M28: =SUMIF(T12_Calc!$N$1:$N$505,"Administrative labor",T12_Calc!$I$1:$I$505) | N28: =SUMIF(T12_Calc!$N$1:$N$505,"Administrative labor",T12_Calc!$J$1:$J$505) | O28: =SUMIF(T12_Calc!$N$1:$N$505,"Administrative labor",T12_Calc!$K$1:$K$505) | P28: =SUMIF(T12_Calc!$N$1:$N$505,"Administrative labor",T12_Calc!$L$1:$L$505) | Q28: =SUMIF(T12_Calc!$N$1:$N$505,"Administrative labor",T12_Calc!$M$1:$M$505) | R28: =SUM(F28:Q28)
A29: Labor | B29: Bonus wages | C29: - | D29: Stabilize annually | E29: Bonus Wages | F29: =SUMIF(T12_Calc!$N$1:$N$505,"Bonus wages",T12_Calc!$B$1:$B$505) | G29: =SUMIF(T12_Calc!$N$1:$N$505,"Bonus wages",T12_Calc!$C$1:$C$505) | H29: =SUMIF(T12_Calc!$N$1:$N$505,"Bonus wages",T12_Calc!$D$1:$D$505) | I29: =SUMIF(T12_Calc!$N$1:$N$505,"Bonus wages",T12_Calc!$E$1:$E$505) | J29: =SUMIF(T12_Calc!$N$1:$N$505,"Bonus wages",T12_Calc!$F$1:$F$505) | K29: =SUMIF(T12_Calc!$N$1:$N$505,"Bonus wages",T12_Calc!$G$1:$G$505) | L29: =SUMIF(T12_Calc!$N$1:$N$505,"Bonus wages",T12_Calc!$H$1:$H$505) | M29: =SUMIF(T12_Calc!$N$1:$N$505,"Bonus wages",T12_Calc!$I$1:$I$505) | N29: =SUMIF(T12_Calc!$N$1:$N$505,"Bonus wages",T12_Calc!$J$1:$J$505) | O29: =SUMIF(T12_Calc!$N$1:$N$505,"Bonus wages",T12_Calc!$K$1:$K$505) | P29: =SUMIF(T12_Calc!$N$1:$N$505,"Bonus wages",T12_Calc!$L$1:$L$505) | Q29: =SUMIF(T12_Calc!$N$1:$N$505,"Bonus wages",T12_Calc!$M$1:$M$505) | R29: =SUM(F29:Q29)
A30: Labor | B30: Overtime wages | C30: - | D30: Flag if >5% of wages | E30: Overtime | Overtime Wages | OT Wages | F30: =SUMIF(T12_Calc!$N$1:$N$505,"Overtime wages",T12_Calc!$B$1:$B$505) | G30: =SUMIF(T12_Calc!$N$1:$N$505,"Overtime wages",T12_Calc!$C$1:$C$505) | H30: =SUMIF(T12_Calc!$N$1:$N$505,"Overtime wages",T12_Calc!$D$1:$D$505) | I30: =SUMIF(T12_Calc!$N$1:$N$505,"Overtime wages",T12_Calc!$E$1:$E$505) | J30: =SUMIF(T12_Calc!$N$1:$N$505,"Overtime wages",T12_Calc!$F$1:$F$505) | K30: =SUMIF(T12_Calc!$N$1:$N$505,"Overtime wages",T12_Calc!$G$1:$G$505) | L30: =SUMIF(T12_Calc!$N$1:$N$505,"Overtime wages",T12_Calc!$H$1:$H$505) | M30: =SUMIF(T12_Calc!$N$1:$N$505,"Overtime wages",T12_Calc!$I$1:$I$505) | N30: =SUMIF(T12_Calc!$N$1:$N$505,"Overtime wages",T12_Calc!$J$1:$J$505) | O30: =SUMIF(T12_Calc!$N$1:$N$505,"Overtime wages",T12_Calc!$K$1:$K$505) | P30: =SUMIF(T12_Calc!$N$1:$N$505,"Overtime wages",T12_Calc!$L$1:$L$505) | Q30: =SUMIF(T12_Calc!$N$1:$N$505,"Overtime wages",T12_Calc!$M$1:$M$505) | R30: =SUM(F30:Q30)
A31: Labor | B31: PTO wages | C31: - | D31: Annualize | E31: PTO Wages | PTO | F31: =SUMIF(T12_Calc!$N$1:$N$505,"PTO wages",T12_Calc!$B$1:$B$505) | G31: =SUMIF(T12_Calc!$N$1:$N$505,"PTO wages",T12_Calc!$C$1:$C$505) | H31: =SUMIF(T12_Calc!$N$1:$N$505,"PTO wages",T12_Calc!$D$1:$D$505) | I31: =SUMIF(T12_Calc!$N$1:$N$505,"PTO wages",T12_Calc!$E$1:$E$505) | J31: =SUMIF(T12_Calc!$N$1:$N$505,"PTO wages",T12_Calc!$F$1:$F$505) | K31: =SUMIF(T12_Calc!$N$1:$N$505,"PTO wages",T12_Calc!$G$1:$G$505) | L31: =SUMIF(T12_Calc!$N$1:$N$505,"PTO wages",T12_Calc!$H$1:$H$505) | M31: =SUMIF(T12_Calc!$N$1:$N$505,"PTO wages",T12_Calc!$I$1:$I$505) | N31: =SUMIF(T12_Calc!$N$1:$N$505,"PTO wages",T12_Calc!$J$1:$J$505) | O31: =SUMIF(T12_Calc!$N$1:$N$505,"PTO wages",T12_Calc!$K$1:$K$505) | P31: =SUMIF(T12_Calc!$N$1:$N$505,"PTO wages",T12_Calc!$L$1:$L$505) | Q31: =SUMIF(T12_Calc!$N$1:$N$505,"PTO wages",T12_Calc!$M$1:$M$505) | R31: =SUM(F31:Q31)
A32: Labor | B32: Payroll taxes | C32: - | E32: Payroll Taxes | F32: =SUMIF(T12_Calc!$N$1:$N$505,"Payroll taxes",T12_Calc!$B$1:$B$505) | G32: =SUMIF(T12_Calc!$N$1:$N$505,"Payroll taxes",T12_Calc!$C$1:$C$505) | H32: =SUMIF(T12_Calc!$N$1:$N$505,"Payroll taxes",T12_Calc!$D$1:$D$505) | I32: =SUMIF(T12_Calc!$N$1:$N$505,"Payroll taxes",T12_Calc!$E$1:$E$505) | J32: =SUMIF(T12_Calc!$N$1:$N$505,"Payroll taxes",T12_Calc!$F$1:$F$505) | K32: =SUMIF(T12_Calc!$N$1:$N$505,"Payroll taxes",T12_Calc!$G$1:$G$505) | L32: =SUMIF(T12_Calc!$N$1:$N$505,"Payroll taxes",T12_Calc!$H$1:$H$505) | M32: =SUMIF(T12_Calc!$N$1:$N$505,"Payroll taxes",T12_Calc!$I$1:$I$505) | N32: =SUMIF(T12_Calc!$N$1:$N$505,"Payroll taxes",T12_Calc!$J$1:$J$505) | O32: =SUMIF(T12_Calc!$N$1:$N$505,"Payroll taxes",T12_Calc!$K$1:$K$505) | P32: =SUMIF(T12_Calc!$N$1:$N$505,"Payroll taxes",T12_Calc!$L$1:$L$505) | Q32: =SUMIF(T12_Calc!$N$1:$N$505,"Payroll taxes",T12_Calc!$M$1:$M$505) | R32: =SUM(F32:Q32)
A33: Labor | B33: Employee benefits | C33: - | E33: Employee Benefits - Insurance | Employee Benefits | F33: =SUMIF(T12_Calc!$N$1:$N$505,"Employee benefits",T12_Calc!$B$1:$B$505) | G33: =SUMIF(T12_Calc!$N$1:$N$505,"Employee benefits",T12_Calc!$C$1:$C$505) | H33: =SUMIF(T12_Calc!$N$1:$N$505,"Employee benefits",T12_Calc!$D$1:$D$505) | I33: =SUMIF(T12_Calc!$N$1:$N$505,"Employee benefits",T12_Calc!$E$1:$E$505) | J33: =SUMIF(T12_Calc!$N$1:$N$505,"Employee benefits",T12_Calc!$F$1:$F$505) | K33: =SUMIF(T12_Calc!$N$1:$N$505,"Employee benefits",T12_Calc!$G$1:$G$505) | L33: =SUMIF(T12_Calc!$N$1:$N$505,"Employee benefits",T12_Calc!$H$1:$H$505) | M33: =SUMIF(T12_Calc!$N$1:$N$505,"Employee benefits",T12_Calc!$I$1:$I$505) | N33: =SUMIF(T12_Calc!$N$1:$N$505,"Employee benefits",T12_Calc!$J$1:$J$505) | O33: =SUMIF(T12_Calc!$N$1:$N$505,"Employee benefits",T12_Calc!$K$1:$K$505) | P33: =SUMIF(T12_Calc!$N$1:$N$505,"Employee benefits",T12_Calc!$L$1:$L$505) | Q33: =SUMIF(T12_Calc!$N$1:$N$505,"Employee benefits",T12_Calc!$M$1:$M$505) | R33: =SUM(F33:Q33)
A34: Labor | B34: Workers' comp insurance | C34: - | E34: Worker's Comp Insurance | Workers Comp Insurance | Workers' Compensation | F34: =SUMIF(T12_Calc!$N$1:$N$505,"Workers' comp insurance",T12_Calc!$B$1:$B$505) | G34: =SUMIF(T12_Calc!$N$1:$N$505,"Workers' comp insurance",T12_Calc!$C$1:$C$505) | H34: =SUMIF(T12_Calc!$N$1:$N$505,"Workers' comp insurance",T12_Calc!$D$1:$D$505) | I34: =SUMIF(T12_Calc!$N$1:$N$505,"Workers' comp insurance",T12_Calc!$E$1:$E$505) | J34: =SUMIF(T12_Calc!$N$1:$N$505,"Workers' comp insurance",T12_Calc!$F$1:$F$505) | K34: =SUMIF(T12_Calc!$N$1:$N$505,"Workers' comp insurance",T12_Calc!$G$1:$G$505) | L34: =SUMIF(T12_Calc!$N$1:$N$505,"Workers' comp insurance",T12_Calc!$H$1:$H$505) | M34: =SUMIF(T12_Calc!$N$1:$N$505,"Workers' comp insurance",T12_Calc!$I$1:$I$505) | N34: =SUMIF(T12_Calc!$N$1:$N$505,"Workers' comp insurance",T12_Calc!$J$1:$J$505) | O34: =SUMIF(T12_Calc!$N$1:$N$505,"Workers' comp insurance",T12_Calc!$K$1:$K$505) | P34: =SUMIF(T12_Calc!$N$1:$N$505,"Workers' comp insurance",T12_Calc!$L$1:$L$505) | Q34: =SUMIF(T12_Calc!$N$1:$N$505,"Workers' comp insurance",T12_Calc!$M$1:$M$505) | R34: =SUM(F34:Q34)
A35: Labor | B35: Employee 401(k) | C35: - | E35: Employee 401(K) | Employee 401(k) | F35: =SUMIF(T12_Calc!$N$1:$N$505,"Employee 401(k)",T12_Calc!$B$1:$B$505) | G35: =SUMIF(T12_Calc!$N$1:$N$505,"Employee 401(k)",T12_Calc!$C$1:$C$505) | H35: =SUMIF(T12_Calc!$N$1:$N$505,"Employee 401(k)",T12_Calc!$D$1:$D$505) | I35: =SUMIF(T12_Calc!$N$1:$N$505,"Employee 401(k)",T12_Calc!$E$1:$E$505) | J35: =SUMIF(T12_Calc!$N$1:$N$505,"Employee 401(k)",T12_Calc!$F$1:$F$505) | K35: =SUMIF(T12_Calc!$N$1:$N$505,"Employee 401(k)",T12_Calc!$G$1:$G$505) | L35: =SUMIF(T12_Calc!$N$1:$N$505,"Employee 401(k)",T12_Calc!$H$1:$H$505) | M35: =SUMIF(T12_Calc!$N$1:$N$505,"Employee 401(k)",T12_Calc!$I$1:$I$505) | N35: =SUMIF(T12_Calc!$N$1:$N$505,"Employee 401(k)",T12_Calc!$J$1:$J$505) | O35: =SUMIF(T12_Calc!$N$1:$N$505,"Employee 401(k)",T12_Calc!$K$1:$K$505) | P35: =SUMIF(T12_Calc!$N$1:$N$505,"Employee 401(k)",T12_Calc!$L$1:$L$505) | Q35: =SUMIF(T12_Calc!$N$1:$N$505,"Employee 401(k)",T12_Calc!$M$1:$M$505) | R35: =SUM(F35:Q35)
A36: Non-Labor | B36: Food cost | C36: - | E36: Food Cost | F36: =SUMIF(T12_Calc!$N$1:$N$505,"Food cost",T12_Calc!$B$1:$B$505) | G36: =SUMIF(T12_Calc!$N$1:$N$505,"Food cost",T12_Calc!$C$1:$C$505) | H36: =SUMIF(T12_Calc!$N$1:$N$505,"Food cost",T12_Calc!$D$1:$D$505) | I36: =SUMIF(T12_Calc!$N$1:$N$505,"Food cost",T12_Calc!$E$1:$E$505) | J36: =SUMIF(T12_Calc!$N$1:$N$505,"Food cost",T12_Calc!$F$1:$F$505) | K36: =SUMIF(T12_Calc!$N$1:$N$505,"Food cost",T12_Calc!$G$1:$G$505) | L36: =SUMIF(T12_Calc!$N$1:$N$505,"Food cost",T12_Calc!$H$1:$H$505) | M36: =SUMIF(T12_Calc!$N$1:$N$505,"Food cost",T12_Calc!$I$1:$I$505) | N36: =SUMIF(T12_Calc!$N$1:$N$505,"Food cost",T12_Calc!$J$1:$J$505) | O36: =SUMIF(T12_Calc!$N$1:$N$505,"Food cost",T12_Calc!$K$1:$K$505) | P36: =SUMIF(T12_Calc!$N$1:$N$505,"Food cost",T12_Calc!$L$1:$L$505) | Q36: =SUMIF(T12_Calc!$N$1:$N$505,"Food cost",T12_Calc!$M$1:$M$505) | R36: =SUM(F36:Q36)
A37: Non-Labor | B37: Dining & kitchen supplies | C37: - | E37: Dietary Supplies | F37: =SUMIF(T12_Calc!$N$1:$N$505,"Dining & kitchen supplies",T12_Calc!$B$1:$B$505) | G37: =SUMIF(T12_Calc!$N$1:$N$505,"Dining & kitchen supplies",T12_Calc!$C$1:$C$505) | H37: =SUMIF(T12_Calc!$N$1:$N$505,"Dining & kitchen supplies",T12_Calc!$D$1:$D$505) | I37: =SUMIF(T12_Calc!$N$1:$N$505,"Dining & kitchen supplies",T12_Calc!$E$1:$E$505) | J37: =SUMIF(T12_Calc!$N$1:$N$505,"Dining & kitchen supplies",T12_Calc!$F$1:$F$505) | K37: =SUMIF(T12_Calc!$N$1:$N$505,"Dining & kitchen supplies",T12_Calc!$G$1:$G$505) | L37: =SUMIF(T12_Calc!$N$1:$N$505,"Dining & kitchen supplies",T12_Calc!$H$1:$H$505) | M37: =SUMIF(T12_Calc!$N$1:$N$505,"Dining & kitchen supplies",T12_Calc!$I$1:$I$505) | N37: =SUMIF(T12_Calc!$N$1:$N$505,"Dining & kitchen supplies",T12_Calc!$J$1:$J$505) | O37: =SUMIF(T12_Calc!$N$1:$N$505,"Dining & kitchen supplies",T12_Calc!$K$1:$K$505) | P37: =SUMIF(T12_Calc!$N$1:$N$505,"Dining & kitchen supplies",T12_Calc!$L$1:$L$505) | Q37: =SUMIF(T12_Calc!$N$1:$N$505,"Dining & kitchen supplies",T12_Calc!$M$1:$M$505) | R37: =SUM(F37:Q37)
A38: Non-Labor | B38: Nursing & care supplies | C38: - | E38: Nursing Supplies | F38: =SUMIF(T12_Calc!$N$1:$N$505,"Nursing & care supplies",T12_Calc!$B$1:$B$505) | G38: =SUMIF(T12_Calc!$N$1:$N$505,"Nursing & care supplies",T12_Calc!$C$1:$C$505) | H38: =SUMIF(T12_Calc!$N$1:$N$505,"Nursing & care supplies",T12_Calc!$D$1:$D$505) | I38: =SUMIF(T12_Calc!$N$1:$N$505,"Nursing & care supplies",T12_Calc!$E$1:$E$505) | J38: =SUMIF(T12_Calc!$N$1:$N$505,"Nursing & care supplies",T12_Calc!$F$1:$F$505) | K38: =SUMIF(T12_Calc!$N$1:$N$505,"Nursing & care supplies",T12_Calc!$G$1:$G$505) | L38: =SUMIF(T12_Calc!$N$1:$N$505,"Nursing & care supplies",T12_Calc!$H$1:$H$505) | M38: =SUMIF(T12_Calc!$N$1:$N$505,"Nursing & care supplies",T12_Calc!$I$1:$I$505) | N38: =SUMIF(T12_Calc!$N$1:$N$505,"Nursing & care supplies",T12_Calc!$J$1:$J$505) | O38: =SUMIF(T12_Calc!$N$1:$N$505,"Nursing & care supplies",T12_Calc!$K$1:$K$505) | P38: =SUMIF(T12_Calc!$N$1:$N$505,"Nursing & care supplies",T12_Calc!$L$1:$L$505) | Q38: =SUMIF(T12_Calc!$N$1:$N$505,"Nursing & care supplies",T12_Calc!$M$1:$M$505) | R38: =SUM(F38:Q38)
A39: Non-Labor | B39: Recreation & activity suppl. | C39: - | E39: Recreation Supplies | F39: =SUMIF(T12_Calc!$N$1:$N$505,"Recreation & activity suppl.",T12_Calc!$B$1:$B$505) | G39: =SUMIF(T12_Calc!$N$1:$N$505,"Recreation & activity suppl.",T12_Calc!$C$1:$C$505) | H39: =SUMIF(T12_Calc!$N$1:$N$505,"Recreation & activity suppl.",T12_Calc!$D$1:$D$505) | I39: =SUMIF(T12_Calc!$N$1:$N$505,"Recreation & activity suppl.",T12_Calc!$E$1:$E$505) | J39: =SUMIF(T12_Calc!$N$1:$N$505,"Recreation & activity suppl.",T12_Calc!$F$1:$F$505) | K39: =SUMIF(T12_Calc!$N$1:$N$505,"Recreation & activity suppl.",T12_Calc!$G$1:$G$505) | L39: =SUMIF(T12_Calc!$N$1:$N$505,"Recreation & activity suppl.",T12_Calc!$H$1:$H$505) | M39: =SUMIF(T12_Calc!$N$1:$N$505,"Recreation & activity suppl.",T12_Calc!$I$1:$I$505) | N39: =SUMIF(T12_Calc!$N$1:$N$505,"Recreation & activity suppl.",T12_Calc!$J$1:$J$505) | O39: =SUMIF(T12_Calc!$N$1:$N$505,"Recreation & activity suppl.",T12_Calc!$K$1:$K$505) | P39: =SUMIF(T12_Calc!$N$1:$N$505,"Recreation & activity suppl.",T12_Calc!$L$1:$L$505) | Q39: =SUMIF(T12_Calc!$N$1:$N$505,"Recreation & activity suppl.",T12_Calc!$M$1:$M$505) | R39: =SUM(F39:Q39)
A40: Non-Labor | B40: R&M fixed | C40: - | E40: R & M-Fixed | R&M-Fixed | Maintenance Supplies | F40: =SUMIF(T12_Calc!$N$1:$N$505,"R&M fixed",T12_Calc!$B$1:$B$505) | G40: =SUMIF(T12_Calc!$N$1:$N$505,"R&M fixed",T12_Calc!$C$1:$C$505) | H40: =SUMIF(T12_Calc!$N$1:$N$505,"R&M fixed",T12_Calc!$D$1:$D$505) | I40: =SUMIF(T12_Calc!$N$1:$N$505,"R&M fixed",T12_Calc!$E$1:$E$505) | J40: =SUMIF(T12_Calc!$N$1:$N$505,"R&M fixed",T12_Calc!$F$1:$F$505) | K40: =SUMIF(T12_Calc!$N$1:$N$505,"R&M fixed",T12_Calc!$G$1:$G$505) | L40: =SUMIF(T12_Calc!$N$1:$N$505,"R&M fixed",T12_Calc!$H$1:$H$505) | M40: =SUMIF(T12_Calc!$N$1:$N$505,"R&M fixed",T12_Calc!$I$1:$I$505) | N40: =SUMIF(T12_Calc!$N$1:$N$505,"R&M fixed",T12_Calc!$J$1:$J$505) | O40: =SUMIF(T12_Calc!$N$1:$N$505,"R&M fixed",T12_Calc!$K$1:$K$505) | P40: =SUMIF(T12_Calc!$N$1:$N$505,"R&M fixed",T12_Calc!$L$1:$L$505) | Q40: =SUMIF(T12_Calc!$N$1:$N$505,"R&M fixed",T12_Calc!$M$1:$M$505) | R40: =SUM(F40:Q40)
A41: Non-Labor | B41: R&M variable | C41: - | E41: R & M-Variable | R&M-Variable | F41: =SUMIF(T12_Calc!$N$1:$N$505,"R&M variable",T12_Calc!$B$1:$B$505) | G41: =SUMIF(T12_Calc!$N$1:$N$505,"R&M variable",T12_Calc!$C$1:$C$505) | H41: =SUMIF(T12_Calc!$N$1:$N$505,"R&M variable",T12_Calc!$D$1:$D$505) | I41: =SUMIF(T12_Calc!$N$1:$N$505,"R&M variable",T12_Calc!$E$1:$E$505) | J41: =SUMIF(T12_Calc!$N$1:$N$505,"R&M variable",T12_Calc!$F$1:$F$505) | K41: =SUMIF(T12_Calc!$N$1:$N$505,"R&M variable",T12_Calc!$G$1:$G$505) | L41: =SUMIF(T12_Calc!$N$1:$N$505,"R&M variable",T12_Calc!$H$1:$H$505) | M41: =SUMIF(T12_Calc!$N$1:$N$505,"R&M variable",T12_Calc!$I$1:$I$505) | N41: =SUMIF(T12_Calc!$N$1:$N$505,"R&M variable",T12_Calc!$J$1:$J$505) | O41: =SUMIF(T12_Calc!$N$1:$N$505,"R&M variable",T12_Calc!$K$1:$K$505) | P41: =SUMIF(T12_Calc!$N$1:$N$505,"R&M variable",T12_Calc!$L$1:$L$505) | Q41: =SUMIF(T12_Calc!$N$1:$N$505,"R&M variable",T12_Calc!$M$1:$M$505) | R41: =SUM(F41:Q41)
A42: Non-Labor | B42: HK & laundry supplies | C42: - | E42: Housekeeping Supplies | Laundry Supplies | F42: =SUMIF(T12_Calc!$N$1:$N$505,"HK & laundry supplies",T12_Calc!$B$1:$B$505) | G42: =SUMIF(T12_Calc!$N$1:$N$505,"HK & laundry supplies",T12_Calc!$C$1:$C$505) | H42: =SUMIF(T12_Calc!$N$1:$N$505,"HK & laundry supplies",T12_Calc!$D$1:$D$505) | I42: =SUMIF(T12_Calc!$N$1:$N$505,"HK & laundry supplies",T12_Calc!$E$1:$E$505) | J42: =SUMIF(T12_Calc!$N$1:$N$505,"HK & laundry supplies",T12_Calc!$F$1:$F$505) | K42: =SUMIF(T12_Calc!$N$1:$N$505,"HK & laundry supplies",T12_Calc!$G$1:$G$505) | L42: =SUMIF(T12_Calc!$N$1:$N$505,"HK & laundry supplies",T12_Calc!$H$1:$H$505) | M42: =SUMIF(T12_Calc!$N$1:$N$505,"HK & laundry supplies",T12_Calc!$I$1:$I$505) | N42: =SUMIF(T12_Calc!$N$1:$N$505,"HK & laundry supplies",T12_Calc!$J$1:$J$505) | O42: =SUMIF(T12_Calc!$N$1:$N$505,"HK & laundry supplies",T12_Calc!$K$1:$K$505) | P42: =SUMIF(T12_Calc!$N$1:$N$505,"HK & laundry supplies",T12_Calc!$L$1:$L$505) | Q42: =SUMIF(T12_Calc!$N$1:$N$505,"HK & laundry supplies",T12_Calc!$M$1:$M$505) | R42: =SUM(F42:Q42)
A43: Non-Labor | B43: Sales, adv. & marketing | C43: - | E43: Advertising and Promotion | Advertising & Promotion | F43: =SUMIF(T12_Calc!$N$1:$N$505,"Sales, adv. & marketing",T12_Calc!$B$1:$B$505) | G43: =SUMIF(T12_Calc!$N$1:$N$505,"Sales, adv. & marketing",T12_Calc!$C$1:$C$505) | H43: =SUMIF(T12_Calc!$N$1:$N$505,"Sales, adv. & marketing",T12_Calc!$D$1:$D$505) | I43: =SUMIF(T12_Calc!$N$1:$N$505,"Sales, adv. & marketing",T12_Calc!$E$1:$E$505) | J43: =SUMIF(T12_Calc!$N$1:$N$505,"Sales, adv. & marketing",T12_Calc!$F$1:$F$505) | K43: =SUMIF(T12_Calc!$N$1:$N$505,"Sales, adv. & marketing",T12_Calc!$G$1:$G$505) | L43: =SUMIF(T12_Calc!$N$1:$N$505,"Sales, adv. & marketing",T12_Calc!$H$1:$H$505) | M43: =SUMIF(T12_Calc!$N$1:$N$505,"Sales, adv. & marketing",T12_Calc!$I$1:$I$505) | N43: =SUMIF(T12_Calc!$N$1:$N$505,"Sales, adv. & marketing",T12_Calc!$J$1:$J$505) | O43: =SUMIF(T12_Calc!$N$1:$N$505,"Sales, adv. & marketing",T12_Calc!$K$1:$K$505) | P43: =SUMIF(T12_Calc!$N$1:$N$505,"Sales, adv. & marketing",T12_Calc!$L$1:$L$505) | Q43: =SUMIF(T12_Calc!$N$1:$N$505,"Sales, adv. & marketing",T12_Calc!$M$1:$M$505) | R43: =SUM(F43:Q43)
A44: Non-Labor | B44: Referral fees | C44: - | D44: Normalize at stabilization | E44: Referral Fees | F44: =SUMIF(T12_Calc!$N$1:$N$505,"Referral fees",T12_Calc!$B$1:$B$505) | G44: =SUMIF(T12_Calc!$N$1:$N$505,"Referral fees",T12_Calc!$C$1:$C$505) | H44: =SUMIF(T12_Calc!$N$1:$N$505,"Referral fees",T12_Calc!$D$1:$D$505) | I44: =SUMIF(T12_Calc!$N$1:$N$505,"Referral fees",T12_Calc!$E$1:$E$505) | J44: =SUMIF(T12_Calc!$N$1:$N$505,"Referral fees",T12_Calc!$F$1:$F$505) | K44: =SUMIF(T12_Calc!$N$1:$N$505,"Referral fees",T12_Calc!$G$1:$G$505) | L44: =SUMIF(T12_Calc!$N$1:$N$505,"Referral fees",T12_Calc!$H$1:$H$505) | M44: =SUMIF(T12_Calc!$N$1:$N$505,"Referral fees",T12_Calc!$I$1:$I$505) | N44: =SUMIF(T12_Calc!$N$1:$N$505,"Referral fees",T12_Calc!$J$1:$J$505) | O44: =SUMIF(T12_Calc!$N$1:$N$505,"Referral fees",T12_Calc!$K$1:$K$505) | P44: =SUMIF(T12_Calc!$N$1:$N$505,"Referral fees",T12_Calc!$L$1:$L$505) | Q44: =SUMIF(T12_Calc!$N$1:$N$505,"Referral fees",T12_Calc!$M$1:$M$505) | R44: =SUM(F44:Q44)
A45: Non-Labor | B45: Utilities | C45: - | E45: Utilities | F45: =SUMIF(T12_Calc!$N$1:$N$505,"Utilities",T12_Calc!$B$1:$B$505) | G45: =SUMIF(T12_Calc!$N$1:$N$505,"Utilities",T12_Calc!$C$1:$C$505) | H45: =SUMIF(T12_Calc!$N$1:$N$505,"Utilities",T12_Calc!$D$1:$D$505) | I45: =SUMIF(T12_Calc!$N$1:$N$505,"Utilities",T12_Calc!$E$1:$E$505) | J45: =SUMIF(T12_Calc!$N$1:$N$505,"Utilities",T12_Calc!$F$1:$F$505) | K45: =SUMIF(T12_Calc!$N$1:$N$505,"Utilities",T12_Calc!$G$1:$G$505) | L45: =SUMIF(T12_Calc!$N$1:$N$505,"Utilities",T12_Calc!$H$1:$H$505) | M45: =SUMIF(T12_Calc!$N$1:$N$505,"Utilities",T12_Calc!$I$1:$I$505) | N45: =SUMIF(T12_Calc!$N$1:$N$505,"Utilities",T12_Calc!$J$1:$J$505) | O45: =SUMIF(T12_Calc!$N$1:$N$505,"Utilities",T12_Calc!$K$1:$K$505) | P45: =SUMIF(T12_Calc!$N$1:$N$505,"Utilities",T12_Calc!$L$1:$L$505) | Q45: =SUMIF(T12_Calc!$N$1:$N$505,"Utilities",T12_Calc!$M$1:$M$505) | R45: =SUM(F45:Q45)
A46: Non-Labor | B46: Telephone / IT | C46: - | E46: Telephone/IT | Telephone Reimbursement | F46: =SUMIF(T12_Calc!$N$1:$N$505,"Telephone / IT",T12_Calc!$B$1:$B$505) | G46: =SUMIF(T12_Calc!$N$1:$N$505,"Telephone / IT",T12_Calc!$C$1:$C$505) | H46: =SUMIF(T12_Calc!$N$1:$N$505,"Telephone / IT",T12_Calc!$D$1:$D$505) | I46: =SUMIF(T12_Calc!$N$1:$N$505,"Telephone / IT",T12_Calc!$E$1:$E$505) | J46: =SUMIF(T12_Calc!$N$1:$N$505,"Telephone / IT",T12_Calc!$F$1:$F$505) | K46: =SUMIF(T12_Calc!$N$1:$N$505,"Telephone / IT",T12_Calc!$G$1:$G$505) | L46: =SUMIF(T12_Calc!$N$1:$N$505,"Telephone / IT",T12_Calc!$H$1:$H$505) | M46: =SUMIF(T12_Calc!$N$1:$N$505,"Telephone / IT",T12_Calc!$I$1:$I$505) | N46: =SUMIF(T12_Calc!$N$1:$N$505,"Telephone / IT",T12_Calc!$J$1:$J$505) | O46: =SUMIF(T12_Calc!$N$1:$N$505,"Telephone / IT",T12_Calc!$K$1:$K$505) | P46: =SUMIF(T12_Calc!$N$1:$N$505,"Telephone / IT",T12_Calc!$L$1:$L$505) | Q46: =SUMIF(T12_Calc!$N$1:$N$505,"Telephone / IT",T12_Calc!$M$1:$M$505) | R46: =SUM(F46:Q46)
A47: Non-Labor | B47: P&C insurance (bundled) | C47: - | E47: Bundled Insurance Poilicies | Bundled Insurance Policies | EPLI Insurance | F47: =SUMIF(T12_Calc!$N$1:$N$505,"P&C insurance (bundled)",T12_Calc!$B$1:$B$505) | G47: =SUMIF(T12_Calc!$N$1:$N$505,"P&C insurance (bundled)",T12_Calc!$C$1:$C$505) | H47: =SUMIF(T12_Calc!$N$1:$N$505,"P&C insurance (bundled)",T12_Calc!$D$1:$D$505) | I47: =SUMIF(T12_Calc!$N$1:$N$505,"P&C insurance (bundled)",T12_Calc!$E$1:$E$505) | J47: =SUMIF(T12_Calc!$N$1:$N$505,"P&C insurance (bundled)",T12_Calc!$F$1:$F$505) | K47: =SUMIF(T12_Calc!$N$1:$N$505,"P&C insurance (bundled)",T12_Calc!$G$1:$G$505) | L47: =SUMIF(T12_Calc!$N$1:$N$505,"P&C insurance (bundled)",T12_Calc!$H$1:$H$505) | M47: =SUMIF(T12_Calc!$N$1:$N$505,"P&C insurance (bundled)",T12_Calc!$I$1:$I$505) | N47: =SUMIF(T12_Calc!$N$1:$N$505,"P&C insurance (bundled)",T12_Calc!$J$1:$J$505) | O47: =SUMIF(T12_Calc!$N$1:$N$505,"P&C insurance (bundled)",T12_Calc!$K$1:$K$505) | P47: =SUMIF(T12_Calc!$N$1:$N$505,"P&C insurance (bundled)",T12_Calc!$L$1:$L$505) | Q47: =SUMIF(T12_Calc!$N$1:$N$505,"P&C insurance (bundled)",T12_Calc!$M$1:$M$505) | R47: =SUM(F47:Q47)
A48: Non-Labor | B48: Auto insurance | C48: - | E48: Auto Insurance | F48: =SUMIF(T12_Calc!$N$1:$N$505,"Auto insurance",T12_Calc!$B$1:$B$505) | G48: =SUMIF(T12_Calc!$N$1:$N$505,"Auto insurance",T12_Calc!$C$1:$C$505) | H48: =SUMIF(T12_Calc!$N$1:$N$505,"Auto insurance",T12_Calc!$D$1:$D$505) | I48: =SUMIF(T12_Calc!$N$1:$N$505,"Auto insurance",T12_Calc!$E$1:$E$505) | J48: =SUMIF(T12_Calc!$N$1:$N$505,"Auto insurance",T12_Calc!$F$1:$F$505) | K48: =SUMIF(T12_Calc!$N$1:$N$505,"Auto insurance",T12_Calc!$G$1:$G$505) | L48: =SUMIF(T12_Calc!$N$1:$N$505,"Auto insurance",T12_Calc!$H$1:$H$505) | M48: =SUMIF(T12_Calc!$N$1:$N$505,"Auto insurance",T12_Calc!$I$1:$I$505) | N48: =SUMIF(T12_Calc!$N$1:$N$505,"Auto insurance",T12_Calc!$J$1:$J$505) | O48: =SUMIF(T12_Calc!$N$1:$N$505,"Auto insurance",T12_Calc!$K$1:$K$505) | P48: =SUMIF(T12_Calc!$N$1:$N$505,"Auto insurance",T12_Calc!$L$1:$L$505) | Q48: =SUMIF(T12_Calc!$N$1:$N$505,"Auto insurance",T12_Calc!$M$1:$M$505) | R48: =SUM(F48:Q48)
A49: Non-Labor | B49: Fire / security monitoring | C49: - | E49: Fire/Security Monitoring | F49: =SUMIF(T12_Calc!$N$1:$N$505,"Fire / security monitoring",T12_Calc!$B$1:$B$505) | G49: =SUMIF(T12_Calc!$N$1:$N$505,"Fire / security monitoring",T12_Calc!$C$1:$C$505) | H49: =SUMIF(T12_Calc!$N$1:$N$505,"Fire / security monitoring",T12_Calc!$D$1:$D$505) | I49: =SUMIF(T12_Calc!$N$1:$N$505,"Fire / security monitoring",T12_Calc!$E$1:$E$505) | J49: =SUMIF(T12_Calc!$N$1:$N$505,"Fire / security monitoring",T12_Calc!$F$1:$F$505) | K49: =SUMIF(T12_Calc!$N$1:$N$505,"Fire / security monitoring",T12_Calc!$G$1:$G$505) | L49: =SUMIF(T12_Calc!$N$1:$N$505,"Fire / security monitoring",T12_Calc!$H$1:$H$505) | M49: =SUMIF(T12_Calc!$N$1:$N$505,"Fire / security monitoring",T12_Calc!$I$1:$I$505) | N49: =SUMIF(T12_Calc!$N$1:$N$505,"Fire / security monitoring",T12_Calc!$J$1:$J$505) | O49: =SUMIF(T12_Calc!$N$1:$N$505,"Fire / security monitoring",T12_Calc!$K$1:$K$505) | P49: =SUMIF(T12_Calc!$N$1:$N$505,"Fire / security monitoring",T12_Calc!$L$1:$L$505) | Q49: =SUMIF(T12_Calc!$N$1:$N$505,"Fire / security monitoring",T12_Calc!$M$1:$M$505) | R49: =SUM(F49:Q49)
A50: Non-Labor | B50: Pest elimination | C50: - | E50: Pest Elimination | F50: =SUMIF(T12_Calc!$N$1:$N$505,"Pest elimination",T12_Calc!$B$1:$B$505) | G50: =SUMIF(T12_Calc!$N$1:$N$505,"Pest elimination",T12_Calc!$C$1:$C$505) | H50: =SUMIF(T12_Calc!$N$1:$N$505,"Pest elimination",T12_Calc!$D$1:$D$505) | I50: =SUMIF(T12_Calc!$N$1:$N$505,"Pest elimination",T12_Calc!$E$1:$E$505) | J50: =SUMIF(T12_Calc!$N$1:$N$505,"Pest elimination",T12_Calc!$F$1:$F$505) | K50: =SUMIF(T12_Calc!$N$1:$N$505,"Pest elimination",T12_Calc!$G$1:$G$505) | L50: =SUMIF(T12_Calc!$N$1:$N$505,"Pest elimination",T12_Calc!$H$1:$H$505) | M50: =SUMIF(T12_Calc!$N$1:$N$505,"Pest elimination",T12_Calc!$I$1:$I$505) | N50: =SUMIF(T12_Calc!$N$1:$N$505,"Pest elimination",T12_Calc!$J$1:$J$505) | O50: =SUMIF(T12_Calc!$N$1:$N$505,"Pest elimination",T12_Calc!$K$1:$K$505) | P50: =SUMIF(T12_Calc!$N$1:$N$505,"Pest elimination",T12_Calc!$L$1:$L$505) | Q50: =SUMIF(T12_Calc!$N$1:$N$505,"Pest elimination",T12_Calc!$M$1:$M$505) | R50: =SUM(F50:Q50)
A51: Non-Labor | B51: Real estate taxes | C51: - | D51: Verify assessed value | E51: Property Tax Expense | Real Estate Taxes | F51: =SUMIF(T12_Calc!$N$1:$N$505,"Real estate taxes",T12_Calc!$B$1:$B$505) | G51: =SUMIF(T12_Calc!$N$1:$N$505,"Real estate taxes",T12_Calc!$C$1:$C$505) | H51: =SUMIF(T12_Calc!$N$1:$N$505,"Real estate taxes",T12_Calc!$D$1:$D$505) | I51: =SUMIF(T12_Calc!$N$1:$N$505,"Real estate taxes",T12_Calc!$E$1:$E$505) | J51: =SUMIF(T12_Calc!$N$1:$N$505,"Real estate taxes",T12_Calc!$F$1:$F$505) | K51: =SUMIF(T12_Calc!$N$1:$N$505,"Real estate taxes",T12_Calc!$G$1:$G$505) | L51: =SUMIF(T12_Calc!$N$1:$N$505,"Real estate taxes",T12_Calc!$H$1:$H$505) | M51: =SUMIF(T12_Calc!$N$1:$N$505,"Real estate taxes",T12_Calc!$I$1:$I$505) | N51: =SUMIF(T12_Calc!$N$1:$N$505,"Real estate taxes",T12_Calc!$J$1:$J$505) | O51: =SUMIF(T12_Calc!$N$1:$N$505,"Real estate taxes",T12_Calc!$K$1:$K$505) | P51: =SUMIF(T12_Calc!$N$1:$N$505,"Real estate taxes",T12_Calc!$L$1:$L$505) | Q51: =SUMIF(T12_Calc!$N$1:$N$505,"Real estate taxes",T12_Calc!$M$1:$M$505) | R51: =SUM(F51:Q51)
A52: Non-Labor | B52: Personal property taxes | C52: - | E52: Personal Property Tax Expense | Personal Property Taxes | F52: =SUMIF(T12_Calc!$N$1:$N$505,"Personal property taxes",T12_Calc!$B$1:$B$505) | G52: =SUMIF(T12_Calc!$N$1:$N$505,"Personal property taxes",T12_Calc!$C$1:$C$505) | H52: =SUMIF(T12_Calc!$N$1:$N$505,"Personal property taxes",T12_Calc!$D$1:$D$505) | I52: =SUMIF(T12_Calc!$N$1:$N$505,"Personal property taxes",T12_Calc!$E$1:$E$505) | J52: =SUMIF(T12_Calc!$N$1:$N$505,"Personal property taxes",T12_Calc!$F$1:$F$505) | K52: =SUMIF(T12_Calc!$N$1:$N$505,"Personal property taxes",T12_Calc!$G$1:$G$505) | L52: =SUMIF(T12_Calc!$N$1:$N$505,"Personal property taxes",T12_Calc!$H$1:$H$505) | M52: =SUMIF(T12_Calc!$N$1:$N$505,"Personal property taxes",T12_Calc!$I$1:$I$505) | N52: =SUMIF(T12_Calc!$N$1:$N$505,"Personal property taxes",T12_Calc!$J$1:$J$505) | O52: =SUMIF(T12_Calc!$N$1:$N$505,"Personal property taxes",T12_Calc!$K$1:$K$505) | P52: =SUMIF(T12_Calc!$N$1:$N$505,"Personal property taxes",T12_Calc!$L$1:$L$505) | Q52: =SUMIF(T12_Calc!$N$1:$N$505,"Personal property taxes",T12_Calc!$M$1:$M$505) | R52: =SUM(F52:Q52)
A53: Non-Labor | B53: Legal expenses | C53: - | E53: Legal Expense | Legal Expenses | F53: =SUMIF(T12_Calc!$N$1:$N$505,"Legal expenses",T12_Calc!$B$1:$B$505) | G53: =SUMIF(T12_Calc!$N$1:$N$505,"Legal expenses",T12_Calc!$C$1:$C$505) | H53: =SUMIF(T12_Calc!$N$1:$N$505,"Legal expenses",T12_Calc!$D$1:$D$505) | I53: =SUMIF(T12_Calc!$N$1:$N$505,"Legal expenses",T12_Calc!$E$1:$E$505) | J53: =SUMIF(T12_Calc!$N$1:$N$505,"Legal expenses",T12_Calc!$F$1:$F$505) | K53: =SUMIF(T12_Calc!$N$1:$N$505,"Legal expenses",T12_Calc!$G$1:$G$505) | L53: =SUMIF(T12_Calc!$N$1:$N$505,"Legal expenses",T12_Calc!$H$1:$H$505) | M53: =SUMIF(T12_Calc!$N$1:$N$505,"Legal expenses",T12_Calc!$I$1:$I$505) | N53: =SUMIF(T12_Calc!$N$1:$N$505,"Legal expenses",T12_Calc!$J$1:$J$505) | O53: =SUMIF(T12_Calc!$N$1:$N$505,"Legal expenses",T12_Calc!$K$1:$K$505) | P53: =SUMIF(T12_Calc!$N$1:$N$505,"Legal expenses",T12_Calc!$L$1:$L$505) | Q53: =SUMIF(T12_Calc!$N$1:$N$505,"Legal expenses",T12_Calc!$M$1:$M$505) | R53: =SUM(F53:Q53)
A54: Non-Labor | B54: Professional services | C54: - | E54: Professional Services | F54: =SUMIF(T12_Calc!$N$1:$N$505,"Professional services",T12_Calc!$B$1:$B$505) | G54: =SUMIF(T12_Calc!$N$1:$N$505,"Professional services",T12_Calc!$C$1:$C$505) | H54: =SUMIF(T12_Calc!$N$1:$N$505,"Professional services",T12_Calc!$D$1:$D$505) | I54: =SUMIF(T12_Calc!$N$1:$N$505,"Professional services",T12_Calc!$E$1:$E$505) | J54: =SUMIF(T12_Calc!$N$1:$N$505,"Professional services",T12_Calc!$F$1:$F$505) | K54: =SUMIF(T12_Calc!$N$1:$N$505,"Professional services",T12_Calc!$G$1:$G$505) | L54: =SUMIF(T12_Calc!$N$1:$N$505,"Professional services",T12_Calc!$H$1:$H$505) | M54: =SUMIF(T12_Calc!$N$1:$N$505,"Professional services",T12_Calc!$I$1:$I$505) | N54: =SUMIF(T12_Calc!$N$1:$N$505,"Professional services",T12_Calc!$J$1:$J$505) | O54: =SUMIF(T12_Calc!$N$1:$N$505,"Professional services",T12_Calc!$K$1:$K$505) | P54: =SUMIF(T12_Calc!$N$1:$N$505,"Professional services",T12_Calc!$L$1:$L$505) | Q54: =SUMIF(T12_Calc!$N$1:$N$505,"Professional services",T12_Calc!$M$1:$M$505) | R54: =SUM(F54:Q54)
A55: Non-Labor | B55: Bad debt expense | C55: - | D55: Normalize to 1-2% | E55: Bad Debt Expense | F55: =SUMIF(T12_Calc!$N$1:$N$505,"Bad debt expense",T12_Calc!$B$1:$B$505) | G55: =SUMIF(T12_Calc!$N$1:$N$505,"Bad debt expense",T12_Calc!$C$1:$C$505) | H55: =SUMIF(T12_Calc!$N$1:$N$505,"Bad debt expense",T12_Calc!$D$1:$D$505) | I55: =SUMIF(T12_Calc!$N$1:$N$505,"Bad debt expense",T12_Calc!$E$1:$E$505) | J55: =SUMIF(T12_Calc!$N$1:$N$505,"Bad debt expense",T12_Calc!$F$1:$F$505) | K55: =SUMIF(T12_Calc!$N$1:$N$505,"Bad debt expense",T12_Calc!$G$1:$G$505) | L55: =SUMIF(T12_Calc!$N$1:$N$505,"Bad debt expense",T12_Calc!$H$1:$H$505) | M55: =SUMIF(T12_Calc!$N$1:$N$505,"Bad debt expense",T12_Calc!$I$1:$I$505) | N55: =SUMIF(T12_Calc!$N$1:$N$505,"Bad debt expense",T12_Calc!$J$1:$J$505) | O55: =SUMIF(T12_Calc!$N$1:$N$505,"Bad debt expense",T12_Calc!$K$1:$K$505) | P55: =SUMIF(T12_Calc!$N$1:$N$505,"Bad debt expense",T12_Calc!$L$1:$L$505) | Q55: =SUMIF(T12_Calc!$N$1:$N$505,"Bad debt expense",T12_Calc!$M$1:$M$505) | R55: =SUM(F55:Q55)
A56: Non-Labor | B56: Permits, licenses & dues | C56: - | E56: Permits and Licenses | Dues and Subscriptions | Association Dues | F56: =SUMIF(T12_Calc!$N$1:$N$505,"Permits, licenses & dues",T12_Calc!$B$1:$B$505) | G56: =SUMIF(T12_Calc!$N$1:$N$505,"Permits, licenses & dues",T12_Calc!$C$1:$C$505) | H56: =SUMIF(T12_Calc!$N$1:$N$505,"Permits, licenses & dues",T12_Calc!$D$1:$D$505) | I56: =SUMIF(T12_Calc!$N$1:$N$505,"Permits, licenses & dues",T12_Calc!$E$1:$E$505) | J56: =SUMIF(T12_Calc!$N$1:$N$505,"Permits, licenses & dues",T12_Calc!$F$1:$F$505) | K56: =SUMIF(T12_Calc!$N$1:$N$505,"Permits, licenses & dues",T12_Calc!$G$1:$G$505) | L56: =SUMIF(T12_Calc!$N$1:$N$505,"Permits, licenses & dues",T12_Calc!$H$1:$H$505) | M56: =SUMIF(T12_Calc!$N$1:$N$505,"Permits, licenses & dues",T12_Calc!$I$1:$I$505) | N56: =SUMIF(T12_Calc!$N$1:$N$505,"Permits, licenses & dues",T12_Calc!$J$1:$J$505) | O56: =SUMIF(T12_Calc!$N$1:$N$505,"Permits, licenses & dues",T12_Calc!$K$1:$K$505) | P56: =SUMIF(T12_Calc!$N$1:$N$505,"Permits, licenses & dues",T12_Calc!$L$1:$L$505) | Q56: =SUMIF(T12_Calc!$N$1:$N$505,"Permits, licenses & dues",T12_Calc!$M$1:$M$505) | R56: =SUM(F56:Q56)
A57: Non-Labor | B57: Office, admin & G&A | C57: - | E57: Payroll Admin Fee | Postage | Beautician Expense | Copier/Equipment Lease | Training/Continuing Education | Travel | Gas/Mileage | Conference Attendance | Credit Card Processing Fees | Office Supplies | Uniforms and Linen | Printing Expense | Bank Charges/Penalties | Pre-Employment Expense | F57: =SUMIF(T12_Calc!$N$1:$N$505,"Office, admin & G&A",T12_Calc!$B$1:$B$505) | G57: =SUMIF(T12_Calc!$N$1:$N$505,"Office, admin & G&A",T12_Calc!$C$1:$C$505) | H57: =SUMIF(T12_Calc!$N$1:$N$505,"Office, admin & G&A",T12_Calc!$D$1:$D$505) | I57: =SUMIF(T12_Calc!$N$1:$N$505,"Office, admin & G&A",T12_Calc!$E$1:$E$505) | J57: =SUMIF(T12_Calc!$N$1:$N$505,"Office, admin & G&A",T12_Calc!$F$1:$F$505) | K57: =SUMIF(T12_Calc!$N$1:$N$505,"Office, admin & G&A",T12_Calc!$G$1:$G$505) | L57: =SUMIF(T12_Calc!$N$1:$N$505,"Office, admin & G&A",T12_Calc!$H$1:$H$505) | M57: =SUMIF(T12_Calc!$N$1:$N$505,"Office, admin & G&A",T12_Calc!$I$1:$I$505) | N57: =SUMIF(T12_Calc!$N$1:$N$505,"Office, admin & G&A",T12_Calc!$J$1:$J$505) | O57: =SUMIF(T12_Calc!$N$1:$N$505,"Office, admin & G&A",T12_Calc!$K$1:$K$505) | P57: =SUMIF(T12_Calc!$N$1:$N$505,"Office, admin & G&A",T12_Calc!$L$1:$L$505) | Q57: =SUMIF(T12_Calc!$N$1:$N$505,"Office, admin & G&A",T12_Calc!$M$1:$M$505) | R57: =SUM(F57:Q57)
A58: Non-Labor | B58: Other / miscellaneous | C58: - | E58: Reimbursable Supplies | Building (Bird/Fish) Supplies | Evacuation Expense | Personal purchases for Residen | Resident Gifts/Benefits | F58: =SUMIF(T12_Calc!$N$1:$N$505,"Other / miscellaneous",T12_Calc!$B$1:$B$505) | G58: =SUMIF(T12_Calc!$N$1:$N$505,"Other / miscellaneous",T12_Calc!$C$1:$C$505) | H58: =SUMIF(T12_Calc!$N$1:$N$505,"Other / miscellaneous",T12_Calc!$D$1:$D$505) | I58: =SUMIF(T12_Calc!$N$1:$N$505,"Other / miscellaneous",T12_Calc!$E$1:$E$505) | J58: =SUMIF(T12_Calc!$N$1:$N$505,"Other / miscellaneous",T12_Calc!$F$1:$F$505) | K58: =SUMIF(T12_Calc!$N$1:$N$505,"Other / miscellaneous",T12_Calc!$G$1:$G$505) | L58: =SUMIF(T12_Calc!$N$1:$N$505,"Other / miscellaneous",T12_Calc!$H$1:$H$505) | M58: =SUMIF(T12_Calc!$N$1:$N$505,"Other / miscellaneous",T12_Calc!$I$1:$I$505) | N58: =SUMIF(T12_Calc!$N$1:$N$505,"Other / miscellaneous",T12_Calc!$J$1:$J$505) | O58: =SUMIF(T12_Calc!$N$1:$N$505,"Other / miscellaneous",T12_Calc!$K$1:$K$505) | P58: =SUMIF(T12_Calc!$N$1:$N$505,"Other / miscellaneous",T12_Calc!$L$1:$L$505) | Q58: =SUMIF(T12_Calc!$N$1:$N$505,"Other / miscellaneous",T12_Calc!$M$1:$M$505) | R58: =SUM(F58:Q58)
A59: Non-Labor | B59: Management fee | C59: - | D59: Enter manually if needed | E59: Management Fees | Management Fee | F59: =SUMIF(T12_Calc!$N$1:$N$505,"Management fee",T12_Calc!$B$1:$B$505) | G59: =SUMIF(T12_Calc!$N$1:$N$505,"Management fee",T12_Calc!$C$1:$C$505) | H59: =SUMIF(T12_Calc!$N$1:$N$505,"Management fee",T12_Calc!$D$1:$D$505) | I59: =SUMIF(T12_Calc!$N$1:$N$505,"Management fee",T12_Calc!$E$1:$E$505) | J59: =SUMIF(T12_Calc!$N$1:$N$505,"Management fee",T12_Calc!$F$1:$F$505) | K59: =SUMIF(T12_Calc!$N$1:$N$505,"Management fee",T12_Calc!$G$1:$G$505) | L59: =SUMIF(T12_Calc!$N$1:$N$505,"Management fee",T12_Calc!$H$1:$H$505) | M59: =SUMIF(T12_Calc!$N$1:$N$505,"Management fee",T12_Calc!$I$1:$I$505) | N59: =SUMIF(T12_Calc!$N$1:$N$505,"Management fee",T12_Calc!$J$1:$J$505) | O59: =SUMIF(T12_Calc!$N$1:$N$505,"Management fee",T12_Calc!$K$1:$K$505) | P59: =SUMIF(T12_Calc!$N$1:$N$505,"Management fee",T12_Calc!$L$1:$L$505) | Q59: =SUMIF(T12_Calc!$N$1:$N$505,"Management fee",T12_Calc!$M$1:$M$505) | R59: =SUM(F59:Q59)
A60: Revenue | B60: Gross Rent Revenue | C60: - | F60: =SUMIF(T12_Calc!$N$1:$N$505,"Gross Rent Revenue",T12_Calc!$B$1:$B$505) | G60: =SUMIF(T12_Calc!$N$1:$N$505,"Gross Rent Revenue",T12_Calc!$C$1:$C$505) | H60: =SUMIF(T12_Calc!$N$1:$N$505,"Gross Rent Revenue",T12_Calc!$D$1:$D$505) | I60: =SUMIF(T12_Calc!$N$1:$N$505,"Gross Rent Revenue",T12_Calc!$E$1:$E$505) | J60: =SUMIF(T12_Calc!$N$1:$N$505,"Gross Rent Revenue",T12_Calc!$F$1:$F$505) | K60: =SUMIF(T12_Calc!$N$1:$N$505,"Gross Rent Revenue",T12_Calc!$G$1:$G$505) | L60: =SUMIF(T12_Calc!$N$1:$N$505,"Gross Rent Revenue",T12_Calc!$H$1:$H$505) | M60: =SUMIF(T12_Calc!$N$1:$N$505,"Gross Rent Revenue",T12_Calc!$I$1:$I$505) | N60: =SUMIF(T12_Calc!$N$1:$N$505,"Gross Rent Revenue",T12_Calc!$J$1:$J$505) | O60: =SUMIF(T12_Calc!$N$1:$N$505,"Gross Rent Revenue",T12_Calc!$K$1:$K$505) | P60: =SUMIF(T12_Calc!$N$1:$N$505,"Gross Rent Revenue",T12_Calc!$L$1:$L$505) | Q60: =SUMIF(T12_Calc!$N$1:$N$505,"Gross Rent Revenue",T12_Calc!$M$1:$M$505) | R60: =SUM(F60:Q60)
A61: Revenue | B61: Physical Vacancy | C61: - | F61: =SUMIF(T12_Calc!$N$1:$N$505,"Physical Vacancy",T12_Calc!$B$1:$B$505) | G61: =SUMIF(T12_Calc!$N$1:$N$505,"Physical Vacancy",T12_Calc!$C$1:$C$505) | H61: =SUMIF(T12_Calc!$N$1:$N$505,"Physical Vacancy",T12_Calc!$D$1:$D$505) | I61: =SUMIF(T12_Calc!$N$1:$N$505,"Physical Vacancy",T12_Calc!$E$1:$E$505) | J61: =SUMIF(T12_Calc!$N$1:$N$505,"Physical Vacancy",T12_Calc!$F$1:$F$505) | K61: =SUMIF(T12_Calc!$N$1:$N$505,"Physical Vacancy",T12_Calc!$G$1:$G$505) | L61: =SUMIF(T12_Calc!$N$1:$N$505,"Physical Vacancy",T12_Calc!$H$1:$H$505) | M61: =SUMIF(T12_Calc!$N$1:$N$505,"Physical Vacancy",T12_Calc!$I$1:$I$505) | N61: =SUMIF(T12_Calc!$N$1:$N$505,"Physical Vacancy",T12_Calc!$J$1:$J$505) | O61: =SUMIF(T12_Calc!$N$1:$N$505,"Physical Vacancy",T12_Calc!$K$1:$K$505) | P61: =SUMIF(T12_Calc!$N$1:$N$505,"Physical Vacancy",T12_Calc!$L$1:$L$505) | Q61: =SUMIF(T12_Calc!$N$1:$N$505,"Physical Vacancy",T12_Calc!$M$1:$M$505) | R61: =SUM(F61:Q61)
A62: Revenue | B62: Loss to Lease | C62: - | F62: =SUMIF(T12_Calc!$N$1:$N$505,"Loss to Lease",T12_Calc!$B$1:$B$505) | G62: =SUMIF(T12_Calc!$N$1:$N$505,"Loss to Lease",T12_Calc!$C$1:$C$505) | H62: =SUMIF(T12_Calc!$N$1:$N$505,"Loss to Lease",T12_Calc!$D$1:$D$505) | I62: =SUMIF(T12_Calc!$N$1:$N$505,"Loss to Lease",T12_Calc!$E$1:$E$505) | J62: =SUMIF(T12_Calc!$N$1:$N$505,"Loss to Lease",T12_Calc!$F$1:$F$505) | K62: =SUMIF(T12_Calc!$N$1:$N$505,"Loss to Lease",T12_Calc!$G$1:$G$505) | L62: =SUMIF(T12_Calc!$N$1:$N$505,"Loss to Lease",T12_Calc!$H$1:$H$505) | M62: =SUMIF(T12_Calc!$N$1:$N$505,"Loss to Lease",T12_Calc!$I$1:$I$505) | N62: =SUMIF(T12_Calc!$N$1:$N$505,"Loss to Lease",T12_Calc!$J$1:$J$505) | O62: =SUMIF(T12_Calc!$N$1:$N$505,"Loss to Lease",T12_Calc!$K$1:$K$505) | P62: =SUMIF(T12_Calc!$N$1:$N$505,"Loss to Lease",T12_Calc!$L$1:$L$505) | Q62: =SUMIF(T12_Calc!$N$1:$N$505,"Loss to Lease",T12_Calc!$M$1:$M$505) | R62: =SUM(F62:Q62)
A63: Non-Labor | B63: Auto Expense | C63: - | E63: Auto Expenses | Auto and Mileage Expense | Bus/Shuttle Service | F63: =SUMIF(T12_Calc!$N$1:$N$505,"Auto Expense",T12_Calc!$B$1:$B$505) | G63: =SUMIF(T12_Calc!$N$1:$N$505,"Auto Expense",T12_Calc!$C$1:$C$505) | H63: =SUMIF(T12_Calc!$N$1:$N$505,"Auto Expense",T12_Calc!$D$1:$D$505) | I63: =SUMIF(T12_Calc!$N$1:$N$505,"Auto Expense",T12_Calc!$E$1:$E$505) | J63: =SUMIF(T12_Calc!$N$1:$N$505,"Auto Expense",T12_Calc!$F$1:$F$505) | K63: =SUMIF(T12_Calc!$N$1:$N$505,"Auto Expense",T12_Calc!$G$1:$G$505) | L63: =SUMIF(T12_Calc!$N$1:$N$505,"Auto Expense",T12_Calc!$H$1:$H$505) | M63: =SUMIF(T12_Calc!$N$1:$N$505,"Auto Expense",T12_Calc!$I$1:$I$505) | N63: =SUMIF(T12_Calc!$N$1:$N$505,"Auto Expense",T12_Calc!$J$1:$J$505) | O63: =SUMIF(T12_Calc!$N$1:$N$505,"Auto Expense",T12_Calc!$K$1:$K$505) | P63: =SUMIF(T12_Calc!$N$1:$N$505,"Auto Expense",T12_Calc!$L$1:$L$505) | Q63: =SUMIF(T12_Calc!$N$1:$N$505,"Auto Expense",T12_Calc!$M$1:$M$505) | R63: =SUM(F63:Q63)
A64: Non-Labor | B64: Lease / ground lease | C64: - | E64: Lease Expense | Ground Lease | Land Lease | Facility Lease | Building Lease | Rent Expense | F64: =SUMIF(T12_Calc!$N$1:$N$505,"Lease / ground lease",T12_Calc!$B$1:$B$505) | G64: =SUMIF(T12_Calc!$N$1:$N$505,"Lease / ground lease",T12_Calc!$C$1:$C$505) | H64: =SUMIF(T12_Calc!$N$1:$N$505,"Lease / ground lease",T12_Calc!$D$1:$D$505) | I64: =SUMIF(T12_Calc!$N$1:$N$505,"Lease / ground lease",T12_Calc!$E$1:$E$505) | J64: =SUMIF(T12_Calc!$N$1:$N$505,"Lease / ground lease",T12_Calc!$F$1:$F$505) | K64: =SUMIF(T12_Calc!$N$1:$N$505,"Lease / ground lease",T12_Calc!$G$1:$G$505) | L64: =SUMIF(T12_Calc!$N$1:$N$505,"Lease / ground lease",T12_Calc!$H$1:$H$505) | M64: =SUMIF(T12_Calc!$N$1:$N$505,"Lease / ground lease",T12_Calc!$I$1:$I$505) | N64: =SUMIF(T12_Calc!$N$1:$N$505,"Lease / ground lease",T12_Calc!$J$1:$J$505) | O64: =SUMIF(T12_Calc!$N$1:$N$505,"Lease / ground lease",T12_Calc!$K$1:$K$505) | P64: =SUMIF(T12_Calc!$N$1:$N$505,"Lease / ground lease",T12_Calc!$L$1:$L$505) | Q64: =SUMIF(T12_Calc!$N$1:$N$505,"Lease / ground lease",T12_Calc!$M$1:$M$505) | R64: =SUM(F64:Q64)

Sheet Rent Roll Input
A1: Rent Roll Input — flat table, one row per resident per period | AZ1: RR normalized output paste area
A2: One row per resident per period. Period Date (col S) is the filter key — enter as MM/DD/YYYY for each row. Add as many periods as needed by adding more rows. Cols N and O are auto-calculated. Select period in Rent Roll Recon tab cell B2. | AZ2: input
AZ3: visible
A4: Unit # | B4: Room # | C4: Sq Ft | D4: Care Type | E4: Status | F4: Apt Type | G4: Market Rate | H4: Actual Rate | I4: Concession $ | J4: Concession End Date | K4: Care Level | L4: Care Level $ | M4: Med Mgmt $ | N4: Pharmacy $ | O4: Other LOC $ | P4: Payer Type | Q4: Move-in Date | R4: Resident Name | S4: Period Date | T4: Total LOC $ | U4: Total Monthly Rev | V4: 2nd Person Rent $ | W4: Move-out Date | X4: Balance | Y4: Notes | Z4: Market PSF | AA4: Actual PSF | AB4: ACH | AC4: Meal Plan $ | AD4: Scooter Fee $ | AE4: Housekeeping $ | AF4: Laundry $ | AG4: Pet $ | AH4: Total Ancillary $ | AZ4: v0.2.7
A5: Unit=col A, Care Type=AL, Payer='Primary Resident'→Private Pay, AL Care Level=col I (Basic/Level 2…Level 7), Med Mgmt $=col K, Pharmacy $=col L, Concession $=col G (negative), Period Date=01/31/2026
T7: =IFERROR(L7+M7+N7+O7,0) | U7: =IFERROR(H7+IFERROR(I7,0)+T7+IFERROR(AH7,0),0) | AH7: =IFERROR(IFERROR(V7,0)+IFERROR(AC7,0)+IFERROR(AD7,0)+IFERROR(AE7,0)+IFERROR(AF7,0)+IFERROR(AG7,0),0)
T8: =IFERROR(L8+M8+N8+O8,0) | U8: =IFERROR(H8+IFERROR(I8,0)+T8+IFERROR(AH8,0),0) | AH8: =IFERROR(IFERROR(V8,0)+IFERROR(AC8,0)+IFERROR(AD8,0)+IFERROR(AE8,0)+IFERROR(AF8,0)+IFERROR(AG8,0),0)
T9: =IFERROR(L9+M9+N9+O9,0) | U9: =IFERROR(H9+IFERROR(I9,0)+T9+IFERROR(AH9,0),0) | AH9: =IFERROR(IFERROR(V9,0)+IFERROR(AC9,0)+IFERROR(AD9,0)+IFERROR(AE9,0)+IFERROR(AF9,0)+IFERROR(AG9,0),0)
T10: =IFERROR(L10+M10+N10+O10,0) | U10: =IFERROR(H10+IFERROR(I10,0)+T10+IFERROR(AH10,0),0) | AH10: =IFERROR(IFERROR(V10,0)+IFERROR(AC10,0)+IFERROR(AD10,0)+IFERROR(AE10,0)+IFERROR(AF10,0)+IFERROR(AG10,0),0)
T11: =IFERROR(L11+M11+N11+O11,0) | U11: =IFERROR(H11+IFERROR(I11,0)+T11+IFERROR(AH11,0),0) | AH11: =IFERROR(IFERROR(V11,0)+IFERROR(AC11,0)+IFERROR(AD11,0)+IFERROR(AE11,0)+IFERROR(AF11,0)+IFERROR(AG11,0),0)
T12: =IFERROR(L12+M12+N12+O12,0) | U12: =IFERROR(H12+IFERROR(I12,0)+T12+IFERROR(AH12,0),0) | AH12: =IFERROR(IFERROR(V12,0)+IFERROR(AC12,0)+IFERROR(AD12,0)+IFERROR(AE12,0)+IFERROR(AF12,0)+IFERROR(AG12,0),0)
T13: =IFERROR(L13+M13+N13+O13,0) | U13: =IFERROR(H13+IFERROR(I13,0)+T13+IFERROR(AH13,0),0) | AH13: =IFERROR(IFERROR(V13,0)+IFERROR(AC13,0)+IFERROR(AD13,0)+IFERROR(AE13,0)+IFERROR(AF13,0)+IFERROR(AG13,0),0)
T14: =IFERROR(L14+M14+N14+O14,0) | U14: =IFERROR(H14+IFERROR(I14,0)+T14+IFERROR(AH14,0),0) | AH14: =IFERROR(IFERROR(V14,0)+IFERROR(AC14,0)+IFERROR(AD14,0)+IFERROR(AE14,0)+IFERROR(AF14,0)+IFERROR(AG14,0),0)
T15: =IFERROR(L15+M15+N15+O15,0) | U15: =IFERROR(H15+IFERROR(I15,0)+T15+IFERROR(AH15,0),0) | AH15: =IFERROR(IFERROR(V15,0)+IFERROR(AC15,0)+IFERROR(AD15,0)+IFERROR(AE15,0)+IFERROR(AF15,0)+IFERROR(AG15,0),0)
T16: =IFERROR(L16+M16+N16+O16,0) | U16: =IFERROR(H16+IFERROR(I16,0)+T16+IFERROR(AH16,0),0) | AH16: =IFERROR(IFERROR(V16,0)+IFERROR(AC16,0)+IFERROR(AD16,0)+IFERROR(AE16,0)+IFERROR(AF16,0)+IFERROR(AG16,0),0)
T17: =IFERROR(L17+M17+N17+O17,0) | U17: =IFERROR(H17+IFERROR(I17,0)+T17+IFERROR(AH17,0),0) | AH17: =IFERROR(IFERROR(V17,0)+IFERROR(AC17,0)+IFERROR(AD17,0)+IFERROR(AE17,0)+IFERROR(AF17,0)+IFERROR(AG17,0),0)
T18: =IFERROR(L18+M18+N18+O18,0) | U18: =IFERROR(H18+IFERROR(I18,0)+T18+IFERROR(AH18,0),0) | AH18: =IFERROR(IFERROR(V18,0)+IFERROR(AC18,0)+IFERROR(AD18,0)+IFERROR(AE18,0)+IFERROR(AF18,0)+IFERROR(AG18,0),0)
... T606: =IFERROR(L606+M606+N606+O606,0) | U606: =IFERROR(H606+IFERROR(I606,0)+T606+IFERROR(AH606,0),0) | AH606: =IFERROR(IFERROR(V606,0)+IFERROR(AC606,0)+IFERROR(AD606,0)+IFERROR(AE606,0)+IFERROR(AF606,0)+IFERROR(AG606,0),0)

Sheet Rent Roll Recon
A1: Rent Roll Reconciliation — RR vs. T12 Gap Analysis | AZ1: RR ↔ T12 reconciliation diagnostic
A2: Select period: | B2: =IF(MAX('Rent Roll Input'!$S$7:$S$606)>0,MAX('Rent Roll Input'!$S$7:$S$606),"") | C2: ← date from Rent Roll Input col S. All tables auto-update. | AZ2: aggregator
AZ3: visible
A4: Metric | B4: IL | C4: AL | D4: MC | E4: Total | H4: Flag / Note | AZ4: v0.2.7
A6: A · UNIT COUNTS (from selected rent roll period)
A7: Total units (all statuses) | B7: =COUNTIFS('Rent Roll Input'!$S$7:$S$606,'Rent Roll Recon'!$B$2,'Rent Roll Input'!$A$7:$A$606,"<>",'Rent Roll Input'!$D$7:$D$606,"IL") | C7: =COUNTIFS('Rent Roll Input'!$S$7:$S$606,'Rent Roll Recon'!$B$2,'Rent Roll Input'!$A$7:$A$606,"<>",'Rent Roll Input'!$D$7:$D$606,"AL") | D7: =COUNTIFS('Rent Roll Input'!$S$7:$S$606,'Rent Roll Recon'!$B$2,'Rent Roll Input'!$A$7:$A$606,"<>",'Rent Roll Input'!$D$7:$D$606,"MC") | E7: =SUM(B7:D7)
A8: Occupied | B8: =COUNTIFS('Rent Roll Input'!$S$7:$S$606,'Rent Roll Recon'!$B$2,'Rent Roll Input'!$E$7:$E$606,"Occupied",'Rent Roll Input'!$D$7:$D$606,"IL") | C8: =COUNTIFS('Rent Roll Input'!$S$7:$S$606,'Rent Roll Recon'!$B$2,'Rent Roll Input'!$E$7:$E$606,"Occupied",'Rent Roll Input'!$D$7:$D$606,"AL") | D8: =COUNTIFS('Rent Roll Input'!$S$7:$S$606,'Rent Roll Recon'!$B$2,'Rent Roll Input'!$E$7:$E$606,"Occupied",'Rent Roll Input'!$D$7:$D$606,"MC") | E8: =SUM(B8:D8)
A9: Vacant | B9: =COUNTIFS('Rent Roll Input'!$S$7:$S$606,'Rent Roll Recon'!$B$2,'Rent Roll Input'!$E$7:$E$606,"Vacant",'Rent Roll Input'!$D$7:$D$606,"IL") | C9: =COUNTIFS('Rent Roll Input'!$S$7:$S$606,'Rent Roll Recon'!$B$2,'Rent Roll Input'!$E$7:$E$606,"Vacant",'Rent Roll Input'!$D$7:$D$606,"AL") | D9: =COUNTIFS('Rent Roll Input'!$S$7:$S$606,'Rent Roll Recon'!$B$2,'Rent Roll Input'!$E$7:$E$606,"Vacant",'Rent Roll Input'!$D$7:$D$606,"MC") | E9: =SUM(B9:D9)
A10: On notice | B10: =COUNTIFS('Rent Roll Input'!$S$7:$S$606,'Rent Roll Recon'!$B$2,'Rent Roll Input'!$E$7:$E$606,"Notice",'Rent Roll Input'!$D$7:$D$606,"IL") | C10: =COUNTIFS('Rent Roll Input'!$S$7:$S$606,'Rent Roll Recon'!$B$2,'Rent Roll Input'!$E$7:$E$606,"Notice",'Rent Roll Input'!$D$7:$D$606,"AL") | D10: =COUNTIFS('Rent Roll Input'!$S$7:$S$606,'Rent Roll Recon'!$B$2,'Rent Roll Input'!$E$7:$E$606,"Notice",'Rent Roll Input'!$D$7:$D$606,"MC") | E10: =SUM(B10:D10)
A11: Eviction / non-paying | B11: =COUNTIFS('Rent Roll Input'!$S$7:$S$606,'Rent Roll Recon'!$B$2,'Rent Roll Input'!$E$7:$E$606,"Eviction",'Rent Roll Input'!$D$7:$D$606,"IL") | C11: =COUNTIFS('Rent Roll Input'!$S$7:$S$606,'Rent Roll Recon'!$B$2,'Rent Roll Input'!$E$7:$E$606,"Eviction",'Rent Roll Input'!$D$7:$D$606,"AL") | D11: =COUNTIFS('Rent Roll Input'!$S$7:$S$606,'Rent Roll Recon'!$B$2,'Rent Roll Input'!$E$7:$E$606,"Eviction",'Rent Roll Input'!$D$7:$D$606,"MC") | E11: =SUM(B11:D11) | H11: ⚠ Economic vacancy — exclude from stabilized occupancy
A12: Physical occupancy % | B12: =IFERROR(B8/B7,"-") | C12: =IFERROR(C8/C7,"-") | D12: =IFERROR(D8/D7,"-") | E12: =IFERROR(E8/E7,"-")
A13: Economic occupancy % (excl. evictions) | B13: =IFERROR((B8-B11)/B7,"-") | C13: =IFERROR((C8-C11)/C7,"-") | D13: =IFERROR((D8-D11)/D7,"-") | E13: =IFERROR((E8-E11)/E7,"-") | H13: Gap vs. physical occ = true economic vacancy
A15: B · REVENUE RECONCILIATION (RR contracted vs. T12 collected)
A16: RR Gross Potential Rent / mo (Market × all units) | B16: =IFERROR(SUMIFS('Rent Roll Input'!$G$7:$G$606,'Rent Roll Input'!$S$7:$S$606,'Rent Roll Recon'!$B$2,'Rent Roll Input'!$D$7:$D$606,"IL"),0) | C16: =IFERROR(SUMIFS('Rent Roll Input'!$G$7:$G$606,'Rent Roll Input'!$S$7:$S$606,'Rent Roll Recon'!$B$2,'Rent Roll Input'!$D$7:$D$606,"AL"),0) | D16: =IFERROR(SUMIFS('Rent Roll Input'!$G$7:$G$606,'Rent Roll Input'!$S$7:$S$606,'Rent Roll Recon'!$B$2,'Rent Roll Input'!$D$7:$D$606,"MC"),0) | E16: =SUM(B16:D16) | H16: Gross Potential Rent — Market Rate × all units at 100% occupancy. Excludes concessions & vacancy loss. Row 16 − Row 17 = vacancy + market-vs-actual gap. | I16: Implied Monthly
A17: RR effective net base rent / mo (after concessions) | B17: =IFERROR(SUMIFS('Rent Roll Input'!$H$7:$H$606,'Rent Roll Input'!$S$7:$S$606,'Rent Roll Recon'!$B$2,'Rent Roll Input'!$E$7:$E$606,"<>Vacant",'Rent Roll Input'!$E$7:$E$606,"<>Eviction",'Rent Roll Input'!$D$7:$D$606,"IL")+SUMIFS('Rent Roll Input'!$I$7:$I$606,'Rent Roll Input'!$S$7:$S$606,'Rent Roll Recon'!$B$2,'Rent Roll Input'!$E$7:$E$606,"<>Vacant",'Rent Roll Input'!$E$7:$E$606,"<>Eviction",'Rent Roll Input'!$D$7:$D$606,"IL"),0) | C17: =IFERROR(SUMIFS('Rent Roll Input'!$H$7:$H$606,'Rent Roll Input'!$S$7:$S$606,'Rent Roll Recon'!$B$2,'Rent Roll Input'!$E$7:$E$606,"<>Vacant",'Rent Roll Input'!$E$7:$E$606,"<>Eviction",'Rent Roll Input'!$D$7:$D$606,"AL")+SUMIFS('Rent Roll Input'!$I$7:$I$606,'Rent Roll Input'!$S$7:$S$606,'Rent Roll Recon'!$B$2,'Rent Roll Input'!$E$7:$E$606,"<>Vacant",'Rent Roll Input'!$E$7:$E$606,"<>Eviction",'Rent Roll Input'!$D$7:$D$606,"AL"),0) | D17: =IFERROR(SUMIFS('Rent Roll Input'!$H$7:$H$606,'Rent Roll Input'!$S$7:$S$606,'Rent Roll Recon'!$B$2,'Rent Roll Input'!$E$7:$E$606,"<>Vacant",'Rent Roll Input'!$E$7:$E$606,"<>Eviction",'Rent Roll Input'!$D$7:$D$606,"MC")+SUMIFS('Rent Roll Input'!$I$7:$I$606,'Rent Roll Input'!$S$7:$S$606,'Rent Roll Recon'!$B$2,'Rent Roll Input'!$E$7:$E$606,"<>Vacant",'Rent Roll Input'!$E$7:$E$606,"<>Eviction",'Rent Roll Input'!$D$7:$D$606,"MC"),0) | E17: =SUM(B17:D17) | H17: ⚠ Actual rate + concessions — compare to T12 collected | I17: =E17
A18: RR effective net rent (annualized ×12) | B18: =B17*12 | C18: =C17*12 | D18: =D17*12 | E18: =E17*12 | H18: For direct comparison to T12 annual base rent | I18: =E18/12
A19: T12 actual base rent (from Raw Data, annualized) | B19: =IFERROR(INDEX('T12 Raw Data'!R:R,MATCH("Base rent — IL",'T12 Raw Data'!B:B,0)),0) | C19: =IFERROR(INDEX('T12 Raw Data'!R:R,MATCH("Base rent — AL",'T12 Raw Data'!B:B,0)),0) | D19: =IFERROR(INDEX('T12 Raw Data'!R:R,MATCH("Base rent — MC",'T12 Raw Data'!B:B,0)),0) | E19: =SUM(B19:D19) | H19: T12 total base rent from Raw Data | I19: =IFERROR(E19/12,0)
A20: Gap (RR annualized − T12 actual) | B20: =B18-B19 | C20: =C18-C19 | D20: =D18-D19 | E20: =E18-E19 | H20: =IF(E20=0,"Gap = $0 — RR and T12 are perfectly aligned.",IF(ABS(E20/E19)<=0.02,"Gap = "&TEXT(E20,"$#,##0")&" ("&TEXT(E20/E19,"0.0%")&") — within 2%, normal timing variance: partial-month move-ins/outs or rounding.",IF(E20<0,"⚠ Gap = "&TEXT(E20,"$#,##0")&" ("&TEXT(E20/E19,"0.0%")&"). T12 collected MORE than RR projects. Investigate: (1) Occ was higher earlier in T12 — property trending down; (2) Rates were higher in prior months — compression or new concessions; (3) Active concessions are newer than T12 average — not in full T12; ("&"4) Partial-month collections in T12 for move-ins/outs; (5) One-time adjustments or reversals in T12 income statement.","⚠ Gap = "&TEXT(E20,"$#,##0")&" ("&TEXT(E20/E19,"0.0%")&"). RR projects MORE than T12 collected. Investigate: (1) Occupancy has improved during T12 — positive trend; (2) Rates were raised mid-T12 — RR reflects new higher rates; (3) Bad debt or uncollected rent in T12 not visible in RR; (4) Notice residents bill"&"ed but not yet collected; (5) One-time credits or refunds in T12 reduced collected revenue."))) | I20: =IFERROR(IF(E20=0,"-",E20/12),"-")
A22: C · RATE ANALYSIS (RR contracted rate vs. T12 implied ADR)
A23: RR avg contracted rate / occ unit / month | B23: =IFERROR(AVERAGEIFS('Rent Roll Input'!$H$7:$H$606,'Rent Roll Input'!$S$7:$S$606,'Rent Roll Recon'!$B$2,'Rent Roll Input'!$E$7:$E$606,"<>Vacant",'Rent Roll Input'!$E$7:$E$606,"<>Eviction",'Rent Roll Input'!$D$7:$D$606,"IL"),"-") | C23: =IFERROR(AVERAGEIFS('Rent Roll Input'!$H$7:$H$606,'Rent Roll Input'!$S$7:$S$606,'Rent Roll Recon'!$B$2,'Rent Roll Input'!$E$7:$E$606,"<>Vacant",'Rent Roll Input'!$E$7:$E$606,"<>Eviction",'Rent Roll Input'!$D$7:$D$606,"AL"),"-") | D23: =IFERROR(AVERAGEIFS('Rent Roll Input'!$H$7:$H$606,'Rent Roll Input'!$S$7:$S$606,'Rent Roll Recon'!$B$2,'Rent Roll Input'!$E$7:$E$606,"<>Vacant",'Rent Roll Input'!$E$7:$E$606,"<>Eviction",'Rent Roll Input'!$D$7:$D$606,"MC"),"-") | E23: - | H23: Avg gross rate, occupied units
A24: RR avg effective rate (after concessions) | B24: =IFERROR(B17/B8,"-") | C24: =IFERROR(C17/C8,"-") | D24: =IFERROR(D17/D8,"-") | E24: - | H24: ⚠ Net of concessions — use for RevPOR crosscheck
A25: T12 implied ADR (base rent ÷ occ. beds ÷ 12) | B25: =IFERROR('T12 Analytics'!B17,0) | C25: =IFERROR('T12 Analytics'!C17,0) | D25: =IFERROR('T12 Analytics'!D17,0) | E25: - | H25: Back-calculated from T12 Analytics Section 2
A27: D · OCCUPANCY CROSSCHECK (RR snapshot vs. T12 avg occupied beds)
A28: RR occupied units (period snapshot) | B28: =COUNTIFS('Rent Roll Input'!$S$7:$S$606,'Rent Roll Recon'!$B$2,'Rent Roll Input'!$E$7:$E$606,"Occupied",'Rent Roll Input'!$D$7:$D$606,"IL") | C28: =COUNTIFS('Rent Roll Input'!$S$7:$S$606,'Rent Roll Recon'!$B$2,'Rent Roll Input'!$E$7:$E$606,"Occupied",'Rent Roll Input'!$D$7:$D$606,"AL") | D28: =COUNTIFS('Rent Roll Input'!$S$7:$S$606,'Rent Roll Recon'!$B$2,'Rent Roll Input'!$E$7:$E$606,"Occupied",'Rent Roll Input'!$D$7:$D$606,"MC") | E28: =SUM(B28:D28)
A29: T12 avg occupied beds (T12 Analytics Section 1) | B29: =IFERROR('T12 Analytics'!B7,0) | C29: =IFERROR('T12 Analytics'!C7,0) | D29: =IFERROR('T12 Analytics'!D7,0) | E29: =SUM(B29:D29) | H29: T12 12-month avg — compare to RR point-in-time
A30: Delta (RR snapshot − T12 avg) | B30: =B28-B29 | C30: =C28-C29 | D30: =D28-D29 | E30: =E28-E29 | H30: ⚠ Positive = occupancy improved; Negative = declined
A32: E · AUTO-FILL TO T12 ANALYTICS (occupied beds from selected period)
A33: T12 Analytics Section 1 (avg occupied beds) reads from rows below automatically. Override T12 Analytics row 7 directly if needed.
A34: Occupied beds — IL (feeds T12 Analytics B7) | B34: =B28
A35: Occupied beds — AL (feeds T12 Analytics C7) | C35: =C28
A36: Occupied beds — MC (feeds T12 Analytics D7) | D36: =D28
A38: F · PAYER MIX SUMMARY (auto-calculated from selected period)
A39: Payer Type | B39: Resident Count | C39: % of Res. | D39: Monthly Base Rev | E39: % Base Rev | F39: Monthly LOC Rev | G39: % LOC Rev | H39: Total Monthly Rev | I39: % of Total
A40: Private Pay | B40: =COUNTIFS('Rent Roll Input'!$S$7:$S$606,'Rent Roll Recon'!$B$2,'Rent Roll Input'!$E$7:$E$606,"<>Vacant",'Rent Roll Input'!$E$7:$E$606,"<>Eviction",'Rent Roll Input'!$P$7:$P$606,"Private Pay") | C40: =IFERROR(B40/B47,"-") | D40: =IFERROR(SUMIFS('Rent Roll Input'!$H$7:$H$606,'Rent Roll Input'!$S$7:$S$606,'Rent Roll Recon'!$B$2,'Rent Roll Input'!$E$7:$E$606,"<>Vacant",'Rent Roll Input'!$E$7:$E$606,"<>Eviction",'Rent Roll Input'!$P$7:$P$606,"Private Pay")+SUMIFS('Rent Roll Input'!$I$7:$I$606,'Rent Roll Input'!$S$7:$S$606,'Rent Roll Recon'!$B$2,'Rent Roll Input'!$E$7:$E$606,"<>Vacant",'Rent Roll Input'!$E$7:$E$606,"<>Eviction",'Rent Roll Input'!$P$7:$P$606,"Private Pay"),0) | E40: =IFERROR(D40/D47,"-") | F40: =IFERROR(SUMIFS('Rent Roll Input'!$T$7:$T$606,'Rent Roll Input'!$S$7:$S$606,'Rent Roll Recon'!$B$2,'Rent Roll Input'!$E$7:$E$606,"<>Vacant",'Rent Roll Input'!$E$7:$E$606,"<>Eviction",'Rent Roll Input'!$P$7:$P$606,"Private Pay"),0) | G40: =IFERROR(F40/F47,"-") | H40: =D40+F40 | I40: =IFERROR(H40/H47,"-")
A41: Medicaid | B41: =COUNTIFS('Rent Roll Input'!$S$7:$S$606,'Rent Roll Recon'!$B$2,'Rent Roll Input'!$E$7:$E$606,"<>Vacant",'Rent Roll Input'!$E$7:$E$606,"<>Eviction",'Rent Roll Input'!$P$7:$P$606,"Medicaid") | C41: =IFERROR(B41/B47,"-") | D41: =IFERROR(SUMIFS('Rent Roll Input'!$H$7:$H$606,'Rent Roll Input'!$S$7:$S$606,'Rent Roll Recon'!$B$2,'Rent Roll Input'!$E$7:$E$606,"<>Vacant",'Rent Roll Input'!$E$7:$E$606,"<>Eviction",'Rent Roll Input'!$P$7:$P$606,"Medicaid")+SUMIFS('Rent Roll Input'!$I$7:$I$606,'Rent Roll Input'!$S$7:$S$606,'Rent Roll Recon'!$B$2,'Rent Roll Input'!$E$7:$E$606,"<>Vacant",'Rent Roll Input'!$E$7:$E$606,"<>Eviction",'Rent Roll Input'!$P$7:$P$606,"Medicaid"),0) | E41: =IFERROR(D41/D47,"-") | F41: =IFERROR(SUMIFS('Rent Roll Input'!$T$7:$T$606,'Rent Roll Input'!$S$7:$S$606,'Rent Roll Recon'!$B$2,'Rent Roll Input'!$E$7:$E$606,"<>Vacant",'Rent Roll Input'!$E$7:$E$606,"<>Eviction",'Rent Roll Input'!$P$7:$P$606,"Medicaid"),0) | G41: =IFERROR(F41/F47,"-") | H41: =D41+F41 | I41: =IFERROR(H41/H47,"-")
A42: LTC Insurance | B42: =COUNTIFS('Rent Roll Input'!$S$7:$S$606,'Rent Roll Recon'!$B$2,'Rent Roll Input'!$E$7:$E$606,"<>Vacant",'Rent Roll Input'!$E$7:$E$606,"<>Eviction",'Rent Roll Input'!$P$7:$P$606,"LTC Insurance") | C42: =IFERROR(B42/B47,"-") | D42: =IFERROR(SUMIFS('Rent Roll Input'!$H$7:$H$606,'Rent Roll Input'!$S$7:$S$606,'Rent Roll Recon'!$B$2,'Rent Roll Input'!$E$7:$E$606,"<>Vacant",'Rent Roll Input'!$E$7:$E$606,"<>Eviction",'Rent Roll Input'!$P$7:$P$606,"LTC Insurance")+SUMIFS('Rent Roll Input'!$I$7:$I$606,'Rent Roll Input'!$S$7:$S$606,'Rent Roll Recon'!$B$2,'Rent Roll Input'!$E$7:$E$606,"<>Vacant",'Rent Roll Input'!$E$7:$E$606,"<>Eviction",'Rent Roll Input'!$P$7:$P$606,"LTC Insurance"),0) | E42: =IFERROR(D42/D47,"-") | F42: =IFERROR(SUMIFS('Rent Roll Input'!$T$7:$T$606,'Rent Roll Input'!$S$7:$S$606,'Rent Roll Recon'!$B$2,'Rent Roll Input'!$E$7:$E$606,"<>Vacant",'Rent Roll Input'!$E$7:$E$606,"<>Eviction",'Rent Roll Input'!$P$7:$P$606,"LTC Insurance"),0) | G42: =IFERROR(F42/F47,"-") | H42: =D42+F42 | I42: =IFERROR(H42/H47,"-")
A43: VA | B43: =COUNTIFS('Rent Roll Input'!$S$7:$S$606,'Rent Roll Recon'!$B$2,'Rent Roll Input'!$E$7:$E$606,"<>Vacant",'Rent Roll Input'!$E$7:$E$606,"<>Eviction",'Rent Roll Input'!$P$7:$P$606,"VA") | C43: =IFERROR(B43/B47,"-") | D43: =IFERROR(SUMIFS('Rent Roll Input'!$H$7:$H$606,'Rent Roll Input'!$S$7:$S$606,'Rent Roll Recon'!$B$2,'Rent Roll Input'!$E$7:$E$606,"<>Vacant",'Rent Roll Input'!$E$7:$E$606,"<>Eviction",'Rent Roll Input'!$P$7:$P$606,"VA")+SUMIFS('Rent Roll Input'!$I$7:$I$606,'Rent Roll Input'!$S$7:$S$606,'Rent Roll Recon'!$B$2,'Rent Roll Input'!$E$7:$E$606,"<>Vacant",'Rent Roll Input'!$E$7:$E$606,"<>Eviction",'Rent Roll Input'!$P$7:$P$606,"VA"),0) | E43: =IFERROR(D43/D47,"-") | F43: =IFERROR(SUMIFS('Rent Roll Input'!$T$7:$T$606,'Rent Roll Input'!$S$7:$S$606,'Rent Roll Recon'!$B$2,'Rent Roll Input'!$E$7:$E$606,"<>Vacant",'Rent Roll Input'!$E$7:$E$606,"<>Eviction",'Rent Roll Input'!$P$7:$P$606,"VA"),0) | G43: =IFERROR(F43/F47,"-") | H43: =D43+F43 | I43: =IFERROR(H43/H47,"-")
A44: Managed Care | B44: =COUNTIFS('Rent Roll Input'!$S$7:$S$606,'Rent Roll Recon'!$B$2,'Rent Roll Input'!$E$7:$E$606,"<>Vacant",'Rent Roll Input'!$E$7:$E$606,"<>Eviction",'Rent Roll Input'!$P$7:$P$606,"Managed Care") | C44: =IFERROR(B44/B47,"-") | D44: =IFERROR(SUMIFS('Rent Roll Input'!$H$7:$H$606,'Rent Roll Input'!$S$7:$S$606,'Rent Roll Recon'!$B$2,'Rent Roll Input'!$E$7:$E$606,"<>Vacant",'Rent Roll Input'!$E$7:$E$606,"<>Eviction",'Rent Roll Input'!$P$7:$P$606,"Managed Care")+SUMIFS('Rent Roll Input'!$I$7:$I$606,'Rent Roll Input'!$S$7:$S$606,'Rent Roll Recon'!$B$2,'Rent Roll Input'!$E$7:$E$606,"<>Vacant",'Rent Roll Input'!$E$7:$E$606,"<>Eviction",'Rent Roll Input'!$P$7:$P$606,"Managed Care"),0) | E44: =IFERROR(D44/D47,"-") | F44: =IFERROR(SUMIFS('Rent Roll Input'!$T$7:$T$606,'Rent Roll Input'!$S$7:$S$606,'Rent Roll Recon'!$B$2,'Rent Roll Input'!$E$7:$E$606,"<>Vacant",'Rent Roll Input'!$E$7:$E$606,"<>Eviction",'Rent Roll Input'!$P$7:$P$606,"Managed Care"),0) | G44: =IFERROR(F44/F47,"-") | H44: =D44+F44 | I44: =IFERROR(H44/H47,"-")
A45: Self-Pay | B45: =COUNTIFS('Rent Roll Input'!$S$7:$S$606,'Rent Roll Recon'!$B$2,'Rent Roll Input'!$E$7:$E$606,"<>Vacant",'Rent Roll Input'!$E$7:$E$606,"<>Eviction",'Rent Roll Input'!$P$7:$P$606,"Self-Pay") | C45: =IFERROR(B45/B47,"-") | D45: =IFERROR(SUMIFS('Rent Roll Input'!$H$7:$H$606,'Rent Roll Input'!$S$7:$S$606,'Rent Roll Recon'!$B$2,'Rent Roll Input'!$E$7:$E$606,"<>Vacant",'Rent Roll Input'!$E$7:$E$606,"<>Eviction",'Rent Roll Input'!$P$7:$P$606,"Self-Pay")+SUMIFS('Rent Roll Input'!$I$7:$I$606,'Rent Roll Input'!$S$7:$S$606,'Rent Roll Recon'!$B$2,'Rent Roll Input'!$E$7:$E$606,"<>Vacant",'Rent Roll Input'!$E$7:$E$606,"<>Eviction",'Rent Roll Input'!$P$7:$P$606,"Self-Pay"),0) | E45: =IFERROR(D45/D47,"-") | F45: =IFERROR(SUMIFS('Rent Roll Input'!$T$7:$T$606,'Rent Roll Input'!$S$7:$S$606,'Rent Roll Recon'!$B$2,'Rent Roll Input'!$E$7:$E$606,"<>Vacant",'Rent Roll Input'!$E$7:$E$606,"<>Eviction",'Rent Roll Input'!$P$7:$P$606,"Self-Pay"),0) | G45: =IFERROR(F45/F47,"-") | H45: =D45+F45 | I45: =IFERROR(H45/H47,"-")
A46: Other | B46: =COUNTIFS('Rent Roll Input'!$S$7:$S$606,'Rent Roll Recon'!$B$2,'Rent Roll Input'!$E$7:$E$606,"<>Vacant",'Rent Roll Input'!$E$7:$E$606,"<>Eviction",'Rent Roll Input'!$P$7:$P$606,"Other") | C46: =IFERROR(B46/B47,"-") | D46: =IFERROR(SUMIFS('Rent Roll Input'!$H$7:$H$606,'Rent Roll Input'!$S$7:$S$606,'Rent Roll Recon'!$B$2,'Rent Roll Input'!$E$7:$E$606,"<>Vacant",'Rent Roll Input'!$E$7:$E$606,"<>Eviction",'Rent Roll Input'!$P$7:$P$606,"Other")+SUMIFS('Rent Roll Input'!$I$7:$I$606,'Rent Roll Input'!$S$7:$S$606,'Rent Roll Recon'!$B$2,'Rent Roll Input'!$E$7:$E$606,"<>Vacant",'Rent Roll Input'!$E$7:$E$606,"<>Eviction",'Rent Roll Input'!$P$7:$P$606,"Other"),0) | E46: =IFERROR(D46/D47,"-") | F46: =IFERROR(SUMIFS('Rent Roll Input'!$T$7:$T$606,'Rent Roll Input'!$S$7:$S$606,'Rent Roll Recon'!$B$2,'Rent Roll Input'!$E$7:$E$606,"<>Vacant",'Rent Roll Input'!$E$7:$E$606,"<>Eviction",'Rent Roll Input'!$P$7:$P$606,"Other"),0) | G46: =IFERROR(F46/F47,"-") | H46: =D46+F46 | I46: =IFERROR(H46/H47,"-")
A47: Total occupied residents | B47: =SUM(B40:B46) | C47: 100.0% | D47: =SUM(D40:D46) | E47: 100.0% | F47: =SUM(F40:F46) | G47: 100.0% | H47: =SUM(H40:H46) | I47: 100.0%
A48: ⚠ Medicaid: flag for reimbursement rate risk, lower RevPOR impact, and stabilization assumptions. Managed Care: verify per diem rates vs. private pay rates.
A50: G · ARPR BY CARE TYPE (avg revenue per resident / month)
A51: Care Type | B51: Occupied Units | C51: Total Base Rev / mo | D51: ARPR Base ($/mo) | E51: Total LOC Rev / mo | F51: ARPR LOC ($/mo) | G51: Total Rev / mo | H51: ARPR Total ($/mo) | I51: LOC % of Base
A52: IL | B52: =COUNTIFS('Rent Roll Input'!$S$7:$S$606,'Rent Roll Recon'!$B$2,'Rent Roll Input'!$E$7:$E$606,"<>Vacant",'Rent Roll Input'!$E$7:$E$606,"<>Eviction",'Rent Roll Input'!$D$7:$D$606,"IL") | C52: =IFERROR(SUMIFS('Rent Roll Input'!$H$7:$H$606,'Rent Roll Input'!$S$7:$S$606,'Rent Roll Recon'!$B$2,'Rent Roll Input'!$E$7:$E$606,"<>Vacant",'Rent Roll Input'!$E$7:$E$606,"<>Eviction",'Rent Roll Input'!$D$7:$D$606,"IL")+SUMIFS('Rent Roll Input'!$I$7:$I$606,'Rent Roll Input'!$S$7:$S$606,'Rent Roll Recon'!$B$2,'Rent Roll Input'!$E$7:$E$606,"<>Vacant",'Rent Roll Input'!$E$7:$E$606,"<>Eviction",'Rent Roll Input'!$D$7:$D$606,"IL"),0) | D52: =IFERROR(C52/B52,"-") | E52: =IFERROR(SUMIFS('Rent Roll Input'!$T$7:$T$606,'Rent Roll Input'!$S$7:$S$606,'Rent Roll Recon'!$B$2,'Rent Roll Input'!$E$7:$E$606,"<>Vacant",'Rent Roll Input'!$E$7:$E$606,"<>Eviction",'Rent Roll Input'!$D$7:$D$606,"IL"),0) | F52: =IFERROR(E52/B52,"-") | G52: =C52+E52 | H52: =IFERROR(G52/B52,"-") | I52: =IFERROR(E52/C52,"-")
A53: AL | B53: =COUNTIFS('Rent Roll Input'!$S$7:$S$606,'Rent Roll Recon'!$B$2,'Rent Roll Input'!$E$7:$E$606,"<>Vacant",'Rent Roll Input'!$E$7:$E$606,"<>Eviction",'Rent Roll Input'!$D$7:$D$606,"AL") | C53: =IFERROR(SUMIFS('Rent Roll Input'!$H$7:$H$606,'Rent Roll Input'!$S$7:$S$606,'Rent Roll Recon'!$B$2,'Rent Roll Input'!$E$7:$E$606,"<>Vacant",'Rent Roll Input'!$E$7:$E$606,"<>Eviction",'Rent Roll Input'!$D$7:$D$606,"AL")+SUMIFS('Rent Roll Input'!$I$7:$I$606,'Rent Roll Input'!$S$7:$S$606,'Rent Roll Recon'!$B$2,'Rent Roll Input'!$E$7:$E$606,"<>Vacant",'Rent Roll Input'!$E$7:$E$606,"<>Eviction",'Rent Roll Input'!$D$7:$D$606,"AL"),0) | D53: =IFERROR(C53/B53,"-") | E53: =IFERROR(SUMIFS('Rent Roll Input'!$T$7:$T$606,'Rent Roll Input'!$S$7:$S$606,'Rent Roll Recon'!$B$2,'Rent Roll Input'!$E$7:$E$606,"<>Vacant",'Rent Roll Input'!$E$7:$E$606,"<>Eviction",'Rent Roll Input'!$D$7:$D$606,"AL"),0) | F53: =IFERROR(E53/B53,"-") | G53: =C53+E53 | H53: =IFERROR(G53/B53,"-") | I53: =IFERROR(E53/C53,"-")
A54: MC | B54: =COUNTIFS('Rent Roll Input'!$S$7:$S$606,'Rent Roll Recon'!$B$2,'Rent Roll Input'!$E$7:$E$606,"<>Vacant",'Rent Roll Input'!$E$7:$E$606,"<>Eviction",'Rent Roll Input'!$D$7:$D$606,"MC") | C54: =IFERROR(SUMIFS('Rent Roll Input'!$H$7:$H$606,'Rent Roll Input'!$S$7:$S$606,'Rent Roll Recon'!$B$2,'Rent Roll Input'!$E$7:$E$606,"<>Vacant",'Rent Roll Input'!$E$7:$E$606,"<>Eviction",'Rent Roll Input'!$D$7:$D$606,"MC")+SUMIFS('Rent Roll Input'!$I$7:$I$606,'Rent Roll Input'!$S$7:$S$606,'Rent Roll Recon'!$B$2,'Rent Roll Input'!$E$7:$E$606,"<>Vacant",'Rent Roll Input'!$E$7:$E$606,"<>Eviction",'Rent Roll Input'!$D$7:$D$606,"MC"),0) | D54: =IFERROR(C54/B54,"-") | E54: =IFERROR(SUMIFS('Rent Roll Input'!$T$7:$T$606,'Rent Roll Input'!$S$7:$S$606,'Rent Roll Recon'!$B$2,'Rent Roll Input'!$E$7:$E$606,"<>Vacant",'Rent Roll Input'!$E$7:$E$606,"<>Eviction",'Rent Roll Input'!$D$7:$D$606,"MC"),0) | F54: =IFERROR(E54/B54,"-") | G54: =C54+E54 | H54: =IFERROR(G54/B54,"-") | I54: =IFERROR(E54/C54,"-")
A55: Blended (all care types) | B55: =SUM(B52:B54) | C55: =SUM(C52:C54) | D55: =IFERROR(C55/B55,"-") | E55: =SUM(E52:E54) | F55: =IFERROR(E55/B55,"-") | G55: =SUM(G52:G54) | H55: =IFERROR(G55/B55,"-") | I55: =IFERROR(E55/C55,"-")
A57: H · AL CARE LEVEL DISTRIBUTION (acuity mix)
A58: AL Care Level | B58: Count | C58: % of Occupied | D58: Total $/mo | E58: Avg $/ resident | G58: % of Total LOC
A59: Basic | B59: =COUNTIFS('Rent Roll Input'!$S$7:$S$606,'Rent Roll Recon'!$B$2,'Rent Roll Input'!$E$7:$E$606,"<>Vacant",'Rent Roll Input'!$E$7:$E$606,"<>Eviction",'Rent Roll Input'!$K$7:$K$606,"Basic") | C59: =IFERROR(B59/COUNTIFS('Rent Roll Input'!$S$7:$S$606,'Rent Roll Recon'!$B$2,'Rent Roll Input'!$E$7:$E$606,"<>Vacant",'Rent Roll Input'!$E$7:$E$606,"<>Eviction"),"-") | D59: =IF($B$67=0,"",IFERROR(SUMIFS('Rent Roll Input'!$L$7:$L$606,'Rent Roll Input'!$S$7:$S$606,'Rent Roll Recon'!$B$2,'Rent Roll Input'!$E$7:$E$606,"<>Vacant",'Rent Roll Input'!$E$7:$E$606,"<>Eviction",'Rent Roll Input'!$K$7:$K$606,"Basic"),0)) | E59: =IFERROR(D59/B59,"-") | G59: =IFERROR(D59/D67,"-")
A60: Level 2 | B60: =COUNTIFS('Rent Roll Input'!$S$7:$S$606,'Rent Roll Recon'!$B$2,'Rent Roll Input'!$E$7:$E$606,"<>Vacant",'Rent Roll Input'!$E$7:$E$606,"<>Eviction",'Rent Roll Input'!$K$7:$K$606,"Level 2") | C60: =IFERROR(B60/COUNTIFS('Rent Roll Input'!$S$7:$S$606,'Rent Roll Recon'!$B$2,'Rent Roll Input'!$E$7:$E$606,"<>Vacant",'Rent Roll Input'!$E$7:$E$606,"<>Eviction"),"-") | D60: =IF($B$67=0,"",IFERROR(SUMIFS('Rent Roll Input'!$L$7:$L$606,'Rent Roll Input'!$S$7:$S$606,'Rent Roll Recon'!$B$2,'Rent Roll Input'!$E$7:$E$606,"<>Vacant",'Rent Roll Input'!$E$7:$E$606,"<>Eviction",'Rent Roll Input'!$K$7:$K$606,"Level 2"),0)) | E60: =IFERROR(D60/B60,"-") | G60: =IFERROR(D60/D67,"-")
A61: Level 3 | B61: =COUNTIFS('Rent Roll Input'!$S$7:$S$606,'Rent Roll Recon'!$B$2,'Rent Roll Input'!$E$7:$E$606,"<>Vacant",'Rent Roll Input'!$E$7:$E$606,"<>Eviction",'Rent Roll Input'!$K$7:$K$606,"Level 3") | C61: =IFERROR(B61/COUNTIFS('Rent Roll Input'!$S$7:$S$606,'Rent Roll Recon'!$B$2,'Rent Roll Input'!$E$7:$E$606,"<>Vacant",'Rent Roll Input'!$E$7:$E$606,"<>Eviction"),"-") | D61: =IF($B$67=0,"",IFERROR(SUMIFS('Rent Roll Input'!$L$7:$L$606,'Rent Roll Input'!$S$7:$S$606,'Rent Roll Recon'!$B$2,'Rent Roll Input'!$E$7:$E$606,"<>Vacant",'Rent Roll Input'!$E$7:$E$606,"<>Eviction",'Rent Roll Input'!$K$7:$K$606,"Level 3"),0)) | E61: =IFERROR(D61/B61,"-") | G61: =IFERROR(D61/D67,"-")
A62: Level 4 | B62: =COUNTIFS('Rent Roll Input'!$S$7:$S$606,'Rent Roll Recon'!$B$2,'Rent Roll Input'!$E$7:$E$606,"<>Vacant",'Rent Roll Input'!$E$7:$E$606,"<>Eviction",'Rent Roll Input'!$K$7:$K$606,"Level 4") | C62: =IFERROR(B62/COUNTIFS('Rent Roll Input'!$S$7:$S$606,'Rent Roll Recon'!$B$2,'Rent Roll Input'!$E$7:$E$606,"<>Vacant",'Rent Roll Input'!$E$7:$E$606,"<>Eviction"),"-") | D62: =IF($B$67=0,"",IFERROR(SUMIFS('Rent Roll Input'!$L$7:$L$606,'Rent Roll Input'!$S$7:$S$606,'Rent Roll Recon'!$B$2,'Rent Roll Input'!$E$7:$E$606,"<>Vacant",'Rent Roll Input'!$E$7:$E$606,"<>Eviction",'Rent Roll Input'!$K$7:$K$606,"Level 4"),0)) | E62: =IFERROR(D62/B62,"-") | G62: =IFERROR(D62/D67,"-")
A63: Level 5 | B63: =COUNTIFS('Rent Roll Input'!$S$7:$S$606,'Rent Roll Recon'!$B$2,'Rent Roll Input'!$E$7:$E$606,"<>Vacant",'Rent Roll Input'!$E$7:$E$606,"<>Eviction",'Rent Roll Input'!$K$7:$K$606,"Level 5") | C63: =IFERROR(B63/COUNTIFS('Rent Roll Input'!$S$7:$S$606,'Rent Roll Recon'!$B$2,'Rent Roll Input'!$E$7:$E$606,"<>Vacant",'Rent Roll Input'!$E$7:$E$606,"<>Eviction"),"-") | D63: =IF($B$67=0,"",IFERROR(SUMIFS('Rent Roll Input'!$L$7:$L$606,'Rent Roll Input'!$S$7:$S$606,'Rent Roll Recon'!$B$2,'Rent Roll Input'!$E$7:$E$606,"<>Vacant",'Rent Roll Input'!$E$7:$E$606,"<>Eviction",'Rent Roll Input'!$K$7:$K$606,"Level 5"),0)) | E63: =IFERROR(D63/B63,"-") | G63: =IFERROR(D63/D67,"-")
A64: Level 6 | B64: =COUNTIFS('Rent Roll Input'!$S$7:$S$606,'Rent Roll Recon'!$B$2,'Rent Roll Input'!$E$7:$E$606,"<>Vacant",'Rent Roll Input'!$E$7:$E$606,"<>Eviction",'Rent Roll Input'!$K$7:$K$606,"Level 6") | C64: =IFERROR(B64/COUNTIFS('Rent Roll Input'!$S$7:$S$606,'Rent Roll Recon'!$B$2,'Rent Roll Input'!$E$7:$E$606,"<>Vacant",'Rent Roll Input'!$E$7:$E$606,"<>Eviction"),"-") | D64: =IF($B$67=0,"",IFERROR(SUMIFS('Rent Roll Input'!$L$7:$L$606,'Rent Roll Input'!$S$7:$S$606,'Rent Roll Recon'!$B$2,'Rent Roll Input'!$E$7:$E$606,"<>Vacant",'Rent Roll Input'!$E$7:$E$606,"<>Eviction",'Rent Roll Input'!$K$7:$K$606,"Level 6"),0)) | E64: =IFERROR(D64/B64,"-") | G64: =IFERROR(D64/D67,"-")
A65: Level 7 | B65: =COUNTIFS('Rent Roll Input'!$S$7:$S$606,'Rent Roll Recon'!$B$2,'Rent Roll Input'!$E$7:$E$606,"<>Vacant",'Rent Roll Input'!$E$7:$E$606,"<>Eviction",'Rent Roll Input'!$K$7:$K$606,"Level 7") | C65: =IFERROR(B65/COUNTIFS('Rent Roll Input'!$S$7:$S$606,'Rent Roll Recon'!$B$2,'Rent Roll Input'!$E$7:$E$606,"<>Vacant",'Rent Roll Input'!$E$7:$E$606,"<>Eviction"),"-") | D65: =IF($B$67=0,"",IFERROR(SUMIFS('Rent Roll Input'!$L$7:$L$606,'Rent Roll Input'!$S$7:$S$606,'Rent Roll Recon'!$B$2,'Rent Roll Input'!$E$7:$E$606,"<>Vacant",'Rent Roll Input'!$E$7:$E$606,"<>Eviction",'Rent Roll Input'!$K$7:$K$606,"Level 7"),0)) | E65: =IFERROR(D65/B65,"-") | G65: =IFERROR(D65/D67,"-")
A66: Other | B66: =COUNTIFS('Rent Roll Input'!$S$7:$S$606,'Rent Roll Recon'!$B$2,'Rent Roll Input'!$E$7:$E$606,"<>Vacant",'Rent Roll Input'!$E$7:$E$606,"<>Eviction",'Rent Roll Input'!$K$7:$K$606,"Other") | C66: =IFERROR(B66/COUNTIFS('Rent Roll Input'!$S$7:$S$606,'Rent Roll Recon'!$B$2,'Rent Roll Input'!$E$7:$E$606,"<>Vacant",'Rent Roll Input'!$E$7:$E$606,"<>Eviction"),"-") | D66: =IF($B$67=0,"",IFERROR(SUMIFS('Rent Roll Input'!$L$7:$L$606,'Rent Roll Input'!$S$7:$S$606,'Rent Roll Recon'!$B$2,'Rent Roll Input'!$E$7:$E$606,"<>Vacant",'Rent Roll Input'!$E$7:$E$606,"<>Eviction",'Rent Roll Input'!$K$7:$K$606,"Other"),0)) | E66: =IFERROR(D66/B66,"-") | G66: =IFERROR(D66/D67,"-")
A67: Total AL care charges | B67: =SUM(B59:B66) | C67: 100% | D67: =SUM(D59:D66) | E67: =IFERROR(D67/B67,"-") | G67: 100%
A69: I · ANCILLARY CHARGES (Med Mgmt, Pharmacy, Other LOC)
A70: Charge Type | B70: Count Enrolled | C70: % of Occupied | D70: Total $/mo | E70: Avg $/ Enrolled
A71: Medication Management | B71: =COUNTIFS('Rent Roll Input'!$S$7:$S$606,'Rent Roll Recon'!$B$2,'Rent Roll Input'!$E$7:$E$606,"<>Vacant",'Rent Roll Input'!$E$7:$E$606,"<>Eviction",'Rent Roll Input'!$M$7:$M$606,">0") | C71: =IFERROR(COUNTIFS('Rent Roll Input'!$S$7:$S$606,'Rent Roll Recon'!$B$2,'Rent Roll Input'!$E$7:$E$606,"<>Vacant",'Rent Roll Input'!$E$7:$E$606,"<>Eviction",'Rent Roll Input'!$M$7:$M$606,">0")/(COUNTIFS('Rent Roll Input'!$S$7:$S$606,'Rent Roll Recon'!$B$2,'Rent Roll Input'!$E$7:$E$606,"<>Vacant",'Rent Roll Input'!$E$7:$E$606,"<>Eviction")),"-") | D71: =IFERROR(SUMIFS('Rent Roll Input'!$M$7:$M$606,'Rent Roll Input'!$S$7:$S$606,'Rent Roll Recon'!$B$2,'Rent Roll Input'!$E$7:$E$606,"<>Vacant",'Rent Roll Input'!$E$7:$E$606,"<>Eviction"),0) | E71: =IFERROR(D71/B71,"-") | H71: $150–$350 / mo; 26 of 35 in Salem Road
A72: Pharmacy | B72: =COUNTIFS('Rent Roll Input'!$S$7:$S$606,'Rent Roll Recon'!$B$2,'Rent Roll Input'!$E$7:$E$606,"<>Vacant",'Rent Roll Input'!$E$7:$E$606,"<>Eviction",'Rent Roll Input'!$N$7:$N$606,">0") | C72: =IFERROR(COUNTIFS('Rent Roll Input'!$S$7:$S$606,'Rent Roll Recon'!$B$2,'Rent Roll Input'!$E$7:$E$606,"<>Vacant",'Rent Roll Input'!$E$7:$E$606,"<>Eviction",'Rent Roll Input'!$N$7:$N$606,">0")/(COUNTIFS('Rent Roll Input'!$S$7:$S$606,'Rent Roll Recon'!$B$2,'Rent Roll Input'!$E$7:$E$606,"<>Vacant",'Rent Roll Input'!$E$7:$E$606,"<>Eviction")),"-") | D72: =IFERROR(SUMIFS('Rent Roll Input'!$N$7:$N$606,'Rent Roll Input'!$S$7:$S$606,'Rent Roll Recon'!$B$2,'Rent Roll Input'!$E$7:$E$606,"<>Vacant",'Rent Roll Input'!$E$7:$E$606,"<>Eviction"),0) | E72: =IFERROR(D72/B72,"-") | H72: $450 / mo when enrolled
A73: Other LOC | B73: =COUNTIFS('Rent Roll Input'!$S$7:$S$606,'Rent Roll Recon'!$B$2,'Rent Roll Input'!$E$7:$E$606,"<>Vacant",'Rent Roll Input'!$E$7:$E$606,"<>Eviction",'Rent Roll Input'!$O$7:$O$606,">0") | C73: =IFERROR(COUNTIFS('Rent Roll Input'!$S$7:$S$606,'Rent Roll Recon'!$B$2,'Rent Roll Input'!$E$7:$E$606,"<>Vacant",'Rent Roll Input'!$E$7:$E$606,"<>Eviction",'Rent Roll Input'!$O$7:$O$606,">0")/(COUNTIFS('Rent Roll Input'!$S$7:$S$606,'Rent Roll Recon'!$B$2,'Rent Roll Input'!$E$7:$E$606,"<>Vacant",'Rent Roll Input'!$E$7:$E$606,"<>Eviction")),"-") | D73: =IFERROR(SUMIFS('Rent Roll Input'!$O$7:$O$606,'Rent Roll Input'!$S$7:$S$606,'Rent Roll Recon'!$B$2,'Rent Roll Input'!$E$7:$E$606,"<>Vacant",'Rent Roll Input'!$E$7:$E$606,"<>Eviction"),0) | E73: =IFERROR(D73/B73,"-") | H73: Catch-all for additional LOC charges
A74: Total ancillary charges | D74: =SUM(D71:D73)
A75: Total LOC (care level + all ancillary) | D75: =IFERROR(SUMIFS('Rent Roll Input'!$T$7:$T$606,'Rent Roll Input'!$S$7:$S$606,'Rent Roll Recon'!$B$2,'Rent Roll Input'!$E$7:$E$606,"<>Vacant",'Rent Roll Input'!$E$7:$E$606,"<>Eviction"),0)
A77: J · CONCESSION TRACKER (active concessions and expiration flags)
A78: Residents with active concessions | B78: =COUNTIFS('Rent Roll Input'!$S$7:$S$606,'Rent Roll Recon'!$B$2,'Rent Roll Input'!$E$7:$E$606,"<>Vacant",'Rent Roll Input'!$E$7:$E$606,"<>Eviction",'Rent Roll Input'!$I$7:$I$606,"<0")
A79: Total concession $/mo (negative) | B79: =IFERROR(SUMIFS('Rent Roll Input'!$I$7:$I$606,'Rent Roll Input'!$S$7:$S$606,'Rent Roll Recon'!$B$2,'Rent Roll Input'!$E$7:$E$606,"<>Vacant",'Rent Roll Input'!$E$7:$E$606,"<>Eviction",'Rent Roll Input'!$I$7:$I$606,"<0"),0)
A80: Concession as % of gross contracted rent | B80: =IFERROR(B79/E16,"-")
A81: Concessions expiring ≤ 90 days (flag) | B81: =COUNTIFS('Rent Roll Input'!$S$7:$S$606,'Rent Roll Recon'!$B$2,'Rent Roll Input'!$E$7:$E$606,"<>Vacant",'Rent Roll Input'!$E$7:$E$606,"<>Eviction",'Rent Roll Input'!$I$7:$I$606,"<0",'Rent Roll Input'!$J$7:$J$606,"<="&TODAY()+90,'Rent Roll Input'!$J$7:$J$606,">="&TODAY()) | H81: ⚠ Review lease terms — concession burn-off boosts NOI
A82: Concessions expiring ≤ 180 days | B82: =COUNTIFS('Rent Roll Input'!$S$7:$S$606,'Rent Roll Recon'!$B$2,'Rent Roll Input'!$E$7:$E$606,"<>Vacant",'Rent Roll Input'!$E$7:$E$606,"<>Eviction",'Rent Roll Input'!$I$7:$I$606,"<0",'Rent Roll Input'!$J$7:$J$606,"<="&TODAY()+180,'Rent Roll Input'!$J$7:$J$606,">="&TODAY()) | H82: Model future NOI improvement from concession burn-off
A84: Blue=Period selector (B2) | Teal headers = calculated outputs | Yellow = key inputs | Amber = flags requiring review | ARPR = avg revenue per resident/month
A86: K · IL UNIT-TYPE MIX, SIZE & RATE DISPERSION
A87: Unit Type | B87: Count | C87: % of IL | D87: Avg Rate | E87: Min Rate | F87: Max Rate | G87: Avg Sq Ft | H87: $/Sq Ft | I87: Avg Actual PSF
A88: Studio | B88: =COUNTIFS('Rent Roll Input'!$S$7:$S$606,'Rent Roll Recon'!$B$2,'Rent Roll Input'!$E$7:$E$606,"<>Vacant",'Rent Roll Input'!$E$7:$E$606,"<>Eviction",'Rent Roll Input'!$D$7:$D$606,"IL",'Rent Roll Input'!$F$7:$F$606,"Studio") | C88: =IFERROR(B88/COUNTIFS('Rent Roll Input'!$S$7:$S$606,'Rent Roll Recon'!$B$2,'Rent Roll Input'!$E$7:$E$606,"<>Vacant",'Rent Roll Input'!$E$7:$E$606,"<>Eviction",'Rent Roll Input'!$D$7:$D$606,"IL"),"-") | D88: =IFERROR(AVERAGEIFS('Rent Roll Input'!$H$7:$H$606,'Rent Roll Input'!$S$7:$S$606,'Rent Roll Recon'!$B$2,'Rent Roll Input'!$E$7:$E$606,"<>Vacant",'Rent Roll Input'!$E$7:$E$606,"<>Eviction",'Rent Roll Input'!$D$7:$D$606,"IL",'Rent Roll Input'!$F$7:$F$606,"Studio"),"-") | E88: =IFERROR(MINIFS('Rent Roll Input'!$H$7:$H$606,'Rent Roll Input'!$S$7:$S$606,'Rent Roll Recon'!$B$2,'Rent Roll Input'!$E$7:$E$606,"<>Vacant",'Rent Roll Input'!$E$7:$E$606,"<>Eviction",'Rent Roll Input'!$D$7:$D$606,"IL",'Rent Roll Input'!$F$7:$F$606,"Studio"),"-") | F88: =IFERROR(MAXIFS('Rent Roll Input'!$H$7:$H$606,'Rent Roll Input'!$S$7:$S$606,'Rent Roll Recon'!$B$2,'Rent Roll Input'!$E$7:$E$606,"<>Vacant",'Rent Roll Input'!$E$7:$E$606,"<>Eviction",'Rent Roll Input'!$D$7:$D$606,"IL",'Rent Roll Input'!$F$7:$F$606,"Studio"),"-") | G88: =IFERROR(AVERAGEIFS('Rent Roll Input'!$C$7:$C$606,'Rent Roll Input'!$S$7:$S$606,'Rent Roll Recon'!$B$2,'Rent Roll Input'!$E$7:$E$606,"<>Vacant",'Rent Roll Input'!$E$7:$E$606,"<>Eviction",'Rent Roll Input'!$D$7:$D$606,"IL",'Rent Roll Input'!$F$7:$F$606,"Studio"),"-") | H88: =IFERROR(D88/G88,"-") | I88: =IFERROR(AVERAGEIFS('Rent Roll Input'!$AA$7:$AA$606,'Rent Roll Input'!$S$7:$S$606,'Rent Roll Recon'!$B$2,'Rent Roll Input'!$E$7:$E$606,"<>Vacant",'Rent Roll Input'!$E$7:$E$606,"<>Eviction",'Rent Roll Input'!$D$7:$D$606,"IL",'Rent Roll Input'!$F$7:$F$606,"Studio"),"-")
A89: 1 Bedroom | B89: =COUNTIFS('Rent Roll Input'!$S$7:$S$606,'Rent Roll Recon'!$B$2,'Rent Roll Input'!$E$7:$E$606,"<>Vacant",'Rent Roll Input'!$E$7:$E$606,"<>Eviction",'Rent Roll Input'!$D$7:$D$606,"IL",'Rent Roll Input'!$F$7:$F$606,"1 Bedroom") | C89: =IFERROR(B89/COUNTIFS('Rent Roll Input'!$S$7:$S$606,'Rent Roll Recon'!$B$2,'Rent Roll Input'!$E$7:$E$606,"<>Vacant",'Rent Roll Input'!$E$7:$E$606,"<>Eviction",'Rent Roll Input'!$D$7:$D$606,"IL"),"-") | D89: =IFERROR(AVERAGEIFS('Rent Roll Input'!$H$7:$H$606,'Rent Roll Input'!$S$7:$S$606,'Rent Roll Recon'!$B$2,'Rent Roll Input'!$E$7:$E$606,"<>Vacant",'Rent Roll Input'!$E$7:$E$606,"<>Eviction",'Rent Roll Input'!$D$7:$D$606,"IL",'Rent Roll Input'!$F$7:$F$606,"1 Bedroom"),"-") | E89: =IFERROR(MINIFS('Rent Roll Input'!$H$7:$H$606,'Rent Roll Input'!$S$7:$S$606,'Rent Roll Recon'!$B$2,'Rent Roll Input'!$E$7:$E$606,"<>Vacant",'Rent Roll Input'!$E$7:$E$606,"<>Eviction",'Rent Roll Input'!$D$7:$D$606,"IL",'Rent Roll Input'!$F$7:$F$606,"1 Bedroom"),"-") | F89: =IFERROR(MAXIFS('Rent Roll Input'!$H$7:$H$606,'Rent Roll Input'!$S$7:$S$606,'Rent Roll Recon'!$B$2,'Rent Roll Input'!$E$7:$E$606,"<>Vacant",'Rent Roll Input'!$E$7:$E$606,"<>Eviction",'Rent Roll Input'!$D$7:$D$606,"IL",'Rent Roll Input'!$F$7:$F$606,"1 Bedroom"),"-") | G89: =IFERROR(AVERAGEIFS('Rent Roll Input'!$C$7:$C$606,'Rent Roll Input'!$S$7:$S$606,'Rent Roll Recon'!$B$2,'Rent Roll Input'!$E$7:$E$606,"<>Vacant",'Rent Roll Input'!$E$7:$E$606,"<>Eviction",'Rent Roll Input'!$D$7:$D$606,"IL",'Rent Roll Input'!$F$7:$F$606,"1 Bedroom"),"-") | H89: =IFERROR(D89/G89,"-") | I89: =IFERROR(AVERAGEIFS('Rent Roll Input'!$AA$7:$AA$606,'Rent Roll Input'!$S$7:$S$606,'Rent Roll Recon'!$B$2,'Rent Roll Input'!$E$7:$E$606,"<>Vacant",'Rent Roll Input'!$E$7:$E$606,"<>Eviction",'Rent Roll Input'!$D$7:$D$606,"IL",'Rent Roll Input'!$F$7:$F$606,"1 Bedroom"),"-")
A90: 2 Bedroom | B90: =COUNTIFS('Rent Roll Input'!$S$7:$S$606,'Rent Roll Recon'!$B$2,'Rent Roll Input'!$E$7:$E$606,"<>Vacant",'Rent Roll Input'!$E$7:$E$606,"<>Eviction",'Rent Roll Input'!$D$7:$D$606,"IL",'Rent Roll Input'!$F$7:$F$606,"2 Bedroom") | C90: =IFERROR(B90/COUNTIFS('Rent Roll Input'!$S$7:$S$606,'Rent Roll Recon'!$B$2,'Rent Roll Input'!$E$7:$E$606,"<>Vacant",'Rent Roll Input'!$E$7:$E$606,"<>Eviction",'Rent Roll Input'!$D$7:$D$606,"IL"),"-") | D90: =IFERROR(AVERAGEIFS('Rent Roll Input'!$H$7:$H$606,'Rent Roll Input'!$S$7:$S$606,'Rent Roll Recon'!$B$2,'Rent Roll Input'!$E$7:$E$606,"<>Vacant",'Rent Roll Input'!$E$7:$E$606,"<>Eviction",'Rent Roll Input'!$D$7:$D$606,"IL",'Rent Roll Input'!$F$7:$F$606,"2 Bedroom"),"-") | E90: =IFERROR(MINIFS('Rent Roll Input'!$H$7:$H$606,'Rent Roll Input'!$S$7:$S$606,'Rent Roll Recon'!$B$2,'Rent Roll Input'!$E$7:$E$606,"<>Vacant",'Rent Roll Input'!$E$7:$E$606,"<>Eviction",'Rent Roll Input'!$D$7:$D$606,"IL",'Rent Roll Input'!$F$7:$F$606,"2 Bedroom"),"-") | F90: =IFERROR(MAXIFS('Rent Roll Input'!$H$7:$H$606,'Rent Roll Input'!$S$7:$S$606,'Rent Roll Recon'!$B$2,'Rent Roll Input'!$E$7:$E$606,"<>Vacant",'Rent Roll Input'!$E$7:$E$606,"<>Eviction",'Rent Roll Input'!$D$7:$D$606,"IL",'Rent Roll Input'!$F$7:$F$606,"2 Bedroom"),"-") | G90: =IFERROR(AVERAGEIFS('Rent Roll Input'!$C$7:$C$606,'Rent Roll Input'!$S$7:$S$606,'Rent Roll Recon'!$B$2,'Rent Roll Input'!$E$7:$E$606,"<>Vacant",'Rent Roll Input'!$E$7:$E$606,"<>Eviction",'Rent Roll Input'!$D$7:$D$606,"IL",'Rent Roll Input'!$F$7:$F$606,"2 Bedroom"),"-") | H90: =IFERROR(D90/G90,"-") | I90: =IFERROR(AVERAGEIFS('Rent Roll Input'!$AA$7:$AA$606,'Rent Roll Input'!$S$7:$S$606,'Rent Roll Recon'!$B$2,'Rent Roll Input'!$E$7:$E$606,"<>Vacant",'Rent Roll Input'!$E$7:$E$606,"<>Eviction",'Rent Roll Input'!$D$7:$D$606,"IL",'Rent Roll Input'!$F$7:$F$606,"2 Bedroom"),"-")
A91: Cottage / Villa | B91: =COUNTIFS('Rent Roll Input'!$S$7:$S$606,'Rent Roll Recon'!$B$2,'Rent Roll Input'!$E$7:$E$606,"<>Vacant",'Rent Roll Input'!$E$7:$E$606,"<>Eviction",'Rent Roll Input'!$D$7:$D$606,"IL",'Rent Roll Input'!$F$7:$F$606,"Cottage / Villa") | C91: =IFERROR(B91/COUNTIFS('Rent Roll Input'!$S$7:$S$606,'Rent Roll Recon'!$B$2,'Rent Roll Input'!$E$7:$E$606,"<>Vacant",'Rent Roll Input'!$E$7:$E$606,"<>Eviction",'Rent Roll Input'!$D$7:$D$606,"IL"),"-") | D91: =IFERROR(AVERAGEIFS('Rent Roll Input'!$H$7:$H$606,'Rent Roll Input'!$S$7:$S$606,'Rent Roll Recon'!$B$2,'Rent Roll Input'!$E$7:$E$606,"<>Vacant",'Rent Roll Input'!$E$7:$E$606,"<>Eviction",'Rent Roll Input'!$D$7:$D$606,"IL",'Rent Roll Input'!$F$7:$F$606,"Cottage / Villa"),"-") | E91: =IFERROR(MINIFS('Rent Roll Input'!$H$7:$H$606,'Rent Roll Input'!$S$7:$S$606,'Rent Roll Recon'!$B$2,'Rent Roll Input'!$E$7:$E$606,"<>Vacant",'Rent Roll Input'!$E$7:$E$606,"<>Eviction",'Rent Roll Input'!$D$7:$D$606,"IL",'Rent Roll Input'!$F$7:$F$606,"Cottage / Villa"),"-") | F91: =IFERROR(MAXIFS('Rent Roll Input'!$H$7:$H$606,'Rent Roll Input'!$S$7:$S$606,'Rent Roll Recon'!$B$2,'Rent Roll Input'!$E$7:$E$606,"<>Vacant",'Rent Roll Input'!$E$7:$E$606,"<>Eviction",'Rent Roll Input'!$D$7:$D$606,"IL",'Rent Roll Input'!$F$7:$F$606,"Cottage / Villa"),"-") | G91: =IFERROR(AVERAGEIFS('Rent Roll Input'!$C$7:$C$606,'Rent Roll Input'!$S$7:$S$606,'Rent Roll Recon'!$B$2,'Rent Roll Input'!$E$7:$E$606,"<>Vacant",'Rent Roll Input'!$E$7:$E$606,"<>Eviction",'Rent Roll Input'!$D$7:$D$606,"IL",'Rent Roll Input'!$F$7:$F$606,"Cottage / Villa"),"-") | H91: =IFERROR(D91/G91,"-") | I91: =IFERROR(AVERAGEIFS('Rent Roll Input'!$AA$7:$AA$606,'Rent Roll Input'!$S$7:$S$606,'Rent Roll Recon'!$B$2,'Rent Roll Input'!$E$7:$E$606,"<>Vacant",'Rent Roll Input'!$E$7:$E$606,"<>Eviction",'Rent Roll Input'!$D$7:$D$606,"IL",'Rent Roll Input'!$F$7:$F$606,"Cottage / Villa"),"-")
A92: Other | B92: =COUNTIFS('Rent Roll Input'!$S$7:$S$606,'Rent Roll Recon'!$B$2,'Rent Roll Input'!$E$7:$E$606,"<>Vacant",'Rent Roll Input'!$E$7:$E$606,"<>Eviction",'Rent Roll Input'!$D$7:$D$606,"IL",'Rent Roll Input'!$F$7:$F$606,"Other") | C92: =IFERROR(B92/COUNTIFS('Rent Roll Input'!$S$7:$S$606,'Rent Roll Recon'!$B$2,'Rent Roll Input'!$E$7:$E$606,"<>Vacant",'Rent Roll Input'!$E$7:$E$606,"<>Eviction",'Rent Roll Input'!$D$7:$D$606,"IL"),"-") | D92: =IFERROR(AVERAGEIFS('Rent Roll Input'!$H$7:$H$606,'Rent Roll Input'!$S$7:$S$606,'Rent Roll Recon'!$B$2,'Rent Roll Input'!$E$7:$E$606,"<>Vacant",'Rent Roll Input'!$E$7:$E$606,"<>Eviction",'Rent Roll Input'!$D$7:$D$606,"IL",'Rent Roll Input'!$F$7:$F$606,"Other"),"-") | E92: =IFERROR(MINIFS('Rent Roll Input'!$H$7:$H$606,'Rent Roll Input'!$S$7:$S$606,'Rent Roll Recon'!$B$2,'Rent Roll Input'!$E$7:$E$606,"<>Vacant",'Rent Roll Input'!$E$7:$E$606,"<>Eviction",'Rent Roll Input'!$D$7:$D$606,"IL",'Rent Roll Input'!$F$7:$F$606,"Other"),"-") | F92: =IFERROR(MAXIFS('Rent Roll Input'!$H$7:$H$606,'Rent Roll Input'!$S$7:$S$606,'Rent Roll Recon'!$B$2,'Rent Roll Input'!$E$7:$E$606,"<>Vacant",'Rent Roll Input'!$E$7:$E$606,"<>Eviction",'Rent Roll Input'!$D$7:$D$606,"IL",'Rent Roll Input'!$F$7:$F$606,"Other"),"-") | G92: =IFERROR(AVERAGEIFS('Rent Roll Input'!$C$7:$C$606,'Rent Roll Input'!$S$7:$S$606,'Rent Roll Recon'!$B$2,'Rent Roll Input'!$E$7:$E$606,"<>Vacant",'Rent Roll Input'!$E$7:$E$606,"<>Eviction",'Rent Roll Input'!$D$7:$D$606,"IL",'Rent Roll Input'!$F$7:$F$606,"Other"),"-") | H92: =IFERROR(D92/G92,"-") | I92: =IFERROR(AVERAGEIFS('Rent Roll Input'!$AA$7:$AA$606,'Rent Roll Input'!$S$7:$S$606,'Rent Roll Recon'!$B$2,'Rent Roll Input'!$E$7:$E$606,"<>Vacant",'Rent Roll Input'!$E$7:$E$606,"<>Eviction",'Rent Roll Input'!$D$7:$D$606,"IL",'Rent Roll Input'!$F$7:$F$606,"Other"),"-")
A93: Total IL occupied | B93: =SUM(B88:B92) | C93: 100.0% | D93: =IFERROR(AVERAGEIFS('Rent Roll Input'!$H$7:$H$606,'Rent Roll Input'!$S$7:$S$606,'Rent Roll Recon'!$B$2,'Rent Roll Input'!$E$7:$E$606,"<>Vacant",'Rent Roll Input'!$E$7:$E$606,"<>Eviction",'Rent Roll Input'!$D$7:$D$606,"IL"),"-") | E93: =IFERROR(MINIFS('Rent Roll Input'!$H$7:$H$606,'Rent Roll Input'!$S$7:$S$606,'Rent Roll Recon'!$B$2,'Rent Roll Input'!$E$7:$E$606,"<>Vacant",'Rent Roll Input'!$E$7:$E$606,"<>Eviction",'Rent Roll Input'!$D$7:$D$606,"IL"),"-") | F93: =IFERROR(MAXIFS('Rent Roll Input'!$H$7:$H$606,'Rent Roll Input'!$S$7:$S$606,'Rent Roll Recon'!$B$2,'Rent Roll Input'!$E$7:$E$606,"<>Vacant",'Rent Roll Input'!$E$7:$E$606,"<>Eviction",'Rent Roll Input'!$D$7:$D$606,"IL"),"-") | G93: =IFERROR(AVERAGEIFS('Rent Roll Input'!$C$7:$C$606,'Rent Roll Input'!$S$7:$S$606,'Rent Roll Recon'!$B$2,'Rent Roll Input'!$E$7:$E$606,"<>Vacant",'Rent Roll Input'!$E$7:$E$606,"<>Eviction",'Rent Roll Input'!$D$7:$D$606,"IL"),"-") | H93: =IFERROR(D93/G93,"-") | I93: =IFERROR(AVERAGEIFS('Rent Roll Input'!$AA$7:$AA$606,'Rent Roll Input'!$S$7:$S$606,'Rent Roll Recon'!$B$2,'Rent Roll Input'!$E$7:$E$606,"<>Vacant",'Rent Roll Input'!$E$7:$E$606,"<>Eviction",'Rent Roll Input'!$D$7:$D$606,"IL"),"-")
A95: Rate spread (max − min) | B95: =IFERROR(F93-E93,"-")
A96: Rate CV (approx — range ÷ avg ÷ √12) | B96: =IFERROR((F93-E93)/D93/SQRT(12),"-")
A97: Avg sq ft (IL occupied) | B97: =G93
A98: Sq ft range | B98: =IFERROR(MINIFS('Rent Roll Input'!$C$7:$C$606,'Rent Roll Input'!$S$7:$S$606,'Rent Roll Recon'!$B$2,'Rent Roll Input'!$E$7:$E$606,"<>Vacant",'Rent Roll Input'!$E$7:$E$606,"<>Eviction",'Rent Roll Input'!$D$7:$D$606,"IL"),"-") | C98: — | D98: =IFERROR(MAXIFS('Rent Roll Input'!$C$7:$C$606,'Rent Roll Input'!$S$7:$S$606,'Rent Roll Recon'!$B$2,'Rent Roll Input'!$E$7:$E$606,"<>Vacant",'Rent Roll Input'!$E$7:$E$606,"<>Eviction",'Rent Roll Input'!$D$7:$D$606,"IL"),"-")
A99: $/sq ft (IL avg rate ÷ avg sq ft) | B99: =H93
A100: =IF(B93=0,"No IL units in selected period",IF(B96>0.25,"⚠ IL rate CV "&TEXT(B96,"0.0%")&" — wide rate dispersion. "&"Likely legacy in-place rates well below current asking.","✓ IL rate dispersion within normal band."))
A102: L · MC CARE STRUCTURE (auto-detected pattern)
A103: MC Care Pattern detected: | B103: =IF(SUM(B106:B109)=0,"Flat-rate (no care levels recorded)",IF(COUNTIF(B106:B109,">0")=1,"Flat-rate (single tier)",IF(COUNTIF(B106:B109,">0")<=3,"Tiered acuity ("&COUNTIF(B106:B109,">0")&" levels)","Fee-for-service / variable")))
A105: Tier | B105: Count | C105: % of MC | D105: Avg $/mo | E105: Total $/mo
A106: Tier 1 / Basic | B106: =COUNTIFS('Rent Roll Input'!$S$7:$S$606,'Rent Roll Recon'!$B$2,'Rent Roll Input'!$E$7:$E$606,"<>Vacant",'Rent Roll Input'!$E$7:$E$606,"<>Eviction",'Rent Roll Input'!$D$7:$D$606,"MC",'Rent Roll Input'!$K$7:$K$606,"Basic")+COUNTIFS('Rent Roll Input'!$S$7:$S$606,'Rent Roll Recon'!$B$2,'Rent Roll Input'!$E$7:$E$606,"<>Vacant",'Rent Roll Input'!$E$7:$E$606,"<>Eviction",'Rent Roll Input'!$D$7:$D$606,"MC",'Rent Roll Input'!$K$7:$K$606,"Tier 1")+COUNTIFS('Rent Roll Input'!$S$7:$S$606,'Rent Roll Recon'!$B$2,'Rent Roll Input'!$E$7:$E$606,"<>Vacant",'Rent Roll Input'!$E$7:$E$606,"<>Eviction",'Rent Roll Input'!$D$7:$D$606,"MC",'Rent Roll Input'!$K$7:$K$606,"Level 1")+COUNTIFS('Rent Roll Input'!$S$7:$S$606,'Rent Roll Recon'!$B$2,'Rent Roll Input'!$E$7:$E$606,"<>Vacant",'Rent Roll Input'!$E$7:$E$606,"<>Eviction",'Rent Roll Input'!$D$7:$D$606,"MC",'Rent Roll Input'!$K$7:$K$606,"Lvl 1") | C106: =IFERROR(B106/COUNTIFS('Rent Roll Input'!$S$7:$S$606,'Rent Roll Recon'!$B$2,'Rent Roll Input'!$E$7:$E$606,"<>Vacant",'Rent Roll Input'!$E$7:$E$606,"<>Eviction",'Rent Roll Input'!$D$7:$D$606,"MC"),"-") | D106: =IFERROR((SUMIFS('Rent Roll Input'!$L$7:$L$606,'Rent Roll Input'!$S$7:$S$606,'Rent Roll Recon'!$B$2,'Rent Roll Input'!$E$7:$E$606,"<>Vacant",'Rent Roll Input'!$E$7:$E$606,"<>Eviction",'Rent Roll Input'!$D$7:$D$606,"MC",'Rent Roll Input'!$K$7:$K$606,"Basic")+SUMIFS('Rent Roll Input'!$L$7:$L$606,'Rent Roll Input'!$S$7:$S$606,'Rent Roll Recon'!$B$2,'Rent Roll Input'!$E$7:$E$606,"<>Vacant",'Rent Roll Input'!$E$7:$E$606,"<>Eviction",'Rent Roll Input'!$D$7:$D$606,"MC",'Rent Roll Input'!$K$7:$K$606,"Tier 1")+SUMIFS('Rent Roll Input'!$L$7:$L$606,'Rent Roll Input'!$S$7:$S$606,'Rent Roll Recon'!$B$2,'Rent Roll Input'!$E$7:$E$606,"<>Vacant",'Rent Roll Input'!$E$7:$E$606,"<>Eviction",'Rent Roll Input'!$D$7:$D$606,"MC",'Rent Roll Input'!$K$7:$K$606,"Level 1")+SUMIFS('Rent Roll Input'!$L$7:$L$606,'Rent Roll Input'!$S$7:$S$606,'Rent Roll Recon'!$B$2,'Rent Roll Input'!$E$7:$E$606,"<>Vacant",'Rent Roll Input'!$E$7:$E$606,"<>Eviction",'Rent Roll Input'!$D$7:$D$606,"MC",'Rent Roll Input'!$K$7:$K$606,"Lvl 1"))/B106,"-") | E106: =SUMIFS('Rent Roll Input'!$L$7:$L$606,'Rent Roll Input'!$S$7:$S$606,'Rent Roll Recon'!$B$2,'Rent Roll Input'!$E$7:$E$606,"<>Vacant",'Rent Roll Input'!$E$7:$E$606,"<>Eviction",'Rent Roll Input'!$D$7:$D$606,"MC",'Rent Roll Input'!$K$7:$K$606,"Basic")+SUMIFS('Rent Roll Input'!$L$7:$L$606,'Rent Roll Input'!$S$7:$S$606,'Rent Roll Recon'!$B$2,'Rent Roll Input'!$E$7:$E$606,"<>Vacant",'Rent Roll Input'!$E$7:$E$606,"<>Eviction",'Rent Roll Input'!$D$7:$D$606,"MC",'Rent Roll Input'!$K$7:$K$606,"Tier 1")+SUMIFS('Rent Roll Input'!$L$7:$L$606,'Rent Roll Input'!$S$7:$S$606,'Rent Roll Recon'!$B$2,'Rent Roll Input'!$E$7:$E$606,"<>Vacant",'Rent Roll Input'!$E$7:$E$606,"<>Eviction",'Rent Roll Input'!$D$7:$D$606,"MC",'Rent Roll Input'!$K$7:$K$606,"Level 1")+SUMIFS('Rent Roll Input'!$L$7:$L$606,'Rent Roll Input'!$S$7:$S$606,'Rent Roll Recon'!$B$2,'Rent Roll Input'!$E$7:$E$606,"<>Vacant",'Rent Roll Input'!$E$7:$E$606,"<>Eviction",'Rent Roll Input'!$D$7:$D$606,"MC",'Rent Roll Input'!$K$7:$K$606,"Lvl 1")
A107: Tier 2 / Moderate | B107: =COUNTIFS('Rent Roll Input'!$S$7:$S$606,'Rent Roll Recon'!$B$2,'Rent Roll Input'!$E$7:$E$606,"<>Vacant",'Rent Roll Input'!$E$7:$E$606,"<>Eviction",'Rent Roll Input'!$D$7:$D$606,"MC",'Rent Roll Input'!$K$7:$K$606,"Moderate")+COUNTIFS('Rent Roll Input'!$S$7:$S$606,'Rent Roll Recon'!$B$2,'Rent Roll Input'!$E$7:$E$606,"<>Vacant",'Rent Roll Input'!$E$7:$E$606,"<>Eviction",'Rent Roll Input'!$D$7:$D$606,"MC",'Rent Roll Input'!$K$7:$K$606,"Tier 2")+COUNTIFS('Rent Roll Input'!$S$7:$S$606,'Rent Roll Recon'!$B$2,'Rent Roll Input'!$E$7:$E$606,"<>Vacant",'Rent Roll Input'!$E$7:$E$606,"<>Eviction",'Rent Roll Input'!$D$7:$D$606,"MC",'Rent Roll Input'!$K$7:$K$606,"Level 2")+COUNTIFS('Rent Roll Input'!$S$7:$S$606,'Rent Roll Recon'!$B$2,'Rent Roll Input'!$E$7:$E$606,"<>Vacant",'Rent Roll Input'!$E$7:$E$606,"<>Eviction",'Rent Roll Input'!$D$7:$D$606,"MC",'Rent Roll Input'!$K$7:$K$606,"Level 3")+COUNTIFS('Rent Roll Input'!$S$7:$S$606,'Rent Roll Recon'!$B$2,'Rent Roll Input'!$E$7:$E$606,"<>Vacant",'Rent Roll Input'!$E$7:$E$606,"<>Eviction",'Rent Roll Input'!$D$7:$D$606,"MC",'Rent Roll Input'!$K$7:$K$606,"Lvl 2")+COUNTIFS('Rent Roll Input'!$S$7:$S$606,'Rent Roll Recon'!$B$2,'Rent Roll Input'!$E$7:$E$606,"<>Vacant",'Rent Roll Input'!$E$7:$E$606,"<>Eviction",'Rent Roll Input'!$D$7:$D$606,"MC",'Rent Roll Input'!$K$7:$K$606,"Lvl 3") | C107: =IFERROR(B107/COUNTIFS('Rent Roll Input'!$S$7:$S$606,'Rent Roll Recon'!$B$2,'Rent Roll Input'!$E$7:$E$606,"<>Vacant",'Rent Roll Input'!$E$7:$E$606,"<>Eviction",'Rent Roll Input'!$D$7:$D$606,"MC"),"-") | D107: =IFERROR((SUMIFS('Rent Roll Input'!$L$7:$L$606,'Rent Roll Input'!$S$7:$S$606,'Rent Roll Recon'!$B$2,'Rent Roll Input'!$E$7:$E$606,"<>Vacant",'Rent Roll Input'!$E$7:$E$606,"<>Eviction",'Rent Roll Input'!$D$7:$D$606,"MC",'Rent Roll Input'!$K$7:$K$606,"Moderate")+SUMIFS('Rent Roll Input'!$L$7:$L$606,'Rent Roll Input'!$S$7:$S$606,'Rent Roll Recon'!$B$2,'Rent Roll Input'!$E$7:$E$606,"<>Vacant",'Rent Roll Input'!$E$7:$E$606,"<>Eviction",'Rent Roll Input'!$D$7:$D$606,"MC",'Rent Roll Input'!$K$7:$K$606,"Tier 2")+SUMIFS('Rent Roll Input'!$L$7:$L$606,'Rent Roll Input'!$S$7:$S$606,'Rent Roll Recon'!$B$2,'Rent Roll Input'!$E$7:$E$606,"<>Vacant",'Rent Roll Input'!$E$7:$E$606,"<>Eviction",'Rent Roll Input'!$D$7:$D$606,"MC",'Rent Roll Input'!$K$7:$K$606,"Level 2")+SUMIFS('Rent Roll Input'!$L$7:$L$606,'Rent Roll Input'!$S$7:$S$606,'Rent Roll Recon'!$B$2,'Rent Roll Input'!$E$7:$E$606,"<>Vacant",'Rent Roll Input'!$E$7:$E$606,"<>Eviction",'Rent Roll Input'!$D$7:$D$606,"MC",'Rent Roll Input'!$K$7:$K$606,"Level 3")+SUMIFS('Rent Roll Input'!$L$7:$L$606,'Rent Roll Input'!$S$7:$S$606,'Rent Roll Recon'!$B$2,'Rent Roll Input'!$E$7:$E$606,"<>Vacant",'Rent Roll Input'!$E$7:$E$606,"<>Eviction",'Rent Roll Input'!$D$7:$D$606,"MC",'Rent Roll Input'!$K$7:$K$606,"Lvl 2")+SUMIFS('Rent Roll Input'!$L$7:$L$606,'Rent Roll Input'!$S$7:$S$606,'Rent Roll Recon'!$B$2,'Rent Roll Input'!$E$7:$E$606,"<>Vacant",'Rent Roll Input'!$E$7:$E$606,"<>Eviction",'Rent Roll Input'!$D$7:$D$606,"MC",'Rent Roll Input'!$K$7:$K$606,"Lvl 3"))/B107,"-") | E107: =SUMIFS('Rent Roll Input'!$L$7:$L$606,'Rent Roll Input'!$S$7:$S$606,'Rent Roll Recon'!$B$2,'Rent Roll Input'!$E$7:$E$606,"<>Vacant",'Rent Roll Input'!$E$7:$E$606,"<>Eviction",'Rent Roll Input'!$D$7:$D$606,"MC",'Rent Roll Input'!$K$7:$K$606,"Moderate")+SUMIFS('Rent Roll Input'!$L$7:$L$606,'Rent Roll Input'!$S$7:$S$606,'Rent Roll Recon'!$B$2,'Rent Roll Input'!$E$7:$E$606,"<>Vacant",'Rent Roll Input'!$E$7:$E$606,"<>Eviction",'Rent Roll Input'!$D$7:$D$606,"MC",'Rent Roll Input'!$K$7:$K$606,"Tier 2")+SUMIFS('Rent Roll Input'!$L$7:$L$606,'Rent Roll Input'!$S$7:$S$606,'Rent Roll Recon'!$B$2,'Rent Roll Input'!$E$7:$E$606,"<>Vacant",'Rent Roll Input'!$E$7:$E$606,"<>Eviction",'Rent Roll Input'!$D$7:$D$606,"MC",'Rent Roll Input'!$K$7:$K$606,"Level 2")+SUMIFS('Rent Roll Input'!$L$7:$L$606,'Rent Roll Input'!$S$7:$S$606,'Rent Roll Recon'!$B$2,'Rent Roll Input'!$E$7:$E$606,"<>Vacant",'Rent Roll Input'!$E$7:$E$606,"<>Eviction",'Rent Roll Input'!$D$7:$D$606,"MC",'Rent Roll Input'!$K$7:$K$606,"Level 3")+SUMIFS('Rent Roll Input'!$L$7:$L$606,'Rent Roll Input'!$S$7:$S$606,'Rent Roll Recon'!$B$2,'Rent Roll Input'!$E$7:$E$606,"<>Vacant",'Rent Roll Input'!$E$7:$E$606,"<>Eviction",'Rent Roll Input'!$D$7:$D$606,"MC",'Rent Roll Input'!$K$7:$K$606,"Lvl 2")+SUMIFS('Rent Roll Input'!$L$7:$L$606,'Rent Roll Input'!$S$7:$S$606,'Rent Roll Recon'!$B$2,'Rent Roll Input'!$E$7:$E$606,"<>Vacant",'Rent Roll Input'!$E$7:$E$606,"<>Eviction",'Rent Roll Input'!$D$7:$D$606,"MC",'Rent Roll Input'!$K$7:$K$606,"Lvl 3")
A108: Tier 3 / Advanced | B108: =COUNTIFS('Rent Roll Input'!$S$7:$S$606,'Rent Roll Recon'!$B$2,'Rent Roll Input'!$E$7:$E$606,"<>Vacant",'Rent Roll Input'!$E$7:$E$606,"<>Eviction",'Rent Roll Input'!$D$7:$D$606,"MC",'Rent Roll Input'!$K$7:$K$606,"Advanced")+COUNTIFS('Rent Roll Input'!$S$7:$S$606,'Rent Roll Recon'!$B$2,'Rent Roll Input'!$E$7:$E$606,"<>Vacant",'Rent Roll Input'!$E$7:$E$606,"<>Eviction",'Rent Roll Input'!$D$7:$D$606,"MC",'Rent Roll Input'!$K$7:$K$606,"Tier 3")+COUNTIFS('Rent Roll Input'!$S$7:$S$606,'Rent Roll Recon'!$B$2,'Rent Roll Input'!$E$7:$E$606,"<>Vacant",'Rent Roll Input'!$E$7:$E$606,"<>Eviction",'Rent Roll Input'!$D$7:$D$606,"MC",'Rent Roll Input'!$K$7:$K$606,"Level 4")+COUNTIFS('Rent Roll Input'!$S$7:$S$606,'Rent Roll Recon'!$B$2,'Rent Roll Input'!$E$7:$E$606,"<>Vacant",'Rent Roll Input'!$E$7:$E$606,"<>Eviction",'Rent Roll Input'!$D$7:$D$606,"MC",'Rent Roll Input'!$K$7:$K$606,"Level 5")+COUNTIFS('Rent Roll Input'!$S$7:$S$606,'Rent Roll Recon'!$B$2,'Rent Roll Input'!$E$7:$E$606,"<>Vacant",'Rent Roll Input'!$E$7:$E$606,"<>Eviction",'Rent Roll Input'!$D$7:$D$606,"MC",'Rent Roll Input'!$K$7:$K$606,"Level 6")+COUNTIFS('Rent Roll Input'!$S$7:$S$606,'Rent Roll Recon'!$B$2,'Rent Roll Input'!$E$7:$E$606,"<>Vacant",'Rent Roll Input'!$E$7:$E$606,"<>Eviction",'Rent Roll Input'!$D$7:$D$606,"MC",'Rent Roll Input'!$K$7:$K$606,"Level 7")+COUNTIFS('Rent Roll Input'!$S$7:$S$606,'Rent Roll Recon'!$B$2,'Rent Roll Input'!$E$7:$E$606,"<>Vacant",'Rent Roll Input'!$E$7:$E$606,"<>Eviction",'Rent Roll Input'!$D$7:$D$606,"MC",'Rent Roll Input'!$K$7:$K$606,"Lvl 4")+COUNTIFS('Rent Roll Input'!$S$7:$S$606,'Rent Roll Recon'!$B$2,'Rent Roll Input'!$E$7:$E$606,"<>Vacant",'Rent Roll Input'!$E$7:$E$606,"<>Eviction",'Rent Roll Input'!$D$7:$D$606,"MC",'Rent Roll Input'!$K$7:$K$606,"Lvl 5") | C108: =IFERROR(B108/COUNTIFS('Rent Roll Input'!$S$7:$S$606,'Rent Roll Recon'!$B$2,'Rent Roll Input'!$E$7:$E$606,"<>Vacant",'Rent Roll Input'!$E$7:$E$606,"<>Eviction",'Rent Roll Input'!$D$7:$D$606,"MC"),"-") | D108: =IFERROR((SUMIFS('Rent Roll Input'!$L$7:$L$606,'Rent Roll Input'!$S$7:$S$606,'Rent Roll Recon'!$B$2,'Rent Roll Input'!$E$7:$E$606,"<>Vacant",'Rent Roll Input'!$E$7:$E$606,"<>Eviction",'Rent Roll Input'!$D$7:$D$606,"MC",'Rent Roll Input'!$K$7:$K$606,"Advanced")+SUMIFS('Rent Roll Input'!$L$7:$L$606,'Rent Roll Input'!$S$7:$S$606,'Rent Roll Recon'!$B$2,'Rent Roll Input'!$E$7:$E$606,"<>Vacant",'Rent Roll Input'!$E$7:$E$606,"<>Eviction",'Rent Roll Input'!$D$7:$D$606,"MC",'Rent Roll Input'!$K$7:$K$606,"Tier 3")+SUMIFS('Rent Roll Input'!$L$7:$L$606,'Rent Roll Input'!$S$7:$S$606,'Rent Roll Recon'!$B$2,'Rent Roll Input'!$E$7:$E$606,"<>Vacant",'Rent Roll Input'!$E$7:$E$606,"<>Eviction",'Rent Roll Input'!$D$7:$D$606,"MC",'Rent Roll Input'!$K$7:$K$606,"Level 4")+SUMIFS('Rent Roll Input'!$L$7:$L$606,'Rent Roll Input'!$S$7:$S$606,'Rent Roll Recon'!$B$2,'Rent Roll Input'!$E$7:$E$606,"<>Vacant",'Rent Roll Input'!$E$7:$E$606,"<>Eviction",'Rent Roll Input'!$D$7:$D$606,"MC",'Rent Roll Input'!$K$7:$K$606,"Level 5")+SUMIFS('Rent Roll Input'!$L$7:$L$606,'Rent Roll Input'!$S$7:$S$606,'Rent Roll Recon'!$B$2,'Rent Roll Input'!$E$7:$E$606,"<>Vacant",'Rent Roll Input'!$E$7:$E$606,"<>Eviction",'Rent Roll Input'!$D$7:$D$606,"MC",'Rent Roll Input'!$K$7:$K$606,"Level 6")+SUMIFS('Rent Roll Input'!$L$7:$L$606,'Rent Roll Input'!$S$7:$S$606,'Rent Roll Recon'!$B$2,'Rent Roll Input'!$E$7:$E$606,"<>Vacant",'Rent Roll Input'!$E$7:$E$606,"<>Eviction",'Rent Roll Input'!$D$7:$D$606,"MC",'Rent Roll Input'!$K$7:$K$606,"Level 7")+SUMIFS('Rent Roll Input'!$L$7:$L$606,'Rent Roll Input'!$S$7:$S$606,'Rent Roll Recon'!$B$2,'Rent Roll Input'!$E$7:$E$606,"<>Vacant",'Rent Roll Input'!$E$7:$E$606,"<>Eviction",'Rent Roll Input'!$D$7:$D$606,"MC",'Rent Roll Input'!$K$7:$K$606,"Lvl 4")+SUMIFS('Rent Roll Input'!$L$7:$L$606,'Rent Roll Input'!$S$7:$S$606,'Rent Roll Recon'!$B$2,'Rent Roll Input'!$E$7:$E$606,"<>Vacant",'Rent Roll Input'!$E$7:$E$606,"<>Eviction",'Rent Roll Input'!$D$7:$D$606,"MC",'Rent Roll Input'!$K$7:$K$606,"Lvl 5"))/B108,"-") | E108: =SUMIFS('Rent Roll Input'!$L$7:$L$606,'Rent Roll Input'!$S$7:$S$606,'Rent Roll Recon'!$B$2,'Rent Roll Input'!$E$7:$E$606,"<>Vacant",'Rent Roll Input'!$E$7:$E$606,"<>Eviction",'Rent Roll Input'!$D$7:$D$606,"MC",'Rent Roll Input'!$K$7:$K$606,"Advanced")+SUMIFS('Rent Roll Input'!$L$7:$L$606,'Rent Roll Input'!$S$7:$S$606,'Rent Roll Recon'!$B$2,'Rent Roll Input'!$E$7:$E$606,"<>Vacant",'Rent Roll Input'!$E$7:$E$606,"<>Eviction",'Rent Roll Input'!$D$7:$D$606,"MC",'Rent Roll Input'!$K$7:$K$606,"Tier 3")+SUMIFS('Rent Roll Input'!$L$7:$L$606,'Rent Roll Input'!$S$7:$S$606,'Rent Roll Recon'!$B$2,'Rent Roll Input'!$E$7:$E$606,"<>Vacant",'Rent Roll Input'!$E$7:$E$606,"<>Eviction",'Rent Roll Input'!$D$7:$D$606,"MC",'Rent Roll Input'!$K$7:$K$606,"Level 4")+SUMIFS('Rent Roll Input'!$L$7:$L$606,'Rent Roll Input'!$S$7:$S$606,'Rent Roll Recon'!$B$2,'Rent Roll Input'!$E$7:$E$606,"<>Vacant",'Rent Roll Input'!$E$7:$E$606,"<>Eviction",'Rent Roll Input'!$D$7:$D$606,"MC",'Rent Roll Input'!$K$7:$K$606,"Level 5")+SUMIFS('Rent Roll Input'!$L$7:$L$606,'Rent Roll Input'!$S$7:$S$606,'Rent Roll Recon'!$B$2,'Rent Roll Input'!$E$7:$E$606,"<>Vacant",'Rent Roll Input'!$E$7:$E$606,"<>Eviction",'Rent Roll Input'!$D$7:$D$606,"MC",'Rent Roll Input'!$K$7:$K$606,"Level 6")+SUMIFS('Rent Roll Input'!$L$7:$L$606,'Rent Roll Input'!$S$7:$S$606,'Rent Roll Recon'!$B$2,'Rent Roll Input'!$E$7:$E$606,"<>Vacant",'Rent Roll Input'!$E$7:$E$606,"<>Eviction",'Rent Roll Input'!$D$7:$D$606,"MC",'Rent Roll Input'!$K$7:$K$606,"Level 7")+SUMIFS('Rent Roll Input'!$L$7:$L$606,'Rent Roll Input'!$S$7:$S$606,'Rent Roll Recon'!$B$2,'Rent Roll Input'!$E$7:$E$606,"<>Vacant",'Rent Roll Input'!$E$7:$E$606,"<>Eviction",'Rent Roll Input'!$D$7:$D$606,"MC",'Rent Roll Input'!$K$7:$K$606,"Lvl 4")+SUMIFS('Rent Roll Input'!$L$7:$L$606,'Rent Roll Input'!$S$7:$S$606,'Rent Roll Recon'!$B$2,'Rent Roll Input'!$E$7:$E$606,"<>Vacant",'Rent Roll Input'!$E$7:$E$606,"<>Eviction",'Rent Roll Input'!$D$7:$D$606,"MC",'Rent Roll Input'!$K$7:$K$606,"Lvl 5")
A109: Other / unmapped | B109: =MAX(0,COUNTIFS('Rent Roll Input'!$S$7:$S$606,'Rent Roll Recon'!$B$2,'Rent Roll Input'!$E$7:$E$606,"<>Vacant",'Rent Roll Input'!$E$7:$E$606,"<>Eviction",'Rent Roll Input'!$D$7:$D$606,"MC",'Rent Roll Input'!$K$7:$K$606,"?*")-SUM(B106:B108)) | C109: =IFERROR(B109/COUNTIFS('Rent Roll Input'!$S$7:$S$606,'Rent Roll Recon'!$B$2,'Rent Roll Input'!$E$7:$E$606,"<>Vacant",'Rent Roll Input'!$E$7:$E$606,"<>Eviction",'Rent Roll Input'!$D$7:$D$606,"MC"),"-") | D109: — | E109: =MAX(0,SUMIFS('Rent Roll Input'!$L$7:$L$606,'Rent Roll Input'!$S$7:$S$606,'Rent Roll Recon'!$B$2,'Rent Roll Input'!$E$7:$E$606,"<>Vacant",'Rent Roll Input'!$E$7:$E$606,"<>Eviction",'Rent Roll Input'!$D$7:$D$606,"MC")-SUM(E106:E108))
A110: Total MC occupied | B110: =COUNTIFS('Rent Roll Input'!$S$7:$S$606,'Rent Roll Recon'!$B$2,'Rent Roll Input'!$E$7:$E$606,"<>Vacant",'Rent Roll Input'!$E$7:$E$606,"<>Eviction",'Rent Roll Input'!$D$7:$D$606,"MC") | C110: 100.0% | D110: =IFERROR(E110/B110,"-") | E110: =SUMIFS('Rent Roll Input'!$L$7:$L$606,'Rent Roll Input'!$S$7:$S$606,'Rent Roll Recon'!$B$2,'Rent Roll Input'!$E$7:$E$606,"<>Vacant",'Rent Roll Input'!$E$7:$E$606,"<>Eviction",'Rent Roll Input'!$D$7:$D$606,"MC")
A112: MC avg base rent / resident | B112: =IFERROR(AVERAGEIFS('Rent Roll Input'!$H$7:$H$606,'Rent Roll Input'!$S$7:$S$606,'Rent Roll Recon'!$B$2,'Rent Roll Input'!$E$7:$E$606,"<>Vacant",'Rent Roll Input'!$E$7:$E$606,"<>Eviction",'Rent Roll Input'!$D$7:$D$606,"MC"),"-")
A113: MC avg care charge / resident | B113: =IFERROR(D110,"-")
A114: Care charge ÷ base rent ratio | B114: =IFERROR(B113/B112,"-") | C114: =IF(B114>0.3,"⚠ Care charge > 30% of base — acuity-heavy","✓ Within range")
A115: Total MC monthly revenue | B115: =IFERROR(SUMIFS('Rent Roll Input'!$H$7:$H$606,'Rent Roll Input'!$S$7:$S$606,'Rent Roll Recon'!$B$2,'Rent Roll Input'!$E$7:$E$606,"<>Vacant",'Rent Roll Input'!$E$7:$E$606,"<>Eviction",'Rent Roll Input'!$D$7:$D$606,"MC")+SUMIFS('Rent Roll Input'!$L$7:$L$606,'Rent Roll Input'!$S$7:$S$606,'Rent Roll Recon'!$B$2,'Rent Roll Input'!$E$7:$E$606,"<>Vacant",'Rent Roll Input'!$E$7:$E$606,"<>Eviction",'Rent Roll Input'!$D$7:$D$606,"MC")+SUMIFS('Rent Roll Input'!$I$7:$I$606,'Rent Roll Input'!$S$7:$S$606,'Rent Roll Recon'!$B$2,'Rent Roll Input'!$E$7:$E$606,"<>Vacant",'Rent Roll Input'!$E$7:$E$606,"<>Eviction",'Rent Roll Input'!$D$7:$D$606,"MC"),0)
A117: =IF(B110=0,"No MC units in selected period.",IF(LEFT(B103,9)="Flat-rate","Flat-rate MC detected. Tier analysis not applicable; "&"see base rent + care charge totals only.",IF(LEFT(B103,7)="Tiered ","Tiered MC detected. Verify per-tier staffing model supports the implied acuity mix.","Fee-for-service MC detected. Charges vary per resident — "&"review individual care plans for sustainability.")))
...

Sheet Monthly Trending
A1: Monthly Trending — T12 Actuals by Month | AZ1: Per-Label monthly summary by Group
AZ2: aggregator
A3: Category | B3: M01 | C3: M02 | D3: M03 | E3: M04 | F3: M05 | G3: M06 | H3: M07 | I3: M08 | J3: M09 | K3: M10 | L3: M11 | M3: M12 | N3: T12 Total | AZ3: visible
A4: REVENUE | AZ4: v0.2.7
A5: Base rent — IL | B5: =IFERROR(INDEX('T12 Raw Data'!F:F,MATCH("Base rent — IL",'T12 Raw Data'!B:B,0)),0) | C5: =IFERROR(INDEX('T12 Raw Data'!G:G,MATCH("Base rent — IL",'T12 Raw Data'!B:B,0)),0) | D5: =IFERROR(INDEX('T12 Raw Data'!H:H,MATCH("Base rent — IL",'T12 Raw Data'!B:B,0)),0) | E5: =IFERROR(INDEX('T12 Raw Data'!I:I,MATCH("Base rent — IL",'T12 Raw Data'!B:B,0)),0) | F5: =IFERROR(INDEX('T12 Raw Data'!J:J,MATCH("Base rent — IL",'T12 Raw Data'!B:B,0)),0) | G5: =IFERROR(INDEX('T12 Raw Data'!K:K,MATCH("Base rent — IL",'T12 Raw Data'!B:B,0)),0) | H5: =IFERROR(INDEX('T12 Raw Data'!L:L,MATCH("Base rent — IL",'T12 Raw Data'!B:B,0)),0) | I5: =IFERROR(INDEX('T12 Raw Data'!M:M,MATCH("Base rent — IL",'T12 Raw Data'!B:B,0)),0) | J5: =IFERROR(INDEX('T12 Raw Data'!N:N,MATCH("Base rent — IL",'T12 Raw Data'!B:B,0)),0) | K5: =IFERROR(INDEX('T12 Raw Data'!O:O,MATCH("Base rent — IL",'T12 Raw Data'!B:B,0)),0) | L5: =IFERROR(INDEX('T12 Raw Data'!P:P,MATCH("Base rent — IL",'T12 Raw Data'!B:B,0)),0) | M5: =IFERROR(INDEX('T12 Raw Data'!Q:Q,MATCH("Base rent — IL",'T12 Raw Data'!B:B,0)),0) | N5: =SUM(B5:M5)
A6: Base rent — AL | B6: =IFERROR(INDEX('T12 Raw Data'!F:F,MATCH("Base rent — AL",'T12 Raw Data'!B:B,0)),0) | C6: =IFERROR(INDEX('T12 Raw Data'!G:G,MATCH("Base rent — AL",'T12 Raw Data'!B:B,0)),0) | D6: =IFERROR(INDEX('T12 Raw Data'!H:H,MATCH("Base rent — AL",'T12 Raw Data'!B:B,0)),0) | E6: =IFERROR(INDEX('T12 Raw Data'!I:I,MATCH("Base rent — AL",'T12 Raw Data'!B:B,0)),0) | F6: =IFERROR(INDEX('T12 Raw Data'!J:J,MATCH("Base rent — AL",'T12 Raw Data'!B:B,0)),0) | G6: =IFERROR(INDEX('T12 Raw Data'!K:K,MATCH("Base rent — AL",'T12 Raw Data'!B:B,0)),0) | H6: =IFERROR(INDEX('T12 Raw Data'!L:L,MATCH("Base rent — AL",'T12 Raw Data'!B:B,0)),0) | I6: =IFERROR(INDEX('T12 Raw Data'!M:M,MATCH("Base rent — AL",'T12 Raw Data'!B:B,0)),0) | J6: =IFERROR(INDEX('T12 Raw Data'!N:N,MATCH("Base rent — AL",'T12 Raw Data'!B:B,0)),0) | K6: =IFERROR(INDEX('T12 Raw Data'!O:O,MATCH("Base rent — AL",'T12 Raw Data'!B:B,0)),0) | L6: =IFERROR(INDEX('T12 Raw Data'!P:P,MATCH("Base rent — AL",'T12 Raw Data'!B:B,0)),0) | M6: =IFERROR(INDEX('T12 Raw Data'!Q:Q,MATCH("Base rent — AL",'T12 Raw Data'!B:B,0)),0) | N6: =SUM(B6:M6)
A7: Base rent — MC | B7: =IFERROR(INDEX('T12 Raw Data'!F:F,MATCH("Base rent — MC",'T12 Raw Data'!B:B,0)),0) | C7: =IFERROR(INDEX('T12 Raw Data'!G:G,MATCH("Base rent — MC",'T12 Raw Data'!B:B,0)),0) | D7: =IFERROR(INDEX('T12 Raw Data'!H:H,MATCH("Base rent — MC",'T12 Raw Data'!B:B,0)),0) | E7: =IFERROR(INDEX('T12 Raw Data'!I:I,MATCH("Base rent — MC",'T12 Raw Data'!B:B,0)),0) | F7: =IFERROR(INDEX('T12 Raw Data'!J:J,MATCH("Base rent — MC",'T12 Raw Data'!B:B,0)),0) | G7: =IFERROR(INDEX('T12 Raw Data'!K:K,MATCH("Base rent — MC",'T12 Raw Data'!B:B,0)),0) | H7: =IFERROR(INDEX('T12 Raw Data'!L:L,MATCH("Base rent — MC",'T12 Raw Data'!B:B,0)),0) | I7: =IFERROR(INDEX('T12 Raw Data'!M:M,MATCH("Base rent — MC",'T12 Raw Data'!B:B,0)),0) | J7: =IFERROR(INDEX('T12 Raw Data'!N:N,MATCH("Base rent — MC",'T12 Raw Data'!B:B,0)),0) | K7: =IFERROR(INDEX('T12 Raw Data'!O:O,MATCH("Base rent — MC",'T12 Raw Data'!B:B,0)),0) | L7: =IFERROR(INDEX('T12 Raw Data'!P:P,MATCH("Base rent — MC",'T12 Raw Data'!B:B,0)),0) | M7: =IFERROR(INDEX('T12 Raw Data'!Q:Q,MATCH("Base rent — MC",'T12 Raw Data'!B:B,0)),0) | N7: =SUM(B7:M7)
A8: Total base rent | B8: =B5+B6+B7 | C8: =C5+C6+C7 | D8: =D5+D6+D7 | E8: =E5+E6+E7 | F8: =F5+F6+F7 | G8: =G5+G6+G7 | H8: =H5+H6+H7 | I8: =I5+I6+I7 | ... N8: =N5+N6+N7
A9: Gross Potential Rent (if reported in T12) | B9: =IFERROR(INDEX('T12 Raw Data'!F:F,MATCH("Gross Rent Revenue",'T12 Raw Data'!B:B,0)),0) | C9: =IFERROR(INDEX('T12 Raw Data'!G:G,MATCH("Gross Rent Revenue",'T12 Raw Data'!B:B,0)),0) | D9: =IFERROR(INDEX('T12 Raw Data'!H:H,MATCH("Gross Rent Revenue",'T12 Raw Data'!B:B,0)),0) | E9: =IFERROR(INDEX('T12 Raw Data'!I:I,MATCH("Gross Rent Revenue",'T12 Raw Data'!B:B,0)),0) | F9: =IFERROR(INDEX('T12 Raw Data'!J:J,MATCH("Gross Rent Revenue",'T12 Raw Data'!B:B,0)),0) | G9: =IFERROR(INDEX('T12 Raw Data'!K:K,MATCH("Gross Rent Revenue",'T12 Raw Data'!B:B,0)),0) | H9: =IFERROR(INDEX('T12 Raw Data'!L:L,MATCH("Gross Rent Revenue",'T12 Raw Data'!B:B,0)),0) | I9: =IFERROR(INDEX('T12 Raw Data'!M:M,MATCH("Gross Rent Revenue",'T12 Raw Data'!B:B,0)),0) | J9: =IFERROR(INDEX('T12 Raw Data'!N:N,MATCH("Gross Rent Revenue",'T12 Raw Data'!B:B,0)),0) | K9: =IFERROR(INDEX('T12 Raw Data'!O:O,MATCH("Gross Rent Revenue",'T12 Raw Data'!B:B,0)),0) | L9: =IFERROR(INDEX('T12 Raw Data'!P:P,MATCH("Gross Rent Revenue",'T12 Raw Data'!B:B,0)),0) | M9: =IFERROR(INDEX('T12 Raw Data'!Q:Q,MATCH("Gross Rent Revenue",'T12 Raw Data'!B:B,0)),0) | N9: =SUM(B9:M9)
A10: Physical vacancy (if reported in T12) | B10: =IFERROR(INDEX('T12 Raw Data'!F:F,MATCH("Physical Vacancy",'T12 Raw Data'!B:B,0)),0) | C10: =IFERROR(INDEX('T12 Raw Data'!G:G,MATCH("Physical Vacancy",'T12 Raw Data'!B:B,0)),0) | D10: =IFERROR(INDEX('T12 Raw Data'!H:H,MATCH("Physical Vacancy",'T12 Raw Data'!B:B,0)),0) | E10: =IFERROR(INDEX('T12 Raw Data'!I:I,MATCH("Physical Vacancy",'T12 Raw Data'!B:B,0)),0) | F10: =IFERROR(INDEX('T12 Raw Data'!J:J,MATCH("Physical Vacancy",'T12 Raw Data'!B:B,0)),0) | G10: =IFERROR(INDEX('T12 Raw Data'!K:K,MATCH("Physical Vacancy",'T12 Raw Data'!B:B,0)),0) | H10: =IFERROR(INDEX('T12 Raw Data'!L:L,MATCH("Physical Vacancy",'T12 Raw Data'!B:B,0)),0) | I10: =IFERROR(INDEX('T12 Raw Data'!M:M,MATCH("Physical Vacancy",'T12 Raw Data'!B:B,0)),0) | J10: =IFERROR(INDEX('T12 Raw Data'!N:N,MATCH("Physical Vacancy",'T12 Raw Data'!B:B,0)),0) | K10: =IFERROR(INDEX('T12 Raw Data'!O:O,MATCH("Physical Vacancy",'T12 Raw Data'!B:B,0)),0) | L10: =IFERROR(INDEX('T12 Raw Data'!P:P,MATCH("Physical Vacancy",'T12 Raw Data'!B:B,0)),0) | M10: =IFERROR(INDEX('T12 Raw Data'!Q:Q,MATCH("Physical Vacancy",'T12 Raw Data'!B:B,0)),0) | N10: =SUM(B10:M10)
A11: Loss to lease (if reported in T12) | B11: =IFERROR(INDEX('T12 Raw Data'!F:F,MATCH("Loss to Lease",'T12 Raw Data'!B:B,0)),0) | C11: =IFERROR(INDEX('T12 Raw Data'!G:G,MATCH("Loss to Lease",'T12 Raw Data'!B:B,0)),0) | D11: =IFERROR(INDEX('T12 Raw Data'!H:H,MATCH("Loss to Lease",'T12 Raw Data'!B:B,0)),0) | E11: =IFERROR(INDEX('T12 Raw Data'!I:I,MATCH("Loss to Lease",'T12 Raw Data'!B:B,0)),0) | F11: =IFERROR(INDEX('T12 Raw Data'!J:J,MATCH("Loss to Lease",'T12 Raw Data'!B:B,0)),0) | G11: =IFERROR(INDEX('T12 Raw Data'!K:K,MATCH("Loss to Lease",'T12 Raw Data'!B:B,0)),0) | H11: =IFERROR(INDEX('T12 Raw Data'!L:L,MATCH("Loss to Lease",'T12 Raw Data'!B:B,0)),0) | I11: =IFERROR(INDEX('T12 Raw Data'!M:M,MATCH("Loss to Lease",'T12 Raw Data'!B:B,0)),0) | J11: =IFERROR(INDEX('T12 Raw Data'!N:N,MATCH("Loss to Lease",'T12 Raw Data'!B:B,0)),0) | K11: =IFERROR(INDEX('T12 Raw Data'!O:O,MATCH("Loss to Lease",'T12 Raw Data'!B:B,0)),0) | L11: =IFERROR(INDEX('T12 Raw Data'!P:P,MATCH("Loss to Lease",'T12 Raw Data'!B:B,0)),0) | M11: =IFERROR(INDEX('T12 Raw Data'!Q:Q,MATCH("Loss to Lease",'T12 Raw Data'!B:B,0)),0) | N11: =SUM(B11:M11)
A12: LOC revenue — IL | B12: =IFERROR(INDEX('T12 Raw Data'!F:F,MATCH("LOC revenue — IL",'T12 Raw Data'!B:B,0)),0) | C12: =IFERROR(INDEX('T12 Raw Data'!G:G,MATCH("LOC revenue — IL",'T12 Raw Data'!B:B,0)),0) | D12: =IFERROR(INDEX('T12 Raw Data'!H:H,MATCH("LOC revenue — IL",'T12 Raw Data'!B:B,0)),0) | E12: =IFERROR(INDEX('T12 Raw Data'!I:I,MATCH("LOC revenue — IL",'T12 Raw Data'!B:B,0)),0) | F12: =IFERROR(INDEX('T12 Raw Data'!J:J,MATCH("LOC revenue — IL",'T12 Raw Data'!B:B,0)),0) | G12: =IFERROR(INDEX('T12 Raw Data'!K:K,MATCH("LOC revenue — IL",'T12 Raw Data'!B:B,0)),0) | H12: =IFERROR(INDEX('T12 Raw Data'!L:L,MATCH("LOC revenue — IL",'T12 Raw Data'!B:B,0)),0) | I12: =IFERROR(INDEX('T12 Raw Data'!M:M,MATCH("LOC revenue — IL",'T12 Raw Data'!B:B,0)),0) | J12: =IFERROR(INDEX('T12 Raw Data'!N:N,MATCH("LOC revenue — IL",'T12 Raw Data'!B:B,0)),0) | K12: =IFERROR(INDEX('T12 Raw Data'!O:O,MATCH("LOC revenue — IL",'T12 Raw Data'!B:B,0)),0) | L12: =IFERROR(INDEX('T12 Raw Data'!P:P,MATCH("LOC revenue — IL",'T12 Raw Data'!B:B,0)),0) | M12: =IFERROR(INDEX('T12 Raw Data'!Q:Q,MATCH("LOC revenue — IL",'T12 Raw Data'!B:B,0)),0) | N12: =SUM(B12:M12)
A13: LOC revenue — AL | B13: =IFERROR(INDEX('T12 Raw Data'!F:F,MATCH("LOC revenue — AL",'T12 Raw Data'!B:B,0)),0) | C13: =IFERROR(INDEX('T12 Raw Data'!G:G,MATCH("LOC revenue — AL",'T12 Raw Data'!B:B,0)),0) | D13: =IFERROR(INDEX('T12 Raw Data'!H:H,MATCH("LOC revenue — AL",'T12 Raw Data'!B:B,0)),0) | E13: =IFERROR(INDEX('T12 Raw Data'!I:I,MATCH("LOC revenue — AL",'T12 Raw Data'!B:B,0)),0) | F13: =IFERROR(INDEX('T12 Raw Data'!J:J,MATCH("LOC revenue — AL",'T12 Raw Data'!B:B,0)),0) | G13: =IFERROR(INDEX('T12 Raw Data'!K:K,MATCH("LOC revenue — AL",'T12 Raw Data'!B:B,0)),0) | H13: =IFERROR(INDEX('T12 Raw Data'!L:L,MATCH("LOC revenue — AL",'T12 Raw Data'!B:B,0)),0) | I13: =IFERROR(INDEX('T12 Raw Data'!M:M,MATCH("LOC revenue — AL",'T12 Raw Data'!B:B,0)),0) | J13: =IFERROR(INDEX('T12 Raw Data'!N:N,MATCH("LOC revenue — AL",'T12 Raw Data'!B:B,0)),0) | K13: =IFERROR(INDEX('T12 Raw Data'!O:O,MATCH("LOC revenue — AL",'T12 Raw Data'!B:B,0)),0) | L13: =IFERROR(INDEX('T12 Raw Data'!P:P,MATCH("LOC revenue — AL",'T12 Raw Data'!B:B,0)),0) | M13: =IFERROR(INDEX('T12 Raw Data'!Q:Q,MATCH("LOC revenue — AL",'T12 Raw Data'!B:B,0)),0) | N13: =SUM(B13:M13)
A14: LOC revenue — MC | B14: =IFERROR(INDEX('T12 Raw Data'!F:F,MATCH("LOC revenue — MC",'T12 Raw Data'!B:B,0)),0) | C14: =IFERROR(INDEX('T12 Raw Data'!G:G,MATCH("LOC revenue — MC",'T12 Raw Data'!B:B,0)),0) | D14: =IFERROR(INDEX('T12 Raw Data'!H:H,MATCH("LOC revenue — MC",'T12 Raw Data'!B:B,0)),0) | E14: =IFERROR(INDEX('T12 Raw Data'!I:I,MATCH("LOC revenue — MC",'T12 Raw Data'!B:B,0)),0) | F14: =IFERROR(INDEX('T12 Raw Data'!J:J,MATCH("LOC revenue — MC",'T12 Raw Data'!B:B,0)),0) | G14: =IFERROR(INDEX('T12 Raw Data'!K:K,MATCH("LOC revenue — MC",'T12 Raw Data'!B:B,0)),0) | H14: =IFERROR(INDEX('T12 Raw Data'!L:L,MATCH("LOC revenue — MC",'T12 Raw Data'!B:B,0)),0) | I14: =IFERROR(INDEX('T12 Raw Data'!M:M,MATCH("LOC revenue — MC",'T12 Raw Data'!B:B,0)),0) | J14: =IFERROR(INDEX('T12 Raw Data'!N:N,MATCH("LOC revenue — MC",'T12 Raw Data'!B:B,0)),0) | K14: =IFERROR(INDEX('T12 Raw Data'!O:O,MATCH("LOC revenue — MC",'T12 Raw Data'!B:B,0)),0) | L14: =IFERROR(INDEX('T12 Raw Data'!P:P,MATCH("LOC revenue — MC",'T12 Raw Data'!B:B,0)),0) | M14: =IFERROR(INDEX('T12 Raw Data'!Q:Q,MATCH("LOC revenue — MC",'T12 Raw Data'!B:B,0)),0) | N14: =SUM(B14:M14)
A15: Total LOC revenue | B15: =B12+B13+B14 | C15: =C12+C13+C14 | D15: =D12+D13+D14 | E15: =E12+E13+E14 | F15: =F12+F13+F14 | G15: =G12+G13+G14 | H15: =H12+H13+H14 | I15: =I12+I13+I14 | ... N15: =N12+N13+N14
A16: Community / move-in fees | B16: =IFERROR(INDEX('T12 Raw Data'!F:F,MATCH("Community / move-in fees",'T12 Raw Data'!B:B,0)),0) | C16: =IFERROR(INDEX('T12 Raw Data'!G:G,MATCH("Community / move-in fees",'T12 Raw Data'!B:B,0)),0) | D16: =IFERROR(INDEX('T12 Raw Data'!H:H,MATCH("Community / move-in fees",'T12 Raw Data'!B:B,0)),0) | E16: =IFERROR(INDEX('T12 Raw Data'!I:I,MATCH("Community / move-in fees",'T12 Raw Data'!B:B,0)),0) | F16: =IFERROR(INDEX('T12 Raw Data'!J:J,MATCH("Community / move-in fees",'T12 Raw Data'!B:B,0)),0) | G16: =IFERROR(INDEX('T12 Raw Data'!K:K,MATCH("Community / move-in fees",'T12 Raw Data'!B:B,0)),0) | H16: =IFERROR(INDEX('T12 Raw Data'!L:L,MATCH("Community / move-in fees",'T12 Raw Data'!B:B,0)),0) | I16: =IFERROR(INDEX('T12 Raw Data'!M:M,MATCH("Community / move-in fees",'T12 Raw Data'!B:B,0)),0) | J16: =IFERROR(INDEX('T12 Raw Data'!N:N,MATCH("Community / move-in fees",'T12 Raw Data'!B:B,0)),0) | K16: =IFERROR(INDEX('T12 Raw Data'!O:O,MATCH("Community / move-in fees",'T12 Raw Data'!B:B,0)),0) | L16: =IFERROR(INDEX('T12 Raw Data'!P:P,MATCH("Community / move-in fees",'T12 Raw Data'!B:B,0)),0) | M16: =IFERROR(INDEX('T12 Raw Data'!Q:Q,MATCH("Community / move-in fees",'T12 Raw Data'!B:B,0)),0) | N16: =SUM(B16:M16)
A17: Concessions & specials | B17: =IFERROR(INDEX('T12 Raw Data'!F:F,MATCH("Concessions & specials",'T12 Raw Data'!B:B,0)),0) | C17: =IFERROR(INDEX('T12 Raw Data'!G:G,MATCH("Concessions & specials",'T12 Raw Data'!B:B,0)),0) | D17: =IFERROR(INDEX('T12 Raw Data'!H:H,MATCH("Concessions & specials",'T12 Raw Data'!B:B,0)),0) | E17: =IFERROR(INDEX('T12 Raw Data'!I:I,MATCH("Concessions & specials",'T12 Raw Data'!B:B,0)),0) | F17: =IFERROR(INDEX('T12 Raw Data'!J:J,MATCH("Concessions & specials",'T12 Raw Data'!B:B,0)),0) | G17: =IFERROR(INDEX('T12 Raw Data'!K:K,MATCH("Concessions & specials",'T12 Raw Data'!B:B,0)),0) | H17: =IFERROR(INDEX('T12 Raw Data'!L:L,MATCH("Concessions & specials",'T12 Raw Data'!B:B,0)),0) | I17: =IFERROR(INDEX('T12 Raw Data'!M:M,MATCH("Concessions & specials",'T12 Raw Data'!B:B,0)),0) | J17: =IFERROR(INDEX('T12 Raw Data'!N:N,MATCH("Concessions & specials",'T12 Raw Data'!B:B,0)),0) | K17: =IFERROR(INDEX('T12 Raw Data'!O:O,MATCH("Concessions & specials",'T12 Raw Data'!B:B,0)),0) | L17: =IFERROR(INDEX('T12 Raw Data'!P:P,MATCH("Concessions & specials",'T12 Raw Data'!B:B,0)),0) | M17: =IFERROR(INDEX('T12 Raw Data'!Q:Q,MATCH("Concessions & specials",'T12 Raw Data'!B:B,0)),0) | N17: =SUM(B17:M17)
A18: Respite care | B18: =IFERROR(INDEX('T12 Raw Data'!F:F,MATCH("Respite care",'T12 Raw Data'!B:B,0)),0) | C18: =IFERROR(INDEX('T12 Raw Data'!G:G,MATCH("Respite care",'T12 Raw Data'!B:B,0)),0) | D18: =IFERROR(INDEX('T12 Raw Data'!H:H,MATCH("Respite care",'T12 Raw Data'!B:B,0)),0) | E18: =IFERROR(INDEX('T12 Raw Data'!I:I,MATCH("Respite care",'T12 Raw Data'!B:B,0)),0) | F18: =IFERROR(INDEX('T12 Raw Data'!J:J,MATCH("Respite care",'T12 Raw Data'!B:B,0)),0) | G18: =IFERROR(INDEX('T12 Raw Data'!K:K,MATCH("Respite care",'T12 Raw Data'!B:B,0)),0) | H18: =IFERROR(INDEX('T12 Raw Data'!L:L,MATCH("Respite care",'T12 Raw Data'!B:B,0)),0) | I18: =IFERROR(INDEX('T12 Raw Data'!M:M,MATCH("Respite care",'T12 Raw Data'!B:B,0)),0) | J18: =IFERROR(INDEX('T12 Raw Data'!N:N,MATCH("Respite care",'T12 Raw Data'!B:B,0)),0) | K18: =IFERROR(INDEX('T12 Raw Data'!O:O,MATCH("Respite care",'T12 Raw Data'!B:B,0)),0) | L18: =IFERROR(INDEX('T12 Raw Data'!P:P,MATCH("Respite care",'T12 Raw Data'!B:B,0)),0) | M18: =IFERROR(INDEX('T12 Raw Data'!Q:Q,MATCH("Respite care",'T12 Raw Data'!B:B,0)),0) | N18: =SUM(B18:M18)
A19: 2nd Person Revenue | B19: =IFERROR(INDEX('T12 Raw Data'!F:F,MATCH("2nd Person Revenue",'T12 Raw Data'!B:B,0)),0) | C19: =IFERROR(INDEX('T12 Raw Data'!G:G,MATCH("2nd Person Revenue",'T12 Raw Data'!B:B,0)),0) | D19: =IFERROR(INDEX('T12 Raw Data'!H:H,MATCH("2nd Person Revenue",'T12 Raw Data'!B:B,0)),0) | E19: =IFERROR(INDEX('T12 Raw Data'!I:I,MATCH("2nd Person Revenue",'T12 Raw Data'!B:B,0)),0) | F19: =IFERROR(INDEX('T12 Raw Data'!J:J,MATCH("2nd Person Revenue",'T12 Raw Data'!B:B,0)),0) | G19: =IFERROR(INDEX('T12 Raw Data'!K:K,MATCH("2nd Person Revenue",'T12 Raw Data'!B:B,0)),0) | H19: =IFERROR(INDEX('T12 Raw Data'!L:L,MATCH("2nd Person Revenue",'T12 Raw Data'!B:B,0)),0) | I19: =IFERROR(INDEX('T12 Raw Data'!M:M,MATCH("2nd Person Revenue",'T12 Raw Data'!B:B,0)),0) | J19: =IFERROR(INDEX('T12 Raw Data'!N:N,MATCH("2nd Person Revenue",'T12 Raw Data'!B:B,0)),0) | K19: =IFERROR(INDEX('T12 Raw Data'!O:O,MATCH("2nd Person Revenue",'T12 Raw Data'!B:B,0)),0) | L19: =IFERROR(INDEX('T12 Raw Data'!P:P,MATCH("2nd Person Revenue",'T12 Raw Data'!B:B,0)),0) | M19: =IFERROR(INDEX('T12 Raw Data'!Q:Q,MATCH("2nd Person Revenue",'T12 Raw Data'!B:B,0)),0) | N19: =SUM(B19:M19)
A20: Meal Income | B20: =IFERROR(INDEX('T12 Raw Data'!F:F,MATCH("Meal Income",'T12 Raw Data'!B:B,0)),0) | C20: =IFERROR(INDEX('T12 Raw Data'!G:G,MATCH("Meal Income",'T12 Raw Data'!B:B,0)),0) | D20: =IFERROR(INDEX('T12 Raw Data'!H:H,MATCH("Meal Income",'T12 Raw Data'!B:B,0)),0) | E20: =IFERROR(INDEX('T12 Raw Data'!I:I,MATCH("Meal Income",'T12 Raw Data'!B:B,0)),0) | F20: =IFERROR(INDEX('T12 Raw Data'!J:J,MATCH("Meal Income",'T12 Raw Data'!B:B,0)),0) | G20: =IFERROR(INDEX('T12 Raw Data'!K:K,MATCH("Meal Income",'T12 Raw Data'!B:B,0)),0) | H20: =IFERROR(INDEX('T12 Raw Data'!L:L,MATCH("Meal Income",'T12 Raw Data'!B:B,0)),0) | I20: =IFERROR(INDEX('T12 Raw Data'!M:M,MATCH("Meal Income",'T12 Raw Data'!B:B,0)),0) | J20: =IFERROR(INDEX('T12 Raw Data'!N:N,MATCH("Meal Income",'T12 Raw Data'!B:B,0)),0) | K20: =IFERROR(INDEX('T12 Raw Data'!O:O,MATCH("Meal Income",'T12 Raw Data'!B:B,0)),0) | L20: =IFERROR(INDEX('T12 Raw Data'!P:P,MATCH("Meal Income",'T12 Raw Data'!B:B,0)),0) | M20: =IFERROR(INDEX('T12 Raw Data'!Q:Q,MATCH("Meal Income",'T12 Raw Data'!B:B,0)),0) | N20: =SUM(B20:M20)
A21: Housekeeping Income | B21: =IFERROR(INDEX('T12 Raw Data'!F:F,MATCH("Housekeeping Income",'T12 Raw Data'!B:B,0)),0) | C21: =IFERROR(INDEX('T12 Raw Data'!G:G,MATCH("Housekeeping Income",'T12 Raw Data'!B:B,0)),0) | D21: =IFERROR(INDEX('T12 Raw Data'!H:H,MATCH("Housekeeping Income",'T12 Raw Data'!B:B,0)),0) | E21: =IFERROR(INDEX('T12 Raw Data'!I:I,MATCH("Housekeeping Income",'T12 Raw Data'!B:B,0)),0) | F21: =IFERROR(INDEX('T12 Raw Data'!J:J,MATCH("Housekeeping Income",'T12 Raw Data'!B:B,0)),0) | G21: =IFERROR(INDEX('T12 Raw Data'!K:K,MATCH("Housekeeping Income",'T12 Raw Data'!B:B,0)),0) | H21: =IFERROR(INDEX('T12 Raw Data'!L:L,MATCH("Housekeeping Income",'T12 Raw Data'!B:B,0)),0) | I21: =IFERROR(INDEX('T12 Raw Data'!M:M,MATCH("Housekeeping Income",'T12 Raw Data'!B:B,0)),0) | J21: =IFERROR(INDEX('T12 Raw Data'!N:N,MATCH("Housekeeping Income",'T12 Raw Data'!B:B,0)),0) | K21: =IFERROR(INDEX('T12 Raw Data'!O:O,MATCH("Housekeeping Income",'T12 Raw Data'!B:B,0)),0) | L21: =IFERROR(INDEX('T12 Raw Data'!P:P,MATCH("Housekeeping Income",'T12 Raw Data'!B:B,0)),0) | M21: =IFERROR(INDEX('T12 Raw Data'!Q:Q,MATCH("Housekeeping Income",'T12 Raw Data'!B:B,0)),0) | N21: =SUM(B21:M21)
