Workbook
Name Beds: 'Prop Info'!$B$15
Name EGI: Scenarios!$F$50
Name Total_LPA_Equity: Scenarios!$F$33
Name Total_Payroll: 'Staffing Matrix'!$M$67
Name Units: Scenarios!$B$8

Sheet Cover
A1: ASSISTED LIVING FACILITY — INVESTMENT SUMMARY
A2: Confidential — For Authorized Recipients Only
A3: Template Version 11.0 · Updated 2026-06-16 (RR Analysis hide-zero display + formula strip; dynamic Section R unit-type matrix IL/AL/MC/OTH x6; Prop Info OM/Market-Research/Links reformat) · versioning: whole number = structural, .## = non-structural
A4: PROPERTY INFORMATION
A5: Property Name | B5: ='Prop Info'!B4 -> 0
A6: Location | B6: ='Prop Info'!B5 -> 0
A7: Year Built | B7: ='Prop Info'!B9 -> 0
A8: Total Units (physical rooms) | B8: =Scenarios!F8 -> 0 | C8: =IFERROR('Prop Info'!$B$15,0) -> 0
A9: Gross Sq Ft | B9: ='Prop Info'!B11 -> 0
A10: Asset Class | B10: ='Prop Info'!B13 -> 0
A11: Active Scenario | B11: =Scenarios!B2 -> Actuals (T-12)
A12: Licensed Beds / Occupied Beds (Y1) | B12: =IFERROR('Prop Info'!$B$15,0) -> 0 | C12: / | D12: =IFERROR(Scenarios!F51,0) -> 0 | E12: =IFERROR(Scenarios!F51/'Prop Info'!$B$15,0) -> 0
A13: KEY DEAL METRICS
A14: Metric | B14: Value | C14: / Beds | D14: Returns Metric | E14: Value
A15: Purchase Price | B15: =Scenarios!F7 -> 0 | D15: LP IRR | E15: =Waterfall!B69 -> 0
A16: Price Per Room / Per Bed | B16: =Scenarios!F9 | C16: =IFERROR(Scenarios!F7/'Prop Info'!$B$15,0) -> 0 | D16: GP IRR | E16: =Waterfall!E66 -> 0
A17: Total Acquisition Cost | B17: =Scenarios!F17 | D17: LP Equity Multiple | E17: =IFERROR(Waterfall!B67,0) -> 0
A18: Loan Amount (Total) | B18: =Loans!E4 -> 0 | D18: Y1 Cash-on-Cash | E18: ='P&L'!D126 -> 0
A19: LTV | B19: =IFERROR(Scenarios!F150/Scenarios!F7,0) -> 0 | D19: Year 5 NOI | E19: =IFERROR(INDEX('P&L'!D115:M116,1,Scenarios!F86),0)+IFERROR(INDEX('P&L'!D112:M113,1,Scenarios!F86),0) -> 0
A20: LTC | B20: =IFERROR(Scenarios!F150/Scenarios!F17,0) -> 0 | D20: Exit Year | E20: =Scenarios!F86 -> 0
A21: Equity Required | B21: =Scenarios!F31 -> 0 | D21: Exit Cap Rate | E21: =Waterfall!B6 -> 0
A22: Down Payment % | B22: =Scenarios!F10 -> 0 | D22: Gross Sale Price | E22: =Waterfall!B32 -> 0
A23: Entry Cap Rate | B23: =IFERROR('P&L'!D97/Scenarios!F7,0) -> 0 | D23: Net to Equity (Exit) | E23: =Waterfall!B35 -> 0
A24: Stabilized Cap Rate (Y5) | B24: =IFERROR((IFERROR(INDEX('P&L'!D115:M116,1,Scenarios!F86),0)+IFERROR(INDEX('P&L'!D112:M113,1,Scenarios!F86),0))/Scenarios!F7,0) -> 0 | D24: Avg Annual Return (LP) | E24: =IFERROR((Waterfall!M54-(Waterfall!B9+Waterfall!B10))/(Waterfall!B9+Waterfall!B10)/Scenarios!F86,0) -> 0
A26: CAPITAL STACK
A27: Tranche | B27: Amount | C27: % | D27: Rate | E27: Term (yrs) | F27: Amort (yrs)
A28: Senior Loan (1st) | B28: =Scenarios!F92 -> 0 | C28: =IFERROR(Scenarios!F92/Scenarios!F17,0) -> 0 | D28: =Scenarios!F93 -> 0 | E28: =Scenarios!F124 -> 0 | F28: =Scenarios!F94 -> 0
A29: 2nd Loan | B29: =Scenarios!F128 -> 0 | C29: =IFERROR(Scenarios!F128/Scenarios!F17,0) -> 0 | D29: =Scenarios!F129 -> 0 | E29: =Scenarios!F131 -> 0 | F29: =Scenarios!F130 -> 0
A30: Supplemental | B30: =Scenarios!F135 -> 0 | C30: =IFERROR(Scenarios!F135/Scenarios!F17,0) -> 0 | D30: =Scenarios!F136 -> 0 | E30: =Scenarios!F138 -> 0 | F30: =Scenarios!F137 -> 0
A31: GP Equity | B31: =Scenarios!F32 -> 0 | C31: =Scenarios!F28 -> 0.6 | D31: — | E31: — | F31: —
A32: Class A LP Equity | B32: =Scenarios!F33 -> 0 | C32: =Scenarios!F29 -> 0.4 | D32: =Scenarios!F35 -> 0 | E32: — | F32: —
A33: Class B LP Equity | B33: =Scenarios!F34 -> 0 | C33: =Scenarios!F30 -> 0 | D33: — | E33: — | F33: —
A34: TOTAL | B34: =Scenarios!F31 -> 0 | C34: =IFERROR(Scenarios!F31/Scenarios!F17,0) -> 0 | D34: — | E34: — | F34: —
A36: INVESTOR RETURNS SUMMARY
A37: Metric | B37: Class A LP | C37: Class B LP | D37: LP Combined | E37: GP | F37: Notes
A38: Total Equity Invested | B38: =Waterfall!B9 -> 0 | C38: =Waterfall!B10 -> 0 | D38: =Waterfall!B9+Waterfall!B10 -> 0 | E38: =Waterfall!B8 -> 0 | F38: Capital contributed by each party
A39: Total Distributions | B39: =Waterfall!M55 -> 0 | C39: =Waterfall!M56 -> 0 | D39: =Waterfall!M57 -> 0 | E39: =Waterfall!M58 -> 0 | F39: Operating CF + exit proceeds
A40: Net Profit | B40: =Waterfall!M55-Waterfall!B9 -> 0 | C40: =IFERROR(Waterfall!M56-Waterfall!B10,0) -> 0 | D40: =Waterfall!M57-(Waterfall!B9+Waterfall!B10) -> 0 | E40: =Waterfall!M58-Waterfall!B8 -> 0
A41: Equity Multiple (EM) | B41: =IFERROR(Waterfall!B67,0) -> 0 | C41: =IFERROR(Waterfall!C67,0) -> 0 | D41: =IFERROR(Waterfall!D67,0) -> 0 | E41: =IFERROR(Waterfall!E67,0) -> 0 | F41: Total value returned / capital in
A42: IRR | B42: =Waterfall!B69 -> 0 | C42: =Waterfall!C69 -> 0 | D42: =Waterfall!D69 -> 0 | E42: =Waterfall!E69 -> 0 | F42: Includes exit proceeds
A43: Avg Annual Return (simple, incl. exit) | B43: =IFERROR((Waterfall!M55-Waterfall!B9)/Waterfall!B9/Scenarios!F86,0) -> 0 | C43: =IFERROR((Waterfall!M56-Waterfall!B10)/Waterfall!B10/Scenarios!F86,0) -> 0 | D43: =IFERROR((Waterfall!M57-(Waterfall!B9+Waterfall!B10))/(Waterfall!B9+Waterfall!B10)/Scenarios!F86,0) -> 0 | E43: =IFERROR(IF(Waterfall!B8=0,"N/A",(Waterfall!M58-Waterfall!B8)/Waterfall!B8/Scenarios!F86),0) -> N/A | F43: Simple: (total distributions − equity) ÷ equity ÷ hold yrs. Not compounded.
A44: Avg Cash-on-Cash Return | B44: ='P&L'!D127 -> 0 | C44: =IFERROR(IF(Waterfall!B10=0,0,AVERAGE(OFFSET(Waterfall!B53,0,0,1,MIN(Scenarios!F86,10)))/Waterfall!B10),0) -> 0 | D44: ='P&L'!D129 -> 0 | E44: =IFERROR(IF(Waterfall!B8=0,0,AVERAGE(OFFSET(Waterfall!B55,0,0,1,MIN(Scenarios!F86,10)))/Waterfall!B8),0) -> 0 | F44: Annual operating cash ÷ equity invested
A45: EXIT & DEAL METRICS
A46: Hold Period (yrs) | B46: =Scenarios!F86 -> 0
A47: Exit Cap Rate | B47: =Waterfall!B6 -> 0
A48: Exit Year NOI | B48: =IFERROR(INDEX('P&L'!D115:M116,1,Scenarios!F86)+INDEX('P&L'!D112:M113,1,Scenarios!F86),0) -> 0 | F48: Y5 NOI
A49: Gross Sale Price | B49: =Waterfall!B32 -> 0 | F49: NOI ÷ exit cap
A50: Less: Loan Payoff | B50: =Waterfall!B34 -> 0 | F50: Amortized balance
A51: Net Sale Proceeds | B51: =Waterfall!B35 -> 0 | F51: After selling costs & loan

Sheet Prop Info
A1: PROPERTY INFORMATION & MARKET DATA
A2: Blue = manual input. Use the AI Market Research tool (separate app) to auto-populate market fields.
A3: PROPERTY DETAILS | B3: OM Data
A4: Property Name
A5: Location / Address
A6: # Units
A7: # Buildings
A8: Height (stories)
A9: Year Built
A10: Lot Size (acres)
A11: Gross Sq Ft
A12: Parking Spaces
A13: Asset Class (IL/AL/MC/Other/Mix) | C13: Other Care Type name (deal/state):
A14: License Type
A15: Licensed Bed Count
A16: IL Units
A17: AL Units
A18: MC Units
A19: ="Other Care ("&$D$13&") Units" -> Other Care () Units
A20: Occupied Beds — Total | B20: =SUM(B21:B24) -> 0
A21: Occupied Beds — IL
A22: Occupied Beds — AL
A23: Occupied Beds — MC
A24: ="Occupied Beds — Other Care ("&$D$13&")" -> Occupied Beds — Other Care ()
A25: MARKET DATA | B25: OM Data | C25: Market Research Data | D25: Links
A26: City / Market
A27: MSA Name
A28: MSA Population
A29: City Population
A30: MSA Population Growth Rate
A31: City Population Growth Rate
A32: Senior 65+ Population
A33: Senior 65+ Growth Rate
A34: Avg Household Income
A35: Median Income
A36: School Ratings (1-10)
A37: COMPETITIVE MARKET | B37: OM Data | C37: Market Research Data | D37: Links
A38: Avg Monthly Base Rent — IL
A39: Avg Monthly Base Rent — AL
A40: Avg Monthly Base Rent — MC
A41: Avg Care Services Fee
A42: Competitor Occupancy — IL
A43: Competitor Occupancy — AL
A44: Competitor Occupancy — MC
A45: ="Competitor Occupancy — Other Care ("&$D$13&")" -> Competitor Occupancy — Other Care ()
A46: New Supply — Beds Under Construction
A47: Market Penetration Rate
A48: UTILITIES
A49: Electric Meter
A50: Water Meter
A51: Gas
A52: Trash
A53: OTHER NOTES | B53: OM Data | C53: Market Research Data | D53: Links
A54: Other Property Information
A55: Other Market Information
A56: Survey / Regulatory Notes
A57: Value-Add Thesis

Sheet Scenarios
A1: SIDE-BY-SIDE SCENARIO ANALYSIS — "The 10-Minute Offer"
A2: Active Scenario → | B2: Actuals (T-12)
A3: Selecting an active scenario drives P&L, Cover Sheet, and Waterfall calculations. All 4 columns always visible for comparison.
A4: Line Item | B4: Actuals (T-12) | C4: 2. My Version | D4: 3. Projected | E4: 4. Best Scenario | F4: Active Scenario | G4: Licensed Beds / $/Bed | H4: Benchmark
A5: ACQUISITION
A6: Asking Price | C6: =B6 -> 0 | D6: =C6 -> 0 | E6: =D6 -> 0 | F6: =CHOOSE(MATCH(B$2,$B$4:$E$4,0),B6,C6,D6,E6) -> 0 | G6: =IFERROR(F6/F$8,0) -> 0 | H6: $8–16M typical 60-unit AL/MC
A7: Purchase Price / Offer | C7: =B7 -> 0 | D7: =C7 -> 0 | E7: =D7 -> 0 | F7: =CHOOSE(MATCH(B$2,$B$4:$E$4,0),B7,C7,D7,E7) -> 0 | G7: =IFERROR(F7/F$8,0) -> 0 | H7: Offer 5–15% below ask; value-add
A8: # Units (rooms) / Licensed Beds | C8: =Units -> 0 | D8: =C8 -> 0 | E8: =D8 -> 0 | F8: =CHOOSE(MATCH(B$2,$B$4:$E$4,0),B8,C8,D8,E8) -> 0 | G8: ='Prop Info'!$B$15 -> 0 | H8: Licensed beds from Prop Info — drives GPR. Units = physical rooms.
A9: Price Per Unit (physical room) | B9: =IFERROR(B7/B8,"") | C9: =IFERROR(C7/C8,"") | D9: =IFERROR(D7/D8,"") | E9: =IFERROR(E7/E8,"") | F9: =IFERROR(CHOOSE(MATCH(B$2,$B$4:$E$4,0),B9,C9,D9,E9),"") | G9: =IFERROR(F7/'Prop Info'!$B$15,"") | H9: Price per licensed bed = purchase price ÷ licensed beds
A10: Down Payment % | C10: =B10 -> 0 | D10: =C10 -> 0 | E10: =D10 -> 0 | F10: =CHOOSE(MATCH(B$2,$B$4:$E$4,0),B10,C10,D10,E10) -> 0 | H10: 25–35% down; 65–75% LTV target
A11: Down Payment $ | B11: =B10*B7 -> 0 | C11: =C10*C7 -> 0 | D11: =D10*D7 -> 0 | E11: =E10*E7 -> 0 | F11: =CHOOSE(MATCH(B$2,$B$4:$E$4,0),B11,C11,D11,E11) -> 0 | G11: =IFERROR(F11/F$8,0) -> 0 | H11: Auto-calculated from down payment
A12: Repairs / CapEx at Close | B12: =Capex!$D$51 -> 0 | C12: =B12 -> 0 | D12: =Capex!$D$51 -> 0 | E12: =Capex!$D$51 -> 0 | F12: =CHOOSE(MATCH(B$2,$B$4:$E$4,0),B12,C12,D12,E12) -> 0 | G12: =IFERROR(F12/F$8,0) -> 0 | H12: Get contractor bid at LOI stage
A13: Operating Reserves | B13: =(B124/12)*$G$13 -> 0 | C13: =B13 -> 0 | D13: =C13 -> 0 | E13: =D13 -> 0 | F13: =CHOOSE(MATCH(B$2,$B$4:$E$4,0),B13,C13,D13,E13) -> 0 | G13: 1 | H13: 3–6 months operating expenses
A14: Est. Closing Costs | B14: ='Acquisition Costs'!$D$37 | C14: ='Acquisition Costs'!$D$37 | D14: ='Acquisition Costs'!$D$37 | E14: ='Acquisition Costs'!$D$37 | F14: =CHOOSE(MATCH(B$2,$B$4:$E$4,0),B14,C14,D14,E14) | G14: =IFERROR(F14/F7,"") | H14: 1.5–2.5% of purchase price
A15: Acquisition Fee (%) | B15: 0 | C15: =B15 -> 0 | D15: =C15 -> 0 | E15: =D15 -> 0 | F15: =CHOOSE(MATCH(B$2,$B$4:$E$4,0),B15,C15,D15,E15) -> 0 | H15: 0.5–1.5% acq fee standard
A16: Acquisition Fee ($) | B16: =B15*B7 -> 0 | C16: =C15*C7 -> 0 | D16: =D15*D7 -> 0 | E16: =E15*E7 -> 0 | F16: =CHOOSE(MATCH(B$2,$B$4:$E$4,0),B16,C16,D16,E16) -> 0 | G16: =IFERROR(F16/F$8,0) -> 0 | H16: Auto-calculated
A17: TOTAL ACQUISITION COST | B17: =IFERROR(B7+B12+B13+B14+B16,"") | C17: =IFERROR(C7+C12+C13+C14+C16,"") | D17: =IFERROR(D7+D12+D13+D14+D16,"") | E17: =IFERROR(E7+E12+E13+E14+E16,"") | F17: =IFERROR(CHOOSE(MATCH(B$2,$B$4:$E$4,0),B17,C17,D17,E17),"") | G17: =IFERROR(F17/F$8,"") | H17: Auto-calculated total cost
A19: DEBT STRUCTURE
A20: Loan Amount (1st) | B20: =B141 -> 0 | C20: =C141 -> 0 | D20: =D141 -> 0 | E20: =E141 -> 0 | F20: =CHOOSE(MATCH(B$2,$B$4:$E$4,0),B20,C20,D20,E20) -> 0 | H20: 60–70% LTV senior; 75% bridge max
A21: Loan Amount (2nd) | B21: =B148 -> 0 | C21: =C148 -> 0 | D21: =D148 -> 0 | E21: =E148 -> 0 | F21: =CHOOSE(MATCH(B$2,$B$4:$E$4,0),B21,C21,D21,E21) -> 0 | H21: $0 if no mezz; up to 10% of stack
A22: Supplemental Loan | B22: =B155 -> 0 | C22: =C155 -> 0 | D22: =D155 -> 0 | E22: =E155 -> 0 | F22: =CHOOSE(MATCH(B$2,$B$4:$E$4,0),B22,C22,D22,E22) -> 0 | H22: $0 supplemental; add if SBA/seller
A23: Total Debt | B23: =B20+B21+B22 -> 0 | C23: =C20+C21+C22 -> 0 | D23: =D20+D21+D22 -> 0 | E23: =E20+E21+E22 -> 0 | F23: =CHOOSE(MATCH(B$2,$B$4:$E$4,0),B23,C23,D23,E23) -> 0 | H23: Auto-calculated total debt
A24: LTV (Loan/Purchase Price) | B24: =IFERROR(B23/B7,0) -> 0 | C24: =IFERROR(C23/C7,0) -> 0 | D24: =IFERROR(D23/D7,0) -> 0 | E24: =IFERROR(E23/E7,0) -> 0 | F24: =CHOOSE(MATCH(B$2,$B$4:$E$4,0),B24,C24,D24,E24) -> 0 | H24: Target ≤70% LTV (senior only)
A25: LTC (Loan/Total Acq. Cost) | B25: =IFERROR(B23/B17,0) -> 0 | C25: =IFERROR(C23/C17,0) -> 0 | D25: =IFERROR(D23/D17,0) -> 0 | E25: =IFERROR(E23/E17,0) -> 0 | F25: =CHOOSE(MATCH(B$2,$B$4:$E$4,0),B25,C25,D25,E25) -> 0 | H25: Target ≤80–85% LTC (value-add)
A27: EQUITY STRUCTURE
A28: GP Ownership % | B28: 0.6 | C28: =B28 -> 0.6 | D28: =C28 -> 0.6 | E28: =D28 -> 0.6 | F28: =CHOOSE(MATCH(B$2,$B$4:$E$4,0),B28,C28,D28,E28) -> 0.6 | H28: GP co-invest 5–15% of total equity
A29: Class A LP % | B29: =1-B28 -> 0.4 | C29: =1-C28 -> 0.4 | D29: =1-D28 -> 0.4 | E29: =1-E28 -> 0.4 | F29: =CHOOSE(MATCH(B$2,$B$4:$E$4,0),B29,C29,D29,E29) -> 0.4 | H29: Class A LP 40–65% of total equity
A30: Class B LP % (auto) | B30: =1-B28-B29 -> 0 | C30: =1-C28-C29 -> 0 | D30: =1-D28-D29 -> 0 | E30: =1-E28-E29 -> 0 | F30: =CHOOSE(MATCH(B$2,$B$4:$E$4,0),B30,C30,D30,E30) -> 0 | H30: Class B LP 20–40% of total equity
A31: Total Equity (Acq Cost − Debt) | B31: =IFERROR(B17-B170,0) -> 0 | C31: =IFERROR(C17-C170,0) -> 0 | D31: =IFERROR(D17-D170,0) -> 0 | E31: =IFERROR(E17-E170,0) -> 0 | F31: =CHOOSE(MATCH(B$2,$B$4:$E$4,0),B31,C31,D31,E31) -> 0 | H31: Auto-calculated
A32: GP Equity ($) | C32: =B32 -> 0 | D32: =C32 -> 0 | E32: =D32 -> 0 | F32: =CHOOSE(MATCH(B$2,$B$4:$E$4,0),B32,C32,D32,E32) -> 0 | H32: Enter GP co-invest $ directly — not tied to GP Ownership %
A33: Class A LP Equity ($) | B33: =B31-B32 -> 0 | C33: =C31-C32 -> 0 | D33: =D31-D32 -> 0 | E33: =E31-E32 -> 0 | F33: =CHOOSE(MATCH(B$2,$B$4:$E$4,0),B33,C33,D33,E33) -> 0 | H33: Total Equity − GP co-invest. GP can be $0 (all-LP deal).
A34: Class B LP Equity ($) | B34: =B30*B31 -> 0 | C34: =C30*C31 -> 0 | D34: =D30*D31 -> 0 | E34: =E30*E31 -> 0 | F34: =CHOOSE(MATCH(B$2,$B$4:$E$4,0),B34,C34,D34,E34) -> 0 | H34: Auto-calculated
A35: Class A Preferred Return % | B35: 0 | C35: =B35 -> 0 | D35: =C35 -> 0 | E35: =D35 -> 0 | F35: =CHOOSE(MATCH(B$2,$B$4:$E$4,0),B35,C35,D35,E35) -> 0 | H35: Class A pref: 6–9% typical
A36: GP Promote % (defaults to GP% — edit to override) | B36: =B28 -> 0.6 | C36: =C28 -> 0.6 | D36: =D28 -> 0.6 | E36: =E28 -> 0.6 | F36: =CHOOSE(MATCH(B$2,$B$4:$E$4,0),B36,C36,D36,E36) -> 0.6 | H36: Promote: 20–30% GP typical. Edit directly.
A37: INCOME (YEAR 1 SNAPSHOT) — 4-Scenario Model
A38: ── INDEPENDENT LIVING (IL) ──
A39: Licensed Beds — IL | B39: 0 | C39: =B39 -> 0 | D39: =C39 -> 0 | E39: =D39 -> 0 | F39: =CHOOSE(MATCH(B$2,$B$4:$E$4,0),B39,C39,D39,E39) -> 0 | H39: Independent Living bed count
A40: Avg Monthly Rate — IL | B40: 0 | C40: =B40 -> 0 | D40: =C40 -> 0 | E40: =D40 -> 0 | F40: =CHOOSE(MATCH(B$2,$B$4:$E$4,0),B40,C40,D40,E40) -> 0 | H40: IL blended market rate — pull from rent roll
A41: GPR — IL | B41: =B39*B40*12 -> 0 | C41: =C39*C40*12 -> 0 | D41: =D39*D40*12 -> 0 | E41: =E39*E40*12 -> 0 | F41: =CHOOSE(MATCH(B$2,$B$4:$E$4,0),B41,C41,D41,E41) -> 0 | G41: =IFERROR(F41/F$63/12,0) -> 0 | H41: Annual gross potential rent at full IL occupancy
A42: Vacancy % — IL | B42: 0 | C42: =B42 -> 0 | D42: =C42 -> 0 | E42: =D42 -> 0 | F42: =CHOOSE(MATCH(B$2,$B$4:$E$4,0),B42,C42,D42,E42) -> 0 | H42: 10% typical stabilized
A43: Occupied Beds — IL | B43: =ROUND(B39*(1-B42),0) -> 0 | C43: =ROUND(C39*(1-C42),0) -> 0 | D43: =ROUND(D39*(1-D42),0) -> 0 | E43: =ROUND(E39*(1-E42),0) -> 0 | F43: =CHOOSE(MATCH(B$2,$B$4:$E$4,0),B43,C43,D43,E43) -> 0 | H43: IL occupied = IL beds × (1 − IL vac%)
A44: ── ASSISTED LIVING (AL) ──
A45: Licensed Beds — AL | B45: 0 | C45: =B45 -> 0 | D45: =C45 -> 0 | E45: =D45 -> 0 | F45: =CHOOSE(MATCH(B$2,$B$4:$E$4,0),B45,C45,D45,E45) -> 0 | H45: Assisted Living bed count
A46: Avg Monthly Rate — AL | B46: 0 | C46: =B46 -> 0 | D46: =C46 -> 0 | E46: =D46 -> 0 | F46: =CHOOSE(MATCH(B$2,$B$4:$E$4,0),B46,C46,D46,E46) -> 0 | H46: AL median ~$4,774/mo nationally (2024); local range varies
A47: GPR — AL | B47: =B45*B46*12 -> 0 | C47: =C45*C46*12 -> 0 | D47: =D45*D46*12 -> 0 | E47: =E45*E46*12 -> 0 | F47: =CHOOSE(MATCH(B$2,$B$4:$E$4,0),B47,C47,D47,E47) -> 0 | G47: =IFERROR(F47/F$63/12,0) -> 0 | H47: Annual gross potential rent at full AL occupancy
A48: Vacancy % — AL | B48: 0 | C48: =B48 -> 0 | D48: =C48 -> 0 | E48: =D48 -> 0 | F48: =CHOOSE(MATCH(B$2,$B$4:$E$4,0),B48,C48,D48,E48) -> 0 | H48: 12% typical value-add
A49: Occupied Beds — AL | B49: =ROUND(B45*(1-B48),0) -> 0 | C49: =ROUND(C45*(1-C48),0) -> 0 | D49: =ROUND(D45*(1-D48),0) -> 0 | E49: =ROUND(E45*(1-E48),0) -> 0 | F49: =CHOOSE(MATCH(B$2,$B$4:$E$4,0),B49,C49,D49,E49) -> 0 | H49: AL occupied = AL beds × (1 − AL vac%)
A50: ── MEMORY CARE (MC) ──
A51: Licensed Beds — MC | B51: 0 | C51: =B51 -> 0 | D51: =C51 -> 0 | E51: =D51 -> 0 | F51: =CHOOSE(MATCH(B$2,$B$4:$E$4,0),B51,C51,D51,E51) -> 0 | H51: Memory Care bed count
A52: Avg Monthly Rate — MC | B52: 0 | C52: =B52 -> 0 | D52: =C52 -> 0 | E52: =D52 -> 0 | F52: =CHOOSE(MATCH(B$2,$B$4:$E$4,0),B52,C52,D52,E52) -> 0 | H52: MC ~$6,160/mo nationally (2024); premium 25-40% over AL
A53: GPR — MC | B53: =B51*B52*12 -> 0 | C53: =C51*C52*12 -> 0 | D53: =D51*D52*12 -> 0 | E53: =E51*E52*12 -> 0 | F53: =CHOOSE(MATCH(B$2,$B$4:$E$4,0),B53,C53,D53,E53) -> 0 | G53: =IFERROR(F53/F$63/12,0) -> 0 | H53: Annual gross potential rent at full MC occupancy
A54: Vacancy % — MC | B54: 0 | C54: =B54 -> 0 | D54: =C54 -> 0 | E54: =D54 -> 0 | F54: =CHOOSE(MATCH(B$2,$B$4:$E$4,0),B54,C54,D54,E54) -> 0 | H54: MC typically tighter
A55: Occupied Beds — MC | B55: =ROUND(B51*(1-B54),0) -> 0 | C55: =ROUND(C51*(1-C54),0) -> 0 | D55: =ROUND(D51*(1-D54),0) -> 0 | E55: =ROUND(E51*(1-E54),0) -> 0 | F55: =CHOOSE(MATCH(B$2,$B$4:$E$4,0),B55,C55,D55,E55) -> 0 | H55: MC occupied = MC beds × (1 − MC vac%)
A56: ="── OTHER CARE ("&'Prop Info'!$D$13&") ──" -> ── OTHER CARE () ──
A57: =" Licensed Beds — Other Care ("&'Prop Info'!$D$13&")" -> Licensed Beds — Other Care () | B57: 0 | C57: =B57 -> 0 | D57: =C57 -> 0 | E57: =D57 -> 0 | F57: =CHOOSE(MATCH(B$2,$B$4:$E$4,0),B57,C57,D57,E57) -> 0 | H57: RHA (Residential Homes for the Aged, TN) bed count
A58: =" Avg Monthly Rate — Other Care ("&'Prop Info'!$D$13&")" -> Avg Monthly Rate — Other Care () | B58: 0 | C58: =B58 -> 0 | D58: =C58 -> 0 | E58: =D58 -> 0 | F58: =CHOOSE(MATCH(B$2,$B$4:$E$4,0),B58,C58,D58,E58) -> 0 | H58: RHA blended monthly rate — typically below AL
A59: =" GPR — Other Care ("&'Prop Info'!$D$13&")" -> GPR — Other Care () | B59: =B57*B58*12 -> 0 | C59: =C57*C58*12 -> 0 | D59: =D57*D58*12 -> 0 | E59: =E57*E58*12 -> 0 | F59: =CHOOSE(MATCH(B$2,$B$4:$E$4,0),B59,C59,D59,E59) -> 0 | G59: =IFERROR(F59/F$63/12,0) -> 0 | H59: Annual gross potential rent at full RHA occupancy
A60: =" Vacancy % — Other Care ("&'Prop Info'!$D$13&")" -> Vacancy % — Other Care () | B60: 0 | C60: =B60 -> 0 | D60: =C60 -> 0 | E60: =D60 -> 0 | F60: =CHOOSE(MATCH(B$2,$B$4:$E$4,0),B60,C60,D60,E60) -> 0 | H60: RHA vacancy assumption
A61: =" Occupied Beds — Other Care ("&'Prop Info'!$D$13&")" -> Occupied Beds — Other Care () | B61: =ROUND(B57*(1-B60),0) -> 0 | C61: =ROUND(C57*(1-C60),0) -> 0 | D61: =ROUND(D57*(1-D60),0) -> 0 | E61: =ROUND(E57*(1-E60),0) -> 0 | F61: =CHOOSE(MATCH(B$2,$B$4:$E$4,0),B61,C61,D61,E61) -> 0 | H61: RHA occupied = RHA beds × (1 − RHA vac%)
A62: ── TOTALS & OTHER INCOME ──
A63: Total Licensed Beds | B63: =B39+B45+B51+B57 -> 0 | C63: =C39+C45+C51+C57 -> 0 | D63: =D39+D45+D51+D57 -> 0 | E63: =E39+E45+E51+E57 -> 0 | F63: =CHOOSE(MATCH(B$2,$B$4:$E$4,0),B63,C63,D63,E63) -> 0 | H63: Sum of IL+AL+MC+RHA licensed beds — must match Prop Info!B15
A64: Total Occupied Beds | B64: =B43+B49+B55+B61 -> 0 | C64: =C43+C49+C55+C61 -> 0 | D64: =D43+D49+D55+D61 -> 0 | E64: =E43+E49+E55+E61 -> 0 | F64: =CHOOSE(MATCH(B$2,$B$4:$E$4,0),B64,C64,D64,E64) -> 0 | H64: Total occupied beds — drives census-based metrics
A65: TOTAL GROSS POTENTIAL RENT | B65: =B41+B47+B53+B59 -> 0 | C65: =C41+C47+C53+C59 -> 0 | D65: =D41+D47+D53+D59 -> 0 | E65: =E41+E47+E53+E59 -> 0 | F65: =CHOOSE(MATCH(B$2,$B$4:$E$4,0),B65,C65,D65,E65) -> 0 | H65: beds × rate × 12 by level
A66: Blended Vacancy % (GPR-Wtd) | B66: =IFERROR((B42*B41+B48*B47+B54*B53+B60*B59)/B65,0) -> 0 | C66: =IFERROR((C42*C41+C48*C47+C54*C53+C60*C59)/C65,0) -> 0 | D66: =IFERROR((D42*D41+D48*D47+D54*D53+D60*D59)/D65,0) -> 0 | E66: =IFERROR((E42*E41+E48*E47+E54*E53+E60*E59)/E65,0) -> 0 | F66: =CHOOSE(MATCH(B$2,$B$4:$E$4,0),B66,C66,D66,E66) -> 0 | H66: GPR-weighted across IL/AL/MC/RHA: Σ(vac%×GPR) ÷ Total_GPR
A67: Vacancy ($) | B67: =-B66*B65 -> 0 | C67: =-C66*C65 -> 0 | D67: =-D66*D65 -> 0 | E67: =-E66*E65 -> 0 | F67: =CHOOSE(MATCH(B$2,$B$4:$E$4,0),B67,C67,D67,E67) -> 0 | G67: =IFERROR(F67/F$76,0) -> 0 | H67: Vacancy $ = blended vac% × Total GPR (negative)
A68: Loss to Lease % | B68: 0 | C68: =B68 -> 0 | D68: =C68 -> 0 | E68: =D68 -> 0 | F68: =CHOOSE(MATCH(B$2,$B$4:$E$4,0),B68,C68,D68,E68) -> 0 | H68: Loss-to-lease: rate concessions vs market rate
A69: Loss to Lease ($) | B69: =-B68*B65 -> 0 | C69: =-C68*C65 -> 0 | D69: =-D68*D65 -> 0 | E69: =-E68*E65 -> 0 | F69: =CHOOSE(MATCH(B$2,$B$4:$E$4,0),B69,C69,D69,E69) -> 0 | G69: =IFERROR(F69/F$76,0) -> 0 | H69: Loss to lease $ = -LtL% × Total GPR
A70: Concessions / Bad Debt % | B70: 0 | C70: =B70 -> 0 | D70: =C70 -> 0 | E70: =D70 -> 0 | F70: =CHOOSE(MATCH(B$2,$B$4:$E$4,0),B70,C70,D70,E70) -> 0 | H70: Concessions/bad debt: 1-3% of GPR typical
A71: Concessions / Bad Debt ($) | B71: =-B70*B65 -> 0 | C71: =-C70*C65 -> 0 | D71: =-D70*D65 -> 0 | E71: =-E70*E65 -> 0 | F71: =CHOOSE(MATCH(B$2,$B$4:$E$4,0),B71,C71,D71,E71) -> 0 | G71: =IFERROR(F71/F$76,0) -> 0 | H71: Concessions $ = -Conc% × Total GPR
A72: Care Services Fees % | B72: 0 | C72: =B72 -> 0 | D72: =C72 -> 0 | E72: =D72 -> 0 | F72: =CHOOSE(MATCH(B$2,$B$4:$E$4,0),B72,C72,D72,E72) -> 0 | H72: Care services upcharges by acuity level
A73: Care Services Fees ($) | B73: =B72*B65 -> 0 | C73: =C72*C65 -> 0 | D73: =D72*D65 -> 0 | E73: =E72*E65 -> 0 | F73: =CHOOSE(MATCH(B$2,$B$4:$E$4,0),B73,C73,D73,E73) -> 0 | G73: =IFERROR(F73/F$76,0) -> 0 | H73: Care services $ = % × Total GPR (positive add-back)
A74: 2nd Person Revenue | B74: 0 | C74: =B74 -> 0 | D74: =C74 -> 0 | E74: =D74 -> 0 | F74: =CHOOSE(MATCH(B$2,$B$4:$E$4,0),B74,C74,D74,E74) -> 0 | G74: =IFERROR(F74/F$76,0) -> 0 | H74: Spousal/couples fee
A75: Other Income | B75: 0 | C75: =B75 -> 0 | D75: =C75 -> 0 | E75: =D75 -> 0 | F75: =CHOOSE(MATCH(B$2,$B$4:$E$4,0),B75,C75,D75,E75) -> 0 | G75: =IFERROR(F75/F$76,0) -> 0 | H75: Ancillary services, beauty, etc.
A76: EFFECTIVE GROSS INCOME | B76: =B65+B67+B69+B71+B73+B74+B75 -> 0 | C76: =C65+C67+C69+C71+C73+C74+C75 -> 0 | D76: =D65+D67+D69+D71+D73+D74+D75 -> 0 | E76: =E65+E67+E69+E71+E73+E74+E75 -> 0 | F76: =CHOOSE(MATCH(B$2,$B$4:$E$4,0),B76,C76,D76,E76) -> 0 | G76: =IFERROR(F76/F$65,0) -> 0 | H76: EGI = GPR less vacancy/LtL/conc plus care/2P/other
A78: EXPENSES (YEAR 1)
A79: Line Item | B79: Actuals (T-12) | C79: 2. My Version | D79: 3. Projected | E79: =E4 -> 4. Best Scenario | F79: Active Scenario | G79: $/Bed | % EGI | H79: Notes
A80: ── DIRECT LABOR ──
A81: Care staff labor (AL / MC / IL) | C81: =B81 -> 0 | D81: =C81 -> 0 | E81: =D81 -> 0 | F81: =CHOOSE(MATCH(B$2,$B$4:$E$4,0),B81,C81,D81,E81) -> 0 | G81: =IFERROR(F81/F$76,0) -> 0 | H81: Care labor: 20-30% EGI — largest line; tracks acuity & ratios
A82: Wellness / care coordinators | C82: =B82 -> 0 | D82: =C82 -> 0 | E82: =D82 -> 0 | F82: =CHOOSE(MATCH(B$2,$B$4:$E$4,0),B82,C82,D82,E82) -> 0 | G82: =IFERROR(F82/F$76,0) -> 0 | H82: Wellness/nursing leads: 2-4% EGI — RN/LPN salaries
A83: Contract / agency labor | C83: =B83 -> 0 | D83: =C83 -> 0 | E83: =D83 -> 0 | F83: =CHOOSE(MATCH(B$2,$B$4:$E$4,0),B83,C83,D83,E83) -> 0 | G83: =IFERROR(F83/F$76,0) -> 0 | H83: Agency labor: 0-5% EGI stabilized; can spike 5-15% in lease-up
A84: Activities labor | C84: =B84 -> 0 | D84: =C84 -> 0 | E84: =D84 -> 0 | F84: =CHOOSE(MATCH(B$2,$B$4:$E$4,0),B84,C84,D84,E84) -> 0 | G84: =IFERROR(F84/F$76,0) -> 0 | H84: Activities labor: 1-2% EGI — life enrichment program
A85: Dining / food service labor | C85: =B85 -> 0 | D85: =C85 -> 0 | E85: =D85 -> 0 | F85: =CHOOSE(MATCH(B$2,$B$4:$E$4,0),B85,C85,D85,E85) -> 0 | G85: =IFERROR(F85/F$76,0) -> 0 | H85: Dining labor: 4-6% EGI — chef, cooks, servers, dishwashers
A86: Maintenance & housekeeping labor | C86: =B86 -> 0 | D86: =C86 -> 0 | E86: =D86 -> 0 | F86: =CHOOSE(MATCH(B$2,$B$4:$E$4,0),B86,C86,D86,E86) -> 0 | G86: =IFERROR(F86/F$76,0) -> 0 | H86: Maintenance & housekeeping labor: 2-4% EGI
A87: Administrative labor | C87: =B87 -> 0 | D87: =C87 -> 0 | E87: =D87 -> 0 | F87: =CHOOSE(MATCH(B$2,$B$4:$E$4,0),B87,C87,D87,E87) -> 0 | G87: =IFERROR(F87/F$76,0) -> 0 | H87: Administrative labor: 3-5% EGI — ED, business office, sales
A88: Bonus wages | C88: =B88 -> 0 | D88: =C88 -> 0 | E88: =D88 -> 0 | F88: =CHOOSE(MATCH(B$2,$B$4:$E$4,0),B88,C88,D88,E88) -> 0 | G88: =IFERROR(F88/F$76,0) -> 0 | H88: Bonus wages: 0-1% EGI — incentive comp
A89: Total Direct Labor | B89: =SUM(B81:B88) -> 0 | C89: =SUM(C81:C88) -> 0 | D89: =SUM(D81:D88) -> 0 | E89: =SUM(E81:E88) -> 0 | F89: =CHOOSE(MATCH(B$2,$B$4:$E$4,0),B89,C89,D89,E89) -> 0 | G89: =IFERROR(F89/F$76,0) -> 0 | H89: Total Direct Labor: 35-45% EGI stabilized AL/MC
A90: ── PAYROLL BURDEN ──
A91: Overtime wages | C91: =B91 -> 0 | D91: =C91 -> 0 | E91: =D91 -> 0 | F91: =CHOOSE(MATCH(B$2,$B$4:$E$4,0),B91,C91,D91,E91) -> 0 | G91: =IFERROR(F91/F$76,0) -> 0 | H91: Overtime: 1-3% EGI — agency/turnover leading indicator
A92: PTO wages | C92: =B92 -> 0 | D92: =C92 -> 0 | E92: =D92 -> 0 | F92: =CHOOSE(MATCH(B$2,$B$4:$E$4,0),B92,C92,D92,E92) -> 0 | G92: =IFERROR(F92/F$76,0) -> 0 | H92: PTO accrual: 1-2% EGI — vacation/sick wages
A93: Payroll taxes | C93: =B93 -> 0 | D93: =C93 -> 0 | E93: =D93 -> 0 | F93: =CHOOSE(MATCH(B$2,$B$4:$E$4,0),B93,C93,D93,E93) -> 0 | G93: =IFERROR(F93/F$76,0) -> 0 | H93: Payroll taxes: 3-4% EGI (~8-10% of wages: FICA/SUTA/FUTA)
A94: Employee benefits (health/dental/vision) | C94: =B94 -> 0 | D94: =C94 -> 0 | E94: =D94 -> 0 | F94: =CHOOSE(MATCH(B$2,$B$4:$E$4,0),B94,C94,D94,E94) -> 0 | G94: =IFERROR(F94/F$76,0) -> 0 | H94: Health/dental/vision: 4-7% EGI (15-25% of base wages)
A95: Workers' comp insurance | C95: =B95 -> 0 | D95: =C95 -> 0 | E95: =D95 -> 0 | F95: =CHOOSE(MATCH(B$2,$B$4:$E$4,0),B95,C95,D95,E95) -> 0 | G95: =IFERROR(F95/F$76,0) -> 0 | H95: Workers' comp: 1-2% EGI (2-5% of wages; high in care)
A96: Employee 401(k) / retirement | C96: =B96 -> 0 | D96: =C96 -> 0 | E96: =D96 -> 0 | F96: =CHOOSE(MATCH(B$2,$B$4:$E$4,0),B96,C96,D96,E96) -> 0 | G96: =IFERROR(F96/F$76,0) -> 0 | H96: 401(k)/retirement match: 0-1% EGI (1-4% of wages)
A97: Total Payroll Burden | B97: =SUM(B91:B96) -> 0 | C97: =SUM(C91:C96) -> 0 | D97: =SUM(D91:D96) -> 0 | E97: =SUM(E91:E96) -> 0 | F97: =CHOOSE(MATCH(B$2,$B$4:$E$4,0),B97,C97,D97,E97) -> 0 | G97: =IFERROR(F97/F$76,0) -> 0 | H97: Total Payroll Burden: 10-15% EGI (25-35% load on labor)
A98: ── NON-LABOR OPEX ──
A99: Food cost | C99: =B99 -> 0 | D99: =C99 -> 0 | E99: =D99 -> 0 | F99: =CHOOSE(MATCH(B$2,$B$4:$E$4,0),B99,C99,D99,E99) -> 0 | G99: =IFERROR(TEXT(F99/F$76,"0.0%")&" | "&TEXT(F99/F64/365,"$0.00"),"") | H99: Food cost: 4-6% EGI — $8-12 per resident per day target
A100: Dining & kitchen supplies | C100: =B100 -> 0 | D100: =C100 -> 0 | E100: =D100 -> 0 | F100: =CHOOSE(MATCH(B$2,$B$4:$E$4,0),B100,C100,D100,E100) -> 0 | G100: =IFERROR(F100/F$76,0) -> 0 | H100: Dining/kitchen supplies: 0.5-1% EGI — consumables, smallwares
A101: Nursing & care supplies | C101: =B101 -> 0 | D101: =C101 -> 0 | E101: =D101 -> 0 | F101: =CHOOSE(MATCH(B$2,$B$4:$E$4,0),B101,C101,D101,E101) -> 0 | G101: =IFERROR(F101/F$76,0) -> 0 | H101: Nursing/care supplies: 1-2% EGI — incontinence, PPE, wound
A102: Recreation & activity supplies | C102: =B102 -> 0 | D102: =C102 -> 0 | E102: =D102 -> 0 | F102: =CHOOSE(MATCH(B$2,$B$4:$E$4,0),B102,C102,D102,E102) -> 0 | G102: =IFERROR(F102/F$76,0) -> 0 | H102: Activity supplies: 0.2-0.5% EGI — programming materials
A103: R&M — fixed (contracts) | C103: =B103 -> 0 | D103: =C103 -> 0 | E103: =D103 -> 0 | F103: =CHOOSE(MATCH(B$2,$B$4:$E$4,0),B103,C103,D103,E103) -> 0 | G103: =IFERROR(F103/F$76,0) -> 0 | H103: R&M fixed: 1-2% EGI — HVAC, elevator, fire/life contracts
...

Sheet P&L
A1: P&L — 10-YEAR PRO FORMA PROJECTIONS (Active Scenario drives all inputs)
A2: Blue = input | Black = formula | Green = cross-sheet. Escalators auto-pulled from annual averages. Override any cell and highlight yellow.
A4: ESCALATORS & ASSUMPTIONS | D4: Year 1 | E4: Year 2 | F4: Year 3 | G4: Year 4 | H4: Year 5 | I4: Year 6 | J4: Year 7 | K4: Year 8 | L4: Year 9 | M4: Year 10
A5: Annual Revenue Escalator | C5: — | D5: 0.04 | E5: 0.04 | F5: 0.04 | G5: 0.04 | H5: =G5 -> 0.04 | I5: =H5 -> 0.04 | J5: =I5 -> 0.04 | K5: =J5 -> 0.04 | L5: =K5 -> 0.04 | M5: =L5 -> 0.04 | N5: Avg: | O5: =AVERAGE(D5:M5) -> 0.04
A6: Annual Expense Escalator | C6: — | D6: 0.03 | E6: 0.03 | F6: 0.03 | G6: 0.03 | H6: 0.03 | I6: =H6 -> 0.03 | J6: =I6 -> 0.03 | K6: =J6 -> 0.03 | L6: =K6 -> 0.03 | M6: =L6 -> 0.03 | N6: Avg: | O6: =AVERAGE(D6:M6) -> 0.03
A8: Line Item | C8: T-12 Actual | D8: Year 1 | E8: Year 2 | F8: Year 3 | G8: Year 4 | H8: Year 5 | I8: Year 6 | J8: Year 7 | K8: Year 8 | L8: Year 9 | M8: Year 10 | N8: Total (Y1–Y5) | O8: Total (Y1–Y10) | P8: Avg / Yr | Q8: Y1 % EGI / Y1 Value
A9: INCOME
A10: Avg. Rent / Bed | C10: =IFERROR((C43/C42)/12,0) -> 0 | D10: =IFERROR((D43/D42)/12,0) -> 0 | E10: =IFERROR((E43/E42)/12,0) -> 0 | F10: =IFERROR((F43/F42)/12,0) -> 0 | G10: =IFERROR((G43/G42)/12,0) -> 0 | H10: =IFERROR((H43/H42)/12,0) -> 0 | I10: =IFERROR((I43/I42)/12,0) -> 0 | J10: =IFERROR((J43/J42)/12,0) -> 0 | ... M10: =IFERROR((M43/M42)/12,0) -> 0
A11: ── INDEPENDENT LIVING (IL) ──
A12: Licensed Beds — IL | C12: =Scenarios!B39 -> 0 | D12: =Scenarios!F39 -> 0 | E12: =D12 -> 0 | F12: =E12 -> 0 | G12: =F12 -> 0 | H12: =G12 -> 0 | I12: =H12 -> 0 | J12: =I12 -> 0 | K12: =J12 -> 0 | L12: =K12 -> 0 | M12: =L12 -> 0
A13: Avg Monthly Rate — IL | C13: =Scenarios!B40 -> 0 | D13: =Scenarios!F40 -> 0 | E13: =D13*(1+E$5) -> 0 | F13: =E13*(1+F$5) -> 0 | G13: =F13*(1+G$5) -> 0 | H13: =G13*(1+H$5) -> 0 | I13: =H13*(1+I$5) -> 0 | J13: =I13*(1+J$5) -> 0 | K13: =J13*(1+K$5) -> 0 | L13: =K13*(1+L$5) -> 0 | M13: =L13*(1+M$5) -> 0
A14: GPR — IL | C14: =C12*C13*12 -> 0 | D14: =D12*D13*12 -> 0 | E14: =E12*E13*12 -> 0 | F14: =F12*F13*12 -> 0 | G14: =G12*G13*12 -> 0 | H14: =H12*H13*12 -> 0 | I14: =I12*I13*12 -> 0 | J14: =J12*J13*12 -> 0 | ... M14: =M12*M13*12 -> 0 | N14: =SUM(D14:H14) -> 0 | O14: =SUM(D14:M14) -> 0 | P14: =IFERROR(O14/10,0) -> 0 | Q14: =IFERROR(D14/$D$50,0) -> 0
A15: Vacancy % — IL | C15: =Scenarios!B42 -> 0 | D15: =Scenarios!F42 -> 0 | E15: =D15 -> 0 | F15: =E15 -> 0 | G15: =F15 -> 0 | H15: =G15 -> 0 | I15: =H15 -> 0 | J15: =I15 -> 0 | K15: =J15 -> 0 | L15: =K15 -> 0 | M15: =L15 -> 0
A16: Less: Vacancy — IL | C16: =IFERROR(-C15*C14,0) -> 0 | D16: =IFERROR(-D15*D14,0) -> 0 | E16: =IFERROR(-E15*E14,0) -> 0 | F16: =IFERROR(-F15*F14,0) -> 0 | G16: =IFERROR(-G15*G14,0) -> 0 | H16: =IFERROR(-H15*H14,0) -> 0 | I16: =IFERROR(-I15*I14,0) -> 0 | J16: =IFERROR(-J15*J14,0) -> 0 | ... M16: =IFERROR(-M15*M14,0) -> 0
A17: Loss to Lease % — IL | C17: =Scenarios!B68 -> 0 | D17: =Scenarios!F68 -> 0 | E17: =D17 -> 0 | F17: =E17 -> 0 | G17: =F17 -> 0 | H17: =G17 -> 0 | I17: =H17 -> 0 | J17: =I17 -> 0 | K17: =J17 -> 0 | L17: =K17 -> 0 | M17: =L17 -> 0
A18: Less: Loss to Lease — IL | C18: =IFERROR(-C17*C14,0) -> 0 | D18: =IFERROR(-D17*D14,0) -> 0 | E18: =IFERROR(-E17*E14,0) -> 0 | F18: =IFERROR(-F17*F14,0) -> 0 | G18: =IFERROR(-G17*G14,0) -> 0 | H18: =IFERROR(-H17*H14,0) -> 0 | I18: =IFERROR(-I17*I14,0) -> 0 | J18: =IFERROR(-J17*J14,0) -> 0 | ... M18: =IFERROR(-M17*M14,0) -> 0
A19: Bad Debt / Concessions % — IL | C19: =Scenarios!B70 -> 0 | D19: =Scenarios!F70 -> 0 | E19: =D19 -> 0 | F19: =E19 -> 0 | G19: =F19 -> 0 | H19: =G19 -> 0 | I19: =H19 -> 0 | J19: =I19 -> 0 | K19: =J19 -> 0 | L19: =K19 -> 0 | M19: =L19 -> 0
A20: Less: Concessions/Bad Debt — IL | C20: =IFERROR(-C19*C14,0) -> 0 | D20: =IFERROR(-D19*D14,0) -> 0 | E20: =IFERROR(-E19*E14,0) -> 0 | F20: =IFERROR(-F19*F14,0) -> 0 | G20: =IFERROR(-G19*G14,0) -> 0 | H20: =IFERROR(-H19*H14,0) -> 0 | I20: =IFERROR(-I19*I14,0) -> 0 | J20: =IFERROR(-J19*J14,0) -> 0 | ... M20: =IFERROR(-M19*M14,0) -> 0
A21: ── ASSISTED LIVING (AL) ──
A22: Licensed Beds — AL | C22: =Scenarios!B45 -> 0 | D22: =Scenarios!F45 -> 0 | E22: =D22 -> 0 | F22: =E22 -> 0 | G22: =F22 -> 0 | H22: =G22 -> 0 | I22: =H22 -> 0 | J22: =I22 -> 0 | K22: =J22 -> 0 | L22: =K22 -> 0 | M22: =L22 -> 0
A23: Avg Monthly Rate — AL | C23: =Scenarios!B46 -> 0 | D23: =Scenarios!F46 -> 0 | E23: =D23*(1+E$5) -> 0 | F23: =E23*(1+F$5) -> 0 | G23: =F23*(1+G$5) -> 0 | H23: =G23*(1+H$5) -> 0 | I23: =H23*(1+I$5) -> 0 | J23: =I23*(1+J$5) -> 0 | K23: =J23*(1+K$5) -> 0 | L23: =K23*(1+L$5) -> 0 | M23: =L23*(1+M$5) -> 0
A24: GPR — AL | C24: =C22*C23*12 -> 0 | D24: =D22*D23*12 -> 0 | E24: =E22*E23*12 -> 0 | F24: =F22*F23*12 -> 0 | G24: =G22*G23*12 -> 0 | H24: =H22*H23*12 -> 0 | I24: =I22*I23*12 -> 0 | J24: =J22*J23*12 -> 0 | ... M24: =M22*M23*12 -> 0 | N24: =SUM(D24:H24) -> 0 | O24: =SUM(D24:M24) -> 0 | P24: =IFERROR(O24/10,0) -> 0 | Q24: =IFERROR(D24/$D$50,0) -> 0
A25: Vacancy % — AL | C25: =Scenarios!B48 -> 0 | D25: =Scenarios!F48 -> 0 | E25: =D25 -> 0 | F25: =E25 -> 0 | G25: =F25 -> 0 | H25: =G25 -> 0 | I25: =H25 -> 0 | J25: =I25 -> 0 | K25: =J25 -> 0 | L25: =K25 -> 0 | M25: =L25 -> 0
A26: Less: Vacancy — AL | C26: =IFERROR(-C25*C24,0) -> 0 | D26: =IFERROR(-D25*D24,0) -> 0 | E26: =IFERROR(-E25*E24,0) -> 0 | F26: =IFERROR(-F25*F24,0) -> 0 | G26: =IFERROR(-G25*G24,0) -> 0 | H26: =IFERROR(-H25*H24,0) -> 0 | I26: =IFERROR(-I25*I24,0) -> 0 | J26: =IFERROR(-J25*J24,0) -> 0 | ... M26: =IFERROR(-M25*M24,0) -> 0
A27: Loss to Lease % — AL | C27: =Scenarios!B68 -> 0 | D27: =Scenarios!F68 -> 0 | E27: =D27 -> 0 | F27: =E27 -> 0 | G27: =F27 -> 0 | H27: =G27 -> 0 | I27: =H27 -> 0 | J27: =I27 -> 0 | K27: =J27 -> 0 | L27: =K27 -> 0 | M27: =L27 -> 0
A28: Less: Loss to Lease — AL | C28: =IFERROR(-C27*C24,0) -> 0 | D28: =IFERROR(-D27*D24,0) -> 0 | E28: =IFERROR(-E27*E24,0) -> 0 | F28: =IFERROR(-F27*F24,0) -> 0 | G28: =IFERROR(-G27*G24,0) -> 0 | H28: =IFERROR(-H27*H24,0) -> 0 | I28: =IFERROR(-I27*I24,0) -> 0 | J28: =IFERROR(-J27*J24,0) -> 0 | ... M28: =IFERROR(-M27*M24,0) -> 0
A29: Bad Debt / Concessions % — AL | C29: =Scenarios!B70 -> 0 | D29: =Scenarios!F70 -> 0 | E29: =D29 -> 0 | F29: =E29 -> 0 | G29: =F29 -> 0 | H29: =G29 -> 0 | I29: =H29 -> 0 | J29: =I29 -> 0 | K29: =J29 -> 0 | L29: =K29 -> 0 | M29: =L29 -> 0
A30: Less: Concessions/Bad Debt — AL | C30: =IFERROR(-C29*C24,0) -> 0 | D30: =IFERROR(-D29*D24,0) -> 0 | E30: =IFERROR(-E29*E24,0) -> 0 | F30: =IFERROR(-F29*F24,0) -> 0 | G30: =IFERROR(-G29*G24,0) -> 0 | H30: =IFERROR(-H29*H24,0) -> 0 | I30: =IFERROR(-I29*I24,0) -> 0 | J30: =IFERROR(-J29*J24,0) -> 0 | ... M30: =IFERROR(-M29*M24,0) -> 0
A31: ── MEMORY CARE (MC) ──
A32: Licensed Beds — MC | C32: =Scenarios!B51 -> 0 | D32: =Scenarios!F51 -> 0 | E32: =D32 -> 0 | F32: =E32 -> 0 | G32: =F32 -> 0 | H32: =G32 -> 0 | I32: =H32 -> 0 | J32: =I32 -> 0 | K32: =J32 -> 0 | L32: =K32 -> 0 | M32: =L32 -> 0
A33: Avg Monthly Rate — MC | C33: =Scenarios!B52 -> 0 | D33: =Scenarios!F52 -> 0 | E33: =D33*(1+E$5) -> 0 | F33: =E33*(1+F$5) -> 0 | G33: =F33*(1+G$5) -> 0 | H33: =G33*(1+H$5) -> 0 | I33: =H33*(1+I$5) -> 0 | J33: =I33*(1+J$5) -> 0 | K33: =J33*(1+K$5) -> 0 | L33: =K33*(1+L$5) -> 0 | M33: =L33*(1+M$5) -> 0
A34: GPR — MC | C34: =C32*C33*12 -> 0 | D34: =D32*D33*12 -> 0 | E34: =E32*E33*12 -> 0 | F34: =F32*F33*12 -> 0 | G34: =G32*G33*12 -> 0 | H34: =H32*H33*12 -> 0 | I34: =I32*I33*12 -> 0 | J34: =J32*J33*12 -> 0 | ... M34: =M32*M33*12 -> 0 | N34: =SUM(D34:H34) -> 0 | O34: =SUM(D34:M34) -> 0 | P34: =IFERROR(O34/10,0) -> 0 | Q34: =IFERROR(D34/$D$50,0) -> 0
A35: Vacancy % — MC | C35: =Scenarios!B54 -> 0 | D35: =Scenarios!F54 -> 0 | E35: =D35 -> 0 | F35: =E35 -> 0 | G35: =F35 -> 0 | H35: =G35 -> 0 | I35: =H35 -> 0 | J35: =I35 -> 0 | K35: =J35 -> 0 | L35: =K35 -> 0 | M35: =L35 -> 0
A36: Less: Vacancy — MC | C36: =IFERROR(-C35*C34,0) -> 0 | D36: =IFERROR(-D35*D34,0) -> 0 | E36: =IFERROR(-E35*E34,0) -> 0 | F36: =IFERROR(-F35*F34,0) -> 0 | G36: =IFERROR(-G35*G34,0) -> 0 | H36: =IFERROR(-H35*H34,0) -> 0 | I36: =IFERROR(-I35*I34,0) -> 0 | J36: =IFERROR(-J35*J34,0) -> 0 | ... M36: =IFERROR(-M35*M34,0) -> 0
A37: Loss to Lease % — MC | C37: =Scenarios!B68 -> 0 | D37: =Scenarios!F68 -> 0 | E37: =D37 -> 0 | F37: =E37 -> 0 | G37: =F37 -> 0 | H37: =G37 -> 0 | I37: =H37 -> 0 | J37: =I37 -> 0 | K37: =J37 -> 0 | L37: =K37 -> 0 | M37: =L37 -> 0
A38: Less: Loss to Lease — MC | C38: =IFERROR(-C37*C34,0) -> 0 | D38: =IFERROR(-D37*D34,0) -> 0 | E38: =IFERROR(-E37*E34,0) -> 0 | F38: =IFERROR(-F37*F34,0) -> 0 | G38: =IFERROR(-G37*G34,0) -> 0 | H38: =IFERROR(-H37*H34,0) -> 0 | I38: =IFERROR(-I37*I34,0) -> 0 | J38: =IFERROR(-J37*J34,0) -> 0 | ... M38: =IFERROR(-M37*M34,0) -> 0
A39: Bad Debt / Concessions % — MC | C39: =Scenarios!B70 -> 0 | D39: =Scenarios!F70 -> 0 | E39: =D39 -> 0 | F39: =E39 -> 0 | G39: =F39 -> 0 | H39: =G39 -> 0 | I39: =H39 -> 0 | J39: =I39 -> 0 | K39: =J39 -> 0 | L39: =K39 -> 0 | M39: =L39 -> 0
A40: Less: Concessions/Bad Debt — MC | C40: =IFERROR(-C39*C34,0) -> 0 | D40: =IFERROR(-D39*D34,0) -> 0 | E40: =IFERROR(-E39*E34,0) -> 0 | F40: =IFERROR(-F39*F34,0) -> 0 | G40: =IFERROR(-G39*G34,0) -> 0 | H40: =IFERROR(-H39*H34,0) -> 0 | I40: =IFERROR(-I39*I34,0) -> 0 | J40: =IFERROR(-J39*J34,0) -> 0 | ... M40: =IFERROR(-M39*M34,0) -> 0
A41: ── SUMMARY ROLLUP ──
A42: Total Licensed Beds | C42: =C12+C22+C32 -> 0 | D42: =D12+D22+D32 -> 0 | E42: =E12+E22+E32 -> 0 | F42: =F12+F22+F32 -> 0 | G42: =G12+G22+G32 -> 0 | H42: =H12+H22+H32 -> 0 | I42: =I12+I22+I32 -> 0 | J42: =J12+J22+J32 -> 0 | ... M42: =M12+M22+M32 -> 0 | N42: =D42 -> 0 | O42: =D42 -> 0 | P42: =D42 -> 0
A43: TOTAL GROSS POTENTIAL RENT | C43: =C14+C24+C34 -> 0 | D43: =D14+D24+D34 -> 0 | E43: =E14+E24+E34 -> 0 | F43: =F14+F24+F34 -> 0 | G43: =G14+G24+G34 -> 0 | H43: =H14+H24+H34 -> 0 | I43: =I14+I24+I34 -> 0 | J43: =J14+J24+J34 -> 0 | ... M43: =M14+M24+M34 -> 0 | N43: =SUM(D43:H43) -> 0 | O43: =SUM(D43:M43) -> 0 | P43: =IFERROR(O43/10,0) -> 0 | Q43: =IFERROR(D43/$D$50,0) -> 0
A44: Less: Total Vacancy | C44: =C16+C26+C36 -> 0 | D44: =D16+D26+D36 -> 0 | E44: =E16+E26+E36 -> 0 | F44: =F16+F26+F36 -> 0 | G44: =G16+G26+G36 -> 0 | H44: =H16+H26+H36 -> 0 | I44: =I16+I26+I36 -> 0 | J44: =J16+J26+J36 -> 0 | ... M44: =M16+M26+M36 -> 0 | N44: =SUM(D44:H44) -> 0 | O44: =SUM(D44:M44) -> 0 | P44: =IFERROR(O44/10,0) -> 0 | Q44: =IFERROR(D44/$D$50,0) -> 0
A45: Less: Total Loss to Lease | C45: =C18+C28+C38 -> 0 | D45: =D18+D28+D38 -> 0 | E45: =E18+E28+E38 -> 0 | F45: =F18+F28+F38 -> 0 | G45: =G18+G28+G38 -> 0 | H45: =H18+H28+H38 -> 0 | I45: =I18+I28+I38 -> 0 | J45: =J18+J28+J38 -> 0 | ... M45: =M18+M28+M38 -> 0 | N45: =SUM(D45:H45) -> 0 | O45: =SUM(D45:M45) -> 0 | P45: =IFERROR(O45/10,0) -> 0 | Q45: =IFERROR(D45/$D$50,0) -> 0
A46: Less: Total Concessions/Bad Debt | C46: =C20+C30+C40 -> 0 | D46: =D20+D30+D40 -> 0 | E46: =E20+E30+E40 -> 0 | F46: =F20+F30+F40 -> 0 | G46: =G20+G30+G40 -> 0 | H46: =H20+H30+H40 -> 0 | I46: =I20+I30+I40 -> 0 | J46: =J20+J30+J40 -> 0 | ... M46: =M20+M30+M40 -> 0 | N46: =SUM(D46:H46) -> 0 | O46: =SUM(D46:M46) -> 0 | P46: =IFERROR(O46/10,0) -> 0 | Q46: =IFERROR(D46/$D$50,0) -> 0
A47: Care Services Fees | C47: =Scenarios!B73 -> 0 | D47: =Scenarios!F73 -> 0 | E47: =D47*(1+E$5) -> 0 | F47: =E47*(1+F$5) -> 0 | G47: =F47*(1+G$5) -> 0 | H47: =G47*(1+H$5) -> 0 | I47: =H47*(1+I$5) -> 0 | J47: =I47*(1+J$5) -> 0 | K47: =J47*(1+K$5) -> 0 | L47: =K47*(1+L$5) -> 0 | M47: =L47*(1+M$5) -> 0 | N47: =SUM(D47:H47) -> 0 | O47: =SUM(D47:M47) -> 0 | P47: =IFERROR(O47/10,0) -> 0 | Q47: =IFERROR(D47/$D$50,0) -> 0
A48: 2nd Person Revenue | C48: =Scenarios!B74 -> 0 | D48: =Scenarios!F74 -> 0 | E48: =D48*(1+E$5) -> 0 | F48: =E48*(1+F$5) -> 0 | G48: =F48*(1+G$5) -> 0 | H48: =G48*(1+H$5) -> 0 | I48: =H48*(1+I$5) -> 0 | J48: =I48*(1+J$5) -> 0 | K48: =J48*(1+K$5) -> 0 | L48: =K48*(1+L$5) -> 0 | M48: =L48*(1+M$5) -> 0 | N48: =SUM(D48:H48) -> 0 | O48: =SUM(D48:M48) -> 0 | P48: =IFERROR(O48/10,0) -> 0 | Q48: =IFERROR(D48/$D$50,0) -> 0
A49: Other Income | C49: =Scenarios!B75 -> 0 | D49: =Scenarios!F75 -> 0 | E49: =D49*(1+E$5) -> 0 | F49: =E49*(1+F$5) -> 0 | G49: =F49*(1+G$5) -> 0 | H49: =G49*(1+H$5) -> 0 | I49: =H49*(1+I$5) -> 0 | J49: =I49*(1+J$5) -> 0 | K49: =J49*(1+K$5) -> 0 | L49: =K49*(1+L$5) -> 0 | M49: =L49*(1+M$5) -> 0 | N49: =SUM(D49:H49) -> 0 | O49: =SUM(D49:M49) -> 0 | P49: =IFERROR(O49/10,0) -> 0 | Q49: =IFERROR(D49/$D$50,0) -> 0
A50: EFFECTIVE GROSS INCOME | C50: =C43+C44+C45+C46+C47+C48+C49 -> 0 | D50: =D43+D44+D45+D46+D47+D48+D49 -> 0 | E50: =E43+E44+E45+E46+E47+E48+E49 -> 0 | F50: =F43+F44+F45+F46+F47+F48+F49 -> 0 | G50: =G43+G44+G45+G46+G47+G48+G49 -> 0 | H50: =H43+H44+H45+H46+H47+H48+H49 -> 0 | I50: =I43+I44+I45+I46+I47+I48+I49 -> 0 | J50: =J43+J44+J45+J46+J47+J48+J49 -> 0 | ... M50: =M43+M44+M45+M46+M47+M48+M49 -> 0 | N50: =SUM(D50:H50) -> 0 | O50: =SUM(D50:M50) -> 0 | P50: =IFERROR(O50/10,0) -> 0 | Q50: =IFERROR(D50/$D$50,0) -> 0
A51: EXPENSES
A52: ── DIRECT LABOR ──
A53: Care staff labor | C53: =Scenarios!B81 -> 0 | D53: =Scenarios!F81 -> 0 | E53: =D53*(1+E$6) -> 0 | F53: =E53*(1+F$6) -> 0 | G53: =F53*(1+G$6) -> 0 | H53: =G53*(1+H$6) -> 0 | I53: =H53*(1+I$6) -> 0 | J53: =I53*(1+J$6) -> 0 | K53: =J53*(1+K$6) -> 0 | L53: =K53*(1+L$6) -> 0 | M53: =L53*(1+M$6) -> 0
A54: Wellness / care coordinators | C54: =Scenarios!B82 -> 0 | D54: =Scenarios!F82 -> 0 | E54: =D54*(1+E$6) -> 0 | F54: =E54*(1+F$6) -> 0 | G54: =F54*(1+G$6) -> 0 | H54: =G54*(1+H$6) -> 0 | I54: =H54*(1+I$6) -> 0 | J54: =I54*(1+J$6) -> 0 | K54: =J54*(1+K$6) -> 0 | L54: =K54*(1+L$6) -> 0 | M54: =L54*(1+M$6) -> 0
A55: Contract / agency labor | C55: =Scenarios!B83 -> 0 | D55: =Scenarios!F83 -> 0 | E55: =D55*(1+E$6) -> 0 | F55: =E55*(1+F$6) -> 0 | G55: =F55*(1+G$6) -> 0 | H55: =G55*(1+H$6) -> 0 | I55: =H55*(1+I$6) -> 0 | J55: =I55*(1+J$6) -> 0 | K55: =J55*(1+K$6) -> 0 | L55: =K55*(1+L$6) -> 0 | M55: =L55*(1+M$6) -> 0
A56: Activities labor | C56: =Scenarios!B84 -> 0 | D56: =Scenarios!F84 -> 0 | E56: =D56*(1+E$6) -> 0 | F56: =E56*(1+F$6) -> 0 | G56: =F56*(1+G$6) -> 0 | H56: =G56*(1+H$6) -> 0 | I56: =H56*(1+I$6) -> 0 | J56: =I56*(1+J$6) -> 0 | K56: =J56*(1+K$6) -> 0 | L56: =K56*(1+L$6) -> 0 | M56: =L56*(1+M$6) -> 0
A57: Dining / food service labor | C57: =Scenarios!B85 -> 0 | D57: =Scenarios!F85 -> 0 | E57: =D57*(1+E$6) -> 0 | F57: =E57*(1+F$6) -> 0 | G57: =F57*(1+G$6) -> 0 | H57: =G57*(1+H$6) -> 0 | I57: =H57*(1+I$6) -> 0 | J57: =I57*(1+J$6) -> 0 | K57: =J57*(1+K$6) -> 0 | L57: =K57*(1+L$6) -> 0 | M57: =L57*(1+M$6) -> 0
A58: Maintenance & housekeeping labor | C58: =Scenarios!B86 -> 0 | D58: =Scenarios!F86 -> 0 | E58: =D58*(1+E$6) -> 0 | F58: =E58*(1+F$6) -> 0 | G58: =F58*(1+G$6) -> 0 | H58: =G58*(1+H$6) -> 0 | I58: =H58*(1+I$6) -> 0 | J58: =I58*(1+J$6) -> 0 | K58: =J58*(1+K$6) -> 0 | L58: =K58*(1+L$6) -> 0 | M58: =L58*(1+M$6) -> 0
A59: Administrative labor | C59: =Scenarios!B87 -> 0 | D59: =Scenarios!F87 -> 0 | E59: =D59*(1+E$6) -> 0 | F59: =E59*(1+F$6) -> 0 | G59: =F59*(1+G$6) -> 0 | H59: =G59*(1+H$6) -> 0 | I59: =H59*(1+I$6) -> 0 | J59: =I59*(1+J$6) -> 0 | K59: =J59*(1+K$6) -> 0 | L59: =K59*(1+L$6) -> 0 | M59: =L59*(1+M$6) -> 0
A60: Bonus wages | C60: =Scenarios!B88 -> 0 | D60: =Scenarios!F88 -> 0 | E60: =D60*(1+E$6) -> 0 | F60: =E60*(1+F$6) -> 0 | G60: =F60*(1+G$6) -> 0 | H60: =G60*(1+H$6) -> 0 | I60: =H60*(1+I$6) -> 0 | J60: =I60*(1+J$6) -> 0 | K60: =J60*(1+K$6) -> 0 | L60: =K60*(1+L$6) -> 0 | M60: =L60*(1+M$6) -> 0
A61: Total Direct Labor | C61: =Scenarios!B89 -> 0 | D61: =Scenarios!F89 -> 0 | E61: =SUM(E53:E60) -> 0 | F61: =SUM(F53:F60) -> 0 | G61: =SUM(G53:G60) -> 0 | H61: =SUM(H53:H60) -> 0 | I61: =SUM(I53:I60) -> 0 | J61: =SUM(J53:J60) -> 0 | K61: =SUM(K53:K60) -> 0 | L61: =SUM(L53:L60) -> 0 | M61: =SUM(M53:M60) -> 0
A62: ── PAYROLL BURDEN ──
A63: Overtime wages | C63: =Scenarios!B91 -> 0 | D63: =Scenarios!F91 -> 0 | E63: =D63*(1+E$6) -> 0 | F63: =E63*(1+F$6) -> 0 | G63: =F63*(1+G$6) -> 0 | H63: =G63*(1+H$6) -> 0 | I63: =H63*(1+I$6) -> 0 | J63: =I63*(1+J$6) -> 0 | K63: =J63*(1+K$6) -> 0 | L63: =K63*(1+L$6) -> 0 | M63: =L63*(1+M$6) -> 0
A64: PTO wages | C64: =Scenarios!B92 -> 0 | D64: =Scenarios!F92 -> 0 | E64: =D64*(1+E$6) -> 0 | F64: =E64*(1+F$6) -> 0 | G64: =F64*(1+G$6) -> 0 | H64: =G64*(1+H$6) -> 0 | I64: =H64*(1+I$6) -> 0 | J64: =I64*(1+J$6) -> 0 | K64: =J64*(1+K$6) -> 0 | L64: =K64*(1+L$6) -> 0 | M64: =L64*(1+M$6) -> 0
A65: Payroll taxes | C65: =Scenarios!B93 -> 0 | D65: =Scenarios!F93 -> 0 | E65: =D65*(1+E$6) -> 0 | F65: =E65*(1+F$6) -> 0 | G65: =F65*(1+G$6) -> 0 | H65: =G65*(1+H$6) -> 0 | I65: =H65*(1+I$6) -> 0 | J65: =I65*(1+J$6) -> 0 | K65: =J65*(1+K$6) -> 0 | L65: =K65*(1+L$6) -> 0 | M65: =L65*(1+M$6) -> 0
A66: Employee benefits | C66: =Scenarios!B94 -> 0 | D66: =Scenarios!F94 -> 0 | E66: =D66*(1+E$6) -> 0 | F66: =E66*(1+F$6) -> 0 | G66: =F66*(1+G$6) -> 0 | H66: =G66*(1+H$6) -> 0 | I66: =H66*(1+I$6) -> 0 | J66: =I66*(1+J$6) -> 0 | K66: =J66*(1+K$6) -> 0 | L66: =K66*(1+L$6) -> 0 | M66: =L66*(1+M$6) -> 0
A67: Workers' comp insurance | C67: =Scenarios!B95 -> 0 | D67: =Scenarios!F95 -> 0 | E67: =D67*(1+E$6) -> 0 | F67: =E67*(1+F$6) -> 0 | G67: =F67*(1+G$6) -> 0 | H67: =G67*(1+H$6) -> 0 | I67: =H67*(1+I$6) -> 0 | J67: =I67*(1+J$6) -> 0 | K67: =J67*(1+K$6) -> 0 | L67: =K67*(1+L$6) -> 0 | M67: =L67*(1+M$6) -> 0
A68: Employee 401(k) / retirement | C68: =Scenarios!B96 -> 0 | D68: =Scenarios!F96 -> 0 | E68: =D68*(1+E$6) -> 0 | F68: =E68*(1+F$6) -> 0 | G68: =F68*(1+G$6) -> 0 | H68: =G68*(1+H$6) -> 0 | I68: =H68*(1+I$6) -> 0 | J68: =I68*(1+J$6) -> 0 | K68: =J68*(1+K$6) -> 0 | L68: =K68*(1+L$6) -> 0 | M68: =L68*(1+M$6) -> 0
A69: Total Payroll Burden | C69: =Scenarios!B97 -> 0 | D69: =Scenarios!F97 -> 0 | E69: =SUM(E63:E68) -> 0 | F69: =SUM(F63:F68) -> 0 | G69: =SUM(G63:G68) -> 0 | H69: =SUM(H63:H68) -> 0 | I69: =SUM(I63:I68) -> 0 | J69: =SUM(J63:J68) -> 0 | K69: =SUM(K63:K68) -> 0 | L69: =SUM(L63:L68) -> 0 | M69: =SUM(M63:M68) -> 0
A70: ── NON-LABOR OPEX ──
A71: Food cost | C71: =Scenarios!B99 -> 0 | D71: =Scenarios!F99 -> 0 | E71: =D71*(1+E$6) -> 0 | F71: =E71*(1+F$6) -> 0 | G71: =F71*(1+G$6) -> 0 | H71: =G71*(1+H$6) -> 0 | I71: =H71*(1+I$6) -> 0 | J71: =I71*(1+J$6) -> 0 | K71: =J71*(1+K$6) -> 0 | L71: =K71*(1+L$6) -> 0 | M71: =L71*(1+M$6) -> 0
A72: Dining & kitchen supplies | C72: =Scenarios!B100 -> 0 | D72: =Scenarios!F100 -> 0 | E72: =D72*(1+E$6) -> 0 | F72: =E72*(1+F$6) -> 0 | G72: =F72*(1+G$6) -> 0 | H72: =G72*(1+H$6) -> 0 | I72: =H72*(1+I$6) -> 0 | J72: =I72*(1+J$6) -> 0 | K72: =J72*(1+K$6) -> 0 | L72: =K72*(1+L$6) -> 0 | M72: =L72*(1+M$6) -> 0
A73: Nursing & care supplies | C73: =Scenarios!B101 -> 0 | D73: =Scenarios!F101 -> 0 | E73: =D73*(1+E$6) -> 0 | F73: =E73*(1+F$6) -> 0 | G73: =F73*(1+G$6) -> 0 | H73: =G73*(1+H$6) -> 0 | I73: =H73*(1+I$6) -> 0 | J73: =I73*(1+J$6) -> 0 | K73: =J73*(1+K$6) -> 0 | L73: =K73*(1+L$6) -> 0 | M73: =L73*(1+M$6) -> 0
A74: Recreation & activity supplies | C74: =Scenarios!B102 -> 0 | D74: =Scenarios!F102 -> 0 | E74: =D74*(1+E$6) -> 0 | F74: =E74*(1+F$6) -> 0 | G74: =F74*(1+G$6) -> 0 | H74: =G74*(1+H$6) -> 0 | I74: =H74*(1+I$6) -> 0 | J74: =I74*(1+J$6) -> 0 | K74: =J74*(1+K$6) -> 0 | L74: =K74*(1+L$6) -> 0 | M74: =L74*(1+M$6) -> 0
A75: R&M — fixed | C75: =Scenarios!B103 -> 0 | D75: =Scenarios!F103 -> 0 | E75: =D75*(1+E$6) -> 0 | F75: =E75*(1+F$6) -> 0 | G75: =F75*(1+G$6) -> 0 | H75: =G75*(1+H$6) -> 0 | I75: =H75*(1+I$6) -> 0 | J75: =I75*(1+J$6) -> 0 | K75: =J75*(1+K$6) -> 0 | L75: =K75*(1+L$6) -> 0 | M75: =L75*(1+M$6) -> 0
A76: R&M — variable | C76: =Scenarios!B104 -> 0 | D76: =Scenarios!F104 -> 0 | E76: =D76*(1+E$6) -> 0 | F76: =E76*(1+F$6) -> 0 | G76: =F76*(1+G$6) -> 0 | H76: =G76*(1+H$6) -> 0 | I76: =H76*(1+I$6) -> 0 | J76: =I76*(1+J$6) -> 0 | K76: =J76*(1+K$6) -> 0 | L76: =K76*(1+L$6) -> 0 | M76: =L76*(1+M$6) -> 0
A77: Housekeeping & laundry supplies | C77: =Scenarios!B105 -> 0 | D77: =Scenarios!F105 -> 0 | E77: =D77*(1+E$6) -> 0 | F77: =E77*(1+F$6) -> 0 | G77: =F77*(1+G$6) -> 0 | H77: =G77*(1+H$6) -> 0 | I77: =H77*(1+I$6) -> 0 | J77: =I77*(1+J$6) -> 0 | K77: =J77*(1+K$6) -> 0 | L77: =K77*(1+L$6) -> 0 | M77: =L77*(1+M$6) -> 0
A78: Sales, advertising & marketing | C78: =Scenarios!B106 -> 0 | D78: =Scenarios!F106 -> 0 | E78: =D78*(1+E$6) -> 0 | F78: =E78*(1+F$6) -> 0 | G78: =F78*(1+G$6) -> 0 | H78: =G78*(1+H$6) -> 0 | I78: =H78*(1+I$6) -> 0 | J78: =I78*(1+J$6) -> 0 | K78: =J78*(1+K$6) -> 0 | L78: =K78*(1+L$6) -> 0 | M78: =L78*(1+M$6) -> 0
A79: Referral fees | C79: =Scenarios!B107 -> 0 | D79: =Scenarios!F107 -> 0 | E79: =D79*(1+E$6) -> 0 | F79: =E79*(1+F$6) -> 0 | G79: =F79*(1+G$6) -> 0 | H79: =G79*(1+H$6) -> 0 | I79: =H79*(1+I$6) -> 0 | J79: =I79*(1+J$6) -> 0 | K79: =J79*(1+K$6) -> 0 | L79: =K79*(1+L$6) -> 0 | M79: =L79*(1+M$6) -> 0
A80: Utilities | C80: =Scenarios!B108 -> 0 | D80: =Scenarios!F108 -> 0 | E80: =D80*(1+E$6) -> 0 | F80: =E80*(1+F$6) -> 0 | G80: =F80*(1+G$6) -> 0 | H80: =G80*(1+H$6) -> 0 | I80: =H80*(1+I$6) -> 0 | J80: =I80*(1+J$6) -> 0 | K80: =J80*(1+K$6) -> 0 | L80: =K80*(1+L$6) -> 0 | M80: =L80*(1+M$6) -> 0
A81: Telephone / IT / technology | C81: =Scenarios!B109 -> 0 | D81: =Scenarios!F109 -> 0 | E81: =D81*(1+E$6) -> 0 | F81: =E81*(1+F$6) -> 0 | G81: =F81*(1+G$6) -> 0 | H81: =G81*(1+H$6) -> 0 | I81: =H81*(1+I$6) -> 0 | J81: =I81*(1+J$6) -> 0 | K81: =J81*(1+K$6) -> 0 | L81: =K81*(1+L$6) -> 0 | M81: =L81*(1+M$6) -> 0
A82: P&C insurance | C82: =Scenarios!B110 -> 0 | D82: =Scenarios!F110 -> 0 | E82: =D82*(1+E$6) -> 0 | F82: =E82*(1+F$6) -> 0 | G82: =F82*(1+G$6) -> 0 | H82: =G82*(1+H$6) -> 0 | I82: =H82*(1+I$6) -> 0 | J82: =I82*(1+J$6) -> 0 | K82: =J82*(1+K$6) -> 0 | L82: =K82*(1+L$6) -> 0 | M82: =L82*(1+M$6) -> 0
... A93: Other / miscellaneous | C93: =Scenarios!B121 -> 0 | D93: =Scenarios!F121 -> 0 | E93: =D93*(1+E$6) -> 0 | F93: =E93*(1+F$6) -> 0 | G93: =F93*(1+G$6) -> 0 | H93: =G93*(1+H$6) -> 0 | I93: =H93*(1+I$6) -> 0 | J93: =I93*(1+J$6) -> 0 | K93: =J93*(1+K$6) -> 0 | L93: =K93*(1+L$6) -> 0 | M93: =L93*(1+M$6) -> 0
A94: Total Non-Labor OpEx | C94: =Scenarios!B122 -> 0 | D94: =Scenarios!F122 -> 0 | E94: =SUM(E71:E93) -> 0 | F94: =SUM(F71:F93) -> 0 | G94: =SUM(G71:G93) -> 0 | H94: =SUM(H71:H93) -> 0 | I94: =SUM(I71:I93) -> 0 | J94: =SUM(J71:J93) -> 0 | K94: =SUM(K71:K93) -> 0 | L94: =SUM(L71:L93) -> 0 | M94: =SUM(M71:M93) -> 0
A95: Management Fee | C95: =Scenarios!B123 -> 0 | D95: =Scenarios!F123 -> 0 | E95: =E50*0.05 -> 0 | F95: =F50*0.05 -> 0 | G95: =G50*0.05 -> 0 | H95: =H50*0.05 -> 0 | I95: =I50*0.05 -> 0 | J95: =J50*0.05 -> 0 | K95: =K50*0.05 -> 0 | L95: =L50*0.05 -> 0 | M95: =M50*0.05 -> 0 | N95: =SUM(D95:H95) -> 0 | O95: =SUM(D95:M95) -> 0 | P95: =IFERROR(O95/10,0) -> 0 | Q95: =IFERROR(D95/D50,0) -> 0
A96: TOTAL OPERATING EXPENSES | C96: =C61+C69+C94+C95 -> 0 | D96: =D61+D69+D94+D95 -> 0 | E96: =E61+E69+E94+E95 -> 0 | F96: =F61+F69+F94+F95 -> 0 | G96: =G61+G69+G94+G95 -> 0 | H96: =H61+H69+H94+H95 -> 0 | I96: =I61+I69+I94+I95 -> 0 | J96: =J61+J69+J94+J95 -> 0 | ... M96: =M61+M69+M94+M95 -> 0
A97: NET OPERATING INCOME (NOI) | C97: =C50-C96 -> 0 | D97: =D50-D96 -> 0 | E97: =E50-E96 -> 0 | F97: =F50-F96 -> 0 | G97: =G50-G96 -> 0 | H97: =H50-H96 -> 0 | I97: =I50-I96 -> 0 | J97: =J50-J96 -> 0 | ... M97: =M50-M96 -> 0 | N97: =SUM(D97:H97) -> 0 | O97: =SUM(D97:M97) -> 0 | P97: =IFERROR(O97/10,0) -> 0 | Q97: =IFERROR(D97/D50,0) -> 0
A98: Operating Margin | D98: =D97/D50 -> #DIV/0! | E98: =E97/E50 -> #DIV/0! | F98: =F97/F50 -> #DIV/0! | G98: =G97/G50 -> #DIV/0! | H98: =H97/H50 -> #DIV/0! | I98: =I97/I50 -> #DIV/0! | J98: =J97/J50 -> #DIV/0! | K98: =K97/K50 -> #DIV/0! | ... M98: =M97/M50 -> #DIV/0! | N98: =IFERROR(N97/N50,0) -> 0 | O98: =IFERROR(O97/O50,0) -> 0
A99: DEBT SERVICE
A100: Annual Principal Payment | D100: =-IFERROR(Loans!J40,0) -> 0 | E100: =-IFERROR(Loans!K40,0) -> 0 | F100: =-IFERROR(Loans!L40,0) -> 0 | G100: =-IFERROR(Loans!M40,0) -> 0 | H100: =-IFERROR(Loans!N40,0) -> 0 | I100: =-IFERROR(Loans!O40,0) -> 0 | J100: =-IFERROR(Loans!P40,0) -> 0 | K100: =-IFERROR(Loans!Q40,0) -> 0 | ... M100: =-IFERROR(Loans!S40,0) -> 0 | N100: =SUM(D100:H100) -> 0 | O100: =SUM(D100:M100) -> 0
A101: Annual Intereset Payment | D101: =-IFERROR(Loans!J38,0) -> 0 | E101: =-IFERROR(Loans!K38,0) -> 0 | F101: =-IFERROR(Loans!L38,0) -> 0 | G101: =-IFERROR(Loans!M38,0) -> 0 | H101: =-IFERROR(Loans!N38,0) -> 0 | I101: =-IFERROR(Loans!O38,0) -> 0 | J101: =-IFERROR(Loans!P38,0) -> 0 | K101: =-IFERROR(Loans!Q38,0) -> 0 | ... M101: =-IFERROR(Loans!S38,0) -> 0 | N101: =SUM(D101:H101) -> 0 | O101: =SUM(D101:M101) -> 0
A102: Annual Total Debt Service | D102: =D100+D101 -> 0 | E102: =E100+E101 -> 0 | F102: =F100+F101 -> 0 | G102: =G100+G101 -> 0 | H102: =H100+H101 -> 0 | I102: =I100+I101 -> 0 | J102: =J100+J101 -> 0 | K102: =K100+K101 -> 0 | ... M102: =M100+M101 -> 0 | N102: =SUM(D102:H102) -> 0 | O102: =SUM(D102:M102) -> 0 | Q102: =IFERROR(ABS(D102)/D50,0) -> 0
A104: CASH FLOW AFTER DEBT SERVICE | C104: =C97+C102 -> 0 | D104: =D97+D102 -> 0 | E104: =E97+E102 -> 0 | F104: =F97+F102 -> 0 | G104: =G97+G102 -> 0 | H104: =H97+H102 -> 0 | I104: =I97+I102 -> 0 | J104: =J97+J102 -> 0 | ... M104: =M97+M102 -> 0 | N104: =SUM(D104:H104) -> 0 | O104: =SUM(D104:M104) -> 0 | Q104: =IFERROR(D104/D50,0) -> 0
A105: OPERATING RESERVE TRACKER
A106: Opening Reserve Balance | D106: =Scenarios!F13 -> 0 | E106: =D108 -> 0 | F106: =E108 -> 0 | G106: =F108 -> 0 | H106: =G108 -> 0 | I106: =H108 -> 0 | J106: =I108 -> 0 | K106: =J108 -> 0 | L106: =K108 -> 0 | M106: =L108 -> 0
A107: Reserve Draw (CF deficit cover) | D107: =IF(D104<0,MAX(D104,-D106),0) -> 0 | E107: =IF(E104<0,MAX(E104,-E106),0) -> 0 | F107: =IF(F104<0,MAX(F104,-F106),0) -> 0 | G107: =IF(G104<0,MAX(G104,-G106),0) -> 0 | H107: =IF(H104<0,MAX(H104,-H106),0) -> 0 | I107: =IF(I104<0,MAX(I104,-I106),0) -> 0 | J107: =IF(J104<0,MAX(J104,-J106),0) -> 0 | K107: =IF(K104<0,MAX(K104,-K106),0) -> 0 | ... M107: =IF(M104<0,MAX(M104,-M106),0) -> 0
A108: Ending Reserve Balance | D108: =D106+D107 -> 0 | E108: =E106+E107 -> 0 | F108: =F106+F107 -> 0 | G108: =G106+G107 -> 0 | H108: =H106+H107 -> 0 | I108: =I106+I107 -> 0 | J108: =J106+J107 -> 0 | K108: =K106+K107 -> 0 | ... M108: =M106+M107 -> 0
A110: DISTRIBUTIONS FROM CASH FLOW
A111: Asset Mgmt Fee (2.0% equity) | C111: 0.01 | D111: =IF(1>Waterfall!$B$5,0,D50*$C$111) -> 0 | E111: =IF(2>Waterfall!$B$5,0,E50*$C$111) -> 0 | F111: =IF(3>Waterfall!$B$5,0,F50*$C$111) -> 0 | G111: =IF(4>Waterfall!$B$5,0,G50*$C$111) -> 0 | H111: =IF(5>Waterfall!$B$5,0,H50*$C$111) -> 0 | I111: =IF(6>Waterfall!$B$5,0,I50*$C$111) -> 0 | J111: =IF(7>Waterfall!$B$5,0,J50*$C$111) -> 0 | K111: =IF(8>Waterfall!$B$5,0,K50*$C$111) -> 0 | L111: =IF(9>Waterfall!$B$5,0,L50*$C$111) -> 0 | M111: =IF(10>Waterfall!$B$5,0,M50*$C$111) -> 0 | Q111: =IFERROR(D111/D50,0) -> 0
A112: Class A LP Preferred Return | C112: =Scenarios!F35 -> 0 | D112: =IFERROR(Waterfall!B43,0) -> 0 | E112: =IFERROR(Waterfall!C43,0) -> 0 | F112: =IFERROR(Waterfall!D43,0) -> 0 | G112: =IFERROR(Waterfall!E43,0) -> 0 | H112: =IFERROR(Waterfall!F43,0) -> 0 | I112: =IFERROR(Waterfall!G43,0) -> 0 | J112: =IFERROR(Waterfall!H43,0) -> 0 | K112: =IFERROR(Waterfall!I43,0) -> 0 | ... M112: =IFERROR(Waterfall!K43,0) -> 0 | Q112: =IFERROR(D112/D50,0) -> 0
A113: LP Excess CF Share (1 - GP Promote %) | D113: =IFERROR((Waterfall!B55-Waterfall!B43)+Waterfall!B56,0) -> 0 | E113: =IFERROR((Waterfall!C55-Waterfall!C43)+Waterfall!C56,0) -> 0 | F113: =IFERROR((Waterfall!D55-Waterfall!D43)+Waterfall!D56,0) -> 0 | G113: =IFERROR((Waterfall!E55-Waterfall!E43)+Waterfall!E56,0) -> 0 | H113: =IFERROR((Waterfall!F55-Waterfall!F43)+Waterfall!F56,0) -> 0 | I113: =IFERROR((Waterfall!G55-Waterfall!G43)+Waterfall!G56,0) -> 0 | J113: =IFERROR((Waterfall!H55-Waterfall!H43)+Waterfall!H56,0) -> 0 | K113: =IFERROR((Waterfall!I55-Waterfall!I43)+Waterfall!I56,0) -> 0 | ... M113: =IFERROR((Waterfall!K55-Waterfall!K43)+Waterfall!K56,0) -> 0 | Q113: =IFERROR(D113/D50,0) -> 0
A114: GP Excess CF Share (GP Promote %) | D114: =IFERROR(Waterfall!B58,0) -> 0 | E114: =IFERROR(Waterfall!C58,0) -> 0 | F114: =IFERROR(Waterfall!D58,0) -> 0 | G114: =IFERROR(Waterfall!E58,0) -> 0 | H114: =IFERROR(Waterfall!F58,0) -> 0 | I114: =IFERROR(Waterfall!G58,0) -> 0 | J114: =IFERROR(Waterfall!H58,0) -> 0 | K114: =IFERROR(Waterfall!I58,0) -> 0 | ... M114: =IFERROR(Waterfall!K58,0) -> 0 | Q114: =IFERROR(D114/D50,0) -> 0
...

Sheet T-12 Analysis
A1: T-12 ANALYSIS — Trailing 12 Diagnostic Layer (Senior Living)
A2: ANALYSIS on top. Standardized aggregation (Layer 3) and raw paste block (Layer 1) below — scroll down to access data. Per Bed/Month uses occupied beds from Rent Roll Analysis. Benchmarks calibrated to assisted/memory care community norms.
A4: B. RECONCILIATION CHECK — Are all raw lines mapped?
A5: EGI: | B5: =N80 -> 0 | C5: OpEx: | D5: =N132 -> 0 | E5: EBITDAR: | F5: =N135 -> 0 | G5: Unmapped $: | H5: 0 | I5: 🟢 all mapped | L5: EGI / Occ Bed / Mo: | M5: 0
A7: C. TREND ANALYSIS — T-3 vs. T-6 vs. T-12 (annualized)
A8: Metric | B8: T-12 Actual | C8: T-6 Annlzd | D8: T-3 Annlzd | E8: T-3 vs T-12 Δ$ | F8: T-3 vs T-12 Δ% | G8: Direction | H8: Read
A9: EGI | B9: =N80 -> 0 | C9: =(SUM(H58:M61)+SUM(H63:M66)+SUM(H68:M79))*2 -> 0 | D9: =(SUM(K58:M61)+SUM(K63:M66)+SUM(K68:M79))*4 -> 0 | E9: =D9-B9 -> 0 | F9: =IFERROR((D9-B9)/B9,0) -> 0 | G9: =IF(ABS(F9)<0.02,"→ stable",IF(F9>0,"↑ rising","↓ falling")) -> → stable | H9: =IF(ABS(F9)<0.05,"stable","review") -> stable
A10: Total OpEx | B10: =N132 -> 0 | C10: =SUM(H132:M132)*2 -> 0 | D10: =SUM(K132:M132)*4 -> 0 | E10: =D10-B10 -> 0 | F10: =IFERROR((D10-B10)/B10,0) -> 0 | G10: =IF(ABS(F10)<0.02,"→ stable",IF(F10>0,"↑ rising","↓ falling")) -> → stable | H10: =IF(ABS(F10)<0.05,"stable","review") -> stable
A11: EBITDAR | B11: =N80-N132 -> 0 | C11: =C9-C10 -> 0 | D11: =D9-D10 -> 0 | E11: =D11-B11 -> 0 | F11: =IFERROR((D11-B11)/B11,0) -> 0 | G11: =IF(ABS(F11)<0.02,"→ stable",IF(F11>0,"↑ rising","↓ falling")) -> → stable | H11: =IF(ABS(F11)<0.05,"stable","review") -> stable
A12: Bad Debt + Write-offs | B12: =-N79 -> 0 | C12: =-SUM(H79:M79)*2 -> 0 | D12: =-SUM(K79:M79)*4 -> 0 | E12: =D12-B12 -> 0 | F12: =IFERROR((D12-B12)/B12,0) -> 0 | G12: =IF(ABS(F12)<0.02,"→ stable",IF(F12>0,"↑ rising","↓ falling")) -> → stable | H12: =IF(ABS(F12)<0.05,"stable","review") -> stable
A13: Total Labor & Burden | B13: =N102 -> 0 | C13: =SUM(H102:M102)*2 -> 0 | D13: =SUM(K102:M102)*4 -> 0 | E13: =D13-B13 -> 0 | F13: =IFERROR((D13-B13)/B13,0) -> 0 | G13: =IF(ABS(F13)<0.02,"→ stable",IF(F13>0,"↑ rising","↓ falling")) -> → stable | H13: =IF(ABS(F13)<0.05,"stable","review") -> stable
A14: Food Cost | B14: =N104 -> 0 | C14: =SUM(H104:M104)*2 -> 0 | D14: =SUM(K104:M104)*4 -> 0 | E14: =D14-B14 -> 0 | F14: =IFERROR((D14-B14)/B14,0) -> 0 | G14: =IF(ABS(F14)<0.02,"→ stable",IF(F14>0,"↑ rising","↓ falling")) -> → stable | H14: =IF(ABS(F14)<0.05,"stable","review") -> stable
A15: Utilities | B15: =N113 -> 0 | C15: =SUM(H113:M113)*2 -> 0 | D15: =SUM(K113:M113)*4 -> 0 | E15: =D15-B15 -> 0 | F15: =IFERROR((D15-B15)/B15,0) -> 0 | G15: =IF(ABS(F15)<0.02,"→ stable",IF(F15>0,"↑ rising","↓ falling")) -> → stable | H15: =IF(ABS(F15)<0.05,"stable","review") -> stable
A16: Overtime Wages | B16: =N96 -> 0 | C16: =SUM(H96:M96)*2 -> 0 | D16: =SUM(K96:M96)*4 -> 0 | E16: =D16-B16 -> 0 | F16: =IFERROR((D16-B16)/B16,0) -> 0 | G16: =IF(ABS(F16)<0.02,"→ stable",IF(F16>0,"↑ rising","↓ falling")) -> → stable | H16: =IF(ABS(F16)<0.05,"stable","review") -> stable
A18: D. ECONOMIC vs. PHYSICAL OCCUPANCY RECONCILIATION
A19: Licensed Beds (IL + AL + MC)
A20: Physically Occupied Beds
A21: Physical Occupancy % | B21: =IFERROR(B20/B19,0) -> 0
A22: Gross Potential Rent / GPR (annual) | B22: =N83 -> 0
A23: Net Rent Revenue (billed) | B23: =N86 -> 0
A24: Total Revenue / EGI | B24: =N80 -> 0
A25: Economic Occupancy % (Net Rent / GPR) | B25: =IFERROR(B23/B22,0) -> 0
A26: Economic vs. Physical Gap | B26: =B21-B25 -> 0
A27: → Lost Revenue from Gap ($) | B27: =B22*B26 -> 0
A29: E. BAD DEBT & WRITE-OFF LAYERED ANALYSIS
A30: Component | B30: Amount | C30: % of GPR | D30: Per Bed/Mo | E30: Benchmark | F30: Read
A31: Vacancy Loss | B31: =-N77 -> 0 | C31: =IFERROR(B31/$B$22,0) -> 0 | D31: =IFERROR(B31/($B$19*12),0) -> 0 | E31: 5–10% GPR | F31: ok
A32: Bad Debt / Write-offs | B32: =-N79 -> 0 | C32: =IFERROR(B32/$B$22,0) -> 0 | D32: =IFERROR(B32/($B$19*12),0) -> 0 | E32: 1–3% GPR | F32: ok
A33: Concessions & Specials | B33: =-N78 -> 0 | C33: =IFERROR(B33/$B$22,0) -> 0 | D33: =IFERROR(B33/($B$19*12),0) -> 0 | E33: 0.5–2% GPR | F33: ok
A34: Delinquency Change | B34: 0 | C34: =IFERROR(B34/$B$22,0) -> 0 | D34: =IFERROR(B34/($B$19*12),0) -> 0 | E34: <2% GPR | F34: ok
A35: Total Rent Reductions | B35: =SUM(B31:B34) -> 0 | C35: =IFERROR(B35/$B$22,0) -> 0 | D35: =IFERROR(B35/($B$19*12),0) -> 0 | F35: ok
A37: F. TAX & INSURANCE ACCRUAL CHECK
A38: T-12 actuals rarely equal pro forma. Triangulate RE taxes with reassessment estimate; insurance with lender quote.
A40: Real Estate Taxes
A41: T-12 Actual | B41: =N120 -> 0
A42: Pro Forma Estimate | B42: ='P&L'!D86 -> 0
A43: Variance (Actual − PF) | B43: =B41-B42 -> 0
A44: Status | B44: =IF(B41=0,"⚠ not in T-12 — verify with operator / broker",IF(IFERROR(ABS(B43)/B42,1)>0.1,"⚠ variance >10% — review","✓ in range")) -> ⚠ not in T-12 — verify with operator / broker
A46: P&C Insurance
A47: T-12 Actual | B47: =N115 -> 0
A48: Pro Forma Estimate | B48: ='P&L'!D82 -> 0
A49: Variance (Actual − PF) | B49: =B47-B48 -> 0
A50: Status | B50: =IF(B47=0,"⚠ not in T-12 — verify with operator / broker",IF(IFERROR(ABS(B49)/B48,1)>0.1,"⚠ variance >10% — review","✓ in range")) -> ⚠ not in T-12 — verify with operator / broker
A54: ↓ ↓ ↓ DATA TIER BELOW — Standardized Aggregation (Layer 3) and Raw T-12 (Layer 1) ↓ ↓ ↓
A55: H. LAYER 3: STANDARDIZED AGGREGATION — Bucket-level detail (paste from Analyzer UW Export, col E)
A56: Standardized Bucket | B56: =C140 -> Apr-25 | C56: =D140 -> May-25 | D56: =E140 -> Jun-25 | E56: =F140 -> Jul-25 | F56: =G140 -> Aug-25 | G56: =H140 -> Sep-25 | H56: =I140 -> Oct-25 | I56: =J140 -> Nov-25 | ... M56: =N140 -> Mar-26 | N56: T-12 Total | O56: T-3 Annlzd | P56: Per Bed/Mo | Q56: % of EGI | R56: Bench Flag
A57: INCOME (Actual — per T-12)
A58: Base Rent — IL | N58: =SUM(B58:M58) -> 0 | O58: =SUM(K58:M58)*4 -> 0 | P58: =IFERROR(N58/$B$20/12,0) -> 0 | Q58: =IFERROR(N58/N$80,0) -> 0
A59: Base Rent — AL | N59: =SUM(B59:M59) -> 0 | O59: =SUM(K59:M59)*4 -> 0 | P59: =IFERROR(N59/$B$20/12,0) -> 0 | Q59: =IFERROR(N59/N$80,0) -> 0
A60: Base Rent — MC | N60: =SUM(B60:M60) -> 0 | O60: =SUM(K60:M60)*4 -> 0 | P60: =IFERROR(N60/$B$20/12,0) -> 0 | Q60: =IFERROR(N60/N$80,0) -> 0
A61: =" Base Rent — Other Care ("&'Prop Info'!$D$13&")" -> Base Rent — Other Care () | N61: =SUM(B61:M61) -> 0 | O61: =SUM(K61:M61)*4 -> 0 | P61: =IFERROR(N61/$B$20/12,0) -> 0 | Q61: =IFERROR(N61/N$80,0) -> 0
A62: Total Base Rent | N62: =SUM(N58:N61) -> 0 | O62: =SUM(K62:M62)*4 -> 0 | P62: =IFERROR(N62/$B$20/12,0) -> 0 | Q62: =IFERROR(N62/N$80,0) -> 0
A63: LOC / Care Services — IL | N63: =SUM(B63:M63) -> 0 | O63: =SUM(K63:M63)*4 -> 0 | P63: =IFERROR(N63/$B$20/12,0) -> 0 | Q63: =IFERROR(N63/N$80,0) -> 0
A64: LOC / Care Services — AL | N64: =SUM(B64:M64) -> 0 | O64: =SUM(K64:M64)*4 -> 0 | P64: =IFERROR(N64/$B$20/12,0) -> 0 | Q64: =IFERROR(N64/N$80,0) -> 0
A65: LOC / Care Services — MC | N65: =SUM(B65:M65) -> 0 | O65: =SUM(K65:M65)*4 -> 0 | P65: =IFERROR(N65/$B$20/12,0) -> 0 | Q65: =IFERROR(N65/N$80,0) -> 0
A66: =" LOC / Care Services — Other Care ("&'Prop Info'!$D$13&")" -> LOC / Care Services — Other Care () | N66: =SUM(B66:M66) -> 0 | O66: =SUM(K66:M66)*4 -> 0 | P66: =IFERROR(N66/$B$20/12,0) -> 0 | Q66: =IFERROR(N66/N$80,0) -> 0
A67: Total LOC / Care Services | N67: =SUM(N63:N66) -> 0 | O67: =SUM(K67:M67)*4 -> 0 | P67: =IFERROR(N67/$B$20/12,0) -> 0 | Q67: =IFERROR(N67/N$80,0) -> 0
A68: 2nd Person Revenue | N68: =SUM(B68:M68) -> 0 | O68: =SUM(K68:M68)*4 -> 0 | P68: =IFERROR(N68/$B$20/12,0) -> 0 | Q68: =IFERROR(N68/N$80,0) -> 0
A69: Community / Move-in Fees | N69: =SUM(B69:M69) -> 0 | O69: =SUM(K69:M69)*4 -> 0 | P69: =IFERROR(N69/$B$20/12,0) -> 0 | Q69: =IFERROR(N69/N$80,0) -> 0
A70: Respite Care Revenue | N70: =SUM(B70:M70) -> 0 | O70: =SUM(K70:M70)*4 -> 0 | P70: =IFERROR(N70/$B$20/12,0) -> 0 | Q70: =IFERROR(N70/N$80,0) -> 0
A71: Meal Income | N71: =SUM(B71:M71) -> 0 | O71: =SUM(K71:M71)*4 -> 0 | P71: =IFERROR(N71/$B$20/12,0) -> 0 | Q71: =IFERROR(N71/N$80,0) -> 0
A72: Housekeeping Income | N72: =SUM(B72:M72) -> 0 | O72: =SUM(K72:M72)*4 -> 0 | P72: =IFERROR(N72/$B$20/12,0) -> 0 | Q72: =IFERROR(N72/N$80,0) -> 0
A73: Laundry Income | N73: =SUM(B73:M73) -> 0 | O73: =SUM(K73:M73)*4 -> 0 | P73: =IFERROR(N73/$B$20/12,0) -> 0 | Q73: =IFERROR(N73/N$80,0) -> 0
A74: Scooter Fee Revenue | N74: =SUM(B74:M74) -> 0 | O74: =SUM(K74:M74)*4 -> 0 | P74: =IFERROR(N74/$B$20/12,0) -> 0 | Q74: =IFERROR(N74/N$80,0) -> 0
A75: Transfer Fee Revenue | N75: =SUM(B75:M75) -> 0 | O75: =SUM(K75:M75)*4 -> 0 | P75: =IFERROR(N75/$B$20/12,0) -> 0 | Q75: =IFERROR(N75/N$80,0) -> 0
A76: Other Community Revenue | N76: =SUM(B76:M76) -> 0 | O76: =SUM(K76:M76)*4 -> 0 | P76: =IFERROR(N76/$B$20/12,0) -> 0 | Q76: =IFERROR(N76/N$80,0) -> 0
A77: Less: Vacancy / Credit Loss (actual) | N77: =SUM(B77:M77) -> 0 | O77: =SUM(K77:M77)*4 -> 0 | P77: =IFERROR(N77/$B$20/12,0) -> 0 | Q77: =IFERROR(N77/N$80,0) -> 0
A78: Concessions & Specials (contra) | N78: =SUM(B78:M78) -> 0 | O78: =SUM(K78:M78)*4 -> 0 | P78: =IFERROR(N78/$B$20/12,0) -> 0 | Q78: =IFERROR(N78/N$80,0) -> 0
A79: Bad Debt / Write-offs (contra) | N79: =SUM(B79:M79) -> 0 | O79: =SUM(K79:M79)*4 -> 0 | P79: =IFERROR(N79/$B$20/12,0) -> 0 | Q79: =IFERROR(N79/N$80,0) -> 0
A80: EFFECTIVE GROSS INCOME (EGI) | N80: =N62+N67+SUM(N68:N79) -> 0 | O80: =SUM(K80:M80)*4 -> 0 | P80: =IFERROR(N80/$B$20/12,0) -> 0 | Q80: =IFERROR(N80/N$80,0) -> 0
A82: GPR WATERFALL — DIAGNOSTIC (RR market projection; NOT T-12 actual) | N82: T-12 Total | O82: T-3 Annlzd | P82: Per Bed/Mo | Q82: % of EGI | R82: Bench Flag | S82: vs T-12 Actual ($) | T82: vs T-12 (%)
A83: Gross Potential Rent (GPR) | N83: =IFERROR('Rent Roll Analysis'!B30,0) -> 0 | P83: =IFERROR(N83/$B$20/12,0) -> 0 | Q83: =IFERROR(N83/N$80,0) -> 0 | S83: Market GPR (RR ann.)
A84: Less: Loss to Lease | N84: =-IFERROR('Rent Roll Analysis'!B32,0) -> 0 | P84: =IFERROR(N84/$B$20/12,0) -> 0 | Q84: =IFERROR(N84/N$80,0) -> 0
A85: Less: Vacancy Loss | N85: =-IFERROR('Rent Roll Analysis'!B34,0) -> 0 | P85: =IFERROR(N85/$B$20/12,0) -> 0 | Q85: =IFERROR(N85/N$80,0) -> 0
A86: Net Rent (projected) | N86: =N83+N84+N85 -> 0 | P86: =IFERROR(N86/$B$20/12,0) -> 0 | Q86: =IFERROR(N86/N$80,0) -> 0 | S86: =N86-N62 -> 0 | T86: =IFERROR(N86/N62-1,0) -> 0
A87: LABOR — Wages & Burden
A88: Care Staff Labor | B88: 0 | C88: 0 | D88: 0 | E88: 0 | F88: 0 | G88: 0 | H88: 0 | I88: 0 | J88: 0 | K88: 0 | L88: 0 | M88: 0 | N88: =SUM(B88:M88) -> 0 | O88: =SUM(K88:M88)*4 -> 0 | P88: =IFERROR(N88/$B$20/12,0) -> 0 | Q88: =IFERROR(N88/N$80,0) -> 0 | R88: < $500/bed/mo target
A89: Wellness / Care Coordinators | B89: 0 | C89: 0 | D89: 0 | E89: 0 | F89: 0 | G89: 0 | H89: 0 | I89: 0 | J89: 0 | K89: 0 | L89: 0 | M89: 0 | N89: =SUM(B89:M89) -> 0 | O89: =SUM(K89:M89)*4 -> 0 | P89: =IFERROR(N89/$B$20/12,0) -> 0 | Q89: =IFERROR(N89/N$80,0) -> 0
A90: Contract / Agency Labor | B90: 0 | C90: 0 | D90: 0 | E90: 0 | F90: 0 | G90: 0 | H90: 0 | I90: 0 | J90: 0 | K90: 0 | L90: 0 | M90: 0 | N90: =SUM(B90:M90) -> 0 | O90: =SUM(K90:M90)*4 -> 0 | P90: =IFERROR(N90/$B$20/12,0) -> 0 | Q90: =IFERROR(N90/N$80,0) -> 0 | R90: < 2% of total labor ✓
A91: Activities Labor | B91: 0 | C91: 0 | D91: 0 | E91: 0 | F91: 0 | G91: 0 | H91: 0 | I91: 0 | J91: 0 | K91: 0 | L91: 0 | M91: 0 | N91: =SUM(B91:M91) -> 0 | O91: =SUM(K91:M91)*4 -> 0 | P91: =IFERROR(N91/$B$20/12,0) -> 0 | Q91: =IFERROR(N91/N$80,0) -> 0
A92: Dining / Food Service Labor | B92: 0 | C92: 0 | D92: 0 | E92: 0 | F92: 0 | G92: 0 | H92: 0 | I92: 0 | J92: 0 | K92: 0 | L92: 0 | M92: 0 | N92: =SUM(B92:M92) -> 0 | O92: =SUM(K92:M92)*4 -> 0 | P92: =IFERROR(N92/$B$20/12,0) -> 0 | Q92: =IFERROR(N92/N$80,0) -> 0
A93: Maintenance & HK Labor | B93: 0 | C93: 0 | D93: 0 | E93: 0 | F93: 0 | G93: 0 | H93: 0 | I93: 0 | J93: 0 | K93: 0 | L93: 0 | M93: 0 | N93: =SUM(B93:M93) -> 0 | O93: =SUM(K93:M93)*4 -> 0 | P93: =IFERROR(N93/$B$20/12,0) -> 0 | Q93: =IFERROR(N93/N$80,0) -> 0
A94: Administrative Labor | B94: 0 | C94: 0 | D94: 0 | E94: 0 | F94: 0 | G94: 0 | H94: 0 | I94: 0 | J94: 0 | K94: 0 | L94: 0 | M94: 0 | N94: =SUM(B94:M94) -> 0 | O94: =SUM(K94:M94)*4 -> 0 | P94: =IFERROR(N94/$B$20/12,0) -> 0 | Q94: =IFERROR(N94/N$80,0) -> 0
A95: Bonus Wages | B95: 0 | C95: 0 | D95: 0 | E95: 0 | F95: 0 | G95: 0 | H95: 0 | I95: 0 | J95: 0 | K95: 0 | L95: 0 | M95: 0 | N95: =SUM(B95:M95) -> 0 | O95: =SUM(K95:M95)*4 -> 0 | P95: =IFERROR(N95/$B$20/12,0) -> 0 | Q95: =IFERROR(N95/N$80,0) -> 0
A96: Overtime Wages | B96: 0 | C96: 0 | D96: 0 | E96: 0 | F96: 0 | G96: 0 | H96: 0 | I96: 0 | J96: 0 | K96: 0 | L96: 0 | M96: 0 | N96: =SUM(B96:M96) -> 0 | O96: =SUM(K96:M96)*4 -> 0 | P96: =IFERROR(N96/$B$20/12,0) -> 0 | Q96: =IFERROR(N96/N$80,0) -> 0 | R96: < 6% of labor ✓; > 8% ✗
A97: PTO Wages | B97: 0 | C97: 0 | D97: 0 | E97: 0 | F97: 0 | G97: 0 | H97: 0 | I97: 0 | J97: 0 | K97: 0 | L97: 0 | M97: 0 | N97: =SUM(B97:M97) -> 0 | O97: =SUM(K97:M97)*4 -> 0 | P97: =IFERROR(N97/$B$20/12,0) -> 0 | Q97: =IFERROR(N97/N$80,0) -> 0
A98: Payroll Taxes | B98: 0 | C98: 0 | D98: 0 | E98: 0 | F98: 0 | G98: 0 | H98: 0 | I98: 0 | J98: 0 | K98: 0 | L98: 0 | M98: 0 | N98: =SUM(B98:M98) -> 0 | O98: =SUM(K98:M98)*4 -> 0 | P98: =IFERROR(N98/$B$20/12,0) -> 0 | Q98: =IFERROR(N98/N$80,0) -> 0 | R98: ~7.65% of gross wages
A99: Employee Benefits | B99: 0 | C99: 0 | D99: 0 | E99: 0 | F99: 0 | G99: 0 | H99: 0 | I99: 0 | J99: 0 | K99: 0 | L99: 0 | M99: 0 | N99: =SUM(B99:M99) -> 0 | O99: =SUM(K99:M99)*4 -> 0 | P99: =IFERROR(N99/$B$20/12,0) -> 0 | Q99: =IFERROR(N99/N$80,0) -> 0
A100: Workers' Comp Insurance | B100: 0 | C100: 0 | D100: 0 | E100: 0 | F100: 0 | G100: 0 | H100: 0 | I100: 0 | J100: 0 | K100: 0 | L100: 0 | M100: 0 | N100: =SUM(B100:M100) -> 0 | O100: =SUM(K100:M100)*4 -> 0 | P100: =IFERROR(N100/$B$20/12,0) -> 0 | Q100: =IFERROR(N100/N$80,0) -> 0
A101: Employee 401(k) | B101: 0 | C101: 0 | D101: 0 | E101: 0 | F101: 0 | G101: 0 | H101: 0 | I101: 0 | J101: 0 | K101: 0 | L101: 0 | M101: 0 | N101: =SUM(B101:M101) -> 0 | O101: =SUM(K101:M101)*4 -> 0 | P101: =IFERROR(N101/$B$20/12,0) -> 0 | Q101: =IFERROR(N101/N$80,0) -> 0
A102: TOTAL LABOR & BURDEN | B102: =SUM(B88:B101) -> 0 | C102: =SUM(C88:C101) -> 0 | D102: =SUM(D88:D101) -> 0 | E102: =SUM(E88:E101) -> 0 | F102: =SUM(F88:F101) -> 0 | G102: =SUM(G88:G101) -> 0 | H102: =SUM(H88:H101) -> 0 | I102: =SUM(I88:I101) -> 0 | ... N102: =SUM(N88:N101) -> 0 | O102: =SUM(K102:M102)*4 -> 0 | P102: =IFERROR(N102/$B$20/12,0) -> 0 | Q102: =IFERROR(N102/N$80,0) -> 0 | R102: < 55% EGI ✓; > 60% ✗
A103: NON-LABOR OPERATING EXPENSES
A104: Food Cost | B104: 0 | C104: 0 | D104: 0 | E104: 0 | F104: 0 | G104: 0 | H104: 0 | I104: 0 | J104: 0 | K104: 0 | L104: 0 | M104: 0 | N104: =SUM(B104:M104) -> 0 | O104: =SUM(K104:M104)*4 -> 0 | P104: =IFERROR(N104/$B$20/12,0) -> 0 | Q104: =IFERROR(N104/N$80,0) -> 0 | R104: < $200/bed/mo ✓; > $250 ✗
A105: Dining & Kitchen Supplies | B105: 0 | C105: 0 | D105: 0 | E105: 0 | F105: 0 | G105: 0 | H105: 0 | I105: 0 | J105: 0 | K105: 0 | L105: 0 | M105: 0 | N105: =SUM(B105:M105) -> 0 | O105: =SUM(K105:M105)*4 -> 0 | P105: =IFERROR(N105/$B$20/12,0) -> 0 | Q105: =IFERROR(N105/N$80,0) -> 0
A106: Nursing & Care Supplies | B106: 0 | C106: 0 | D106: 0 | E106: 0 | F106: 0 | G106: 0 | H106: 0 | I106: 0 | J106: 0 | K106: 0 | L106: 0 | M106: 0 | N106: =SUM(B106:M106) -> 0 | O106: =SUM(K106:M106)*4 -> 0 | P106: =IFERROR(N106/$B$20/12,0) -> 0 | Q106: =IFERROR(N106/N$80,0) -> 0
A107: Recreation Supplies | B107: 0 | C107: 0 | D107: 0 | E107: 0 | F107: 0 | G107: 0 | H107: 0 | I107: 0 | J107: 0 | K107: 0 | L107: 0 | M107: 0 | N107: =SUM(B107:M107) -> 0 | O107: =SUM(K107:M107)*4 -> 0 | P107: =IFERROR(N107/$B$20/12,0) -> 0 | Q107: =IFERROR(N107/N$80,0) -> 0
A108: R&M — Fixed | B108: 0 | C108: 0 | D108: 0 | E108: 0 | F108: 0 | G108: 0 | H108: 0 | I108: 0 | J108: 0 | K108: 0 | L108: 0 | M108: 0 | N108: =SUM(B108:M108) -> 0 | O108: =SUM(K108:M108)*4 -> 0 | P108: =IFERROR(N108/$B$20/12,0) -> 0 | Q108: =IFERROR(N108/N$80,0) -> 0
A109: R&M — Variable | B109: 0 | C109: 0 | D109: 0 | E109: 0 | F109: 0 | G109: 0 | H109: 0 | I109: 0 | J109: 0 | K109: 0 | L109: 0 | M109: 0 | N109: =SUM(B109:M109) -> 0 | O109: =SUM(K109:M109)*4 -> 0 | P109: =IFERROR(N109/$B$20/12,0) -> 0 | Q109: =IFERROR(N109/N$80,0) -> 0
A110: HK & Laundry Supplies | B110: 0 | C110: 0 | D110: 0 | E110: 0 | F110: 0 | G110: 0 | H110: 0 | I110: 0 | J110: 0 | K110: 0 | L110: 0 | M110: 0 | N110: =SUM(B110:M110) -> 0 | O110: =SUM(K110:M110)*4 -> 0 | P110: =IFERROR(N110/$B$20/12,0) -> 0 | Q110: =IFERROR(N110/N$80,0) -> 0
A111: Sales, Adv. & Marketing | B111: 0 | C111: 0 | D111: 0 | E111: 0 | F111: 0 | G111: 0 | H111: 0 | I111: 0 | J111: 0 | K111: 0 | L111: 0 | M111: 0 | N111: =SUM(B111:M111) -> 0 | O111: =SUM(K111:M111)*4 -> 0 | P111: =IFERROR(N111/$B$20/12,0) -> 0 | Q111: =IFERROR(N111/N$80,0) -> 0
...

Sheet Acquisition Costs
A1: ACQUISITION COSTS — USE OF CAPITAL
A3: USE OF CAPITAL SUMMARY
A4: Purchase Price | D4: =Scenarios!F7 -> 0
A5: Less: Total Loan Amount | D5: =-Scenarios!F23 -> 0
A6: Down Payment Required | D6: =D4+D5 -> 0
A7: Closing Costs | D7: =D37
A8: Acquisition Fee | B8: =Scenarios!F15 -> 0 | D8: =Scenarios!F16 -> 0
A9: Repair Escrow / CapEx | D9: =Scenarios!F12 -> 0
A10: Operating Reserves | D10: =Scenarios!F13 -> 0
A11: TOTAL CASH AT CLOSE | D11: =SUM(D6:D10) -> 0
A13: CLOSING COSTS DETAIL
A14: Item | B14: Rate/Factor | C14: Notes | D14: Amount
A15: LENDER FEES & THIRD-PARTY COSTS
A16: Environmental (EDR)
A17: Appraisal
A18: Structural Inspection
A19: Lender Legal Fees
A20: Bank Doc Prep Fee
A21: Origination Fee | B21: =Scenarios!F146 -> 0 | C21: Total origination fees — all tranches | D21: =Scenarios!F146*Scenarios!F141+Scenarios!F153*Scenarios!F148+Scenarios!F160*Scenarios!F155 -> 0
A22: TITLE & CLOSING COSTS
A23: Title Policy | B23: 0.003 | C23: 0.30% of purchase price | D23: =B23*Scenarios!F7 -> 0
A24: Survey
A25: Recording
A26: Transfer Taxes | B26: 0.0035 | C26: 0.35% of purchase price | D26: =B26*Scenarios!F7 -> 0
A27: Title Processing Fee
A28: Title Search
A29: Attorney Fees
A30: OTHER COSTS
A31: Legal (LLC, PPM, OA)
A32: Property Inspection
A33: Travel
A34: Miscellaneous
A35: RE Taxes | D35: =Scenarios!F114/4 -> 0
A36: Insurance | D36: =Scenarios!F110/4 -> 0
A37: TOTAL CLOSING & OTHER COSTS | D37: =IF(D4=0, "",SUM(D16:D36))
A38: Closing Costs excl. 1st-Loan Origination (LTC solver input) | D38: =IF(D4=0,0,SUM(D16:D20)+SUM(D22:D36)+Scenarios!F153*Scenarios!F148+Scenarios!F160*Scenarios!F155) -> 0

Sheet Staffing Matrix
A1: STAFFING MATRIX — PER-SHIFT | FTE BUILD | HPPD | TOTAL PAYROLL → P&L R28
A2: Blue=Input | Black=Formula | Green=Cross-sheet. Cell M69 (Total Payroll) feeds P&L!C28 automatically. Census pulled from Scenarios sheet.
A4: SECTION 1 — CENSUS & STAFFING RATE ASSUMPTIONS
A5: Total Units (physical rooms, from Scenarios) | C5: =IFERROR(Scenarios!F8,90) -> 0 | D5: Physical rooms ≠ licensed beds — see Prop Info for bed count
A6: AL Occupied Beds (Y1 census) | D6: Enter occupied bed count, not room count
A7: MC Occupied Beds (Y1 census) | D7: Enter occupied bed count, not room count
A8: IL Occupied Beds (Y1 census)
A9: Total Care Residents (AL + MC occupied beds) | C9: =C6+C7 -> 0
A10: Licensed Beds (from Prop Info — regulatory ceiling) | C10: =IFERROR('Prop Info'!$B$15,0) -> 0 | D10: Licensed beds = regulatory max. Occupied beds ≤ licensed beds.
A11: Rate & Cost Assumptions
A12: Benefits Load (FICA + health + 401k) | C12: 0.2 | D12: Typical 18–22%
A13: Overtime Load | C13: 0.05 | D13: 5% of base wages; AL/MC often higher
A14: Eve Differential ($/hr premium) | C14: 1.5 | D14: 3p–11p shift
A15: Night Differential ($/hr premium) | C15: 2.5 | D15: 11p–7a shift
A16: Weekend Premium ($/hr) | C16: 0.75 | D16: Added to shift differential
A18: Target Staffing Ratios (residents : 1 staff)
A19: Ratio-driven CNA rows auto-calculate headcount. Verify against your state DOH minimum requirements.
A20: AL — Day Shift (1:X residents per aide) | C20: 6 | D20: 1:6 day; increase MC urgency
A21: AL — Evening Shift (1:X) | C21: 7 | D21: 1:7 eve; lighter acuity overnight
A22: AL — Night Shift (1:X) | C22: 10 | D22: 1:10 night minimum
A23: MC — Day Shift (1:X) | C23: 5 | D23: 1:5 MC day; CMS recommends closer to 1:4
A24: MC — Evening Shift (1:X) | C24: 6 | D24: 1:6 MC eve
A25: MC — Night Shift (1:X) | C25: 8 | D25: 1:8 MC night
A27: SECTION 2 — PER-SHIFT HEADCOUNT MATRIX (staff per shift × 6 shifts)
C28: WEEKDAY | F28: WEEKEND | I28: Hrs/Wk | J28: FTEs | K28: Base $/hr | L28: Shift-Adj $/hr | M28: Annual Cost ($) | N28: % Total Payroll
A29: Position | B29: Dept | C29: Day 7a–3p | D29: Eve 3p–11p | E29: Night 11p–7a | F29: Day 7a–3p | G29: Eve 3p–11p | H29: Night 11p–7a
A30: Care Staff
A31: Director of Nursing | B31: Care | D31: 0 | E31: 0 | G31: 0 | H31: 0 | I31: =((C31+D31+E31)*5+(F31+G31+H31)*2)*8 -> 0 | J31: =IFERROR(I31*52/2080,0) -> 0 | L31: =IFERROR((C31*K31+D31*(K31+$C$14)+E31*(K31+$C$15)+F31*(K31+$C$16)+G31*(K31+$C$14+$C$16)+H31*(K31+$C$15+$C$16))/MAX(C31+D31+E31+F31+G31+H31,1),K31) -> 0 | M31: =IFERROR(J31*2080*L31*(1+$C$12)*(1+$C$13),0) -> 0 | N31: =IFERROR(M31/M67,0) -> 0
A32: RN / Asst DON | B32: Care | E32: 0 | G32: 0 | H32: 0 | I32: =((C32+D32+E32)*5+(F32+G32+H32)*2)*8 -> 0 | J32: =IFERROR(I32*52/2080,0) -> 0 | L32: =IFERROR((C32*K32+D32*(K32+$C$14)+E32*(K32+$C$15)+F32*(K32+$C$16)+G32*(K32+$C$14+$C$16)+H32*(K32+$C$15+$C$16))/MAX(C32+D32+E32+F32+G32+H32,1),K32) -> 0 | M32: =IFERROR(J32*2080*L32*(1+$C$12)*(1+$C$13),0) -> 0 | N32: =IFERROR(M32/M67,0) -> 0
A33: Med Tech / CMA | B33: Care | I33: =((C33+D33+E33)*5+(F33+G33+H33)*2)*8 -> 0 | J33: =IFERROR(I33*52/2080,0) -> 0 | L33: =IFERROR((C33*K33+D33*(K33+$C$14)+E33*(K33+$C$15)+F33*(K33+$C$16)+G33*(K33+$C$14+$C$16)+H33*(K33+$C$15+$C$16))/MAX(C33+D33+E33+F33+G33+H33,1),K33) -> 0 | M33: =IFERROR(J33*2080*L33*(1+$C$12)*(1+$C$13),0) -> 0 | N33: =IFERROR(M33/M67,0) -> 0
A34: CNA — Day (AL) | B34: Care | C34: =IFERROR(CEILING(C6/C20,1),0) -> 0 | D34: 0 | E34: 0 | F34: =IFERROR(CEILING(C6/C20,1),0) -> 0 | G34: 0 | H34: 0 | I34: =((C34+D34+E34)*5+(F34+G34+H34)*2)*8 -> 0 | J34: =IFERROR(I34*52/2080,0) -> 0 | L34: =IFERROR((C34*K34+D34*(K34+$C$14)+E34*(K34+$C$15)+F34*(K34+$C$16)+G34*(K34+$C$14+$C$16)+H34*(K34+$C$15+$C$16))/MAX(C34+D34+E34+F34+G34+H34,1),K34) -> 0 | M34: =IFERROR(J34*2080*L34*(1+$C$12)*(1+$C$13),0) -> 0 | N34: =IFERROR(M34/M67,0) -> 0
A35: CNA — Eve (AL) | B35: Care | C35: 0 | D35: =IFERROR(CEILING(C6/C21,1),0) -> 0 | E35: 0 | F35: 0 | G35: =IFERROR(CEILING(C6/C21,1),0) -> 0 | H35: 0 | I35: =((C35+D35+E35)*5+(F35+G35+H35)*2)*8 -> 0 | J35: =IFERROR(I35*52/2080,0) -> 0 | L35: =IFERROR((C35*K35+D35*(K35+$C$14)+E35*(K35+$C$15)+F35*(K35+$C$16)+G35*(K35+$C$14+$C$16)+H35*(K35+$C$15+$C$16))/MAX(C35+D35+E35+F35+G35+H35,1),K35) -> 0 | M35: =IFERROR(J35*2080*L35*(1+$C$12)*(1+$C$13),0) -> 0 | N35: =IFERROR(M35/M67,0) -> 0
A36: CNA — Night (AL) | B36: Care | C36: 0 | D36: 0 | E36: =IFERROR(CEILING(C6/C22,1),0) -> 0 | F36: 0 | G36: 0 | H36: =IFERROR(CEILING(C6/C22,1),0) -> 0 | I36: =((C36+D36+E36)*5+(F36+G36+H36)*2)*8 -> 0 | J36: =IFERROR(I36*52/2080,0) -> 0 | L36: =IFERROR((C36*K36+D36*(K36+$C$14)+E36*(K36+$C$15)+F36*(K36+$C$16)+G36*(K36+$C$14+$C$16)+H36*(K36+$C$15+$C$16))/MAX(C36+D36+E36+F36+G36+H36,1),K36) -> 0 | M36: =IFERROR(J36*2080*L36*(1+$C$12)*(1+$C$13),0) -> 0 | N36: =IFERROR(M36/M67,0) -> 0
A37: CNA — Day (MC) | B37: Care | C37: =IFERROR(CEILING(C7/C23,1),0) -> 0 | D37: 0 | E37: 0 | F37: =IFERROR(CEILING(C7/C23,1),0) -> 0 | G37: 0 | H37: 0 | I37: =((C37+D37+E37)*5+(F37+G37+H37)*2)*8 -> 0 | J37: =IFERROR(I37*52/2080,0) -> 0 | L37: =IFERROR((C37*K37+D37*(K37+$C$14)+E37*(K37+$C$15)+F37*(K37+$C$16)+G37*(K37+$C$14+$C$16)+H37*(K37+$C$15+$C$16))/MAX(C37+D37+E37+F37+G37+H37,1),K37) -> 0 | M37: =IFERROR(J37*2080*L37*(1+$C$12)*(1+$C$13),0) -> 0 | N37: =IFERROR(M37/M67,0) -> 0
A38: CNA — Eve (MC) | B38: Care | C38: 0 | D38: =IFERROR(CEILING(C7/C24,1),0) -> 0 | E38: 0 | F38: 0 | G38: =IFERROR(CEILING(C7/C24,1),0) -> 0 | H38: 0 | I38: =((C38+D38+E38)*5+(F38+G38+H38)*2)*8 -> 0 | J38: =IFERROR(I38*52/2080,0) -> 0 | L38: =IFERROR((C38*K38+D38*(K38+$C$14)+E38*(K38+$C$15)+F38*(K38+$C$16)+G38*(K38+$C$14+$C$16)+H38*(K38+$C$15+$C$16))/MAX(C38+D38+E38+F38+G38+H38,1),K38) -> 0 | M38: =IFERROR(J38*2080*L38*(1+$C$12)*(1+$C$13),0) -> 0 | N38: =IFERROR(M38/M67,0) -> 0
A39: CNA — Night (MC) | B39: Care | C39: 0 | D39: 0 | E39: =IFERROR(CEILING(C7/C25,1),0) -> 0 | F39: 0 | G39: 0 | H39: =IFERROR(CEILING(C7/C25,1),0) -> 0 | I39: =((C39+D39+E39)*5+(F39+G39+H39)*2)*8 -> 0 | J39: =IFERROR(I39*52/2080,0) -> 0 | L39: =IFERROR((C39*K39+D39*(K39+$C$14)+E39*(K39+$C$15)+F39*(K39+$C$16)+G39*(K39+$C$14+$C$16)+H39*(K39+$C$15+$C$16))/MAX(C39+D39+E39+F39+G39+H39,1),K39) -> 0 | M39: =IFERROR(J39*2080*L39*(1+$C$12)*(1+$C$13),0) -> 0 | N39: =IFERROR(M39/M67,0) -> 0
A40: Subtotal — Care Staff | C40: =SUM(C31:C39) -> 0 | D40: =SUM(D31:D39) -> 0 | E40: =SUM(E31:E39) -> 0 | F40: =SUM(F31:F39) -> 0 | G40: =SUM(G31:G39) -> 0 | H40: =SUM(H31:H39) -> 0 | I40: =SUM(I31:I39) -> 0 | J40: =SUM(J31:J39) -> 0 | M40: =SUM(M31:M39) -> 0
A42: Dining
A43: Dining Manager / Chef | B43: Dining | E43: 0 | H43: 0 | I43: =((C43+D43+E43)*5+(F43+G43+H43)*2)*8 -> 0 | J43: =IFERROR(I43*52/2080,0) -> 0 | L43: =IFERROR((C43*K43+D43*(K43+$C$14)+E43*(K43+$C$15)+F43*(K43+$C$16)+G43*(K43+$C$14+$C$16)+H43*(K43+$C$15+$C$16))/MAX(C43+D43+E43+F43+G43+H43,1),K43) -> 0 | M43: =IFERROR(J43*2080*L43*(1+$C$12)*(1+$C$13),0) -> 0 | N43: =IFERROR(M43/M67,0) -> 0
A44: Cook | B44: Dining | E44: 0 | H44: 0 | I44: =((C44+D44+E44)*5+(F44+G44+H44)*2)*8 -> 0 | J44: =IFERROR(I44*52/2080,0) -> 0 | L44: =IFERROR((C44*K44+D44*(K44+$C$14)+E44*(K44+$C$15)+F44*(K44+$C$16)+G44*(K44+$C$14+$C$16)+H44*(K44+$C$15+$C$16))/MAX(C44+D44+E44+F44+G44+H44,1),K44) -> 0 | M44: =IFERROR(J44*2080*L44*(1+$C$12)*(1+$C$13),0) -> 0 | N44: =IFERROR(M44/M67,0) -> 0
A45: Dietary Aide / Server | B45: Dining | E45: 0 | H45: 0 | I45: =((C45+D45+E45)*5+(F45+G45+H45)*2)*8 -> 0 | J45: =IFERROR(I45*52/2080,0) -> 0 | L45: =IFERROR((C45*K45+D45*(K45+$C$14)+E45*(K45+$C$15)+F45*(K45+$C$16)+G45*(K45+$C$14+$C$16)+H45*(K45+$C$15+$C$16))/MAX(C45+D45+E45+F45+G45+H45,1),K45) -> 0 | M45: =IFERROR(J45*2080*L45*(1+$C$12)*(1+$C$13),0) -> 0 | N45: =IFERROR(M45/M67,0) -> 0
A46: Dishwasher | B46: Dining | E46: 0 | H46: 0 | I46: =((C46+D46+E46)*5+(F46+G46+H46)*2)*8 -> 0 | J46: =IFERROR(I46*52/2080,0) -> 0 | L46: =IFERROR((C46*K46+D46*(K46+$C$14)+E46*(K46+$C$15)+F46*(K46+$C$16)+G46*(K46+$C$14+$C$16)+H46*(K46+$C$15+$C$16))/MAX(C46+D46+E46+F46+G46+H46,1),K46) -> 0 | M46: =IFERROR(J46*2080*L46*(1+$C$12)*(1+$C$13),0) -> 0 | N46: =IFERROR(M46/M67,0) -> 0
A47: Subtotal — Dining | C47: =SUM(C43:C46) -> 0 | D47: =SUM(D43:D46) -> 0 | E47: =SUM(E43:E46) -> 0 | F47: =SUM(F43:F46) -> 0 | G47: =SUM(G43:G46) -> 0 | H47: =SUM(H43:H46) -> 0 | I47: =SUM(I43:I46) -> 0 | J47: =SUM(J43:J46) -> 0 | M47: =SUM(M43:M46) -> 0
A49: Housekeeping / Laundry
A50: Housekeeper Sup. | B50: H/K | D50: 0 | E50: 0 | G50: 0 | H50: 0 | I50: =((C50+D50+E50)*5+(F50+G50+H50)*2)*8 -> 0 | J50: =IFERROR(I50*52/2080,0) -> 0 | L50: =IFERROR((C50*K50+D50*(K50+$C$14)+E50*(K50+$C$15)+F50*(K50+$C$16)+G50*(K50+$C$14+$C$16)+H50*(K50+$C$15+$C$16))/MAX(C50+D50+E50+F50+G50+H50,1),K50) -> 0 | M50: =IFERROR(J50*2080*L50*(1+$C$12)*(1+$C$13),0) -> 0 | N50: =IFERROR(M50/M67,0) -> 0
A51: Housekeeper | B51: H/K | D51: 0 | E51: 0 | G51: 0 | H51: 0 | I51: =((C51+D51+E51)*5+(F51+G51+H51)*2)*8 -> 0 | J51: =IFERROR(I51*52/2080,0) -> 0 | L51: =IFERROR((C51*K51+D51*(K51+$C$14)+E51*(K51+$C$15)+F51*(K51+$C$16)+G51*(K51+$C$14+$C$16)+H51*(K51+$C$15+$C$16))/MAX(C51+D51+E51+F51+G51+H51,1),K51) -> 0 | M51: =IFERROR(J51*2080*L51*(1+$C$12)*(1+$C$13),0) -> 0 | N51: =IFERROR(M51/M67,0) -> 0
A52: Laundry Aide | B52: H/K | E52: 0 | G52: 0 | H52: 0 | I52: =((C52+D52+E52)*5+(F52+G52+H52)*2)*8 -> 0 | J52: =IFERROR(I52*52/2080,0) -> 0 | L52: =IFERROR((C52*K52+D52*(K52+$C$14)+E52*(K52+$C$15)+F52*(K52+$C$16)+G52*(K52+$C$14+$C$16)+H52*(K52+$C$15+$C$16))/MAX(C52+D52+E52+F52+G52+H52,1),K52) -> 0 | M52: =IFERROR(J52*2080*L52*(1+$C$12)*(1+$C$13),0) -> 0 | N52: =IFERROR(M52/M67,0) -> 0
A53: Subtotal — Housekeeping / Laundry | C53: =SUM(C50:C52) -> 0 | D53: =SUM(D50:D52) -> 0 | E53: =SUM(E50:E52) -> 0 | F53: =SUM(F50:F52) -> 0 | G53: =SUM(G50:G52) -> 0 | H53: =SUM(H50:H52) -> 0 | I53: =SUM(I50:I52) -> 0 | J53: =SUM(J50:J52) -> 0 | M53: =SUM(M50:M52) -> 0
A55: Maintenance, Activities & Admin
A56: Maintenance Sup. | B56: Maint | D56: 0 | E56: 0 | G56: 0 | H56: 0 | I56: =((C56+D56+E56)*5+(F56+G56+H56)*2)*8 -> 0 | J56: =IFERROR(I56*52/2080,0) -> 0 | L56: =IFERROR((C56*K56+D56*(K56+$C$14)+E56*(K56+$C$15)+F56*(K56+$C$16)+G56*(K56+$C$14+$C$16)+H56*(K56+$C$15+$C$16))/MAX(C56+D56+E56+F56+G56+H56,1),K56) -> 0 | M56: =IFERROR(J56*2080*L56*(1+$C$12)*(1+$C$13),0) -> 0 | N56: =IFERROR(M56/M67,0) -> 0
A57: Maintenance Tech | B57: Maint | D57: 0 | E57: 0 | G57: 0 | H57: 0 | I57: =((C57+D57+E57)*5+(F57+G57+H57)*2)*8 -> 0 | J57: =IFERROR(I57*52/2080,0) -> 0 | L57: =IFERROR((C57*K57+D57*(K57+$C$14)+E57*(K57+$C$15)+F57*(K57+$C$16)+G57*(K57+$C$14+$C$16)+H57*(K57+$C$15+$C$16))/MAX(C57+D57+E57+F57+G57+H57,1),K57) -> 0 | M57: =IFERROR(J57*2080*L57*(1+$C$12)*(1+$C$13),0) -> 0 | N57: =IFERROR(M57/M67,0) -> 0
A58: Activities Director | B58: Admin | E58: 0 | H58: 0 | I58: =((C58+D58+E58)*5+(F58+G58+H58)*2)*8 -> 0 | J58: =IFERROR(I58*52/2080,0) -> 0 | L58: =IFERROR((C58*K58+D58*(K58+$C$14)+E58*(K58+$C$15)+F58*(K58+$C$16)+G58*(K58+$C$14+$C$16)+H58*(K58+$C$15+$C$16))/MAX(C58+D58+E58+F58+G58+H58,1),K58) -> 0 | M58: =IFERROR(J58*2080*L58*(1+$C$12)*(1+$C$13),0) -> 0 | N58: =IFERROR(M58/M67,0) -> 0
A59: Activities Aide | B59: Admin | E59: 0 | H59: 0 | I59: =((C59+D59+E59)*5+(F59+G59+H59)*2)*8 -> 0 | J59: =IFERROR(I59*52/2080,0) -> 0 | L59: =IFERROR((C59*K59+D59*(K59+$C$14)+E59*(K59+$C$15)+F59*(K59+$C$16)+G59*(K59+$C$14+$C$16)+H59*(K59+$C$15+$C$16))/MAX(C59+D59+E59+F59+G59+H59,1),K59) -> 0 | M59: =IFERROR(J59*2080*L59*(1+$C$12)*(1+$C$13),0) -> 0 | N59: =IFERROR(M59/M67,0) -> 0
A60: Sales / Mktg Director | B60: Admin | D60: 0 | E60: 0 | G60: 0 | H60: 0 | I60: =((C60+D60+E60)*5+(F60+G60+H60)*2)*8 -> 0 | J60: =IFERROR(I60*52/2080,0) -> 0 | L60: =IFERROR((C60*K60+D60*(K60+$C$14)+E60*(K60+$C$15)+F60*(K60+$C$16)+G60*(K60+$C$14+$C$16)+H60*(K60+$C$15+$C$16))/MAX(C60+D60+E60+F60+G60+H60,1),K60) -> 0 | M60: =IFERROR(J60*2080*L60*(1+$C$12)*(1+$C$13),0) -> 0 | N60: =IFERROR(M60/M67,0) -> 0
A61: Business Office Mgr | B61: Admin | D61: 0 | E61: 0 | F61: 0 | G61: 0 | H61: 0 | I61: =((C61+D61+E61)*5+(F61+G61+H61)*2)*8 -> 0 | J61: =IFERROR(I61*52/2080,0) -> 0 | L61: =IFERROR((C61*K61+D61*(K61+$C$14)+E61*(K61+$C$15)+F61*(K61+$C$16)+G61*(K61+$C$14+$C$16)+H61*(K61+$C$15+$C$16))/MAX(C61+D61+E61+F61+G61+H61,1),K61) -> 0 | M61: =IFERROR(J61*2080*L61*(1+$C$12)*(1+$C$13),0) -> 0 | N61: =IFERROR(M61/M67,0) -> 0
A62: Receptionist | B62: Admin | E62: 0 | G62: 0 | H62: 0 | I62: =((C62+D62+E62)*5+(F62+G62+H62)*2)*8 -> 0 | J62: =IFERROR(I62*52/2080,0) -> 0 | L62: =IFERROR((C62*K62+D62*(K62+$C$14)+E62*(K62+$C$15)+F62*(K62+$C$16)+G62*(K62+$C$14+$C$16)+H62*(K62+$C$15+$C$16))/MAX(C62+D62+E62+F62+G62+H62,1),K62) -> 0 | M62: =IFERROR(J62*2080*L62*(1+$C$12)*(1+$C$13),0) -> 0 | N62: =IFERROR(M62/M67,0) -> 0
A63: Transportation Driver | B63: Admin | D63: 0 | E63: 0 | F63: 0 | G63: 0 | H63: 0 | I63: =((C63+D63+E63)*5+(F63+G63+H63)*2)*8 -> 0 | J63: =IFERROR(I63*52/2080,0) -> 0 | L63: =IFERROR((C63*K63+D63*(K63+$C$14)+E63*(K63+$C$15)+F63*(K63+$C$16)+G63*(K63+$C$14+$C$16)+H63*(K63+$C$15+$C$16))/MAX(C63+D63+E63+F63+G63+H63,1),K63) -> 0 | M63: =IFERROR(J63*2080*L63*(1+$C$12)*(1+$C$13),0) -> 0 | N63: =IFERROR(M63/M67,0) -> 0
A64: Executive Director | B64: Admin | D64: 0 | E64: 0 | F64: 0 | G64: 0 | H64: 0 | I64: =((C64+D64+E64)*5+(F64+G64+H64)*2)*8 -> 0 | J64: =IFERROR(I64*52/2080,0) -> 0 | L64: =IFERROR((C64*K64+D64*(K64+$C$14)+E64*(K64+$C$15)+F64*(K64+$C$16)+G64*(K64+$C$14+$C$16)+H64*(K64+$C$15+$C$16))/MAX(C64+D64+E64+F64+G64+H64,1),K64) -> 0 | M64: =IFERROR(J64*2080*L64*(1+$C$12)*(1+$C$13),0) -> 0 | N64: =IFERROR(M64/M67,0) -> 0
A65: Subtotal — Maintenance, Activities & Admin | C65: =SUM(C56:C64) -> 0 | D65: =SUM(D56:D64) -> 0 | E65: =SUM(E56:E64) -> 0 | F65: =SUM(F56:F64) -> 0 | G65: =SUM(G56:G64) -> 0 | H65: =SUM(H56:H64) -> 0 | I65: =SUM(I56:I64) -> 0 | J65: =SUM(J56:J64) -> 0 | M65: =SUM(M56:M64) -> 0
A67: TOTAL PAYROLL — ALL DEPARTMENTS →→ feeds P&L row 28 | C67: =C40+C47+C53+C65 -> 0 | D67: =D40+D47+D53+D65 -> 0 | E67: =E40+E47+E53+E65 -> 0 | F67: =F40+F47+F53+F65 -> 0 | G67: =G40+G47+G53+G65 -> 0 | H67: =H40+H47+H53+H65 -> 0 | I67: =I40+I47+I53+I65 -> 0 | J67: =J40+J47+J53+J65 -> 0 | M67: =M40+M47+M53+M65+O67 -> 0 | P67: Manual Entry
A69: SECTION 3 — STAFFING LOAD HEATMAP (actual vs. target ratios per shift)
A70: Green=at/below target | Orange=10–20% over target | Red=>20% over (understaffing risk)
A71: Shift | B71: Residents | C71: WD Staff | D71: WD Ratio (R:S) | E71: WE Staff | F71: WE Ratio (R:S) | G71: Target Ratio | H71: WD vs Target | I71: Status | J71: HPPD | K71: Benchmark
A72: AL — Day (7a–3p) | B72: =C6 -> 0 | C72: =C34 -> 0 | D72: =IFERROR(C6/C34,0) -> 0 | E72: =F34 -> 0 | F72: =IFERROR(C6/F34,0) -> 0 | G72: =C20 -> 6 | H72: =IFERROR(D72-G72,0) -> -6 | I72: =IFERROR(IF(D72<=G72,"On target",IF(D72<=G72*1.2,"Slightly over","Understaffed")),"-") -> On target | J72: =IFERROR(C34*8/C6,0) -> 0
A73: AL — Eve (3p–11p) | B73: =C6 -> 0 | C73: =D35 -> 0 | D73: =IFERROR(C6/D35,0) -> 0 | E73: =G35 -> 0 | F73: =IFERROR(C6/G35,0) -> 0 | G73: =C21 -> 7 | H73: =IFERROR(D73-G73,0) -> -7 | I73: =IFERROR(IF(D73<=G73,"On target",IF(D73<=G73*1.2,"Slightly over","Understaffed")),"-") -> On target | J73: =IFERROR(D35*8/C6,0) -> 0
A74: AL — Night (11p–7a) | B74: =C6 -> 0 | C74: =E36 -> 0 | D74: =IFERROR(C6/E36,0) -> 0 | E74: =H36 -> 0 | F74: =IFERROR(C6/H36,0) -> 0 | G74: =C22 -> 10 | H74: =IFERROR(D74-G74,0) -> -10 | I74: =IFERROR(IF(D74<=G74,"On target",IF(D74<=G74*1.2,"Slightly over","Understaffed")),"-") -> On target | J74: =IFERROR(E36*8/C6,0) -> 0
A75: MC — Day (7a–3p) | B75: =C7 -> 0 | C75: =C37 -> 0 | D75: =IFERROR(C7/C37,0) -> 0 | E75: =F37 -> 0 | F75: =IFERROR(C7/F37,0) -> 0 | G75: =C23 -> 5 | H75: =IFERROR(D75-G75,0) -> -5 | I75: =IFERROR(IF(D75<=G75,"On target",IF(D75<=G75*1.2,"Slightly over","Understaffed")),"-") -> On target | J75: =IFERROR(C37*8/C7,0) -> 0
A76: MC — Eve (3p–11p) | B76: =C7 -> 0 | C76: =D38 -> 0 | D76: =IFERROR(C7/D38,0) -> 0 | E76: =G38 -> 0 | F76: =IFERROR(C7/G38,0) -> 0 | G76: =C24 -> 6 | H76: =IFERROR(D76-G76,0) -> -6 | I76: =IFERROR(IF(D76<=G76,"On target",IF(D76<=G76*1.2,"Slightly over","Understaffed")),"-") -> On target | J76: =IFERROR(D38*8/C7,0) -> 0
A77: MC — Night (11p–7a) | B77: =C7 -> 0 | C77: =E39 -> 0 | D77: =IFERROR(C7/E39,0) -> 0 | E77: =H39 -> 0 | F77: =IFERROR(C7/H39,0) -> 0 | G77: =C25 -> 8 | H77: =IFERROR(D77-G77,0) -> -8 | I77: =IFERROR(IF(D77<=G77,"On target",IF(D77<=G77*1.2,"Slightly over","Understaffed")),"-") -> On target | J77: =IFERROR(E39*8/C7,0) -> 0
A79: SECTION 4 — HPPD TRACKER (Hours Per Patient Day)
A80: HPPD = care staff FTEs × 2080 ÷ 365 ÷ occupied beds. Benchmark: AL 2.5–3.5 | MC 3.5–4.5. Watched by buyers, lenders, and surveyors.
A81: Metric | B81: Calculated | C81: Bench Low | D81: Bench High | E81: Status | F81: Delta vs Mid
A82: Care HPPD — AL | B82: =IFERROR((J31+J32+J33+J34+J35+J36+J37+J38+J39)*2080/365/C6,0) -> 0 | C82: 2.5 | D82: 3.5 | E82: =IFERROR(IF(B82<C82,"Below bench",IF(B82>D82,"Above bench","In range")),"-") -> Below bench | F82: =IFERROR(B82-(C82+D82)/2,0) -> -3
A83: Care HPPD — MC | B83: =IFERROR((J31+J32+J33+J34+J35+J36+J37+J38+J39)*2080/365/C7,0) -> 0 | C83: 3.5 | D83: 4.5 | E83: =IFERROR(IF(B83<C83,"Below bench",IF(B83>D83,"Above bench","In range")),"-") -> Below bench | F83: =IFERROR(B83-(C83+D83)/2,0) -> -4
A84: Care HPPD — Combined | B84: =IFERROR((J31+J32+J33+J34+J35+J36+J37+J38+J39)*2080/365/(C6+C7),0) -> 0 | C84: 3 | D84: 4 | E84: =IFERROR(IF(B84<C84,"Below bench",IF(B84>D84,"Above bench","In range")),"-") -> Below bench | F84: =IFERROR(B84-(C84+D84)/2,0) -> -3.5
A85: Labor Cost / Resident / Day ($) | B85: =IFERROR(M67/365/(C6+C7+C8),0) -> 0 | C85: 80 | D85: 140 | E85: =IFERROR(IF(B85<C85,"Below bench",IF(B85>D85,"Above bench","In range")),"-") -> Below bench | F85: =IFERROR(B85-(C85+D85)/2,0) -> -110
A87: SECTION 5 — PAYROLL OUTPUT → P&L FEED
A88: Total Payroll (cell M67) feeds P&L sheet row 28 automatically. Verify the P&L Payroll row shows a green formula.
A89: Total Annual Payroll (all departments) | C89: =M67 -> 0 | D89: ← This value feeds P&L!C28 (Year 1 Payroll) | E89: P&L formula in C28: ='Staffing Matrix'!M67
A90: Total FTEs (all departments) | C90: =J67 -> 0 | D90: Full-time equivalents across all 6 shifts
A91: Avg Annual Cost per FTE | C91: =IFERROR(M67/J67,0) -> 0 | D91: Loaded cost: wages + benefits + OT
A93: SECTION 6 — COST PER RESIDENT DAY (PRD) & LABOR INTENSITY ANALYSIS
A94: PRD ties labor cost to census — the lens operators and lenders use alongside HPPD. All figures are annual / occupied-bed based. Enter agency spend below; everything else auto-calculates.
A96: A. BASE — OCCUPIED RESIDENTS & ANNUAL RESIDENT DAYS
A97: Metric | B97: Value | C97: Bench Low | D97: Bench High | E97: Notes
A98: Total Occupied Residents (AL + MC + IL) | B98: =C6+C7+C8 -> 0 | C98: — | D98: — | E98: From Section 1 census inputs
A99: Annual Resident Days (residents × 365) | B99: =IFERROR(B98*365,0) -> 0 | C99: — | D99: — | E99: Denominator for all PRD metrics below
A101: B. LABOR COST PER RESIDENT DAY — BY DEPARTMENT ($)
A102: Benchmarks: NIC/Argentum/LeadingAge AL industry data. MC typically runs 25–40% higher.
A103: Department | B103: Annual Payroll ($) | C103: PRD Cost ($/day) | D103: Bench Low | E103: Bench High | F103: Status
A104: Care Staff (DON, RN, Med Tech, CNAs) | B104: =M40 -> 0 | C104: =IFERROR(M40/B99,0) -> 0 | D104: 45 | E104: 75 | F104: =IFERROR(IF(C104=0,"—",IF(C104<D104,"Below bench",IF(C104>E104,"Above bench","In range"))),"") -> —
A105: Dining / Food Service | B105: =M47 -> 0 | C105: =IFERROR(M47/B99,0) -> 0 | D105: 12 | E105: 22 | F105: =IFERROR(IF(C105=0,"—",IF(C105<D105,"Below bench",IF(C105>E105,"Above bench","In range"))),"") -> —
A106: Housekeeping & Laundry | B106: =M53 -> 0 | C106: =IFERROR(M53/B99,0) -> 0 | D106: 6 | E106: 14 | F106: =IFERROR(IF(C106=0,"—",IF(C106<D106,"Below bench",IF(C106>E106,"Above bench","In range"))),"") -> —
A107: Maintenance, Activities & Admin | B107: =M65 -> 0 | C107: =IFERROR(M65/B99,0) -> 0 | D107: 8 | E107: 18 | F107: =IFERROR(IF(C107=0,"—",IF(C107<D107,"Below bench",IF(C107>E107,"Above bench","In range"))),"") -> —
A108: TOTAL LABOR PRD (all departments) | B108: =M67 -> 0 | C108: =IFERROR(M67/B99,0) -> 0 | D108: 85 | E108: 130 | F108: =IFERROR(IF(C108=0,"—",IF(C108<D108,"Below bench",IF(C108>E108,"Above bench","In range"))),"") -> —
A110: C. CONTRACT / AGENCY LABOR EXPOSURE
A111: Agency >10–15% of total payroll is flagged by lenders and operators as a census-instability risk. Enter annual agency spend — PRD and exposure % calculate automatically.
A112: Metric | B112: Value | C112: Bench Low | D112: Bench High | E112: Status
A113: Contract / Agency Labor — Annual ($) ← enter here | B113: 0 | C113: — | D113: — | E113: Blue cell — enter actual or budgeted agency spend
A114: Agency Labor PRD ($/resident day) | B114: =IFERROR(B113/B99,0) -> 0 | C114: 0 | D114: 20 | E114: =IFERROR(IF(B114=0,"—",IF(B114<=D114,"In range",IF(B114<=D114*1.5,"Watch","High — review"))),"") -> —
...

Sheet Rent Roll Analysis
A1: RENT ROLL ANALYSIS — Diagnostic Layer (Senior Living)
A2: ANALYSIS on top. Raw rent roll below — paste from RentrollApp-Cl output. AR aging columns Q–T blank (paste from Analyzer AR Input or operator AR aging report). Care level: IL = Independent Living · AL = Assisted Living · MC = Memory Care.
A4: B. HEALTH CHECK — RR vs. Prop Info reconciliation
A5: Date: | C5: Property: | D5: =TODAY() -> 46189 | E5: Lic Beds (Prop): | F5: ='Prop Info'!B15 -> 0 | G5: Lic Beds (RR): | H5: =COUNTA(B224:B623) -> 0 | I5: Match: | J5: =IF(F5=H5,"✓ match","⚠ mismatch: "&(H5-F5)) -> ✓ match | K5: Total AR: | L5: =SUM(M224:M623) -> 0 | N5: On Notice: | O5: =COUNTIF(E224:E623,"Notice") -> 0 | Q5: Occupied: | R5: =COUNTIF(E224:E623,"Occupied")+COUNTIF(E224:E623,"Notice") -> 0
D6: As of date for diagnostic
A7: C. CARE LEVEL CENSUS — Licensed beds, occupancy, and rate by level
A8: Care Level | B8: Licensed Beds | C8: Occupied Beds | D8: Occupancy % | E8: Avg Monthly Rate | F8: GPR (ann.) | G8: Avg LOC Rev/Bed | H8: Total Revenue
A9: IL — Independent Living | B9: =COUNTIF($C$224:$C$623,"IL") -> 0 | C9: =COUNTIFS($C$224:$C$623,"IL",$E$224:$E$623,"Occupied")+COUNTIFS($C$224:$C$623,"IL",$E$224:$E$623,"Notice") -> 0 | D9: =IFERROR(C9/B9,0) -> 0 | E9: =IFERROR(AVERAGEIFS($L$224:$L$623,$C$224:$C$623,"IL",$L$224:$L$623,">0"),0) -> 0 | F9: =IFERROR(B9*AVERAGEIFS($I$224:$I$623,$C$224:$C$623,"IL",$I$224:$I$623,">0")*12,0) -> 0 | G9: =IFERROR(SUMIFS($K$224:$K$623,$C$224:$C$623,"IL")/MAX(C9,1),0) -> 0 | H9: =SUMIFS($L$224:$L$623,$C$224:$C$623,"IL")*12 -> 0
A10: AL — Assisted Living | B10: =COUNTIF($C$224:$C$623,"AL") -> 0 | C10: =COUNTIFS($C$224:$C$623,"AL",$E$224:$E$623,"Occupied")+COUNTIFS($C$224:$C$623,"AL",$E$224:$E$623,"Notice") -> 0 | D10: =IFERROR(C10/B10,0) -> 0 | E10: =IFERROR(AVERAGEIFS($L$224:$L$623,$C$224:$C$623,"AL",$L$224:$L$623,">0"),0) -> 0 | F10: =IFERROR(B10*AVERAGEIFS($I$224:$I$623,$C$224:$C$623,"AL",$I$224:$I$623,">0")*12,0) -> 0 | G10: =IFERROR(SUMIFS($K$224:$K$623,$C$224:$C$623,"AL")/MAX(C10,1),0) -> 0 | H10: =SUMIFS($L$224:$L$623,$C$224:$C$623,"AL")*12 -> 0
A11: MC — Memory Care | B11: =COUNTIF($C$224:$C$623,"MC") -> 0 | C11: =COUNTIFS($C$224:$C$623,"MC",$E$224:$E$623,"Occupied")+COUNTIFS($C$224:$C$623,"MC",$E$224:$E$623,"Notice") -> 0 | D11: =IFERROR(C11/B11,0) -> 0 | E11: =IFERROR(AVERAGEIFS($L$224:$L$623,$C$224:$C$623,"MC",$L$224:$L$623,">0"),0) -> 0 | F11: =IFERROR(B11*AVERAGEIFS($I$224:$I$623,$C$224:$C$623,"MC",$I$224:$I$623,">0")*12,0) -> 0 | G11: =IFERROR(SUMIFS($K$224:$K$623,$C$224:$C$623,"MC")/MAX(C11,1),0) -> 0 | H11: =SUMIFS($L$224:$L$623,$C$224:$C$623,"MC")*12 -> 0
A12: ='Prop Info'!$D$13&" — Other Care" -> — Other Care | B12: =COUNTIF($C$224:$C$623,"OTH") -> 0 | C12: =COUNTIFS($C$224:$C$623,"OTH",$E$224:$E$623,"Occupied")+COUNTIFS($C$224:$C$623,"OTH",$E$224:$E$623,"Notice") -> 0 | D12: =IFERROR(C12/B12,0) -> 0 | E12: =IFERROR(AVERAGEIFS($L$224:$L$623,$C$224:$C$623,"OTH",$L$224:$L$623,">0"),0) -> 0 | F12: =IFERROR(B12*AVERAGEIFS($I$224:$I$623,$C$224:$C$623,"OTH",$I$224:$I$623,">0")*12,0) -> 0 | G12: =IFERROR(SUMIFS($K$224:$K$623,$C$224:$C$623,"OTH")/MAX(C12,1),0) -> 0 | H12: =SUMIFS($L$224:$L$623,$C$224:$C$623,"OTH")*12 -> 0
A13: TOTAL | B13: =SUM(B9:B12) -> 0 | C13: =SUM(C9:C12) -> 0 | D13: =IFERROR(C13/B13,0) -> 0 | E13: =IFERROR(SUMIFS($L$224:$L$623,$L$224:$L$623,">0")/COUNTIFS($L$224:$L$623,">0"),0) -> 0 | F13: =SUM(F9:F12) -> 0 | G13: =IFERROR(SUM(K224:K623)/MAX(C13,1),0) -> 0 | H13: =SUM(H9:H12) -> 0
A15: D. RESIDENT STATUS TAXONOMY — Where everyone stands
A16: Status Bucket | B16: # Beds | C16: % of Total | D16: Sched Charges ($/mo) | E16: Avg Rate/Bed | F16: AR Balance
A17: Occupied — Current (paying, no balance) | B17: =COUNTIFS($E$224:$E$623,"Occupied",$M$224:$M$623,"<=0")+COUNTIFS($E$224:$E$623,"Occupied",$M$224:$M$623,"") -> 0 | C17: =IFERROR(B17/$B$25,0) -> 0 | D17: =IFERROR(SUMIFS($L$224:$L$623,$E$224:$E$623,"Occupied",$M$224:$M$623,"<=0")+SUMIFS($L$224:$L$623,$E$224:$E$623,"Occupied",$M$224:$M$623,""),0) -> 0 | E17: =IFERROR(D17/MAX(B17,1),0) -> 0 | F17: 0
A18: Occupied — Delinquent (30+ days past due) | B18: =COUNTIFS($E$224:$E$623,"Occupied",$M$224:$M$623,">0")+COUNTIFS($E$224:$E$623,"Notice",$M$224:$M$623,">0") -> 0 | C18: =IFERROR(B18/$B$25,0) -> 0 | D18: =SUMIFS($L$224:$L$623,$E$224:$E$623,"Occupied",$M$224:$M$623,">0")+SUMIFS($L$224:$L$623,$E$224:$E$623,"Notice",$M$224:$M$623,">0") -> 0 | E18: =IFERROR(D18/MAX(B18,1),0) -> 0 | F18: =SUMIFS($M$224:$M$623,$E$224:$E$623,"Occupied",$M$224:$M$623,">0")+SUMIFS($M$224:$M$623,$E$224:$E$623,"Notice",$M$224:$M$623,">0") -> 0
A19: Occupied — On Notice (30-day notice given) | B19: =COUNTIF($E$224:$E$623,"Notice") -> 0 | C19: =IFERROR(B19/$B$25,0) -> 0 | D19: =SUMIFS($L$224:$L$623,$E$224:$E$623,"Notice") -> 0 | E19: =IFERROR(D19/MAX(B19,1),0) -> 0 | F19: =SUMIFS($M$224:$M$623,$E$224:$E$623,"Notice") -> 0
A20: Occupied — Respite / Short-term | B20: =COUNTIF($E$224:$E$623,"Respite") -> 0 | C20: =IFERROR(B20/$B$25,0) -> 0 | D20: =SUMIFS($L$224:$L$623,$E$224:$E$623,"Respite") -> 0 | E20: =IFERROR(D20/MAX(B20,1),0) -> 0 | F20: =SUMIFS($M$224:$M$623,$E$224:$E$623,"Respite") -> 0
A21: Occupied — Hospice | B21: =COUNTIF($E$224:$E$623,"Hospice") -> 0 | C21: =IFERROR(B21/$B$25,0) -> 0 | D21: =SUMIFS($L$224:$L$623,$E$224:$E$623,"Hospice") -> 0 | E21: =IFERROR(D21/MAX(B21,1),0) -> 0 | F21: =SUMIFS($M$224:$M$623,$E$224:$E$623,"Hospice") -> 0
A22: Vacant — Turned (ready) | B22: =COUNTIFS($E$224:$E$623,"Vacant",$H$224:$H$623,"<>") -> 0 | C22: =IFERROR(B22/$B$25,0) -> 0 | D22: 0 | E22: 0 | F22: 0
A23: Vacant — Not Turned | B23: =COUNTIFS($E$224:$E$623,"Vacant",$H$224:$H$623,"") -> 0 | C23: =IFERROR(B23/$B$25,0) -> 0 | D23: 0 | E23: 0 | F23: 0
A24: Reserved / Pre-Admitted (signed, not in) | B24: =COUNTIF($E$224:$E$623,"Reserved")+COUNTIFS($E$224:$E$623,"Vacant",$G$224:$G$623,">"&TODAY()) -> 0 | C24: =IFERROR(B24/$B$25,0) -> 0 | D24: =SUMIFS($L$224:$L$623,$E$224:$E$623,"Reserved") -> 0 | E24: =IFERROR(D24/MAX(B24,1),0) -> 0 | F24: 0
A25: TOTAL | B25: =COUNTA($B$224:$B$623) -> 0 | C25: =SUM(C17:C24) -> 0 | D25: =SUM(D17:D24) -> 0 | E25: =IFERROR(D25/MAX(B25,1),0) -> 0 | F25: =SUM(F17:F24) -> 0
A26: Tie-out: Occ + Vacant + Reserved = Licensed Beds | Occ Mkt + Vac Loss should tie to Section E GPR
A28: E. GPR RECONCILIATION — Three views of potential revenue
A29: Metric | B29: Annual Amount | C29: Per Bed/Mo | D29: Notes
A30: Market GPR (all licensed beds × market rate × 12) | B30: =SUM(I224:I623)*12 -> 0 | C30: =IFERROR(B30/12/MAX(B13,1),0) -> 0 | D30: Max revenue at 100% occupancy
A31: Scheduled GPR (occupied × sched charges × 12) | B31: {=SUMPRODUCT((($E$224:$E$623="Occupied")+($E$224:$E$623="Notice"))*$L$224:$L$623)*12} -> 0 | C31: =IFERROR(B31/12/MAX(C13,1),0) -> 0 | D31: Contracted charges on occupied beds
A32: Loss to Lease (achievable rate − in-place scheduled, occupied) | B32: {=(SUMPRODUCT((($C$224:$C$623="IL")*(($E$224:$E$623="Occupied")+($E$224:$E$623="Notice")))*(_xlfn.MAXIFS($L$224:$L$623,$C$224:$C$623,"IL",$E$224:$E$623,"Occupied")-$L$224:$L$623))+SUMPRODUCT((($C$224:$C$623="AL")*(($E$224:$E$623="Occupied")+($E$224:$E$623="Notice")))*(_xlfn.MAXIFS($L$224:$L$623,$C$224:$C$623,"AL",$E$224:$E$623,"Occupied")-$L$224:$L$623))+SUMPRODUCT((($C$224:$C$623="MC")*(($E$224:$E$623="Occupied")+($E$224:$E$623="Notice")))*(_xlfn.MAXIFS($L$224:$L$623,$C$224:$C$623,"MC",$E$224:$E$623,"Occupied")-$L$224:$L$623)))*12} -> 0 | C32: =IFERROR(B32/12/MAX(C13,1),0) -> 0 | D32: Achievable = max scheduled rate within same care level (peer ceiling per CL)
A33: Loss to Lease % | B33: =IFERROR(B32/B31,0) -> 0 | D33: LTL as % of scheduled GPR
A34: Vacancy Loss (vacant beds × market rate × 12) | B34: =SUMIFS($I$224:$I$623,$E$224:$E$623,"Vacant")*12 -> 0 | C34: =IFERROR(B34/12/MAX(COUNTIF($E$224:$E$623,"Vacant"),1),0) -> 0 | D34: Lost revenue from empty beds
A35: Bad Debt Risk (delinquent + on-notice × sched × 12) | B35: =F18*12+F19*12 -> 0 | C35: =IFERROR(B35/12/MAX(B18+B19,1),0) -> 0 | D35: Annualized at-risk revenue
A36: LOC / Care Services Revenue (Analyzer UW Output) | B36: =SUM(K224:K623)*12 -> 0 | C36: =IFERROR(B36/12/MAX(C13,1),0) -> 0 | D36: Add-on care charges — source from Analyzer
A37: Economic GPR (Market − LTL − Vac − Bad Debt + LOC) | B37: =B30-B32-B34-B35+B36 -> 0 | C37: =IFERROR(B37/12/MAX(B13,1),0) -> 0 | D37: Realistic collected revenue estimate
A38: Economic Occupancy % (Econ GPR / Market GPR) | B38: =IFERROR(B37/B30,0) -> 0 | D38: Compare to physical occupancy above
A39: Current RR GPR — Occupied Scheduled (point-in-time) | B39: {=SUMPRODUCT((($E$224:$E$623="Occupied")+($E$224:$E$623="Notice"))*$L$224:$L$623)*12} -> 0 | C39: =IFERROR(B39/12/MAX(C13,1),0) -> 0 | D39: Scheduled rent × occupied beds × 12
A40: Market vs Actual Collected (operator posted rate − actual charges, occupied) | B40: {=SUMPRODUCT((($E$224:$E$623="Occupied")+($E$224:$E$623="Notice"))*($I$224:$I$623-$J$224:$J$623))*12} -> 0 | C40: =IFERROR(B40/12/MAX(C13,1),0) -> 0 | D40: Negative = collecting MORE than posted market (over-billing or care fees in I). Positive = collecting LESS than posted market (concessions / discounts in actuals).
A41: F. LENGTH OF STAY COHORT — How long residents have been here
A42: Tenure | B42: # Residents | C42: % Occupied | D42: Avg Sched Rate | E42: Avg Market Rate | F42: LTL/mo/bed | G42: Read
A43: 0–6 months | B43: {=SUMPRODUCT((($E$224:$E$623="Occupied")+($E$224:$E$623="Notice"))*($G$224:$G$623>=TODAY()-180)*($G$224:$G$623<>""))} -> 0 | C43: =IFERROR(B43/MAX($C$13,1),0) -> 0 | D43: {=IFERROR(SUMPRODUCT((($E$224:$E$623="Occupied")+($E$224:$E$623="Notice"))*($G$224:$G$623>=TODAY()-180)*($G$224:$G$623<>"")*$L$224:$L$623)/MAX(B43,1),0)} -> 0 | E43: {=IFERROR(SUMPRODUCT((($E$224:$E$623="Occupied")+($E$224:$E$623="Notice"))*($G$224:$G$623>=TODAY()-180)*($G$224:$G$623<>"")*$I$224:$I$623)/MAX(B43,1),0)} -> 0 | F43: =IFERROR(E43-D43,0) -> 0 | G43: Recent admissions — high care needs assessment period
A44: 6–12 months | B44: {=SUMPRODUCT((($E$224:$E$623="Occupied")+($E$224:$E$623="Notice"))*($G$224:$G$623>=TODAY()-365)*($G$224:$G$623<TODAY()-180)*($G$224:$G$623<>""))} -> 0 | C44: =IFERROR(B44/MAX($C$13,1),0) -> 0 | D44: {=IFERROR(SUMPRODUCT((($E$224:$E$623="Occupied")+($E$224:$E$623="Notice"))*($G$224:$G$623>=TODAY()-365)*($G$224:$G$623<TODAY()-180)*($G$224:$G$623<>"")*$L$224:$L$623)/MAX(B44,1),0)} -> 0 | E44: {=IFERROR(SUMPRODUCT((($E$224:$E$623="Occupied")+($E$224:$E$623="Notice"))*($G$224:$G$623>=TODAY()-365)*($G$224:$G$623<TODAY()-180)*($G$224:$G$623<>"")*$I$224:$I$623)/MAX(B44,1),0)} -> 0 | F44: =IFERROR(E44-D44,0) -> 0 | G44: Stabilizing
A45: 1–2 years | B45: {=SUMPRODUCT((($E$224:$E$623="Occupied")+($E$224:$E$623="Notice"))*($G$224:$G$623>=TODAY()-730)*($G$224:$G$623<TODAY()-365)*($G$224:$G$623<>""))} -> 0 | C45: =IFERROR(B45/MAX($C$13,1),0) -> 0 | D45: {=IFERROR(SUMPRODUCT((($E$224:$E$623="Occupied")+($E$224:$E$623="Notice"))*($G$224:$G$623>=TODAY()-730)*($G$224:$G$623<TODAY()-365)*($G$224:$G$623<>"")*$L$224:$L$623)/MAX(B45,1),0)} -> 0 | E45: {=IFERROR(SUMPRODUCT((($E$224:$E$623="Occupied")+($E$224:$E$623="Notice"))*($G$224:$G$623>=TODAY()-730)*($G$224:$G$623<TODAY()-365)*($G$224:$G$623<>"")*$I$224:$I$623)/MAX(B45,1),0)} -> 0 | F45: =IFERROR(E45-D45,0) -> 0 | G45: Established residents
A46: 2–3 years | B46: {=SUMPRODUCT((($E$224:$E$623="Occupied")+($E$224:$E$623="Notice"))*($G$224:$G$623>=TODAY()-1095)*($G$224:$G$623<TODAY()-730)*($G$224:$G$623<>""))} -> 0 | C46: =IFERROR(B46/MAX($C$13,1),0) -> 0 | D46: {=IFERROR(SUMPRODUCT((($E$224:$E$623="Occupied")+($E$224:$E$623="Notice"))*($G$224:$G$623>=TODAY()-1095)*($G$224:$G$623<TODAY()-730)*($G$224:$G$623<>"")*$L$224:$L$623)/MAX(B46,1),0)} -> 0 | E46: {=IFERROR(SUMPRODUCT((($E$224:$E$623="Occupied")+($E$224:$E$623="Notice"))*($G$224:$G$623>=TODAY()-1095)*($G$224:$G$623<TODAY()-730)*($G$224:$G$623<>"")*$I$224:$I$623)/MAX(B46,1),0)} -> 0 | F46: =IFERROR(E46-D46,0) -> 0 | G46: Likely below market rate
A47: 3+ years | B47: {=SUMPRODUCT((($E$224:$E$623="Occupied")+($E$224:$E$623="Notice"))*($G$224:$G$623<TODAY()-1095)*($G$224:$G$623<>""))} -> 0 | C47: =IFERROR(B47/MAX($C$13,1),0) -> 0 | D47: {=IFERROR(SUMPRODUCT((($E$224:$E$623="Occupied")+($E$224:$E$623="Notice"))*($G$224:$G$623<TODAY()-1095)*($G$224:$G$623<>"")*$L$224:$L$623)/MAX(B47,1),0)} -> 0 | E47: {=IFERROR(SUMPRODUCT((($E$224:$E$623="Occupied")+($E$224:$E$623="Notice"))*($G$224:$G$623<TODAY()-1095)*($G$224:$G$623<>"")*$I$224:$I$623)/MAX(B47,1),0)} -> 0 | F47: =IFERROR(E47-D47,0) -> 0 | G47: Deep below market — rate increase opportunity
A50: G. DAYS VACANT TRACKER — How long have the empty beds been empty?
A51: Calculated from last discharge / move-out date. Blank discharge = unknown duration.
A52: Vacancy Bucket | B52: # Beds | C52: % of Vacant | D52: Lost Revenue ($/yr) | E52: Est. Turn Scope
A53: 0–30 days since discharge | B53: {=SUMPRODUCT(($E$224:$E$623="Vacant")*($H$224:$H$623>=TODAY()-30)*($H$224:$H$623<>""))} -> 0 | C53: =IFERROR(B53/MAX(COUNTIF($E$224:$E$623,"Vacant"),1),0) -> 0 | D53: {=SUMPRODUCT(($E$224:$E$623="Vacant")*($H$224:$H$623>=TODAY()-30)*($H$224:$H$623<>"")*$I$224:$I$623)*12} -> 0 | E53: Standard turn
A54: 31–90 days | B54: {=SUMPRODUCT(($E$224:$E$623="Vacant")*($H$224:$H$623>=TODAY()-90)*($H$224:$H$623<TODAY()-30)*($H$224:$H$623<>""))} -> 0 | C54: =IFERROR(B54/MAX(COUNTIF($E$224:$E$623,"Vacant"),1),0) -> 0 | D54: {=SUMPRODUCT(($E$224:$E$623="Vacant")*($H$224:$H$623>=TODAY()-90)*($H$224:$H$623<TODAY()-30)*($H$224:$H$623<>"")*$I$224:$I$623)*12} -> 0 | E54: Light to medium refurb
A55: 90–180 days | B55: {=SUMPRODUCT(($E$224:$E$623="Vacant")*($H$224:$H$623>=TODAY()-180)*($H$224:$H$623<TODAY()-90)*($H$224:$H$623<>""))} -> 0 | C55: =IFERROR(B55/MAX(COUNTIF($E$224:$E$623,"Vacant"),1),0) -> 0 | D55: {=SUMPRODUCT(($E$224:$E$623="Vacant")*($H$224:$H$623>=TODAY()-180)*($H$224:$H$623<TODAY()-90)*($H$224:$H$623<>"")*$I$224:$I$623)*12} -> 0 | E55: Medium refurb likely
A56: 180–365 days | B56: {=SUMPRODUCT(($E$224:$E$623="Vacant")*($H$224:$H$623>=TODAY()-365)*($H$224:$H$623<TODAY()-180)*($H$224:$H$623<>""))} -> 0 | C56: =IFERROR(B56/MAX(COUNTIF($E$224:$E$623,"Vacant"),1),0) -> 0 | D56: {=SUMPRODUCT(($E$224:$E$623="Vacant")*($H$224:$H$623>=TODAY()-365)*($H$224:$H$623<TODAY()-180)*($H$224:$H$623<>"")*$I$224:$I$623)*12} -> 0 | E56: Heavy refurb / deep clean
A57: 365+ days | B57: {=SUMPRODUCT(($E$224:$E$623="Vacant")*($H$224:$H$623<TODAY()-365)*($H$224:$H$623<>""))} -> 0 | C57: =IFERROR(B57/MAX(COUNTIF($E$224:$E$623,"Vacant"),1),0) -> 0 | D57: {=SUMPRODUCT(($E$224:$E$623="Vacant")*($H$224:$H$623<TODAY()-365)*($H$224:$H$623<>"")*$I$224:$I$623)*12} -> 0 | E57: Assess for off-line / renovation
A58: Discharge date unknown | B58: =COUNTIFS($E$224:$E$623,"Vacant",$H$224:$H$623,"") -> 0 | C58: =IFERROR(B58/MAX(COUNTIF($E$224:$E$623,"Vacant"),1),0) -> 0 | D58: =SUMIFS($I$224:$I$623,$E$224:$E$623,"Vacant",$H$224:$H$623,"")*12 -> 0 | E58: Investigate
A59: Total Lost Annual Revenue | B59: =SUM(B53:B58) -> 0 | C59: =SUM(C53:C58) -> 0 | D59: =SUM(D53:D58) -> 0
A62: H. DELINQUENCY — AR aging summary (paste from Analyzer AR Input or operator aging report into cols Q–T)
A63: Aging Bucket | B63: # Residents | C63: Total $ | D63: % of Total AR | E63: Avg per Resident | F63: Payer Mix Flag
A64: 0–30 Days | B64: {=SUMPRODUCT(($O$224:$O$623>0)*1)} -> 0 | C64: =SUM(O224:O623) -> 0 | D64: =IFERROR(C64/MAX(SUM($M$224:$M$623),1),0) -> 0 | E64: =IFERROR(C64/MAX(B64,1),0) -> 0 | F64: Current
A65: 31–60 Days | B65: {=SUMPRODUCT(($P$224:$P$623>0)*1)} -> 0 | C65: =SUM(P224:P623) -> 0 | D65: =IFERROR(C65/MAX(SUM($M$224:$M$623),1),0) -> 0 | E65: =IFERROR(C65/MAX(B65,1),0) -> 0 | F65: Watch
A66: 61–90 Days | B66: {=SUMPRODUCT(($Q$224:$Q$623>0)*1)} -> 0 | C66: =SUM(Q224:Q623) -> 0 | D66: =IFERROR(C66/MAX(SUM($M$224:$M$623),1),0) -> 0 | E66: =IFERROR(C66/MAX(B66,1),0) -> 0 | F66: Escalate
A67: 90+ Days | B67: {=SUMPRODUCT(($R$224:$R$623>0)*1)} -> 0 | C67: =SUM(R224:R623) -> 0 | D67: =IFERROR(C67/MAX(SUM($M$224:$M$623),1),0) -> 0 | E67: =IFERROR(C67/MAX(B67,1),0) -> 0 | F67: Collections
A68: Total AR (from balance col) | B68: =COUNTIF($M$224:$M$623,">0") -> 0 | C68: =SUM(M224:M623) -> 0 | D68: =IF(SUM(C64:C67)=0,0,SUM(C64:C67)/MAX(C68,1)) -> 0 | E68: =IFERROR(C68/MAX(B68,1),0) -> 0 | F68: =IF(SUM(C64:C67)=0,"⚠ aging not loaded — paste aging report into N–Q","✓ aging loaded") -> ⚠ aging not loaded — paste aging report into N–Q
A71: I. TOP-10 DELINQUENT RESIDENTS — Highest AR balances
A72: Sorted by Balance descending. ✱✱ prefix = operator flagged for legal/collections action.
A73: Rank | B73: Wing | C73: Bed | D73: Resident | E73: Care Level | F73: Payer Type | G73: AR Balance | H73: Deposit | I73: Flag | J73: Deposit | K73: Net Exposure | L73: Notes
A74: 1 | B74: {=IFERROR(INDEX($A$224:$A$623,MATCH(LARGE($M$224:$M$623+ROW($M$224:$M$623)/1000000,ROW()-72),$M$224:$M$623+ROW($M$224:$M$623)/1000000,0)),"")} -> 0 | C74: {=IFERROR(INDEX($B$224:$B$623,MATCH(LARGE($M$224:$M$623+ROW($M$224:$M$623)/1000000,ROW()-72),$M$224:$M$623+ROW($M$224:$M$623)/1000000,0)),"")} -> 0 | D74: {=IFERROR(INDEX($F$224:$F$623,MATCH(LARGE($M$224:$M$623+ROW($M$224:$M$623)/1000000,ROW()-72),$M$224:$M$623+ROW($M$224:$M$623)/1000000,0)),"")} -> 0 | E74: {=IFERROR(INDEX($C$224:$C$623,MATCH(LARGE($M$224:$M$623+ROW($M$224:$M$623)/1000000,ROW()-72),$M$224:$M$623+ROW($M$224:$M$623)/1000000,0)),"")} -> 0 | F74: {=IFERROR(INDEX($S$224:$S$623,MATCH(LARGE($M$224:$M$623+ROW($M$224:$M$623)/1000000,ROW()-72),$M$224:$M$623+ROW($M$224:$M$623)/1000000,0)),"")} -> 0 | G74: =IFERROR(LARGE($M$224:$M$623,ROW()-72),0) -> 0 | H74: =IFERROR(INDEX($N$224:$N$623,MATCH(LARGE($M$224:$M$623+ROW($M$224:$M$623)/1000000,ROW()-72),$M$224:$M$623+ROW($M$224:$M$623)/1000000,0)),0) -> 0 | I74: =IFERROR(IF(LEFT(INDEX($S$211:$S$610,MATCH(LARGE($L$211:$L$610+ROW($L$211:$L$610)/1000000,ROW()-72),$L$211:$L$610+ROW($L$211:$L$610)/1000000,0)),2)="✱✱","✱✱",""),"") | J74: 0 | K74: 0
A75: 2 | B75: {=IFERROR(INDEX($A$224:$A$623,MATCH(LARGE($M$224:$M$623+ROW($M$224:$M$623)/1000000,ROW()-72),$M$224:$M$623+ROW($M$224:$M$623)/1000000,0)),"")} -> 0 | C75: {=IFERROR(INDEX($B$224:$B$623,MATCH(LARGE($M$224:$M$623+ROW($M$224:$M$623)/1000000,ROW()-72),$M$224:$M$623+ROW($M$224:$M$623)/1000000,0)),"")} -> 0 | D75: {=IFERROR(INDEX($F$224:$F$623,MATCH(LARGE($M$224:$M$623+ROW($M$224:$M$623)/1000000,ROW()-72),$M$224:$M$623+ROW($M$224:$M$623)/1000000,0)),"")} -> 0 | E75: {=IFERROR(INDEX($C$224:$C$623,MATCH(LARGE($M$224:$M$623+ROW($M$224:$M$623)/1000000,ROW()-72),$M$224:$M$623+ROW($M$224:$M$623)/1000000,0)),"")} -> 0 | F75: {=IFERROR(INDEX($S$224:$S$623,MATCH(LARGE($M$224:$M$623+ROW($M$224:$M$623)/1000000,ROW()-72),$M$224:$M$623+ROW($M$224:$M$623)/1000000,0)),"")} -> 0 | G75: =IFERROR(LARGE($M$224:$M$623,ROW()-72),0) -> 0 | H75: =IFERROR(INDEX($N$224:$N$623,MATCH(LARGE($M$224:$M$623+ROW($M$224:$M$623)/1000000,ROW()-72),$M$224:$M$623+ROW($M$224:$M$623)/1000000,0)),0) -> 0 | I75: =IFERROR(IF(LEFT(INDEX($S$211:$S$610,MATCH(LARGE($L$211:$L$610+ROW($L$211:$L$610)/1000000,ROW()-72),$L$211:$L$610+ROW($L$211:$L$610)/1000000,0)),2)="✱✱","✱✱",""),"") | J75: 0 | K75: 0
A76: 3 | B76: {=IFERROR(INDEX($A$224:$A$623,MATCH(LARGE($M$224:$M$623+ROW($M$224:$M$623)/1000000,ROW()-72),$M$224:$M$623+ROW($M$224:$M$623)/1000000,0)),"")} -> 0 | C76: {=IFERROR(INDEX($B$224:$B$623,MATCH(LARGE($M$224:$M$623+ROW($M$224:$M$623)/1000000,ROW()-72),$M$224:$M$623+ROW($M$224:$M$623)/1000000,0)),"")} -> 0 | D76: {=IFERROR(INDEX($F$224:$F$623,MATCH(LARGE($M$224:$M$623+ROW($M$224:$M$623)/1000000,ROW()-72),$M$224:$M$623+ROW($M$224:$M$623)/1000000,0)),"")} -> 0 | E76: {=IFERROR(INDEX($C$224:$C$623,MATCH(LARGE($M$224:$M$623+ROW($M$224:$M$623)/1000000,ROW()-72),$M$224:$M$623+ROW($M$224:$M$623)/1000000,0)),"")} -> 0 | F76: {=IFERROR(INDEX($S$224:$S$623,MATCH(LARGE($M$224:$M$623+ROW($M$224:$M$623)/1000000,ROW()-72),$M$224:$M$623+ROW($M$224:$M$623)/1000000,0)),"")} -> 0 | G76: =IFERROR(LARGE($M$224:$M$623,ROW()-72),0) -> 0 | H76: =IFERROR(INDEX($N$224:$N$623,MATCH(LARGE($M$224:$M$623+ROW($M$224:$M$623)/1000000,ROW()-72),$M$224:$M$623+ROW($M$224:$M$623)/1000000,0)),0) -> 0 | I76: =IFERROR(IF(LEFT(INDEX($S$211:$S$610,MATCH(LARGE($L$211:$L$610+ROW($L$211:$L$610)/1000000,ROW()-72),$L$211:$L$610+ROW($L$211:$L$610)/1000000,0)),2)="✱✱","✱✱",""),"") | J76: 0 | K76: 0
A77: 4 | B77: {=IFERROR(INDEX($A$224:$A$623,MATCH(LARGE($M$224:$M$623+ROW($M$224:$M$623)/1000000,ROW()-72),$M$224:$M$623+ROW($M$224:$M$623)/1000000,0)),"")} -> 0 | C77: {=IFERROR(INDEX($B$224:$B$623,MATCH(LARGE($M$224:$M$623+ROW($M$224:$M$623)/1000000,ROW()-72),$M$224:$M$623+ROW($M$224:$M$623)/1000000,0)),"")} -> 0 | D77: {=IFERROR(INDEX($F$224:$F$623,MATCH(LARGE($M$224:$M$623+ROW($M$224:$M$623)/1000000,ROW()-72),$M$224:$M$623+ROW($M$224:$M$623)/1000000,0)),"")} -> 0 | E77: {=IFERROR(INDEX($C$224:$C$623,MATCH(LARGE($M$224:$M$623+ROW($M$224:$M$623)/1000000,ROW()-72),$M$224:$M$623+ROW($M$224:$M$623)/1000000,0)),"")} -> 0 | F77: {=IFERROR(INDEX($S$224:$S$623,MATCH(LARGE($M$224:$M$623+ROW($M$224:$M$623)/1000000,ROW()-72),$M$224:$M$623+ROW($M$224:$M$623)/1000000,0)),"")} -> 0 | G77: =IFERROR(LARGE($M$224:$M$623,ROW()-72),0) -> 0 | H77: =IFERROR(INDEX($N$224:$N$623,MATCH(LARGE($M$224:$M$623+ROW($M$224:$M$623)/1000000,ROW()-72),$M$224:$M$623+ROW($M$224:$M$623)/1000000,0)),0) -> 0 | I77: =IFERROR(IF(LEFT(INDEX($S$211:$S$610,MATCH(LARGE($L$211:$L$610+ROW($L$211:$L$610)/1000000,ROW()-72),$L$211:$L$610+ROW($L$211:$L$610)/1000000,0)),2)="✱✱","✱✱",""),"") | J77: 0 | K77: 0
A78: 5 | B78: {=IFERROR(INDEX($A$224:$A$623,MATCH(LARGE($M$224:$M$623+ROW($M$224:$M$623)/1000000,ROW()-72),$M$224:$M$623+ROW($M$224:$M$623)/1000000,0)),"")} -> 0 | C78: {=IFERROR(INDEX($B$224:$B$623,MATCH(LARGE($M$224:$M$623+ROW($M$224:$M$623)/1000000,ROW()-72),$M$224:$M$623+ROW($M$224:$M$623)/1000000,0)),"")} -> 0 | D78: {=IFERROR(INDEX($F$224:$F$623,MATCH(LARGE($M$224:$M$623+ROW($M$224:$M$623)/1000000,ROW()-72),$M$224:$M$623+ROW($M$224:$M$623)/1000000,0)),"")} -> 0 | E78: {=IFERROR(INDEX($C$224:$C$623,MATCH(LARGE($M$224:$M$623+ROW($M$224:$M$623)/1000000,ROW()-72),$M$224:$M$623+ROW($M$224:$M$623)/1000000,0)),"")} -> 0 | F78: {=IFERROR(INDEX($S$224:$S$623,MATCH(LARGE($M$224:$M$623+ROW($M$224:$M$623)/1000000,ROW()-72),$M$224:$M$623+ROW($M$224:$M$623)/1000000,0)),"")} -> 0 | G78: =IFERROR(LARGE($M$224:$M$623,ROW()-72),0) -> 0 | H78: =IFERROR(INDEX($N$224:$N$623,MATCH(LARGE($M$224:$M$623+ROW($M$224:$M$623)/1000000,ROW()-72),$M$224:$M$623+ROW($M$224:$M$623)/1000000,0)),0) -> 0 | I78: =IFERROR(IF(LEFT(INDEX($S$211:$S$610,MATCH(LARGE($L$211:$L$610+ROW($L$211:$L$610)/1000000,ROW()-72),$L$211:$L$610+ROW($L$211:$L$610)/1000000,0)),2)="✱✱","✱✱",""),"") | J78: 0 | K78: 0
A79: 6 | B79: {=IFERROR(INDEX($A$224:$A$623,MATCH(LARGE($M$224:$M$623+ROW($M$224:$M$623)/1000000,ROW()-72),$M$224:$M$623+ROW($M$224:$M$623)/1000000,0)),"")} -> 0 | C79: {=IFERROR(INDEX($B$224:$B$623,MATCH(LARGE($M$224:$M$623+ROW($M$224:$M$623)/1000000,ROW()-72),$M$224:$M$623+ROW($M$224:$M$623)/1000000,0)),"")} -> 0 | D79: {=IFERROR(INDEX($F$224:$F$623,MATCH(LARGE($M$224:$M$623+ROW($M$224:$M$623)/1000000,ROW()-72),$M$224:$M$623+ROW($M$224:$M$623)/1000000,0)),"")} -> 0 | E79: {=IFERROR(INDEX($C$224:$C$623,MATCH(LARGE($M$224:$M$623+ROW($M$224:$M$623)/1000000,ROW()-72),$M$224:$M$623+ROW($M$224:$M$623)/1000000,0)),"")} -> 0 | F79: {=IFERROR(INDEX($S$224:$S$623,MATCH(LARGE($M$224:$M$623+ROW($M$224:$M$623)/1000000,ROW()-72),$M$224:$M$623+ROW($M$224:$M$623)/1000000,0)),"")} -> 0 | G79: =IFERROR(LARGE($M$224:$M$623,ROW()-72),0) -> 0 | H79: =IFERROR(INDEX($N$224:$N$623,MATCH(LARGE($M$224:$M$623+ROW($M$224:$M$623)/1000000,ROW()-72),$M$224:$M$623+ROW($M$224:$M$623)/1000000,0)),0) -> 0 | I79: =IFERROR(IF(LEFT(INDEX($S$211:$S$610,MATCH(LARGE($L$211:$L$610+ROW($L$211:$L$610)/1000000,ROW()-72),$L$211:$L$610+ROW($L$211:$L$610)/1000000,0)),2)="✱✱","✱✱",""),"") | J79: 0 | K79: 0
A80: 7 | B80: {=IFERROR(INDEX($A$224:$A$623,MATCH(LARGE($M$224:$M$623+ROW($M$224:$M$623)/1000000,ROW()-72),$M$224:$M$623+ROW($M$224:$M$623)/1000000,0)),"")} -> 0 | C80: {=IFERROR(INDEX($B$224:$B$623,MATCH(LARGE($M$224:$M$623+ROW($M$224:$M$623)/1000000,ROW()-72),$M$224:$M$623+ROW($M$224:$M$623)/1000000,0)),"")} -> 0 | D80: {=IFERROR(INDEX($F$224:$F$623,MATCH(LARGE($M$224:$M$623+ROW($M$224:$M$623)/1000000,ROW()-72),$M$224:$M$623+ROW($M$224:$M$623)/1000000,0)),"")} -> 0 | E80: {=IFERROR(INDEX($C$224:$C$623,MATCH(LARGE($M$224:$M$623+ROW($M$224:$M$623)/1000000,ROW()-72),$M$224:$M$623+ROW($M$224:$M$623)/1000000,0)),"")} -> 0 | F80: {=IFERROR(INDEX($S$224:$S$623,MATCH(LARGE($M$224:$M$623+ROW($M$224:$M$623)/1000000,ROW()-72),$M$224:$M$623+ROW($M$224:$M$623)/1000000,0)),"")} -> 0 | G80: =IFERROR(LARGE($M$224:$M$623,ROW()-72),0) -> 0 | H80: =IFERROR(INDEX($N$224:$N$623,MATCH(LARGE($M$224:$M$623+ROW($M$224:$M$623)/1000000,ROW()-72),$M$224:$M$623+ROW($M$224:$M$623)/1000000,0)),0) -> 0 | I80: =IFERROR(IF(LEFT(INDEX($S$211:$S$610,MATCH(LARGE($L$211:$L$610+ROW($L$211:$L$610)/1000000,ROW()-72),$L$211:$L$610+ROW($L$211:$L$610)/1000000,0)),2)="✱✱","✱✱",""),"") | J80: 0 | K80: 0
A81: 8 | B81: {=IFERROR(INDEX($A$224:$A$623,MATCH(LARGE($M$224:$M$623+ROW($M$224:$M$623)/1000000,ROW()-72),$M$224:$M$623+ROW($M$224:$M$623)/1000000,0)),"")} -> 0 | C81: {=IFERROR(INDEX($B$224:$B$623,MATCH(LARGE($M$224:$M$623+ROW($M$224:$M$623)/1000000,ROW()-72),$M$224:$M$623+ROW($M$224:$M$623)/1000000,0)),"")} -> 0 | D81: {=IFERROR(INDEX($F$224:$F$623,MATCH(LARGE($M$224:$M$623+ROW($M$224:$M$623)/1000000,ROW()-72),$M$224:$M$623+ROW($M$224:$M$623)/1000000,0)),"")} -> 0 | E81: {=IFERROR(INDEX($C$224:$C$623,MATCH(LARGE($M$224:$M$623+ROW($M$224:$M$623)/1000000,ROW()-72),$M$224:$M$623+ROW($M$224:$M$623)/1000000,0)),"")} -> 0 | F81: {=IFERROR(INDEX($S$224:$S$623,MATCH(LARGE($M$224:$M$623+ROW($M$224:$M$623)/1000000,ROW()-72),$M$224:$M$623+ROW($M$224:$M$623)/1000000,0)),"")} -> 0 | G81: =IFERROR(LARGE($M$224:$M$623,ROW()-72),0) -> 0 | H81: =IFERROR(INDEX($N$224:$N$623,MATCH(LARGE($M$224:$M$623+ROW($M$224:$M$623)/1000000,ROW()-72),$M$224:$M$623+ROW($M$224:$M$623)/1000000,0)),0) -> 0 | I81: =IFERROR(IF(LEFT(INDEX($S$211:$S$610,MATCH(LARGE($L$211:$L$610+ROW($L$211:$L$610)/1000000,ROW()-72),$L$211:$L$610+ROW($L$211:$L$610)/1000000,0)),2)="✱✱","✱✱",""),"") | J81: 0 | K81: 0
A82: 9 | B82: {=IFERROR(INDEX($A$224:$A$623,MATCH(LARGE($M$224:$M$623+ROW($M$224:$M$623)/1000000,ROW()-72),$M$224:$M$623+ROW($M$224:$M$623)/1000000,0)),"")} -> 0 | C82: {=IFERROR(INDEX($B$224:$B$623,MATCH(LARGE($M$224:$M$623+ROW($M$224:$M$623)/1000000,ROW()-72),$M$224:$M$623+ROW($M$224:$M$623)/1000000,0)),"")} -> 0 | D82: {=IFERROR(INDEX($F$224:$F$623,MATCH(LARGE($M$224:$M$623+ROW($M$224:$M$623)/1000000,ROW()-72),$M$224:$M$623+ROW($M$224:$M$623)/1000000,0)),"")} -> 0 | E82: {=IFERROR(INDEX($C$224:$C$623,MATCH(LARGE($M$224:$M$623+ROW($M$224:$M$623)/1000000,ROW()-72),$M$224:$M$623+ROW($M$224:$M$623)/1000000,0)),"")} -> 0 | F82: {=IFERROR(INDEX($S$224:$S$623,MATCH(LARGE($M$224:$M$623+ROW($M$224:$M$623)/1000000,ROW()-72),$M$224:$M$623+ROW($M$224:$M$623)/1000000,0)),"")} -> 0 | G82: =IFERROR(LARGE($M$224:$M$623,ROW()-72),0) -> 0 | H82: =IFERROR(INDEX($N$224:$N$623,MATCH(LARGE($M$224:$M$623+ROW($M$224:$M$623)/1000000,ROW()-72),$M$224:$M$623+ROW($M$224:$M$623)/1000000,0)),0) -> 0 | I82: =IFERROR(IF(LEFT(INDEX($S$211:$S$610,MATCH(LARGE($L$211:$L$610+ROW($L$211:$L$610)/1000000,ROW()-72),$L$211:$L$610+ROW($L$211:$L$610)/1000000,0)),2)="✱✱","✱✱",""),"") | J82: 0 | K82: 0
A83: 10 | B83: {=IFERROR(INDEX($A$224:$A$623,MATCH(LARGE($M$224:$M$623+ROW($M$224:$M$623)/1000000,ROW()-72),$M$224:$M$623+ROW($M$224:$M$623)/1000000,0)),"")} -> 0 | C83: {=IFERROR(INDEX($B$224:$B$623,MATCH(LARGE($M$224:$M$623+ROW($M$224:$M$623)/1000000,ROW()-72),$M$224:$M$623+ROW($M$224:$M$623)/1000000,0)),"")} -> 0 | D83: {=IFERROR(INDEX($F$224:$F$623,MATCH(LARGE($M$224:$M$623+ROW($M$224:$M$623)/1000000,ROW()-72),$M$224:$M$623+ROW($M$224:$M$623)/1000000,0)),"")} -> 0 | E83: {=IFERROR(INDEX($C$224:$C$623,MATCH(LARGE($M$224:$M$623+ROW($M$224:$M$623)/1000000,ROW()-72),$M$224:$M$623+ROW($M$224:$M$623)/1000000,0)),"")} -> 0 | F83: {=IFERROR(INDEX($S$224:$S$623,MATCH(LARGE($M$224:$M$623+ROW($M$224:$M$623)/1000000,ROW()-72),$M$224:$M$623+ROW($M$224:$M$623)/1000000,0)),"")} -> 0 | G83: =IFERROR(LARGE($M$224:$M$623,ROW()-72),0) -> 0 | H83: =IFERROR(INDEX($N$224:$N$623,MATCH(LARGE($M$224:$M$623+ROW($M$224:$M$623)/1000000,ROW()-72),$M$224:$M$623+ROW($M$224:$M$623)/1000000,0)),0) -> 0 | I83: =IFERROR(IF(LEFT(INDEX($S$211:$S$610,MATCH(LARGE($L$211:$L$610+ROW($L$211:$L$610)/1000000,ROW()-72),$L$211:$L$610+ROW($L$211:$L$610)/1000000,0)),2)="✱✱","✱✱",""),"") | J83: 0 | K83: 0
A84: Top 10 Total | G84: =SUM(G74:G83) -> 0 | H84: 0 | I84: 0 | J84: 0 | K84: 0
A85: Top 10 as % of total AR | G85: =IFERROR(G84/MAX(SUM($M$224:$M$623),1),0) -> 0 | I85: 0
A86: Collections-flagged Residents (count) | B86: {=SUMPRODUCT((LEFT($T$224:$T$623,2)="✱✱")*1)} -> 0 | C86: Collections $ Exposure | D86: =SUMIFS($M$224:$M$623,$T$224:$T$623,"✱✱*") -> 0 | F86: =IFERROR(D86/MAX(SUM($M$224:$M$623),1),0) -> 0 | G86: 0
A88: J. ADMISSION VELOCITY — Recent move-ins (how fast is this property leasing?)
A89: Move-ins within last N days. Annualized pace helps benchmark against stabilized absorption assumptions.
A90: Window | B90: # New Admissions | C90: Avg Rate Achieved | D90: Annualized Pace (beds/yr) | E90: Mo to Stabilize at Pace
A91: Last 30 days | B91: {=SUMPRODUCT(($G$224:$G$623>=TODAY()-30)*($G$224:$G$623<>""))} -> 0 | C91: {=IFERROR(SUMPRODUCT(($G$224:$G$623>=TODAY()-30)*($G$224:$G$623<>"")*$L$224:$L$623)/MAX(B91,1),0)} -> 0 | D91: =B91*(365/30) -> 0 | E91: =IFERROR((COUNTIFS($E$224:$E$623,"Vacant")+COUNTIFS($E$224:$E$623,"Vacant - Available")+COUNTIFS($E$224:$E$623,"Vacant - Not Turned"))/MAX(D91,0.001)*12,0) -> 0
A92: Last 60 days | B92: {=SUMPRODUCT(($G$224:$G$623>=TODAY()-60)*($G$224:$G$623<>""))} -> 0 | C92: {=IFERROR(SUMPRODUCT(($G$224:$G$623>=TODAY()-60)*($G$224:$G$623<>"")*$L$224:$L$623)/MAX(B92,1),0)} -> 0 | D92: =B92*(365/60) -> 0 | E92: =IFERROR((COUNTIFS($E$224:$E$623,"Vacant")+COUNTIFS($E$224:$E$623,"Vacant - Available")+COUNTIFS($E$224:$E$623,"Vacant - Not Turned"))/MAX(D92,0.001)*12,0) -> 0
A93: Last 90 days | B93: {=SUMPRODUCT(($G$224:$G$623>=TODAY()-90)*($G$224:$G$623<>""))} -> 0 | C93: {=IFERROR(SUMPRODUCT(($G$224:$G$623>=TODAY()-90)*($G$224:$G$623<>"")*$L$224:$L$623)/MAX(B93,1),0)} -> 0 | D93: =B93*(365/90) -> 0 | E93: =IFERROR((COUNTIFS($E$224:$E$623,"Vacant")+COUNTIFS($E$224:$E$623,"Vacant - Available")+COUNTIFS($E$224:$E$623,"Vacant - Not Turned"))/MAX(D93,0.001)*12,0) -> 0
A94: Last 180 days | B94: {=SUMPRODUCT(($G$224:$G$623>=TODAY()-180)*($G$224:$G$623<>""))} -> 0 | C94: {=IFERROR(SUMPRODUCT(($G$224:$G$623>=TODAY()-180)*($G$224:$G$623<>"")*$L$224:$L$623)/MAX(B94,1),0)} -> 0 | D94: =B94*(365/180) -> 0 | E94: =IFERROR((COUNTIFS($E$224:$E$623,"Vacant")+COUNTIFS($E$224:$E$623,"Vacant - Available")+COUNTIFS($E$224:$E$623,"Vacant - Not Turned"))/MAX(D94,0.001)*12,0) -> 0
A97: K. PAYER MIX — Revenue resilience and reimbursement risk
A98: Medicaid/Medicare are government-backed (lower default risk). Private pay is market-sensitive. LTC Insurance is contractual but requires prior auth.
A99: Payer Type | B99: # Residents | C99: % Occupied | D99: Monthly Revenue | E99: Annual Revenue | F99: % of Sched | G99: Reliability | H99: 90+ AR $
A100: Private Pay | B100: =COUNTIF($S$224:$S$623,"Private Pay") -> 0 | C100: =IFERROR(B100/MAX(COUNTIF($E$224:$E$623,"Occupied")+COUNTIF($E$224:$E$623,"Notice"),1),0) -> 0 | D100: =SUMIF($S$224:$S$623,"Private Pay",$L$224:$L$623) -> 0 | E100: =D100*12 -> 0 | F100: =IFERROR(D100/MAX(SUM($L$224:$L$623),1),0) -> 0 | G100: 0 | H100: 🟡 market-sensitive
A101: Medicaid | B101: =COUNTIF($S$224:$S$623,"Medicaid") -> 0 | C101: =IFERROR(B101/MAX(COUNTIF($E$224:$E$623,"Occupied")+COUNTIF($E$224:$E$623,"Notice"),1),0) -> 0 | D101: =SUMIF($S$224:$S$623,"Medicaid",$L$224:$L$623) -> 0 | E101: =D101*12 -> 0 | F101: =IFERROR(D101/MAX(SUM($L$224:$L$623),1),0) -> 0 | G101: 0 | H101: 🟢 govt-backed
A102: Medicare | B102: =COUNTIF($S$224:$S$623,"Medicare") -> 0 | C102: =IFERROR(B102/MAX(COUNTIF($E$224:$E$623,"Occupied")+COUNTIF($E$224:$E$623,"Notice"),1),0) -> 0 | D102: =SUMIF($S$224:$S$623,"Medicare",$L$224:$L$623) -> 0 | E102: =D102*12 -> 0 | F102: =IFERROR(D102/MAX(SUM($L$224:$L$623),1),0) -> 0 | G102: 0 | H102: 🟢 govt-backed (episodic)
A103: VA Benefits | B103: =COUNTIF($S$224:$S$623,"VA*") -> 0 | C103: =IFERROR(B103/MAX(COUNTIF($E$224:$E$623,"Occupied")+COUNTIF($E$224:$E$623,"Notice"),1),0) -> 0 | D103: =SUMIF($S$224:$S$623,"VA*",$L$224:$L$623) -> 0 | E103: =D103*12 -> 0 | F103: =IFERROR(D103/MAX(SUM($L$224:$L$623),1),0) -> 0 | G103: 0 | H103: 🟢 govt-backed
A104: LTC Insurance | B104: =COUNTIF($S$224:$S$623,"LTC*") -> 0 | C104: =IFERROR(B104/MAX(COUNTIF($E$224:$E$623,"Occupied")+COUNTIF($E$224:$E$623,"Notice"),1),0) -> 0 | D104: =SUMIF($S$224:$S$623,"LTC*",$L$224:$L$623) -> 0 | E104: =D104*12 -> 0 | F104: =IFERROR(D104/MAX(SUM($L$224:$L$623),1),0) -> 0 | G104: 0 | H104: 🟡 contractual / prior-auth risk
A105: Other / Unknown | B105: =COUNTIFS($E$224:$E$623,"Occupied")+COUNTIFS($E$224:$E$623,"Notice")-SUM(B100:B104) -> 0 | C105: =IFERROR(B105/MAX(COUNTIF($E$224:$E$623,"Occupied")+COUNTIF($E$224:$E$623,"Notice"),1),0) -> 0 | D105: =SUMIFS($L$224:$L$623,$E$224:$E$623,"Occupied")+SUMIFS($L$224:$L$623,$E$224:$E$623,"Notice")-SUM(D100:D104) -> 0 | E105: =D105*12 -> 0 | F105: =IFERROR(D105/MAX(SUM($L$224:$L$623),1),0) -> 0 | G105: 0
A106: TOTAL | B106: =SUM(B100:B105) -> 0 | C106: =SUM(C100:C105) -> 0 | D106: =SUM(D100:D105) -> 0 | E106: =SUM(E100:E105) -> 0 | F106: =SUM(F100:F105) -> 0 | G106: 0
A108: Private Pay Concentration: | B108: =C100 -> 0 | D108: Govt-backed (Medicaid+Medicare+VA): | E108: =C101+C102+C103 -> 0
A110: L. RATE PER BED BY CARE LEVEL — Pricing posture vs. comp set
A111: Compare avg scheduled rate to market rate from Rental Comps tab. >5% below market = recapture opportunity.
A112: Care Level | B112: # Occupied | C112: Avg Sched Rate | D112: Avg Market Rate | E112: LTL/mo | F112: LTL % | G112: Annual Recapture | H112: vs Comp Flag
A113: IL — Independent Living | B113: =COUNTIFS($C$224:$C$623,"IL",$E$224:$E$623,"Occupied")+COUNTIFS($C$224:$C$623,"IL",$E$224:$E$623,"Notice") -> 0 | C113: =IFERROR(SUMIFS($L$224:$L$623,$C$224:$C$623,"IL",$E$224:$E$623,"Occupied")/MAX(COUNTIFS($C$224:$C$623,"IL",$E$224:$E$623,"Occupied"),1),0) -> 0 | D113: =IFERROR(SUMIFS($I$224:$I$623,$C$224:$C$623,"IL")/MAX(COUNTIF($C$224:$C$623,"IL"),1),0) -> 0 | E113: =MAX(D113-C113,0)*B113 -> 0 | F113: =IFERROR((D113-C113)/MAX(D113,1),0) -> 0 | G113: 0 | H113: — see Rental Comps —
A114: AL — Assisted Living | B114: =COUNTIFS($C$224:$C$623,"AL",$E$224:$E$623,"Occupied")+COUNTIFS($C$224:$C$623,"AL",$E$224:$E$623,"Notice") -> 0 | C114: =IFERROR(SUMIFS($L$224:$L$623,$C$224:$C$623,"AL",$E$224:$E$623,"Occupied")/MAX(COUNTIFS($C$224:$C$623,"AL",$E$224:$E$623,"Occupied"),1),0) -> 0 | D114: =IFERROR(SUMIFS($I$224:$I$623,$C$224:$C$623,"AL")/MAX(COUNTIF($C$224:$C$623,"AL"),1),0) -> 0 | E114: =MAX(D114-C114,0)*B114 -> 0 | F114: =IFERROR((D114-C114)/MAX(D114,1),0) -> 0 | G114: 0 | H114: — see Rental Comps —
...

Sheet Rental Comps
A1: RENTAL COMPS — BY CARE LEVEL | P1: UNIT MIX & TARGET RENT ANALYSIS — Reference only. Blue = input · Green = formula · Target defaults to comp avg for care level.
A2: Enter up to 12 comps per care level. Summary auto-calculates averages and rate position vs. subject property. | N2: Rent Basis: | O2: Average | P2: Unit Type | Q2: Sq Ft | R2: # Units | S2: Current Rent | V2: Target Rent | AA2: Notes
A3: SUBJECT PROPERTY → | E3: ='Prop Info'!B2 -> 0 | F3: =Scenarios!F38 -> 0 | G3: =Scenarios!F38 -> 0 | H3: =Scenarios!F38 -> 0 | P3: Type | Q3: Sq Ft | R3: # Units | S3: Avg / mo | T3: Total / mo | U3: $ / Sq Ft | V3: Target / mo | W3: Delta % | X3: Delta $ | Y3: Total / mo | Z3: $ / Sq Ft | AA3: Notes
P4: IL — INDEPENDENT LIVING
A5: INDEPENDENT LIVING (IL) COMPS | P5: IL Studio | Q5: =IFERROR(AVERAGEIFS('Rent Roll Analysis'!T:T,'Rent Roll Analysis'!Y:Y,"IL|Studio",'Rent Roll Analysis'!T:T,">0"),0) -> 0 | R5: =COUNTIF('Rent Roll Analysis'!Y:Y,"IL|Studio") -> 0 | S5: =IFERROR(IF($O$2="Max",_xlfn.MAXIFS('Rent Roll Analysis'!I:I,'Rent Roll Analysis'!X:X,"IL|Studio"),AVERAGEIFS('Rent Roll Analysis'!I:I,'Rent Roll Analysis'!X:X,"IL|Studio",'Rent Roll Analysis'!I:I,">0")),0) -> 0 | T5: =IFERROR(S5*R5,0) -> 0 | U5: =IFERROR(S5/Q5,0) -> 0 | V5: =IFERROR(H19,0) -> 0 | W5: =IFERROR(V5/S5-1,"") | X5: =IFERROR(V5-S5,"") -> 0 | Y5: =IFERROR(V5*R5,0) -> 0 | Z5: =IFERROR(V5/Q5,0) -> 0
A6: Distance (mi) | B6: Vintage | C6: Units | D6: Type | E6: Property Name | F6: Base Rent/mo | G6: Care Fee/mo | H6: All-In Rate | I6: Occupancy % | J6: Sq Ft | K6: $/Sq Ft | L6: Notes | P6: IL 1-Bed | Q6: =IFERROR(AVERAGEIFS('Rent Roll Analysis'!T:T,'Rent Roll Analysis'!Y:Y,"IL|1 Bedroom",'Rent Roll Analysis'!T:T,">0"),0) -> 0 | R6: =COUNTIF('Rent Roll Analysis'!Y:Y,"IL|1 Bedroom") -> 0 | S6: =IFERROR(IF($O$2="Max",_xlfn.MAXIFS('Rent Roll Analysis'!I:I,'Rent Roll Analysis'!X:X,"IL|1 Bedroom"),AVERAGEIFS('Rent Roll Analysis'!I:I,'Rent Roll Analysis'!X:X,"IL|1 Bedroom",'Rent Roll Analysis'!I:I,">0")),0) -> 0 | T6: =IFERROR(S6*R6,0) -> 0 | U6: =IFERROR(S6/Q6,0) -> 0 | V6: =IFERROR(H19,0) -> 0 | W6: =IFERROR(V6/S6-1,"") | X6: =IFERROR(V6-S6,"") -> 0 | Y6: =IFERROR(V6*R6,0) -> 0 | Z6: =IFERROR(V6/Q6,0) -> 0
H7: =IFERROR(F7+G7,0) -> 0 | K7: =IFERROR(F7/J7,0) -> 0 | P7: IL 2-Bed | Q7: =IFERROR(AVERAGEIFS('Rent Roll Analysis'!T:T,'Rent Roll Analysis'!Y:Y,"IL|2 Bedroom",'Rent Roll Analysis'!T:T,">0"),0) -> 0 | R7: =COUNTIF('Rent Roll Analysis'!Y:Y,"IL|2 Bedroom") -> 0 | S7: =IFERROR(IF($O$2="Max",_xlfn.MAXIFS('Rent Roll Analysis'!I:I,'Rent Roll Analysis'!X:X,"IL|2 Bedroom"),AVERAGEIFS('Rent Roll Analysis'!I:I,'Rent Roll Analysis'!X:X,"IL|2 Bedroom",'Rent Roll Analysis'!I:I,">0")),0) -> 0 | T7: =IFERROR(S7*R7,0) -> 0 | U7: =IFERROR(S7/Q7,0) -> 0 | V7: =IFERROR(H19,0) -> 0 | W7: =IFERROR(V7/S7-1,"") | X7: =IFERROR(V7-S7,"") -> 0 | Y7: =IFERROR(V7*R7,0) -> 0 | Z7: =IFERROR(V7/Q7,0) -> 0
H8: =IFERROR(F8+G8,0) -> 0 | K8: =IFERROR(F8/J8,0) -> 0 | P8: AL — ASSISTED LIVING
H9: =IFERROR(F9+G9,0) -> 0 | K9: =IFERROR(F9/J9,0) -> 0 | P9: AL Studio (Pvt) | Q9: =IFERROR(AVERAGEIFS('Rent Roll Analysis'!T:T,'Rent Roll Analysis'!Y:Y,"AL|Studio",'Rent Roll Analysis'!T:T,">0"),0) -> 0 | R9: =COUNTIF('Rent Roll Analysis'!Y:Y,"AL|Studio") -> 0 | S9: =IFERROR(IF($O$2="Max",_xlfn.MAXIFS('Rent Roll Analysis'!I:I,'Rent Roll Analysis'!X:X,"AL|Studio"),AVERAGEIFS('Rent Roll Analysis'!I:I,'Rent Roll Analysis'!X:X,"AL|Studio",'Rent Roll Analysis'!I:I,">0")),0) -> 0 | T9: =IFERROR(S9*R9,0) -> 0 | U9: =IFERROR(S9/Q9,0) -> 0 | V9: =IFERROR(H36,0) -> 0 | W9: =IFERROR(V9/S9-1,"") | X9: =IFERROR(V9-S9,"") -> 0 | Y9: =IFERROR(V9*R9,0) -> 0 | Z9: =IFERROR(V9/Q9,0) -> 0
H10: =IFERROR(F10+G10,0) -> 0 | K10: =IFERROR(F10/J10,0) -> 0 | P10: AL Semi-Private | Q10: =IFERROR(AVERAGEIFS('Rent Roll Analysis'!T:T,'Rent Roll Analysis'!Y:Y,"AL|Semi-Private",'Rent Roll Analysis'!T:T,">0"),0) -> 0 | R10: =COUNTIF('Rent Roll Analysis'!Y:Y,"AL|Semi-Private") -> 0 | S10: =IFERROR(IF($O$2="Max",_xlfn.MAXIFS('Rent Roll Analysis'!I:I,'Rent Roll Analysis'!X:X,"AL|Semi-Private"),AVERAGEIFS('Rent Roll Analysis'!I:I,'Rent Roll Analysis'!X:X,"AL|Semi-Private",'Rent Roll Analysis'!I:I,">0")),0) -> 0 | T10: =IFERROR(S10*R10,0) -> 0 | U10: =IFERROR(S10/Q10,0) -> 0 | V10: =IFERROR(H36,0) -> 0 | W10: =IFERROR(V10/S10-1,"") | X10: =IFERROR(V10-S10,"") -> 0 | Y10: =IFERROR(V10*R10,0) -> 0 | Z10: =IFERROR(V10/Q10,0) -> 0
H11: =IFERROR(F11+G11,0) -> 0 | K11: =IFERROR(F11/J11,0) -> 0 | P11: AL 1-Bed | Q11: =IFERROR(AVERAGEIFS('Rent Roll Analysis'!T:T,'Rent Roll Analysis'!Y:Y,"AL|1 Bedroom",'Rent Roll Analysis'!T:T,">0"),0) -> 0 | R11: =COUNTIF('Rent Roll Analysis'!Y:Y,"AL|1 Bedroom") -> 0 | S11: =IFERROR(IF($O$2="Max",_xlfn.MAXIFS('Rent Roll Analysis'!I:I,'Rent Roll Analysis'!X:X,"AL|1 Bedroom"),AVERAGEIFS('Rent Roll Analysis'!I:I,'Rent Roll Analysis'!X:X,"AL|1 Bedroom",'Rent Roll Analysis'!I:I,">0")),0) -> 0 | T11: =IFERROR(S11*R11,0) -> 0 | U11: =IFERROR(S11/Q11,0) -> 0 | V11: =IFERROR(H36,0) -> 0 | W11: =IFERROR(V11/S11-1,"") | X11: =IFERROR(V11-S11,"") -> 0 | Y11: =IFERROR(V11*R11,0) -> 0 | Z11: =IFERROR(V11/Q11,0) -> 0
H12: =IFERROR(F12+G12,0) -> 0 | K12: =IFERROR(F12/J12,0) -> 0 | P12: MC — MEMORY CARE
H13: =IFERROR(F13+G13,0) -> 0 | K13: =IFERROR(F13/J13,0) -> 0 | P13: MC Studio (Pvt) | Q13: =IFERROR(AVERAGEIFS('Rent Roll Analysis'!T:T,'Rent Roll Analysis'!Y:Y,"MC|Studio",'Rent Roll Analysis'!T:T,">0"),0) -> 0 | R13: =COUNTIF('Rent Roll Analysis'!Y:Y,"MC|Studio") -> 0 | S13: =IFERROR(IF($O$2="Max",_xlfn.MAXIFS('Rent Roll Analysis'!I:I,'Rent Roll Analysis'!X:X,"MC|Studio"),AVERAGEIFS('Rent Roll Analysis'!I:I,'Rent Roll Analysis'!X:X,"MC|Studio",'Rent Roll Analysis'!I:I,">0")),0) -> 0 | T13: =IFERROR(S13*R13,0) -> 0 | U13: =IFERROR(S13/Q13,0) -> 0 | V13: =IFERROR(H53,0) -> 0 | W13: =IFERROR(V13/S13-1,"") | X13: =IFERROR(V13-S13,"") -> 0 | Y13: =IFERROR(V13*R13,0) -> 0 | Z13: =IFERROR(V13/Q13,0) -> 0
H14: =IFERROR(F14+G14,0) -> 0 | K14: =IFERROR(F14/J14,0) -> 0 | P14: MC Semi-Private | Q14: =IFERROR(AVERAGEIFS('Rent Roll Analysis'!T:T,'Rent Roll Analysis'!Y:Y,"MC|Semi-Private",'Rent Roll Analysis'!T:T,">0"),0) -> 0 | R14: =COUNTIF('Rent Roll Analysis'!Y:Y,"MC|Semi-Private") -> 0 | S14: =IFERROR(IF($O$2="Max",_xlfn.MAXIFS('Rent Roll Analysis'!I:I,'Rent Roll Analysis'!X:X,"MC|Semi-Private"),AVERAGEIFS('Rent Roll Analysis'!I:I,'Rent Roll Analysis'!X:X,"MC|Semi-Private",'Rent Roll Analysis'!I:I,">0")),0) -> 0 | T14: =IFERROR(S14*R14,0) -> 0 | U14: =IFERROR(S14/Q14,0) -> 0 | V14: =IFERROR(H53,0) -> 0 | W14: =IFERROR(V14/S14-1,"") | X14: =IFERROR(V14-S14,"") -> 0 | Y14: =IFERROR(V14*R14,0) -> 0 | Z14: =IFERROR(V14/Q14,0) -> 0
H15: =IFERROR(F15+G15,0) -> 0 | K15: =IFERROR(F15/J15,0) -> 0 | P15: Other | Q15: =IFERROR(AVERAGEIFS('Rent Roll Analysis'!$T$224:$T$623,'Rent Roll Analysis'!$Y$224:$Y$623,"<>",'Rent Roll Analysis'!$Y$224:$Y$623,"<>IL|Studio",'Rent Roll Analysis'!$Y$224:$Y$623,"<>IL|1 Bedroom",'Rent Roll Analysis'!$Y$224:$Y$623,"<>IL|2 Bedroom",'Rent Roll Analysis'!$Y$224:$Y$623,"<>AL|Studio",'Rent Roll Analysis'!$Y$224:$Y$623,"<>AL|Semi-Private",'Rent Roll Analysis'!$Y$224:$Y$623,"<>AL|1 Bedroom",'Rent Roll Analysis'!$Y$224:$Y$623,"<>MC|Studio",'Rent Roll Analysis'!$Y$224:$Y$623,"<>MC|Semi-Private",'Rent Roll Analysis'!$T$224:$T$623,">0"),0) -> 0 | R15: =COUNTIF('Rent Roll Analysis'!$Y$224:$Y$623,"?*")-R5-R6-R7-R9-R10-R11-R13-R14 -> 0 | S15: =IFERROR(IF($O$2="Max",_xlfn.MAXIFS('Rent Roll Analysis'!$I$224:$I$623,'Rent Roll Analysis'!$X$224:$X$623,"<>",'Rent Roll Analysis'!$X$224:$X$623,"<>IL|Studio",'Rent Roll Analysis'!$X$224:$X$623,"<>IL|1 Bedroom",'Rent Roll Analysis'!$X$224:$X$623,"<>IL|2 Bedroom",'Rent Roll Analysis'!$X$224:$X$623,"<>AL|Studio",'Rent Roll Analysis'!$X$224:$X$623,"<>AL|Semi-Private",'Rent Roll Analysis'!$X$224:$X$623,"<>AL|1 Bedroom",'Rent Roll Analysis'!$X$224:$X$623,"<>MC|Studio",'Rent Roll Analysis'!$X$224:$X$623,"<>MC|Semi-Private"),AVERAGEIFS('Rent Roll Analysis'!$I$224:$I$623,'Rent Roll Analysis'!$X$224:$X$623,"<>",'Rent Roll Analysis'!$X$224:$X$623,"<>IL|Studio",'Rent Roll Analysis'!$X$224:$X$623,"<>IL|1 Bedroom",'Rent Roll Analysis'!$X$224:$X$623,"<>IL|2 Bedroom",'Rent Roll Analysis'!$X$224:$X$623,"<>AL|Studio",'Rent Roll Analysis'!$X$224:$X$623,"<>AL|Semi-Private",'Rent Roll Analysis'!$X$224:$X$623,"<>AL|1 Bedroom",'Rent Roll Analysis'!$X$224:$X$623,"<>MC|Studio",'Rent Roll Analysis'!$X$224:$X$623,"<>MC|Semi-Private",'Rent Roll Analysis'!$I$224:$I$623,">0")),0) -> 0 | T15: =IFERROR(S15*R15,0) -> 0 | U15: =IFERROR(S15/Q15,0) -> 0 | V15: =IFERROR(AVERAGE(H19,H36,H53),0) -> 0 | W15: =IFERROR(V15/S15-1,"") | X15: =IFERROR(V15-S15,"") -> 0 | Y15: =IFERROR(V15*R15,0) -> 0 | Z15: =IFERROR(V15/Q15,0) -> 0
H16: =IFERROR(F16+G16,0) -> 0 | K16: =IFERROR(F16/J16,0) -> 0 | P16: Total / Average | Q16: =IFERROR((Q5*R5+Q6*R6+Q7*R7+Q9*R9+Q10*R10+Q11*R11+Q13*R13+Q14*R14+Q15*R15)/(R5+R6+R7+R9+R10+R11+R13+R14+R15),0) -> 0 | R16: =IFERROR(R5+R6+R7+R9+R10+R11+R13+R14+R15,0) -> 0 | S16: =IFERROR((R5*S5+R6*S6+R7*S7+R9*S9+R10*S10+R11*S11+R13*S13+R14*S14+R15*S15)/(R5+R6+R7+R9+R10+R11+R13+R14+R15),0) -> 0 | T16: =IFERROR(T5+T6+T7+T9+T10+T11+T13+T14+T15,0) -> 0 | U16: =IFERROR(T16/Q16,0) -> 0 | V16: =IFERROR((R5*V5+R6*V6+R7*V7+R9*V9+R10*V10+R11*V11+R13*V13+R14*V14+R15*V15)/(R5+R6+R7+R9+R10+R11+R13+R14+R15),0) -> 0 | W16: =IFERROR(V16/S16-1,"") | X16: =IFERROR(V16-S16,"") -> 0 | Y16: =IFERROR(Y5+Y6+Y7+Y9+Y10+Y11+Y13+Y14+Y15,0) -> 0 | Z16: =IFERROR(Y16/Q16,0) -> 0
H17: =IFERROR(F17+G17,0) -> 0 | K17: =IFERROR(F17/J17,0) -> 0 | P17: VALUE-ADD UNITS (manual inputs — negative R = removed, positive R = added)
H18: =IFERROR(F18+G18,0) -> 0 | K18: =IFERROR(F18/J18,0) -> 0 | P18: IL — Value-Add
A19: AVG — IN | F19: =IFERROR(AVERAGEIF(F7:F18,">"&0),0) -> 0 | G19: =IFERROR(AVERAGEIF(G7:G18,">"&0),0) -> 0 | H19: =IFERROR(AVERAGEIF(H7:H18,">"&0),0) -> 0 | I19: =IFERROR(AVERAGEIF(I7:I18,">"&0),0) -> 0 | P19: Add row 1 (label me) | T19: =IFERROR(S19*R19,0) -> 0 | U19: =IFERROR(S19/Q19,0) -> 0 | V19: =IFERROR(H19,0) -> 0 | W19: =IFERROR(V19/S19-1,"") | X19: =IFERROR(V19-S19,"") -> 0 | Y19: =IFERROR(V19*R19,0) -> 0 | Z19: =IFERROR(V19/Q19,0) -> 0
A20: Subj. vs. Avg IN Rent | F20: =Scenarios!F38-F19 -> 0 | P20: Add row 2 (label me) | T20: =IFERROR(S20*R20,0) -> 0 | U20: =IFERROR(S20/Q20,0) -> 0 | V20: =IFERROR(H19,0) -> 0 | W20: =IFERROR(V20/S20-1,"") | X20: =IFERROR(V20-S20,"") -> 0 | Y20: =IFERROR(V20*R20,0) -> 0 | Z20: =IFERROR(V20/Q20,0) -> 0
P21: AL — Value-Add
A22: ASSISTED LIVING (AL) COMPS | P22: Add row 1 (label me) | T22: =IFERROR(S22*R22,0) -> 0 | U22: =IFERROR(S22/Q22,0) -> 0 | V22: =IFERROR(H36,0) -> 0 | W22: =IFERROR(V22/S22-1,"") | X22: =IFERROR(V22-S22,"") -> 0 | Y22: =IFERROR(V22*R22,0) -> 0 | Z22: =IFERROR(V22/Q22,0) -> 0
A23: Distance (mi) | B23: Vintage | C23: Units | D23: Type | E23: Property Name | F23: Base Rent/mo | G23: Care Fee/mo | H23: All-In Rate | I23: Occupancy % | J23: Sq Ft | K23: $/Sq Ft | L23: Notes | P23: Add row 2 (label me) | T23: =IFERROR(S23*R23,0) -> 0 | U23: =IFERROR(S23/Q23,0) -> 0 | V23: =IFERROR(H36,0) -> 0 | W23: =IFERROR(V23/S23-1,"") | X23: =IFERROR(V23-S23,"") -> 0 | Y23: =IFERROR(V23*R23,0) -> 0 | Z23: =IFERROR(V23/Q23,0) -> 0
H24: =IFERROR(F24+G24,0) -> 0 | K24: =IFERROR(F24/J24,0) -> 0 | P24: MC — Value-Add
H25: =IFERROR(F25+G25,0) -> 0 | K25: =IFERROR(F25/J25,0) -> 0 | P25: Add row 1 (label me) | T25: =IFERROR(S25*R25,0) -> 0 | U25: =IFERROR(S25/Q25,0) -> 0 | V25: =IFERROR(H53,0) -> 0 | W25: =IFERROR(V25/S25-1,"") | X25: =IFERROR(V25-S25,"") -> 0 | Y25: =IFERROR(V25*R25,0) -> 0 | Z25: =IFERROR(V25/Q25,0) -> 0
H26: =IFERROR(F26+G26,0) -> 0 | K26: =IFERROR(F26/J26,0) -> 0 | P26: Subtotal — Value-Add | Q26: {=IFERROR(SUMPRODUCT(Q19:Q25,ABS(R19:R25))/SUMPRODUCT(ABS(R19:R25)),0)} -> 0 | R26: =SUM(R19:R25) -> 0 | S26: {=IFERROR(SUMPRODUCT(S19:S25,ABS(R19:R25))/SUMPRODUCT(ABS(R19:R25)),0)} -> 0 | T26: =SUM(T19:T25) -> 0 | U26: =IFERROR(T26/(Q26*R26),0) -> 0 | V26: {=IFERROR(SUMPRODUCT(V19:V25,ABS(R19:R25))/SUMPRODUCT(ABS(R19:R25)),0)} -> 0 | W26: =IFERROR(V26/S26-1,"") | X26: =IFERROR(V26-S26,"") -> 0 | Y26: =SUM(Y19:Y25) -> 0 | Z26: =IFERROR(Y26/(Q26*R26),0) -> 0
H27: =IFERROR(F27+G27,0) -> 0 | K27: =IFERROR(F27/J27,0) -> 0 | P27: TOTAL — STABILIZED (In-Place + Value-Add) | Q27: =IFERROR((Q16*R16+Q26*R26)/(R16+R26),0) -> 0 | R27: =R16+R26 -> 0 | S27: =IFERROR((S16*R16+S26*R26)/(R16+R26),0) -> 0 | T27: =T16+T26 -> 0 | U27: =IFERROR(T27/(Q27*R27),0) -> 0 | V27: =IFERROR((V16*R16+V26*R26)/(R16+R26),0) -> 0 | W27: =IFERROR(V27/S27-1,"") | X27: =IFERROR(V27-S27,"") -> 0 | Y27: =Y16+Y26 -> 0 | Z27: =IFERROR(Y27/(Q27*R27),0) -> 0
H28: =IFERROR(F28+G28,0) -> 0 | K28: =IFERROR(F28/J28,0) -> 0
H29: =IFERROR(F29+G29,0) -> 0 | K29: =IFERROR(F29/J29,0) -> 0 | P29: SUMMARY | Q29: Toggle Avg/Max at O2 to flex Current rents
H30: =IFERROR(F30+G30,0) -> 0 | K30: =IFERROR(F30/J30,0) -> 0 | S30: Current (In-Place) | V30: Target (Comp Repriced) | Y30: Projected (Stabilized) | AB30: T-12 Actual
H31: =IFERROR(F31+G31,0) -> 0 | K31: =IFERROR(F31/J31,0) -> 0 | P31: Gross Potential Revenue / mo | S31: =IFERROR(T16,0) -> 0 | V31: =IFERROR(Y16,0) -> 0 | Y31: =IFERROR(T27,0) -> 0 | AA31: Sum of In-Place rows T5:T15 (Avg/Max toggle drives this) | AB31: =IFERROR('T-12 Analysis'!N83/12,0) -> 0 | AC31: T-12 historical GPR (12-mo billed rent before vacancy/LtL)
H32: =IFERROR(F32+G32,0) -> 0 | K32: =IFERROR(F32/J32,0) -> 0 | P32: Gross Potential Revenue / yr (annualized) | S32: =IFERROR(S31*12,0) -> 0 | V32: =IFERROR(V31*12,0) -> 0 | Y32: =IFERROR(Y31*12,0) -> 0 | AA32: row 31 x 12 | AB32: =IFERROR('T-12 Analysis'!N83,0) -> 0 | AC32: From T-12!N58 Gross Potential Rent
H33: =IFERROR(F33+G33,0) -> 0 | K33: =IFERROR(F33/J33,0) -> 0 | P33: Implied Avg Rate / Bed / mo | S33: =IFERROR(S31/R16,0) -> 0 | V33: =IFERROR(V31/R16,0) -> 0 | Y33: =IFERROR(Y31/R27,0) -> 0 | AA33: row 31 / R16 (in-place); Projected uses R27 (stabilized) | AB33: =IFERROR('T-12 Analysis'!N83/12/'Prop Info'!B15,0) -> 0 | AC33: divided by 12 / licensed beds
H34: =IFERROR(F34+G34,0) -> 0 | K34: =IFERROR(F34/J34,0) -> 0 | P34: Gap vs Current ($/mo) | S34: - | V34: =IFERROR(V31-S31,"") -> 0 | Y34: =IFERROR(Y31-S31,"") -> 0 | AA34: Uplift opportunity vs in-place | AB34: =IFERROR(AB31-S31,"") -> 0 | AC34: Positive = current rent roll below historical; negative = above
H35: =IFERROR(F35+G35,0) -> 0 | K35: =IFERROR(F35/J35,0) -> 0
A36: AVG — AS | F36: =IFERROR(AVERAGEIF(F24:F35,">"&0),0) -> 0 | G36: =IFERROR(AVERAGEIF(G24:G35,">"&0),0) -> 0 | H36: =IFERROR(AVERAGEIF(H24:H35,">"&0),0) -> 0 | I36: =IFERROR(AVERAGEIF(I24:I35,">"&0),0) -> 0
A37: Subj. vs. Avg AS Rent | F37: =Scenarios!F38-F36 -> 0
A39: MEMORY CARE (MC) COMPS
A40: Distance (mi) | B40: Vintage | C40: Units | D40: Type | E40: Property Name | F40: Base Rent/mo | G40: Care Fee/mo | H40: All-In Rate | I40: Occupancy % | J40: Sq Ft | K40: $/Sq Ft | L40: Notes
H41: =IFERROR(F41+G41,0) -> 0 | K41: =IFERROR(F41/J41,0) -> 0
H42: =IFERROR(F42+G42,0) -> 0 | K42: =IFERROR(F42/J42,0) -> 0
H43: =IFERROR(F43+G43,0) -> 0 | K43: =IFERROR(F43/J43,0) -> 0
H44: =IFERROR(F44+G44,0) -> 0 | K44: =IFERROR(F44/J44,0) -> 0
H45: =IFERROR(F45+G45,0) -> 0 | K45: =IFERROR(F45/J45,0) -> 0
H46: =IFERROR(F46+G46,0) -> 0 | K46: =IFERROR(F46/J46,0) -> 0
H47: =IFERROR(F47+G47,0) -> 0 | K47: =IFERROR(F47/J47,0) -> 0
H48: =IFERROR(F48+G48,0) -> 0 | K48: =IFERROR(F48/J48,0) -> 0
H49: =IFERROR(F49+G49,0) -> 0 | K49: =IFERROR(F49/J49,0) -> 0
H50: =IFERROR(F50+G50,0) -> 0 | K50: =IFERROR(F50/J50,0) -> 0
H51: =IFERROR(F51+G51,0) -> 0 | K51: =IFERROR(F51/J51,0) -> 0
H52: =IFERROR(F52+G52,0) -> 0 | K52: =IFERROR(F52/J52,0) -> 0
A53: AVG — ME | F53: =IFERROR(AVERAGEIF(F41:F52,">"&0),0) -> 0 | G53: =IFERROR(AVERAGEIF(G41:G52,">"&0),0) -> 0 | H53: =IFERROR(AVERAGEIF(H41:H52,">"&0),0) -> 0 | I53: =IFERROR(AVERAGEIF(I41:I52,">"&0),0) -> 0
A54: Subj. vs. Avg ME Rent | F54: =Scenarios!F38-F53 -> 0

Sheet Capex
A1: CAPITAL EXPENDITURE BUDGET — DETAILED BREAKDOWN
A2: Classify each item as Value-Add (VA) or Maintenance (M). VA flows into LTC; Maintenance is operating reserve.
A3: Item | B3: Qty | C3: Unit Cost | D3: Total Cost | E3: VA or M? | F3: Funded By | G3: Notes
A4: EXTERIOR & GROUNDS
A5: Roof Replacement | D5: =B5*C5 -> 0
A6: Parking Lot Resurface | D6: =B6*C6 -> 0
A7: Landscaping / Curb Appeal | D7: =B7*C7 -> 0
A8: Signage | D8: =B8*C8 -> 0
A9: Exterior Paint / Siding | D9: =B9*C9 -> 0
A10: Lighting (exterior) | D10: =B10*C10 -> 0
A11: Subtotal — EXTERIOR & GROUNDS | D11: =SUM(D5:D10) -> 0
A13: COMMON AREAS
A14: Lobby / Reception Renovation | B14: 1 | D14: =B14*C14 -> 0 | E14: M | G14: Placeholders
A15: Dining Room Renovation | D15: =B15*C15 -> 0 | G15: Placeholders
A16: Activity Room Renovation | D16: =B16*C16 -> 0 | G16: Placeholders
A17: Hallway Flooring | D17: =B17*C17 -> 0
A18: Common Area Furniture (FF&E) | D18: =B18*C18 -> 0 | G18: placehodlers
A19: Elevator Modernization | D19: =B19*C19 -> 0
A20: Subtotal — COMMON AREAS | D20: =SUM(D14:D19) -> 0
A22: UNIT INTERIORS
A23: Unit Flooring (per unit) | D23: =B23*C23 -> 0
A24: Unit Paint (per unit) | D24: =B24*C24 -> 0
A25: Bathroom Grab Bars / ADA (per unit) | D25: =B25*C25 -> 0
A26: Kitchen Appliances (per unit) | D26: =B26*C26 -> 0
A27: Unit Door / Hardware Upgrade | D27: =B27*C27 -> 0
A28: Window Replacement (per unit) | D28: =B28*C28 -> 0
A29: Subtotal — UNIT INTERIORS | D29: =SUM(D23:D28) -> 0
A31: MEDICAL & SAFETY
A32: Nurse Call System Upgrade | D32: =B32*C32 -> 0
A33: Fire Suppression / Sprinklers | D33: =B33*C33 -> 0
A34: HVAC Units | D34: =B34*C34 -> 0
A35: Emergency Generator | D35: =B35*C35 -> 0
A36: Security Camera System | D36: =B36*C36 -> 0
A37: Medication Management System | D37: =B37*C37 -> 0
A38: Subtotal — MEDICAL & SAFETY | D38: =SUM(D32:D37) -> 0
A40: TECHNOLOGY & SYSTEMS
A41: EHR / Resident Mgmt Software | D41: =B41*C41 -> 0
A42: WiFi Infrastructure | D42: =B42*C42 -> 0
A43: Telephone / Intercom System | D43: =B43*C43 -> 0
A44: Access Control / Key Card | D44: =B44*C44 -> 0
A45: Subtotal — TECHNOLOGY & SYSTEMS | D45: =SUM(D41:D44) -> 0
A47: CONTINGENCY
A48: Contingency (10%) | D48: =(D11+D20+D29+D38+D45)*0.1 -> 0
A49: Subtotal — CONTINGENCY | D49: =SUM(D48) -> 0
A51: TOTAL CAPEX BUDGET | D51: =SUM(D11,D20,D29,D38,D45,D49) -> 0
A52: Value-Add CapEx (VA) | D52: =SUMIF(E4:E50,"VA",D4:D50) -> 0
A53: Maintenance CapEx (M) | D53: =SUMIF(E4:E50,"M",D4:D50) -> 0

Sheet Exit Strategy
A1: EXIT STRATEGY — REFINANCE & SALE ANALYSIS
A4: =IF(ISNUMBER(C5),"Refi - Year "&C5,"Refinance (set Refi Year below)") -> Refinance (set Refi Year below) | E4: =IF(ISNUMBER(Scenarios!F135),"Sale - Year "&Scenarios!F135,"Sale (set Exit Year in Scenarios)") -> Sale - Year 0
A5: Refi Year (or NA) | C5: NA | E5: Net Operating Income | G5: =IFERROR(INDEX('P&L'!D97:M97,1,Scenarios!F135),0) -> 0
A6: Net Operating Income | C6: =IFERROR(IF(ISNUMBER(C5),_xlfn.SINGLE(INDEX('P&L'!D97:M97,1,C5)),0),0) -> 0 | E6: Cap Rate | G6: =Scenarios!F136 -> 0
A7: Cap Rate at Re-Finance | C7: 0.06 | E7: Insurance/Tax/Lender Escrows | G7: =SUM('Acquisition Costs'!D35:D36) -> 0
A8: Appraised Value | C8: =IFERROR(C6/C7,0) -> 0 | E8: Operating Reserves remaining | G8: =IFERROR(INDEX('P&L'!D108:M108,1,Scenarios!F135),0) -> 0 | I8: Remaining capital in account for operating reserves
A9: Re-Finance LTV | C9: 0.75 | E9: Sales Price | G9: =IFERROR(G5/G6,0) -> 0
A10: Interest Rate | C10: 0.07 | E10: Sales Cost | F10: 0.03 | G10: =-G9*F10 -> 0
A11: Term / Amortization (Years) | C11: 30 | E11: Outstanding Loan Balance | G11: =-(IFERROR(INDEX(Loans!J43:S43,1,Scenarios!F135),0)) -> 0
A12: Re-Finance Loan Amount | C12: =IFERROR(C8*C9,0) -> 0 | E12: Total Equity | G12: =G9+G10+G11+G7+G8 -> 0
A13: - Re-Finance Costs | B13: 0.02 | C13: =-C12*B13 -> 0 | E13: - Return of Member Capital | G13: =Scenarios!F33+Scenarios!F34 -> 0
A14: - Prepayment Penalty | C14: 0 | E14: - Members Preferred Return Deficiency | G14: =IFERROR(MAX((Waterfall!M39+Waterfall!M41)-(Waterfall!M40+Waterfall!M42),0),0) -> 0
A15: - Repay Outstanding Loan Balance | C15: =-(IFERROR(INDEX(Loans!J43:S43,1,C5),0)) -> 0 | E15: Net Proceeds/Profit from Sale | G15: =G12-G13-G14 -> 0
A16: Gross Proceeds from Re-Finance | C16: =IFERROR(C12+C13+C14+C15,0) -> 0 | E16: Principal Reduction | G16: =IFERROR(Scenarios!F141-INDEX(Loans!J43:S43,1,Scenarios!F135),0) -> 0
A17: - Return of Member Capital | C17: =IFERROR(MIN(C16,Scenarios!$F$33+Scenarios!$F$34),0) -> 0 | E17: Appreciation | G17: =G15-G16 -> 0
A18: Capital Account Balance After Re-Fi | C18: =IFERROR(MAX(Scenarios!$F$33+Scenarios!$F$34-C17,0),0) -> 0 | E18: Capital Transaction Fee to Mgr | F18: 0.01 | G18: =G9*F18 -> 0
A19: % of Initial Investment Returned | C19: =IFERROR(C17/(Scenarios!$F$33+Scenarios!$F$34),0) -> 0 | E19: Net Proceeds/Profit Paid to Members | F19: =1-Scenarios!F36 -> 0.4 | G19: =(G15-G18)*(1-Scenarios!F36) -> 0
A20: Net Proceeds/Profit from Re-Finance | C20: =IFERROR(C16-C17,0) -> 0 | E20: Net Proceeds/Profit Paid to Manager | F20: =Scenarios!F36 -> 0.6 | G20: =(G15-G18)*Scenarios!F36 -> 0
A21: Principal Reduction | C21: =IFERROR(Scenarios!F141-INDEX(Loans!J43:S43,1,C5),0) -> 0 | E21: Total Cash to Members at Sale (Init. Cptl. + Apprec.) | G21: =G13+G19 -> 0
A22: Appreciation | C22: =IFERROR(MAX(C20-C21,0),0) -> 0
A23: Capital Transaction Fee to Mgr | B23: 0.01 | C23: =C8*B23 -> 0 | E23: After Final Disposition
A24: Net Proceeds/Profit Paid to Members | B24: =1-Scenarios!F36 -> 0.4 | C24: =(C20-C23)*(1-Scenarios!F36) -> 0 | E24: Total Profits from Appreciation Paid to Members | G24: =G19 -> 0
A25: Net Proceeds/Profit Paid to Manager | B25: =Scenarios!F36 -> 0.6 | C25: =(C20-C23)*Scenarios!F36 -> 0 | E25: Total Cash to Members | G25: =G21 -> 0
A26: Total Cash to Members at Refi (Init. Cptl. + Apprec.) | C26: =C17+C24 -> 0 | E26: Internal Rate of Return (IRR) — Class A LP | G26: ='XIRR Analysis'!H54 -> 0
A27: Ending Capital Account Balance | C27: =IFERROR(MAX(Scenarios!$F$33+Scenarios!$F$34-C26,0),0) -> 0 | E27: Average Cash on Cash Return — Class A LP | G27: ='LP Return Illustration'!B30 -> 0
A28: Re-Finance IO Period | C28: 12
A31: Scenarios Tab
A32: Loans Tab

Sheet Waterfall
A1: WATERFALL & RETURNS — DYNAMIC DISTRIBUTION MODEL
A2: Inputs at top. All distributions cascade automatically. Class A/B LP toggle in row 7. Active Scenario drives equity and NOI. | P2: HOW THE 3-TIER IRR-HURDLE PROMOTE WORKS (live - updates with your inputs)
A4: WATERFALL INPUTS (auto-linked to active scenario — override here if needed) | P4: Distributable cash each period is paid in this order:
A5: Hold Period (years) | B5: =Scenarios!F135 -> 0 | C5: From Scenarios — selectable exit year | P5: =" 1. Preferred return - Class A "&TEXT($B$11,"0.0%")&" (rows 42-45)" -> 1. Preferred return - Class A 0.0% (rows 42-45)
A6: Exit Cap Rate | B6: =Scenarios!F136 -> 0 | C6: Applied to Y{hold} NOI | P6: 2. Return of capital at exit (rows 36-38)
A7: Selling Costs at Exit | B7: 0.03 | C7: 2.5% of gross sale price | P7: 3. Residual promote - split LP / GP by IRR tier (engine rows 104-114)
A8: GP Equity | B8: =Scenarios!F32 -> 0 | C8: Co-invest; promote governed by tiers below
A9: Class A LP Equity | B9: =Scenarios!F33 -> 0 | C9: Preferred equity — priority capital return | P9: TIER SWITCHING (on the LP cumulative IRR - pref + capital + promote)
A10: Class B LP Equity | B10: =Scenarios!F34 -> 0 | C10: Common equity — participates in promote | P10: =" Tier 1 - up to "&TEXT($B$17,"0.0%")&" IRR LP "&TEXT($B$15,"0%")&" / GP "&TEXT(1-$B$15,"0%") -> Tier 1 - up to 0.0% IRR LP 40% / GP 60%
A11: Class A Preferred Return % | B11: =Scenarios!F35 -> 0 | C11: Annual pref on Class A equity | P11: =" Tier 2 - "&TEXT($B$17,"0.0%")&" to "&TEXT($B$20,"0.0%")&" IRR LP "&TEXT($B$18,"0%")&" / GP "&TEXT(1-$B$18,"0%") -> Tier 2 - 0.0% to 0.0% IRR LP 50% / GP 50%
A12: Class B Preferred Return % | B12: 0 | C12: Annual pref on Class B equity | D12: Class B Treatment → | E12: Pref Only | F12: Pref Only = Class B pref only, no promote. Common Equity = Class B shares LP promote proportionally by equity. | P12: =" Tier 3 - above "&TEXT($B$20,"0.0%")&" IRR LP "&TEXT($B$21,"0%")&" / GP "&TEXT(1-$B$21,"0%") -> Tier 3 - above 0.0% IRR LP 50% / GP 50%
A13: GP Preferred Return % | B13: 0 | C13: Set 0 if GP pref not negotiated
A14: Use Two LP Classes? (YES/NO) | B14: =IF(Scenarios!F34>0,"YES","NO") -> NO | C14: Auto: YES only when Class B equity > 0 | P14: HOW IT WORKS (accreting-hurdle method - no iteration)
A15: Tier 1 LP Split % | B15: =Scenarios!F29 -> 0.4 | C15: LP share above pref, below Tier 1 hurdle | P15: Each IRR hurdle is an LP capital balance that grows at the hurdle rate and
A16: Tier 1 GP Split % | B16: =1-B15 -> 0.6 | C16: Auto = 1 - LP % | P16: is paid down by every LP dollar (pref + return of capital + promote).
A17: Tier 1 IRR Hurdle | B17: 0 | C17: LP blended IRR to trigger Tier 2 | P17: When a balance reaches zero the LP has earned that IRR, and the promote
A18: Tier 2 LP Split % | B18: 0.5 | C18: Above Tier 1 hurdle | P18: steps to the next tier. Exit is folded into the hold year (B5).
A19: Tier 2 GP Split % | B19: =1-B18 -> 0.5 | C19: GP promote above Tier 1
A20: Tier 2 IRR Hurdle | B20: 0 | C20: LP blended IRR to trigger Tier 3 | P20: LIVE RESULT (IRR shown on XIRR basis)
A21: Tier 3 LP Split % | B21: 0.5 | C21: Above Tier 2 hurdle | P21: =" Hold "&TEXT($B$5,"0")&" yrs - LP equity "&TEXT($B$9+$B$10,"$#,##0")&" - LP IRR (XIRR) "&TEXT($B$69,"0.0%") -> Hold 0 yrs - LP equity $0 - LP IRR (XIRR) 0.0%
A22: Tier 3 GP Split % | B22: =1-B21 -> 0.5 | C22: Super-promote above Tier 2 | P22: =" Tier-1 hurdle "&TEXT($B$17,"0.0%")&": "&IF($B$69>=$B$17,"CLEARED","not cleared")&" Tier-2 hurdle "&TEXT($B$20,"0.0%")&": "&IF($B$69>=$B$20,"CLEARED","not cleared") -> Tier-1 hurdle 0.0%: CLEARED Tier-2 hurdle 0.0%: CLEARED
A23: Refi Proceeds Treatment | B23: Return of Capital | C23: Options: "Return of Capital" or "Waterfall" — controls how refi cash-out is treated | P23: =" Total LP distributions "&TEXT($M$57,"$#,##0")&" (EM "&TEXT(IFERROR($M$57/($B$9+$B$10),0),"0.00")&"x)" -> Total LP distributions $0 (EM 0.00x)
A24: ANNUAL CASH FLOW & DISTRIBUTION WATERFALL | P24: =" Total GP distributions "&TEXT($M$58,"$#,##0") -> Total GP distributions $0
A25: Line Item | B25: Year 1 | C25: Year 2 | D25: Year 3 | E25: Year 4 | F25: Year 5 | G25: Year 6 | H25: Year 7 | I25: Year 8 | J25: Year 9 | K25: Year 10 | L25: Exit Proceeds | M25: Total ($) | P25: =" of which GP promote "&TEXT($M$49,"$#,##0") -> of which GP promote $0
A26: NOI (from P&L) | B26: =IF(1>$B$5,0,'P&L'!D97) -> 0 | C26: =IF(2>$B$5,0,'P&L'!E97) -> 0 | D26: =IF(3>$B$5,0,'P&L'!F97) -> 0 | E26: =IF(4>$B$5,0,'P&L'!G97) -> 0 | F26: =IF(5>$B$5,0,'P&L'!H97) -> 0 | G26: =IF(6>$B$5,0,'P&L'!I97) -> 0 | H26: =IF(7>$B$5,0,'P&L'!J97) -> 0 | I26: =IF(8>$B$5,0,'P&L'!K97) -> 0 | J26: =IF(9>$B$5,0,'P&L'!L97) -> 0 | K26: =IF(10>$B$5,0,'P&L'!M97) -> 0 | M26: =SUM(B26:K26) -> 0
A27: Less: Debt Service (annual) | B27: =IF(1>$B$5,0,-INDEX(Loans!$J$42:$S$42,1,1)) -> 0 | C27: =IF(2>$B$5,0,-INDEX(Loans!$J$42:$S$42,1,2)) -> 0 | D27: =IF(3>$B$5,0,-INDEX(Loans!$J$42:$S$42,1,3)) -> 0 | E27: =IF(4>$B$5,0,-INDEX(Loans!$J$42:$S$42,1,4)) -> 0 | F27: =IF(5>$B$5,0,-INDEX(Loans!$J$42:$S$42,1,5)) -> 0 | G27: =IF(6>$B$5,0,-INDEX(Loans!$J$42:$S$42,1,6)) -> 0 | H27: =IF(7>$B$5,0,-INDEX(Loans!$J$42:$S$42,1,7)) -> 0 | I27: =IF(8>$B$5,0,-INDEX(Loans!$J$42:$S$42,1,8)) -> 0 | J27: =IF(9>$B$5,0,-INDEX(Loans!$J$42:$S$42,1,9)) -> 0 | K27: =IF(10>$B$5,0,-INDEX(Loans!$J$42:$S$42,1,10)) -> 0 | M27: =SUM(B27:K27) -> 0 | P27: TO USE IT
A28: Free Cash Flow (FCF) | B28: =IF(1>$B$5,0,IFERROR(B26+B27-'P&L'!D111+IF($B$23="Waterfall",IF(ISNUMBER('Exit Strategy'!$C$5),IF(1='Exit Strategy'!$C$5,'Exit Strategy'!$C$16,0),0),0),0)) -> 0 | C28: =IF(2>$B$5,0,IFERROR(C26+C27-'P&L'!E111+IF($B$23="Waterfall",IF(ISNUMBER('Exit Strategy'!$C$5),IF(2='Exit Strategy'!$C$5,'Exit Strategy'!$C$16,0),0),0),0)) -> 0 | D28: =IF(3>$B$5,0,IFERROR(D26+D27-'P&L'!F111+IF($B$23="Waterfall",IF(ISNUMBER('Exit Strategy'!$C$5),IF(3='Exit Strategy'!$C$5,'Exit Strategy'!$C$16,0),0),0),0)) -> 0 | E28: =IF(4>$B$5,0,IFERROR(E26+E27-'P&L'!G111+IF($B$23="Waterfall",IF(ISNUMBER('Exit Strategy'!$C$5),IF(4='Exit Strategy'!$C$5,'Exit Strategy'!$C$16,0),0),0),0)) -> 0 | F28: =IF(5>$B$5,0,IFERROR(F26+F27-'P&L'!H111+IF($B$23="Waterfall",IF(ISNUMBER('Exit Strategy'!$C$5),IF(5='Exit Strategy'!$C$5,'Exit Strategy'!$C$16,0),0),0),0)) -> 0 | G28: =IF(6>$B$5,0,IFERROR(G26+G27-'P&L'!I111+IF($B$23="Waterfall",IF(ISNUMBER('Exit Strategy'!$C$5),IF(6='Exit Strategy'!$C$5,'Exit Strategy'!$C$16,0),0),0),0)) -> 0 | H28: =IF(7>$B$5,0,IFERROR(H26+H27-'P&L'!J111+IF($B$23="Waterfall",IF(ISNUMBER('Exit Strategy'!$C$5),IF(7='Exit Strategy'!$C$5,'Exit Strategy'!$C$16,0),0),0),0)) -> 0 | I28: =IF(8>$B$5,0,IFERROR(I26+I27-'P&L'!K111+IF($B$23="Waterfall",IF(ISNUMBER('Exit Strategy'!$C$5),IF(8='Exit Strategy'!$C$5,'Exit Strategy'!$C$16,0),0),0),0)) -> 0 | J28: =IF(9>$B$5,0,IFERROR(J26+J27-'P&L'!L111+IF($B$23="Waterfall",IF(ISNUMBER('Exit Strategy'!$C$5),IF(9='Exit Strategy'!$C$5,'Exit Strategy'!$C$16,0),0),0),0)) -> 0 | K28: =IF(10>$B$5,0,IFERROR(K26+K27-'P&L'!M111+IF($B$23="Waterfall",IF(ISNUMBER('Exit Strategy'!$C$5),IF(10='Exit Strategy'!$C$5,'Exit Strategy'!$C$16,0),0),0),0)) -> 0 | M28: =SUM(B28:K28) -> 0 | P28: Enter the three tier splits in B15 / B18 / B21 and the two IRR hurdles
P29: in B17 / B20. With all splits equal (today default) the tiers act as one;
A30: EXIT PROCEEDS ANALYSIS | P30: enter a ladder (e.g. 90% / 70% / 50%) to engage the promote. B17 and B20
A31: Exit Year NOI | B31: ='Exit Strategy'!G5 -> 0 | P31: then move the LP / GP split.
A32: Gross Sale Price (NOI ÷ Exit Cap) | B32: ='Exit Strategy'!G9 -> 0
A33: Less: Selling Costs + Disposition Fee | B33: ='Exit Strategy'!G10+'Exit Strategy'!G18 -> 0 | P33: GP distributions (row 58) run through the exit year (up to year 10).
A34: Less: Loan Payoff | B34: ='Exit Strategy'!G11 -> 0 | P34: Audit: promote engine rows 104-114; visual rows 116-121.
A35: NET SALE PROCEEDS | B35: =B32+B33+B34 -> 0
A36: Return of Capital — Class A LP | B36: =IF(1>$B$5,0,MIN($B$9,IF(AND($B$23="Return of Capital",ISNUMBER('Exit Strategy'!$C$5),1='Exit Strategy'!$C$5),MAX('Exit Strategy'!$C$16,0),0))) -> 0 | C36: =IF(2>$B$5,0,MIN($B$9,IF(AND($B$23="Return of Capital",ISNUMBER('Exit Strategy'!$C$5),2='Exit Strategy'!$C$5),MAX('Exit Strategy'!$C$16,0),0))) -> 0 | D36: =IF(3>$B$5,0,MIN($B$9,IF(AND($B$23="Return of Capital",ISNUMBER('Exit Strategy'!$C$5),3='Exit Strategy'!$C$5),MAX('Exit Strategy'!$C$16,0),0))) -> 0 | E36: =IF(4>$B$5,0,MIN($B$9,IF(AND($B$23="Return of Capital",ISNUMBER('Exit Strategy'!$C$5),4='Exit Strategy'!$C$5),MAX('Exit Strategy'!$C$16,0),0))) -> 0 | F36: =IF(5>$B$5,0,MIN($B$9,IF(AND($B$23="Return of Capital",ISNUMBER('Exit Strategy'!$C$5),5='Exit Strategy'!$C$5),MAX('Exit Strategy'!$C$16,0),0))) -> 0 | G36: =IF(6>$B$5,0,MIN($B$9,IF(AND($B$23="Return of Capital",ISNUMBER('Exit Strategy'!$C$5),6='Exit Strategy'!$C$5),MAX('Exit Strategy'!$C$16,0),0))) -> 0 | H36: =IF(7>$B$5,0,MIN($B$9,IF(AND($B$23="Return of Capital",ISNUMBER('Exit Strategy'!$C$5),7='Exit Strategy'!$C$5),MAX('Exit Strategy'!$C$16,0),0))) -> 0 | I36: =IF(8>$B$5,0,MIN($B$9,IF(AND($B$23="Return of Capital",ISNUMBER('Exit Strategy'!$C$5),8='Exit Strategy'!$C$5),MAX('Exit Strategy'!$C$16,0),0))) -> 0 | J36: =IF(9>$B$5,0,MIN($B$9,IF(AND($B$23="Return of Capital",ISNUMBER('Exit Strategy'!$C$5),9='Exit Strategy'!$C$5),MAX('Exit Strategy'!$C$16,0),0))) -> 0 | K36: =IF(10>$B$5,0,MIN($B$9,IF(AND($B$23="Return of Capital",ISNUMBER('Exit Strategy'!$C$5),10='Exit Strategy'!$C$5),MAX('Exit Strategy'!$C$16,0),0))) -> 0 | L36: =MIN(B9,MAX(B35,0)) -> 0 | M36: =SUM(B36:L36) -> 0
A37: Return of Capital — Class B LP | B37: =IF(1>$B$5,0,IF($B$14="YES",MIN($B$10,MAX(IF(AND($B$23="Return of Capital",ISNUMBER('Exit Strategy'!$C$5),1='Exit Strategy'!$C$5),MAX('Exit Strategy'!$C$16,0),0)-B36,0)),0)) -> 0 | C37: =IF(2>$B$5,0,IF($B$14="YES",MIN($B$10,MAX(IF(AND($B$23="Return of Capital",ISNUMBER('Exit Strategy'!$C$5),2='Exit Strategy'!$C$5),MAX('Exit Strategy'!$C$16,0),0)-C36,0)),0)) -> 0 | D37: =IF(3>$B$5,0,IF($B$14="YES",MIN($B$10,MAX(IF(AND($B$23="Return of Capital",ISNUMBER('Exit Strategy'!$C$5),3='Exit Strategy'!$C$5),MAX('Exit Strategy'!$C$16,0),0)-D36,0)),0)) -> 0 | E37: =IF(4>$B$5,0,IF($B$14="YES",MIN($B$10,MAX(IF(AND($B$23="Return of Capital",ISNUMBER('Exit Strategy'!$C$5),4='Exit Strategy'!$C$5),MAX('Exit Strategy'!$C$16,0),0)-E36,0)),0)) -> 0 | F37: =IF(5>$B$5,0,IF($B$14="YES",MIN($B$10,MAX(IF(AND($B$23="Return of Capital",ISNUMBER('Exit Strategy'!$C$5),5='Exit Strategy'!$C$5),MAX('Exit Strategy'!$C$16,0),0)-F36,0)),0)) -> 0 | G37: =IF(6>$B$5,0,IF($B$14="YES",MIN($B$10,MAX(IF(AND($B$23="Return of Capital",ISNUMBER('Exit Strategy'!$C$5),6='Exit Strategy'!$C$5),MAX('Exit Strategy'!$C$16,0),0)-G36,0)),0)) -> 0 | H37: =IF(7>$B$5,0,IF($B$14="YES",MIN($B$10,MAX(IF(AND($B$23="Return of Capital",ISNUMBER('Exit Strategy'!$C$5),7='Exit Strategy'!$C$5),MAX('Exit Strategy'!$C$16,0),0)-H36,0)),0)) -> 0 | I37: =IF(8>$B$5,0,IF($B$14="YES",MIN($B$10,MAX(IF(AND($B$23="Return of Capital",ISNUMBER('Exit Strategy'!$C$5),8='Exit Strategy'!$C$5),MAX('Exit Strategy'!$C$16,0),0)-I36,0)),0)) -> 0 | J37: =IF(9>$B$5,0,IF($B$14="YES",MIN($B$10,MAX(IF(AND($B$23="Return of Capital",ISNUMBER('Exit Strategy'!$C$5),9='Exit Strategy'!$C$5),MAX('Exit Strategy'!$C$16,0),0)-J36,0)),0)) -> 0 | K37: =IF(10>$B$5,0,IF($B$14="YES",MIN($B$10,MAX(IF(AND($B$23="Return of Capital",ISNUMBER('Exit Strategy'!$C$5),10='Exit Strategy'!$C$5),MAX('Exit Strategy'!$C$16,0),0)-K36,0)),0)) -> 0 | L37: =IF(B14="YES",MIN(B10,MAX(MAX(B35,0)-L36,0)),0) -> 0 | M37: =SUM(B37:L37) -> 0
A38: Return of Capital — GP | B38: =IF(1>$B$5,0,MIN($B$8,MAX(IF(AND($B$23="Return of Capital",ISNUMBER('Exit Strategy'!$C$5),1='Exit Strategy'!$C$5),MAX('Exit Strategy'!$C$16,0),0)-B36-B37,0))) -> 0 | C38: =IF(2>$B$5,0,MIN($B$8,MAX(IF(AND($B$23="Return of Capital",ISNUMBER('Exit Strategy'!$C$5),2='Exit Strategy'!$C$5),MAX('Exit Strategy'!$C$16,0),0)-C36-C37,0))) -> 0 | D38: =IF(3>$B$5,0,MIN($B$8,MAX(IF(AND($B$23="Return of Capital",ISNUMBER('Exit Strategy'!$C$5),3='Exit Strategy'!$C$5),MAX('Exit Strategy'!$C$16,0),0)-D36-D37,0))) -> 0 | E38: =IF(4>$B$5,0,MIN($B$8,MAX(IF(AND($B$23="Return of Capital",ISNUMBER('Exit Strategy'!$C$5),4='Exit Strategy'!$C$5),MAX('Exit Strategy'!$C$16,0),0)-E36-E37,0))) -> 0 | F38: =IF(5>$B$5,0,MIN($B$8,MAX(IF(AND($B$23="Return of Capital",ISNUMBER('Exit Strategy'!$C$5),5='Exit Strategy'!$C$5),MAX('Exit Strategy'!$C$16,0),0)-F36-F37,0))) -> 0 | G38: =IF(6>$B$5,0,MIN($B$8,MAX(IF(AND($B$23="Return of Capital",ISNUMBER('Exit Strategy'!$C$5),6='Exit Strategy'!$C$5),MAX('Exit Strategy'!$C$16,0),0)-G36-G37,0))) -> 0 | H38: =IF(7>$B$5,0,MIN($B$8,MAX(IF(AND($B$23="Return of Capital",ISNUMBER('Exit Strategy'!$C$5),7='Exit Strategy'!$C$5),MAX('Exit Strategy'!$C$16,0),0)-H36-H37,0))) -> 0 | I38: =IF(8>$B$5,0,MIN($B$8,MAX(IF(AND($B$23="Return of Capital",ISNUMBER('Exit Strategy'!$C$5),8='Exit Strategy'!$C$5),MAX('Exit Strategy'!$C$16,0),0)-I36-I37,0))) -> 0 | J38: =IF(9>$B$5,0,MIN($B$8,MAX(IF(AND($B$23="Return of Capital",ISNUMBER('Exit Strategy'!$C$5),9='Exit Strategy'!$C$5),MAX('Exit Strategy'!$C$16,0),0)-J36-J37,0))) -> 0 | K38: =IF(10>$B$5,0,MIN($B$8,MAX(IF(AND($B$23="Return of Capital",ISNUMBER('Exit Strategy'!$C$5),10='Exit Strategy'!$C$5),MAX('Exit Strategy'!$C$16,0),0)-K36-K37,0))) -> 0 | L38: =MIN(B8,MAX(MAX(B35,0)-L36-L37,0)) -> 0 | M38: =SUM(B38:L38) -> 0
A40: ANNUAL DISTRIBUTION WATERFALL
A41: Distribution Tier | B41: Year 1 | C41: Year 2 | D41: Year 3 | E41: Year 4 | F41: Year 5 | G41: Year 6 | H41: Year 7 | I41: Year 8 | J41: Year 9 | K41: Year 10 | L41: Exit Proceeds | M41: Total ($)
A42: Class A LP Preferred Return | B42: =IF(1>$B$5,0,B9*B11) -> 0 | C42: =IF(2>$B$5,0,B9*B11) -> 0 | D42: =IF(3>$B$5,0,B9*B11) -> 0 | E42: =IF(4>$B$5,0,B9*B11) -> 0 | F42: =IF(5>$B$5,0,B9*B11) -> 0 | G42: =IF(6>$B$5,0,B9*B11) -> 0 | H42: =IF(7>$B$5,0,B9*B11) -> 0 | I42: =IF(8>$B$5,0,B9*B11) -> 0 | J42: =IF(9>$B$5,0,B9*B11) -> 0 | K42: =IF(10>$B$5,0,B9*B11) -> 0 | L42: 0 | M42: =SUM(B42:K42) -> 0
A43: Class A Pref Distributed | B43: =MAX(MIN(B28,B42),0) -> 0 | C43: =MAX(MIN(C28,C42),0) -> 0 | D43: =MAX(MIN(D28,D42),0) -> 0 | E43: =MAX(MIN(E28,E42),0) -> 0 | F43: =MAX(MIN(F28,F42),0) -> 0 | G43: =MAX(MIN(G28,G42),0) -> 0 | H43: =MAX(MIN(H28,H42),0) -> 0 | I43: =MAX(MIN(I28,I42),0) -> 0 | ... K43: =MAX(MIN(K28,K42),0) -> 0 | L43: 0 | M43: =SUM(B43:K43) -> 0
A44: Class B LP Preferred Return | B44: =IF(1>$B$5,0,IF(B14="YES",B10*B12,0)) -> 0 | C44: =IF(2>$B$5,0,IF(B14="YES",B10*B12,0)) -> 0 | D44: =IF(3>$B$5,0,IF(B14="YES",B10*B12,0)) -> 0 | E44: =IF(4>$B$5,0,IF(B14="YES",B10*B12,0)) -> 0 | F44: =IF(5>$B$5,0,IF(B14="YES",B10*B12,0)) -> 0 | G44: =IF(6>$B$5,0,IF(B14="YES",B10*B12,0)) -> 0 | H44: =IF(7>$B$5,0,IF(B14="YES",B10*B12,0)) -> 0 | I44: =IF(8>$B$5,0,IF(B14="YES",B10*B12,0)) -> 0 | J44: =IF(9>$B$5,0,IF(B14="YES",B10*B12,0)) -> 0 | K44: =IF(10>$B$5,0,IF(B14="YES",B10*B12,0)) -> 0 | L44: 0 | M44: =SUM(B44:K44) -> 0
A45: Class B Pref Distributed | B45: =IF(B14="YES",MIN(MAX(B28-B43,0),B44),0) -> 0 | C45: =IF(B14="YES",MIN(MAX(C28-C43,0),C44),0) -> 0 | D45: =IF(B14="YES",MIN(MAX(D28-D43,0),D44),0) -> 0 | E45: =IF(B14="YES",MIN(MAX(E28-E43,0),E44),0) -> 0 | F45: =IF(B14="YES",MIN(MAX(F28-F43,0),F44),0) -> 0 | G45: =IF(B14="YES",MIN(MAX(G28-G43,0),G44),0) -> 0 | H45: =IF(B14="YES",MIN(MAX(H28-H43,0),H44),0) -> 0 | I45: =IF(B14="YES",MIN(MAX(I28-I43,0),I44),0) -> 0 | J45: =IF(B14="YES",MIN(MAX(J28-J43,0),J44),0) -> 0 | K45: =IF(B14="YES",MIN(MAX(K28-K43,0),K44),0) -> 0 | L45: 0 | M45: =SUM(B45:K45) -> 0
A46: FCF Remaining After Prefs | B46: =MAX(B28-B43-B45,0) -> 0 | C46: =MAX(C28-C43-C45,0) -> 0 | D46: =MAX(D28-D43-D45,0) -> 0 | E46: =MAX(E28-E43-E45,0) -> 0 | F46: =MAX(F28-F43-F45,0) -> 0 | G46: =MAX(G28-G43-G45,0) -> 0 | H46: =MAX(H28-H43-H45,0) -> 0 | I46: =MAX(I28-I43-I45,0) -> 0 | ... K46: =MAX(K28-K43-K45,0) -> 0 | L46: =MAX(B35,0) -> 0 | M46: =SUM(B46:L46) -> 0
A48: LP Promote (FCF - 3-tier) | B48: =B113 -> 0 | C48: =C113 -> 0 | D48: =D113 -> 0 | E48: =E113 -> 0 | F48: =F113 -> 0 | G48: =G113 -> 0 | H48: =H113 -> 0 | I48: =I113 -> 0 | ... L48: =L113 -> 0 | M48: =SUM(B48:L48) -> 0
A49: GP Promote (FCF - 3-tier) | B49: =B114 -> 0 | C49: =C114 -> 0 | D49: =D114 -> 0 | E49: =E114 -> 0 | F49: =F114 -> 0 | G49: =G114 -> 0 | H49: =H114 -> 0 | I49: =I114 -> 0 | ... L49: =L114 -> 0 | M49: =SUM(B49:L49) -> 0
A50: LP Cash-on-Cash % (operating) | B50: =IFERROR(B57/($B$9+$B$10),0) -> 0 | C50: =IFERROR(C57/($B$9+$B$10),0) -> 0 | D50: =IFERROR(D57/($B$9+$B$10),0) -> 0 | E50: =IFERROR(E57/($B$9+$B$10),0) -> 0 | F50: =IFERROR(F57/($B$9+$B$10),0) -> 0 | G50: =IFERROR(G57/($B$9+$B$10),0) -> 0 | H50: =IFERROR(H57/($B$9+$B$10),0) -> 0 | I50: =IFERROR(I57/($B$9+$B$10),0) -> 0 | ... K50: =IFERROR(K57/($B$9+$B$10),0) -> 0 | M50: =SUM(B50:K50) -> 0
A55: TOTAL CLASS A LP DISTRIBUTIONS | B55: =IF($E$12="Common Equity",B43+B48*IFERROR($B$9/($B$9+$B$10),1),B43+B48) -> 0 | C55: =IF($E$12="Common Equity",C43+C48*IFERROR($B$9/($B$9+$B$10),1),C43+C48) -> 0 | D55: =IF($E$12="Common Equity",D43+D48*IFERROR($B$9/($B$9+$B$10),1),D43+D48) -> 0 | E55: =IF($E$12="Common Equity",E43+E48*IFERROR($B$9/($B$9+$B$10),1),E43+E48) -> 0 | F55: =IF($E$12="Common Equity",F43+F48*IFERROR($B$9/($B$9+$B$10),1),F43+F48) -> 0 | G55: =IF($E$12="Common Equity",G43+G48*IFERROR($B$9/($B$9+$B$10),1),G43+G48) -> 0 | H55: =IF($E$12="Common Equity",H43+H48*IFERROR($B$9/($B$9+$B$10),1),H43+H48) -> 0 | I55: =IF($E$12="Common Equity",I43+I48*IFERROR($B$9/($B$9+$B$10),1),I43+I48) -> 0 | ... K55: =IF($E$12="Common Equity",K43+K48*IFERROR($B$9/($B$9+$B$10),1),K43+K48) -> 0 | L55: =IF($E$12="Common Equity",L43+L48*IFERROR($B$9/($B$9+$B$10),1)+L36,L43+L48+L36) -> 0 | M55: =SUM(B55:L55) -> 0
A56: TOTAL CLASS B LP DISTRIBUTIONS | B56: =IF($E$12="Common Equity",B45+B48*IFERROR($B$10/($B$9+$B$10),0),B45) -> 0 | C56: =IF($E$12="Common Equity",C45+C48*IFERROR($B$10/($B$9+$B$10),0),C45) -> 0 | D56: =IF($E$12="Common Equity",D45+D48*IFERROR($B$10/($B$9+$B$10),0),D45) -> 0 | E56: =IF($E$12="Common Equity",E45+E48*IFERROR($B$10/($B$9+$B$10),0),E45) -> 0 | F56: =IF($E$12="Common Equity",F45+F48*IFERROR($B$10/($B$9+$B$10),0),F45) -> 0 | G56: =IF($E$12="Common Equity",G45+G48*IFERROR($B$10/($B$9+$B$10),0),G45) -> 0 | H56: =IF($E$12="Common Equity",H45+H48*IFERROR($B$10/($B$9+$B$10),0),H45) -> 0 | I56: =IF($E$12="Common Equity",I45+I48*IFERROR($B$10/($B$9+$B$10),0),I45) -> 0 | ... K56: =IF($E$12="Common Equity",K45+K48*IFERROR($B$10/($B$9+$B$10),0),K45) -> 0 | L56: =IF($E$12="Common Equity",L45+L48*IFERROR($B$10/($B$9+$B$10),0)+L37,L45+L37) -> 0 | M56: =SUM(B56:L56) -> 0
A57: TOTAL LP DISTRIBUTIONS (A+B) | B57: =B55+B56 -> 0 | C57: =C55+C56 -> 0 | D57: =D55+D56 -> 0 | E57: =E55+E56 -> 0 | F57: =F55+F56 -> 0 | G57: =G55+G56 -> 0 | H57: =H55+H56 -> 0 | I57: =I55+I56 -> 0 | ... L57: =L55+L56 -> 0 | M57: =SUM(B57:L57) -> 0
A58: TOTAL GP DISTRIBUTIONS | B58: =B49 -> 0 | C58: =C49 -> 0 | D58: =D49 -> 0 | E58: =E49 -> 0 | F58: =F49 -> 0 | G58: =G49 -> 0 | H58: =H49 -> 0 | I58: =I49 -> 0 | ... K58: =K49 -> 0 | L58: =L49+L38 -> 0 | M58: =SUM(B58:L58) -> 0
A60: INVESTOR RETURNS SUMMARY
A61: Metric | B61: Class A LP | C61: Class B LP | D61: LP (Combined) | E61: GP | F61: Notes
A62: [IRR Helper] Class A LP Cash Flows | B62: =-B9 -> 0 | C62: =IF(1>$B$5,0,B55+IF(1=$B$5,L55,0)) -> 0 | D62: =IF(2>$B$5,0,C55+IF(2=$B$5,L55,0)) -> 0 | E62: =IF(3>$B$5,0,D55+IF(3=$B$5,L55,0)) -> 0 | F62: =IF(4>$B$5,0,E55+IF(4=$B$5,L55,0)) -> 0 | G62: =IF(5>$B$5,0,F55+IF(5=$B$5,L55,0)) -> 0 | H62: =IF(6>$B$5,0,G55+IF(6=$B$5,L55,0)) -> 0 | I62: =IF(7>$B$5,0,H55+IF(7=$B$5,L55,0)) -> 0 | J62: =IF(8>$B$5,0,I55+IF(8=$B$5,L55,0)) -> 0 | K62: =IF(9>$B$5,0,J55+IF(9=$B$5,L55,0)) -> 0 | L62: =IF(10>$B$5,0,K55+IF(10=$B$5,L55,0)) -> 0
A63: [IRR Helper] Class B LP Cash Flows | B63: =-B10 -> 0 | C63: =IF(1>$B$5,0,B56+IF(1=$B$5,L56,0)) -> 0 | D63: =IF(2>$B$5,0,C56+IF(2=$B$5,L56,0)) -> 0 | E63: =IF(3>$B$5,0,D56+IF(3=$B$5,L56,0)) -> 0 | F63: =IF(4>$B$5,0,E56+IF(4=$B$5,L56,0)) -> 0 | G63: =IF(5>$B$5,0,F56+IF(5=$B$5,L56,0)) -> 0 | H63: =IF(6>$B$5,0,G56+IF(6=$B$5,L56,0)) -> 0 | I63: =IF(7>$B$5,0,H56+IF(7=$B$5,L56,0)) -> 0 | J63: =IF(8>$B$5,0,I56+IF(8=$B$5,L56,0)) -> 0 | K63: =IF(9>$B$5,0,J56+IF(9=$B$5,L56,0)) -> 0 | L63: =IF(10>$B$5,0,K56+IF(10=$B$5,L56,0)) -> 0
A64: [IRR Helper] GP Cash Flows | B64: =-B8 -> 0 | C64: =IF(1>$B$5,0,B58+IF(1=$B$5,L58,0)) -> 0 | D64: =IF(2>$B$5,0,C58+IF(2=$B$5,L58,0)) -> 0 | E64: =IF(3>$B$5,0,D58+IF(3=$B$5,L58,0)) -> 0 | F64: =IF(4>$B$5,0,E58+IF(4=$B$5,L58,0)) -> 0 | G64: =IF(5>$B$5,0,F58+IF(5=$B$5,L58,0)) -> 0 | H64: =IF(6>$B$5,0,G58+IF(6=$B$5,L58,0)) -> 0 | I64: =IF(7>$B$5,0,H58+IF(7=$B$5,L58,0)) -> 0 | J64: =IF(8>$B$5,0,I58+IF(8=$B$5,L58,0)) -> 0 | K64: =IF(9>$B$5,0,J58+IF(9=$B$5,L58,0)) -> 0 | L64: =IF(10>$B$5,0,K58+IF(10=$B$5,L58,0)) -> 0
A65: Total Equity Invested | B65: =B9 -> 0 | C65: =B10 -> 0 | D65: =B9+B10 -> 0 | E65: =B8 -> 0
A66: Total Distributions | B66: =M55 -> 0 | C66: =M56 -> 0 | D66: =M57 -> 0 | E66: =M58 -> 0
A67: Equity Multiple (EM) | B67: =IFERROR(B66/B65,0) -> 0 | C67: =IFERROR(C66/C65,0) -> 0 | D67: =IFERROR(D66/D65,0) -> 0 | E67: =IFERROR(E66/E65,0) -> 0
A68: Net Profit | B68: =B66-B65 -> 0 | C68: =C66-C65 -> 0 | D68: =D66-D65 -> 0 | E68: =E66-E65 -> 0
A69: IRR | B69: ='XIRR Analysis'!H54 -> 0 | C69: =IFERROR(IRR(B63:M63),0) -> 0 | D69: =IFERROR(IF(B10=0,B69,IRR(B70:M70)),0) -> 0 | E69: =IFERROR(IRR(B64:M64),0) -> 0
A70: [IRR Helper] Combined LP Cash Flows
A73: LP CAPITAL BALANCE TRACKER (Unreturned Capital by Year)
A74: Party | B74: Y0 (Invested) | C74: Y1 | D74: Y2 | E74: Y3 | F74: Y4 | G74: Y5 | H74: Y6 | I74: Y7 | J74: Y8 | K74: Y9 | L74: Y10 | M74: Exit
A75: Class A LP — Invested Capital | B75: =B9 -> 0 | C75: =IF(1>$B$5,0,MAX(B75-IF($B$23="Return of Capital",IF(ISNUMBER('Exit Strategy'!$C$5),IF(1='Exit Strategy'!$C$5,'Exit Strategy'!$C$16*IFERROR($B$9/($B$9+$B$10),1),0),0),0),0)) -> 0 | D75: =IF(2>$B$5,0,MAX(C75-IF($B$23="Return of Capital",IF(ISNUMBER('Exit Strategy'!$C$5),IF(2='Exit Strategy'!$C$5,'Exit Strategy'!$C$16*IFERROR($B$9/($B$9+$B$10),1),0),0),0),0)) -> 0 | E75: =IF(3>$B$5,0,MAX(D75-IF($B$23="Return of Capital",IF(ISNUMBER('Exit Strategy'!$C$5),IF(3='Exit Strategy'!$C$5,'Exit Strategy'!$C$16*IFERROR($B$9/($B$9+$B$10),1),0),0),0),0)) -> 0 | F75: =IF(4>$B$5,0,MAX(E75-IF($B$23="Return of Capital",IF(ISNUMBER('Exit Strategy'!$C$5),IF(4='Exit Strategy'!$C$5,'Exit Strategy'!$C$16*IFERROR($B$9/($B$9+$B$10),1),0),0),0),0)) -> 0 | G75: =IF(5>$B$5,0,MAX(F75-IF($B$23="Return of Capital",IF(ISNUMBER('Exit Strategy'!$C$5),IF(5='Exit Strategy'!$C$5,'Exit Strategy'!$C$16*IFERROR($B$9/($B$9+$B$10),1),0),0),0),0)) -> 0 | H75: =IF(6>$B$5,0,MAX(G75-IF($B$23="Return of Capital",IF(ISNUMBER('Exit Strategy'!$C$5),IF(6='Exit Strategy'!$C$5,'Exit Strategy'!$C$16*IFERROR($B$9/($B$9+$B$10),1),0),0),0),0)) -> 0 | I75: =IF(7>$B$5,0,MAX(H75-IF($B$23="Return of Capital",IF(ISNUMBER('Exit Strategy'!$C$5),IF(7='Exit Strategy'!$C$5,'Exit Strategy'!$C$16*IFERROR($B$9/($B$9+$B$10),1),0),0),0),0)) -> 0 | J75: =IF(8>$B$5,0,MAX(I75-IF($B$23="Return of Capital",IF(ISNUMBER('Exit Strategy'!$C$5),IF(8='Exit Strategy'!$C$5,'Exit Strategy'!$C$16*IFERROR($B$9/($B$9+$B$10),1),0),0),0),0)) -> 0 | K75: =IF(9>$B$5,0,MAX(J75-IF($B$23="Return of Capital",IF(ISNUMBER('Exit Strategy'!$C$5),IF(9='Exit Strategy'!$C$5,'Exit Strategy'!$C$16*IFERROR($B$9/($B$9+$B$10),1),0),0),0),0)) -> 0 | L75: =IF(10>$B$5,0,MAX(K75-IF($B$23="Return of Capital",IF(ISNUMBER('Exit Strategy'!$C$5),IF(10='Exit Strategy'!$C$5,'Exit Strategy'!$C$16*IFERROR($B$9/($B$9+$B$10),1),0),0),0),0)) -> 0 | M75: =B75 -> 0 | N75: =MAX(K75-L51,0) -> 0
A76: Less: Refi — Return of Capital | B76: — | C76: =IF($B$23="Return of Capital",IF(ISNUMBER('Exit Strategy'!$C$5),IF(1='Exit Strategy'!$C$5,'Exit Strategy'!$C$16*IFERROR($B$9/($B$9+$B$10),1),0),0),0) -> 0 | D76: =IF($B$23="Return of Capital",IF(ISNUMBER('Exit Strategy'!$C$5),IF(2='Exit Strategy'!$C$5,'Exit Strategy'!$C$16*IFERROR($B$9/($B$9+$B$10),1),0),0),0) -> 0 | E76: =IF($B$23="Return of Capital",IF(ISNUMBER('Exit Strategy'!$C$5),IF(3='Exit Strategy'!$C$5,'Exit Strategy'!$C$16*IFERROR($B$9/($B$9+$B$10),1),0),0),0) -> 0 | F76: =IF($B$23="Return of Capital",IF(ISNUMBER('Exit Strategy'!$C$5),IF(4='Exit Strategy'!$C$5,'Exit Strategy'!$C$16*IFERROR($B$9/($B$9+$B$10),1),0),0),0) -> 0 | G76: =IF($B$23="Return of Capital",IF(ISNUMBER('Exit Strategy'!$C$5),IF(5='Exit Strategy'!$C$5,'Exit Strategy'!$C$16*IFERROR($B$9/($B$9+$B$10),1),0),0),0) -> 0 | H76: =IF($B$23="Return of Capital",IF(ISNUMBER('Exit Strategy'!$C$5),IF(6='Exit Strategy'!$C$5,'Exit Strategy'!$C$16*IFERROR($B$9/($B$9+$B$10),1),0),0),0) -> 0 | I76: =IF($B$23="Return of Capital",IF(ISNUMBER('Exit Strategy'!$C$5),IF(7='Exit Strategy'!$C$5,'Exit Strategy'!$C$16*IFERROR($B$9/($B$9+$B$10),1),0),0),0) -> 0 | J76: =IF($B$23="Return of Capital",IF(ISNUMBER('Exit Strategy'!$C$5),IF(8='Exit Strategy'!$C$5,'Exit Strategy'!$C$16*IFERROR($B$9/($B$9+$B$10),1),0),0),0) -> 0 | K76: =IF($B$23="Return of Capital",IF(ISNUMBER('Exit Strategy'!$C$5),IF(9='Exit Strategy'!$C$5,'Exit Strategy'!$C$16*IFERROR($B$9/($B$9+$B$10),1),0),0),0) -> 0 | L76: =IF($B$23="Return of Capital",IF(ISNUMBER('Exit Strategy'!$C$5),IF(10='Exit Strategy'!$C$5,'Exit Strategy'!$C$16*IFERROR($B$9/($B$9+$B$10),1),0),0),0) -> 0 | M76: =SUM(C76:L76) -> 0 | N76: =L51 -> 0
A77: Closing Balance | B77: =B75 -> 0 | C77: =C75 -> 0 | D77: =D75 -> 0 | E77: =E75 -> 0 | F77: =F75 -> 0 | G77: =G75 -> 0 | H77: =H75 -> 0 | I77: =I75 -> 0 | ... M77: =M75 -> 0
A79: Total LP — Invested Capital | B79: =B9+B10 -> 0 | C79: =IF(1>$B$5,0,MAX(B79-IF($B$23="Return of Capital",IF(ISNUMBER('Exit Strategy'!$C$5),IF(1='Exit Strategy'!$C$5,'Exit Strategy'!$C$16,0),0),0),0)) -> 0 | D79: =IF(2>$B$5,0,MAX(C79-IF($B$23="Return of Capital",IF(ISNUMBER('Exit Strategy'!$C$5),IF(2='Exit Strategy'!$C$5,'Exit Strategy'!$C$16,0),0),0),0)) -> 0 | E79: =IF(3>$B$5,0,MAX(D79-IF($B$23="Return of Capital",IF(ISNUMBER('Exit Strategy'!$C$5),IF(3='Exit Strategy'!$C$5,'Exit Strategy'!$C$16,0),0),0),0)) -> 0 | F79: =IF(4>$B$5,0,MAX(E79-IF($B$23="Return of Capital",IF(ISNUMBER('Exit Strategy'!$C$5),IF(4='Exit Strategy'!$C$5,'Exit Strategy'!$C$16,0),0),0),0)) -> 0 | G79: =IF(5>$B$5,0,MAX(F79-IF($B$23="Return of Capital",IF(ISNUMBER('Exit Strategy'!$C$5),IF(5='Exit Strategy'!$C$5,'Exit Strategy'!$C$16,0),0),0),0)) -> 0 | H79: =IF(6>$B$5,0,MAX(G79-IF($B$23="Return of Capital",IF(ISNUMBER('Exit Strategy'!$C$5),IF(6='Exit Strategy'!$C$5,'Exit Strategy'!$C$16,0),0),0),0)) -> 0 | I79: =IF(7>$B$5,0,MAX(H79-IF($B$23="Return of Capital",IF(ISNUMBER('Exit Strategy'!$C$5),IF(7='Exit Strategy'!$C$5,'Exit Strategy'!$C$16,0),0),0),0)) -> 0 | J79: =IF(8>$B$5,0,MAX(I79-IF($B$23="Return of Capital",IF(ISNUMBER('Exit Strategy'!$C$5),IF(8='Exit Strategy'!$C$5,'Exit Strategy'!$C$16,0),0),0),0)) -> 0 | K79: =IF(9>$B$5,0,MAX(J79-IF($B$23="Return of Capital",IF(ISNUMBER('Exit Strategy'!$C$5),IF(9='Exit Strategy'!$C$5,'Exit Strategy'!$C$16,0),0),0),0)) -> 0 | L79: =IF(10>$B$5,0,MAX(K79-IF($B$23="Return of Capital",IF(ISNUMBER('Exit Strategy'!$C$5),IF(10='Exit Strategy'!$C$5,'Exit Strategy'!$C$16,0),0),0),0)) -> 0 | M79: =B79 -> 0 | N79: =MAX(K79-L51-L52,0) -> 0
A80: Less: Refi — Return of Capital (Total LP)
A81: Closing Balance (Total LP) | B81: =B79 -> 0 | C81: =C79 -> 0 | D81: =D79 -> 0 | E81: =E79 -> 0 | F81: =F79 -> 0 | G81: =G79 -> 0 | H81: =H79 -> 0 | I81: =I79 -> 0 | ... M81: =M79 -> 0
A83: Note: When toggle = "Return of Capital", refi proceeds reduce LP capital balance and are excluded from operating FCF waterfall. When toggle = "Waterfall", refi proceeds flow through the distribution cascade as additional FCF.
A85: GP ECONOMICS SUMMARY — All Income Streams by Year
A86: Income Source | B86: Y1 | C86: Y2 | D86: Y3 | E86: Y4 | F86: Y5 | G86: Y6 | H86: Y7 | I86: Y8 | J86: Y9 | K86: Y10 | L86: Exit | M86: TOTAL ($)
A87: Acquisition Fee (one-time at close) | B87: =Scenarios!F16 -> 0 | C87: 0 | D87: 0 | E87: 0 | F87: 0 | G87: 0 | H87: 0 | I87: 0 | J87: 0 | K87: 0 | L87: 0 | M87: =Scenarios!F16 -> 0
A88: Asset Management Fee (annual) | B88: =IF(1>$B$5,0,IFERROR('P&L'!D111,0)) -> 0 | C88: =IF(2>$B$5,0,IFERROR('P&L'!E111,0)) -> 0 | D88: =IF(3>$B$5,0,IFERROR('P&L'!F111,0)) -> 0 | E88: =IF(4>$B$5,0,IFERROR('P&L'!G111,0)) -> 0 | F88: =IF(5>$B$5,0,IFERROR('P&L'!H111,0)) -> 0 | G88: =IF(6>$B$5,0,IFERROR('P&L'!I111,0)) -> 0 | H88: =IF(7>$B$5,0,IFERROR('P&L'!J111,0)) -> 0 | I88: =IF(8>$B$5,0,IFERROR('P&L'!K111,0)) -> 0 | J88: =IF(9>$B$5,0,IFERROR('P&L'!L111,0)) -> 0 | K88: =IF(10>$B$5,0,IFERROR('P&L'!M111,0)) -> 0 | L88: 0 | M88: =SUM(B88:L88) -> 0
A89: Operating Promote (Waterfall — annual) | B89: =B49 -> 0 | C89: =C49 -> 0 | D89: =D49 -> 0 | E89: =E49 -> 0 | F89: =F49 -> 0 | G89: =G49 -> 0 | H89: =H49 -> 0 | I89: =I49 -> 0 | ... L89: =L49 -> 0 | M89: =SUM(B89:L89) -> 0
A90: Disposition Fee (at exit) | B90: 0 | C90: 0 | D90: 0 | E90: 0 | F90: 0 | G90: 0 | H90: 0 | I90: 0 | J90: 0 | K90: 0 | L90: ='Exit Strategy'!G18 -> 0 | M90: ='Exit Strategy'!G18 -> 0
A91: GP Co-invest Return (at exit) | F91: 0 | G91: 0 | H91: 0 | I91: 0 | J91: 0 | K91: 0 | L91: =L38 -> 0 | M91: =L38 -> 0
A92: TOTAL GP ECONOMICS | B92: =B87+B88+B89+B90+B91 -> 0 | C92: =C87+C88+C89+C90+C91 -> 0 | D92: =D87+D88+D89+D90+D91 -> 0 | E92: =E87+E88+E89+E90+E91 -> 0 | F92: =F87+F88+F89+F90+F91 -> 0 | G92: =G87+G88+G89+G90+G91 -> 0 | H92: =H87+H88+H89+H90+H91 -> 0 | I92: =I87+I88+I89+I90+I91 -> 0 | ... M92: =M87+M88+M89+M90+M91 -> 0
A94: GP ECONOMICS — BREAKDOWN BY TYPE
A95: Category | B95: Total ($) | C95: % of GP Economics | D95: Notes
A96: Total Fees (Acq + Mgmt + Disposition) | B96: =M87+M88+M90 -> 0 | C96: =IFERROR(B96/M92,0) -> 0 | D96: One-time + annual + exit fees
A97: Total Promote (operating waterfall) | B97: =M89 -> 0 | C97: =IFERROR(B97/M92,0) -> 0 | D97: GP share of FCF above LP pref
A98: Co-invest Return (capital returned at exit)
A99: GRAND TOTAL | B99: =M92 -> 0 | C99: 1 | D99: All GP income streams combined
A101: GP economics include: (1) Acquisition fee at close, (2) Asset mgmt fee annually, (3) Waterfall promote above LP pref, (4) Disposition fee at sale, (5) Return of GP co-invest equity. Promote tracks Scenarios!F36 (GP Promote %). Note: GP co-invest return is return OF capital, not profit — included for completeness.
A104: -- PROMOTE TIER ENGINE (IRR hurdles; pref counts toward IRR) --
A105: LP non-promote cash (pref + ROC) | B105: =B43+B45+B36+B37 -> 0 | C105: =C43+C45+C36+C37 -> 0 | D105: =D43+D45+D36+D37 -> 0 | E105: =E43+E45+E36+E37 -> 0 | F105: =F43+F45+F36+F37 -> 0 | G105: =G43+G45+G36+G37 -> 0 | H105: =H43+H45+H36+H37 -> 0 | I105: =I43+I45+I36+I37 -> 0 | ... L105: =L43+L45+L36+L37 -> 0
A106: Residual to promote (after ROC) | B106: =B46 -> 0 | C106: =C46 -> 0 | D106: =D46 -> 0 | E106: =E46 -> 0 | F106: =F46 -> 0 | G106: =G46 -> 0 | H106: =H46 -> 0 | I106: =I46 -> 0 | ... K106: =K46 -> 0 | L106: =MAX(L46-L36-L37-L38,0) -> 0
A107: Tier-1 hurdle bal - start (accreted @ B17) | B107: =($B$9+$B$10)*(1+$B$17) -> 0 | C107: =B111*(1+$B$17) -> 0 | D107: =C111*(1+$B$17) -> 0 | E107: =D111*(1+$B$17) -> 0 | F107: =E111*(1+$B$17) -> 0 | G107: =F111*(1+$B$17) -> 0 | H107: =G111*(1+$B$17) -> 0 | I107: =H111*(1+$B$17) -> 0 | J107: =I111*(1+$B$17) -> 0 | K107: =J111*(1+$B$17) -> 0 | L107: =IFERROR(INDEX($B$111:$K$111,1,$B$5),0) -> 0
A108: Tier-2 hurdle bal - start (accreted @ B20) | B108: =($B$9+$B$10)*(1+$B$20) -> 0 | C108: =B112*(1+$B$20) -> 0 | D108: =C112*(1+$B$20) -> 0 | E108: =D112*(1+$B$20) -> 0 | F108: =E112*(1+$B$20) -> 0 | G108: =F112*(1+$B$20) -> 0 | H108: =G112*(1+$B$20) -> 0 | I108: =H112*(1+$B$20) -> 0 | J108: =I112*(1+$B$20) -> 0 | K108: =J112*(1+$B$20) -> 0 | L108: =IFERROR(INDEX($B$112:$K$112,1,$B$5),0) -> 0
A109: P1 (tier-1 residual portion) | B109: =IF($B$15<=0,B106,MIN(B106,MAX(B107-B105,0)/$B$15)) -> 0 | C109: =IF($B$15<=0,C106,MIN(C106,MAX(C107-C105,0)/$B$15)) -> 0 | D109: =IF($B$15<=0,D106,MIN(D106,MAX(D107-D105,0)/$B$15)) -> 0 | E109: =IF($B$15<=0,E106,MIN(E106,MAX(E107-E105,0)/$B$15)) -> 0 | F109: =IF($B$15<=0,F106,MIN(F106,MAX(F107-F105,0)/$B$15)) -> 0 | G109: =IF($B$15<=0,G106,MIN(G106,MAX(G107-G105,0)/$B$15)) -> 0 | H109: =IF($B$15<=0,H106,MIN(H106,MAX(H107-H105,0)/$B$15)) -> 0 | I109: =IF($B$15<=0,I106,MIN(I106,MAX(I107-I105,0)/$B$15)) -> 0 | ... L109: =IF($B$15<=0,L106,MIN(L106,MAX(L107-L105,0)/$B$15)) -> 0
A110: P2 (tier-2 residual portion) | B110: =IF($B$18<=0,B106-B109,MIN(B106-B109,MAX((B108-B105)-$B$15*B109,0)/$B$18)) -> 0 | C110: =IF($B$18<=0,C106-C109,MIN(C106-C109,MAX((C108-C105)-$B$15*C109,0)/$B$18)) -> 0 | D110: =IF($B$18<=0,D106-D109,MIN(D106-D109,MAX((D108-D105)-$B$15*D109,0)/$B$18)) -> 0 | E110: =IF($B$18<=0,E106-E109,MIN(E106-E109,MAX((E108-E105)-$B$15*E109,0)/$B$18)) -> 0 | F110: =IF($B$18<=0,F106-F109,MIN(F106-F109,MAX((F108-F105)-$B$15*F109,0)/$B$18)) -> 0 | G110: =IF($B$18<=0,G106-G109,MIN(G106-G109,MAX((G108-G105)-$B$15*G109,0)/$B$18)) -> 0 | H110: =IF($B$18<=0,H106-H109,MIN(H106-H109,MAX((H108-H105)-$B$15*H109,0)/$B$18)) -> 0 | I110: =IF($B$18<=0,I106-I109,MIN(I106-I109,MAX((I108-I105)-$B$15*I109,0)/$B$18)) -> 0 | ... L110: =IF($B$18<=0,L106-L109,MIN(L106-L109,MAX((L108-L105)-$B$15*L109,0)/$B$18)) -> 0
A111: Tier-1 hurdle bal - end | B111: =(B107-B105)-$B$15*B109 -> 0 | C111: =(C107-C105)-$B$15*C109 -> 0 | D111: =(D107-D105)-$B$15*D109 -> 0 | E111: =(E107-E105)-$B$15*E109 -> 0 | F111: =(F107-F105)-$B$15*F109 -> 0 | G111: =(G107-G105)-$B$15*G109 -> 0 | H111: =(H107-H105)-$B$15*H109 -> 0 | I111: =(I107-I105)-$B$15*I109 -> 0 | ... L111: =(L107-L105)-$B$15*L109 -> 0
A112: Tier-2 hurdle bal - end | B112: =(B108-B105)-$B$15*B109-$B$18*B110 -> 0 | C112: =(C108-C105)-$B$15*C109-$B$18*C110 -> 0 | D112: =(D108-D105)-$B$15*D109-$B$18*D110 -> 0 | E112: =(E108-E105)-$B$15*E109-$B$18*E110 -> 0 | F112: =(F108-F105)-$B$15*F109-$B$18*F110 -> 0 | G112: =(G108-G105)-$B$15*G109-$B$18*G110 -> 0 | H112: =(H108-H105)-$B$15*H109-$B$18*H110 -> 0 | I112: =(I108-I105)-$B$15*I109-$B$18*I110 -> 0 | ... L112: =(L108-L105)-$B$15*L109-$B$18*L110 -> 0
A113: LP Promote (all tiers) | B113: =IFERROR($B$15*B109+$B$18*B110+$B$21*(B106-B109-B110),0) -> 0 | C113: =IFERROR($B$15*C109+$B$18*C110+$B$21*(C106-C109-C110),0) -> 0 | D113: =IFERROR($B$15*D109+$B$18*D110+$B$21*(D106-D109-D110),0) -> 0 | E113: =IFERROR($B$15*E109+$B$18*E110+$B$21*(E106-E109-E110),0) -> 0 | F113: =IFERROR($B$15*F109+$B$18*F110+$B$21*(F106-F109-F110),0) -> 0 | G113: =IFERROR($B$15*G109+$B$18*G110+$B$21*(G106-G109-G110),0) -> 0 | H113: =IFERROR($B$15*H109+$B$18*H110+$B$21*(H106-H109-H110),0) -> 0 | I113: =IFERROR($B$15*I109+$B$18*I110+$B$21*(I106-I109-I110),0) -> 0 | ... L113: =IFERROR($B$15*L109+$B$18*L110+$B$21*(L106-L109-L110),0) -> 0
A114: GP Promote (all tiers) | B114: =B106-B113 -> 0 | C114: =C106-C113 -> 0 | D114: =D106-D113 -> 0 | E114: =E106-E113 -> 0 | F114: =F106-F113 -> 0 | G114: =G106-G113 -> 0 | H114: =H106-H113 -> 0 | I114: =I106-I113 -> 0 | ... L114: =L106-L113 -> 0
A116: -- VISUAL: promote split & hurdle clearance by period --
A117: Period | B117: =B41 -> Year 1 | C117: =C41 -> Year 2 | D117: =D41 -> Year 3 | E117: =E41 -> Year 4 | F117: =F41 -> Year 5 | G117: =G41 -> Year 6 | H117: =H41 -> Year 7 | I117: =I41 -> Year 8 | ... L117: =L41 -> Exit Proceeds
A118: LP share of period promote | B118: =IFERROR(B113/B106,"") | C118: =IFERROR(C113/C106,"") | D118: =IFERROR(D113/D106,"") | E118: =IFERROR(E113/E106,"") | F118: =IFERROR(F113/F106,"") | G118: =IFERROR(G113/G106,"") | H118: =IFERROR(H113/H106,"") | I118: =IFERROR(I113/I106,"") | ... L118: =IFERROR(L113/L106,"")
...

Sheet LP Return Illustration
A1: LP RETURN ILLUSTRATION
A2: Investment Amount | B2: =Total_LPA_Equity -> 0 | C2: ← Change this to illustrate any LP
A3: LP Class | B3: Class A | C3: ← Select Class A or Class B | E3: Ownership % of LP Pool | F3: =IFERROR($B$2/IF($B$3="Class A",Waterfall!$B$9,Waterfall!$B$10),0) -> 0 | G3: Pref Rate | H3: =IF($B$3="Class A",Waterfall!$B$11,Waterfall!$B$12) -> 0
A5: Member Returns Based On Specific $ Invested | B5: 1 | C5: 2 | D5: 3 | E5: 4 | F5: 5 | G5: 6 | H5: 7 | I5: 8 | J5: 9 | K5: 10 | L5: Return $ | M5: Return %
A6: A. INVESTED CAPITAL
A7: Beginning Member Capital Account Balance | B7: =IF(1>Waterfall!$B$5,0,$B$2) -> 0 | C7: =IF(2>Waterfall!$B$5,0,$B$2) -> 0 | D7: =IF(3>Waterfall!$B$5,0,$B$2) -> 0 | E7: =IF(4>Waterfall!$B$5,0,$B$2) -> 0 | F7: =IF(5>Waterfall!$B$5,0,$B$2) -> 0 | G7: =IF(6>Waterfall!$B$5,0,$B$2) -> 0 | H7: =IF(7>Waterfall!$B$5,0,$B$2) -> 0 | I7: =IF(8>Waterfall!$B$5,0,$B$2) -> 0 | J7: =IF(9>Waterfall!$B$5,0,$B$2) -> 0 | K7: =IF(10>Waterfall!$B$5,0,$B$2) -> 0
A8: % of Overall LP Pool Ownership for $ Invested | B8: =IF(1>Waterfall!$B$5,"",IFERROR($B$2/IF($B$3="Class A",Waterfall!$B$9,Waterfall!$B$10),0)) | C8: =IF(2>Waterfall!$B$5,"",IFERROR($B$2/IF($B$3="Class A",Waterfall!$B$9,Waterfall!$B$10),0)) | D8: =IF(3>Waterfall!$B$5,"",IFERROR($B$2/IF($B$3="Class A",Waterfall!$B$9,Waterfall!$B$10),0)) | E8: =IF(4>Waterfall!$B$5,"",IFERROR($B$2/IF($B$3="Class A",Waterfall!$B$9,Waterfall!$B$10),0)) | F8: =IF(5>Waterfall!$B$5,"",IFERROR($B$2/IF($B$3="Class A",Waterfall!$B$9,Waterfall!$B$10),0)) | G8: =IF(6>Waterfall!$B$5,"",IFERROR($B$2/IF($B$3="Class A",Waterfall!$B$9,Waterfall!$B$10),0)) | H8: =IF(7>Waterfall!$B$5,"",IFERROR($B$2/IF($B$3="Class A",Waterfall!$B$9,Waterfall!$B$10),0)) | I8: =IF(8>Waterfall!$B$5,"",IFERROR($B$2/IF($B$3="Class A",Waterfall!$B$9,Waterfall!$B$10),0)) | J8: =IF(9>Waterfall!$B$5,"",IFERROR($B$2/IF($B$3="Class A",Waterfall!$B$9,Waterfall!$B$10),0)) | K8: =IF(10>Waterfall!$B$5,"",IFERROR($B$2/IF($B$3="Class A",Waterfall!$B$9,Waterfall!$B$10),0))
A9: B. PREFERRED RETURN TRACKING
A10: Preferred Return Accrued (Annual Target) | B10: =IF(1>Waterfall!$B$5,0,$B$2*IF($B$3="Class A",Waterfall!$B$11,Waterfall!$B$12)) -> 0 | C10: =IF(2>Waterfall!$B$5,0,$B$2*IF($B$3="Class A",Waterfall!$B$11,Waterfall!$B$12)) -> 0 | D10: =IF(3>Waterfall!$B$5,0,$B$2*IF($B$3="Class A",Waterfall!$B$11,Waterfall!$B$12)) -> 0 | E10: =IF(4>Waterfall!$B$5,0,$B$2*IF($B$3="Class A",Waterfall!$B$11,Waterfall!$B$12)) -> 0 | F10: =IF(5>Waterfall!$B$5,0,$B$2*IF($B$3="Class A",Waterfall!$B$11,Waterfall!$B$12)) -> 0 | G10: =IF(6>Waterfall!$B$5,0,$B$2*IF($B$3="Class A",Waterfall!$B$11,Waterfall!$B$12)) -> 0 | H10: =IF(7>Waterfall!$B$5,0,$B$2*IF($B$3="Class A",Waterfall!$B$11,Waterfall!$B$12)) -> 0 | I10: =IF(8>Waterfall!$B$5,0,$B$2*IF($B$3="Class A",Waterfall!$B$11,Waterfall!$B$12)) -> 0 | J10: =IF(9>Waterfall!$B$5,0,$B$2*IF($B$3="Class A",Waterfall!$B$11,Waterfall!$B$12)) -> 0 | K10: =IF(10>Waterfall!$B$5,0,$B$2*IF($B$3="Class A",Waterfall!$B$11,Waterfall!$B$12)) -> 0 | M10: =SUM(B10:K10) -> 0
A11: Preferred Return Paid (Actual Distributed) | B11: =IF(1>Waterfall!$B$5,0,IFERROR($B$2/IF($B$3="Class A",Waterfall!$B$9,Waterfall!$B$10),0)*IF($B$3="Class A",Waterfall!B43,Waterfall!B45)) -> 0 | C11: =IF(2>Waterfall!$B$5,0,IFERROR($B$2/IF($B$3="Class A",Waterfall!$B$9,Waterfall!$B$10),0)*IF($B$3="Class A",Waterfall!C43,Waterfall!C45)) -> 0 | D11: =IF(3>Waterfall!$B$5,0,IFERROR($B$2/IF($B$3="Class A",Waterfall!$B$9,Waterfall!$B$10),0)*IF($B$3="Class A",Waterfall!D43,Waterfall!D45)) -> 0 | E11: =IF(4>Waterfall!$B$5,0,IFERROR($B$2/IF($B$3="Class A",Waterfall!$B$9,Waterfall!$B$10),0)*IF($B$3="Class A",Waterfall!E43,Waterfall!E45)) -> 0 | F11: =IF(5>Waterfall!$B$5,0,IFERROR($B$2/IF($B$3="Class A",Waterfall!$B$9,Waterfall!$B$10),0)*IF($B$3="Class A",Waterfall!F43,Waterfall!F45)) -> 0 | G11: =IF(6>Waterfall!$B$5,0,IFERROR($B$2/IF($B$3="Class A",Waterfall!$B$9,Waterfall!$B$10),0)*IF($B$3="Class A",Waterfall!G43,Waterfall!G45)) -> 0 | H11: =IF(7>Waterfall!$B$5,0,IFERROR($B$2/IF($B$3="Class A",Waterfall!$B$9,Waterfall!$B$10),0)*IF($B$3="Class A",Waterfall!H43,Waterfall!H45)) -> 0 | I11: =IF(8>Waterfall!$B$5,0,IFERROR($B$2/IF($B$3="Class A",Waterfall!$B$9,Waterfall!$B$10),0)*IF($B$3="Class A",Waterfall!I43,Waterfall!I45)) -> 0 | J11: =IF(9>Waterfall!$B$5,0,IFERROR($B$2/IF($B$3="Class A",Waterfall!$B$9,Waterfall!$B$10),0)*IF($B$3="Class A",Waterfall!J43,Waterfall!J45)) -> 0 | K11: =IF(10>Waterfall!$B$5,0,IFERROR($B$2/IF($B$3="Class A",Waterfall!$B$9,Waterfall!$B$10),0)*IF($B$3="Class A",Waterfall!K43,Waterfall!K45)) -> 0 | M11: =SUM(B11:K11) -> 0
A12: Cumulative Preferred Return Shortfall | B12: =IF(1>Waterfall!$B$5,0,MAX(B10-B11,0)) -> 0 | C12: =IF(2>Waterfall!$B$5,0,MAX(B12+C10-C11,0)) -> 0 | D12: =IF(3>Waterfall!$B$5,0,MAX(C12+D10-D11,0)) -> 0 | E12: =IF(4>Waterfall!$B$5,0,MAX(D12+E10-E11,0)) -> 0 | F12: =IF(5>Waterfall!$B$5,0,MAX(E12+F10-F11,0)) -> 0 | G12: =IF(6>Waterfall!$B$5,0,MAX(F12+G10-G11,0)) -> 0 | H12: =IF(7>Waterfall!$B$5,0,MAX(G12+H10-H11,0)) -> 0 | I12: =IF(8>Waterfall!$B$5,0,MAX(H12+I10-I11,0)) -> 0 | J12: =IF(9>Waterfall!$B$5,0,MAX(I12+J10-J11,0)) -> 0 | K12: =IF(10>Waterfall!$B$5,0,MAX(J12+K10-K11,0)) -> 0 | M12: =INDEX(B12:K12,MIN(Waterfall!$B$5,10)) -> #VALUE!
A13: C. ANNUAL CASH DISTRIBUTIONS
A14: Member Cashflow (Total Distribution) | B14: =IF(1>Waterfall!$B$5,0,IFERROR($B$2/IF($B$3="Class A",Waterfall!$B$9,Waterfall!$B$10),0)*IF($B$3="Class A",Waterfall!B55,Waterfall!B56)) -> 0 | C14: =IF(2>Waterfall!$B$5,0,IFERROR($B$2/IF($B$3="Class A",Waterfall!$B$9,Waterfall!$B$10),0)*IF($B$3="Class A",Waterfall!C55,Waterfall!C56)) -> 0 | D14: =IF(3>Waterfall!$B$5,0,IFERROR($B$2/IF($B$3="Class A",Waterfall!$B$9,Waterfall!$B$10),0)*IF($B$3="Class A",Waterfall!D55,Waterfall!D56)) -> 0 | E14: =IF(4>Waterfall!$B$5,0,IFERROR($B$2/IF($B$3="Class A",Waterfall!$B$9,Waterfall!$B$10),0)*IF($B$3="Class A",Waterfall!E55,Waterfall!E56)) -> 0 | F14: =IF(5>Waterfall!$B$5,0,IFERROR($B$2/IF($B$3="Class A",Waterfall!$B$9,Waterfall!$B$10),0)*IF($B$3="Class A",Waterfall!F55,Waterfall!F56)) -> 0 | G14: =IF(6>Waterfall!$B$5,0,IFERROR($B$2/IF($B$3="Class A",Waterfall!$B$9,Waterfall!$B$10),0)*IF($B$3="Class A",Waterfall!G55,Waterfall!G56)) -> 0 | H14: =IF(7>Waterfall!$B$5,0,IFERROR($B$2/IF($B$3="Class A",Waterfall!$B$9,Waterfall!$B$10),0)*IF($B$3="Class A",Waterfall!H55,Waterfall!H56)) -> 0 | I14: =IF(8>Waterfall!$B$5,0,IFERROR($B$2/IF($B$3="Class A",Waterfall!$B$9,Waterfall!$B$10),0)*IF($B$3="Class A",Waterfall!I55,Waterfall!I56)) -> 0 | J14: =IF(9>Waterfall!$B$5,0,IFERROR($B$2/IF($B$3="Class A",Waterfall!$B$9,Waterfall!$B$10),0)*IF($B$3="Class A",Waterfall!J55,Waterfall!J56)) -> 0 | K14: =IF(10>Waterfall!$B$5,0,IFERROR($B$2/IF($B$3="Class A",Waterfall!$B$9,Waterfall!$B$10),0)*IF($B$3="Class A",Waterfall!K55,Waterfall!K56)) -> 0 | L14: =SUM(B14:K14) -> 0 | M14: =SUM(B14:K14) -> 0
A15: Cash on Cash Return | B15: =IF(1>Waterfall!$B$5,0,IFERROR(B14/$B$2,0)) -> 0 | C15: =IF(2>Waterfall!$B$5,0,IFERROR(C14/$B$2,0)) -> 0 | D15: =IF(3>Waterfall!$B$5,0,IFERROR(D14/$B$2,0)) -> 0 | E15: =IF(4>Waterfall!$B$5,0,IFERROR(E14/$B$2,0)) -> 0 | F15: =IF(5>Waterfall!$B$5,0,IFERROR(F14/$B$2,0)) -> 0 | G15: =IF(6>Waterfall!$B$5,0,IFERROR(G14/$B$2,0)) -> 0 | H15: =IF(7>Waterfall!$B$5,0,IFERROR(H14/$B$2,0)) -> 0 | I15: =IF(8>Waterfall!$B$5,0,IFERROR(I14/$B$2,0)) -> 0 | J15: =IF(9>Waterfall!$B$5,0,IFERROR(J14/$B$2,0)) -> 0 | K15: =IF(10>Waterfall!$B$5,0,IFERROR(K14/$B$2,0)) -> 0
A16: Average Cash on Cash Return to Date | B16: =IF(1>Waterfall!$B$5,0,IFERROR(SUM($B$14:B14)/(1*$B$2),0)) -> 0 | C16: =IF(2>Waterfall!$B$5,0,IFERROR(SUM($B$14:C14)/(2*$B$2),0)) -> 0 | D16: =IF(3>Waterfall!$B$5,0,IFERROR(SUM($B$14:D14)/(3*$B$2),0)) -> 0 | E16: =IF(4>Waterfall!$B$5,0,IFERROR(SUM($B$14:E14)/(4*$B$2),0)) -> 0 | F16: =IF(5>Waterfall!$B$5,0,IFERROR(SUM($B$14:F14)/(5*$B$2),0)) -> 0 | G16: =IF(6>Waterfall!$B$5,0,IFERROR(SUM($B$14:G14)/(6*$B$2),0)) -> 0 | H16: =IF(7>Waterfall!$B$5,0,IFERROR(SUM($B$14:H14)/(7*$B$2),0)) -> 0 | I16: =IF(8>Waterfall!$B$5,0,IFERROR(SUM($B$14:I14)/(8*$B$2),0)) -> 0 | J16: =IF(9>Waterfall!$B$5,0,IFERROR(SUM($B$14:J14)/(9*$B$2),0)) -> 0 | K16: =IF(10>Waterfall!$B$5,0,IFERROR(SUM($B$14:K14)/(10*$B$2),0)) -> 0
A17: D. CAPITAL EVENTS
