Workbook
Name EGI: Scenarios!$F$50
Name StdBuckets: _StdCOA!$A$4:$A$56
Name Total_Payroll: Payroll!$F$25
Name Units: Scenarios!$B$8

Sheet Cover
A1: =IF('Prop Info'!B4="","MULTIFAMILY — INVESTMENT SUMMARY","MULTIFAMILY — INVESTMENT SUMMARY"&" — "&'Prop Info'!B4) -> MULTIFAMILY — INVESTMENT SUMMARY
A2: Confidential — For Authorized Recipients Only
A4: PROPERTY INFORMATION
A5: Property Name | B5: ='Prop Info'!B4 -> 0
A6: Location | B6: ='Prop Info'!B5 -> 0
A7: Year Built | B7: ='Prop Info'!B9 -> 0
A8: Total Units | B8: =Scenarios!F8 -> 0
A9: Gross Sq Ft | B9: ='Prop Info'!B11 -> 0
A10: Asset Class (A/B/C) | B10: ='Prop Info'!B13 -> 0
A11: Active Scenario | B11: =Scenarios!B2 -> 1. T-12 Actuals
A12: Avg Monthly Rent / Unit | B12: =Scenarios!F39 -> 0
A13: KEY DEAL METRICS
A14: Metric | B14: Value | C14: / Beds | D14: Returns Metric | E14: Value
A15: Purchase Price | B15: =Scenarios!F7 -> 0 | D15: LP IRR | E15: =Waterfall!B66 -> 0
A16: Price Per Unit | B16: =Scenarios!F9 -> 0 | C16: =IFERROR(Scenarios!F7/'Prop Info'!$B$6,0) -> 0 | D16: GP IRR | E16: =Waterfall!E66 -> 0
A17: Total Acquisition Cost | B17: =IFERROR(Scenarios!F17,0) -> 0 | D17: LP Equity Multiple | E17: =Waterfall!B64 -> 0
A18: Loan Amount (Total) | B18: =Scenarios!F117 -> 0 | D18: Y1 Cash-on-Cash | E18: ='P&L'!D68
A19: LTV | B19: =IFERROR(Scenarios!F117/Scenarios!F7,0) -> 0 | D19: Year 5 NOI | E19: ='P&L'!H40
A20: LTC | B20: =IFERROR(Scenarios!F117/Scenarios!F17,0) -> 0 | D20: Exit Year | E20: =Scenarios!F82 -> 0
A21: Equity Required | B21: =Scenarios!F31 -> 0 | D21: Exit Cap Rate | E21: =Waterfall!B6 -> 0
A22: Down Payment % | B22: =Scenarios!F10 -> 0.2 | D22: Gross Sale Price | E22: =Waterfall!B32 -> 0
A23: Entry Cap Rate | B23: =IFERROR('P&L'!D40/Scenarios!F7,0) -> 0 | D23: Net to Equity (Exit) | E23: =Waterfall!B35 -> 0
A24: Stabilized Cap Rate (Y5) | B24: =IFERROR('P&L'!H40/Scenarios!F7,0) -> 0 | D24: Avg Annual Return (LP) | E24: =IFERROR((Waterfall!M54-(Waterfall!B9+Waterfall!B10))/(Waterfall!B9+Waterfall!B10)/Scenarios!F82,0) -> 0
A26: CAPITAL STACK
A27: Tranche | B27: Amount | C27: % | D27: Rate | E27: Term (yrs) | F27: Amort (yrs)
A28: Senior Loan (1st) | B28: =Scenarios!F88 -> 0 | C28: =IFERROR(Scenarios!F88/Scenarios!F17,0) -> 0 | D28: =Scenarios!F89 -> 0 | E28: =Scenarios!F91 -> 0 | F28: =Scenarios!F90 -> 0
A29: 2nd Loan | B29: =Scenarios!F95 -> 0 | C29: =IFERROR(Scenarios!F95/Scenarios!F17,0) -> 0 | D29: =Scenarios!F96 -> 0 | E29: =Scenarios!F98 -> 0 | F29: =Scenarios!F97 -> 0
A30: Supplemental | B30: =Scenarios!F102 -> 0 | C30: =IFERROR(Scenarios!F102/Scenarios!F17,0) -> 0 | D30: =Scenarios!F103 -> 0 | E30: =Scenarios!F105 -> 0 | F30: =Scenarios!F104 -> 0
A31: GP Equity | B31: =Scenarios!F32 -> 0 | C31: =Scenarios!F28 -> 0.3 | D31: — | E31: — | F31: —
A32: Class A LP Equity | B32: =Scenarios!F33 -> 0 | C32: =Scenarios!F29 -> 0.7 | D32: =Scenarios!F35 -> 0 | E32: — | F32: —
A33: Class B LP Equity | B33: =Scenarios!F34 -> 0 | C33: =Scenarios!F30 -> 0 | D33: — | E33: — | F33: —
A34: TOTAL | B34: =Scenarios!F31 -> 0 | C34: =IFERROR(Scenarios!F31/Scenarios!F17,0) -> 0 | D34: — | E34: — | F34: —
A36: INVESTOR RETURNS SUMMARY
A37: Metric | B37: Class A LP | C37: Class B LP | D37: LP Combined | E37: GP | F37: Notes
A38: Total Equity Invested | B38: =Waterfall!B9 -> 0 | C38: =Waterfall!B10 -> 0 | D38: =Waterfall!B9+Waterfall!B10 -> 0 | E38: =Waterfall!B8 -> 0 | F38: Capital contributed by each party
A39: Total Distributions | B39: =Waterfall!M52 -> 0 | C39: =Waterfall!M53 -> 0 | D39: =Waterfall!M54 -> 0 | E39: =Waterfall!M55 -> 0 | F39: Operating CF + exit proceeds
A40: Net Profit | B40: =Waterfall!M52-Waterfall!B9 -> 0 | C40: =IFERROR(Waterfall!M53-Waterfall!B10,0) -> 0 | D40: =Waterfall!M54-(Waterfall!B9+Waterfall!B10) -> 0 | E40: =Waterfall!M55-Waterfall!B8 -> 0
A41: Equity Multiple (EM) | B41: =IFERROR(Waterfall!B64,0) -> 0 | C41: =IFERROR(Waterfall!C64,0) -> 0 | D41: =IFERROR(Waterfall!D64,0) -> 0 | E41: =IFERROR(Waterfall!E64,0) -> 0 | F41: Total value returned / capital in
A42: IRR | B42: =Waterfall!B66 -> 0 | C42: =Waterfall!C66 -> 0 | D42: =Waterfall!D66 -> 0 | E42: =Waterfall!E66 -> 0 | F42: Includes exit proceeds
A43: Avg Annual Return (simple, incl. exit) | B43: =IFERROR((Waterfall!M52-Waterfall!B9)/Waterfall!B9/Scenarios!F82,0) -> 0 | C43: =IFERROR((Waterfall!M53-Waterfall!B10)/Waterfall!B10/Scenarios!F82,0) -> 0 | D43: =IFERROR((Waterfall!M54-(Waterfall!B9+Waterfall!B10))/(Waterfall!B9+Waterfall!B10)/Scenarios!F82,0) -> 0 | E43: =IFERROR(IF(Waterfall!B8=0,"N/A",(Waterfall!M55-Waterfall!B8)/Waterfall!B8/Scenarios!F82),0) -> N/A | F43: Simple: (total distributions − equity) ÷ equity ÷ hold yrs. Not compounded.
A44: EXIT & DEAL METRICS
A45: Hold Period (yrs) | B45: =Scenarios!F82 -> 0
A46: Exit Cap Rate | B46: =Waterfall!B6 -> 0
A47: Exit Year NOI | B47: ='P&L'!H40 | F47: Y5 NOI
A48: Gross Sale Price | B48: =Waterfall!B32 -> 0 | F48: NOI ÷ exit cap
A49: Less: Loan Payoff | B49: =Waterfall!B34 -> 0 | F49: Amortized balance
A50: Net Sale Proceeds | B50: =Waterfall!B35 -> 0 | F50: After selling costs & loan
A52: Version: | B52: v16
A53: Last Updated: | B53: 2026-06-12 — 3-tier IRR-hurdle waterfall engine; reserve tracker; pref shortfall tracking
A54: NAVIGATION & LEGEND | D54: TAB NAVIGATION
A55: Color Legend: | D55: =HYPERLINK("#Inputs!A1","Inputs") -> Inputs | E55: =HYPERLINK("#Loans!A1","Loans") -> Loans
A56: Blue | B56: Hardcoded input — type here | D56: =HYPERLINK("#'Prop Info'!A1","Prop Info") -> Prop Info | E56: =HYPERLINK("#'Acquisition Costs'!A1","Acquisition Costs") -> Acquisition Costs
A57: Black | B57: Same-sheet formula — do not edit | D57: =HYPERLINK("#'Data Refresh'!A1","Data Refresh") -> Data Refresh | E57: =HYPERLINK("#'Rental Comps'!A1","Rental Comps") -> Rental Comps
A58: Green | B58: Cross-sheet link — do not edit | D58: =HYPERLINK("#'Data Checklist'!A1","Data Checklist") -> Data Checklist | E58: =HYPERLINK("#Capex!A1","Capex") -> Capex
A59: Red | B59: External file link — do not edit | D59: =HYPERLINK("#Scenarios!A1","Scenarios") -> Scenarios | E59: =HYPERLINK("#'Staffing Matrix'!A1","Staffing Matrix") -> Staffing Matrix
D60: =HYPERLINK("#'T-12 Analysis'!A1","T-12 Analysis") -> T-12 Analysis | E60: =HYPERLINK("#Waterfall!A1","Waterfall") -> Waterfall
D61: =HYPERLINK("#'Recapture & Upside'!A1","Recapture & Upside") -> Recapture & Upside | E61: =HYPERLINK("#'Exit Strategy'!A1","Exit Strategy") -> Exit Strategy
D62: =HYPERLINK("#'Rent Roll Analysis'!A1","Rent Roll Analysis") -> Rent Roll Analysis | E62: =HYPERLINK("#Sensitivity!A1","Sensitivity") -> Sensitivity
D63: =HYPERLINK("#'P&L'!A1","P&L") -> P&L | E63: =HYPERLINK("#'LP Return Illustration'!A1","LP Return Illustration") -> LP Return Illustration
D64: =HYPERLINK("#'Lease-Up & Capital Call'!A1","Lease-Up & Capital Call") -> Lease-Up & Capital Call | E64: =HYPERLINK("#'Portfolio Rollup'!A1","Portfolio Rollup") -> Portfolio Rollup

Sheet Dashboard
B1: =IF('Prop Info'!B4=0,"Property",'Prop Info'!B4)&" — Underwriting" -> Property — Underwriting | R1: DASHBOARD CALC ENGINE (helper — unlevered returns / NPV)
B2: =IF('Prop Info'!B6=0,"",TEXT('Prop Info'!B6,"#,##0")&" Units")&IF('Prop Info'!B5=0,""," · "&'Prop Info'!B5) | R2: Discount Rate (NPV) | S2: 0.08
B3: $, unless noted otherwise | R3: Hold Period (yrs) | S3: =IF(Scenarios!F82=0,5,Scenarios!F82) -> 5
R4: Exit Cap Rate | S4: =IF(Scenarios!F83=0,0.0725,Scenarios!F83) -> 0.0725
B5: Property Overview | H5: Sources and Uses of Capital | R5: Sale Cost % | S5: =IFERROR(ABS('Exit Strategy'!G10)/'Exit Strategy'!G9,0.02) -> 0.02
B6: Property Name | D6: =IF('Prop Info'!B4=0,"",'Prop Info'!B4) | H6: Sources of Capital | J6: Assumption | L6: % | M6: $ | N6: $ / RSF | O6: $ / Unit | R6: Total Cost (basis) | S6: =Scenarios!F17 -> 0
B7: Address | D7: =IF('Prop Info'!B5=0,"",'Prop Info'!B5) | H7: Total Debt | L7: =IFERROR(M7/$M$11,0) -> 0 | M7: =Scenarios!F23 -> 0 | N7: =IFERROR(M7/'Prop Info'!$B$15,0) -> 0 | O7: =IFERROR(M7/'Prop Info'!$B$6,0) -> 0 | R7: Total Equity | S7: =Scenarios!F31 -> 0
B8: City / Market | D8: =IF('Prop Info'!B20=0,"",'Prop Info'!B20) | H8: LP Equity | L8: =IFERROR(M8/$M$11,0) -> 0 | M8: =Scenarios!F33+Scenarios!F34 -> 0 | N8: =IFERROR(M8/'Prop Info'!$B$15,0) -> 0 | O8: =IFERROR(M8/'Prop Info'!$B$6,0) -> 0 | R8: Forward NOI (exit+1) | S8: {=IFERROR(INDEX('P&L'!$D$40:$M$40,1,$S$3+1),0)}
B9: Submarket / MSA | D9: =IF('Prop Info'!B21=0,"",'Prop Info'!B21) | H9: GP Equity | L9: =IFERROR(M9/$M$11,0) -> 0 | M9: =Scenarios!F32 -> 0 | N9: =IFERROR(M9/'Prop Info'!$B$15,0) -> 0 | O9: =IFERROR(M9/'Prop Info'!$B$6,0) -> 0 | R9: Unlev Net Sale | S9: =IFERROR($S$8/$S$4*(1-$S$5),0) -> 0
B10: Building Class | D10: =IF('Prop Info'!B13=0,"",'Prop Info'!B13) | H10: Total Equity | L10: =IFERROR(M10/$M$11,0) -> 0 | M10: =Scenarios!F31 -> 0 | N10: =IFERROR(M10/'Prop Info'!$B$15,0) -> 0 | O10: =IFERROR(M10/'Prop Info'!$B$6,0) -> 0
B11: Amenity Tier | D11: =IF('Prop Info'!B14=0,"",'Prop Info'!B14) | H11: Total Sources of Capital | L11: =IFERROR(M11/$M$11,0) -> 0 | M11: =M7+M10 -> 0 | N11: =IFERROR(M11/'Prop Info'!$B$15,0) -> 0 | O11: =IFERROR(M11/'Prop Info'!$B$6,0) -> 0
B12: Year Built | D12: =IF('Prop Info'!B9=0,"",TEXT('Prop Info'!B9,"0")) | R12: Year | S12: 0 | T12: 1 | U12: 2 | V12: 3 | W12: 4 | X12: 5 | Y12: 6 | Z12: 7 | AA12: 8 | AB12: 9 | AC12: 10
B13: Acquisition Date | H13: Uses of Capital | J13: Assumption | L13: % | M13: $ | N13: $ / RSF | O13: $ / Unit | R13: Unlev NOI | S13: 0 | T13: =IF(AND(T$12>=1,T$12<=$S$3),N(INDEX('P&L'!$D$40:$M$40,1,T$12)),0) -> 0 | U13: =IF(AND(U$12>=1,U$12<=$S$3),N(INDEX('P&L'!$D$40:$M$40,1,U$12)),0) -> 0 | V13: =IF(AND(V$12>=1,V$12<=$S$3),N(INDEX('P&L'!$D$40:$M$40,1,V$12)),0) -> 0 | W13: =IF(AND(W$12>=1,W$12<=$S$3),N(INDEX('P&L'!$D$40:$M$40,1,W$12)),0) -> 0 | X13: =IF(AND(X$12>=1,X$12<=$S$3),N(INDEX('P&L'!$D$40:$M$40,1,X$12)),0) -> 0 | Y13: =IF(AND(Y$12>=1,Y$12<=$S$3),N(INDEX('P&L'!$D$40:$M$40,1,Y$12)),0) -> 0 | Z13: =IF(AND(Z$12>=1,Z$12<=$S$3),N(INDEX('P&L'!$D$40:$M$40,1,Z$12)),0) -> 0 | AA13: =IF(AND(AA$12>=1,AA$12<=$S$3),N(INDEX('P&L'!$D$40:$M$40,1,AA$12)),0) -> 0 | ... AC13: =IF(AND(AC$12>=1,AC$12<=$S$3),N(INDEX('P&L'!$D$40:$M$40,1,AC$12)),0) -> 0
H14: Purchase Price | L14: =IFERROR(M14/$M$19,0) -> 0 | M14: =Scenarios!F7 -> 0 | N14: =IFERROR(M14/'Prop Info'!$B$15,0) -> 0 | O14: =IFERROR(M14/'Prop Info'!$B$6,0) -> 0 | R14: Unlev Sale | S14: 0 | T14: =IF(T$12=$S$3,$S$9,0) -> 0 | U14: =IF(U$12=$S$3,$S$9,0) -> 0 | V14: =IF(V$12=$S$3,$S$9,0) -> 0 | W14: =IF(W$12=$S$3,$S$9,0) -> 0 | X14: =IF(X$12=$S$3,$S$9,0) -> 0 | Y14: =IF(Y$12=$S$3,$S$9,0) -> 0 | Z14: =IF(Z$12=$S$3,$S$9,0) -> 0 | AA14: =IF(AA$12=$S$3,$S$9,0) -> 0 | ... AC14: =IF(AC$12=$S$3,$S$9,0) -> 0
B15: Number of Units | D15: ='Prop Info'!B6 -> 0 | H15: Capital Improvements | L15: =IFERROR(M15/$M$19,0) -> 0 | M15: =Scenarios!F12 -> 0 | N15: =IFERROR(M15/'Prop Info'!$B$15,0) -> 0 | O15: =IFERROR(M15/'Prop Info'!$B$6,0) -> 0 | R15: Unlev Total CF | S15: =-$S$6 -> 0 | T15: =N(T13)+N(T14) -> 0 | U15: =N(U13)+N(U14) -> 0 | V15: =N(V13)+N(V14) -> 0 | W15: =N(W13)+N(W14) -> 0 | X15: =N(X13)+N(X14) -> 0 | Y15: =N(Y13)+N(Y14) -> 0 | Z15: =N(Z13)+N(Z14) -> 0 | AA15: =N(AA13)+N(AA14) -> 0 | ... AC15: =N(AC13)+N(AC14) -> 0
B16: Number of Buildings | D16: ='Prop Info'!B7 -> 0 | H16: Closing & Legal | J16: =IF(Scenarios!F7=0,"",TEXT(M16/M14,"0.0%")&" of Purchase Price") | L16: =IFERROR(M16/$M$19,0) -> 0 | M16: =Scenarios!F14 -> 0 | N16: =IFERROR(M16/'Prop Info'!$B$15,0) -> 0 | O16: =IFERROR(M16/'Prop Info'!$B$6,0) -> 0 | R16: Lev Op CF | S16: =-$S$7 -> 0 | T16: =IF(AND(T$12>=1,T$12<=$S$3),N(INDEX('P&L'!$D$48:$M$48,1,T$12)),0) -> 0 | U16: =IF(AND(U$12>=1,U$12<=$S$3),N(INDEX('P&L'!$D$48:$M$48,1,U$12)),0) -> 0 | V16: =IF(AND(V$12>=1,V$12<=$S$3),N(INDEX('P&L'!$D$48:$M$48,1,V$12)),0) -> 0 | W16: =IF(AND(W$12>=1,W$12<=$S$3),N(INDEX('P&L'!$D$48:$M$48,1,W$12)),0) -> 0 | X16: =IF(AND(X$12>=1,X$12<=$S$3),N(INDEX('P&L'!$D$48:$M$48,1,X$12)),0) -> 0 | Y16: =IF(AND(Y$12>=1,Y$12<=$S$3),N(INDEX('P&L'!$D$48:$M$48,1,Y$12)),0) -> 0 | Z16: =IF(AND(Z$12>=1,Z$12<=$S$3),N(INDEX('P&L'!$D$48:$M$48,1,Z$12)),0) -> 0 | AA16: =IF(AND(AA$12>=1,AA$12<=$S$3),N(INDEX('P&L'!$D$48:$M$48,1,AA$12)),0) -> 0 | ... AC16: =IF(AND(AC$12>=1,AC$12<=$S$3),N(INDEX('P&L'!$D$48:$M$48,1,AC$12)),0) -> 0
B17: Total Rentable SF | D17: ='Prop Info'!B15 -> 0 | H17: Acquisition Fee | J17: =IF(Scenarios!F7=0,"",TEXT(M17/M14,"0.0%")&" of Purchase Price") | L17: =IFERROR(M17/$M$19,0) -> 0 | M17: =Scenarios!F16 -> 0 | N17: =IFERROR(M17/'Prop Info'!$B$15,0) -> 0 | O17: =IFERROR(M17/'Prop Info'!$B$6,0) -> 0 | R17: Lev Total CF | S17: =-$S$7 -> 0 | T17: =N(T16)+IF(T$12=$S$3,N(Waterfall!$B$35),0) -> 0 | U17: =N(U16)+IF(U$12=$S$3,N(Waterfall!$B$35),0) -> 0 | V17: =N(V16)+IF(V$12=$S$3,N(Waterfall!$B$35),0) -> 0 | W17: =N(W16)+IF(W$12=$S$3,N(Waterfall!$B$35),0) -> 0 | X17: =N(X16)+IF(X$12=$S$3,N(Waterfall!$B$35),0) -> 0 | Y17: =N(Y16)+IF(Y$12=$S$3,N(Waterfall!$B$35),0) -> 0 | Z17: =N(Z16)+IF(Z$12=$S$3,N(Waterfall!$B$35),0) -> 0 | AA17: =N(AA16)+IF(AA$12=$S$3,N(Waterfall!$B$35),0) -> 0 | ... AC17: =N(AC16)+IF(AC$12=$S$3,N(Waterfall!$B$35),0) -> 0
B18: Average RSF | D18: =IFERROR('Prop Info'!B15/'Prop Info'!B6,0) -> 0 | H18: Operating Reserves | L18: =IFERROR(M18/$M$19,0) -> 0 | M18: =Scenarios!F13 -> 0 | N18: =IFERROR(M18/'Prop Info'!$B$15,0) -> 0 | O18: =IFERROR(M18/'Prop Info'!$B$6,0) -> 0
B19: Land Area | D19: ='Prop Info'!B10 -> 0 | H19: Total Uses of Capital | L19: =IFERROR(M19/$M$19,0) -> 0 | M19: =SUM(M14:M18) -> 0 | N19: =IFERROR(M19/'Prop Info'!$B$15,0) -> 0 | O19: =IFERROR(M19/'Prop Info'!$B$6,0) -> 0 | R19: Unlev IRR | S19: =IFERROR(IRR(S15:AC15),0) -> 0
B20: Units / Acre | D20: =IFERROR('Prop Info'!B6/'Prop Info'!B10,0) -> 0 | R20: Unlev MOIC | S20: =IFERROR(SUM(T15:AC15)/$S$6,0) -> 0
B21: Parking Spaces | D21: ='Prop Info'!B12 -> 0 | R21: Unlev Profit | S21: =SUM(S15:AC15) -> 0
B22: Parking Ratio (Spaces / 1K SF) | D22: =IFERROR('Prop Info'!B12/('Prop Info'!B15/1000),0) -> 0 | H22: Unit Mix and Pro Forma Rents | R22: Unlev Equity | S22: =$S$6 -> 0
H23: Unit Type | I23: % Reno | J23: Units | K23: Avg RSF | L23: In-Place $/U | M23: $/RSF | N23: Rent Prem. | O23: Post-Reno $/U | R23: Unlev Avg Yield | S23: =IFERROR(SUM(T13:AC13)/$S$3/$S$6,0) -> 0
B24: Returns Summary | H24: {=IFERROR(INDEX(_xlfn.UNIQUE(_xlfn._xlws.FILTER('Rent Roll Analysis'!$C$273:$C$1772,'Rent Roll Analysis'!$C$273:$C$1772<>"")),ROW()-23),"")} | J24: =IF($H24="","",COUNTIF('Rent Roll Analysis'!$C$273:$C$1772,$H24)) | K24: =IF($H24="","",IFERROR(AVERAGEIF('Rent Roll Analysis'!$C$273:$C$1772,$H24,'Rent Roll Analysis'!$D$273:$D$1772),0)) | L24: =IF($H24="","",IFERROR(AVERAGEIF('Rent Roll Analysis'!$C$273:$C$1772,$H24,'Rent Roll Analysis'!$N$273:$N$1772),0)) | M24: =IFERROR(L24/K24,0) -> 0 | O24: =IF($H24="","",N(L24)+N(N24))
D25: Unlevered | E25: Levered (LP) | H25: {=IFERROR(INDEX(_xlfn.UNIQUE(_xlfn._xlws.FILTER('Rent Roll Analysis'!$C$273:$C$1772,'Rent Roll Analysis'!$C$273:$C$1772<>"")),ROW()-23),"")} | J25: =IF($H25="","",COUNTIF('Rent Roll Analysis'!$C$273:$C$1772,$H25)) | K25: =IF($H25="","",IFERROR(AVERAGEIF('Rent Roll Analysis'!$C$273:$C$1772,$H25,'Rent Roll Analysis'!$D$273:$D$1772),0)) | L25: =IF($H25="","",IFERROR(AVERAGEIF('Rent Roll Analysis'!$C$273:$C$1772,$H25,'Rent Roll Analysis'!$N$273:$N$1772),0)) | M25: =IFERROR(L25/K25,0) -> 0 | O25: =IF($H25="","",N(L25)+N(N25)) | R25: Lev Avg Yield | S25: =IFERROR(SUM(T16:AC16)/$S$3/$S$7,0) -> 0
B26: IRR | D26: =S19 -> 0 | E26: =IFERROR(N(Waterfall!D66),0) -> 0 | H26: {=IFERROR(INDEX(_xlfn.UNIQUE(_xlfn._xlws.FILTER('Rent Roll Analysis'!$C$273:$C$1772,'Rent Roll Analysis'!$C$273:$C$1772<>"")),ROW()-23),"")} | J26: =IF($H26="","",COUNTIF('Rent Roll Analysis'!$C$273:$C$1772,$H26)) | K26: =IF($H26="","",IFERROR(AVERAGEIF('Rent Roll Analysis'!$C$273:$C$1772,$H26,'Rent Roll Analysis'!$D$273:$D$1772),0)) | L26: =IF($H26="","",IFERROR(AVERAGEIF('Rent Roll Analysis'!$C$273:$C$1772,$H26,'Rent Roll Analysis'!$N$273:$N$1772),0)) | M26: =IFERROR(L26/K26,0) -> 0 | O26: =IF($H26="","",N(L26)+N(N26))
B27: MOIC | D27: =S20 -> 0 | E27: =IFERROR(N(Waterfall!D64),0) -> 0 | H27: {=IFERROR(INDEX(_xlfn.UNIQUE(_xlfn._xlws.FILTER('Rent Roll Analysis'!$C$273:$C$1772,'Rent Roll Analysis'!$C$273:$C$1772<>"")),ROW()-23),"")} | J27: =IF($H27="","",COUNTIF('Rent Roll Analysis'!$C$273:$C$1772,$H27)) | K27: =IF($H27="","",IFERROR(AVERAGEIF('Rent Roll Analysis'!$C$273:$C$1772,$H27,'Rent Roll Analysis'!$D$273:$D$1772),0)) | L27: =IF($H27="","",IFERROR(AVERAGEIF('Rent Roll Analysis'!$C$273:$C$1772,$H27,'Rent Roll Analysis'!$N$273:$N$1772),0)) | M27: =IFERROR(L27/K27,0) -> 0 | O27: =IF($H27="","",N(L27)+N(N27)) | R27: Current Value (NPV) | S27: =NPV($S$2,T15:AC15) -> 0
B28: Profit | D28: =S21 -> 0 | E28: =IFERROR(N(Waterfall!D65),0) -> 0 | H28: {=IFERROR(INDEX(_xlfn.UNIQUE(_xlfn._xlws.FILTER('Rent Roll Analysis'!$C$273:$C$1772,'Rent Roll Analysis'!$C$273:$C$1772<>"")),ROW()-23),"")} | J28: =IF($H28="","",COUNTIF('Rent Roll Analysis'!$C$273:$C$1772,$H28)) | K28: =IF($H28="","",IFERROR(AVERAGEIF('Rent Roll Analysis'!$C$273:$C$1772,$H28,'Rent Roll Analysis'!$D$273:$D$1772),0)) | L28: =IF($H28="","",IFERROR(AVERAGEIF('Rent Roll Analysis'!$C$273:$C$1772,$H28,'Rent Roll Analysis'!$N$273:$N$1772),0)) | M28: =IFERROR(L28/K28,0) -> 0 | O28: =IF($H28="","",N(L28)+N(N28)) | R28: Implied Cap | S28: =IFERROR(N('P&L'!$D$40)/$S$27,0) -> 0
B29: Equity | D29: =S22 -> 0 | E29: =N(Waterfall!B9)+N(Waterfall!B10) -> 0 | H29: {=IFERROR(INDEX(_xlfn.UNIQUE(_xlfn._xlws.FILTER('Rent Roll Analysis'!$C$273:$C$1772,'Rent Roll Analysis'!$C$273:$C$1772<>"")),ROW()-23),"")} | J29: =IF($H29="","",COUNTIF('Rent Roll Analysis'!$C$273:$C$1772,$H29)) | K29: =IF($H29="","",IFERROR(AVERAGEIF('Rent Roll Analysis'!$C$273:$C$1772,$H29,'Rent Roll Analysis'!$D$273:$D$1772),0)) | L29: =IF($H29="","",IFERROR(AVERAGEIF('Rent Roll Analysis'!$C$273:$C$1772,$H29,'Rent Roll Analysis'!$N$273:$N$1772),0)) | M29: =IFERROR(L29/K29,0) -> 0 | O29: =IF($H29="","",N(L29)+N(N29)) | R29: Yr 1 NOI | S29: =N('P&L'!$D$40) -> 0
B30: Average Yield | D30: =S23 -> 0 | E30: =S25 -> 0 | H30: Total / Weighted Avg | I30: =IFERROR(SUMPRODUCT(I24:I29,J24:J29)/SUM(J24:J29),0) -> 0 | J30: =SUM(J24:J29) -> 0 | K30: =IFERROR(SUMPRODUCT(K24:K29,J24:J29)/J30,0) -> 0 | L30: =IFERROR(SUMPRODUCT(L24:L29,J24:J29)/J30,0) -> 0 | M30: =IFERROR(L30/K30,0) -> 0 | N30: =IFERROR(SUMPRODUCT(N24:N29,J24:J29)/J30,0) -> 0 | O30: =N(L30)+N(N30) -> 0
R31: SENS ENGINE (Levered approx: IRR=MOIC^(1/yr)-1)
B32: NPV Reversion | H32: Pro Forma Assumptions
B33: Discount Rate | D33: =S2 -> 0.08 | E33: Current Value | F33: =S27 -> 0 | J33: Yr. 1 | K33: Yr. 2 | L33: Yr. 3 | M33: Yr. 4 | N33: Yr. 5 | O33: Yr. 6 + | S33: =MAX(1,$S$3-1) -> 4 | T33: =$S$3 -> 5 | U33: =$S$3+1 -> 6 | W33: =S33 -> 4 | X33: =T33 -> 5 | Y33: =U33 -> 6
B34: Per Unit | D34: =IFERROR(S27/'Prop Info'!$B$6,0) -> 0 | E34: Per RSF | F34: =IFERROR(S27/'Prop Info'!$B$15,0) -> 0 | H34: Growth Rates | R34: =$S$4-0.005 -> 0.0675 | S34: =IFERROR(((N(INDEX('P&L'!$D$40:$M$40,1,S$33+1))/$R34*(1-$S$5)-N(Scenarios!$F$116)+SUM(INDEX($T$16:$AC$16,1,1):INDEX($T$16:$AC$16,1,S$33)))/$S$7)^(1/S$33)-1,0) -> 0 | T34: =IFERROR(((N(INDEX('P&L'!$D$40:$M$40,1,T$33+1))/$R34*(1-$S$5)-N(Scenarios!$F$116)+SUM(INDEX($T$16:$AC$16,1,1):INDEX($T$16:$AC$16,1,T$33)))/$S$7)^(1/T$33)-1,0) -> 0 | U34: =IFERROR(((N(INDEX('P&L'!$D$40:$M$40,1,U$33+1))/$R34*(1-$S$5)-N(Scenarios!$F$116)+SUM(INDEX($T$16:$AC$16,1,1):INDEX($T$16:$AC$16,1,U$33)))/$S$7)^(1/U$33)-1,0) -> 0 | V34: =R34 -> 0.0675 | W34: =IFERROR((N(INDEX('P&L'!$D$40:$M$40,1,W$33+1))/$V34*(1-$S$5)-N(Scenarios!$F$116)+SUM(INDEX($T$16:$AC$16,1,1):INDEX($T$16:$AC$16,1,W$33)))/$S$7,0) -> 0 | X34: =IFERROR((N(INDEX('P&L'!$D$40:$M$40,1,X$33+1))/$V34*(1-$S$5)-N(Scenarios!$F$116)+SUM(INDEX($T$16:$AC$16,1,1):INDEX($T$16:$AC$16,1,X$33)))/$S$7,0) -> 0 | Y34: =IFERROR((N(INDEX('P&L'!$D$40:$M$40,1,Y$33+1))/$V34*(1-$S$5)-N(Scenarios!$F$116)+SUM(INDEX($T$16:$AC$16,1,1):INDEX($T$16:$AC$16,1,Y$33)))/$S$7,0) -> 0
B35: Yr. 1 NOI | D35: =S29 -> 0 | E35: Imp. Cap Rate | F35: =S28 -> 0 | H35: Current Rent | J35: =IFERROR(N('P&L'!D10)/N('P&L'!C10)-1,0) -> 0 | K35: =IFERROR(N('P&L'!E10)/N('P&L'!D10)-1,0) -> 0 | L35: =IFERROR(N('P&L'!F10)/N('P&L'!E10)-1,0) -> 0 | M35: =IFERROR(N('P&L'!G10)/N('P&L'!F10)-1,0) -> 0 | N35: =IFERROR(N('P&L'!H10)/N('P&L'!G10)-1,0) -> 0 | O35: =IFERROR(N('P&L'!I10)/N('P&L'!H10)-1,0) -> 0 | R35: =$S$4-0.0025 -> 0.07 | S35: =IFERROR(((N(INDEX('P&L'!$D$40:$M$40,1,S$33+1))/$R35*(1-$S$5)-N(Scenarios!$F$116)+SUM(INDEX($T$16:$AC$16,1,1):INDEX($T$16:$AC$16,1,S$33)))/$S$7)^(1/S$33)-1,0) -> 0 | T35: =IFERROR(((N(INDEX('P&L'!$D$40:$M$40,1,T$33+1))/$R35*(1-$S$5)-N(Scenarios!$F$116)+SUM(INDEX($T$16:$AC$16,1,1):INDEX($T$16:$AC$16,1,T$33)))/$S$7)^(1/T$33)-1,0) -> 0 | U35: =IFERROR(((N(INDEX('P&L'!$D$40:$M$40,1,U$33+1))/$R35*(1-$S$5)-N(Scenarios!$F$116)+SUM(INDEX($T$16:$AC$16,1,1):INDEX($T$16:$AC$16,1,U$33)))/$S$7)^(1/U$33)-1,0) -> 0 | V35: =R35 -> 0.07 | W35: =IFERROR((N(INDEX('P&L'!$D$40:$M$40,1,W$33+1))/$V35*(1-$S$5)-N(Scenarios!$F$116)+SUM(INDEX($T$16:$AC$16,1,1):INDEX($T$16:$AC$16,1,W$33)))/$S$7,0) -> 0 | X35: =IFERROR((N(INDEX('P&L'!$D$40:$M$40,1,X$33+1))/$V35*(1-$S$5)-N(Scenarios!$F$116)+SUM(INDEX($T$16:$AC$16,1,1):INDEX($T$16:$AC$16,1,X$33)))/$S$7,0) -> 0 | Y35: =IFERROR((N(INDEX('P&L'!$D$40:$M$40,1,Y$33+1))/$V35*(1-$S$5)-N(Scenarios!$F$116)+SUM(INDEX($T$16:$AC$16,1,1):INDEX($T$16:$AC$16,1,Y$33)))/$S$7,0) -> 0
H36: Post-Renovation Rent | J36: =IFERROR(N('P&L'!D10)/N('P&L'!C10)-1,0) -> 0 | K36: =IFERROR(N('P&L'!E10)/N('P&L'!D10)-1,0) -> 0 | L36: =IFERROR(N('P&L'!F10)/N('P&L'!E10)-1,0) -> 0 | M36: =IFERROR(N('P&L'!G10)/N('P&L'!F10)-1,0) -> 0 | N36: =IFERROR(N('P&L'!H10)/N('P&L'!G10)-1,0) -> 0 | O36: =IFERROR(N('P&L'!I10)/N('P&L'!H10)-1,0) -> 0 | R36: =$S$4 -> 0.0725 | S36: =IFERROR(((N(INDEX('P&L'!$D$40:$M$40,1,S$33+1))/$R36*(1-$S$5)-N(Scenarios!$F$116)+SUM(INDEX($T$16:$AC$16,1,1):INDEX($T$16:$AC$16,1,S$33)))/$S$7)^(1/S$33)-1,0) -> 0 | T36: =IFERROR(((N(INDEX('P&L'!$D$40:$M$40,1,T$33+1))/$R36*(1-$S$5)-N(Scenarios!$F$116)+SUM(INDEX($T$16:$AC$16,1,1):INDEX($T$16:$AC$16,1,T$33)))/$S$7)^(1/T$33)-1,0) -> 0 | U36: =IFERROR(((N(INDEX('P&L'!$D$40:$M$40,1,U$33+1))/$R36*(1-$S$5)-N(Scenarios!$F$116)+SUM(INDEX($T$16:$AC$16,1,1):INDEX($T$16:$AC$16,1,U$33)))/$S$7)^(1/U$33)-1,0) -> 0 | V36: =R36 -> 0.0725 | W36: =IFERROR((N(INDEX('P&L'!$D$40:$M$40,1,W$33+1))/$V36*(1-$S$5)-N(Scenarios!$F$116)+SUM(INDEX($T$16:$AC$16,1,1):INDEX($T$16:$AC$16,1,W$33)))/$S$7,0) -> 0 | X36: =IFERROR((N(INDEX('P&L'!$D$40:$M$40,1,X$33+1))/$V36*(1-$S$5)-N(Scenarios!$F$116)+SUM(INDEX($T$16:$AC$16,1,1):INDEX($T$16:$AC$16,1,X$33)))/$S$7,0) -> 0 | Y36: =IFERROR((N(INDEX('P&L'!$D$40:$M$40,1,Y$33+1))/$V36*(1-$S$5)-N(Scenarios!$F$116)+SUM(INDEX($T$16:$AC$16,1,1):INDEX($T$16:$AC$16,1,Y$33)))/$S$7,0) -> 0
H37: Utility & Other Income | J37: =IFERROR(N('P&L'!D18)/N('P&L'!C18)-1,0) -> 0 | K37: =IFERROR(N('P&L'!E18)/N('P&L'!D18)-1,0) -> 0 | L37: =IFERROR(N('P&L'!F18)/N('P&L'!E18)-1,0) -> 0 | M37: =IFERROR(N('P&L'!G18)/N('P&L'!F18)-1,0) -> 0 | N37: =IFERROR(N('P&L'!H18)/N('P&L'!G18)-1,0) -> 0 | O37: =IFERROR(N('P&L'!I18)/N('P&L'!H18)-1,0) -> 0 | R37: =$S$4+0.0025 -> 0.075 | S37: =IFERROR(((N(INDEX('P&L'!$D$40:$M$40,1,S$33+1))/$R37*(1-$S$5)-N(Scenarios!$F$116)+SUM(INDEX($T$16:$AC$16,1,1):INDEX($T$16:$AC$16,1,S$33)))/$S$7)^(1/S$33)-1,0) -> 0 | T37: =IFERROR(((N(INDEX('P&L'!$D$40:$M$40,1,T$33+1))/$R37*(1-$S$5)-N(Scenarios!$F$116)+SUM(INDEX($T$16:$AC$16,1,1):INDEX($T$16:$AC$16,1,T$33)))/$S$7)^(1/T$33)-1,0) -> 0 | U37: =IFERROR(((N(INDEX('P&L'!$D$40:$M$40,1,U$33+1))/$R37*(1-$S$5)-N(Scenarios!$F$116)+SUM(INDEX($T$16:$AC$16,1,1):INDEX($T$16:$AC$16,1,U$33)))/$S$7)^(1/U$33)-1,0) -> 0 | V37: =R37 -> 0.075 | W37: =IFERROR((N(INDEX('P&L'!$D$40:$M$40,1,W$33+1))/$V37*(1-$S$5)-N(Scenarios!$F$116)+SUM(INDEX($T$16:$AC$16,1,1):INDEX($T$16:$AC$16,1,W$33)))/$S$7,0) -> 0 | X37: =IFERROR((N(INDEX('P&L'!$D$40:$M$40,1,X$33+1))/$V37*(1-$S$5)-N(Scenarios!$F$116)+SUM(INDEX($T$16:$AC$16,1,1):INDEX($T$16:$AC$16,1,X$33)))/$S$7,0) -> 0 | Y37: =IFERROR((N(INDEX('P&L'!$D$40:$M$40,1,Y$33+1))/$V37*(1-$S$5)-N(Scenarios!$F$116)+SUM(INDEX($T$16:$AC$16,1,1):INDEX($T$16:$AC$16,1,Y$33)))/$S$7,0) -> 0
B38: Exit Assumptions | H38: General OpEx | J38: =IFERROR((N('P&L'!D38)-N('P&L'!D28))/(N('P&L'!C38)-N('P&L'!C28))-1,0) -> 0 | K38: =IFERROR((N('P&L'!E38)-N('P&L'!E28))/(N('P&L'!D38)-N('P&L'!D28))-1,0) -> 0 | L38: =IFERROR((N('P&L'!F38)-N('P&L'!F28))/(N('P&L'!E38)-N('P&L'!E28))-1,0) -> 0 | M38: =IFERROR((N('P&L'!G38)-N('P&L'!G28))/(N('P&L'!F38)-N('P&L'!F28))-1,0) -> 0 | N38: =IFERROR((N('P&L'!H38)-N('P&L'!H28))/(N('P&L'!G38)-N('P&L'!G28))-1,0) -> 0 | O38: =IFERROR((N('P&L'!I38)-N('P&L'!I28))/(N('P&L'!H38)-N('P&L'!H28))-1,0) -> 0 | R38: =$S$4+0.005 -> 0.0775 | S38: =IFERROR(((N(INDEX('P&L'!$D$40:$M$40,1,S$33+1))/$R38*(1-$S$5)-N(Scenarios!$F$116)+SUM(INDEX($T$16:$AC$16,1,1):INDEX($T$16:$AC$16,1,S$33)))/$S$7)^(1/S$33)-1,0) -> 0 | T38: =IFERROR(((N(INDEX('P&L'!$D$40:$M$40,1,T$33+1))/$R38*(1-$S$5)-N(Scenarios!$F$116)+SUM(INDEX($T$16:$AC$16,1,1):INDEX($T$16:$AC$16,1,T$33)))/$S$7)^(1/T$33)-1,0) -> 0 | U38: =IFERROR(((N(INDEX('P&L'!$D$40:$M$40,1,U$33+1))/$R38*(1-$S$5)-N(Scenarios!$F$116)+SUM(INDEX($T$16:$AC$16,1,1):INDEX($T$16:$AC$16,1,U$33)))/$S$7)^(1/U$33)-1,0) -> 0 | V38: =R38 -> 0.0775 | W38: =IFERROR((N(INDEX('P&L'!$D$40:$M$40,1,W$33+1))/$V38*(1-$S$5)-N(Scenarios!$F$116)+SUM(INDEX($T$16:$AC$16,1,1):INDEX($T$16:$AC$16,1,W$33)))/$S$7,0) -> 0 | X38: =IFERROR((N(INDEX('P&L'!$D$40:$M$40,1,X$33+1))/$V38*(1-$S$5)-N(Scenarios!$F$116)+SUM(INDEX($T$16:$AC$16,1,1):INDEX($T$16:$AC$16,1,X$33)))/$S$7,0) -> 0 | Y38: =IFERROR((N(INDEX('P&L'!$D$40:$M$40,1,Y$33+1))/$V38*(1-$S$5)-N(Scenarios!$F$116)+SUM(INDEX($T$16:$AC$16,1,1):INDEX($T$16:$AC$16,1,Y$33)))/$S$7,0) -> 0
B39: Exit Year | D39: ="Yr. "&TEXT(S3,"0") -> Yr. 5 | E39: Exit Month | F39: ="Mo. "&TEXT(S3*12,"0") -> Mo. 60 | H39: Real Estate Taxes | J39: =IFERROR(N('P&L'!D28)/N('P&L'!C28)-1,0) -> 0 | K39: =IFERROR(N('P&L'!E28)/N('P&L'!D28)-1,0) -> 0 | L39: =IFERROR(N('P&L'!F28)/N('P&L'!E28)-1,0) -> 0 | M39: =IFERROR(N('P&L'!G28)/N('P&L'!F28)-1,0) -> 0 | N39: =IFERROR(N('P&L'!H28)/N('P&L'!G28)-1,0) -> 0 | O39: =IFERROR(N('P&L'!I28)/N('P&L'!H28)-1,0) -> 0
B40: Forward NOI | F40: =S8 | H40: Operating Assumptions
B41: (%) Exit Cap Rate | F41: =S4 -> 0.0725 | H41: Vacancy Rate (% of EGI) | J41: ='P&L'!D11 -> 0 | K41: ='P&L'!E11 -> 0.12 | L41: ='P&L'!F11 -> 0.1 | M41: ='P&L'!G11 -> 0.1 | N41: ='P&L'!H11 -> 0.1 | O41: ='P&L'!I11 -> 0.1
B42: (=) Sale Price | F42: =IFERROR(S8/S4,0) -> 0 | H42: Loss to Lease (% of GPR) | J42: ='P&L'!D13 -> 0 | K42: ='P&L'!E13 -> 0.01 | L42: ='P&L'!F13 -> 0.01 | M42: ='P&L'!G13 -> 0.01 | N42: ='P&L'!H13 -> 0.01 | O42: ='P&L'!I13 -> 0.01
B43: Per Unit | D43: =IFERROR(F42/'Prop Info'!$B$6,0) -> 0 | E43: Per RSF | F43: =IFERROR(F42/'Prop Info'!$B$15,0) -> 0 | H43: Bad Debt & Concessions (% of EGI) | J43: ='P&L'!D15 -> 0.1 | K43: ='P&L'!E15 -> 0.03 | L43: ='P&L'!F15 -> 0.03 | M43: ='P&L'!G15 -> 0.03 | N43: ='P&L'!H15 -> 0.03 | O43: ='P&L'!I15 -> 0.03
B44: (-) Sale Cost | D44: =S5 -> 0.02 | F44: =-F42*S5 -> 0
B45: (=) Net Sale Proceeds | F45: =F42+F44 -> 0
B48: Exit Year & Cap Sensitivity on Levered IRR | MOIC
C49: Exit Cap Rate | D49: Exit Year
D50: ="Yr. "&TEXT(S33,"0") -> Yr. 4 | E50: ="Yr. "&TEXT(T33,"0") -> Yr. 5 | F50: ="Yr. "&TEXT(U33,"0") -> Yr. 6
C51: =R34 -> 0.0675 | D51: =TEXT(S34,"0.0%")&" | "&TEXT(W34,"0.00")&"x" -> 0.0% | 0.00x | E51: =TEXT(T34,"0.0%")&" | "&TEXT(X34,"0.00")&"x" -> 0.0% | 0.00x | F51: =TEXT(U34,"0.0%")&" | "&TEXT(Y34,"0.00")&"x" -> 0.0% | 0.00x
C52: =R35 -> 0.07 | D52: =TEXT(S35,"0.0%")&" | "&TEXT(W35,"0.00")&"x" -> 0.0% | 0.00x | E52: =TEXT(T35,"0.0%")&" | "&TEXT(X35,"0.00")&"x" -> 0.0% | 0.00x | F52: =TEXT(U35,"0.0%")&" | "&TEXT(Y35,"0.00")&"x" -> 0.0% | 0.00x
C53: =R36 -> 0.0725 | D53: =TEXT(S36,"0.0%")&" | "&TEXT(W36,"0.00")&"x" -> 0.0% | 0.00x | E53: =TEXT(T36,"0.0%")&" | "&TEXT(X36,"0.00")&"x" -> 0.0% | 0.00x | F53: =TEXT(U36,"0.0%")&" | "&TEXT(Y36,"0.00")&"x" -> 0.0% | 0.00x
C54: =R37 -> 0.075 | D54: =TEXT(S37,"0.0%")&" | "&TEXT(W37,"0.00")&"x" -> 0.0% | 0.00x | E54: =TEXT(T37,"0.0%")&" | "&TEXT(X37,"0.00")&"x" -> 0.0% | 0.00x | F54: =TEXT(U37,"0.0%")&" | "&TEXT(Y37,"0.00")&"x" -> 0.0% | 0.00x
C55: =R38 -> 0.0775 | D55: =TEXT(S38,"0.0%")&" | "&TEXT(W38,"0.00")&"x" -> 0.0% | 0.00x | E55: =TEXT(T38,"0.0%")&" | "&TEXT(X38,"0.00")&"x" -> 0.0% | 0.00x | F55: =TEXT(U38,"0.0%")&" | "&TEXT(Y38,"0.00")&"x" -> 0.0% | 0.00x

Sheet Inputs
A1: =IF('Prop Info'!B4="","MODEL INPUTS — NAVIGATION","MODEL INPUTS — NAVIGATION"&" — "&'Prop Info'!B4) -> MODEL INPUTS — NAVIGATION
A3: COLOR LEGEND
A4: Blue | B4: Hardcoded input — type here
A5: Black | B5: Same-sheet formula — do not edit
A6: Green | B6: Cross-sheet link — do not edit
A7: Red | B7: External file link — do not edit
A9: Total input cells: | B9: 452 | C9: across | D9: 14 | E9: tabs
A11: Tab | B11: Cell | C11: Label | D11: Current Value
A12: SCENARIOS | B12: 66 inputs
A13: Scenarios | B13: =HYPERLINK("#Scenarios!B10","B10") -> B10 | C13: Down Payment % | D13: 0.2
A14: Scenarios | B14: =HYPERLINK("#Scenarios!B15","B15") -> B15 | C14: Acquisition Fee (%) | D14: 0.03
A15: Scenarios | B15: =HYPERLINK("#Scenarios!B28","B28") -> B28 | C15: GP Ownership % | D15: 0.3
A16: Scenarios | B16: =HYPERLINK("#Scenarios!C28","C28") -> C28 | C16: GP Ownership % | D16: 0.3
A17: Scenarios | B17: =HYPERLINK("#Scenarios!C32","C32") -> C32 | C17: GP Equity ($) | D17: 0
A18: Scenarios | B18: =HYPERLINK("#Scenarios!B35","B35") -> B35 | C18: Class A Preferred Return % | D18: 0
A19: Scenarios | B19: =HYPERLINK("#Scenarios!C35","C35") -> C35 | C19: Class A Preferred Return % | D19: 0
A20: Scenarios | B20: =HYPERLINK("#Scenarios!B36","B36") -> B36 | C20: Class B Preferred Return % (T-12 Actuals) | D20: =Scenarios!B36 -> 0
A21: Scenarios | B21: =HYPERLINK("#Scenarios!C36","C36") -> C36 | C21: Class B Preferred Return % (My Version) | D21: =Scenarios!C36 -> 0
A22: Scenarios | B22: =HYPERLINK("#Scenarios!D36","D36") -> D36 | C22: Class B Preferred Return % (Projected) | D22: =Scenarios!D36 -> 0
A23: Scenarios | B23: =HYPERLINK("#Scenarios!E36","E36") -> E36 | C23: Class B Preferred Return % (Offer) | D23: =Scenarios!E36 -> 0
A24: Scenarios | B24: =HYPERLINK("#Scenarios!C46","C46") -> C46 | C24: Covered/garage: 1–3% of GPR | D24: 0
A25: Scenarios | B25: =HYPERLINK("#Scenarios!B77","B77") -> B77 | C25: Market Cap Rate | D25: 0.08
A26: Scenarios | B26: =HYPERLINK("#Scenarios!D77","D77") -> D77 | C26: Market Cap Rate | D26: 0.08
A27: Scenarios | B27: =HYPERLINK("#Scenarios!E77","E77") -> E77 | C27: Market Cap Rate | D27: 0.08
A28: Scenarios | B28: =HYPERLINK("#Scenarios!B79","B79") -> B79 | C28: As-Is Appraised Value | D28: 0
A29: Scenarios | B29: =HYPERLINK("#Scenarios!D80","D80") -> D80 | C29: Exit Year | D29: 7
A30: Scenarios | B30: =HYPERLINK("#Scenarios!E80","E80") -> E80 | C30: Exit Year | D30: 7
A31: Scenarios | B31: =HYPERLINK("#Scenarios!D81","D81") -> D81 | C31: Exit Cap Rate | D31: 0.085
A32: Scenarios | B32: =HYPERLINK("#Scenarios!E81","E81") -> E81 | C32: Exit Cap Rate | D32: 0.085
A33: Scenarios | B33: =HYPERLINK("#Scenarios!B91","B91") -> B91 | C33: Origination Fee % — 1st | D33: 0.01
A34: Scenarios | B34: =HYPERLINK("#Scenarios!C91","C91") -> C91 | C34: Origination Fee % — 1st | D34: 0.01
A35: Scenarios | B35: =HYPERLINK("#Scenarios!C93","C93") -> C93 | C35: Loan Amount — 2nd ($) | D35: 0
A36: Scenarios | B36: =HYPERLINK("#Scenarios!C94","C94") -> C94 | C36: Interest Rate — 2nd (%) | D36: 0
A37: Scenarios | B37: =HYPERLINK("#Scenarios!C95","C95") -> C95 | C37: Amortization (years) — 2nd | D37: 0
A38: Scenarios | B38: =HYPERLINK("#Scenarios!C96","C96") -> C96 | C38: Loan Term (years) — 2nd | D38: 0
A39: Scenarios | B39: =HYPERLINK("#Scenarios!C97","C97") -> C97 | C39: Interest-Only Period (months) — 2nd | D39: 0
A40: Scenarios | B40: =HYPERLINK("#Scenarios!B98","B98") -> B98 | C40: Origination Fee % — 2nd | D40: 0
A41: Scenarios | B41: =HYPERLINK("#Scenarios!C98","C98") -> C98 | C41: Origination Fee % — 2nd | D41: 0
A42: Scenarios | B42: =HYPERLINK("#Scenarios!C100","C100") -> C100 | C42: Loan Amount — Supplemental ($) | D42: 0
A43: Scenarios | B43: =HYPERLINK("#Scenarios!C101","C101") -> C101 | C43: Interest Rate — Supplemental (%) | D43: 0
A44: Scenarios | B44: =HYPERLINK("#Scenarios!C102","C102") -> C102 | C44: Amortization (years) — Supplemental | D44: 0
A45: Scenarios | B45: =HYPERLINK("#Scenarios!C103","C103") -> C103 | C45: Loan Term (years) — Supplemental | D45: 0
A46: Scenarios | B46: =HYPERLINK("#Scenarios!C104","C104") -> C104 | C46: Interest-Only Period (months) — Supplemental | D46: 0
A47: Scenarios | B47: =HYPERLINK("#Scenarios!B105","B105") -> B105 | C47: Origination Fee % — Supplemental | D47: 0
A48: Scenarios | B48: =HYPERLINK("#Scenarios!C105","C105") -> C105 | C48: Origination Fee % — Supplemental | D48: 0
A49: Scenarios | B49: =HYPERLINK("#Scenarios!B124","B124") -> B124 | C49: Vacancy % | D49: 0.05
A50: Scenarios | B50: =HYPERLINK("#Scenarios!C124","C124") -> C124 | C50: Vacancy % | D50: 0.08
A51: Scenarios | B51: =HYPERLINK("#Scenarios!D124","D124") -> D124 | C51: Vacancy % | D51: 0.12
A52: Scenarios | B52: =HYPERLINK("#Scenarios!E124","E124") -> E124 | C52: Vacancy % | D52: 0.15
A53: Scenarios | B53: =HYPERLINK("#Scenarios!B125","B125") -> B125 | C53: Bad Debt / Concessions % | D53: 0.02
A54: Scenarios | B54: =HYPERLINK("#Scenarios!C125","C125") -> C125 | C54: Bad Debt / Concessions % | D54: 0.03
A55: Scenarios | B55: =HYPERLINK("#Scenarios!D125","D125") -> D125 | C55: Bad Debt / Concessions % | D55: 0.05
A56: Scenarios | B56: =HYPERLINK("#Scenarios!E125","E125") -> E125 | C56: Bad Debt / Concessions % | D56: 0.06
A57: Scenarios | B57: =HYPERLINK("#Scenarios!B126","B126") -> B126 | C57: Loss to Lease % | D57: 0.03
A58: Scenarios | B58: =HYPERLINK("#Scenarios!C126","C126") -> C126 | C58: Loss to Lease % | D58: 0.02
A59: Scenarios | B59: =HYPERLINK("#Scenarios!D126","D126") -> D126 | C59: Loss to Lease % | D59: 0.01
A60: Scenarios | B60: =HYPERLINK("#Scenarios!E126","E126") -> E126 | C60: Loss to Lease % | D60: 0
A61: Scenarios | B61: =HYPERLINK("#Scenarios!B127","B127") -> B127 | C61: Mgmt Fee % | D61: 0.03
A62: Scenarios | B62: =HYPERLINK("#Scenarios!C127","C127") -> C127 | C62: Mgmt Fee % | D62: 0.04
A63: Scenarios | B63: =HYPERLINK("#Scenarios!D127","D127") -> D127 | C63: Mgmt Fee % | D63: 0.06
A64: Scenarios | B64: =HYPERLINK("#Scenarios!E127","E127") -> E127 | C64: Mgmt Fee % | D64: 0.08
A65: Scenarios | B65: =HYPERLINK("#Scenarios!B128","B128") -> B128 | C65: Insurance / Unit / Yr | D65: 600
A66: Scenarios | B66: =HYPERLINK("#Scenarios!C128","C128") -> C128 | C66: Insurance / Unit / Yr | D66: 650
A67: Scenarios | B67: =HYPERLINK("#Scenarios!D128","D128") -> D128 | C67: Insurance / Unit / Yr | D67: 700
A68: Scenarios | B68: =HYPERLINK("#Scenarios!E128","E128") -> E128 | C68: Insurance / Unit / Yr | D68: 750
A69: Scenarios | B69: =HYPERLINK("#Scenarios!B129","B129") -> B129 | C69: CapEx Reserve / Unit / Yr | D69: 250
A70: Scenarios | B70: =HYPERLINK("#Scenarios!C129","C129") -> C129 | C70: CapEx Reserve / Unit / Yr | D70: 350
A71: Scenarios | B71: =HYPERLINK("#Scenarios!D129","D129") -> D129 | C71: CapEx Reserve / Unit / Yr | D71: 450
A72: Scenarios | B72: =HYPERLINK("#Scenarios!E129","E129") -> E129 | C72: CapEx Reserve / Unit / Yr | D72: 500
A73: Scenarios | B73: =HYPERLINK("#Scenarios!B130","B130") -> B130 | C73: R&M / Unit / Yr | D73: 550
A74: Scenarios | B74: =HYPERLINK("#Scenarios!C130","C130") -> C130 | C74: R&M / Unit / Yr | D74: 700
A75: Scenarios | B75: =HYPERLINK("#Scenarios!D130","D130") -> D130 | C75: R&M / Unit / Yr | D75: 900
A76: Scenarios | B76: =HYPERLINK("#Scenarios!E130","E130") -> E130 | C76: R&M / Unit / Yr | D76: 1000
A77: Scenarios | B77: =HYPERLINK("#Scenarios!C149","C149") -> C149 | C77: Op Reserve Release Year | D77: 3
A78: Scenarios | B78: =HYPERLINK("#Scenarios!C150","C150") -> C150 | C78: Op Reserve Release Amount ($) | D78: 0
A80: DATA CHECKLIST | B80: 74 inputs
A81: Data Checklist | B81: =HYPERLINK("#'Data Checklist'!A8","A8") -> A8 | C81: ⚠ Trailing 12 (T-12) — current month-end | D81: 1
A82: Data Checklist | B82: =HYPERLINK("#'Data Checklist'!A9","A9") -> A9 | C82: ⚠ Trailing 3 (T-3) — current month-end | D82: 2
A83: Data Checklist | B83: =HYPERLINK("#'Data Checklist'!A10","A10") -> A10 | C83: Year-to-Date Income Statement (current FY) | D83: 3
A84: Data Checklist | B84: =HYPERLINK("#'Data Checklist'!A11","A11") -> A11 | C84: Prior Year (Y-1) Annual Income Statement | D84: 4
A85: Data Checklist | B85: =HYPERLINK("#'Data Checklist'!A12","A12") -> A12 | C85: Prior Year (Y-2) Annual Income Statement | D85: 5
A86: Data Checklist | B86: =HYPERLINK("#'Data Checklist'!A13","A13") -> A13 | C86: Budget vs Actual — current FY | D86: 6
A87: Data Checklist | B87: =HYPERLINK("#'Data Checklist'!A14","A14") -> A14 | C87: General Ledger (current FY) | D87: 7
A88: Data Checklist | B88: =HYPERLINK("#'Data Checklist'!A15","A15") -> A15 | C88: Bank Statements (last 3 months) | D88: 8
A89: Data Checklist | B89: =HYPERLINK("#'Data Checklist'!A16","A16") -> A16 | C89: Tax Returns (last 2 years) | D89: 9
A90: Data Checklist | B90: =HYPERLINK("#'Data Checklist'!A19","A19") -> A19 | C90: ⚠ Current Rent Roll (with all status detail) | D90: 10
A91: Data Checklist | B91: =HYPERLINK("#'Data Checklist'!A20","A20") -> A20 | C91: ⚠ Detailed AR Aging (0-30, 31-60, 61-90, 90+) | D91: 11
A92: Data Checklist | B92: =HYPERLINK("#'Data Checklist'!A21","A21") -> A21 | C92: ⚠ Eviction Status Report | D92: 12
A93: Data Checklist | B93: =HYPERLINK("#'Data Checklist'!A22","A22") -> A22 | C93: Lease Files / Tenant Files (sample) | D93: 13
A94: Data Checklist | B94: =HYPERLINK("#'Data Checklist'!A23","A23") -> A23 | C94: ⚠ Bankruptcy / Litigation Disclosures | D94: 14
A95: Data Checklist | B95: =HYPERLINK("#'Data Checklist'!A24","A24") -> A24 | C95: Concession Log (last 12 months) | D95: 15
A96: Data Checklist | B96: =HYPERLINK("#'Data Checklist'!A25","A25") -> A25 | C96: Move-In/Move-Out Report (last 12 months) | D96: 16
A97: Data Checklist | B97: =HYPERLINK("#'Data Checklist'!A26","A26") -> A26 | C97: Pre-Paid Rent / Security Deposits Schedule | D97: 17
A98: Data Checklist | B98: =HYPERLINK("#'Data Checklist'!A27","A27") -> A27 | C98: Delinquency History (24 months) | D98: 18
A99: Data Checklist | B99: =HYPERLINK("#'Data Checklist'!A30","A30") -> A30 | C99: ⚠ Property Tax Bills (last 2 years) | D99: 19
A100: Data Checklist | B100: =HYPERLINK("#'Data Checklist'!A31","A31") -> A31 | C100: ⚠ Property Tax Reassessment Estimate | D100: 20
A101: Data Checklist | B101: =HYPERLINK("#'Data Checklist'!A32","A32") -> A32 | C101: ⚠ Insurance Policy & Premium Detail | D101: 21
A102: Data Checklist | B102: =HYPERLINK("#'Data Checklist'!A33","A33") -> A33 | C102: ⚠ Insurance Loss Runs (5 years) | D102: 22
A103: Data Checklist | B103: =HYPERLINK("#'Data Checklist'!A34","A34") -> A34 | C103: ⚠ Utility Bills (Water/Electric/Gas — 12 months) | D103: 23
A104: Data Checklist | B104: =HYPERLINK("#'Data Checklist'!A35","A35") -> A35 | C104: Trash / Recycling Contract | D104: 24
...

Sheet Prop Info
A1: =IF('Prop Info'!B4="","PROPERTY INFORMATION & MARKET DATA","PROPERTY INFORMATION & MARKET DATA"&" — "&'Prop Info'!B4) -> PROPERTY INFORMATION & MARKET DATA
A2: Blue = manual input. Use the AI Market Research tool (separate app) to auto-populate market fields.
A3: PROPERTY DETAILS
A4: Property Name
A5: Location / Address
A6: # Units
A7: # Buildings
A8: Height (stories)
A9: Year Built
A10: Lot Size (acres)
A11: Gross Sq Ft
A12: Parking Spaces
A13: Building Class (A/B/C)
... A47: Value-Add Thesis

Sheet Data Refresh
A1: =IF('Prop Info'!B4="","DATA REFRESH — Power Query connections for live market data","DATA REFRESH — Power Query connections for live market data"&" — "&'Prop Info'!B4) -> DATA REFRESH — Power Query connections for live market data
A2: Pulls Census, FRED, and BLS data on demand. Refresh updates these cells in Prop Info automatically.
A4: A. HOW THIS WORKS
A5: 1. Get free API keys (5 min, one-time):
A6: • Census Bureau: https://api.census.gov/data/key_signup.html
A7: • FRED (St. Louis Fed): https://fred.stlouisfed.org/docs/api/api_key.html
A8: • BLS (optional): https://data.bls.gov/registrationEngine/
A10: 2. Open Excel → Data tab → Get Data → From Other Sources → Blank Query → Advanced Editor
A12: 3. Paste the M code from sections B, C, or D below into the editor. Replace YOUR_KEY_HERE with your key.
A14: 4. Name the query (e.g. "Census_Demographics"), click Close & Load → Load To → Existing Worksheet → "_API_Output" tab.
A16: 5. To refresh: Data tab → Refresh All. Prop Info cells will recalculate from latest API data.
A18: 6. To schedule auto-refresh: Data → Connections → Properties → "Refresh every X min" or "Refresh on file open".
A21: B. CENSUS ACS 1-YEAR API — covers 7 of 17 Prop Info cells
A22: Atlanta MSA (CBSA #12060). Returns population, age cohorts, income, household tenure in one call.
A24: Prop Info Cell | B24: Metric | C24: Census ACS Variable | D24: Last Refreshed | E24: Notes
A25: B22 | B25: MSA Population | C25: B01003_001E | D25: (set after refresh) | E25: Total pop, single variable
A26: B23 | B26: City Population | C26: B01003_001E (place geo) | D26: (set after refresh) | E26: Separate query — geography=place:04000
A27: B25 | B27: Renter-Age Pop (25–44) | C27: B01001_011E..014E + _035E..038E | D27: (set after refresh) | E27: Sum 8 male+female age cohorts
A28: B27 | B28: Avg Household Income | C28: B19025_001E / B11001_001E | D28: (set after refresh) | E28: Aggregate income / household count
A29: B28 | B29: Median Income | C29: B19013_001E | D29: (set after refresh) | E29: Direct variable
A30: B37 | B30: Renter Household % | C30: B25003_003E / B25003_001E | D30: (set after refresh) | E30: Renter-occupied / total occupied
A31: B24 | B31: Population Growth Rate | C31: (B01003_001E[year] - B01003_001E[year-1]) / prev | D31: (set after refresh) | E31: Two queries: current year + prior year
A33: M code → paste into Power Query Advanced Editor:
A34: let // ===== USER CONFIGURATION ===== ApiKey = "YOUR_CENSUS_API_KEY", // Free at https://api.census.gov/data/key_signup.html Year = "2024", // Latest ACS 1-year CbsaCode = "12060", // Atlanta-Sandy Springs-Roswell MSA // ===== VARIABLES TO FETCH ===== // B01003_001E = Total population // B01001_011E..014E = Male age 25-44 cohorts (4 brackets) // B01001_035E..038E = Female age 25-44 cohorts (4 brackets) // B19013_001E = Median household income // B19025_001E = Aggregate household income (for mean calc) // B11001_001E = Total households // B25003_001E = Total occupied housing units // B25003_003E = Renter-occupied housing units Vars = "NAME,B01003_001E,B01001_011E,B01001_012E,B01001_013E,B01001_014E,B01001_035E,B01001_036E,B01001_037E,B01001_038E,B19013_001E,B19025_001E,B11001_001E,B25003_001E,B25003_003E", Url = "https://api.census.gov/data/" & Year & "/acs/acs1?get=" & Vars & "&for=metropolitan%20statistical%20area/micropolitan%20statistical%20area:" & CbsaCode & "&key=" & ApiKey, Source = Json.Document(Web.Contents(Url)), Headers = List.Transform(Source{0}, Text.From), Data = List.Transform(List.Skip(Source, 1), each List.Transform(_, Text.From)), Raw = #table(Headers, Data), // Convert numeric columns NumCols = List.RemoveItems(Headers, {"NAME"}), Typed = Table.TransformColumnTypes(Raw, List.Transform(NumCols, each {_, type number})), // ===== DERIVED METRICS ===== Pop = Record.Field(Typed{0}, "B01003_001E"), RenterAge = Record.Field(Typed{0}, "B01001_011E") + Record.Field(Typed{0}, "B01001_012E") + Record.Field(Typed{0}, "B01001_013E") + Record.Field(Typed{0}, "B01001_014E") + Record.Field(Typed{0}, "B01001_035E") + Record.Field(Typed{0}, "B01001_036E") + Record.Field(Typed{0}, "B01001_037E") + Record.Field(Typed{0}, "B01001_038E"), MedInc = Record.Field(Typed{0}, "B19013_001E"), AggInc = Record.Field(Typed{0}, "B19025_001E"), Households = Record.Field(Typed{0}, "B11001_001E"), AvgInc = if Households > 0 then AggInc / Households else null, OccUnits = Record.Field(Typed{0}, "B25003_001E"), RenterUnits = Record.Field(Typed{0}, "B25003_003E"), RenterPct = if OccUnits > 0 then RenterUnits / OccUnits else null, // ===== OUTPUT TABLE ===== Output = #table( {"Metric", "Value", "Source", "Refreshed"}, { {"MSA Population", Pop, "Census ACS B01003_001E", DateTime.LocalNow()}, {"Renter-Age Population (25-44)", RenterAge, "Census ACS B01001 sum", DateTime.LocalNow()}, {"Median Household Income", MedInc, "Census ACS B19013_001E", DateTime.LocalNow()}, {"Avg Household Income", AvgInc, "Census ACS B19025/B11001", DateTime.LocalNow()}, {"Renter Household %", RenterPct, "Census ACS B25003_003/_001E", DateTime.LocalNow()} } ) in Output
A36: C. FRED API — population growth + economic proxies
A37: Use this for time-series data: population growth rate, building permits (supply proxy), employment.
A39: Prop Info Cell | B39: Metric | C39: FRED Series ID | D39: Last Refreshed | E39: Notes
A40: B24 | B40: Population Growth Rate | C40: ATLPOP | D40: (set after refresh) | E40: Annual MSA population — derive YoY %
A41: B36 | B41: Housing Starts (proxy) | C41: ATLA013BPPRIVSA | D41: (set after refresh) | E41: Building permits — proxy for new supply
A42: — | B42: Atlanta unemployment | C42: ATLA013URN | D42: (set after refresh) | E42: Indicates renter income strength
A43: — | B43: Per capita income | C43: PCPI13013 | D43: (set after refresh) | E43: Atlanta MSA per capita personal income
A45: M code → paste into Power Query Advanced Editor:
A46: let // ===== USER CONFIGURATION ===== ApiKey = "YOUR_FRED_API_KEY", // Free at https://fred.stlouisfed.org/docs/api/api_key.html SeriesId = "ATLPOP", // Atlanta MSA Resident Population (annual) Url = "https://api.stlouisfed.org/fred/series/observations?series_id=" & SeriesId & "&api_key=" & ApiKey & "&file_type=json&sort_order=desc&limit=10", Source = Json.Document(Web.Contents(Url)), Observations = Source[observations], Raw = Table.FromRecords(Observations), Typed = Table.TransformColumnTypes(Raw, {{"date", type date}, {"value", type number}}), Sorted = Table.Sort(Typed, {{"date", Order.Descending}}), // Calculate YoY growth rate Latest = Sorted{0}[value], Prior = Sorted{1}[value], Growth = if Prior > 0 then (Latest - Prior) / Prior else null, // Output table Output = #table( {"Metric", "Value", "Source", "AsOf", "Refreshed"}, { {"Latest Population", Latest, "FRED " & SeriesId, Sorted{0}[date], DateTime.LocalNow()}, {"Prior Year Population", Prior, "FRED " & SeriesId, Sorted{1}[date], DateTime.LocalNow()}, {"YoY Growth Rate", Growth, "FRED derived", Sorted{0}[date], DateTime.LocalNow()} } ) in Output
A48: D. WIRE API OUTPUT INTO PROP INFO — formula pattern
A49: After Power Query loads to a sheet (e.g. '_API_Output'), replace Prop Info column B with formulas like:
A51: Cell | B51: Formula | D51: Pulls
A52: Prop Info!B22 | B52: =INDEX(_api_output!b:b, MATCH("MSA Population", _api_output!a:a, 0)) | D52: Pull MSA pop from Census query output
A53: Prop Info!B25 | B53: =INDEX(_api_output!b:b, MATCH("Renter-Age Population (25-44)", _api_output!a:a, 0)) | D53: Pull renter-age count
A54: Prop Info!B28 | B54: =INDEX(_api_output!b:b, MATCH("Median Household Income", _api_output!a:a, 0)) | D54: Pull median income
A55: Prop Info!B37 | B55: =INDEX(_api_output!b:b, MATCH("Renter Household %", _api_output!a:a, 0)) | D55: Pull renter %
A56: Prop Info!B24 | B56: =INDEX(_api_output_fred!b:b, MATCH("YoY Growth Rate", _api_output_fred!a:a, 0)) | D56: Pull pop growth from FRED query
A58: E. MANUAL REFRESH — 10 of 17 cells (apartment market + school data)
A59: These metrics have no free API at MSA granularity. Update quarterly from the URLs below or paste from CoStar/Yardi if subscribed.
A61: Cell | B61: Metric | C61: Best free quarterly source | D61: Frequency | E61: Notes
A62: B26 | B62: Renter-Age Pop Growth Rate | C62: Derive from Census ACS YoY (script needed) | D62: Annual | E62: Could be added to Census Power Query
A63: B29 | B63: School District Rating | C63: https://www.greatschools.org | D63: On address change | E63: Address-specific lookup
A64: B31 | B64: 3BR Units (clarify intent) | C64: Internal data | D64: On address change | E64: Field intent unclear
A65: B32 | B65: Blended Avg Monthly Rent | C65: Yardi Matrix Atlanta MMR (free quarterly summary) | D65: Quarterly | E65: https://www.yardimatrix.com/blog/
A66: B33 | B66: Avg Unit SF | C66: RentCafe Atlanta market trends | D66: Annual | E66: https://www.rentcafe.com/average-rent-market-trends/us/ga/atlanta/
A67: B34 | B67: Market Vacancy Rate | C67: Multiple: Matthews, Northmarq, Yardi quarterly reports | D67: Quarterly | E67: Average 3-4 sources
A68: B35 | B68: Market Rent Growth (Annual) | C68: Yardi Matrix YoY rent change | D68: Quarterly | E68: Same source as B32
A69: B36 | B69: Units Under Construction | C69: Yardi Matrix or MMG/Northmarq forecast reports | D69: Quarterly | E69: Sub for FRED if MF-specific needed
A71: F. CURRENT STATUS — what each Prop Info cell currently shows
A72: Live read of Prop Info column B values. After Power Query setup + wiring, these refresh automatically.
A74: Cell | B74: Metric | C74: Current Value | D74: Refresh Method | E74: API Available?
A75: B22 | B75: MSA Population | C75: ='Prop Info'!B22 -> 0 | D75: Census ACS | E75: 🟢 Yes
A76: B23 | B76: City Population | C76: ='Prop Info'!B23 -> 0 | D76: Census ACS (place) | E76: 🟢 Yes
A77: B24 | B77: Population Growth Rate | C77: ='Prop Info'!B24 -> 0 | D77: FRED | E77: 🟢 Yes
A78: B25 | B78: Renter-Age Pop (25–44) | C78: ='Prop Info'!B25 -> 0 | D78: Census ACS | E78: 🟢 Yes
A79: B26 | B79: Renter-Age Growth Rate | C79: ='Prop Info'!B26 -> 0 | D79: Census ACS (derived) | E79: 🟡 Possible
A80: B27 | B80: Avg Household Income | C80: ='Prop Info'!B27 -> 0 | D80: Census ACS | E80: 🟢 Yes
A81: B28 | B81: Median Income | C81: ='Prop Info'!B28 -> 0 | D81: Census ACS | E81: 🟢 Yes
A82: B29 | B82: School District Rating | C82: ='Prop Info'!B29 -> 0 | D82: Manual | E82: 🔴 No
A83: B31 | B83: 3BR Units | C83: ='Prop Info'!B31 -> 0 | D83: Manual / clarify | E83: 🔴 No
A84: B32 | B84: Blended Avg Monthly Rent | C84: ='Prop Info'!B32 -> 0 | D84: Manual (paid Yardi) | E84: 🔴 No
A85: B33 | B85: Avg Unit SF | C85: ='Prop Info'!B33 -> 0 | D85: Manual | E85: 🔴 No
A86: B34 | B86: Market Vacancy Rate | C86: ='Prop Info'!B34 -> 0 | D86: Manual | E86: 🔴 No
A87: B35 | B87: Market Rent Growth | C87: ='Prop Info'!B35 -> 0 | D87: Manual | E87: 🔴 No
A88: B36 | B88: Units Under Construction | C88: ='Prop Info'!B36 -> 0 | D88: Manual / FRED proxy | E88: 🟡 Proxy only
A89: B37 | B89: Renter Household % | C89: ='Prop Info'!B37 -> 0 | D89: Census ACS | E89: 🟢 Yes
A91: COVERAGE SUMMARY:
A92: 🟢 Auto-refresh via free API: 7 cells (population, age, income, renter %)
A93: 🟡 Possible with extra work: 2 cells (renter age growth, supply proxy)
A94: 🔴 Manual quarterly refresh: 6 cells (apartment market, schools)

Sheet Data Checklist
A1: =IF('Prop Info'!B4="","DATA CHECKLIST — Due Diligence Tracker","DATA CHECKLIST — Due Diligence Tracker"&" — "&'Prop Info'!B4) -> DATA CHECKLIST — Due Diligence Tracker
A2: Track every DD item from request through review. Status dropdown drives % complete and color flags. Cross-Check column shows reconciliation formulas where relevant.
F3: Total Items | G3: Complete | H3: % Complete | I3: Critical Open | J3: Status
F4: =COUNT(A7:A97) -> 74 | G4: =COUNTIF(C7:C97,"Complete")+COUNTIF(C7:C97,"N/A") -> 0 | H4: =IFERROR(G4/F4,0) -> 0 | I4: =SUMPRODUCT((LEFT(B7:B97,1)="⚠")*(C7:C97<>"Complete")*(C7:C97<>"N/A")) -> 32 | J4: =IF(I4>5,"🔴 many critical open",IF(I4>0,"🟡 critical items pending","🟢 critical items resolved")) -> 🔴 many critical open
A6: # | B6: Item | C6: Status | D6: Date Requested | E6: Date Received | F6: Source / Counterparty | G6: Format | H6: Reviewer | I6: Cross-Check / Reconciliation | J6: Notes
A7: A. FINANCIAL STATEMENTS
A8: 1 | B8: ⚠ Trailing 12 (T-12) — current month-end | C8: Not Requested | I8: =IF('T-12 Analysis'!N80>0,"✓ EGI loaded $"&TEXT('T-12 Analysis'!N80,"#,##0"),"⚠ T-12 not loaded") -> ⚠ T-12 not loaded | J8: PSI/Yardi cash basis Apr 2025-Mar 2026
A9: 2 | B9: ⚠ Trailing 3 (T-3) — current month-end | C9: Not Requested | I9: =IF('T-12 Analysis'!O80>0,"✓ T-3 derived from T-12","derive from T-12 monthly") -> derive from T-12 monthly | J9: Derived from T-12 monthly columns
A10: 3 | B10: Year-to-Date Income Statement (current FY) | C10: Not Requested | J10: YTD compared to prior year same period
A11: 4 | B11: Prior Year (Y-1) Annual Income Statement | C11: Not Requested | J11: For T-12 trend comparison
A12: 5 | B12: Prior Year (Y-2) Annual Income Statement | C12: Not Requested | J12: Validates 3-year trajectory
A13: 6 | B13: Budget vs Actual — current FY | C13: Not Requested | J13: Reveals operator forecasting accuracy
A14: 7 | B14: General Ledger (current FY) | C14: Not Requested | J14: For deep-dive on individual accounts
A15: 8 | B15: Bank Statements (last 3 months) | C15: Not Requested | J15: For revenue verification
A16: 9 | B16: Tax Returns (last 2 years) | C16: Not Requested | J16: Form 8825 / Schedule E
A18: B. RENT ROLL & ACCOUNTS RECEIVABLE
A19: 10 | B19: ⚠ Current Rent Roll (with all status detail) | C19: Received | I19: =IF('Rent Roll Analysis'!I5>0,"✓ "&'Rent Roll Analysis'!I5&" units in RR vs "&'Rent Roll Analysis'!G5&" total","⚠ RR not loaded") -> ⚠ RR not loaded | J19: As of 4/16/2026
A20: 11 | B20: ⚠ Detailed AR Aging (0-30, 31-60, 61-90, 90+) | C20: Received | I20: =IF('Rent Roll Analysis'!C94>0,"✓ Total AR $"&TEXT('Rent Roll Analysis'!C94,"#,##0"),"⚠ AR not loaded") -> ⚠ AR not loaded | J20: In rent roll columns Q-T
A21: 12 | B21: ⚠ Eviction Status Report | C21: Received | I21: =IF('Rent Roll Analysis'!B113>0,"✓ "&'Rent Roll Analysis'!B113&" units flagged for legal/eviction (** in source)","none flagged") -> none flagged | J21: 9 active evictions, 1 bankruptcy known
A22: 13 | B22: Lease Files / Tenant Files (sample) | C22: Not Requested | J22: Pull random sample of 10-15 leases
A23: 14 | B23: ⚠ Bankruptcy / Litigation Disclosures | C23: Received | I23: =IF('Rent Roll Analysis'!D113>0,"⚠ $"&TEXT('Rent Roll Analysis'!D113,"#,##0")&" AR exposure on legal cohort","none on record") -> none on record | J23: Smith N6 Ch 7 filed 3/28/26
A24: 15 | B24: Concession Log (last 12 months) | C24: Not Requested | J24: Reconcile to T-12 concession lines
A25: 16 | B25: Move-In/Move-Out Report (last 12 months) | C25: Not Requested | J25: For turnover rate calculation
A26: 17 | B26: Pre-Paid Rent / Security Deposits Schedule | C26: Not Requested | J26: Liability transfer at closing
A27: 18 | B27: Delinquency History (24 months) | C27: Not Requested | J27: Trend analysis on collection
A29: C. OPERATING EXPENSE DETAIL
A30: 19 | B30: ⚠ Property Tax Bills (last 2 years) | C30: Not Requested | J30: Validate accrual + millage rate
A31: 20 | B31: ⚠ Property Tax Reassessment Estimate | C31: Not Requested | J31: Critical: post-sale reassessment
A32: 21 | B32: ⚠ Insurance Policy & Premium Detail | C32: Not Requested | J32: Validate insurance line + coverage
A33: 22 | B33: ⚠ Insurance Loss Runs (5 years) | C33: Not Requested | J33: Material claims history
A34: 23 | B34: ⚠ Utility Bills (Water/Electric/Gas — 12 months) | C34: Not Requested | I34: =IF('T-12 Analysis'!P96>70,"⚠ water $"&TEXT('T-12 Analysis'!P96,"0.00")&" PUPM — investigate","ok") -> ok | J34: Water bill $198K — investigate leak
A35: 24 | B35: Trash / Recycling Contract | C35: Not Requested
A36: 25 | B36: Pest Control Contract | C36: Not Requested
A37: 26 | B37: Landscaping Contract | C37: Not Requested
A38: 27 | B38: Property Management Agreement | C38: Not Requested | J38: Termination notice required for sale
A39: 28 | B39: Service Contracts — All | C39: Not Requested | J39: Pool, elevator, HVAC, security, etc.
A40: 29 | B40: Vendor Invoices (sample, last 6 months) | C40: Not Requested | J40: For expense verification
A41: 30 | B41: ⚠ Payroll Register (current employees) | C41: Not Requested | J41: On-site staff & wages
A42: 31 | B42: Employee Benefits Schedule | C42: Not Requested | J42: Healthcare, 401k contribution
A44: D. CAPITAL EXPENDITURES
A45: 32 | B45: ⚠ CapEx History (last 5 years) | C45: Not Requested | J45: What's already been done?
A46: 33 | B46: ⚠ Pending CapEx / Open POs | C46: Not Requested | J46: Near-term obligations
A47: 34 | B47: ⚠ Property Condition Report (PCR/PCA) | C47: Not Requested | J47: 3rd party engineering report
A48: 35 | B48: ⚠ Roof Inspection / Warranty | C48: Not Requested
A49: 36 | B49: HVAC Age & Condition Inventory | C49: Not Requested | J49: Per unit — system age
A50: 37 | B50: ⚠ Plumbing Inspection | C50: Not Requested | I50: =IF('T-12 Analysis'!P96>70,"⚠ likely leak — inspect","ok") -> ok | J50: Critical given water bill
A51: 38 | B51: Electrical / Panel Inspection | C51: Not Requested
A52: 39 | B52: ⚠ Make-Ready Backlog Detail (per unit) | C52: Not Requested | J52: 77 vacant not ready — get scope per unit
A54: E. PROPERTY PHYSICAL & ENVIRONMENTAL
A55: 40 | B55: ⚠ ALTA Survey (current) | C55: Not Requested | J55: Less than 5 years old preferred
A56: 41 | B56: ⚠ Phase I Environmental (ESA) | C56: Not Requested | J56: Most lenders require
A57: 42 | B57: Phase II ESA (if recommended) | C57: Not Requested | J57: Only if Phase I flags
A58: 43 | B58: Asbestos / Lead Inspection | C58: Not Requested | J58: Pre-1978 builds especially
A59: 44 | B59: Mold / Moisture Inspection | C59: Not Requested
A60: 45 | B60: Termite / WDO Report | C60: Not Requested
A61: 46 | B61: ⚠ Floodplain Determination | C61: Not Requested | J61: FEMA flood zone — drives insurance
A62: 47 | B62: ⚠ Zoning Verification | C62: Not Requested | J62: Confirm legal use
A63: 48 | B63: Site Plans / As-Builts | C63: Not Requested
A64: 49 | B64: Building Permits / C of O | C64: Not Requested
A66: F. TITLE & LEGAL
A67: 50 | B67: ⚠ Title Commitment / Preliminary Report | C67: Not Requested
A68: 51 | B68: ⚠ Recorded Deed (most recent) | C68: Not Requested
A69: 52 | B69: ⚠ Easements / Restrictive Covenants | C69: Not Requested
A70: 53 | B70: ⚠ Liens / UCC Search | C70: Not Requested
A71: 54 | B71: ⚠ Pending Litigation | C71: Not Requested
A72: 55 | B72: ⚠ Code Violations / Citations | C72: Not Requested
A73: 56 | B73: Operating Agreement / LLC Docs | C73: Not Requested | J73: For seller entity
A75: G. MARKET INFO
A76: 57 | B76: Comparable Sales (last 24 months) | C76: Not Requested | J76: Within 1-mile / similar class
A77: 58 | B77: Rental Comp Survey (current) | C77: Not Requested | J77: Drives Rental Comps tab
A78: 59 | B78: CoStar / RealPage Submarket Report | C78: Not Requested
A79: 60 | B79: Demographic Report (3-mile/5-mile) | C79: Not Requested
A80: 61 | B80: New Supply Pipeline (under construction) | C80: Not Requested | J80: Within 3 miles
A81: 62 | B81: Employment / Major Employers | C81: Not Requested
A82: 63 | B82: School District Ratings | C82: Not Requested
A84: H. LOAN / DEBT
A85: 64 | B85: Existing Loan Documents (if assumable) | C85: Not Requested | J85: Note, mortgage, all amendments
A86: 65 | B86: Loan Payoff Statement | C86: Not Requested | J86: Closing requirement
A87: 66 | B87: Prepayment Penalty / Defeasance Calc | C87: Not Requested
A88: 67 | B88: ⚠ Term Sheet — New Loan | C88: Not Requested | J88: For UW assumptions
A89: 68 | B89: Lender Quotes (multiple) | C89: Not Requested | J89: 3 quotes minimum
A90: 69 | B90: Appraisal (most recent) | C90: Not Requested | J90: Validates LTV assumption
A92: I. SELLER & TRANSACTION
A93: 70 | B93: ⚠ Letter of Intent (LOI) | C93: Not Requested
A94: 71 | B94: ⚠ Purchase & Sale Agreement (PSA) | C94: Not Requested
A95: 72 | B95: ⚠ Seller Disclosure Statement | C95: Not Requested
A96: 73 | B96: Operating Agreement Amendments | C96: Not Requested
A97: 74 | B97: Closing Statement (HUD/CD) | C97: Not Requested | J97: Drives Acquisition Costs

Sheet Scenarios
A1: =IF('Prop Info'!B4="","SIDE-BY-SIDE SCENARIO ANALYSIS — ""The 10-Minute Offer""","SIDE-BY-SIDE SCENARIO ANALYSIS — ""The 10-Minute Offer"""&" — "&'Prop Info'!B4) -> SIDE-BY-SIDE SCENARIO ANALYSIS — "The 10-Minute Offer"
A2: Active Scenario → | B2: 1. T-12 Actuals
A3: Selecting an active scenario drives P&L, Cover Sheet, and Sensitivity tabs. Column B = T-12 Actuals (last 12 months, hardwired to T-12 Analysis). Yellow cells have explanatory comments — hover to see source mapping.
A4: Line Item | B4: 1. T-12 Actuals | C4: 2. My Version | D4: 3. Projected | E4: 4. Offer | F4: Active Scenario | G4: $/Unit | H4: Benchmark
A5: ACQUISITION
A6: Asking Price | C6: =IFERROR(B6,0) -> 0 | D6: =IFERROR(C6,0) -> 0 | E6: =IFERROR(D6,0) -> 0 | F6: =IFERROR(CHOOSE(MATCH(B$2,{"1. T-12 Actuals","2. My Version","3. Projected","4. Offer"},0),B6,C6,D6,E6),0) -> 0 | G6: =IFERROR(IF((B6/Units)=0,"",(B6/Units)),"") | H6: $5–100M+ MF; Class A 250-unit typically $40–100M
A7: Purchase Price / Offer | C7: =IFERROR(B7,0) -> 0 | D7: =IFERROR(C7,0) -> 0 | E7: =IFERROR(D7,0) -> 0 | F7: =IFERROR(CHOOSE(MATCH(B$2,{"1. T-12 Actuals","2. My Version","3. Projected","4. Offer"},0),B7,C7,D7,E7),0) -> 0 | G7: =IFERROR(IF((B7/Units)=0,"",(B7/Units)),"") | H7: Offer 3–8% below ask; value-add plays
A8: # Units | B8: =IFERROR('Prop Info'!B6,0) -> 0 | C8: =IFERROR(Units,0) -> 0 | D8: =IFERROR(C8,0) -> 0 | E8: =IFERROR(D8,0) -> 0 | F8: =IFERROR(CHOOSE(MATCH(B$2,{"1. T-12 Actuals","2. My Version","3. Projected","4. Offer"},0),B8,C8,D8,E8),0) -> 0 | G8: =IFERROR(IF(('Prop Info'!$B$6)=0,"",('Prop Info'!$B$6)),"") | H8: Total unit count — drives GPR and all per-unit metrics
A9: Price Per Unit | B9: =IFERROR(IFERROR(B7/B8,0),0) -> 0 | C9: =IFERROR(IFERROR(C7/C8,0),0) -> 0 | D9: =IFERROR(IFERROR(D7/D8,0),0) -> 0 | E9: =IFERROR(IFERROR(E7/E8,0),0) -> 0 | F9: =IFERROR(CHOOSE(MATCH(B$2,{"1. T-12 Actuals","2. My Version","3. Projected","4. Offer"},0),B9,C9,D9,E9),0) -> 0 | G9: =IFERROR(IF((IFERROR(F7/'Prop Info'!$B$6,0))=0,"",(IFERROR(F7/'Prop Info'!$B$6,0))),"") | H9: Class A: $200–400k/door; Class B: $100–200k/door
A10: Down Payment % | B10: 0.2 | C10: =IFERROR(B10,0) -> 0.2 | D10: =IFERROR(C10,0) -> 0.2 | E10: =IFERROR(D10,0) -> 0.2 | F10: =IFERROR(CHOOSE(MATCH(B$2,{"1. T-12 Actuals","2. My Version","3. Projected","4. Offer"},0),B10,C10,D10,E10),0) -> 0.2 | H10: 25–35% down; 65–75% LTV target
A11: Down Payment $ | B11: =IFERROR(B10*B7,0) -> 0 | C11: =IFERROR(C10*C7,0) -> 0 | D11: =IFERROR(D10*D7,0) -> 0 | E11: =IFERROR(E10*E7,0) -> 0 | F11: =IFERROR(CHOOSE(MATCH(B$2,{"1. T-12 Actuals","2. My Version","3. Projected","4. Offer"},0),B11,C11,D11,E11),0) -> 0 | H11: Auto-calculated from down payment
A12: Repairs / CapEx at Close | B12: =IFERROR(Capex!$D$51,0) -> 0 | C12: =IFERROR(Capex!$D$51,0) -> 0 | D12: =IFERROR(Capex!$D$51,0) -> 0 | E12: =IFERROR(Capex!$D$51,0) -> 0 | F12: =IFERROR(CHOOSE(MATCH(B$2,{"1. T-12 Actuals","2. My Version","3. Projected","4. Offer"},0),B12,C12,D12,E12),0) -> 0 | H12: Get contractor bid at LOI stage
A13: Operating Reserves | B13: =IFERROR((B70/12)*G13,0) -> 0 | C13: =B13 -> 0 | D13: =C13 -> 0 | E13: =D13 -> 0 | F13: =IFERROR(CHOOSE(MATCH(B$2,{"1. T-12 Actuals","2. My Version","3. Projected","4. Offer"},0),B13,C13,D13,E13),0) -> 0 | G13: 1 | H13: 3–6 months operating expenses
A14: Est. Closing Costs | B14: =IFERROR('Acquisition Costs'!$D$35,0) -> 0 | C14: =IFERROR('Acquisition Costs'!$D$35,0) -> 0 | D14: =IFERROR('Acquisition Costs'!$D$35,0) -> 0 | E14: =IFERROR('Acquisition Costs'!$D$35,0) -> 0 | F14: =IFERROR(CHOOSE(MATCH(B$2,{"1. T-12 Actuals","2. My Version","3. Projected","4. Offer"},0),B14,C14,D14,E14),0) -> 0 | G14: =IFERROR(IF((IFERROR(F14/F7,0))=0,"",(IFERROR(F14/F7,0))),"") | H14: 1.5–2.5% of purchase price
A15: Acquisition Fee (%) | B15: 0.02 | C15: =IFERROR(B15,0) -> 0.02 | D15: =IFERROR(C15,0) -> 0.02 | E15: =IFERROR(D15,0) -> 0.02 | F15: =IFERROR(CHOOSE(MATCH(B$2,{"1. T-12 Actuals","2. My Version","3. Projected","4. Offer"},0),B15,C15,D15,E15),0) -> 0.02 | H15: 0.5–1.5% acquisition fee standard
A16: Acquisition Fee ($) | B16: =IFERROR(B15*B7,0) -> 0 | C16: =IFERROR(C15*C7,0) -> 0 | D16: =IFERROR(D15*D7,0) -> 0 | E16: =IFERROR(E15*E7,0) -> 0 | F16: =IFERROR(CHOOSE(MATCH(B$2,{"1. T-12 Actuals","2. My Version","3. Projected","4. Offer"},0),B16,C16,D16,E16),0) -> 0 | H16: Auto-calculated
A17: TOTAL ACQUISITION COST | B17: =IFERROR(B7+IFERROR(VALUE(B12),0)+IFERROR(VALUE(B13),0)+IFERROR(VALUE(B14),0)+IFERROR(VALUE(B16),0),"") -> 0 | C17: =IFERROR(C7+IFERROR(VALUE(C12),0)+IFERROR(VALUE(C13),0)+IFERROR(VALUE(C14),0)+IFERROR(VALUE(C16),0),"") -> 0 | D17: =IFERROR(D7+IFERROR(VALUE(D12),0)+IFERROR(VALUE(D13),0)+IFERROR(VALUE(D14),0)+IFERROR(VALUE(D16),0),"") -> 0 | E17: =IFERROR(E7+IFERROR(VALUE(E12),0)+IFERROR(VALUE(E13),0)+IFERROR(VALUE(E14),0)+IFERROR(VALUE(E16),0),"") -> 0 | F17: =IFERROR(CHOOSE(MATCH(B$2,{"1. T-12 Actuals","2. My Version","3. Projected","4. Offer"},0),B17,C17,D17,E17),0) -> 0 | H17: Auto-calculated total cost
A19: DEBT STRUCTURE
A20: Loan Amount (1st) | B20: =IFERROR(B88,0) -> 0 | C20: =IFERROR(C88,0) -> 0 | D20: =IFERROR(D88,0) -> 0 | E20: =IFERROR(E88,0) -> 0 | F20: =IFERROR(CHOOSE(MATCH(B$2,{"1. T-12 Actuals","2. My Version","3. Projected","4. Offer"},0),B20,C20,D20,E20),0) -> 0 | H20: 65–75% LTV; Agency (FNMA/FHLMC) or CMBS/bridge
A21: Loan Amount (2nd) | B21: =IFERROR(B95,0) -> 0 | C21: =IFERROR(C95,0) -> 0 | D21: =IFERROR(D95,0) -> 0 | E21: =IFERROR(E95,0) -> 0 | F21: =IFERROR(CHOOSE(MATCH(B$2,{"1. T-12 Actuals","2. My Version","3. Projected","4. Offer"},0),B21,C21,D21,E21),0) -> 0 | H21: $0 if no mezz; up to 10% of stack
A22: Supplemental Loan | B22: =IFERROR(B102,0) -> 0 | C22: =IFERROR(C102,0) -> 0 | D22: =IFERROR(D102,0) -> 0 | E22: =IFERROR(E102,0) -> 0 | F22: =IFERROR(CHOOSE(MATCH(B$2,{"1. T-12 Actuals","2. My Version","3. Projected","4. Offer"},0),B22,C22,D22,E22),0) -> 0 | H22: $0 supplemental; add if SBA/seller
A23: Total Debt | B23: =IFERROR(B20+B21+B22,0) -> 0 | C23: =IFERROR(C20+C21+C22,0) -> 0 | D23: =IFERROR(D20+D21+D22,0) -> 0 | E23: =IFERROR(E20+E21+E22,0) -> 0 | F23: =IFERROR(CHOOSE(MATCH(B$2,{"1. T-12 Actuals","2. My Version","3. Projected","4. Offer"},0),B23,C23,D23,E23),0) -> 0 | H23: Auto-calculated total debt
A24: LTV (Loan/Purchase Price) | B24: =IFERROR(IFERROR(B23/B7,0),0) -> 0 | C24: =IFERROR(IFERROR(C23/C7,0),0) -> 0 | D24: =IFERROR(IFERROR(D23/D7,0),0) -> 0 | E24: =IFERROR(IFERROR(E23/E7,0),0) -> 0 | F24: =IFERROR(CHOOSE(MATCH(B$2,{"1. T-12 Actuals","2. My Version","3. Projected","4. Offer"},0),B24,C24,D24,E24),0) -> 0 | H24: Target ≤75% LTV; agency max 80%
A25: LTC (Loan/Total Acq. Cost) | B25: =IFERROR(IFERROR(B23/B17,0),0) -> 0 | C25: =IFERROR(IFERROR(C23/C17,0),0) -> 0 | D25: =IFERROR(IFERROR(D23/D17,0),0) -> 0 | E25: =IFERROR(IFERROR(E23/E17,0),0) -> 0 | F25: =IFERROR(CHOOSE(MATCH(B$2,{"1. T-12 Actuals","2. My Version","3. Projected","4. Offer"},0),B25,C25,D25,E25),0) -> 0 | H25: Target ≤85% LTC (value-add); 75–80% stabilized
A27: EQUITY STRUCTURE
A28: GP Ownership % | B28: 0.3 | C28: 0.3 | D28: =IFERROR(C28,0) -> 0.3 | E28: =IFERROR(D28,0) -> 0.3 | F28: =IFERROR(CHOOSE(MATCH(B$2,{"1. T-12 Actuals","2. My Version","3. Projected","4. Offer"},0),B28,C28,D28,E28),0) -> 0.3 | H28: GP co-invest 5–20% of total equity
A29: Class A LP % | B29: =IFERROR(1-B28,0) -> 0.7 | C29: =IFERROR(1-C28,0) -> 0.7 | D29: =IFERROR(1-D28,0) -> 0.7 | E29: =IFERROR(1-E28,0) -> 0.7 | F29: =IFERROR(CHOOSE(MATCH(B$2,{"1. T-12 Actuals","2. My Version","3. Projected","4. Offer"},0),B29,C29,D29,E29),0) -> 0.7 | H29: Class A LP 40–70% of total equity
A30: Class B LP % (auto) | B30: =IFERROR(1-B28-B29,0) -> 0 | C30: =IFERROR(1-C28-C29,0) -> 0 | D30: =IFERROR(1-D28-D29,0) -> 0 | E30: =IFERROR(1-E28-E29,0) -> 0 | F30: =IFERROR(CHOOSE(MATCH(B$2,{"1. T-12 Actuals","2. My Version","3. Projected","4. Offer"},0),B30,C30,D30,E30),0) -> 0 | H30: Class B LP 20–40% of total equity
A31: Total Equity (Acq Cost − Debt) | B31: =IFERROR(IFERROR(B17-B117,0),0) -> 0 | C31: =IFERROR(IFERROR(C17-C117,0),0) -> 0 | D31: =IFERROR(IFERROR(D17-D117,0),0) -> 0 | E31: =IFERROR(IFERROR(E17-E117,0),0) -> 0 | F31: =IFERROR(CHOOSE(MATCH(B$2,{"1. T-12 Actuals","2. My Version","3. Projected","4. Offer"},0),B31,C31,D31,E31),0) -> 0 | H31: Auto-calculated
A32: GP Equity ($) | B32: 0 | C32: =B32 -> 0 | D32: =C32 -> 0 | E32: =D32 -> 0 | F32: =IFERROR(CHOOSE(MATCH(B$2,{"1. T-12 Actuals","2. My Version","3. Projected","4. Offer"},0),B32,C32,D32,E32),0) -> 0 | H32: Enter GP co-invest $ directly — not tied to GP Ownership %
A33: Class A LP Equity ($) | B33: =IFERROR(B31-B32,0) -> 0 | C33: =IFERROR(C31-C32,0) -> 0 | D33: =IFERROR(D31-D32,0) -> 0 | E33: =IFERROR(E31-E32,0) -> 0 | F33: =IFERROR(CHOOSE(MATCH(B$2,{"1. T-12 Actuals","2. My Version","3. Projected","4. Offer"},0),B33,C33,D33,E33),0) -> 0 | H33: Total Equity − GP co-invest. GP can be $0 (all-LP deal).
A34: Class B LP Equity ($) | B34: =IFERROR(B30*B31,0) -> 0 | C34: =IFERROR(C30*C31,0) -> 0 | D34: =IFERROR(D30*D31,0) -> 0 | E34: =IFERROR(E30*E31,0) -> 0 | F34: =IFERROR(CHOOSE(MATCH(B$2,{"1. T-12 Actuals","2. My Version","3. Projected","4. Offer"},0),B34,C34,D34,E34),0) -> 0 | H34: Auto-calculated
A35: Class A Preferred Return % | F35: =IFERROR(CHOOSE(MATCH(B$2,{"1. T-12 Actuals","2. My Version","3. Projected","4. Offer"},0),B35,C35,D35,E35),0) -> 0 | H35: Class A pref: 6–8% typical MF PE
A36: Class B Preferred Return % | F36: =IFERROR(CHOOSE(MATCH(B$2,{"1. T-12 Actuals","2. My Version","3. Projected","4. Offer"},0),B36,C36,D36,E36),0) -> 0 | H36: Class B pref (subordinated); 0 if no Class B equity
A37: GP Promote % (defaults to GP% — edit to override) | B37: =IFERROR(B28,0) -> 0.3 | C37: =IFERROR(C28,0) -> 0.3 | D37: =IFERROR(D28,0) -> 0.3 | E37: =IFERROR(E28,0) -> 0.3 | F37: =IFERROR(CHOOSE(MATCH(B$2,{"1. T-12 Actuals","2. My Version","3. Projected","4. Offer"},0),B37,C37,D37,E37),0) -> 0.3 | H37: Promote: 20–30% GP typical
A38: INCOME (YEAR 1 SNAPSHOT) — Revenue is per UNIT, not per bed
A39: Avg Monthly Rent / Unit (at 100% occupancy) | B39: =IFERROR(C39,0) -> 0 | C39: =IFERROR(IFERROR(IF('T-12 Analysis'!N58>=MAX('Rent Roll Analysis'!B26,'Rent Roll Analysis'!B34)*0.95,'T-12 Analysis'!N58,MAX('Rent Roll Analysis'!B26,'Rent Roll Analysis'!B34))/12/'Prop Info'!$B$6,0),0) -> 0 | D39: =IFERROR('Rent Roll Analysis'!C34,0) -> 0 | E39: =IFERROR(D39,0) -> 0 | F39: =IFERROR(CHOOSE(MATCH(B$2,{"1. T-12 Actuals","2. My Version","3. Projected","4. Offer"},0),B39,C39,D39,E39),0) -> 0 | H39: Avg rent × total units × 12 = max revenue potential | I39: C38 benchmark = MAX(RR Market GPR, Occupied Scheduled GPR). If residents pay above listed market rent, occupied scheduled is the truer market. T-12 credibility check and fallback both use this MAX. B38 = T-12 actuals (unchanged).
A40: Gross Potential Rent (at 100% unit occupancy) | B40: =IFERROR('Prop Info'!$B$6*B39*12,0) -> 0 | C40: =IFERROR('Prop Info'!$B$6*C39*12,0) -> 0 | D40: =IFERROR('Prop Info'!$B$6*D39*12,0) -> 0 | E40: =IFERROR('Prop Info'!$B$6*E39*12,0) -> 0 | F40: =IFERROR(CHOOSE(MATCH(B$2,{"1. T-12 Actuals","2. My Version","3. Projected","4. Offer"},0),B40,C40,D40,E40),0) -> 0 | H40: Units × avg rent × 12 — maximum revenue at 100% occupancy
A41: Unit Vacancy % (unoccupied units ÷ total units) | B41: =IFERROR(C41,0) -> 0 | C41: =IFERROR(IFERROR(('Rent Roll Analysis'!B13+'Rent Roll Analysis'!B14)/'Prop Info'!$B$6,0),0) -> 0 | D41: =IFERROR(C41,0) -> 0 | E41: =IFERROR(D41,0) -> 0 | F41: =IFERROR(CHOOSE(MATCH(B$2,{"1. T-12 Actuals","2. My Version","3. Projected","4. Offer"},0),B41,C41,D41,E41),0) -> 0 | H41: Class A target 5–8%; value-add 10–15% at acquisition
A42: Vacancy ($) | B42: =IFERROR(-B41*B40,0) -> 0 | C42: =IFERROR(-C41*C40,0) -> 0 | D42: =IFERROR(-D41*D40,0) -> 0 | E42: =IFERROR(-E41*E40,0) -> 0 | F42: =IFERROR(CHOOSE(MATCH(B$2,{"1. T-12 Actuals","2. My Version","3. Projected","4. Offer"},0),B42,C42,D42,E42),0) -> 0
A43: Other Revenue Adj % (Down/Employee Units, Prepaid Rent change) | B43: =IFERROR(IFERROR(B44/B40,0),0) -> 0 | D43: =IFERROR(C43,0) -> 0 | E43: =IFERROR(D43,0) -> 0 | F43: =IFERROR(CHOOSE(MATCH(B$2,{"1. T-12 Actuals","2. My Version","3. Projected","4. Offer"},0),B43,C43,D43,E43),0) -> 0 | H43: 1–3% loss to lease typical MF
A44: Other Revenue Adj ($) | B44: =IFERROR(C44,0) -> 0 | C44: =IFERROR(-C43*C40,0) -> 0 | D44: =IFERROR(-D43*D40,0) -> 0 | E44: =IFERROR(-E43*E40,0) -> 0 | F44: =IFERROR(CHOOSE(MATCH(B$2,{"1. T-12 Actuals","2. My Version","3. Projected","4. Offer"},0),B44,C44,D44,E44),0) -> 0
A45: Concessions / Bad Debt % | B45: =IFERROR(ABS('T-12 Analysis'!N63+'T-12 Analysis'!N64+'T-12 Analysis'!N65+'T-12 Analysis'!N59)/'T-12 Analysis'!N58,0) -> 0 | C45: =IFERROR(B45,0) -> 0 | D45: =IFERROR(C45,0) -> 0 | E45: =IFERROR(D45,0) -> 0 | F45: =IFERROR(CHOOSE(MATCH(B$2,{"1. T-12 Actuals","2. My Version","3. Projected","4. Offer"},0),B45,C45,D45,E45),0) -> 0 | H45: 0.5–2% bad debt/concessions
A46: Concessions / Bad Debt ($) | B46: =IFERROR(-B45*B40,0) -> 0 | C46: =IFERROR(-C45*C40,0) -> 0 | D46: =IFERROR(-D45*D40,0) -> 0 | E46: =IFERROR(-E45*E40,0) -> 0 | F46: =IFERROR(CHOOSE(MATCH(B$2,{"1. T-12 Actuals","2. My Version","3. Projected","4. Offer"},0),B46,C46,D46,E46),0) -> 0
A47: Parking Revenue % (of GPR; use 0 if surface/free) | B47: =IFERROR('T-12 Analysis'!N73/'T-12 Analysis'!N58,0) -> 0 | C47: 0 | D47: =IFERROR(C47,0) -> 0 | E47: =IFERROR(D47,0) -> 0 | F47: =IFERROR(CHOOSE(MATCH(B$2,{"1. T-12 Actuals","2. My Version","3. Projected","4. Offer"},0),B47,C47,D47,E47),0) -> 0 | H47: Covered/garage: 1–3% of GPR
A48: Parking Revenue ($) | B48: =IFERROR(B47*B40,0) -> 0 | C48: =IFERROR(C47*C40,0) -> 0 | D48: =IFERROR(D47*D40,0) -> 0 | E48: =IFERROR(E47*E40,0) -> 0 | F48: =IFERROR(CHOOSE(MATCH(B$2,{"1. T-12 Actuals","2. My Version","3. Projected","4. Offer"},0),B48,C48,D48,E48),0) -> 0 | H48: Or enter flat $ (e.g. # spaces × $100/mo × 12)
A49: Other Income (T-12 base + Committed Recapture — Year 1) | B49: =IFERROR('T-12 Analysis'!N79,0) -> 0 | C49: =IFERROR('T-12 Analysis'!N79+'Recapture & Upside'!L84,0) -> 0 | D49: =IFERROR('T-12 Analysis'!N79+'Recapture & Upside'!L84,0) -> 0 | E49: =IFERROR('T-12 Analysis'!N79+'Recapture & Upside'!L84,0) -> 0 | F49: =IFERROR(CHOOSE(MATCH(B$2,{"1. T-12 Actuals","2. My Version","3. Projected","4. Offer"},0),B49,C49,D49,E49),0) -> 0
A50: EFFECTIVE GROSS INCOME | B50: =IFERROR(VALUE(IF(B40="",0,B40))+VALUE(IF(B42="",0,B42))+VALUE(IF(B44="",0,B44))+VALUE(IF(B46="",0,B46))+VALUE(IF(B48="",0,B48))+VALUE(IF(B49="",0,B49)),0) -> 0 | C50: =IFERROR(VALUE(IF(C40="",0,C40))+VALUE(IF(C42="",0,C42))+VALUE(IF(C44="",0,C44))+VALUE(IF(C46="",0,C46))+VALUE(IF(C48="",0,C48))+VALUE(IF(C49="",0,C49)),0) -> 0 | D50: =IFERROR(VALUE(IF(D40="",0,D40))+VALUE(IF(D42="",0,D42))+VALUE(IF(D44="",0,D44))+VALUE(IF(D46="",0,D46))+VALUE(IF(D48="",0,D48))+VALUE(IF(D49="",0,D49)),0) -> 0 | E50: =IFERROR(VALUE(IF(E40="",0,E40))+VALUE(IF(E42="",0,E42))+VALUE(IF(E44="",0,E44))+VALUE(IF(E46="",0,E46))+VALUE(IF(E48="",0,E48))+VALUE(IF(E49="",0,E49)),0) -> 0 | F50: =IFERROR(CHOOSE(MATCH(B$2,{"1. T-12 Actuals","2. My Version","3. Projected","4. Offer"},0),B50,C50,D50,E50),0) -> 0
A51: ↳ Occupied Units (units × (1 − vacancy%)) | B51: =IFERROR(IFERROR(ROUND('Prop Info'!$B$6*(1-B41),0),0),0) -> 0 | C51: =IFERROR(IFERROR(ROUND('Prop Info'!$B$6*(1-C41),0),0),0) -> 0 | D51: =IFERROR(IFERROR(ROUND('Prop Info'!$B$6*(1-D41),0),0),0) -> 0 | E51: =IFERROR(IFERROR(ROUND('Prop Info'!$B$6*(1-E41),0),0),0) -> 0 | F51: =IFERROR(CHOOSE(MATCH(B$2,{"1. T-12 Actuals","2. My Version","3. Projected","4. Offer"},0),B51,C51,D51,E51),0) -> 0 | H51: Total units × occupancy% — revenue-generating units
A52: EXPENSES (YEAR 1)
A53: Line Item | B53: 1. T-12 Actuals | C53: 2. My Versio | D53: 3. Projected | E53: 4. Offer | F53: Active | G53: $/Bed | % EGI | H53: Notes
A54: Leasing & Marketing | B54: =IFERROR('T-12 Analysis'!N89,0) -> 0 | C54: =IFERROR(B54,0) -> 0 | D54: =IFERROR(C54,0) -> 0 | E54: =IFERROR(D54,0) -> 0 | F54: =IFERROR(CHOOSE(MATCH(B$2,{"1. T-12 Actuals","2. My Version","3. Projected","4. Offer"},0),B54,C54,D54,E54),0) -> 0 | G54: =IFERROR(IF((IFERROR(TEXT(F54/'Prop Info'!$B$6,"$#,##0")&"/Unit | "&TEXT(F54/F50,"0.0%"),""))=0,"",(IFERROR(TEXT(F54/'Prop Info'!$B$6,"$#,##0")&"/Unit | "&TEXT(F54/F50,"0.0%"),""))),"") | H54: $350–800/unit; Class A 1–2% EGI
A55: Grounds / Landscaping | B55: =IFERROR('T-12 Analysis'!N84,0) -> 0 | C55: =IFERROR(B55,0) -> 0 | D55: =IFERROR(C55,0) -> 0 | E55: =IFERROR(D55,0) -> 0 | F55: =IFERROR(CHOOSE(MATCH(B$2,{"1. T-12 Actuals","2. My Version","3. Projected","4. Offer"},0),B55,C55,D55,E55),0) -> 0 | G55: =IFERROR(IF((IFERROR(TEXT(F55/'Prop Info'!$B$6,"$#,##0")&"/Unit | "&TEXT(F55/F50,"0.0%"),""))=0,"",(IFERROR(TEXT(F55/'Prop Info'!$B$6,"$#,##0")&"/Unit | "&TEXT(F55/F50,"0.0%"),""))),"") | H55: $300–700/unit; landscapes scale with unit count | I55: added landscaping and sanitation together
A56: Gas & Electric (common areas) | B56: =IFERROR('T-12 Analysis'!N94+'T-12 Analysis'!N95,0) -> 0 | C56: =IFERROR(B56,0) -> 0 | D56: =IFERROR(C56,0) -> 0 | E56: =IFERROR(D56,0) -> 0 | F56: =IFERROR(CHOOSE(MATCH(B$2,{"1. T-12 Actuals","2. My Version","3. Projected","4. Offer"},0),B56,C56,D56,E56),0) -> 0 | G56: =IFERROR(IF((IFERROR(TEXT(F56/'Prop Info'!$B$6,"$#,##0")&"/Unit | "&TEXT(F56/F50,"0.0%"),""))=0,"",(IFERROR(TEXT(F56/'Prop Info'!$B$6,"$#,##0")&"/Unit | "&TEXT(F56/F50,"0.0%"),""))),"") | H56: $600–1,200/unit (common area electric + gas)
A57: General / Admin | B57: =IFERROR('T-12 Analysis'!N90+'T-12 Analysis'!N98,0) -> 0 | C57: =IFERROR(B57,0) -> 0 | D57: =IFERROR(C57,0) -> 0 | E57: =IFERROR(D57,0) -> 0 | F57: =IFERROR(CHOOSE(MATCH(B$2,{"1. T-12 Actuals","2. My Version","3. Projected","4. Offer"},0),B57,C57,D57,E57),0) -> 0 | G57: =IFERROR(IF((IFERROR(TEXT(F57/'Prop Info'!$B$6,"$#,##0")&"/Unit | "&TEXT(F57/F50,"0.0%"),""))=0,"",(IFERROR(TEXT(F57/'Prop Info'!$B$6,"$#,##0")&"/Unit | "&TEXT(F57/F50,"0.0%"),""))),"") | H57: $200–500/unit; scales with property size
A58: Insurance | B58: =IFERROR('T-12 Analysis'!N92,0) -> 0 | C58: =IFERROR(B58,0) -> 0 | D58: =IFERROR(C58,0) -> 0 | E58: =IFERROR(D58,0) -> 0 | F58: =IFERROR(CHOOSE(MATCH(B$2,{"1. T-12 Actuals","2. My Version","3. Projected","4. Offer"},0),B58,C58,D58,E58),0) -> 0 | G58: =IFERROR(IF((IFERROR(TEXT(F58/'Prop Info'!$B$6,"$#,##0")&"/Unit | "&TEXT(F58/F50,"0.0%"),""))=0,"",(IFERROR(TEXT(F58/'Prop Info'!$B$6,"$#,##0")&"/Unit | "&TEXT(F58/F50,"0.0%"),""))),"") | H58: $800–1,500/unit; Class A higher, earthquake/flood add-ons
A59: Legal | B59: =IFERROR('T-12 Analysis'!N91,0) -> 0 | C59: =IFERROR(B59,0) -> 0 | D59: =IFERROR(C59,0) -> 0 | E59: =IFERROR(D59,0) -> 0 | F59: =IFERROR(CHOOSE(MATCH(B$2,{"1. T-12 Actuals","2. My Version","3. Projected","4. Offer"},0),B59,C59,D59,E59),0) -> 0 | G59: =IFERROR(IF((IFERROR(TEXT(F59/'Prop Info'!$B$6,"$#,##0")&"/Unit | "&TEXT(F59/F50,"0.0%"),""))=0,"",(IFERROR(TEXT(F59/'Prop Info'!$B$6,"$#,##0")&"/Unit | "&TEXT(F59/F50,"0.0%"),""))),"") | H59: $150–400/unit; HOA/entity legal
A60: Real Estate Taxes | B60: =IFERROR('T-12 Analysis'!N93,0) -> 0 | C60: =IFERROR(B60,0) -> 0 | D60: =IFERROR(C60,0) -> 0 | E60: =IFERROR(D60,0) -> 0 | F60: =IFERROR(CHOOSE(MATCH(B$2,{"1. T-12 Actuals","2. My Version","3. Projected","4. Offer"},0),B60,C60,D60,E60),0) -> 0 | G60: =IFERROR(IF((IFERROR(TEXT(F60/'Prop Info'!$B$6,"$#,##0")&"/Unit | "&TEXT(F60/F50,"0.0%"),""))=0,"",(IFERROR(TEXT(F60/'Prop Info'!$B$6,"$#,##0")&"/Unit | "&TEXT(F60/F50,"0.0%"),""))),"") | H60: $800–2,500/unit; varies by jurisdiction and assessment
A61: Trash Removal | B61: =IFERROR('T-12 Analysis'!N97,0) -> 0 | C61: =IFERROR(B61,0) -> 0 | D61: =IFERROR(C61,0) -> 0 | E61: =IFERROR(D61,0) -> 0 | F61: =IFERROR(CHOOSE(MATCH(B$2,{"1. T-12 Actuals","2. My Version","3. Projected","4. Offer"},0),B61,C61,D61,E61),0) -> 0 | G61: =IFERROR(IF((IFERROR(TEXT(F61/'Prop Info'!$B$6,"$#,##0")&"/Unit | "&TEXT(F61/F50,"0.0%"),""))=0,"",(IFERROR(TEXT(F61/'Prop Info'!$B$6,"$#,##0")&"/Unit | "&TEXT(F61/F50,"0.0%"),""))),"") | H61: $100–250/unit; per-unit trash / valet waste
A62: Management Fee (% of EGI) | B62: =IFERROR('T-12 Analysis'!N99,0) -> 0 | C62: =IFERROR(C50*0.05,0) -> 0 | D62: =IFERROR(D50*0.05,0) -> 0 | E62: =IFERROR(E50*0.05,0) -> 0 | F62: =IFERROR(CHOOSE(MATCH(B$2,{"1. T-12 Actuals","2. My Version","3. Projected","4. Offer"},0),B62,C62,D62,E62),0) -> 0 | G62: =IFERROR(IF((IFERROR(TEXT(F62/'Prop Info'!$B$6,"$#,##0")&"/Unit | "&TEXT(F62/F50,"0.0%"),""))=0,"",(IFERROR(TEXT(F62/'Prop Info'!$B$6,"$#,##0")&"/Unit | "&TEXT(F62/F50,"0.0%"),""))),"") | H62: 4–6% EGI typical MF; 3.5% large portfolios
A63: On-Site Payroll (from Staffing) | B63: =IFERROR('T-12 Analysis'!N88,0) -> 0 | C63: =IFERROR(IFERROR(Total_Payroll,0),0) -> 0 | D63: =IFERROR(IFERROR(Total_Payroll,0),0) -> 0 | E63: =IFERROR(IFERROR(Total_Payroll,0),0) -> 0 | F63: =IFERROR(CHOOSE(MATCH(B$2,{"1. T-12 Actuals","2. My Version","3. Projected","4. Offer"},0),B63,C63,D63,E63),0) -> 0 | G63: =IFERROR(IF((IFERROR(TEXT(F63/'Prop Info'!$B$6,"$#,##0")&"/Unit | "&TEXT(F63/F50,"0.0%"),""))=0,"",(IFERROR(TEXT(F63/'Prop Info'!$B$6,"$#,##0")&"/Unit | "&TEXT(F63/F50,"0.0%"),""))),"") | H63: From staffing model — scales with unit count
A64: Repairs & Maintenance | B64: =IFERROR('T-12 Analysis'!N82+'T-12 Analysis'!N85,0) -> 0 | C64: =IFERROR(B64,0) -> 0 | D64: =IFERROR(C64,0) -> 0 | E64: =IFERROR(D64,0) -> 0 | F64: =IFERROR(CHOOSE(MATCH(B$2,{"1. T-12 Actuals","2. My Version","3. Projected","4. Offer"},0),B64,C64,D64,E64),0) -> 0 | G64: =IFERROR(IF((IFERROR(TEXT(F64/'Prop Info'!$B$6,"$#,##0")&"/Unit | "&TEXT(F64/F50,"0.0%"),""))=0,"",(IFERROR(TEXT(F64/'Prop Info'!$B$6,"$#,##0")&"/Unit | "&TEXT(F64/F50,"0.0%"),""))),"") | H64: $400–900/unit; value-add higher in stabilization
A65: Contract Services | B65: =IFERROR('T-12 Analysis'!N83,0) -> 0 | C65: =IFERROR(B65,0) -> 0 | D65: =IFERROR(C65,0) -> 0 | E65: =IFERROR(D65,0) -> 0 | F65: =IFERROR(CHOOSE(MATCH(B$2,{"1. T-12 Actuals","2. My Version","3. Projected","4. Offer"},0),B65,C65,D65,E65),0) -> 0
A66: Make-Ready / Turnover | B66: =IFERROR('T-12 Analysis'!N87,0) -> 0 | C66: =IFERROR(B66,0) -> 0 | D66: =IFERROR(C66,0) -> 0 | E66: =IFERROR(D66,0) -> 0 | F66: =IFERROR(CHOOSE(MATCH(B$2,{"1. T-12 Actuals","2. My Version","3. Projected","4. Offer"},0),B66,C66,D66,E66),0) -> 0 | G66: =IFERROR(IF((IFERROR(TEXT(F66/'Prop Info'!$B$6,"$#,##0")&"/Unit | "&TEXT(F66/F50,"0.0%"),""))=0,"",(IFERROR(TEXT(F66/'Prop Info'!$B$6,"$#,##0")&"/Unit | "&TEXT(F66/F50,"0.0%"),""))),"") | H66: $300–800/unit; depends on turnover rate and finish level
A67: Water & Sewer | B67: =IFERROR('T-12 Analysis'!N96,0) -> 0 | C67: =IFERROR(B67,0) -> 0 | D67: =IFERROR(C67,0) -> 0 | E67: =IFERROR(D67,0) -> 0 | F67: =IFERROR(CHOOSE(MATCH(B$2,{"1. T-12 Actuals","2. My Version","3. Projected","4. Offer"},0),B67,C67,D67,E67),0) -> 0 | G67: =IFERROR(IF((IFERROR(TEXT(F67/'Prop Info'!$B$6,"$#,##0")&"/Unit | "&TEXT(F67/F50,"0.0%"),""))=0,"",(IFERROR(TEXT(F67/'Prop Info'!$B$6,"$#,##0")&"/Unit | "&TEXT(F67/F50,"0.0%"),""))),"") | H67: $400–1,000/unit; master-metered typical
A68: Amenity Maintenance (Pool/Gym/Lounge) | B68: =IFERROR('T-12 Analysis'!N86,0) -> 0 | C68: =IFERROR(B68,0) -> 0 | D68: =IFERROR(C68,0) -> 0 | E68: =IFERROR(D68,0) -> 0 | F68: =IFERROR(CHOOSE(MATCH(B$2,{"1. T-12 Actuals","2. My Version","3. Projected","4. Offer"},0),B68,C68,D68,E68),0) -> 0 | G68: =IFERROR(IF((IFERROR(TEXT(F68/'Prop Info'!$B$6,"$#,##0")&"/Unit | "&TEXT(F68/F50,"0.0%"),""))=0,"",(IFERROR(TEXT(F68/'Prop Info'!$B$6,"$#,##0")&"/Unit | "&TEXT(F68/F50,"0.0%"),""))),"") | H68: $200–600/unit; Class A pool/gym/lounge maintenance
A69: CapEx / Replacement Reserve | C69: =IFERROR(B69,0) -> 0 | D69: =IFERROR(C69,0) -> 0 | E69: =IFERROR(D69,0) -> 0 | F69: =IFERROR(CHOOSE(MATCH(B$2,{"1. T-12 Actuals","2. My Version","3. Projected","4. Offer"},0),B69,C69,D69,E69),0) -> 0 | G69: =IFERROR(IF((IFERROR(TEXT(F69/'Prop Info'!$B$6,"$#,##0")&"/Unit | "&TEXT(F69/F50,"0.0%"),""))=0,"",(IFERROR(TEXT(F69/'Prop Info'!$B$6,"$#,##0")&"/Unit | "&TEXT(F69/F50,"0.0%"),""))),"") | H69: $200–400/unit; Class A use $350–500/unit
A70: TOTAL EXPENSES | B70: =IFERROR(SUM(B54:B69),0) -> 0 | C70: =IFERROR(SUM(C54:C69),0) -> 0 | D70: =IFERROR(SUM(D54:D69),0) -> 0 | E70: =IFERROR(SUM(E54:E69),0) -> 0 | F70: =IFERROR(CHOOSE(MATCH(B$2,{"1. T-12 Actuals","2. My Version","3. Projected","4. Offer"},0),B70,C70,D70,E70),0) -> 0 | G70: =IFERROR(IF((IFERROR(TEXT(F70/'Prop Info'!$B$6,"$#,##0")&"/Unit | "&TEXT(F70/F50,"0.0%"),""))=0,"",(IFERROR(TEXT(F70/'Prop Info'!$B$6,"$#,##0")&"/Unit | "&TEXT(F70/F50,"0.0%"),""))),"")
A72: NET OPERATING INCOME | B72: =IFERROR(B50-B70,0) -> 0 | C72: =IFERROR(C50-C70,0) -> 0 | D72: =IFERROR(D50-D70,0) -> 0 | E72: =IFERROR(E50-E70,0) -> 0 | F72: =IFERROR(CHOOSE(MATCH(B$2,{"1. T-12 Actuals","2. My Version","3. Projected","4. Offer"},0),B72,C72,D72,E72),0) -> 0 | G72: =IFERROR(IF((IFERROR(TEXT(F72/'Prop Info'!$B$15,"$#,##0")&"/Bed | "&TEXT(F72/F50,"0.0%"),""))=0,"",(IFERROR(TEXT(F72/'Prop Info'!$B$15,"$#,##0")&"/Bed | "&TEXT(F72/F50,"0.0%"),""))),"")
A74: DEAL SUMMARY METRICS
A75: Cap Rate (NOI/Purchase Price) | B75: =IFERROR(IFERROR(B72/B7,0),0) -> 0 | C75: =IFERROR(IFERROR(C72/C7,0),0) -> 0 | D75: =IFERROR(IFERROR(D72/D7,0),0) -> 0 | E75: =IFERROR(IFERROR(E72/E7,0),0) -> 0 | F75: =IFERROR(CHOOSE(MATCH(B$2,{"1. T-12 Actuals","2. My Version","3. Projected","4. Offer"},0),B75,C75,D75,E75),0) -> 0
A76: Debt Service (Annual) | B76: =IFERROR(B115,0) -> 0 | C76: =IFERROR(C115,0) -> 0 | D76: =IFERROR(D115,0) -> 0 | E76: =IFERROR(E115,0) -> 0 | F76: =IFERROR(CHOOSE(MATCH(B$2,{"1. T-12 Actuals","2. My Version","3. Projected","4. Offer"},0),B76,C76,D76,E76),0) -> 0 | H76: DSCR target ≥1.20x; watch Y1
A77: Cash Flow After Debt Service | B77: =IFERROR(B72-B76,0) -> 0 | C77: =IFERROR(C72-C76,0) -> 0 | D77: =IFERROR(D72-D76,0) -> 0 | E77: =IFERROR(E72-E76,0) -> 0 | F77: =IFERROR(CHOOSE(MATCH(B$2,{"1. T-12 Actuals","2. My Version","3. Projected","4. Offer"},0),B77,C77,D77,E77),0) -> 0 | H77: Positive Y2+ for value-add
A78: Debt Coverage Ratio | B78: =IFERROR(IFERROR(B72/B76,0),0) -> 0 | C78: =IFERROR(IFERROR(C72/C76,0),0) -> 0 | D78: =IFERROR(IFERROR(D72/D76,0),0) -> 0 | E78: =IFERROR(IFERROR(E72/E76,0),0) -> 0 | F78: =IFERROR(CHOOSE(MATCH(B$2,{"1. T-12 Actuals","2. My Version","3. Projected","4. Offer"},0),B78,C78,D78,E78),0) -> 0 | H78: ≥1.20x required; ≥1.25x agency underwriting
A79: Market Cap Rate | C79: =IFERROR(B79,0) -> 0 | D79: =IFERROR(C79,0) -> 0 | E79: =IFERROR(D79,0) -> 0 | F79: =IFERROR(CHOOSE(MATCH(B$2,{"1. T-12 Actuals","2. My Version","3. Projected","4. Offer"},0),B79,C79,D79,E79),0) -> 0 | H79: 4.5–6.5% MF cap rate; Class A metro lower end
A80: Fair Market Value (NOI/Mkt Cap) | B80: =IFERROR(IFERROR(B72/B79,0),0) -> 0 | C80: =IFERROR(IFERROR(C72/C79,0),0) -> 0 | D80: =IFERROR(IFERROR(D72/D79,0),0) -> 0 | E80: =IFERROR(IFERROR(E72/E79,0),0) -> 0 | F80: =IFERROR(CHOOSE(MATCH(B$2,{"1. T-12 Actuals","2. My Version","3. Projected","4. Offer"},0),B80,C80,D80,E80),0) -> 0
A81: As-Is Appraised Value | B81: =IFERROR(B7,0) -> 0 | C81: =IFERROR(C7,0) -> 0 | D81: =IFERROR(D7,0) -> 0 | E81: =IFERROR(E7,0) -> 0 | F81: =IFERROR(CHOOSE(MATCH(B$2,{"1. T-12 Actuals","2. My Version","3. Projected","4. Offer"},0),B81,C81,D81,E81),0) -> 0 | H81: Lender as-is appraisal input (per scenario). Enter 0 to default to FMV (row 78). LTV row 117 uses IFERROR(this, FMV).
A82: Exit Year | C82: =IFERROR(B82,0) -> 0 | D82: =IFERROR(C82,0) -> 0 | E82: =IFERROR(D82,0) -> 0 | F82: =IFERROR(CHOOSE(MATCH(B$2,{"1. T-12 Actuals","2. My Version","3. Projected","4. Offer"},0),B82,C82,D82,E82),0) -> 0 | H82: Hold: 3–7 years typical value-add PE
A83: Exit Cap Rate | C83: =IFERROR(B83,0) -> 0 | D83: =IFERROR(C83,0) -> 0 | E83: =IFERROR(D83,0) -> 0 | F83: =IFERROR(CHOOSE(MATCH(B$2,{"1. T-12 Actuals","2. My Version","3. Projected","4. Offer"},0),B83,C83,D83,E83),0) -> 0 | H83: Exit cap: entry + 25–75 bps; buyer-driven compression in Class A
A85: DEBT STRUCTURE — PER-SCENARIO LOAN INPUTS (drives Loans, Waterfall & P&L)
A86: Blue = input per scenario. Active scenario col F feeds all downstream sheets. Use $0 for unused tranches.
A87: 1ST LOAN — SENIOR / PRIMARY
A88: Loan Amount — 1st ($) | B88: =IFERROR(IF(B120="YES",B17*(1-B10),B7*(1-B10)),0) -> 0 | C88: =IFERROR(IF(C120="YES",C17*(1-C10),C7*(1-C10)),0) -> 0 | D88: =IFERROR(IF(D120="YES",D17*(1-D10),D7*(1-D10)),0) -> 0 | E88: =IFERROR(IF(E120="YES",E17*(1-E10),E7*(1-E10)),0) -> 0 | F88: =IFERROR(CHOOSE(MATCH(B$2,{"1. T-12 Actuals","2. My Version","3. Projected","4. Offer"},0),B88,C88,D88,E88),0) -> 0 | H88: 60–70% LTV first lien; $0 to disable
A89: Interest Rate — 1st (%) | C89: =B89 -> 0 | D89: =C89 -> 0 | E89: =D89 -> 0 | F89: =IFERROR(CHOOSE(MATCH(B$2,{"1. T-12 Actuals","2. My Version","3. Projected","4. Offer"},0),B89,C89,D89,E89),0) -> 0 | H89: Bridge: 6–8%; Agency FNMA/FHLMC: 5–6.5%
A90: Amortization (years) — 1st | C90: =B90 -> 0 | D90: =C90 -> 0 | E90: =D90 -> 0 | F90: =IFERROR(CHOOSE(MATCH(B$2,{"1. T-12 Actuals","2. My Version","3. Projected","4. Offer"},0),B90,C90,D90,E90),0) -> 0 | H90: 25–30yr amortization standard; IO period common
A91: Loan Term (years) — 1st | C91: =B91 -> 0 | D91: =C91 -> 0 | E91: =D91 -> 0 | F91: =IFERROR(CHOOSE(MATCH(B$2,{"1. T-12 Actuals","2. My Version","3. Projected","4. Offer"},0),B91,C91,D91,E91),0) -> 0 | H91: Match hold period
A92: Interest-Only Period (months) — 1st | C92: =B92 -> 0 | D92: =C92 -> 0 | E92: =D92 -> 0 | F92: =IFERROR(CHOOSE(MATCH(B$2,{"1. T-12 Actuals","2. My Version","3. Projected","4. Offer"},0),B92,C92,D92,E92),0) -> 0 | H92: IO 0–24 months; 0=fully amortizing
A93: Origination Fee % — 1st | B93: 0.01 | C93: 0.01 | D93: =IFERROR(C93,0) -> 0.01 | E93: =IFERROR(D93,0) -> 0.01 | F93: =IFERROR(CHOOSE(MATCH(B$2,{"1. T-12 Actuals","2. My Version","3. Projected","4. Offer"},0),B93,C93,D93,E93),0) -> 0.01 | H93: 0.5–1.5% origination; 1–2% bridge
A94: 2ND LOAN — MEZZANINE / BRIDGE
A95: Loan Amount — 2nd ($) | C95: 0 | F95: =IFERROR(CHOOSE(MATCH(B$2,{"1. T-12 Actuals","2. My Version","3. Projected","4. Offer"},0),B95,C95,D95,E95),0) -> 0 | H95: $0 if no mezz; up to 10% of stack
A96: Interest Rate — 2nd (%) | C96: 0 | F96: =IFERROR(CHOOSE(MATCH(B$2,{"1. T-12 Actuals","2. My Version","3. Projected","4. Offer"},0),B96,C96,D96,E96),0) -> 0 | H96: Mezz: 8–12% typical
A97: Amortization (years) — 2nd | C97: 0 | F97: =IFERROR(CHOOSE(MATCH(B$2,{"1. T-12 Actuals","2. My Version","3. Projected","4. Offer"},0),B97,C97,D97,E97),0) -> 0
A98: Loan Term (years) — 2nd | C98: 0 | F98: =IFERROR(CHOOSE(MATCH(B$2,{"1. T-12 Actuals","2. My Version","3. Projected","4. Offer"},0),B98,C98,D98,E98),0) -> 0
A99: Interest-Only Period (months) — 2nd | C99: 0 | F99: =IFERROR(CHOOSE(MATCH(B$2,{"1. T-12 Actuals","2. My Version","3. Projected","4. Offer"},0),B99,C99,D99,E99),0) -> 0
A100: Origination Fee % — 2nd | B100: 0 | C100: 0 | D100: =IFERROR(C100,0) -> 0 | E100: =IFERROR(D100,0) -> 0 | F100: =IFERROR(CHOOSE(MATCH(B$2,{"1. T-12 Actuals","2. My Version","3. Projected","4. Offer"},0),B100,C100,D100,E100),0) -> 0 | H100: 0.5–1.5% origination; 1–2% bridge
A101: SUPPLEMENTAL — SBA / SELLER CARRY
A102: Loan Amount — Supplemental ($) | C102: 0 | F102: =IFERROR(CHOOSE(MATCH(B$2,{"1. T-12 Actuals","2. My Version","3. Projected","4. Offer"},0),B102,C102,D102,E102),0) -> 0 | H102: $0 if no supplemental tranche
A103: Interest Rate — Supplemental (%) | C103: 0 | F103: =IFERROR(CHOOSE(MATCH(B$2,{"1. T-12 Actuals","2. My Version","3. Projected","4. Offer"},0),B103,C103,D103,E103),0) -> 0
A104: Amortization (years) — Supplemental | C104: 0 | F104: =IFERROR(CHOOSE(MATCH(B$2,{"1. T-12 Actuals","2. My Version","3. Projected","4. Offer"},0),B104,C104,D104,E104),0) -> 0
A105: Loan Term (years) — Supplemental | C105: 0 | F105: =IFERROR(CHOOSE(MATCH(B$2,{"1. T-12 Actuals","2. My Version","3. Projected","4. Offer"},0),B105,C105,D105,E105),0) -> 0
...

Sheet Acquisition Costs
A1: =IF('Prop Info'!B4="","ACQUISITION COSTS — USE OF CAPITAL","ACQUISITION COSTS — USE OF CAPITAL"&" — "&'Prop Info'!B4) -> ACQUISITION COSTS — USE OF CAPITAL
A3: USE OF CAPITAL SUMMARY
A4: Purchase Price | D4: =Scenarios!F7 -> 0
A5: Less: Total Loan Amount | D5: =-Scenarios!F116 -> 0
A6: Down Payment Required | D6: =D4+D5 -> 0
A7: Closing Costs | D7: =D35 -> 0
A8: Acquisition Fee | B8: =Scenarios!F15 -> 0.02 | D8: =Scenarios!F16 -> 0
A9: Repair Escrow / CapEx | D9: =Scenarios!F12 -> 0
A10: Operating Reserves | D10: =IFERROR(Scenarios!F13,0) -> 0
A11: TOTAL CASH AT CLOSE | D11: =SUM(D6:D10) -> 0
A13: CLOSING COSTS DETAIL
A14: Item | B14: Rate/Factor | C14: Notes | D14: Amount
A15: LENDER FEES & THIRD-PARTY COSTS
A16: Environmental (EDR) | C16: Phase I ESA — flat fee | D16: 3500
A17: Appraisal | C17: Commercial appraisal — flat fee | D17: 6500
A18: Structural Inspection | C18: PCA / structural — flat fee | D18: 4500
A19: Lender Legal Fees | C19: Lender counsel — flat fee | D19: 15000
A20: Bank Doc Prep Fee | C20: Lender doc prep — flat fee | D20: 2500
A21: Origination Fee | B21: =Loans!B9 -> 0.01 | C21: Total origination fees — all tranches | D21: =Loans!E10 -> 0
A22: TITLE & CLOSING COSTS
A23: Title Policy | B23: 0.003 | C23: 0.30% of purchase price | D23: =B23*Scenarios!F7 -> 0
A24: Survey | C24: ALTA survey — flat fee | D24: 5000
A25: Recording | C25: Recording fees — flat fee | D25: 1500
A26: Transfer Taxes | B26: 0.0035 | C26: 0.35% of purchase price | D26: =B26*Scenarios!F7 -> 0
A27: Title Processing Fee | C27: Title processing — flat fee | D27: 750
A28: Title Search | C28: Title search — flat fee | D28: 500
A29: Attorney Fees | C29: Buyer's counsel — flat fee | D29: 12500
A30: OTHER COSTS
A31: Legal (LLC, PPM, OA) | C31: Sponsor legal — LLC formation, PPM, operating agreement | D31: 7500
A32: Property Inspection | C32: Buyer property walks & unit inspections — flat estimate | D32: 3500
A33: Travel | C33: Sponsor travel & DD logistics — flat estimate | D33: 7500
A34: Miscellaneous | B34: 0.005 | C34: Contingency — % of Purchase Price for unknowns | D34: =B34*Scenarios!F7 -> 0
A35: TOTAL CLOSING & OTHER COSTS | D35: =IF(Scenarios!$F$7=0,0,SUM(D16:D34)) -> 0

Sheet T-12 Analysis
A1: =IF('Prop Info'!B4="","T-12 ANALYSIS — Trailing 12 Diagnostic Layer","T-12 ANALYSIS — Trailing 12 Diagnostic Layer"&" — "&'Prop Info'!B4) -> T-12 ANALYSIS — Trailing 12 Diagnostic Layer
A2: ANALYSIS on top. Standardized aggregation (Layer 3) and raw paste block (Layer 1) below — scroll down to access data.
A4: B. RECONCILIATION CHECK — Are all raw lines mapped?
A5: EGI: | B5: =N80 -> 0 | C5: OpEx: | D5: =N100 -> 0 | E5: NOI: | F5: =N101 -> 0 | G5: Unmapped $: | H5: =SUMIF(P106:P255,"",O106:O255)+SUMIF(P106:P255,"— UNMAPPED —",O106:O255) -> 0 | I5: =IF(ABS(H5)<1,"🟢 all mapped","🔴 mapping incomplete") -> 🟢 all mapped | L5: EGI/Unit/Mo: | M5: =IFERROR(N80/12/'Prop Info'!$B$6,0) -> 0
A7: C. TREND ANALYSIS — T-3 vs. T-6 vs. T-12 (annualized)
A8: Metric | B8: T-12 Actual | C8: T-6 Annlzd | D8: T-3 Annlzd | E8: T-3 vs T-12 Δ$ | F8: T-3 vs T-12 Δ% | G8: Direction | H8: Read
A9: EGI | B9: =N80 -> 0 | C9: =SUM(H80:M80)*2 -> 0 | D9: =SUM(K80:M80)*4 -> 0 | E9: =D9-B9 -> 0 | F9: =IFERROR(D9/B9-1,0) -> 0 | G9: =IF(F9>0.05,"↑ rising",IF(F9<-0.05,"↓ falling","→ stable")) -> → stable | H9: =IF(F9>0.1,"improving",IF(F9<-0.1,"⚠ deteriorating","stable")) -> stable
A10: Total OpEx | B10: =N100 -> 0 | C10: =SUM(H100:M100)*2 -> 0 | D10: =SUM(K100:M100)*4 -> 0 | E10: =D10-B10 -> 0 | F10: =IFERROR(D10/B10-1,0) -> 0 | G10: =IF(F10>0.05,"↑ rising",IF(F10<-0.05,"↓ falling","→ stable")) -> → stable | H10: =IF(F10>0.1,"⚠ deteriorating",IF(F10<-0.1,"improving","stable")) -> stable
A11: NOI | B11: =N101 -> 0 | C11: =SUM(H101:M101)*2 -> 0 | D11: =SUM(K101:M101)*4 -> 0 | E11: =D11-B11 -> 0 | F11: =IFERROR(D11/B11-1,0) -> 0 | G11: =IF(F11>0.05,"↑ rising",IF(F11<-0.05,"↓ falling","→ stable")) -> → stable | H11: =IF(F11>0.1,"improving",IF(F11<-0.1,"⚠ deteriorating","stable")) -> stable
A12: Bad Debt + Write-offs | B12: =N65 -> 0 | C12: =SUM(H65:M65)*2 -> 0 | D12: =SUM(K65:M65)*4 -> 0 | E12: =D12-B12 -> 0 | F12: =IFERROR(D12/B12-1,0) -> 0 | G12: =IF(F12>0.05,"↑ rising",IF(F12<-0.05,"↓ falling","→ stable")) -> → stable | H12: =IF(F12>0.1,"⚠ deteriorating",IF(F12<-0.1,"improving","stable")) -> stable
A13: Water & Sewer | B13: =N96 -> 0 | C13: =SUM(H96:M96)*2 -> 0 | D13: =SUM(K96:M96)*4 -> 0 | E13: =D13-B13 -> 0 | F13: =IFERROR(D13/B13-1,0) -> 0 | G13: =IF(F13>0.05,"↑ rising",IF(F13<-0.05,"↓ falling","→ stable")) -> → stable | H13: =IF(F13>0.1,"⚠ deteriorating",IF(F13<-0.1,"improving","stable")) -> stable
A14: Payroll | B14: =N88 -> 0 | C14: =SUM(H88:M88)*2 -> 0 | D14: =SUM(K88:M88)*4 -> 0 | E14: =D14-B14 -> 0 | F14: =IFERROR(D14/B14-1,0) -> 0 | G14: =IF(F14>0.05,"↑ rising",IF(F14<-0.05,"↓ falling","→ stable")) -> → stable | H14: =IF(F14>0.1,"⚠ deteriorating",IF(F14<-0.1,"improving","stable")) -> stable
A15: Repairs & Maintenance | B15: =N82 -> 0 | C15: =SUM(H82:M82)*2 -> 0 | D15: =SUM(K82:M82)*4 -> 0 | E15: =D15-B15 -> 0 | F15: =IFERROR(D15/B15-1,0) -> 0 | G15: =IF(F15>0.05,"↑ rising",IF(F15<-0.05,"↓ falling","→ stable")) -> → stable | H15: =IF(F15>0.1,"⚠ deteriorating",IF(F15<-0.1,"improving","stable")) -> stable
A16: Make-Ready | B16: =N87 -> 0 | C16: =SUM(H87:M87)*2 -> 0 | D16: =SUM(K87:M87)*4 -> 0 | E16: =D16-B16 -> 0 | F16: =IFERROR(D16/B16-1,0) -> 0 | G16: =IF(F16>0.05,"↑ rising",IF(F16<-0.05,"↓ falling","→ stable")) -> → stable | H16: =IF(F16>0.1,"⚠ deteriorating",IF(F16<-0.1,"improving","stable")) -> stable
A18: D. ECONOMIC vs. PHYSICAL OCCUPANCY RECONCILIATION
A19: Total Units | B19: ='Prop Info'!$B$6 -> 0
A20: Physically Occupied Units | B20: ='Rent Roll Analysis'!T5 -> 0
A21: Physical Occupancy % | B21: =IFERROR(B20/B19,0) -> 0
A22: Gross Potential Rent (annual) | B22: =N58 -> 0
A23: Gross Rent Billed (Net Rent Rev) | B23: =N67 -> 0
A24: Total Revenue (EGI) | B24: =N80 -> 0
A25: Economic Occupancy % (Net Rent / GPR) | B25: =IFERROR(B23/B22,0) -> 0
A26: Economic vs. Physical Gap | B26: =B21-B25 -> 0
A27: → Lost Revenue from Gap ($) | B27: =B26*B22 -> 0
A29: E. BAD DEBT & WRITE-OFF LAYERED ANALYSIS
A30: Component | B30: Amount | C30: % of GPR | D30: PUPM | E30: Benchmark | F30: Read
A31: Vacancy Loss | B31: =ABS(N60) -> 0 | C31: =IFERROR(B31/N58,0) -> 0 | D31: =IFERROR(B31/12/'Prop Info'!$B$6,0) -> 0 | E31: 5-8% GPR
A32: Bad Debt / Write-offs | B32: =ABS(N65) -> 0 | C32: =IFERROR(B32/N58,0) -> 0 | D32: =IFERROR(B32/12/'Prop Info'!$B$6,0) -> 0 | E32: 1-3% GPR
A33: Concessions | B33: =ABS(N63) -> 0 | C33: =IFERROR(B33/N58,0) -> 0 | D33: =IFERROR(B33/12/'Prop Info'!$B$6,0) -> 0 | E33: 0.5-2% GPR
A34: Delinquency Change | B34: =ABS(N64) -> 0 | C34: =IFERROR(B34/N58,0) -> 0 | D34: =IFERROR(B34/12/'Prop Info'!$B$6,0) -> 0 | E34: <2% GPR
A35: Down Units Loss | B35: =ABS(N61) -> 0 | C35: =IFERROR(B35/N58,0) -> 0 | D35: =IFERROR(B35/12/'Prop Info'!$B$6,0) -> 0 | E35: <1% GPR
A36: Employee Units | B36: =ABS(N62) -> 0 | C36: =IFERROR(B36/N58,0) -> 0 | D36: =IFERROR(B36/12/'Prop Info'!$B$6,0) -> 0 | E36: <1% GPR
A37: Total Rent Reductions | B37: =SUM(B31:B36) -> 0 | C37: =IFERROR(B37/N58,0) -> 0 | F37: =IF(C37>0.2,"🔴 critical",IF(C37>0.13,"⚠ high","ok")) -> ok
A39: F. TAX & INSURANCE ACCRUAL CHECK
A40: T-12 actuals are rarely the right pro forma number. Triangulate with reassessment estimate and lender quote. Status flags missing/skipped accruals.
A42: Real Estate Taxes
A43: T-12 Actual | B43: =N93 -> 0
A44: Pro Forma Estimate | B44: =Scenarios!F60 -> 0
A45: Variance (Actual − PF) | B45: =B43-B44 -> 0
A46: Status | B46: =IF(B43=0,"⚠ not in T-12 — likely paid at entity level — VERIFY",IF(B44=0,"⚠ pro forma not set",IF(ABS(B45)/B44>0.2,"⚠ material variance","ok"))) -> ⚠ not in T-12 — likely paid at entity level — VERIFY
A48: Insurance
A49: T-12 Actual | B49: =N92 -> 0
A50: Pro Forma Estimate | B50: =Scenarios!F58 -> 0
A51: Variance | B51: =B49-B50 -> 0
A52: Status | B52: =IF(B49=0,"⚠ not in T-12 — likely paid at entity level — VERIFY",IF(B50=0,"⚠ pro forma not set",IF(ABS(B51)/B50>0.2,"⚠ material variance","ok"))) -> ⚠ not in T-12 — likely paid at entity level — VERIFY
A54: ↓ ↓ ↓ DATA TIER BELOW — Standardized Aggregation (Layer 3) and Raw T-12 (Layer 1) ↓ ↓ ↓
A55: H. LAYER 3: STANDARDIZED AGGREGATION — Bucket-level detail
A56: Standardized Bucket | B56: Apr-25 | C56: May-25 | D56: Jun-25 | E56: Jul-25 | F56: Aug-25 | G56: Sep-25 | H56: Oct-25 | I56: Nov-25 | J56: Dec-25 | K56: Jan-26 | L56: Feb-26 | M56: Mar-26 | N56: T-12 Total | O56: T-3 Annlzd | P56: PUPM | Q56: % of EGI | R56: Bench Flag
A57: INCOME
A58: Gross Potential Rent | B58: =SUMIFS($C$106:$C$255,$P$106:$P$255,"Gross Potential Rent") -> 0 | C58: =SUMIFS($D$106:$D$255,$P$106:$P$255,"Gross Potential Rent") -> 0 | D58: =SUMIFS($E$106:$E$255,$P$106:$P$255,"Gross Potential Rent") -> 0 | E58: =SUMIFS($F$106:$F$255,$P$106:$P$255,"Gross Potential Rent") -> 0 | F58: =SUMIFS($G$106:$G$255,$P$106:$P$255,"Gross Potential Rent") -> 0 | G58: =SUMIFS($H$106:$H$255,$P$106:$P$255,"Gross Potential Rent") -> 0 | H58: =SUMIFS($I$106:$I$255,$P$106:$P$255,"Gross Potential Rent") -> 0 | I58: =SUMIFS($J$106:$J$255,$P$106:$P$255,"Gross Potential Rent") -> 0 | J58: =SUMIFS($K$106:$K$255,$P$106:$P$255,"Gross Potential Rent") -> 0 | K58: =SUMIFS($L$106:$L$255,$P$106:$P$255,"Gross Potential Rent") -> 0 | L58: =SUMIFS($M$106:$M$255,$P$106:$P$255,"Gross Potential Rent") -> 0 | M58: =SUMIFS($N$106:$N$255,$P$106:$P$255,"Gross Potential Rent") -> 0 | N58: =SUMIFS($O$106:$O$255,$P$106:$P$255,"Gross Potential Rent") -> 0 | O58: =SUM(K58:M58)*4 -> 0 | P58: =IFERROR(N58/12/'Prop Info'!$B$6,0) -> 0 | Q58: =IFERROR(N58/N$80,0) -> 0 | R58: =IFERROR(IF(OR(VLOOKUP(A58,_StdCOA!$A$4:$E$56,4,0)=0,VLOOKUP(A58,_StdCOA!$A$4:$E$56,5,0)=0),"",IF(ABS(P58)>VLOOKUP(A58,_StdCOA!$A$4:$E$56,5,0),"🔴 high",IF(ABS(P58)<VLOOKUP(A58,_StdCOA!$A$4:$E$56,4,0),"🟢 low","🟡 in range"))),"")
A59: Gain/Loss on Market Rent | B59: =SUMIFS($C$106:$C$255,$P$106:$P$255,"Gain/Loss on Market Rent") -> 0 | C59: =SUMIFS($D$106:$D$255,$P$106:$P$255,"Gain/Loss on Market Rent") -> 0 | D59: =SUMIFS($E$106:$E$255,$P$106:$P$255,"Gain/Loss on Market Rent") -> 0 | E59: =SUMIFS($F$106:$F$255,$P$106:$P$255,"Gain/Loss on Market Rent") -> 0 | F59: =SUMIFS($G$106:$G$255,$P$106:$P$255,"Gain/Loss on Market Rent") -> 0 | G59: =SUMIFS($H$106:$H$255,$P$106:$P$255,"Gain/Loss on Market Rent") -> 0 | H59: =SUMIFS($I$106:$I$255,$P$106:$P$255,"Gain/Loss on Market Rent") -> 0 | I59: =SUMIFS($J$106:$J$255,$P$106:$P$255,"Gain/Loss on Market Rent") -> 0 | J59: =SUMIFS($K$106:$K$255,$P$106:$P$255,"Gain/Loss on Market Rent") -> 0 | K59: =SUMIFS($L$106:$L$255,$P$106:$P$255,"Gain/Loss on Market Rent") -> 0 | L59: =SUMIFS($M$106:$M$255,$P$106:$P$255,"Gain/Loss on Market Rent") -> 0 | M59: =SUMIFS($N$106:$N$255,$P$106:$P$255,"Gain/Loss on Market Rent") -> 0 | N59: =SUMIFS($O$106:$O$255,$P$106:$P$255,"Gain/Loss on Market Rent") -> 0 | O59: =SUM(K59:M59)*4 -> 0 | P59: =IFERROR(N59/12/'Prop Info'!$B$6,0) -> 0 | Q59: =IFERROR(N59/N$80,0) -> 0 | R59: =IFERROR(IF(OR(VLOOKUP(A59,_StdCOA!$A$4:$E$56,4,0)=0,VLOOKUP(A59,_StdCOA!$A$4:$E$56,5,0)=0),"",IF(ABS(P59)>VLOOKUP(A59,_StdCOA!$A$4:$E$56,5,0),"🔴 high",IF(ABS(P59)<VLOOKUP(A59,_StdCOA!$A$4:$E$56,4,0),"🟢 low","🟡 in range"))),"")
A60: Vacancy Loss | B60: =SUMIFS($C$106:$C$255,$P$106:$P$255,"Vacancy Loss") -> 0 | C60: =SUMIFS($D$106:$D$255,$P$106:$P$255,"Vacancy Loss") -> 0 | D60: =SUMIFS($E$106:$E$255,$P$106:$P$255,"Vacancy Loss") -> 0 | E60: =SUMIFS($F$106:$F$255,$P$106:$P$255,"Vacancy Loss") -> 0 | F60: =SUMIFS($G$106:$G$255,$P$106:$P$255,"Vacancy Loss") -> 0 | G60: =SUMIFS($H$106:$H$255,$P$106:$P$255,"Vacancy Loss") -> 0 | H60: =SUMIFS($I$106:$I$255,$P$106:$P$255,"Vacancy Loss") -> 0 | I60: =SUMIFS($J$106:$J$255,$P$106:$P$255,"Vacancy Loss") -> 0 | J60: =SUMIFS($K$106:$K$255,$P$106:$P$255,"Vacancy Loss") -> 0 | K60: =SUMIFS($L$106:$L$255,$P$106:$P$255,"Vacancy Loss") -> 0 | L60: =SUMIFS($M$106:$M$255,$P$106:$P$255,"Vacancy Loss") -> 0 | M60: =SUMIFS($N$106:$N$255,$P$106:$P$255,"Vacancy Loss") -> 0 | N60: =SUMIFS($O$106:$O$255,$P$106:$P$255,"Vacancy Loss") -> 0 | O60: =SUM(K60:M60)*4 -> 0 | P60: =IFERROR(N60/12/'Prop Info'!$B$6,0) -> 0 | Q60: =IFERROR(N60/N$80,0) -> 0 | R60: =IFERROR(IF(OR(VLOOKUP(A60,_StdCOA!$A$4:$E$56,4,0)=0,VLOOKUP(A60,_StdCOA!$A$4:$E$56,5,0)=0),"",IF(ABS(P60)>VLOOKUP(A60,_StdCOA!$A$4:$E$56,5,0),"🔴 high",IF(ABS(P60)<VLOOKUP(A60,_StdCOA!$A$4:$E$56,4,0),"🟢 low","🟡 in range"))),"")
A61: Down Units Loss | B61: =SUMIFS($C$106:$C$255,$P$106:$P$255,"Down Units Loss") -> 0 | C61: =SUMIFS($D$106:$D$255,$P$106:$P$255,"Down Units Loss") -> 0 | D61: =SUMIFS($E$106:$E$255,$P$106:$P$255,"Down Units Loss") -> 0 | E61: =SUMIFS($F$106:$F$255,$P$106:$P$255,"Down Units Loss") -> 0 | F61: =SUMIFS($G$106:$G$255,$P$106:$P$255,"Down Units Loss") -> 0 | G61: =SUMIFS($H$106:$H$255,$P$106:$P$255,"Down Units Loss") -> 0 | H61: =SUMIFS($I$106:$I$255,$P$106:$P$255,"Down Units Loss") -> 0 | I61: =SUMIFS($J$106:$J$255,$P$106:$P$255,"Down Units Loss") -> 0 | J61: =SUMIFS($K$106:$K$255,$P$106:$P$255,"Down Units Loss") -> 0 | K61: =SUMIFS($L$106:$L$255,$P$106:$P$255,"Down Units Loss") -> 0 | L61: =SUMIFS($M$106:$M$255,$P$106:$P$255,"Down Units Loss") -> 0 | M61: =SUMIFS($N$106:$N$255,$P$106:$P$255,"Down Units Loss") -> 0 | N61: =SUMIFS($O$106:$O$255,$P$106:$P$255,"Down Units Loss") -> 0 | O61: =SUM(K61:M61)*4 -> 0 | P61: =IFERROR(N61/12/'Prop Info'!$B$6,0) -> 0 | Q61: =IFERROR(N61/N$80,0) -> 0 | R61: =IFERROR(IF(OR(VLOOKUP(A61,_StdCOA!$A$4:$E$56,4,0)=0,VLOOKUP(A61,_StdCOA!$A$4:$E$56,5,0)=0),"",IF(ABS(P61)>VLOOKUP(A61,_StdCOA!$A$4:$E$56,5,0),"🔴 high",IF(ABS(P61)<VLOOKUP(A61,_StdCOA!$A$4:$E$56,4,0),"🟢 low","🟡 in range"))),"")
A62: Employee Units | B62: =SUMIFS($C$106:$C$255,$P$106:$P$255,"Employee Units") -> 0 | C62: =SUMIFS($D$106:$D$255,$P$106:$P$255,"Employee Units") -> 0 | D62: =SUMIFS($E$106:$E$255,$P$106:$P$255,"Employee Units") -> 0 | E62: =SUMIFS($F$106:$F$255,$P$106:$P$255,"Employee Units") -> 0 | F62: =SUMIFS($G$106:$G$255,$P$106:$P$255,"Employee Units") -> 0 | G62: =SUMIFS($H$106:$H$255,$P$106:$P$255,"Employee Units") -> 0 | H62: =SUMIFS($I$106:$I$255,$P$106:$P$255,"Employee Units") -> 0 | I62: =SUMIFS($J$106:$J$255,$P$106:$P$255,"Employee Units") -> 0 | J62: =SUMIFS($K$106:$K$255,$P$106:$P$255,"Employee Units") -> 0 | K62: =SUMIFS($L$106:$L$255,$P$106:$P$255,"Employee Units") -> 0 | L62: =SUMIFS($M$106:$M$255,$P$106:$P$255,"Employee Units") -> 0 | M62: =SUMIFS($N$106:$N$255,$P$106:$P$255,"Employee Units") -> 0 | N62: =SUMIFS($O$106:$O$255,$P$106:$P$255,"Employee Units") -> 0 | O62: =SUM(K62:M62)*4 -> 0 | P62: =IFERROR(N62/12/'Prop Info'!$B$6,0) -> 0 | Q62: =IFERROR(N62/N$80,0) -> 0 | R62: =IFERROR(IF(OR(VLOOKUP(A62,_StdCOA!$A$4:$E$56,4,0)=0,VLOOKUP(A62,_StdCOA!$A$4:$E$56,5,0)=0),"",IF(ABS(P62)>VLOOKUP(A62,_StdCOA!$A$4:$E$56,5,0),"🔴 high",IF(ABS(P62)<VLOOKUP(A62,_StdCOA!$A$4:$E$56,4,0),"🟢 low","🟡 in range"))),"")
A63: Concessions | B63: =SUMIFS($C$106:$C$255,$P$106:$P$255,"Concessions") -> 0 | C63: =SUMIFS($D$106:$D$255,$P$106:$P$255,"Concessions") -> 0 | D63: =SUMIFS($E$106:$E$255,$P$106:$P$255,"Concessions") -> 0 | E63: =SUMIFS($F$106:$F$255,$P$106:$P$255,"Concessions") -> 0 | F63: =SUMIFS($G$106:$G$255,$P$106:$P$255,"Concessions") -> 0 | G63: =SUMIFS($H$106:$H$255,$P$106:$P$255,"Concessions") -> 0 | H63: =SUMIFS($I$106:$I$255,$P$106:$P$255,"Concessions") -> 0 | I63: =SUMIFS($J$106:$J$255,$P$106:$P$255,"Concessions") -> 0 | J63: =SUMIFS($K$106:$K$255,$P$106:$P$255,"Concessions") -> 0 | K63: =SUMIFS($L$106:$L$255,$P$106:$P$255,"Concessions") -> 0 | L63: =SUMIFS($M$106:$M$255,$P$106:$P$255,"Concessions") -> 0 | M63: =SUMIFS($N$106:$N$255,$P$106:$P$255,"Concessions") -> 0 | N63: =SUMIFS($O$106:$O$255,$P$106:$P$255,"Concessions") -> 0 | O63: =SUM(K63:M63)*4 -> 0 | P63: =IFERROR(N63/12/'Prop Info'!$B$6,0) -> 0 | Q63: =IFERROR(N63/N$80,0) -> 0 | R63: =IFERROR(IF(OR(VLOOKUP(A63,_StdCOA!$A$4:$E$56,4,0)=0,VLOOKUP(A63,_StdCOA!$A$4:$E$56,5,0)=0),"",IF(ABS(P63)>VLOOKUP(A63,_StdCOA!$A$4:$E$56,5,0),"🔴 high",IF(ABS(P63)<VLOOKUP(A63,_StdCOA!$A$4:$E$56,4,0),"🟢 low","🟡 in range"))),"")
A64: Delinquency Change | B64: =SUMIFS($C$106:$C$255,$P$106:$P$255,"Delinquency Change") -> 0 | C64: =SUMIFS($D$106:$D$255,$P$106:$P$255,"Delinquency Change") -> 0 | D64: =SUMIFS($E$106:$E$255,$P$106:$P$255,"Delinquency Change") -> 0 | E64: =SUMIFS($F$106:$F$255,$P$106:$P$255,"Delinquency Change") -> 0 | F64: =SUMIFS($G$106:$G$255,$P$106:$P$255,"Delinquency Change") -> 0 | G64: =SUMIFS($H$106:$H$255,$P$106:$P$255,"Delinquency Change") -> 0 | H64: =SUMIFS($I$106:$I$255,$P$106:$P$255,"Delinquency Change") -> 0 | I64: =SUMIFS($J$106:$J$255,$P$106:$P$255,"Delinquency Change") -> 0 | J64: =SUMIFS($K$106:$K$255,$P$106:$P$255,"Delinquency Change") -> 0 | K64: =SUMIFS($L$106:$L$255,$P$106:$P$255,"Delinquency Change") -> 0 | L64: =SUMIFS($M$106:$M$255,$P$106:$P$255,"Delinquency Change") -> 0 | M64: =SUMIFS($N$106:$N$255,$P$106:$P$255,"Delinquency Change") -> 0 | N64: =SUMIFS($O$106:$O$255,$P$106:$P$255,"Delinquency Change") -> 0 | O64: =SUM(K64:M64)*4 -> 0 | P64: =IFERROR(N64/12/'Prop Info'!$B$6,0) -> 0 | Q64: =IFERROR(N64/N$80,0) -> 0 | R64: =IFERROR(IF(OR(VLOOKUP(A64,_StdCOA!$A$4:$E$56,4,0)=0,VLOOKUP(A64,_StdCOA!$A$4:$E$56,5,0)=0),"",IF(ABS(P64)>VLOOKUP(A64,_StdCOA!$A$4:$E$56,5,0),"🔴 high",IF(ABS(P64)<VLOOKUP(A64,_StdCOA!$A$4:$E$56,4,0),"🟢 low","🟡 in range"))),"")
A65: Write-offs / Bad Debt | B65: =SUMIFS($C$106:$C$255,$P$106:$P$255,"Write-offs / Bad Debt") -> 0 | C65: =SUMIFS($D$106:$D$255,$P$106:$P$255,"Write-offs / Bad Debt") -> 0 | D65: =SUMIFS($E$106:$E$255,$P$106:$P$255,"Write-offs / Bad Debt") -> 0 | E65: =SUMIFS($F$106:$F$255,$P$106:$P$255,"Write-offs / Bad Debt") -> 0 | F65: =SUMIFS($G$106:$G$255,$P$106:$P$255,"Write-offs / Bad Debt") -> 0 | G65: =SUMIFS($H$106:$H$255,$P$106:$P$255,"Write-offs / Bad Debt") -> 0 | H65: =SUMIFS($I$106:$I$255,$P$106:$P$255,"Write-offs / Bad Debt") -> 0 | I65: =SUMIFS($J$106:$J$255,$P$106:$P$255,"Write-offs / Bad Debt") -> 0 | J65: =SUMIFS($K$106:$K$255,$P$106:$P$255,"Write-offs / Bad Debt") -> 0 | K65: =SUMIFS($L$106:$L$255,$P$106:$P$255,"Write-offs / Bad Debt") -> 0 | L65: =SUMIFS($M$106:$M$255,$P$106:$P$255,"Write-offs / Bad Debt") -> 0 | M65: =SUMIFS($N$106:$N$255,$P$106:$P$255,"Write-offs / Bad Debt") -> 0 | N65: =SUMIFS($O$106:$O$255,$P$106:$P$255,"Write-offs / Bad Debt") -> 0 | O65: =SUM(K65:M65)*4 -> 0 | P65: =IFERROR(N65/12/'Prop Info'!$B$6,0) -> 0 | Q65: =IFERROR(N65/N$80,0) -> 0 | R65: =IFERROR(IF(OR(VLOOKUP(A65,_StdCOA!$A$4:$E$56,4,0)=0,VLOOKUP(A65,_StdCOA!$A$4:$E$56,5,0)=0),"",IF(ABS(P65)>VLOOKUP(A65,_StdCOA!$A$4:$E$56,5,0),"🔴 high",IF(ABS(P65)<VLOOKUP(A65,_StdCOA!$A$4:$E$56,4,0),"🟢 low","🟡 in range"))),"")
A66: Prepaid Rent Change | B66: =SUMIFS($C$106:$C$255,$P$106:$P$255,"Prepaid Rent Change") -> 0 | C66: =SUMIFS($D$106:$D$255,$P$106:$P$255,"Prepaid Rent Change") -> 0 | D66: =SUMIFS($E$106:$E$255,$P$106:$P$255,"Prepaid Rent Change") -> 0 | E66: =SUMIFS($F$106:$F$255,$P$106:$P$255,"Prepaid Rent Change") -> 0 | F66: =SUMIFS($G$106:$G$255,$P$106:$P$255,"Prepaid Rent Change") -> 0 | G66: =SUMIFS($H$106:$H$255,$P$106:$P$255,"Prepaid Rent Change") -> 0 | H66: =SUMIFS($I$106:$I$255,$P$106:$P$255,"Prepaid Rent Change") -> 0 | I66: =SUMIFS($J$106:$J$255,$P$106:$P$255,"Prepaid Rent Change") -> 0 | J66: =SUMIFS($K$106:$K$255,$P$106:$P$255,"Prepaid Rent Change") -> 0 | K66: =SUMIFS($L$106:$L$255,$P$106:$P$255,"Prepaid Rent Change") -> 0 | L66: =SUMIFS($M$106:$M$255,$P$106:$P$255,"Prepaid Rent Change") -> 0 | M66: =SUMIFS($N$106:$N$255,$P$106:$P$255,"Prepaid Rent Change") -> 0 | N66: =SUMIFS($O$106:$O$255,$P$106:$P$255,"Prepaid Rent Change") -> 0 | O66: =SUM(K66:M66)*4 -> 0 | P66: =IFERROR(N66/12/'Prop Info'!$B$6,0) -> 0 | Q66: =IFERROR(N66/N$80,0) -> 0 | R66: =IFERROR(IF(OR(VLOOKUP(A66,_StdCOA!$A$4:$E$56,4,0)=0,VLOOKUP(A66,_StdCOA!$A$4:$E$56,5,0)=0),"",IF(ABS(P66)>VLOOKUP(A66,_StdCOA!$A$4:$E$56,5,0),"🔴 high",IF(ABS(P66)<VLOOKUP(A66,_StdCOA!$A$4:$E$56,4,0),"🟢 low","🟡 in range"))),"")
A67: Net Rent Revenue | B67: =B58+B59+B60+B61+B62+B63+B64+B65+B66 -> 0 | C67: =C58+C59+C60+C61+C62+C63+C64+C65+C66 -> 0 | D67: =D58+D59+D60+D61+D62+D63+D64+D65+D66 -> 0 | E67: =E58+E59+E60+E61+E62+E63+E64+E65+E66 -> 0 | F67: =F58+F59+F60+F61+F62+F63+F64+F65+F66 -> 0 | G67: =G58+G59+G60+G61+G62+G63+G64+G65+G66 -> 0 | H67: =H58+H59+H60+H61+H62+H63+H64+H65+H66 -> 0 | I67: =I58+I59+I60+I61+I62+I63+I64+I65+I66 -> 0 | ... N67: =N58+N59+N60+N61+N62+N63+N64+N65+N66 -> 0 | O67: =SUM(K67:M67)*4 -> 0 | P67: =IFERROR(N67/12/'Prop Info'!$B$6,0) -> 0 | Q67: =IFERROR(N67/N$80,0) -> 0
A68: MTM Fees | B68: =SUMIFS($C$106:$C$255,$P$106:$P$255,"MTM Fees") -> 0 | C68: =SUMIFS($D$106:$D$255,$P$106:$P$255,"MTM Fees") -> 0 | D68: =SUMIFS($E$106:$E$255,$P$106:$P$255,"MTM Fees") -> 0 | E68: =SUMIFS($F$106:$F$255,$P$106:$P$255,"MTM Fees") -> 0 | F68: =SUMIFS($G$106:$G$255,$P$106:$P$255,"MTM Fees") -> 0 | G68: =SUMIFS($H$106:$H$255,$P$106:$P$255,"MTM Fees") -> 0 | H68: =SUMIFS($I$106:$I$255,$P$106:$P$255,"MTM Fees") -> 0 | I68: =SUMIFS($J$106:$J$255,$P$106:$P$255,"MTM Fees") -> 0 | J68: =SUMIFS($K$106:$K$255,$P$106:$P$255,"MTM Fees") -> 0 | K68: =SUMIFS($L$106:$L$255,$P$106:$P$255,"MTM Fees") -> 0 | L68: =SUMIFS($M$106:$M$255,$P$106:$P$255,"MTM Fees") -> 0 | M68: =SUMIFS($N$106:$N$255,$P$106:$P$255,"MTM Fees") -> 0 | N68: =SUMIFS($O$106:$O$255,$P$106:$P$255,"MTM Fees") -> 0 | O68: =SUM(K68:M68)*4 -> 0 | P68: =IFERROR(N68/12/'Prop Info'!$B$6,0) -> 0 | Q68: =IFERROR(N68/N$80,0) -> 0 | R68: =IFERROR(IF(OR(VLOOKUP(A68,_StdCOA!$A$4:$E$56,4,0)=0,VLOOKUP(A68,_StdCOA!$A$4:$E$56,5,0)=0),"",IF(ABS(P68)>VLOOKUP(A68,_StdCOA!$A$4:$E$56,5,0),"🔴 high",IF(ABS(P68)<VLOOKUP(A68,_StdCOA!$A$4:$E$56,4,0),"🟢 low","🟡 in range"))),"")
A69: Application Fees | B69: =SUMIFS($C$106:$C$255,$P$106:$P$255,"Application Fees") -> 0 | C69: =SUMIFS($D$106:$D$255,$P$106:$P$255,"Application Fees") -> 0 | D69: =SUMIFS($E$106:$E$255,$P$106:$P$255,"Application Fees") -> 0 | E69: =SUMIFS($F$106:$F$255,$P$106:$P$255,"Application Fees") -> 0 | F69: =SUMIFS($G$106:$G$255,$P$106:$P$255,"Application Fees") -> 0 | G69: =SUMIFS($H$106:$H$255,$P$106:$P$255,"Application Fees") -> 0 | H69: =SUMIFS($I$106:$I$255,$P$106:$P$255,"Application Fees") -> 0 | I69: =SUMIFS($J$106:$J$255,$P$106:$P$255,"Application Fees") -> 0 | J69: =SUMIFS($K$106:$K$255,$P$106:$P$255,"Application Fees") -> 0 | K69: =SUMIFS($L$106:$L$255,$P$106:$P$255,"Application Fees") -> 0 | L69: =SUMIFS($M$106:$M$255,$P$106:$P$255,"Application Fees") -> 0 | M69: =SUMIFS($N$106:$N$255,$P$106:$P$255,"Application Fees") -> 0 | N69: =SUMIFS($O$106:$O$255,$P$106:$P$255,"Application Fees") -> 0 | O69: =SUM(K69:M69)*4 -> 0 | P69: =IFERROR(N69/12/'Prop Info'!$B$6,0) -> 0 | Q69: =IFERROR(N69/N$80,0) -> 0 | R69: =IFERROR(IF(OR(VLOOKUP(A69,_StdCOA!$A$4:$E$56,4,0)=0,VLOOKUP(A69,_StdCOA!$A$4:$E$56,5,0)=0),"",IF(ABS(P69)>VLOOKUP(A69,_StdCOA!$A$4:$E$56,5,0),"🔴 high",IF(ABS(P69)<VLOOKUP(A69,_StdCOA!$A$4:$E$56,4,0),"🟢 low","🟡 in range"))),"")
A70: Late Fees | B70: =SUMIFS($C$106:$C$255,$P$106:$P$255,"Late Fees") -> 0 | C70: =SUMIFS($D$106:$D$255,$P$106:$P$255,"Late Fees") -> 0 | D70: =SUMIFS($E$106:$E$255,$P$106:$P$255,"Late Fees") -> 0 | E70: =SUMIFS($F$106:$F$255,$P$106:$P$255,"Late Fees") -> 0 | F70: =SUMIFS($G$106:$G$255,$P$106:$P$255,"Late Fees") -> 0 | G70: =SUMIFS($H$106:$H$255,$P$106:$P$255,"Late Fees") -> 0 | H70: =SUMIFS($I$106:$I$255,$P$106:$P$255,"Late Fees") -> 0 | I70: =SUMIFS($J$106:$J$255,$P$106:$P$255,"Late Fees") -> 0 | J70: =SUMIFS($K$106:$K$255,$P$106:$P$255,"Late Fees") -> 0 | K70: =SUMIFS($L$106:$L$255,$P$106:$P$255,"Late Fees") -> 0 | L70: =SUMIFS($M$106:$M$255,$P$106:$P$255,"Late Fees") -> 0 | M70: =SUMIFS($N$106:$N$255,$P$106:$P$255,"Late Fees") -> 0 | N70: =SUMIFS($O$106:$O$255,$P$106:$P$255,"Late Fees") -> 0 | O70: =SUM(K70:M70)*4 -> 0 | P70: =IFERROR(N70/12/'Prop Info'!$B$6,0) -> 0 | Q70: =IFERROR(N70/N$80,0) -> 0 | R70: =IFERROR(IF(OR(VLOOKUP(A70,_StdCOA!$A$4:$E$56,4,0)=0,VLOOKUP(A70,_StdCOA!$A$4:$E$56,5,0)=0),"",IF(ABS(P70)>VLOOKUP(A70,_StdCOA!$A$4:$E$56,5,0),"🔴 high",IF(ABS(P70)<VLOOKUP(A70,_StdCOA!$A$4:$E$56,4,0),"🟢 low","🟡 in range"))),"")
A71: Utility Reimbursement | B71: =SUMIFS($C$106:$C$255,$P$106:$P$255,_StdCOA!$A$16)+SUMIFS($C$106:$C$255,$P$106:$P$255,_StdCOA!$A$42)+SUMIFS($C$106:$C$255,$P$106:$P$255,_StdCOA!$A$43)+SUMIFS($C$106:$C$255,$P$106:$P$255,_StdCOA!$A$44)+SUMIFS($C$106:$C$255,$P$106:$P$255,_StdCOA!$A$45) -> 0 | C71: =SUMIFS($D$106:$D$255,$P$106:$P$255,_StdCOA!$A$16)+SUMIFS($D$106:$D$255,$P$106:$P$255,_StdCOA!$A$42)+SUMIFS($D$106:$D$255,$P$106:$P$255,_StdCOA!$A$43)+SUMIFS($D$106:$D$255,$P$106:$P$255,_StdCOA!$A$44)+SUMIFS($D$106:$D$255,$P$106:$P$255,_StdCOA!$A$45) -> 0 | D71: =SUMIFS($E$106:$E$255,$P$106:$P$255,_StdCOA!$A$16)+SUMIFS($E$106:$E$255,$P$106:$P$255,_StdCOA!$A$42)+SUMIFS($E$106:$E$255,$P$106:$P$255,_StdCOA!$A$43)+SUMIFS($E$106:$E$255,$P$106:$P$255,_StdCOA!$A$44)+SUMIFS($E$106:$E$255,$P$106:$P$255,_StdCOA!$A$45) -> 0 | E71: =SUMIFS($F$106:$F$255,$P$106:$P$255,_StdCOA!$A$16)+SUMIFS($F$106:$F$255,$P$106:$P$255,_StdCOA!$A$42)+SUMIFS($F$106:$F$255,$P$106:$P$255,_StdCOA!$A$43)+SUMIFS($F$106:$F$255,$P$106:$P$255,_StdCOA!$A$44)+SUMIFS($F$106:$F$255,$P$106:$P$255,_StdCOA!$A$45) -> 0 | F71: =SUMIFS($G$106:$G$255,$P$106:$P$255,_StdCOA!$A$16)+SUMIFS($G$106:$G$255,$P$106:$P$255,_StdCOA!$A$42)+SUMIFS($G$106:$G$255,$P$106:$P$255,_StdCOA!$A$43)+SUMIFS($G$106:$G$255,$P$106:$P$255,_StdCOA!$A$44)+SUMIFS($G$106:$G$255,$P$106:$P$255,_StdCOA!$A$45) -> 0 | G71: =SUMIFS($H$106:$H$255,$P$106:$P$255,_StdCOA!$A$16)+SUMIFS($H$106:$H$255,$P$106:$P$255,_StdCOA!$A$42)+SUMIFS($H$106:$H$255,$P$106:$P$255,_StdCOA!$A$43)+SUMIFS($H$106:$H$255,$P$106:$P$255,_StdCOA!$A$44)+SUMIFS($H$106:$H$255,$P$106:$P$255,_StdCOA!$A$45) -> 0 | H71: =SUMIFS($I$106:$I$255,$P$106:$P$255,_StdCOA!$A$16)+SUMIFS($I$106:$I$255,$P$106:$P$255,_StdCOA!$A$42)+SUMIFS($I$106:$I$255,$P$106:$P$255,_StdCOA!$A$43)+SUMIFS($I$106:$I$255,$P$106:$P$255,_StdCOA!$A$44)+SUMIFS($I$106:$I$255,$P$106:$P$255,_StdCOA!$A$45) -> 0 | I71: =SUMIFS($J$106:$J$255,$P$106:$P$255,_StdCOA!$A$16)+SUMIFS($J$106:$J$255,$P$106:$P$255,_StdCOA!$A$42)+SUMIFS($J$106:$J$255,$P$106:$P$255,_StdCOA!$A$43)+SUMIFS($J$106:$J$255,$P$106:$P$255,_StdCOA!$A$44)+SUMIFS($J$106:$J$255,$P$106:$P$255,_StdCOA!$A$45) -> 0 | J71: =SUMIFS($K$106:$K$255,$P$106:$P$255,_StdCOA!$A$16)+SUMIFS($K$106:$K$255,$P$106:$P$255,_StdCOA!$A$42)+SUMIFS($K$106:$K$255,$P$106:$P$255,_StdCOA!$A$43)+SUMIFS($K$106:$K$255,$P$106:$P$255,_StdCOA!$A$44)+SUMIFS($K$106:$K$255,$P$106:$P$255,_StdCOA!$A$45) -> 0 | K71: =SUMIFS($L$106:$L$255,$P$106:$P$255,_StdCOA!$A$16)+SUMIFS($L$106:$L$255,$P$106:$P$255,_StdCOA!$A$42)+SUMIFS($L$106:$L$255,$P$106:$P$255,_StdCOA!$A$43)+SUMIFS($L$106:$L$255,$P$106:$P$255,_StdCOA!$A$44)+SUMIFS($L$106:$L$255,$P$106:$P$255,_StdCOA!$A$45) -> 0 | L71: =SUMIFS($M$106:$M$255,$P$106:$P$255,_StdCOA!$A$16)+SUMIFS($M$106:$M$255,$P$106:$P$255,_StdCOA!$A$42)+SUMIFS($M$106:$M$255,$P$106:$P$255,_StdCOA!$A$43)+SUMIFS($M$106:$M$255,$P$106:$P$255,_StdCOA!$A$44)+SUMIFS($M$106:$M$255,$P$106:$P$255,_StdCOA!$A$45) -> 0 | M71: =SUMIFS($N$106:$N$255,$P$106:$P$255,_StdCOA!$A$16)+SUMIFS($N$106:$N$255,$P$106:$P$255,_StdCOA!$A$42)+SUMIFS($N$106:$N$255,$P$106:$P$255,_StdCOA!$A$43)+SUMIFS($N$106:$N$255,$P$106:$P$255,_StdCOA!$A$44)+SUMIFS($N$106:$N$255,$P$106:$P$255,_StdCOA!$A$45)+SUMIFS($N$106:$N$255,$P$106:$P$255,_StdCOA!$A$46)+SUMIFS($N$106:$N$255,$P$106:$P$255,_StdCOA!$A$47)+SUMIFS($N$106:$N$255,$P$106:$P$255,_StdCOA!$A$48) -> 0 | N71: =SUMIFS($O$106:$O$255,$P$106:$P$255,_StdCOA!$A$16)+SUMIFS($O$106:$O$255,$P$106:$P$255,_StdCOA!$A$42)+SUMIFS($O$106:$O$255,$P$106:$P$255,_StdCOA!$A$43)+SUMIFS($O$106:$O$255,$P$106:$P$255,_StdCOA!$A$44)+SUMIFS($O$106:$O$255,$P$106:$P$255,_StdCOA!$A$45)+SUMIFS($O$106:$O$255,$P$106:$P$255,_StdCOA!$A$46)+SUMIFS($O$106:$O$255,$P$106:$P$255,_StdCOA!$A$47)+SUMIFS($O$106:$O$255,$P$106:$P$255,_StdCOA!$A$48) -> 0 | O71: =SUM(K71:M71)*4 -> 0 | P71: =IFERROR(N71/12/'Prop Info'!$B$6,0) -> 0 | Q71: =IFERROR(N71/N$80,0) -> 0 | R71: =IFERROR(IF(OR(VLOOKUP(A71,_StdCOA!$A$4:$E$56,4,0)=0,VLOOKUP(A71,_StdCOA!$A$4:$E$56,5,0)=0),"",IF(ABS(P71)>VLOOKUP(A71,_StdCOA!$A$4:$E$56,5,0),"🔴 high",IF(ABS(P71)<VLOOKUP(A71,_StdCOA!$A$4:$E$56,4,0),"🟢 low","🟡 in range"))),"")
A72: Pet Fees | B72: =SUMIFS($C$106:$C$255,$P$106:$P$255,"Pet Fees") -> 0 | C72: =SUMIFS($D$106:$D$255,$P$106:$P$255,"Pet Fees") -> 0 | D72: =SUMIFS($E$106:$E$255,$P$106:$P$255,"Pet Fees") -> 0 | E72: =SUMIFS($F$106:$F$255,$P$106:$P$255,"Pet Fees") -> 0 | F72: =SUMIFS($G$106:$G$255,$P$106:$P$255,"Pet Fees") -> 0 | G72: =SUMIFS($H$106:$H$255,$P$106:$P$255,"Pet Fees") -> 0 | H72: =SUMIFS($I$106:$I$255,$P$106:$P$255,"Pet Fees") -> 0 | I72: =SUMIFS($J$106:$J$255,$P$106:$P$255,"Pet Fees") -> 0 | J72: =SUMIFS($K$106:$K$255,$P$106:$P$255,"Pet Fees") -> 0 | K72: =SUMIFS($L$106:$L$255,$P$106:$P$255,"Pet Fees") -> 0 | L72: =SUMIFS($M$106:$M$255,$P$106:$P$255,"Pet Fees") -> 0 | M72: =SUMIFS($N$106:$N$255,$P$106:$P$255,"Pet Fees") -> 0 | N72: =SUMIFS($O$106:$O$255,$P$106:$P$255,"Pet Fees") -> 0 | O72: =SUM(K72:M72)*4 -> 0 | P72: =IFERROR(N72/12/'Prop Info'!$B$6,0) -> 0 | Q72: =IFERROR(N72/N$80,0) -> 0 | R72: =IFERROR(IF(OR(VLOOKUP(A72,_StdCOA!$A$4:$E$56,4,0)=0,VLOOKUP(A72,_StdCOA!$A$4:$E$56,5,0)=0),"",IF(ABS(P72)>VLOOKUP(A72,_StdCOA!$A$4:$E$56,5,0),"🔴 high",IF(ABS(P72)<VLOOKUP(A72,_StdCOA!$A$4:$E$56,4,0),"🟢 low","🟡 in range"))),"")
A73: Parking Income | B73: =SUMIFS($C$106:$C$255,$P$106:$P$255,"Parking Income") -> 0 | C73: =SUMIFS($D$106:$D$255,$P$106:$P$255,"Parking Income") -> 0 | D73: =SUMIFS($E$106:$E$255,$P$106:$P$255,"Parking Income") -> 0 | E73: =SUMIFS($F$106:$F$255,$P$106:$P$255,"Parking Income") -> 0 | F73: =SUMIFS($G$106:$G$255,$P$106:$P$255,"Parking Income") -> 0 | G73: =SUMIFS($H$106:$H$255,$P$106:$P$255,"Parking Income") -> 0 | H73: =SUMIFS($I$106:$I$255,$P$106:$P$255,"Parking Income") -> 0 | I73: =SUMIFS($J$106:$J$255,$P$106:$P$255,"Parking Income") -> 0 | J73: =SUMIFS($K$106:$K$255,$P$106:$P$255,"Parking Income") -> 0 | K73: =SUMIFS($L$106:$L$255,$P$106:$P$255,"Parking Income") -> 0 | L73: =SUMIFS($M$106:$M$255,$P$106:$P$255,"Parking Income") -> 0 | M73: =SUMIFS($N$106:$N$255,$P$106:$P$255,"Parking Income") -> 0 | N73: =SUMIFS($O$106:$O$255,$P$106:$P$255,"Parking Income") -> 0 | O73: =SUM(K73:M73)*4 -> 0 | P73: =IFERROR(N73/12/'Prop Info'!$B$6,0) -> 0 | Q73: =IFERROR(N73/N$80,0) -> 0 | R73: =IFERROR(IF(OR(VLOOKUP(A73,_StdCOA!$A$4:$E$56,4,0)=0,VLOOKUP(A73,_StdCOA!$A$4:$E$56,5,0)=0),"",IF(ABS(P73)>VLOOKUP(A73,_StdCOA!$A$4:$E$56,5,0),"🔴 high",IF(ABS(P73)<VLOOKUP(A73,_StdCOA!$A$4:$E$56,4,0),"🟢 low","🟡 in range"))),"")
A74: Amenity Fees | B74: =SUMIFS($C$106:$C$255,$P$106:$P$255,"Amenity Fees") -> 0 | C74: =SUMIFS($D$106:$D$255,$P$106:$P$255,"Amenity Fees") -> 0 | D74: =SUMIFS($E$106:$E$255,$P$106:$P$255,"Amenity Fees") -> 0 | E74: =SUMIFS($F$106:$F$255,$P$106:$P$255,"Amenity Fees") -> 0 | F74: =SUMIFS($G$106:$G$255,$P$106:$P$255,"Amenity Fees") -> 0 | G74: =SUMIFS($H$106:$H$255,$P$106:$P$255,"Amenity Fees") -> 0 | H74: =SUMIFS($I$106:$I$255,$P$106:$P$255,"Amenity Fees") -> 0 | I74: =SUMIFS($J$106:$J$255,$P$106:$P$255,"Amenity Fees") -> 0 | J74: =SUMIFS($K$106:$K$255,$P$106:$P$255,"Amenity Fees") -> 0 | K74: =SUMIFS($L$106:$L$255,$P$106:$P$255,"Amenity Fees") -> 0 | L74: =SUMIFS($M$106:$M$255,$P$106:$P$255,"Amenity Fees") -> 0 | M74: =SUMIFS($N$106:$N$255,$P$106:$P$255,"Amenity Fees") -> 0 | N74: =SUMIFS($O$106:$O$255,$P$106:$P$255,"Amenity Fees") -> 0 | O74: =SUM(K74:M74)*4 -> 0 | P74: =IFERROR(N74/12/'Prop Info'!$B$6,0) -> 0 | Q74: =IFERROR(N74/N$80,0) -> 0 | R74: =IFERROR(IF(OR(VLOOKUP(A74,_StdCOA!$A$4:$E$56,4,0)=0,VLOOKUP(A74,_StdCOA!$A$4:$E$56,5,0)=0),"",IF(ABS(P74)>VLOOKUP(A74,_StdCOA!$A$4:$E$56,5,0),"🔴 high",IF(ABS(P74)<VLOOKUP(A74,_StdCOA!$A$4:$E$56,4,0),"🟢 low","🟡 in range"))),"")
A75: Admin Fees | B75: =SUMIFS($C$106:$C$255,$P$106:$P$255,"Admin Fees") -> 0 | C75: =SUMIFS($D$106:$D$255,$P$106:$P$255,"Admin Fees") -> 0 | D75: =SUMIFS($E$106:$E$255,$P$106:$P$255,"Admin Fees") -> 0 | E75: =SUMIFS($F$106:$F$255,$P$106:$P$255,"Admin Fees") -> 0 | F75: =SUMIFS($G$106:$G$255,$P$106:$P$255,"Admin Fees") -> 0 | G75: =SUMIFS($H$106:$H$255,$P$106:$P$255,"Admin Fees") -> 0 | H75: =SUMIFS($I$106:$I$255,$P$106:$P$255,"Admin Fees") -> 0 | I75: =SUMIFS($J$106:$J$255,$P$106:$P$255,"Admin Fees") -> 0 | J75: =SUMIFS($K$106:$K$255,$P$106:$P$255,"Admin Fees") -> 0 | K75: =SUMIFS($L$106:$L$255,$P$106:$P$255,"Admin Fees") -> 0 | L75: =SUMIFS($M$106:$M$255,$P$106:$P$255,"Admin Fees") -> 0 | M75: =SUMIFS($N$106:$N$255,$P$106:$P$255,"Admin Fees") -> 0 | N75: =SUMIFS($O$106:$O$255,$P$106:$P$255,"Admin Fees") -> 0 | O75: =SUM(K75:M75)*4 -> 0 | P75: =IFERROR(N75/12/'Prop Info'!$B$6,0) -> 0 | Q75: =IFERROR(N75/N$80,0) -> 0 | R75: =IFERROR(IF(OR(VLOOKUP(A75,_StdCOA!$A$4:$E$56,4,0)=0,VLOOKUP(A75,_StdCOA!$A$4:$E$56,5,0)=0),"",IF(ABS(P75)>VLOOKUP(A75,_StdCOA!$A$4:$E$56,5,0),"🔴 high",IF(ABS(P75)<VLOOKUP(A75,_StdCOA!$A$4:$E$56,4,0),"🟢 low","🟡 in range"))),"")
A76: Insurance Pass-Thru | B76: =SUMIFS($C$106:$C$255,$P$106:$P$255,"Insurance Pass-Thru") -> 0 | C76: =SUMIFS($D$106:$D$255,$P$106:$P$255,"Insurance Pass-Thru") -> 0 | D76: =SUMIFS($E$106:$E$255,$P$106:$P$255,"Insurance Pass-Thru") -> 0 | E76: =SUMIFS($F$106:$F$255,$P$106:$P$255,"Insurance Pass-Thru") -> 0 | F76: =SUMIFS($G$106:$G$255,$P$106:$P$255,"Insurance Pass-Thru") -> 0 | G76: =SUMIFS($H$106:$H$255,$P$106:$P$255,"Insurance Pass-Thru") -> 0 | H76: =SUMIFS($I$106:$I$255,$P$106:$P$255,"Insurance Pass-Thru") -> 0 | I76: =SUMIFS($J$106:$J$255,$P$106:$P$255,"Insurance Pass-Thru") -> 0 | J76: =SUMIFS($K$106:$K$255,$P$106:$P$255,"Insurance Pass-Thru") -> 0 | K76: =SUMIFS($L$106:$L$255,$P$106:$P$255,"Insurance Pass-Thru") -> 0 | L76: =SUMIFS($M$106:$M$255,$P$106:$P$255,"Insurance Pass-Thru") -> 0 | M76: =SUMIFS($N$106:$N$255,$P$106:$P$255,"Insurance Pass-Thru") -> 0 | N76: =SUMIFS($O$106:$O$255,$P$106:$P$255,"Insurance Pass-Thru") -> 0 | O76: =SUM(K76:M76)*4 -> 0 | P76: =IFERROR(N76/12/'Prop Info'!$B$6,0) -> 0 | Q76: =IFERROR(N76/N$80,0) -> 0 | R76: =IFERROR(IF(OR(VLOOKUP(A76,_StdCOA!$A$4:$E$56,4,0)=0,VLOOKUP(A76,_StdCOA!$A$4:$E$56,5,0)=0),"",IF(ABS(P76)>VLOOKUP(A76,_StdCOA!$A$4:$E$56,5,0),"🔴 high",IF(ABS(P76)<VLOOKUP(A76,_StdCOA!$A$4:$E$56,4,0),"🟢 low","🟡 in range"))),"")
A77: Misc Other Income | B77: =SUMIFS($C$106:$C$255,$P$106:$P$255,"Misc Other Income") -> 0 | C77: =SUMIFS($D$106:$D$255,$P$106:$P$255,"Misc Other Income") -> 0 | D77: =SUMIFS($E$106:$E$255,$P$106:$P$255,"Misc Other Income") -> 0 | E77: =SUMIFS($F$106:$F$255,$P$106:$P$255,"Misc Other Income") -> 0 | F77: =SUMIFS($G$106:$G$255,$P$106:$P$255,"Misc Other Income") -> 0 | G77: =SUMIFS($H$106:$H$255,$P$106:$P$255,"Misc Other Income") -> 0 | H77: =SUMIFS($I$106:$I$255,$P$106:$P$255,"Misc Other Income") -> 0 | I77: =SUMIFS($J$106:$J$255,$P$106:$P$255,"Misc Other Income") -> 0 | J77: =SUMIFS($K$106:$K$255,$P$106:$P$255,"Misc Other Income") -> 0 | K77: =SUMIFS($L$106:$L$255,$P$106:$P$255,"Misc Other Income") -> 0 | L77: =SUMIFS($M$106:$M$255,$P$106:$P$255,"Misc Other Income") -> 0 | M77: =SUMIFS($N$106:$N$255,$P$106:$P$255,"Misc Other Income") -> 0 | N77: =SUMIFS($O$106:$O$255,$P$106:$P$255,"Misc Other Income") -> 0 | O77: =SUM(K77:M77)*4 -> 0 | P77: =IFERROR(N77/12/'Prop Info'!$B$6,0) -> 0 | Q77: =IFERROR(N77/N$80,0) -> 0 | R77: =IFERROR(IF(OR(VLOOKUP(A77,_StdCOA!$A$4:$E$56,4,0)=0,VLOOKUP(A77,_StdCOA!$A$4:$E$56,5,0)=0),"",IF(ABS(P77)>VLOOKUP(A77,_StdCOA!$A$4:$E$56,5,0),"🔴 high",IF(ABS(P77)<VLOOKUP(A77,_StdCOA!$A$4:$E$56,4,0),"🟢 low","🟡 in range"))),"")
A78: Renter's Insurance | B78: =SUMIFS($C$106:$C$255,$P$106:$P$255,$A78) -> 0 | C78: =SUMIFS($D$106:$D$255,$P$106:$P$255,$A78) -> 0 | D78: =SUMIFS($E$106:$E$255,$P$106:$P$255,$A78) -> 0 | E78: =SUMIFS($F$106:$F$255,$P$106:$P$255,$A78) -> 0 | F78: =SUMIFS($G$106:$G$255,$P$106:$P$255,$A78) -> 0 | G78: =SUMIFS($H$106:$H$255,$P$106:$P$255,$A78) -> 0 | H78: =SUMIFS($I$106:$I$255,$P$106:$P$255,$A78) -> 0 | I78: =SUMIFS($J$106:$J$255,$P$106:$P$255,$A78) -> 0 | J78: =SUMIFS($K$106:$K$255,$P$106:$P$255,$A78) -> 0 | K78: =SUMIFS($L$106:$L$255,$P$106:$P$255,$A78) -> 0 | L78: =SUMIFS($M$106:$M$255,$P$106:$P$255,$A78) -> 0 | M78: =SUMIFS($N$106:$N$255,$P$106:$P$255,$A78) -> 0 | N78: =SUMIFS($O$106:$O$255,$P$106:$P$255,$A78) -> 0 | O78: =SUM(K78:M78)*4 -> 0 | P78: =IFERROR(N78/12/'Prop Info'!$B$6,0) -> 0 | Q78: =IFERROR(N78/N$80,0) -> 0
A79: Total Other Income | B79: =B68+B69+B70+B71+B72+B73+B74+B75+B76+B77+B78 -> 0 | C79: =C68+C69+C70+C71+C72+C73+C74+C75+C76+C77+C78 -> 0 | D79: =D68+D69+D70+D71+D72+D73+D74+D75+D76+D77+D78 -> 0 | E79: =E68+E69+E70+E71+E72+E73+E74+E75+E76+E77+E78 -> 0 | F79: =F68+F69+F70+F71+F72+F73+F74+F75+F76+F77+F78 -> 0 | G79: =G68+G69+G70+G71+G72+G73+G74+G75+G76+G77+G78 -> 0 | H79: =H68+H69+H70+H71+H72+H73+H74+H75+H76+H77+H78 -> 0 | I79: =I68+I69+I70+I71+I72+I73+I74+I75+I76+I77+I78 -> 0 | ... N79: =N68+N69+N70+N71+N72+N73+N74+N75+N76+N77+N78 -> 0 | O79: =SUM(K79:M79)*4 -> 0 | P79: =IFERROR(N79/12/'Prop Info'!$B$6,0) -> 0 | Q79: =IFERROR(N79/N$80,0) -> 0
A80: EFFECTIVE GROSS INCOME | B80: =B67+B79 -> 0 | C80: =C67+C79 -> 0 | D80: =D67+D79 -> 0 | E80: =E67+E79 -> 0 | F80: =F67+F79 -> 0 | G80: =G67+G79 -> 0 | H80: =H67+H79 -> 0 | I80: =I67+I79 -> 0 | ... N80: =N67+N79 -> 0 | O80: =SUM(K80:M80)*4 -> 0 | P80: =IFERROR(N80/12/'Prop Info'!$B$6,0) -> 0 | Q80: =IFERROR(N80/N$80,0) -> 0
A81: OPERATING EXPENSES
A82: Repairs & Maintenance | B82: =SUMIFS($C$106:$C$255,$P$106:$P$255,"Repairs & Maintenance") -> 0 | C82: =SUMIFS($D$106:$D$255,$P$106:$P$255,"Repairs & Maintenance") -> 0 | D82: =SUMIFS($E$106:$E$255,$P$106:$P$255,"Repairs & Maintenance") -> 0 | E82: =SUMIFS($F$106:$F$255,$P$106:$P$255,"Repairs & Maintenance") -> 0 | F82: =SUMIFS($G$106:$G$255,$P$106:$P$255,"Repairs & Maintenance") -> 0 | G82: =SUMIFS($H$106:$H$255,$P$106:$P$255,"Repairs & Maintenance") -> 0 | H82: =SUMIFS($I$106:$I$255,$P$106:$P$255,"Repairs & Maintenance") -> 0 | I82: =SUMIFS($J$106:$J$255,$P$106:$P$255,"Repairs & Maintenance") -> 0 | J82: =SUMIFS($K$106:$K$255,$P$106:$P$255,"Repairs & Maintenance") -> 0 | K82: =SUMIFS($L$106:$L$255,$P$106:$P$255,"Repairs & Maintenance") -> 0 | L82: =SUMIFS($M$106:$M$255,$P$106:$P$255,"Repairs & Maintenance") -> 0 | M82: =SUMIFS($N$106:$N$255,$P$106:$P$255,"Repairs & Maintenance") -> 0 | N82: =SUMIFS($O$106:$O$255,$P$106:$P$255,"Repairs & Maintenance") -> 0 | O82: =SUM(K82:M82)*4 -> 0 | P82: =IFERROR(N82/12/'Prop Info'!$B$6,0) -> 0 | Q82: =IFERROR(N82/N$80,0) -> 0 | R82: =IFERROR(IF(OR(VLOOKUP(A82,_StdCOA!$A$4:$E$56,4,0)=0,VLOOKUP(A82,_StdCOA!$A$4:$E$56,5,0)=0),"",IF(ABS(P82)>VLOOKUP(A82,_StdCOA!$A$4:$E$56,5,0),"🔴 high",IF(ABS(P82)<VLOOKUP(A82,_StdCOA!$A$4:$E$56,4,0),"🟢 low","🟡 in range"))),"") -> 🟢 low
A83: Contract Services | B83: =SUMIFS($C$106:$C$255,$P$106:$P$255,"Contract Services") -> 0 | C83: =SUMIFS($D$106:$D$255,$P$106:$P$255,"Contract Services") -> 0 | D83: =SUMIFS($E$106:$E$255,$P$106:$P$255,"Contract Services") -> 0 | E83: =SUMIFS($F$106:$F$255,$P$106:$P$255,"Contract Services") -> 0 | F83: =SUMIFS($G$106:$G$255,$P$106:$P$255,"Contract Services") -> 0 | G83: =SUMIFS($H$106:$H$255,$P$106:$P$255,"Contract Services") -> 0 | H83: =SUMIFS($I$106:$I$255,$P$106:$P$255,"Contract Services") -> 0 | I83: =SUMIFS($J$106:$J$255,$P$106:$P$255,"Contract Services") -> 0 | J83: =SUMIFS($K$106:$K$255,$P$106:$P$255,"Contract Services") -> 0 | K83: =SUMIFS($L$106:$L$255,$P$106:$P$255,"Contract Services") -> 0 | L83: =SUMIFS($M$106:$M$255,$P$106:$P$255,"Contract Services") -> 0 | M83: =SUMIFS($N$106:$N$255,$P$106:$P$255,"Contract Services") -> 0 | N83: =SUMIFS($O$106:$O$255,$P$106:$P$255,"Contract Services") -> 0 | O83: =SUM(K83:M83)*4 -> 0 | P83: =IFERROR(N83/12/'Prop Info'!$B$6,0) -> 0 | Q83: =IFERROR(N83/N$80,0) -> 0 | R83: =IFERROR(IF(OR(VLOOKUP(A83,_StdCOA!$A$4:$E$56,4,0)=0,VLOOKUP(A83,_StdCOA!$A$4:$E$56,5,0)=0),"",IF(ABS(P83)>VLOOKUP(A83,_StdCOA!$A$4:$E$56,5,0),"🔴 high",IF(ABS(P83)<VLOOKUP(A83,_StdCOA!$A$4:$E$56,4,0),"🟢 low","🟡 in range"))),"")
A84: Landscaping | B84: =SUMIFS($C$106:$C$255,$P$106:$P$255,"Landscaping") -> 0 | C84: =SUMIFS($D$106:$D$255,$P$106:$P$255,"Landscaping") -> 0 | D84: =SUMIFS($E$106:$E$255,$P$106:$P$255,"Landscaping") -> 0 | E84: =SUMIFS($F$106:$F$255,$P$106:$P$255,"Landscaping") -> 0 | F84: =SUMIFS($G$106:$G$255,$P$106:$P$255,"Landscaping") -> 0 | G84: =SUMIFS($H$106:$H$255,$P$106:$P$255,"Landscaping") -> 0 | H84: =SUMIFS($I$106:$I$255,$P$106:$P$255,"Landscaping") -> 0 | I84: =SUMIFS($J$106:$J$255,$P$106:$P$255,"Landscaping") -> 0 | J84: =SUMIFS($K$106:$K$255,$P$106:$P$255,"Landscaping") -> 0 | K84: =SUMIFS($L$106:$L$255,$P$106:$P$255,"Landscaping") -> 0 | L84: =SUMIFS($M$106:$M$255,$P$106:$P$255,"Landscaping") -> 0 | M84: =SUMIFS($N$106:$N$255,$P$106:$P$255,"Landscaping") -> 0 | N84: =SUMIFS($O$106:$O$255,$P$106:$P$255,"Landscaping") -> 0 | O84: =SUM(K84:M84)*4 -> 0 | P84: =IFERROR(N84/12/'Prop Info'!$B$6,0) -> 0 | Q84: =IFERROR(N84/N$80,0) -> 0 | R84: =IFERROR(IF(OR(VLOOKUP(A84,_StdCOA!$A$4:$E$56,4,0)=0,VLOOKUP(A84,_StdCOA!$A$4:$E$56,5,0)=0),"",IF(ABS(P84)>VLOOKUP(A84,_StdCOA!$A$4:$E$56,5,0),"🔴 high",IF(ABS(P84)<VLOOKUP(A84,_StdCOA!$A$4:$E$56,4,0),"🟢 low","🟡 in range"))),"") -> 🟢 low
A85: Pest Control | B85: =SUMIFS($C$106:$C$255,$P$106:$P$255,"Pest Control") -> 0 | C85: =SUMIFS($D$106:$D$255,$P$106:$P$255,"Pest Control") -> 0 | D85: =SUMIFS($E$106:$E$255,$P$106:$P$255,"Pest Control") -> 0 | E85: =SUMIFS($F$106:$F$255,$P$106:$P$255,"Pest Control") -> 0 | F85: =SUMIFS($G$106:$G$255,$P$106:$P$255,"Pest Control") -> 0 | G85: =SUMIFS($H$106:$H$255,$P$106:$P$255,"Pest Control") -> 0 | H85: =SUMIFS($I$106:$I$255,$P$106:$P$255,"Pest Control") -> 0 | I85: =SUMIFS($J$106:$J$255,$P$106:$P$255,"Pest Control") -> 0 | J85: =SUMIFS($K$106:$K$255,$P$106:$P$255,"Pest Control") -> 0 | K85: =SUMIFS($L$106:$L$255,$P$106:$P$255,"Pest Control") -> 0 | L85: =SUMIFS($M$106:$M$255,$P$106:$P$255,"Pest Control") -> 0 | M85: =SUMIFS($N$106:$N$255,$P$106:$P$255,"Pest Control") -> 0 | N85: =SUMIFS($O$106:$O$255,$P$106:$P$255,"Pest Control") -> 0 | O85: =SUM(K85:M85)*4 -> 0 | P85: =IFERROR(N85/12/'Prop Info'!$B$6,0) -> 0 | Q85: =IFERROR(N85/N$80,0) -> 0 | R85: =IFERROR(IF(OR(VLOOKUP(A85,_StdCOA!$A$4:$E$56,4,0)=0,VLOOKUP(A85,_StdCOA!$A$4:$E$56,5,0)=0),"",IF(ABS(P85)>VLOOKUP(A85,_StdCOA!$A$4:$E$56,5,0),"🔴 high",IF(ABS(P85)<VLOOKUP(A85,_StdCOA!$A$4:$E$56,4,0),"🟢 low","🟡 in range"))),"") -> 🟢 low
A86: Pool / Amenity Maintenance | B86: =SUMIFS($C$106:$C$255,$P$106:$P$255,"Pool / Amenity Maintenance") -> 0 | C86: =SUMIFS($D$106:$D$255,$P$106:$P$255,"Pool / Amenity Maintenance") -> 0 | D86: =SUMIFS($E$106:$E$255,$P$106:$P$255,"Pool / Amenity Maintenance") -> 0 | E86: =SUMIFS($F$106:$F$255,$P$106:$P$255,"Pool / Amenity Maintenance") -> 0 | F86: =SUMIFS($G$106:$G$255,$P$106:$P$255,"Pool / Amenity Maintenance") -> 0 | G86: =SUMIFS($H$106:$H$255,$P$106:$P$255,"Pool / Amenity Maintenance") -> 0 | H86: =SUMIFS($I$106:$I$255,$P$106:$P$255,"Pool / Amenity Maintenance") -> 0 | I86: =SUMIFS($J$106:$J$255,$P$106:$P$255,"Pool / Amenity Maintenance") -> 0 | J86: =SUMIFS($K$106:$K$255,$P$106:$P$255,"Pool / Amenity Maintenance") -> 0 | K86: =SUMIFS($L$106:$L$255,$P$106:$P$255,"Pool / Amenity Maintenance") -> 0 | L86: =SUMIFS($M$106:$M$255,$P$106:$P$255,"Pool / Amenity Maintenance") -> 0 | M86: =SUMIFS($N$106:$N$255,$P$106:$P$255,"Pool / Amenity Maintenance") -> 0 | N86: =SUMIFS($O$106:$O$255,$P$106:$P$255,"Pool / Amenity Maintenance") -> 0 | O86: =SUM(K86:M86)*4 -> 0 | P86: =IFERROR(N86/12/'Prop Info'!$B$6,0) -> 0 | Q86: =IFERROR(N86/N$80,0) -> 0 | R86: =IFERROR(IF(OR(VLOOKUP(A86,_StdCOA!$A$4:$E$56,4,0)=0,VLOOKUP(A86,_StdCOA!$A$4:$E$56,5,0)=0),"",IF(ABS(P86)>VLOOKUP(A86,_StdCOA!$A$4:$E$56,5,0),"🔴 high",IF(ABS(P86)<VLOOKUP(A86,_StdCOA!$A$4:$E$56,4,0),"🟢 low","🟡 in range"))),"") -> 🟢 low
A87: Make-Ready / Turnover | B87: =SUMIFS($C$106:$C$255,$P$106:$P$255,"Make-Ready / Turnover") -> 0 | C87: =SUMIFS($D$106:$D$255,$P$106:$P$255,"Make-Ready / Turnover") -> 0 | D87: =SUMIFS($E$106:$E$255,$P$106:$P$255,"Make-Ready / Turnover") -> 0 | E87: =SUMIFS($F$106:$F$255,$P$106:$P$255,"Make-Ready / Turnover") -> 0 | F87: =SUMIFS($G$106:$G$255,$P$106:$P$255,"Make-Ready / Turnover") -> 0 | G87: =SUMIFS($H$106:$H$255,$P$106:$P$255,"Make-Ready / Turnover") -> 0 | H87: =SUMIFS($I$106:$I$255,$P$106:$P$255,"Make-Ready / Turnover") -> 0 | I87: =SUMIFS($J$106:$J$255,$P$106:$P$255,"Make-Ready / Turnover") -> 0 | J87: =SUMIFS($K$106:$K$255,$P$106:$P$255,"Make-Ready / Turnover") -> 0 | K87: =SUMIFS($L$106:$L$255,$P$106:$P$255,"Make-Ready / Turnover") -> 0 | L87: =SUMIFS($M$106:$M$255,$P$106:$P$255,"Make-Ready / Turnover") -> 0 | M87: =SUMIFS($N$106:$N$255,$P$106:$P$255,"Make-Ready / Turnover") -> 0 | N87: =SUMIFS($O$106:$O$255,$P$106:$P$255,"Make-Ready / Turnover") -> 0 | O87: =SUM(K87:M87)*4 -> 0 | P87: =IFERROR(N87/12/'Prop Info'!$B$6,0) -> 0 | Q87: =IFERROR(N87/N$80,0) -> 0 | R87: =IFERROR(IF(OR(VLOOKUP(A87,_StdCOA!$A$4:$E$56,4,0)=0,VLOOKUP(A87,_StdCOA!$A$4:$E$56,5,0)=0),"",IF(ABS(P87)>VLOOKUP(A87,_StdCOA!$A$4:$E$56,5,0),"🔴 high",IF(ABS(P87)<VLOOKUP(A87,_StdCOA!$A$4:$E$56,4,0),"🟢 low","🟡 in range"))),"") -> 🟢 low
A88: Payroll — On-Site | B88: =SUMIFS($C$106:$C$255,$P$106:$P$255,"Payroll — On-Site") -> 0 | C88: =SUMIFS($D$106:$D$255,$P$106:$P$255,"Payroll — On-Site") -> 0 | D88: =SUMIFS($E$106:$E$255,$P$106:$P$255,"Payroll — On-Site") -> 0 | E88: =SUMIFS($F$106:$F$255,$P$106:$P$255,"Payroll — On-Site") -> 0 | F88: =SUMIFS($G$106:$G$255,$P$106:$P$255,"Payroll — On-Site") -> 0 | G88: =SUMIFS($H$106:$H$255,$P$106:$P$255,"Payroll — On-Site") -> 0 | H88: =SUMIFS($I$106:$I$255,$P$106:$P$255,"Payroll — On-Site") -> 0 | I88: =SUMIFS($J$106:$J$255,$P$106:$P$255,"Payroll — On-Site") -> 0 | J88: =SUMIFS($K$106:$K$255,$P$106:$P$255,"Payroll — On-Site") -> 0 | K88: =SUMIFS($L$106:$L$255,$P$106:$P$255,"Payroll — On-Site") -> 0 | L88: =SUMIFS($M$106:$M$255,$P$106:$P$255,"Payroll — On-Site") -> 0 | M88: =SUMIFS($N$106:$N$255,$P$106:$P$255,"Payroll — On-Site") -> 0 | N88: =SUMIFS($O$106:$O$255,$P$106:$P$255,"Payroll — On-Site") -> 0 | O88: =SUM(K88:M88)*4 -> 0 | P88: =IFERROR(N88/12/'Prop Info'!$B$6,0) -> 0 | Q88: =IFERROR(N88/N$80,0) -> 0 | R88: =IFERROR(IF(OR(VLOOKUP(A88,_StdCOA!$A$4:$E$56,4,0)=0,VLOOKUP(A88,_StdCOA!$A$4:$E$56,5,0)=0),"",IF(ABS(P88)>VLOOKUP(A88,_StdCOA!$A$4:$E$56,5,0),"🔴 high",IF(ABS(P88)<VLOOKUP(A88,_StdCOA!$A$4:$E$56,4,0),"🟢 low","🟡 in range"))),"") -> 🟢 low
A89: Leasing & Marketing | B89: =SUMIFS($C$106:$C$255,$P$106:$P$255,"Leasing & Marketing") -> 0 | C89: =SUMIFS($D$106:$D$255,$P$106:$P$255,"Leasing & Marketing") -> 0 | D89: =SUMIFS($E$106:$E$255,$P$106:$P$255,"Leasing & Marketing") -> 0 | E89: =SUMIFS($F$106:$F$255,$P$106:$P$255,"Leasing & Marketing") -> 0 | F89: =SUMIFS($G$106:$G$255,$P$106:$P$255,"Leasing & Marketing") -> 0 | G89: =SUMIFS($H$106:$H$255,$P$106:$P$255,"Leasing & Marketing") -> 0 | H89: =SUMIFS($I$106:$I$255,$P$106:$P$255,"Leasing & Marketing") -> 0 | I89: =SUMIFS($J$106:$J$255,$P$106:$P$255,"Leasing & Marketing") -> 0 | J89: =SUMIFS($K$106:$K$255,$P$106:$P$255,"Leasing & Marketing") -> 0 | K89: =SUMIFS($L$106:$L$255,$P$106:$P$255,"Leasing & Marketing") -> 0 | L89: =SUMIFS($M$106:$M$255,$P$106:$P$255,"Leasing & Marketing") -> 0 | M89: =SUMIFS($N$106:$N$255,$P$106:$P$255,"Leasing & Marketing") -> 0 | N89: =SUMIFS($O$106:$O$255,$P$106:$P$255,"Leasing & Marketing") -> 0 | O89: =SUM(K89:M89)*4 -> 0 | P89: =IFERROR(N89/12/'Prop Info'!$B$6,0) -> 0 | Q89: =IFERROR(N89/N$80,0) -> 0 | R89: =IFERROR(IF(OR(VLOOKUP(A89,_StdCOA!$A$4:$E$56,4,0)=0,VLOOKUP(A89,_StdCOA!$A$4:$E$56,5,0)=0),"",IF(ABS(P89)>VLOOKUP(A89,_StdCOA!$A$4:$E$56,5,0),"🔴 high",IF(ABS(P89)<VLOOKUP(A89,_StdCOA!$A$4:$E$56,4,0),"🟢 low","🟡 in range"))),"") -> 🟢 low
A90: General & Administrative | B90: =SUMIFS($C$106:$C$255,$P$106:$P$255,"General & Administrative") -> 0 | C90: =SUMIFS($D$106:$D$255,$P$106:$P$255,"General & Administrative") -> 0 | D90: =SUMIFS($E$106:$E$255,$P$106:$P$255,"General & Administrative") -> 0 | E90: =SUMIFS($F$106:$F$255,$P$106:$P$255,"General & Administrative") -> 0 | F90: =SUMIFS($G$106:$G$255,$P$106:$P$255,"General & Administrative") -> 0 | G90: =SUMIFS($H$106:$H$255,$P$106:$P$255,"General & Administrative") -> 0 | H90: =SUMIFS($I$106:$I$255,$P$106:$P$255,"General & Administrative") -> 0 | I90: =SUMIFS($J$106:$J$255,$P$106:$P$255,"General & Administrative") -> 0 | J90: =SUMIFS($K$106:$K$255,$P$106:$P$255,"General & Administrative") -> 0 | K90: =SUMIFS($L$106:$L$255,$P$106:$P$255,"General & Administrative") -> 0 | L90: =SUMIFS($M$106:$M$255,$P$106:$P$255,"General & Administrative") -> 0 | M90: =SUMIFS($N$106:$N$255,$P$106:$P$255,"General & Administrative") -> 0 | N90: =SUMIFS($O$106:$O$255,$P$106:$P$255,"General & Administrative") -> 0 | O90: =SUM(K90:M90)*4 -> 0 | P90: =IFERROR(N90/12/'Prop Info'!$B$6,0) -> 0 | Q90: =IFERROR(N90/N$80,0) -> 0 | R90: =IFERROR(IF(OR(VLOOKUP(A90,_StdCOA!$A$4:$E$56,4,0)=0,VLOOKUP(A90,_StdCOA!$A$4:$E$56,5,0)=0),"",IF(ABS(P90)>VLOOKUP(A90,_StdCOA!$A$4:$E$56,5,0),"🔴 high",IF(ABS(P90)<VLOOKUP(A90,_StdCOA!$A$4:$E$56,4,0),"🟢 low","🟡 in range"))),"") -> 🟢 low
A91: Legal / Eviction | B91: =SUMIFS($C$106:$C$255,$P$106:$P$255,"Legal / Eviction") -> 0 | C91: =SUMIFS($D$106:$D$255,$P$106:$P$255,"Legal / Eviction") -> 0 | D91: =SUMIFS($E$106:$E$255,$P$106:$P$255,"Legal / Eviction") -> 0 | E91: =SUMIFS($F$106:$F$255,$P$106:$P$255,"Legal / Eviction") -> 0 | F91: =SUMIFS($G$106:$G$255,$P$106:$P$255,"Legal / Eviction") -> 0 | G91: =SUMIFS($H$106:$H$255,$P$106:$P$255,"Legal / Eviction") -> 0 | H91: =SUMIFS($I$106:$I$255,$P$106:$P$255,"Legal / Eviction") -> 0 | I91: =SUMIFS($J$106:$J$255,$P$106:$P$255,"Legal / Eviction") -> 0 | J91: =SUMIFS($K$106:$K$255,$P$106:$P$255,"Legal / Eviction") -> 0 | K91: =SUMIFS($L$106:$L$255,$P$106:$P$255,"Legal / Eviction") -> 0 | L91: =SUMIFS($M$106:$M$255,$P$106:$P$255,"Legal / Eviction") -> 0 | M91: =SUMIFS($N$106:$N$255,$P$106:$P$255,"Legal / Eviction") -> 0 | N91: =SUMIFS($O$106:$O$255,$P$106:$P$255,"Legal / Eviction") -> 0 | O91: =SUM(K91:M91)*4 -> 0 | P91: =IFERROR(N91/12/'Prop Info'!$B$6,0) -> 0 | Q91: =IFERROR(N91/N$80,0) -> 0 | R91: =IFERROR(IF(OR(VLOOKUP(A91,_StdCOA!$A$4:$E$56,4,0)=0,VLOOKUP(A91,_StdCOA!$A$4:$E$56,5,0)=0),"",IF(ABS(P91)>VLOOKUP(A91,_StdCOA!$A$4:$E$56,5,0),"🔴 high",IF(ABS(P91)<VLOOKUP(A91,_StdCOA!$A$4:$E$56,4,0),"🟢 low","🟡 in range"))),"") -> 🟢 low
A92: Insurance | B92: =SUMIFS($C$106:$C$255,$P$106:$P$255,"Insurance") -> 0 | C92: =SUMIFS($D$106:$D$255,$P$106:$P$255,"Insurance") -> 0 | D92: =SUMIFS($E$106:$E$255,$P$106:$P$255,"Insurance") -> 0 | E92: =SUMIFS($F$106:$F$255,$P$106:$P$255,"Insurance") -> 0 | F92: =SUMIFS($G$106:$G$255,$P$106:$P$255,"Insurance") -> 0 | G92: =SUMIFS($H$106:$H$255,$P$106:$P$255,"Insurance") -> 0 | H92: =SUMIFS($I$106:$I$255,$P$106:$P$255,"Insurance") -> 0 | I92: =SUMIFS($J$106:$J$255,$P$106:$P$255,"Insurance") -> 0 | J92: =SUMIFS($K$106:$K$255,$P$106:$P$255,"Insurance") -> 0 | K92: =SUMIFS($L$106:$L$255,$P$106:$P$255,"Insurance") -> 0 | L92: =SUMIFS($M$106:$M$255,$P$106:$P$255,"Insurance") -> 0 | M92: =SUMIFS($N$106:$N$255,$P$106:$P$255,"Insurance") -> 0 | N92: =SUMIFS($O$106:$O$255,$P$106:$P$255,"Insurance") -> 0 | O92: =SUM(K92:M92)*4 -> 0 | P92: =IFERROR(N92/12/'Prop Info'!$B$6,0) -> 0 | Q92: =IFERROR(N92/N$80,0) -> 0 | R92: =IFERROR(IF(OR(VLOOKUP(A92,_StdCOA!$A$4:$E$56,4,0)=0,VLOOKUP(A92,_StdCOA!$A$4:$E$56,5,0)=0),"",IF(ABS(P92)>VLOOKUP(A92,_StdCOA!$A$4:$E$56,5,0),"🔴 high",IF(ABS(P92)<VLOOKUP(A92,_StdCOA!$A$4:$E$56,4,0),"🟢 low","🟡 in range"))),"") -> 🟢 low
A93: Real Estate Taxes | B93: =SUMIFS($C$106:$C$255,$P$106:$P$255,"Real Estate Taxes") -> 0 | C93: =SUMIFS($D$106:$D$255,$P$106:$P$255,"Real Estate Taxes") -> 0 | D93: =SUMIFS($E$106:$E$255,$P$106:$P$255,"Real Estate Taxes") -> 0 | E93: =SUMIFS($F$106:$F$255,$P$106:$P$255,"Real Estate Taxes") -> 0 | F93: =SUMIFS($G$106:$G$255,$P$106:$P$255,"Real Estate Taxes") -> 0 | G93: =SUMIFS($H$106:$H$255,$P$106:$P$255,"Real Estate Taxes") -> 0 | H93: =SUMIFS($I$106:$I$255,$P$106:$P$255,"Real Estate Taxes") -> 0 | I93: =SUMIFS($J$106:$J$255,$P$106:$P$255,"Real Estate Taxes") -> 0 | J93: =SUMIFS($K$106:$K$255,$P$106:$P$255,"Real Estate Taxes") -> 0 | K93: =SUMIFS($L$106:$L$255,$P$106:$P$255,"Real Estate Taxes") -> 0 | L93: =SUMIFS($M$106:$M$255,$P$106:$P$255,"Real Estate Taxes") -> 0 | M93: =SUMIFS($N$106:$N$255,$P$106:$P$255,"Real Estate Taxes") -> 0 | N93: =SUMIFS($O$106:$O$255,$P$106:$P$255,"Real Estate Taxes") -> 0 | O93: =SUM(K93:M93)*4 -> 0 | P93: =IFERROR(N93/12/'Prop Info'!$B$6,0) -> 0 | Q93: =IFERROR(N93/N$80,0) -> 0 | R93: =IFERROR(IF(OR(VLOOKUP(A93,_StdCOA!$A$4:$E$56,4,0)=0,VLOOKUP(A93,_StdCOA!$A$4:$E$56,5,0)=0),"",IF(ABS(P93)>VLOOKUP(A93,_StdCOA!$A$4:$E$56,5,0),"🔴 high",IF(ABS(P93)<VLOOKUP(A93,_StdCOA!$A$4:$E$56,4,0),"🟢 low","🟡 in range"))),"") -> 🟢 low
A94: Utilities — Electric | B94: =SUMIFS($C$106:$C$255,$P$106:$P$255,"Utilities — Electric") -> 0 | C94: =SUMIFS($D$106:$D$255,$P$106:$P$255,"Utilities — Electric") -> 0 | D94: =SUMIFS($E$106:$E$255,$P$106:$P$255,"Utilities — Electric") -> 0 | E94: =SUMIFS($F$106:$F$255,$P$106:$P$255,"Utilities — Electric") -> 0 | F94: =SUMIFS($G$106:$G$255,$P$106:$P$255,"Utilities — Electric") -> 0 | G94: =SUMIFS($H$106:$H$255,$P$106:$P$255,"Utilities — Electric") -> 0 | H94: =SUMIFS($I$106:$I$255,$P$106:$P$255,"Utilities — Electric") -> 0 | I94: =SUMIFS($J$106:$J$255,$P$106:$P$255,"Utilities — Electric") -> 0 | J94: =SUMIFS($K$106:$K$255,$P$106:$P$255,"Utilities — Electric") -> 0 | K94: =SUMIFS($L$106:$L$255,$P$106:$P$255,"Utilities — Electric") -> 0 | L94: =SUMIFS($M$106:$M$255,$P$106:$P$255,"Utilities — Electric") -> 0 | M94: =SUMIFS($N$106:$N$255,$P$106:$P$255,"Utilities — Electric") -> 0 | N94: =SUMIFS($O$106:$O$255,$P$106:$P$255,"Utilities — Electric") -> 0 | O94: =SUM(K94:M94)*4 -> 0 | P94: =IFERROR(N94/12/'Prop Info'!$B$6,0) -> 0 | Q94: =IFERROR(N94/N$80,0) -> 0 | R94: =IFERROR(IF(OR(VLOOKUP(A94,_StdCOA!$A$4:$E$56,4,0)=0,VLOOKUP(A94,_StdCOA!$A$4:$E$56,5,0)=0),"",IF(ABS(P94)>VLOOKUP(A94,_StdCOA!$A$4:$E$56,5,0),"🔴 high",IF(ABS(P94)<VLOOKUP(A94,_StdCOA!$A$4:$E$56,4,0),"🟢 low","🟡 in range"))),"") -> 🟢 low
A95: Utilities — Gas | B95: =SUMIFS($C$106:$C$255,$P$106:$P$255,"Utilities — Gas") -> 0 | C95: =SUMIFS($D$106:$D$255,$P$106:$P$255,"Utilities — Gas") -> 0 | D95: =SUMIFS($E$106:$E$255,$P$106:$P$255,"Utilities — Gas") -> 0 | E95: =SUMIFS($F$106:$F$255,$P$106:$P$255,"Utilities — Gas") -> 0 | F95: =SUMIFS($G$106:$G$255,$P$106:$P$255,"Utilities — Gas") -> 0 | G95: =SUMIFS($H$106:$H$255,$P$106:$P$255,"Utilities — Gas") -> 0 | H95: =SUMIFS($I$106:$I$255,$P$106:$P$255,"Utilities — Gas") -> 0 | I95: =SUMIFS($J$106:$J$255,$P$106:$P$255,"Utilities — Gas") -> 0 | J95: =SUMIFS($K$106:$K$255,$P$106:$P$255,"Utilities — Gas") -> 0 | K95: =SUMIFS($L$106:$L$255,$P$106:$P$255,"Utilities — Gas") -> 0 | L95: =SUMIFS($M$106:$M$255,$P$106:$P$255,"Utilities — Gas") -> 0 | M95: =SUMIFS($N$106:$N$255,$P$106:$P$255,"Utilities — Gas") -> 0 | N95: =SUMIFS($O$106:$O$255,$P$106:$P$255,"Utilities — Gas") -> 0 | O95: =SUM(K95:M95)*4 -> 0 | P95: =IFERROR(N95/12/'Prop Info'!$B$6,0) -> 0 | Q95: =IFERROR(N95/N$80,0) -> 0 | R95: =IFERROR(IF(OR(VLOOKUP(A95,_StdCOA!$A$4:$E$56,4,0)=0,VLOOKUP(A95,_StdCOA!$A$4:$E$56,5,0)=0),"",IF(ABS(P95)>VLOOKUP(A95,_StdCOA!$A$4:$E$56,5,0),"🔴 high",IF(ABS(P95)<VLOOKUP(A95,_StdCOA!$A$4:$E$56,4,0),"🟢 low","🟡 in range"))),"")
A96: Utilities — Water/Sewer | B96: =SUMIFS($C$106:$C$255,$P$106:$P$255,"Utilities — Water/Sewer") -> 0 | C96: =SUMIFS($D$106:$D$255,$P$106:$P$255,"Utilities — Water/Sewer") -> 0 | D96: =SUMIFS($E$106:$E$255,$P$106:$P$255,"Utilities — Water/Sewer") -> 0 | E96: =SUMIFS($F$106:$F$255,$P$106:$P$255,"Utilities — Water/Sewer") -> 0 | F96: =SUMIFS($G$106:$G$255,$P$106:$P$255,"Utilities — Water/Sewer") -> 0 | G96: =SUMIFS($H$106:$H$255,$P$106:$P$255,"Utilities — Water/Sewer") -> 0 | H96: =SUMIFS($I$106:$I$255,$P$106:$P$255,"Utilities — Water/Sewer") -> 0 | I96: =SUMIFS($J$106:$J$255,$P$106:$P$255,"Utilities — Water/Sewer") -> 0 | J96: =SUMIFS($K$106:$K$255,$P$106:$P$255,"Utilities — Water/Sewer") -> 0 | K96: =SUMIFS($L$106:$L$255,$P$106:$P$255,"Utilities — Water/Sewer") -> 0 | L96: =SUMIFS($M$106:$M$255,$P$106:$P$255,"Utilities — Water/Sewer") -> 0 | M96: =SUMIFS($N$106:$N$255,$P$106:$P$255,"Utilities — Water/Sewer") -> 0 | N96: =SUMIFS($O$106:$O$255,$P$106:$P$255,"Utilities — Water/Sewer") -> 0 | O96: =SUM(K96:M96)*4 -> 0 | P96: =IFERROR(N96/12/'Prop Info'!$B$6,0) -> 0 | Q96: =IFERROR(N96/N$80,0) -> 0 | R96: =IFERROR(IF(OR(VLOOKUP(A96,_StdCOA!$A$4:$E$56,4,0)=0,VLOOKUP(A96,_StdCOA!$A$4:$E$56,5,0)=0),"",IF(ABS(P96)>VLOOKUP(A96,_StdCOA!$A$4:$E$56,5,0),"🔴 high",IF(ABS(P96)<VLOOKUP(A96,_StdCOA!$A$4:$E$56,4,0),"🟢 low","🟡 in range"))),"") -> 🟢 low
A97: Utilities — Trash | B97: =SUMIFS($C$106:$C$255,$P$106:$P$255,"Utilities — Trash") -> 0 | C97: =SUMIFS($D$106:$D$255,$P$106:$P$255,"Utilities — Trash") -> 0 | D97: =SUMIFS($E$106:$E$255,$P$106:$P$255,"Utilities — Trash") -> 0 | E97: =SUMIFS($F$106:$F$255,$P$106:$P$255,"Utilities — Trash") -> 0 | F97: =SUMIFS($G$106:$G$255,$P$106:$P$255,"Utilities — Trash") -> 0 | G97: =SUMIFS($H$106:$H$255,$P$106:$P$255,"Utilities — Trash") -> 0 | H97: =SUMIFS($I$106:$I$255,$P$106:$P$255,"Utilities — Trash") -> 0 | I97: =SUMIFS($J$106:$J$255,$P$106:$P$255,"Utilities — Trash") -> 0 | J97: =SUMIFS($K$106:$K$255,$P$106:$P$255,"Utilities — Trash") -> 0 | K97: =SUMIFS($L$106:$L$255,$P$106:$P$255,"Utilities — Trash") -> 0 | L97: =SUMIFS($M$106:$M$255,$P$106:$P$255,"Utilities — Trash") -> 0 | M97: =SUMIFS($N$106:$N$255,$P$106:$P$255,"Utilities — Trash") -> 0 | N97: =SUMIFS($O$106:$O$255,$P$106:$P$255,"Utilities — Trash") -> 0 | O97: =SUM(K97:M97)*4 -> 0 | P97: =IFERROR(N97/12/'Prop Info'!$B$6,0) -> 0 | Q97: =IFERROR(N97/N$80,0) -> 0 | R97: =IFERROR(IF(OR(VLOOKUP(A97,_StdCOA!$A$4:$E$56,4,0)=0,VLOOKUP(A97,_StdCOA!$A$4:$E$56,5,0)=0),"",IF(ABS(P97)>VLOOKUP(A97,_StdCOA!$A$4:$E$56,5,0),"🔴 high",IF(ABS(P97)<VLOOKUP(A97,_StdCOA!$A$4:$E$56,4,0),"🟢 low","🟡 in range"))),"") -> 🟢 low
A98: Utilities — Internet/Cable | B98: =SUMIFS($C$106:$C$255,$P$106:$P$255,"Utilities — Internet/Cable") -> 0 | C98: =SUMIFS($D$106:$D$255,$P$106:$P$255,"Utilities — Internet/Cable") -> 0 | D98: =SUMIFS($E$106:$E$255,$P$106:$P$255,"Utilities — Internet/Cable") -> 0 | E98: =SUMIFS($F$106:$F$255,$P$106:$P$255,"Utilities — Internet/Cable") -> 0 | F98: =SUMIFS($G$106:$G$255,$P$106:$P$255,"Utilities — Internet/Cable") -> 0 | G98: =SUMIFS($H$106:$H$255,$P$106:$P$255,"Utilities — Internet/Cable") -> 0 | H98: =SUMIFS($I$106:$I$255,$P$106:$P$255,"Utilities — Internet/Cable") -> 0 | I98: =SUMIFS($J$106:$J$255,$P$106:$P$255,"Utilities — Internet/Cable") -> 0 | J98: =SUMIFS($K$106:$K$255,$P$106:$P$255,"Utilities — Internet/Cable") -> 0 | K98: =SUMIFS($L$106:$L$255,$P$106:$P$255,"Utilities — Internet/Cable") -> 0 | L98: =SUMIFS($M$106:$M$255,$P$106:$P$255,"Utilities — Internet/Cable") -> 0 | M98: =SUMIFS($N$106:$N$255,$P$106:$P$255,"Utilities — Internet/Cable") -> 0 | N98: =SUMIFS($O$106:$O$255,$P$106:$P$255,"Utilities — Internet/Cable") -> 0 | O98: =SUM(K98:M98)*4 -> 0 | P98: =IFERROR(N98/12/'Prop Info'!$B$6,0) -> 0 | Q98: =IFERROR(N98/N$80,0) -> 0 | R98: =IFERROR(IF(OR(VLOOKUP(A98,_StdCOA!$A$4:$E$56,4,0)=0,VLOOKUP(A98,_StdCOA!$A$4:$E$56,5,0)=0),"",IF(ABS(P98)>VLOOKUP(A98,_StdCOA!$A$4:$E$56,5,0),"🔴 high",IF(ABS(P98)<VLOOKUP(A98,_StdCOA!$A$4:$E$56,4,0),"🟢 low","🟡 in range"))),"") -> 🟢 low
A99: Management Fee | B99: =SUMIFS($C$106:$C$255,$P$106:$P$255,"Management Fee") -> 0 | C99: =SUMIFS($D$106:$D$255,$P$106:$P$255,"Management Fee") -> 0 | D99: =SUMIFS($E$106:$E$255,$P$106:$P$255,"Management Fee") -> 0 | E99: =SUMIFS($F$106:$F$255,$P$106:$P$255,"Management Fee") -> 0 | F99: =SUMIFS($G$106:$G$255,$P$106:$P$255,"Management Fee") -> 0 | G99: =SUMIFS($H$106:$H$255,$P$106:$P$255,"Management Fee") -> 0 | H99: =SUMIFS($I$106:$I$255,$P$106:$P$255,"Management Fee") -> 0 | I99: =SUMIFS($J$106:$J$255,$P$106:$P$255,"Management Fee") -> 0 | J99: =SUMIFS($K$106:$K$255,$P$106:$P$255,"Management Fee") -> 0 | K99: =SUMIFS($L$106:$L$255,$P$106:$P$255,"Management Fee") -> 0 | L99: =SUMIFS($M$106:$M$255,$P$106:$P$255,"Management Fee") -> 0 | M99: =SUMIFS($N$106:$N$255,$P$106:$P$255,"Management Fee") -> 0 | N99: =SUMIFS($O$106:$O$255,$P$106:$P$255,"Management Fee") -> 0 | O99: =SUM(K99:M99)*4 -> 0 | P99: =IFERROR(N99/12/'Prop Info'!$B$6,0) -> 0 | Q99: =IFERROR(N99/N$80,0) -> 0 | R99: =IFERROR(IF(OR(VLOOKUP(A99,_StdCOA!$A$4:$E$56,4,0)=0,VLOOKUP(A99,_StdCOA!$A$4:$E$56,5,0)=0),"",IF(ABS(P99)>VLOOKUP(A99,_StdCOA!$A$4:$E$56,5,0),"🔴 high",IF(ABS(P99)<VLOOKUP(A99,_StdCOA!$A$4:$E$56,4,0),"🟢 low","🟡 in range"))),"") -> 🟢 low
A100: TOTAL OPERATING EXPENSES | B100: =SUM(B82:B99) -> 0 | C100: =SUM(C82:C99) -> 0 | D100: =SUM(D82:D99) -> 0 | E100: =SUM(E82:E99) -> 0 | F100: =SUM(F82:F99) -> 0 | G100: =SUM(G82:G99) -> 0 | H100: =SUM(H82:H99) -> 0 | I100: =SUM(I82:I99) -> 0 | ... N100: =SUM(N82:N99) -> 0 | O100: =SUM(K100:M100)*4 -> 0 | P100: =IFERROR(N100/12/'Prop Info'!$B$6,0) -> 0 | Q100: =IFERROR(N100/N$80,0) -> 0
A101: NET OPERATING INCOME | B101: =B80-B100 -> 0 | C101: =C80-C100 -> 0 | D101: =D80-D100 -> 0 | E101: =E80-E100 -> 0 | F101: =F80-F100 -> 0 | G101: =G80-G100 -> 0 | H101: =H80-H100 -> 0 | I101: =I80-I100 -> 0 | ... N101: =N80-N100 -> 0 | O101: =SUM(K101:M101)*4 -> 0 | P101: =IFERROR(N101/12/'Prop Info'!$B$6,0) -> 0 | Q101: =IFERROR(N101/N$80,0) -> 0
A104: I. LAYER 1: RAW T-12 (paste operator data here, then map column P)
A105: Acct # | B105: Account Name (raw) | C105: Apr-25 | D105: May-25 | E105: Jun-25 | F105: Jul-25 | G105: Aug-25 | H105: Sep-25 | I105: Oct-25 | J105: Nov-25 | K105: Dec-25 | L105: Jan-26 | M105: Feb-26 | N105: Mar-26 | O105: T-12 Total | P105: → MAPPING | Q105: Variance | R105: Notes
O106: =SUM(C106:N106) -> 0 | P106: Gross Potential Rent | Q106: =IF(O106=0,"",IF(ABS(O106-SUM(C106:N106))<0.01,"✓","⚠"))
O107: =SUM(C107:N107) -> 0 | P107: Gain/Loss on Market Rent | Q107: =IF(O107=0,"",IF(ABS(O107-SUM(C107:N107))<0.01,"✓","⚠"))
O108: =SUM(C108:N108) -> 0 | P108: Vacancy Loss | Q108: =IF(O108=0,"",IF(ABS(O108-SUM(C108:N108))<0.01,"✓","⚠"))
O109: =SUM(C109:N109) -> 0 | P109: Down Units Loss | Q109: =IF(O109=0,"",IF(ABS(O109-SUM(C109:N109))<0.01,"✓","⚠"))
O110: =SUM(C110:N110) -> 0 | P110: Employee Units | Q110: =IF(O110=0,"",IF(ABS(O110-SUM(C110:N110))<0.01,"✓","⚠"))
...

Sheet Recapture & Upside
A1: =HYPERLINK("#Inputs!A1","← Inputs") -> ← Inputs | B1: =IF('Prop Info'!B4="","RECAPTURE & UPSIDE ANALYSIS — How much money is being left on the table?","RECAPTURE & UPSIDE ANALYSIS — How much money is being left on the table?"&" — "&'Prop Info'!B4) -> RECAPTURE & UPSIDE ANALYSIS — How much money is being left on the table?
B2: Blue = property context | Yellow = your input | Green = auto formula | Purple = projected totals
B3: Income Scenario (distressed override): | C3: 1. T-12 Actuals | E3: ← Switch to My Version / Projected when T-12 distorted (high vacancy, below-market rents)
B4: PROPERTY REFERENCE | E4: ACTIVE SCENARIO CONTEXT | I4: COMMITTED UPSIDE SUMMARY
B5: Total Units | C5: ='Prop Info'!$B$6 -> 0 | E5: Scenario: | F5: =C3 -> 1. T-12 Actuals | I5: Committed Y1 $ | L5: =L84 -> 0 | M5: ← Y1 feeds Scenarios Other Income
B6: Occupancy % | C6: =IFERROR(COUNTIF('Rent Roll Analysis'!E273:E1772,"Occupied*")/'Prop Info'!$B$6,0) -> 0 | E6: Rent/Unit (active): | F6: =IFERROR(CHOOSE(MATCH(C3,{"1. T-12 Actuals","2. My Version","3. Projected","4. Offer"},0),Scenarios!B39,Scenarios!C39,Scenarios!D39,Scenarios!E39),0) -> 0 | I6: Committed Stab $ | L6: =M84 -> 0 | M6: ← Stab feeds P&L Year 2 ramp
B7: Occupied Units | C7: =IFERROR(COUNTIF('Rent Roll Analysis'!E273:E1772,"Occupied*"),0) -> 0 | E7: Vacancy % (active): | F7: =IFERROR(CHOOSE(MATCH(C3,{"1. T-12 Actuals","2. My Version","3. Projected","4. Offer"},0),Scenarios!B41,Scenarios!C41,Scenarios!D41,Scenarios!E41),0) -> 0 | I7: Total Possible Y1 $ | L7: =J84 -> 18750 | M7: ← all upside at target adoption
B8: Vacancy % | C8: =IFERROR(1-C6,0) -> 1 | D8: ← cross-check Scenarios!B40 | E8: Units × Rent/Mo: | F8: ='Prop Info'!$B$6*C6*12 -> 0 | I8: Total Possible Stab $ | L8: =K84 -> 37500 | M8: ← all upside stabilized run-rate
B10: A. RUBS RECAPTURE — Per-utility billing coverage vs T-12 cost
B11: Coverage% = T-12 Recapture ÷ T-12 Cost. Gap = (Target coverage × Cost) − current recapture. Y1=0 (12-18 month rollout). Stab = full gap.
A12: # | B12: Utility | C12: T-12 Utility Cost | D12: T-12 Recapture $ | E12: Coverage % Now | F12: Target Coverage % | G12: N/A | H12: Annual Gap $ | I12: Pursue? | J12: Y1 Upside $ | K12: Stab Upside $ | L12: Y1 Total Recapture $ | M12: Stab Total Recapture $ | N12: Notes
A13: 1 | B13: Water / Sewer | C13: ='T-12 Analysis'!N96 -> 0 | D13: =SUMIFS('T-12 Analysis'!$O$106:$O$255,'T-12 Analysis'!$P$106:$P$255,_StdCOA!$A$42) -> 0 | E13: =IFERROR(D13/C13,0) -> 0 | F13: 0.7 | G13: — | H13: =MAX(C13*F13-D13,0) -> 0 | J13: =0 -> 0 | K13: =H13 -> 0 | L13: =D13+J13 -> 0 | M13: =D13+K13 -> 0 | N13: Operator does NOT separately track water RUBS. See Other Utility Reimb row.
A14: 2 | B14: Electric (common areas) | C14: ='T-12 Analysis'!N94 -> 0 | D14: =SUMIFS('T-12 Analysis'!$O$106:$O$255,'T-12 Analysis'!$P$106:$P$255,_StdCOA!$A$43) -> 0 | E14: =IFERROR(D14/C14,0) -> 0 | F14: 0 | G14: — | H14: =MAX(C14*F14-D14,0) -> 0 | J14: =0 -> 0 | K14: =H14 -> 0 | L14: =D14+J14 -> 0 | M14: =D14+K14 -> 0 | N14: Operator bills back common-area electric (acct 4815=$6,313). Tenant pays in-unit.
A15: 3 | B15: Gas (common) | C15: ='T-12 Analysis'!N95 -> 0 | D15: =SUMIFS('T-12 Analysis'!$O$106:$O$255,'T-12 Analysis'!$P$106:$P$255,_StdCOA!$A$47) -> 0 | E15: =IFERROR(D15/C15,0) -> 0 | F15: 0 | G15: — | H15: =MAX(C15*F15-D15,0) -> 0 | J15: =0 -> 0 | K15: =H15 -> 0 | L15: =D15+J15 -> 0 | M15: =D15+K15 -> 0 | N15: Hidden Lakes has no gas service.
A16: 4 | B16: Trash | C16: ='T-12 Analysis'!N97 -> 0 | D16: =SUMIFS('T-12 Analysis'!$O$106:$O$255,'T-12 Analysis'!$P$106:$P$255,_StdCOA!$A$44) -> 0 | E16: =IFERROR(D16/C16,0) -> 0 | F16: 0.5 | G16: — | H16: =MAX(C16*F16-D16,0) -> 0 | J16: =0 -> 0 | K16: =H16 -> 0 | L16: =D16+J16 -> 0 | M16: =D16+K16 -> 0 | N16: Not tracked separately. Standard $10-25/unit/mo flat fee.
A17: 5 | B17: Internet / Cable (bulk) | C17: ='T-12 Analysis'!N98 -> 0 | D17: =SUMIFS('T-12 Analysis'!$O$106:$O$255,'T-12 Analysis'!$P$106:$P$255,_StdCOA!$A$48) -> 0 | E17: =IFERROR(D17/C17,0) -> 0 | F17: 1 | G17: — | H17: =MAX(C17*F17-D17,0) -> 0 | J17: =0 -> 0 | K17: =H17 -> 0 | L17: =D17+J17 -> 0 | M17: =D17+K17 -> 0 | N17: Bulk-billed $1,465; full passthrough opportunity.
A18: 6 | B18: Pest Control | C18: ='T-12 Analysis'!N85 -> 0 | D18: =SUMIFS('T-12 Analysis'!$O$106:$O$255,'T-12 Analysis'!$P$106:$P$255,_StdCOA!$A$46) -> 0 | E18: =IFERROR(D18/C18,0) -> 0 | F18: 0.5 | G18: — | H18: =MAX(C18*F18-D18,0) -> 0 | J18: =0 -> 0 | K18: =H18 -> 0 | L18: =D18+J18 -> 0 | M18: =D18+K18 -> 0 | N18: Acct 4820=$678 reimbursed. Standard $3-5/unit/mo flat fee.
A19: 7 | B19: Other Utility Reimb | C19: =0 -> 0 | D19: =SUMIFS('T-12 Analysis'!$O$106:$O$255,'T-12 Analysis'!$P$106:$P$255,_StdCOA!$A$45) -> 0 | E19: N/A | F19: N/A | G19: N/A | H19: =0 -> 0 | J19: =0 -> 0 | K19: =0 -> 0 | L19: =D19 -> 0 | M19: =D19 -> 0 | N19: Acct 4825 ($39,241)+4855 ($206). Mostly water RUBS; operator does not break out by utility.
B20: TOTAL | C20: =SUM(C13:C19) -> 0 | D20: =SUM(D13:D19) -> 0 | E20: =IFERROR(D20/C20,0) -> 0 | H20: =SUM(H13:H19) -> 0 | J20: =SUM(J13:J19) -> 0 | K20: =SUM(K13:K19) -> 0 | L20: =SUM(L13:L19) -> 0 | M20: =SUM(M13:M19) -> 0
B21: Tie-out: T-12 Recapture (D20) | D21: =IF(ABS(D20-'T-12 Analysis'!N71)<1,"✓ ties to T-12!N71","⚠ off by $"&TEXT(D20-'T-12 Analysis'!N71,"#,##0")) -> ✓ ties to T-12!N71 | E21: ← D20 should equal T-12 Analysis!N71
B23: B. LOSS-TO-LEASE RECAPTURE — In-place rents vs market
B24: Uses current-market LTL only (conservative). Renovated/post-capex rent uplift is in row 4 (pulls from Capex tab). Scenario selector at C3 drives rows 1-2.
A25: # | B25: Metric | C25: Gap Value $ | D25: Annualized $ | E25: Y1 Capture % | F25: Stab Capture % | G25: — | H25: Full Opportunity $ | I25: Pursue? | J25: Y1 Upside $ | K25: Stab Upside $ | L25: Y1 Total $ | M25: Stab Total $ | N25: Notes
A26: 1 | B26: Loss to Lease (Mkt − Sched, occupied) | C26: =IF(C3="1. T-12 Actuals",'Rent Roll Analysis'!B28,CHOOSE(MATCH(C3,{"1. T-12 Actuals","2. My Version","3. Projected","4. Offer"},0),Scenarios!B39,Scenarios!C39,Scenarios!D39,Scenarios!E39)*'Prop Info'!$B$6*12-'Rent Roll Analysis'!B27) -> 0 | D26: =ABS(C26) -> 0 | E26: 0.3 | F26: 0.7 | G26: — | H26: =D26 -> 0 | J26: =D26*E26 -> 0 | K26: =D26*F26 -> 0 | L26: =J26 -> 0 | M26: =K26 -> 0 | N26: ~30% Y1 via renewals; 70%+ stabilized.
A27: 2 | B27: Vacancy Loss (vacant × market rent) | C27: =IF(C3="1. T-12 Actuals",'Rent Roll Analysis'!B30,-CHOOSE(MATCH(C3,{"1. T-12 Actuals","2. My Version","3. Projected","4. Offer"},0),Scenarios!B39,Scenarios!C39,Scenarios!D39,Scenarios!E39)*'Prop Info'!$B$6*12*CHOOSE(MATCH(C3,{"1. T-12 Actuals","2. My Version","3. Projected","4. Offer"},0),Scenarios!B41,Scenarios!C41,Scenarios!D41,Scenarios!E41)) -> 0 | D27: =ABS(C27) -> 0 | E27: 0.4 | F27: 0.85 | G27: — | H27: =D27 -> 0 | J27: =D27*E27 -> 0 | K27: =D27*F27 -> 0 | L27: =J27 -> 0 | M27: =K27 -> 0 | N27: 40% of vacant leased Y1; 85% stabilized.
A28: 3 | B28: Bad Debt Risk (legal-flagged) | C28: ='Rent Roll Analysis'!B31 -> 0 | D28: =ABS(C28) -> 0 | E28: 0.5 | F28: 0.8 | G28: — | H28: =D28 -> 0 | J28: =D28*E28 -> 0 | K28: =D28*F28 -> 0 | L28: =J28 -> 0 | M28: =K28 -> 0 | N28: Eviction resolves ~50% Y1; 80%+ stabilized.
A29: 4 | B29: Renovated Upside (post-capex) | C29: =IFERROR(Capex!$D$51,0) -> 0 | D29: =ABS(C29) -> 0 | E29: 0 | F29: 1 | G29: — | H29: =D29 -> 0 | J29: =D29*E29 -> 0 | K29: =D29*F29 -> 0 | L29: =J29 -> 0 | M29: =K29 -> 0 | N29: Pulls from Capex tab rent-bump assumptions.
B30: TOTAL | D30: =SUM(D26:D29) -> 0 | J30: =SUM(J26:J29) -> 0 | K30: =SUM(K26:K29) -> 0 | L30: =SUM(L26:L29) -> 0 | M30: =SUM(M26:M29) -> 0
B32: C. RECURRING FEES — Monthly revenue streams not fully collected
B33: Monthly per-unit fees. D=current $/unit derived from T-12. E/F=your targets (yellow). G=capture % of market rate. H=realistic annual gap at target adoption. J/K=net new above T-12.
A34: # | B34: Fee Type | C34: T-12 Annual $ | D34: Current $/Unit/Mo | E34: Target $/Unit/Mo | F34: Adoption % | G34: Capture % | H34: Annual Gap $ | I34: Pursue? | J34: Y1 Upside $ | K34: Stab Upside $ | L34: Y1 Total $ | M34: Stab Total $ | N34: Notes
A35: 1 | B35: Pet Rent (monthly) | C35: ='T-12 Analysis'!N72 -> 0 | D35: =IFERROR(C35/'Prop Info'!$B$6/12,0) -> 0 | E35: 35 | F35: 0.2 | G35: =IFERROR(D35/E35,0) -> 0 | H35: =MAX(E35*F35*'Prop Info'!$B$6*12-C35,0) -> 0 | I35: Y | J35: =MAX(E35*F35*'Prop Info'!$B$6*12*0.5-C35,0) -> 0 | K35: =MAX(E35*F35*'Prop Info'!$B$6*12-C35,0) -> 0 | L35: =C35+J35 -> 0 | M35: =C35+K35 -> 0 | N35: Monthly surcharge per pet. $25-50/mo; ~30% of units have pets.
A36: 2 | B36: Reserved Parking | C36: =0 -> 0 | D36: =IFERROR(C36/'Prop Info'!$B$6/12,0) -> 0 | E36: 25 | G36: =IFERROR(D36/E36,0) -> 0 | H36: =MAX(E36*F36*'Prop Info'!$B$6*12-C36,0) -> 0 | J36: =MAX(E36*F36*'Prop Info'!$B$6*12*0.5-C36,0) -> 0 | K36: =MAX(E36*F36*'Prop Info'!$B$6*12-C36,0) -> 0 | L36: =C36+J36 -> 0 | M36: =C36+K36 -> 0 | N36: Upgrade to reserved spot. $20-30/mo suburban garden.
A37: 3 | B37: Covered Parking | C37: =0 -> 0 | D37: =IFERROR(C37/'Prop Info'!$B$6/12,0) -> 0 | E37: 50 | G37: =IFERROR(D37/E37,0) -> 0 | H37: =MAX(E37*F37*'Prop Info'!$B$6*12-C37,0) -> 0 | J37: =MAX(E37*F37*'Prop Info'!$B$6*12*0.5-C37,0) -> 0 | K37: =MAX(E37*F37*'Prop Info'!$B$6*12-C37,0) -> 0 | L37: =C37+J37 -> 0 | M37: =C37+K37 -> 0 | N37: Carport/garage; $35-75/mo.
A38: 4 | B38: EV Parking (charger) | C38: =0 -> 0 | D38: =IFERROR(C38/'Prop Info'!$B$6/12,0) -> 0 | E38: 75 | G38: =IFERROR(D38/E38,0) -> 0 | H38: =MAX(E38*F38*'Prop Info'!$B$6*12-C38,0) -> 0 | J38: =MAX(E38*F38*'Prop Info'!$B$6*12*0.5-C38,0) -> 0 | K38: =MAX(E38*F38*'Prop Info'!$B$6*12-C38,0) -> 0 | L38: =C38+J38 -> 0 | M38: =C38+K38 -> 0 | N38: Reserved EV spot with charging access. New revenue stream.
A39: 5 | B39: Late Fee (enforcement) | C39: ='T-12 Analysis'!N70 -> 0 | D39: =IFERROR(C39/'Prop Info'!$B$6/12,0) -> 0 | E39: 75 | F39: 0.1 | G39: =IFERROR(D39/E39,0) -> 0 | H39: =MAX(E39*F39*'Prop Info'!$B$6*12-C39,0) -> 0 | J39: =MAX(E39*F39*'Prop Info'!$B$6*12*0.5-C39,0) -> 0 | K39: =MAX(E39*F39*'Prop Info'!$B$6*12-C39,0) -> 0 | L39: =C39+J39 -> 0 | M39: =C39+K39 -> 0 | N39: T-12 shows $26,725 — improve enforcement, not rate.
A40: 6 | B40: Amenity Package — base | C40: ='T-12 Analysis'!N74 -> 0 | D40: =IFERROR(C40/'Prop Info'!$B$6/12,0) -> 0 | E40: 15 | F40: 1 | G40: =IFERROR(D40/E40,0) -> 0 | H40: =MAX(E40*F40*'Prop Info'!$B$6*12-C40,0) -> 0 | J40: =MAX(E40*F40*'Prop Info'!$B$6*12*0.5-C40,0) -> 0 | K40: =MAX(E40*F40*'Prop Info'!$B$6*12-C40,0) -> 0 | L40: =C40+J40 -> 0 | M40: =C40+K40 -> 0 | N40: Universal monthly add for pool/gym/lounge access.
A41: 7 | B41: Amenity Premium (dog park/tech) | C41: =0 -> 0 | D41: =IFERROR(C41/'Prop Info'!$B$6/12,0) -> 0 | E41: 10 | G41: =IFERROR(D41/E41,0) -> 0 | H41: =MAX(E41*F41*'Prop Info'!$B$6*12-C41,0) -> 0 | J41: =MAX(E41*F41*'Prop Info'!$B$6*12*0.5-C41,0) -> 0 | K41: =MAX(E41*F41*'Prop Info'!$B$6*12-C41,0) -> 0 | L41: =C41+J41 -> 0 | M41: =C41+K41 -> 0 | N41: Add-on for premium amenities post-capex.
A42: 8 | B42: Renters Insurance Mandate | C42: ='T-12 Analysis'!N78 -> 0 | D42: =IFERROR(C42/'Prop Info'!$B$6/12,0) -> 0 | E42: 12 | G42: =IFERROR(D42/E42,0) -> 0 | H42: =MAX(E42*F42*'Prop Info'!$B$6*12-C42,0) -> 0 | J42: =MAX(E42*F42*'Prop Info'!$B$6*12*0.5-C42,0) -> 0 | K42: =MAX(E42*F42*'Prop Info'!$B$6*12-C42,0) -> 0 | L42: =C42+J42 -> 0 | M42: =C42+K42 -> 0 | N42: $14-15 wholesale; $12 charged or admin fee per policy.
A43: 9 | B43: RUBS Implementation | C43: =0 -> 0 | D43: =IFERROR(C43/'Prop Info'!$B$6/12,0) -> 0 | E43: 25 | F43: 0.9 | G43: =IFERROR(D43/E43,0) -> 0 | H43: =MAX(E43*F43*'Prop Info'!$B$6*12-C43,0) -> 0 | I43: Y | J43: =MAX(E43*F43*'Prop Info'!$B$6*12*0.5-C43,0) -> 0 | K43: =MAX(E43*F43*'Prop Info'!$B$6*12-C43,0) -> 0 | L43: =C43+J43 -> 0 | M43: =C43+K43 -> 0 | N43: → Quantified in Section A. $0 here to avoid double-count.
A44: 10 | B44: Package Service / Lockers | C44: =0 -> 0 | D44: =IFERROR(C44/'Prop Info'!$B$6/12,0) -> 0 | E44: 5 | G44: =IFERROR(D44/E44,0) -> 0 | H44: =MAX(E44*F44*'Prop Info'!$B$6*12-C44,0) -> 0 | J44: =MAX(E44*F44*'Prop Info'!$B$6*12*0.5-C44,0) -> 0 | K44: =MAX(E44*F44*'Prop Info'!$B$6*12-C44,0) -> 0 | L44: =C44+J44 -> 0 | M44: =C44+K44 -> 0 | N44: $3-8/unit/mo Amazon Hub or smartbox.
A45: 11 | B45: Storage / Common Bins | C45: =0 -> 0 | D45: =IFERROR(C45/'Prop Info'!$B$6/12,0) -> 0 | E45: 15 | G45: =IFERROR(D45/E45,0) -> 0 | H45: =MAX(E45*F45*'Prop Info'!$B$6*12-C45,0) -> 0 | J45: =MAX(E45*F45*'Prop Info'!$B$6*12*0.5-C45,0) -> 0 | K45: =MAX(E45*F45*'Prop Info'!$B$6*12-C45,0) -> 0 | L45: =C45+J45 -> 0 | M45: =C45+K45 -> 0 | N45: New revenue. Garage bays or storage rooms.
A46: 12 | B46: Lease Lock Fee | C46: =0 -> 0 | D46: =IFERROR(C46/'Prop Info'!$B$6/12,0) -> 0 | E46: 12 | G46: =IFERROR(D46/E46,0) -> 0 | H46: =MAX(E46*F46*'Prop Info'!$B$6*12-C46,0) -> 0 | J46: =MAX(E46*F46*'Prop Info'!$B$6*12*0.5-C46,0) -> 0 | K46: =MAX(E46*F46*'Prop Info'!$B$6*12-C46,0) -> 0 | L46: =C46+J46 -> 0 | M46: =C46+K46 -> 0 | N46: Tenant pays monthly fee to lock renewal rate. ~40% adoption.
A47: 13 | B47: Utilities Service Fee | C47: =0 -> 0 | D47: =IFERROR(C47/'Prop Info'!$B$6/12,0) -> 0 | E47: 8 | G47: =IFERROR(D47/E47,0) -> 0 | H47: =MAX(E47*F47*'Prop Info'!$B$6*12-C47,0) -> 0 | J47: =MAX(E47*F47*'Prop Info'!$B$6*12*0.5-C47,0) -> 0 | K47: =MAX(E47*F47*'Prop Info'!$B$6*12-C47,0) -> 0 | L47: =C47+J47 -> 0 | M47: =C47+K47 -> 0 | N47: Flat admin fee for billing/handling utility passthroughs.
A48: 14 | B48: Damage Waiver | C48: =0 -> 0 | D48: =IFERROR(C48/'Prop Info'!$B$6/12,0) -> 0 | E48: 10 | G48: =IFERROR(D48/E48,0) -> 0 | H48: =MAX(E48*F48*'Prop Info'!$B$6*12-C48,0) -> 0 | J48: =MAX(E48*F48*'Prop Info'!$B$6*12*0.5-C48,0) -> 0 | K48: =MAX(E48*F48*'Prop Info'!$B$6*12-C48,0) -> 0 | L48: =C48+J48 -> 0 | M48: =C48+K48 -> 0 | N48: Alternative to security deposit; 30% adoption typical.
A49: 15 | B49: Trash Removal (valet) | C49: =0 -> 0 | D49: =IFERROR(C49/'Prop Info'!$B$6/12,0) -> 0 | E49: 25 | G49: =IFERROR(D49/E49,0) -> 0 | H49: =MAX(E49*F49*'Prop Info'!$B$6*12-C49,0) -> 0 | J49: =MAX(E49*F49*'Prop Info'!$B$6*12*0.5-C49,0) -> 0 | K49: =MAX(E49*F49*'Prop Info'!$B$6*12-C49,0) -> 0 | L49: =C49+J49 -> 0 | M49: =C49+K49 -> 0 | N49: $25/mo doorstep trash; 70% adoption in suburban garden.
A50: 16 | B50: Cable Revenue (bulk) | C50: ='T-12 Analysis'!N98 -> 0 | D50: =IFERROR(C50/'Prop Info'!$B$6/12,0) -> 0 | E50: 30 | F50: 0.8 | G50: =IFERROR(D50/E50,0) -> 0 | H50: =MAX(E50*F50*'Prop Info'!$B$6*12-C50,0) -> 0 | J50: =MAX(E50*F50*'Prop Info'!$B$6*12*0.5-C50,0) -> 0 | K50: =MAX(E50*F50*'Prop Info'!$B$6*12-C50,0) -> 0 | L50: =C50+J50 -> 0 | M50: =C50+K50 -> 0 | N50: Bulk cable/internet upcharge; resell $30 vs $15-20 wholesale.
A51: 17 | B51: Convenience Fees (online pay) | C51: =0 -> 0 | D51: =IFERROR(C51/'Prop Info'!$B$6/12,0) -> 0 | E51: 3 | G51: =IFERROR(D51/E51,0) -> 0 | H51: =MAX(E51*F51*'Prop Info'!$B$6*12-C51,0) -> 0 | J51: =MAX(E51*F51*'Prop Info'!$B$6*12*0.5-C51,0) -> 0 | K51: =MAX(E51*F51*'Prop Info'!$B$6*12-C51,0) -> 0 | L51: =C51+J51 -> 0 | M51: =C51+K51 -> 0 | N51: Standard $2-5 per online payment — pure margin.
A52: 18 | B52: Other (laundry / vending) | C52: ='T-12 Analysis'!N77 -> 0 | D52: =IFERROR(C52/'Prop Info'!$B$6/12,0) -> 0 | E52: 2 | F52: 1 | G52: =IFERROR(D52/E52,0) -> 0 | H52: =MAX(E52*F52*'Prop Info'!$B$6*12-C52,0) -> 0 | J52: =MAX(E52*F52*'Prop Info'!$B$6*12*0.5-C52,0) -> 0 | K52: =MAX(E52*F52*'Prop Info'!$B$6*12-C52,0) -> 0 | L52: =C52+J52 -> 0 | M52: =C52+K52 -> 0 | N52: Misc revenue typically embedded in rent.
B53: TOTAL RECURRING FEES | C53: =SUM(C35:C52) -> 0 | J53: =SUM(J35:J52) -> 0 | K53: =SUM(K35:K52) -> 0 | L53: =SUM(L35:L52) -> 0 | M53: =SUM(M35:M52) -> 0
B55: D. ONE-TIME FEES — Per-event fees at lease events
B56: Annual revenue = Fee $ × # Events × 100% (events already count actual occurrences). D = implied effective rate from T-12. G = effective rate vs market fee. Y1 uses Y1 Ramp % (K56). | J56: Y1 Ramp %: | K56: 0.5 | L56: ← % of full-year capture in Y1 (default 50%)
A57: # | B57: Fee Type | C57: T-12 Annual $ | D57: Effective $/Event | E57: Market Fee $ | F57: # Events / Yr | G57: Capture % | H57: Annual Gap $ | I57: Pursue? | J57: Y1 Upside $ | K57: Stab Upside $ | L57: Y1 Total $ | M57: Stab Total $ | N57: Notes
A58: 1 | B58: Application Fee | C58: ='T-12 Analysis'!N69 -> 0 | D58: =IFERROR(C58/F58,0) -> 0 | E58: 75 | F58: 72 | G58: =IFERROR(D58/E58,0) -> 0 | H58: =MAX(E58*F58-C58,0) -> 5400 | J58: =MAX(E58*F58*$K$56-C58,0) -> 2700 | K58: =MAX(E58*F58-C58,0) -> 5400 | L58: =C58+J58 -> 2700 | M58: =C58+K58 -> 5400 | N58: T-12 shows $1,675 — undercollected. Enter expected applications/yr.
A59: 2 | B59: Pet Fee (one-time deposit) | C59: =0 -> 0 | D59: =IFERROR(C59/F59,0) -> 0 | E59: 250 | F59: 21 | G59: =IFERROR(D59/E59,0) -> 0 | H59: =MAX(E59*F59-C59,0) -> 5250 | J59: =MAX(E59*F59*$K$56-C59,0) -> 2625 | K59: =MAX(E59*F59-C59,0) -> 5250 | L59: =C59+J59 -> 2625 | M59: =C59+K59 -> 5250 | N59: One-time pet enrollment at move-in. ~21 events if 30% of move-ins have pets.
A60: 3 | B60: MTM Fee (month-to-month) | C60: ='T-12 Analysis'!N68 -> 0 | D60: =IFERROR(C60/F60,0) -> 0 | E60: 150 | F60: 7 | G60: =IFERROR(D60/E60,0) -> 0 | H60: =MAX(E60*F60-C60,0) -> 1050 | J60: =MAX(E60*F60*$K$56-C60,0) -> 525 | K60: =MAX(E60*F60-C60,0) -> 1050 | L60: =C60+J60 -> 525 | M60: =C60+K60 -> 1050 | N60: Per-month MTM premium × # tenants going MTM/yr (~5-10% of base).
A61: 4 | B61: Lease Break Fee | C61: =0 -> 0 | D61: =IFERROR(C61/F61,0) -> 0 | E61: 1500 | F61: 4 | G61: =IFERROR(D61/E61,0) -> 0 | H61: =MAX(E61*F61-C61,0) -> 6000 | J61: =MAX(E61*F61*$K$56-C61,0) -> 3000 | K61: =MAX(E61*F61-C61,0) -> 6000 | L61: =C61+J61 -> 3000 | M61: =C61+K61 -> 6000 | N61: Lease break events/yr (~5% of leases break early).
A62: 5 | B62: Utility Setup Fee | C62: =0 -> 0 | D62: =IFERROR(C62/F62,0) -> 0 | E62: 75 | F62: 72 | G62: =IFERROR(D62/E62,0) -> 0 | H62: =MAX(E62*F62-C62,0) -> 5400 | J62: =MAX(E62*F62*$K$56-C62,0) -> 2700 | K62: =MAX(E62*F62-C62,0) -> 5400 | L62: =C62+J62 -> 2700 | M62: =C62+K62 -> 5400 | N62: One-time at move-in for utility transfer. = # move-ins/yr.
A63: 6 | B63: Admin / Lease Renewal Fee | C63: ='T-12 Analysis'!N75 -> 0 | D63: =IFERROR(C63/F63,0) -> 0 | E63: 200 | F63: 72 | G63: =IFERROR(D63/E63,0) -> 0 | H63: =MAX(E63*F63-C63,0) -> 14400 | J63: =MAX(E63*F63*$K$56-C63,0) -> 7200 | K63: =MAX(E63*F63-C63,0) -> 14400 | L63: =C63+J63 -> 7200 | M63: =C63+K63 -> 14400 | N63: Per renewal event/yr. T-12 shows $3,974 already collected.
B64: Enter expected # events directly in column F (e.g., 60 turnovers/yr = 60 events).
B65: TOTAL ONE-TIME FEES | C65: =SUM(C58:C63) -> 0 | J65: =SUM(J58:J63) -> 18750 | K65: =SUM(K58:K63) -> 37500 | L65: =SUM(L58:L63) -> 18750 | M65: =SUM(M58:M63) -> 37500
B67: E. BILLABLE UPSIDE — Net-new services beyond standard fee schedule
B68: Items that cost nothing additional but generate margin if charged. T-12=0 for all — 100% of J/K is net-new. Excludes items already in C/D to avoid double-count.
A69: # | B69: Item | C69: T-12 Annual $ | D69: Current $/Unit/Mo | E69: Target $/Unit/Mo | F69: Adoption % | G69: Capture % | H69: Full Opportunity $ | I69: Pursue? | J69: Y1 Upside $ | K69: Stab Upside $ | L69: Y1 Total $ | M69: Stab Total $ | N69: Notes
A70: 1 | B70: Smart Home Tech (locks/thermo) | C70: =0 -> 0 | D70: =0 -> 0 | E70: 25 | F70: 0.5 | G70: =0 -> 0 | H70: =E70*F70*'Prop Info'!$B$6*12 -> 0 | J70: =E70*F70*'Prop Info'!$B$6*12*0.5 -> 0 | K70: =E70*F70*'Prop Info'!$B$6*12 -> 0 | L70: =J70 -> 0 | M70: =K70 -> 0 | N70: Tech upgrade rolled at lease renewal. $25-35/unit/mo.
A71: 2 | B71: Furnished Unit Premium | C71: =0 -> 0 | D71: =0 -> 0 | E71: 200 | F71: 0.05 | G71: =0 -> 0 | H71: =E71*F71*'Prop Info'!$B$6*12 -> 0 | J71: =E71*F71*'Prop Info'!$B$6*12*0.5 -> 0 | K71: =E71*F71*'Prop Info'!$B$6*12 -> 0 | L71: =J71 -> 0 | M71: =K71 -> 0 | N71: 5-10% of units; furniture amortized over 24 months.
A72: 3 | B72: Short-Term / Corp Housing Premium | C72: =0 -> 0 | D72: =0 -> 0 | E72: 400 | F72: 0.03 | G72: =0 -> 0 | H72: =E72*F72*'Prop Info'!$B$6*12 -> 0 | J72: =E72*F72*'Prop Info'!$B$6*12*0.5 -> 0 | K72: =E72*F72*'Prop Info'!$B$6*12 -> 0 | L72: =J72 -> 0 | M72: =K72 -> 0 | N72: 3% of units at premium nightly rate.
A73: 4 | B73: Co-Working Lounge Access | C73: =0 -> 0 | D73: =0 -> 0 | E73: 15 | F73: 0.3 | G73: =0 -> 0 | H73: =E73*F73*'Prop Info'!$B$6*12 -> 0 | J73: =E73*F73*'Prop Info'!$B$6*12*0.5 -> 0 | K73: =E73*F73*'Prop Info'!$B$6*12 -> 0 | L73: =J73 -> 0 | M73: =K73 -> 0 | N73: Convert unused space; $15/mo per resident user.
B75: TOTAL BILLABLE UPSIDE | C75: =0 -> 0 | J75: =SUM(J70:J73) -> 0 | K75: =SUM(K70:K73) -> 0 | L75: =SUM(L70:L73) -> 0 | M75: =SUM(M70:M73) -> 0
B77: F. GRAND TOTAL — All recapture and upside categories
B78: Category | C78: T-12 Baseline $ | J78: Total Possible Y1 $ | K78: Total Possible Stab $ | L78: Committed Y1 $ | M78: Committed Stab $ | N78: Notes
B79: A. RUBS Recapture | C79: =D20 -> 0 | J79: =J20 -> 0 | K79: =K20 -> 0 | L79: =SUMIF(I13:I19,"Y",J13:J19) -> 0 | M79: =SUMIF(I13:I19,"Y",K13:K19) -> 0 | N79: Sub-meter rollout 12-18 months. Y1=0.
B80: B. Loss-to-Lease | C80: =0 -> 0 | J80: =J30 -> 0 | K80: =K30 -> 0 | L80: =SUMIF(I26:I29,"Y",J26:J29) -> 0 | M80: =SUMIF(I26:I29,"Y",K26:K29) -> 0 | N80: Captured at lease renewals + new leases.
B81: C. Recurring Fees | C81: =C53 -> 0 | J81: =J53 -> 0 | K81: =K53 -> 0 | L81: =SUMIF(I35:I52,"Y",J35:J52) -> 0 | M81: =SUMIF(I35:I52,"Y",K35:K52) -> 0 | N81: Pet/parking/admin fees from rollout.
B82: D. One-Time Fees | C82: =C65 -> 0 | J82: =J65 -> 18750 | K82: =K65 -> 37500 | L82: =SUMIF(I58:I63,"Y",J58:J63) -> 0 | M82: =SUMIF(I58:I63,"Y",K58:K63) -> 0 | N82: Per-event fees at move-in/renewal.
B83: E. Billable Upside | C83: =0 -> 0 | J83: =J75 -> 0 | K83: =K75 -> 0 | L83: =SUMIF(I70:I73,"Y",J70:J73) -> 0 | M83: =SUMIF(I70:I73,"Y",K70:K73) -> 0 | N83: New service offerings.
B84: GRAND TOTAL | C84: =SUM(C79:C83) -> 0 | J84: =SUM(J79:J83) -> 18750 | K84: =SUM(K79:K83) -> 37500 | L84: =SUM(L79:L83) -> 0 | M84: =SUM(M79:M83) -> 0
L85: ← Y1 feeds Scenarios!C/D/E48 | M85: ← Stab feeds P&L Y2 ramp
B87: VALUE-CREATION MULTIPLIER
B88: Stabilized NOI add (Committed Stab): | C88: =M84 -> 0
B89: Exit cap rate (Scenarios market): | C89: =Scenarios!C79 -> 0
B90: Implied value creation: | C90: =IFERROR(C88/C89,0) -> 0 | E90: ← Committed Stab NOI add ÷ cap rate = property value uplift from pursued items

Sheet Rent Roll Analysis
A1: =IF('Prop Info'!B4="","RENT ROLL ANALYSIS — Diagnostic Layer","RENT ROLL ANALYSIS — Diagnostic Layer"&" — "&'Prop Info'!B4) -> RENT ROLL ANALYSIS — Diagnostic Layer
A2: ANALYSIS on top. Raw rent roll below — 143 units pre-loaded from source 4/16/2026. AR aging columns Q-T blank (paste from separate AR aging report).
A4: B. HEALTH CHECK — RR vs Prop Info reconciliation
A5: Date: | C5: Property: | D5: ='Prop Info'!B4 -> 0 | F5: Units (Prop): | G5: ='Prop Info'!B6 -> 0 | H5: Units (RR): | I5: =COUNTA(B273:B1772) -> 0 | J5: Match: | K5: =IF(I5=G5,"✓ match",IF(I5=0,"⚠ no data","⚠ mismatch")) -> ✓ match | M5: Total AR: | N5: =SUM(O273:O1772) -> 0 | P5: Legal cases: | Q5: =COUNTIF(G273:G1772,TRUE()) -> 0 | S5: Occupied: | T5: =COUNTIF(E273:E1772,"Occupied*") -> 0
A7: C. UNIT STATUS TAXONOMY — Where everyone stands
A8: Status Bucket | B8: # Units | C8: % of Total | D8: Sched Charges ($/mo) | E8: Market Rent ($/mo) | F8: Avg Sched / Unit | G8: AR Balance
A9: Occupied — Current (no legal) | B9: =COUNTIFS(E273:E1772,"Occupied*",G273:G1772,FALSE(),O273:O1772,"<500") -> 0 | C9: =IFERROR(B9/'Prop Info'!$B$6,0) -> 0 | D9: =SUMIFS(N273:N1772,E273:E1772,"Occupied*",G273:G1772,FALSE(),O273:O1772,"<500") -> 0 | E9: =SUMIFS(L273:L1772,E273:E1772,"Occupied*",G273:G1772,FALSE(),O273:O1772,"<500") -> 0 | F9: =IFERROR(D9/B9,0) -> 0 | G9: =SUMIFS(O273:O1772,E273:E1772,"Occupied*",G273:G1772,FALSE(),O273:O1772,"<500") -> 0
A10: Occupied — Delinquent (>$500, no legal) | B10: =COUNTIFS(E273:E1772,"Occupied*",G273:G1772,FALSE(),O273:O1772,">=500") -> 0 | C10: =IFERROR(B10/'Prop Info'!$B$6,0) -> 0 | D10: =SUMIFS(N273:N1772,E273:E1772,"Occupied*",G273:G1772,FALSE(),O273:O1772,">=500") -> 0 | E10: =SUMIFS(L273:L1772,E273:E1772,"Occupied*",G273:G1772,FALSE(),O273:O1772,">=500") -> 0 | F10: =IFERROR(D10/B10,0) -> 0 | G10: =SUMIFS(O273:O1772,E273:E1772,"Occupied*",G273:G1772,FALSE(),O273:O1772,">=500") -> 0
A11: Occupied — Legal/Eviction (** flag) | B11: =COUNTIFS(E273:E1772,"Occupied*",G273:G1772,TRUE()) -> 0 | C11: =IFERROR(B11/'Prop Info'!$B$6,0) -> 0 | D11: =SUMIFS(N273:N1772,E273:E1772,"Occupied*",G273:G1772,TRUE()) -> 0 | E11: =SUMIFS(L273:L1772,E273:E1772,"Occupied*",G273:G1772,TRUE()) -> 0 | F11: =IFERROR(D11/B11,0) -> 0 | G11: =SUMIFS(O273:O1772,E273:E1772,"Occupied*",G273:G1772,TRUE()) -> 0
A13: Vacant Unrented Ready | B13: =COUNTIF(E273:E1772,"Vacant Unrented Ready") -> 0 | C13: =IFERROR(B13/'Prop Info'!$B$6,0) -> 0 | D13: =SUMIF(E273:E1772,"Vacant Unrented Ready",N273:N1772) -> 0 | E13: =SUMIF(E273:E1772,"Vacant Unrented Ready",L273:L1772) -> 0 | F13: 0 | G13: =SUMIF(E273:E1772,"Vacant Unrented Ready",O273:O1772) -> 0
A14: Vacant Unrented Not Ready | B14: =COUNTIF(E273:E1772,"Vacant Unrented Not Ready") -> 0 | C14: =IFERROR(B14/'Prop Info'!$B$6,0) -> 0 | D14: =SUMIF(E273:E1772,"Vacant Unrented Not Ready",N273:N1772) -> 0 | E14: =SUMIF(E273:E1772,"Vacant Unrented Not Ready",L273:L1772) -> 0 | F14: 0 | G14: =SUMIF(E273:E1772,"Vacant Unrented Not Ready",O273:O1772) -> 0
A15: Down / Off-line | B15: =COUNTIF(E273:E1772,"Down*") -> 0 | C15: =IFERROR(B15/'Prop Info'!$B$6,0) -> 0 | D15: =SUMIF(E273:E1772,"Down*",N273:N1772) -> 0 | E15: =SUMIF(E273:E1772,"Down*",L273:L1772) -> 0 | F15: 0 | G15: =SUMIF(E273:E1772,"Down*",O273:O1772) -> 0
A16: Vacant — Leased / Pre-Leased | B16: =COUNTIF(E273:E1772,"Vacant*Leased*")+COUNTIF(E273:E1772,"Vacant Rented*") -> 0 | C16: =IFERROR(B16/'Prop Info'!$B$6,0) -> 0 | D16: =SUMIF(E273:E1772,"Vacant*Leased*",N273:N1772)+SUMIF(E273:E1772,"Vacant Rented*",N273:N1772) -> 0 | E16: =SUMIF(E273:E1772,"Vacant*Leased*",L273:L1772)+SUMIF(E273:E1772,"Vacant Rented*",L273:L1772) -> 0 | F16: 0 | G16: =SUMIF(E273:E1772,"Vacant*Leased*",O273:O1772)+SUMIF(E273:E1772,"Vacant Rented*",O273:O1772) -> 0
A17: Model / Employee / Other | B17: =COUNTIF(E273:E1772,"Model")+COUNTIF(E273:E1772,"Employee")+COUNTIF(E273:E1772,"Office") -> 0 | C17: =IFERROR(B17/'Prop Info'!$B$6,0) -> 0 | D17: =SUMIF(E273:E1772,"Model",N273:N1772)+SUMIF(E273:E1772,"Employee",N273:N1772)+SUMIF(E273:E1772,"Office",N273:N1772) -> 0 | E17: =SUMIF(E273:E1772,"Model",L273:L1772)+SUMIF(E273:E1772,"Employee",L273:L1772)+SUMIF(E273:E1772,"Office",L273:L1772) -> 0 | F17: 0 | G17: =SUMIF(E273:E1772,"Model",O273:O1772)+SUMIF(E273:E1772,"Employee",O273:O1772)+SUMIF(E273:E1772,"Office",O273:O1772) -> 0
A18: Unmatched / Other status | B18: =MAX(0,COUNTA(E273:E1772)-SUM(B9:B17)) -> 0 | C18: =IFERROR(B18/'Prop Info'!$B$6,0) -> 0 | D18: =MAX(0,SUM(N273:N1772)-SUM(D9:D17)) -> 0 | E18: =MAX(0,SUM(L273:L1772)-SUM(E9:E17)) -> 0 | G18: =MAX(0,SUM(O273:O1772)-SUM(G9:G17)) -> 0
A19: memo: Occupied units On Notice | B19: {=SUMPRODUCT((ISNUMBER(SEARCH("Occupied",E273:E1772)))*(((ISNUMBER(SEARCH("NTV",E273:E1772)))+(ISNUMBER(SEARCH("Notice",E273:E1772)))*(1-ISNUMBER(SEARCH("No Notice",E273:E1772)))+(K273:K1772<>""))>0))} -> 0 | C19: =IFERROR(B19/'Prop Info'!$B$6,0) -> 0
A20: check: TOTAL = Prop Info unit count | B20: =IF(B21='Prop Info'!$B$6,"✓ ties","⚠ off by "&TEXT(B21-'Prop Info'!$B$6,"#,##0")) -> ✓ ties
A21: TOTAL | B21: =SUM(B9:B18) -> 0 | C21: =IFERROR(B21/'Prop Info'!$B$6,0) -> 0 | D21: =SUM(D9:D18) -> 0 | E21: =SUM(E9:E18) -> 0 | F21: =IFERROR(SUM(D9:D11)/SUM(B9:B11),0) -> 0 | G21: =SUM(G9:G18) -> 0 | H21: ← avg sched/occupied unit
A22: Tie-out: Occ Mkt + Vac Loss = Section D GPR | B22: =IF(ABS(E21*12+ABS(B30)-B26)<1,"✓ Occ Mkt + Vac Loss ties to Section D GPR","⚠ Off by $"&TEXT(B26-E21*12-ABS(B30),"#,##0")) -> ✓ Occ Mkt + Vac Loss ties to Section D GPR
A24: D. GPR RECONCILIATION — Three views of "potential rent"
A25: Metric | B25: Annual Amount | C25: PUPM | D25: Notes
A26: Market GPR (all units × market rent × 12) | B26: =SUMPRODUCT((L273:L1772)*1)*12 -> 0 | C26: =IFERROR(B26/'Prop Info'!$B$6/12,0) -> 0 | D26: Max revenue if all units leased at market rent
A27: Scheduled GPR (occupied × scheduled charges × 12) | B27: =SUMPRODUCT((N273:N1772)*1)*12 -> 0 | C27: =IFERROR(B27/COUNTIF(E273:E1772,"Occupied*")/12,0) -> 0 | D27: What occupied residents are contracted to pay
A28: Loss to Lease (Mkt − Sched on occupied) | B28: =SUMIFS(L273:L1772,E273:E1772,"Occupied*")*12 - B27 -> 0 | D28: Negative = below-market in-place rent (recapture upside)
A29: Loss to Lease % | B29: =IFERROR(B28/(SUMIFS(L273:L1772,E273:E1772,"Occupied*")*12),0) -> 0
A30: Vacancy Loss (vacant × market × 12) | B30: =-SUMIFS(L273:L1772,E273:E1772,"Vacant*")*12 -> 0 | D30: Lost revenue from physical vacancy
A31: Bad Debt Risk (legal-flagged units × scheduled × 12) | B31: =SUMIFS(N273:N1772,G273:G1772,TRUE())*12 -> 0 | D31: Annualized exposure on legally-flagged units
A32: Economic GPR (Mkt − LTL − Vac − Bad Debt) | B32: =B26-IF(B28>0,B28,0)+B30-B31 -> 0 | C32: =IFERROR(B32/'Prop Info'!$B$6/12,0) -> 0 | D32: Realistic collected rent estimate
A33: Economic Occupancy % (Econ GPR / Mkt GPR) | B33: =IFERROR(B32/B26,0) -> 0 | D33: Compare to physical occupancy from Section C
A34: Current RR GPR — Occupied Scheduled (as-is) | B34: =SUMIFS(N273:N1772,E273:E1772,"Occupied*")*12 -> 0 | C34: =IFERROR(B34/COUNTIF(E273:E1772,"Occupied*")/12,0) -> 0 | D34: Scheduled rent on occupied units × 12 (point-in-time snapshot)
A35: T-3 GPR Annualized (last 3 months × 4) | B35: ='T-12 Analysis'!O58 -> 0 | C35: =IFERROR(B35/'Prop Info'!$B$6/12,0) -> 0 | D35: Trailing 3-month GPR × 4 — momentum vs T-12 average. Source: T-12 Analysis!O58
A36: E. LEASE EXPIRATION SCHEDULE — Next 24 months
A37: Months count from TODAY(). Blank or past lease-end on occupied = MTM/Open bucket.
A38: Month | B38: # Expirations | C38: % of Occupied | D38: Sched Rent | E38: Market Rent | F38: LTL at Renewal | G38: Cumulative %
A39: =TEXT(EDATE(TODAY(),0),"mmm yyyy") -> Jun 2026 | B39: =SUMPRODUCT((J273:J1772>=DATE(YEAR(EDATE(TODAY(),0)),MONTH(EDATE(TODAY(),0)),1))*(J273:J1772<DATE(YEAR(EDATE(TODAY(),1)),MONTH(EDATE(TODAY(),1)),1))*1) -> 0 | C39: =IFERROR(B39/COUNTIF(E273:E1772,"Occupied*"),0) -> 0 | D39: =SUMPRODUCT((J273:J1772>=DATE(YEAR(EDATE(TODAY(),0)),MONTH(EDATE(TODAY(),0)),1))*(J273:J1772<DATE(YEAR(EDATE(TODAY(),1)),MONTH(EDATE(TODAY(),1)),1))*(N273:N1772)) -> 0 | E39: =SUMPRODUCT((J273:J1772>=DATE(YEAR(EDATE(TODAY(),0)),MONTH(EDATE(TODAY(),0)),1))*(J273:J1772<DATE(YEAR(EDATE(TODAY(),1)),MONTH(EDATE(TODAY(),1)),1))*(L273:L1772)) -> 0 | F39: =E39-D39 -> 0 | G39: =C39 -> 0
A40: =TEXT(EDATE(TODAY(),1),"mmm yyyy") -> Jul 2026 | B40: =SUMPRODUCT((J273:J1772>=DATE(YEAR(EDATE(TODAY(),1)),MONTH(EDATE(TODAY(),1)),1))*(J273:J1772<DATE(YEAR(EDATE(TODAY(),2)),MONTH(EDATE(TODAY(),2)),1))*1) -> 0 | C40: =IFERROR(B40/COUNTIF(E273:E1772,"Occupied*"),0) -> 0 | D40: =SUMPRODUCT((J273:J1772>=DATE(YEAR(EDATE(TODAY(),1)),MONTH(EDATE(TODAY(),1)),1))*(J273:J1772<DATE(YEAR(EDATE(TODAY(),2)),MONTH(EDATE(TODAY(),2)),1))*(N273:N1772)) -> 0 | E40: =SUMPRODUCT((J273:J1772>=DATE(YEAR(EDATE(TODAY(),1)),MONTH(EDATE(TODAY(),1)),1))*(J273:J1772<DATE(YEAR(EDATE(TODAY(),2)),MONTH(EDATE(TODAY(),2)),1))*(L273:L1772)) -> 0 | F40: =E40-D40 -> 0 | G40: =G39+C40 -> 0
A41: =TEXT(EDATE(TODAY(),2),"mmm yyyy") -> Aug 2026 | B41: =SUMPRODUCT((J273:J1772>=DATE(YEAR(EDATE(TODAY(),2)),MONTH(EDATE(TODAY(),2)),1))*(J273:J1772<DATE(YEAR(EDATE(TODAY(),3)),MONTH(EDATE(TODAY(),3)),1))*1) -> 0 | C41: =IFERROR(B41/COUNTIF(E273:E1772,"Occupied*"),0) -> 0 | D41: =SUMPRODUCT((J273:J1772>=DATE(YEAR(EDATE(TODAY(),2)),MONTH(EDATE(TODAY(),2)),1))*(J273:J1772<DATE(YEAR(EDATE(TODAY(),3)),MONTH(EDATE(TODAY(),3)),1))*(N273:N1772)) -> 0 | E41: =SUMPRODUCT((J273:J1772>=DATE(YEAR(EDATE(TODAY(),2)),MONTH(EDATE(TODAY(),2)),1))*(J273:J1772<DATE(YEAR(EDATE(TODAY(),3)),MONTH(EDATE(TODAY(),3)),1))*(L273:L1772)) -> 0 | F41: =E41-D41 -> 0 | G41: =G40+C41 -> 0
A42: =TEXT(EDATE(TODAY(),3),"mmm yyyy") -> Sep 2026 | B42: =SUMPRODUCT((J273:J1772>=DATE(YEAR(EDATE(TODAY(),3)),MONTH(EDATE(TODAY(),3)),1))*(J273:J1772<DATE(YEAR(EDATE(TODAY(),4)),MONTH(EDATE(TODAY(),4)),1))*1) -> 0 | C42: =IFERROR(B42/COUNTIF(E273:E1772,"Occupied*"),0) -> 0 | D42: =SUMPRODUCT((J273:J1772>=DATE(YEAR(EDATE(TODAY(),3)),MONTH(EDATE(TODAY(),3)),1))*(J273:J1772<DATE(YEAR(EDATE(TODAY(),4)),MONTH(EDATE(TODAY(),4)),1))*(N273:N1772)) -> 0 | E42: =SUMPRODUCT((J273:J1772>=DATE(YEAR(EDATE(TODAY(),3)),MONTH(EDATE(TODAY(),3)),1))*(J273:J1772<DATE(YEAR(EDATE(TODAY(),4)),MONTH(EDATE(TODAY(),4)),1))*(L273:L1772)) -> 0 | F42: =E42-D42 -> 0 | G42: =G41+C42 -> 0
A43: =TEXT(EDATE(TODAY(),4),"mmm yyyy") -> Oct 2026 | B43: =SUMPRODUCT((J273:J1772>=DATE(YEAR(EDATE(TODAY(),4)),MONTH(EDATE(TODAY(),4)),1))*(J273:J1772<DATE(YEAR(EDATE(TODAY(),5)),MONTH(EDATE(TODAY(),5)),1))*1) -> 0 | C43: =IFERROR(B43/COUNTIF(E273:E1772,"Occupied*"),0) -> 0 | D43: =SUMPRODUCT((J273:J1772>=DATE(YEAR(EDATE(TODAY(),4)),MONTH(EDATE(TODAY(),4)),1))*(J273:J1772<DATE(YEAR(EDATE(TODAY(),5)),MONTH(EDATE(TODAY(),5)),1))*(N273:N1772)) -> 0 | E43: =SUMPRODUCT((J273:J1772>=DATE(YEAR(EDATE(TODAY(),4)),MONTH(EDATE(TODAY(),4)),1))*(J273:J1772<DATE(YEAR(EDATE(TODAY(),5)),MONTH(EDATE(TODAY(),5)),1))*(L273:L1772)) -> 0 | F43: =E43-D43 -> 0 | G43: =G42+C43 -> 0
A44: =TEXT(EDATE(TODAY(),5),"mmm yyyy") -> Nov 2026 | B44: =SUMPRODUCT((J273:J1772>=DATE(YEAR(EDATE(TODAY(),5)),MONTH(EDATE(TODAY(),5)),1))*(J273:J1772<DATE(YEAR(EDATE(TODAY(),6)),MONTH(EDATE(TODAY(),6)),1))*1) -> 0 | C44: =IFERROR(B44/COUNTIF(E273:E1772,"Occupied*"),0) -> 0 | D44: =SUMPRODUCT((J273:J1772>=DATE(YEAR(EDATE(TODAY(),5)),MONTH(EDATE(TODAY(),5)),1))*(J273:J1772<DATE(YEAR(EDATE(TODAY(),6)),MONTH(EDATE(TODAY(),6)),1))*(N273:N1772)) -> 0 | E44: =SUMPRODUCT((J273:J1772>=DATE(YEAR(EDATE(TODAY(),5)),MONTH(EDATE(TODAY(),5)),1))*(J273:J1772<DATE(YEAR(EDATE(TODAY(),6)),MONTH(EDATE(TODAY(),6)),1))*(L273:L1772)) -> 0 | F44: =E44-D44 -> 0 | G44: =G43+C44 -> 0
A45: =TEXT(EDATE(TODAY(),6),"mmm yyyy") -> Dec 2026 | B45: =SUMPRODUCT((J273:J1772>=DATE(YEAR(EDATE(TODAY(),6)),MONTH(EDATE(TODAY(),6)),1))*(J273:J1772<DATE(YEAR(EDATE(TODAY(),7)),MONTH(EDATE(TODAY(),7)),1))*1) -> 0 | C45: =IFERROR(B45/COUNTIF(E273:E1772,"Occupied*"),0) -> 0 | D45: =SUMPRODUCT((J273:J1772>=DATE(YEAR(EDATE(TODAY(),6)),MONTH(EDATE(TODAY(),6)),1))*(J273:J1772<DATE(YEAR(EDATE(TODAY(),7)),MONTH(EDATE(TODAY(),7)),1))*(N273:N1772)) -> 0 | E45: =SUMPRODUCT((J273:J1772>=DATE(YEAR(EDATE(TODAY(),6)),MONTH(EDATE(TODAY(),6)),1))*(J273:J1772<DATE(YEAR(EDATE(TODAY(),7)),MONTH(EDATE(TODAY(),7)),1))*(L273:L1772)) -> 0 | F45: =E45-D45 -> 0 | G45: =G44+C45 -> 0
A46: =TEXT(EDATE(TODAY(),7),"mmm yyyy") -> Jan 2027 | B46: =SUMPRODUCT((J273:J1772>=DATE(YEAR(EDATE(TODAY(),7)),MONTH(EDATE(TODAY(),7)),1))*(J273:J1772<DATE(YEAR(EDATE(TODAY(),8)),MONTH(EDATE(TODAY(),8)),1))*1) -> 0 | C46: =IFERROR(B46/COUNTIF(E273:E1772,"Occupied*"),0) -> 0 | D46: =SUMPRODUCT((J273:J1772>=DATE(YEAR(EDATE(TODAY(),7)),MONTH(EDATE(TODAY(),7)),1))*(J273:J1772<DATE(YEAR(EDATE(TODAY(),8)),MONTH(EDATE(TODAY(),8)),1))*(N273:N1772)) -> 0 | E46: =SUMPRODUCT((J273:J1772>=DATE(YEAR(EDATE(TODAY(),7)),MONTH(EDATE(TODAY(),7)),1))*(J273:J1772<DATE(YEAR(EDATE(TODAY(),8)),MONTH(EDATE(TODAY(),8)),1))*(L273:L1772)) -> 0 | F46: =E46-D46 -> 0 | G46: =G45+C46 -> 0
A47: =TEXT(EDATE(TODAY(),8),"mmm yyyy") -> Feb 2027 | B47: =SUMPRODUCT((J273:J1772>=DATE(YEAR(EDATE(TODAY(),8)),MONTH(EDATE(TODAY(),8)),1))*(J273:J1772<DATE(YEAR(EDATE(TODAY(),9)),MONTH(EDATE(TODAY(),9)),1))*1) -> 0 | C47: =IFERROR(B47/COUNTIF(E273:E1772,"Occupied*"),0) -> 0 | D47: =SUMPRODUCT((J273:J1772>=DATE(YEAR(EDATE(TODAY(),8)),MONTH(EDATE(TODAY(),8)),1))*(J273:J1772<DATE(YEAR(EDATE(TODAY(),9)),MONTH(EDATE(TODAY(),9)),1))*(N273:N1772)) -> 0 | E47: =SUMPRODUCT((J273:J1772>=DATE(YEAR(EDATE(TODAY(),8)),MONTH(EDATE(TODAY(),8)),1))*(J273:J1772<DATE(YEAR(EDATE(TODAY(),9)),MONTH(EDATE(TODAY(),9)),1))*(L273:L1772)) -> 0 | F47: =E47-D47 -> 0 | G47: =G46+C47 -> 0
A48: =TEXT(EDATE(TODAY(),9),"mmm yyyy") -> Mar 2027 | B48: =SUMPRODUCT((J273:J1772>=DATE(YEAR(EDATE(TODAY(),9)),MONTH(EDATE(TODAY(),9)),1))*(J273:J1772<DATE(YEAR(EDATE(TODAY(),10)),MONTH(EDATE(TODAY(),10)),1))*1) -> 0 | C48: =IFERROR(B48/COUNTIF(E273:E1772,"Occupied*"),0) -> 0 | D48: =SUMPRODUCT((J273:J1772>=DATE(YEAR(EDATE(TODAY(),9)),MONTH(EDATE(TODAY(),9)),1))*(J273:J1772<DATE(YEAR(EDATE(TODAY(),10)),MONTH(EDATE(TODAY(),10)),1))*(N273:N1772)) -> 0 | E48: =SUMPRODUCT((J273:J1772>=DATE(YEAR(EDATE(TODAY(),9)),MONTH(EDATE(TODAY(),9)),1))*(J273:J1772<DATE(YEAR(EDATE(TODAY(),10)),MONTH(EDATE(TODAY(),10)),1))*(L273:L1772)) -> 0 | F48: =E48-D48 -> 0 | G48: =G47+C48 -> 0
A49: =TEXT(EDATE(TODAY(),10),"mmm yyyy") -> Apr 2027 | B49: =SUMPRODUCT((J273:J1772>=DATE(YEAR(EDATE(TODAY(),10)),MONTH(EDATE(TODAY(),10)),1))*(J273:J1772<DATE(YEAR(EDATE(TODAY(),11)),MONTH(EDATE(TODAY(),11)),1))*1) -> 0 | C49: =IFERROR(B49/COUNTIF(E273:E1772,"Occupied*"),0) -> 0 | D49: =SUMPRODUCT((J273:J1772>=DATE(YEAR(EDATE(TODAY(),10)),MONTH(EDATE(TODAY(),10)),1))*(J273:J1772<DATE(YEAR(EDATE(TODAY(),11)),MONTH(EDATE(TODAY(),11)),1))*(N273:N1772)) -> 0 | E49: =SUMPRODUCT((J273:J1772>=DATE(YEAR(EDATE(TODAY(),10)),MONTH(EDATE(TODAY(),10)),1))*(J273:J1772<DATE(YEAR(EDATE(TODAY(),11)),MONTH(EDATE(TODAY(),11)),1))*(L273:L1772)) -> 0 | F49: =E49-D49 -> 0 | G49: =G48+C49 -> 0
A50: =TEXT(EDATE(TODAY(),11),"mmm yyyy") -> May 2027 | B50: =SUMPRODUCT((J273:J1772>=DATE(YEAR(EDATE(TODAY(),11)),MONTH(EDATE(TODAY(),11)),1))*(J273:J1772<DATE(YEAR(EDATE(TODAY(),12)),MONTH(EDATE(TODAY(),12)),1))*1) -> 0 | C50: =IFERROR(B50/COUNTIF(E273:E1772,"Occupied*"),0) -> 0 | D50: =SUMPRODUCT((J273:J1772>=DATE(YEAR(EDATE(TODAY(),11)),MONTH(EDATE(TODAY(),11)),1))*(J273:J1772<DATE(YEAR(EDATE(TODAY(),12)),MONTH(EDATE(TODAY(),12)),1))*(N273:N1772)) -> 0 | E50: =SUMPRODUCT((J273:J1772>=DATE(YEAR(EDATE(TODAY(),11)),MONTH(EDATE(TODAY(),11)),1))*(J273:J1772<DATE(YEAR(EDATE(TODAY(),12)),MONTH(EDATE(TODAY(),12)),1))*(L273:L1772)) -> 0 | F50: =E50-D50 -> 0 | G50: =G49+C50 -> 0
A51: =TEXT(EDATE(TODAY(),12),"mmm yyyy") -> Jun 2027 | B51: =SUMPRODUCT((J273:J1772>=DATE(YEAR(EDATE(TODAY(),12)),MONTH(EDATE(TODAY(),12)),1))*(J273:J1772<DATE(YEAR(EDATE(TODAY(),13)),MONTH(EDATE(TODAY(),13)),1))*1) -> 0 | C51: =IFERROR(B51/COUNTIF(E273:E1772,"Occupied*"),0) -> 0 | D51: =SUMPRODUCT((J273:J1772>=DATE(YEAR(EDATE(TODAY(),12)),MONTH(EDATE(TODAY(),12)),1))*(J273:J1772<DATE(YEAR(EDATE(TODAY(),13)),MONTH(EDATE(TODAY(),13)),1))*(N273:N1772)) -> 0 | E51: =SUMPRODUCT((J273:J1772>=DATE(YEAR(EDATE(TODAY(),12)),MONTH(EDATE(TODAY(),12)),1))*(J273:J1772<DATE(YEAR(EDATE(TODAY(),13)),MONTH(EDATE(TODAY(),13)),1))*(L273:L1772)) -> 0 | F51: =E51-D51 -> 0 | G51: =G50+C51 -> 0
A52: =TEXT(EDATE(TODAY(),13),"mmm yyyy") -> Jul 2027 | B52: =SUMPRODUCT((J273:J1772>=DATE(YEAR(EDATE(TODAY(),13)),MONTH(EDATE(TODAY(),13)),1))*(J273:J1772<DATE(YEAR(EDATE(TODAY(),14)),MONTH(EDATE(TODAY(),14)),1))*1) -> 0 | C52: =IFERROR(B52/COUNTIF(E273:E1772,"Occupied*"),0) -> 0 | D52: =SUMPRODUCT((J273:J1772>=DATE(YEAR(EDATE(TODAY(),13)),MONTH(EDATE(TODAY(),13)),1))*(J273:J1772<DATE(YEAR(EDATE(TODAY(),14)),MONTH(EDATE(TODAY(),14)),1))*(N273:N1772)) -> 0 | E52: =SUMPRODUCT((J273:J1772>=DATE(YEAR(EDATE(TODAY(),13)),MONTH(EDATE(TODAY(),13)),1))*(J273:J1772<DATE(YEAR(EDATE(TODAY(),14)),MONTH(EDATE(TODAY(),14)),1))*(L273:L1772)) -> 0 | F52: =E52-D52 -> 0 | G52: =G51+C52 -> 0
A53: =TEXT(EDATE(TODAY(),14),"mmm yyyy") -> Aug 2027 | B53: =SUMPRODUCT((J273:J1772>=DATE(YEAR(EDATE(TODAY(),14)),MONTH(EDATE(TODAY(),14)),1))*(J273:J1772<DATE(YEAR(EDATE(TODAY(),15)),MONTH(EDATE(TODAY(),15)),1))*1) -> 0 | C53: =IFERROR(B53/COUNTIF(E273:E1772,"Occupied*"),0) -> 0 | D53: =SUMPRODUCT((J273:J1772>=DATE(YEAR(EDATE(TODAY(),14)),MONTH(EDATE(TODAY(),14)),1))*(J273:J1772<DATE(YEAR(EDATE(TODAY(),15)),MONTH(EDATE(TODAY(),15)),1))*(N273:N1772)) -> 0 | E53: =SUMPRODUCT((J273:J1772>=DATE(YEAR(EDATE(TODAY(),14)),MONTH(EDATE(TODAY(),14)),1))*(J273:J1772<DATE(YEAR(EDATE(TODAY(),15)),MONTH(EDATE(TODAY(),15)),1))*(L273:L1772)) -> 0 | F53: =E53-D53 -> 0 | G53: =G52+C53 -> 0
A54: =TEXT(EDATE(TODAY(),15),"mmm yyyy") -> Sep 2027 | B54: =SUMPRODUCT((J273:J1772>=DATE(YEAR(EDATE(TODAY(),15)),MONTH(EDATE(TODAY(),15)),1))*(J273:J1772<DATE(YEAR(EDATE(TODAY(),16)),MONTH(EDATE(TODAY(),16)),1))*1) -> 0 | C54: =IFERROR(B54/COUNTIF(E273:E1772,"Occupied*"),0) -> 0 | D54: =SUMPRODUCT((J273:J1772>=DATE(YEAR(EDATE(TODAY(),15)),MONTH(EDATE(TODAY(),15)),1))*(J273:J1772<DATE(YEAR(EDATE(TODAY(),16)),MONTH(EDATE(TODAY(),16)),1))*(N273:N1772)) -> 0 | E54: =SUMPRODUCT((J273:J1772>=DATE(YEAR(EDATE(TODAY(),15)),MONTH(EDATE(TODAY(),15)),1))*(J273:J1772<DATE(YEAR(EDATE(TODAY(),16)),MONTH(EDATE(TODAY(),16)),1))*(L273:L1772)) -> 0 | F54: =E54-D54 -> 0 | G54: =G53+C54 -> 0
A55: =TEXT(EDATE(TODAY(),16),"mmm yyyy") -> Oct 2027 | B55: =SUMPRODUCT((J273:J1772>=DATE(YEAR(EDATE(TODAY(),16)),MONTH(EDATE(TODAY(),16)),1))*(J273:J1772<DATE(YEAR(EDATE(TODAY(),17)),MONTH(EDATE(TODAY(),17)),1))*1) -> 0 | C55: =IFERROR(B55/COUNTIF(E273:E1772,"Occupied*"),0) -> 0 | D55: =SUMPRODUCT((J273:J1772>=DATE(YEAR(EDATE(TODAY(),16)),MONTH(EDATE(TODAY(),16)),1))*(J273:J1772<DATE(YEAR(EDATE(TODAY(),17)),MONTH(EDATE(TODAY(),17)),1))*(N273:N1772)) -> 0 | E55: =SUMPRODUCT((J273:J1772>=DATE(YEAR(EDATE(TODAY(),16)),MONTH(EDATE(TODAY(),16)),1))*(J273:J1772<DATE(YEAR(EDATE(TODAY(),17)),MONTH(EDATE(TODAY(),17)),1))*(L273:L1772)) -> 0 | F55: =E55-D55 -> 0 | G55: =G54+C55 -> 0
A56: =TEXT(EDATE(TODAY(),17),"mmm yyyy") -> Nov 2027 | B56: =SUMPRODUCT((J273:J1772>=DATE(YEAR(EDATE(TODAY(),17)),MONTH(EDATE(TODAY(),17)),1))*(J273:J1772<DATE(YEAR(EDATE(TODAY(),18)),MONTH(EDATE(TODAY(),18)),1))*1) -> 0 | C56: =IFERROR(B56/COUNTIF(E273:E1772,"Occupied*"),0) -> 0 | D56: =SUMPRODUCT((J273:J1772>=DATE(YEAR(EDATE(TODAY(),17)),MONTH(EDATE(TODAY(),17)),1))*(J273:J1772<DATE(YEAR(EDATE(TODAY(),18)),MONTH(EDATE(TODAY(),18)),1))*(N273:N1772)) -> 0 | E56: =SUMPRODUCT((J273:J1772>=DATE(YEAR(EDATE(TODAY(),17)),MONTH(EDATE(TODAY(),17)),1))*(J273:J1772<DATE(YEAR(EDATE(TODAY(),18)),MONTH(EDATE(TODAY(),18)),1))*(L273:L1772)) -> 0 | F56: =E56-D56 -> 0 | G56: =G55+C56 -> 0
A57: =TEXT(EDATE(TODAY(),18),"mmm yyyy") -> Dec 2027 | B57: =SUMPRODUCT((J273:J1772>=DATE(YEAR(EDATE(TODAY(),18)),MONTH(EDATE(TODAY(),18)),1))*(J273:J1772<DATE(YEAR(EDATE(TODAY(),19)),MONTH(EDATE(TODAY(),19)),1))*1) -> 0 | C57: =IFERROR(B57/COUNTIF(E273:E1772,"Occupied*"),0) -> 0 | D57: =SUMPRODUCT((J273:J1772>=DATE(YEAR(EDATE(TODAY(),18)),MONTH(EDATE(TODAY(),18)),1))*(J273:J1772<DATE(YEAR(EDATE(TODAY(),19)),MONTH(EDATE(TODAY(),19)),1))*(N273:N1772)) -> 0 | E57: =SUMPRODUCT((J273:J1772>=DATE(YEAR(EDATE(TODAY(),18)),MONTH(EDATE(TODAY(),18)),1))*(J273:J1772<DATE(YEAR(EDATE(TODAY(),19)),MONTH(EDATE(TODAY(),19)),1))*(L273:L1772)) -> 0 | F57: =E57-D57 -> 0 | G57: =G56+C57 -> 0
A58: =TEXT(EDATE(TODAY(),19),"mmm yyyy") -> Jan 2028 | B58: =SUMPRODUCT((J273:J1772>=DATE(YEAR(EDATE(TODAY(),19)),MONTH(EDATE(TODAY(),19)),1))*(J273:J1772<DATE(YEAR(EDATE(TODAY(),20)),MONTH(EDATE(TODAY(),20)),1))*1) -> 0 | C58: =IFERROR(B58/COUNTIF(E273:E1772,"Occupied*"),0) -> 0 | D58: =SUMPRODUCT((J273:J1772>=DATE(YEAR(EDATE(TODAY(),19)),MONTH(EDATE(TODAY(),19)),1))*(J273:J1772<DATE(YEAR(EDATE(TODAY(),20)),MONTH(EDATE(TODAY(),20)),1))*(N273:N1772)) -> 0 | E58: =SUMPRODUCT((J273:J1772>=DATE(YEAR(EDATE(TODAY(),19)),MONTH(EDATE(TODAY(),19)),1))*(J273:J1772<DATE(YEAR(EDATE(TODAY(),20)),MONTH(EDATE(TODAY(),20)),1))*(L273:L1772)) -> 0 | F58: =E58-D58 -> 0 | G58: =G57+C58 -> 0
A59: =TEXT(EDATE(TODAY(),20),"mmm yyyy") -> Feb 2028 | B59: =SUMPRODUCT((J273:J1772>=DATE(YEAR(EDATE(TODAY(),20)),MONTH(EDATE(TODAY(),20)),1))*(J273:J1772<DATE(YEAR(EDATE(TODAY(),21)),MONTH(EDATE(TODAY(),21)),1))*1) -> 0 | C59: =IFERROR(B59/COUNTIF(E273:E1772,"Occupied*"),0) -> 0 | D59: =SUMPRODUCT((J273:J1772>=DATE(YEAR(EDATE(TODAY(),20)),MONTH(EDATE(TODAY(),20)),1))*(J273:J1772<DATE(YEAR(EDATE(TODAY(),21)),MONTH(EDATE(TODAY(),21)),1))*(N273:N1772)) -> 0 | E59: =SUMPRODUCT((J273:J1772>=DATE(YEAR(EDATE(TODAY(),20)),MONTH(EDATE(TODAY(),20)),1))*(J273:J1772<DATE(YEAR(EDATE(TODAY(),21)),MONTH(EDATE(TODAY(),21)),1))*(L273:L1772)) -> 0 | F59: =E59-D59 -> 0 | G59: =G58+C59 -> 0
A60: =TEXT(EDATE(TODAY(),21),"mmm yyyy") -> Mar 2028 | B60: =SUMPRODUCT((J273:J1772>=DATE(YEAR(EDATE(TODAY(),21)),MONTH(EDATE(TODAY(),21)),1))*(J273:J1772<DATE(YEAR(EDATE(TODAY(),22)),MONTH(EDATE(TODAY(),22)),1))*1) -> 0 | C60: =IFERROR(B60/COUNTIF(E273:E1772,"Occupied*"),0) -> 0 | D60: =SUMPRODUCT((J273:J1772>=DATE(YEAR(EDATE(TODAY(),21)),MONTH(EDATE(TODAY(),21)),1))*(J273:J1772<DATE(YEAR(EDATE(TODAY(),22)),MONTH(EDATE(TODAY(),22)),1))*(N273:N1772)) -> 0 | E60: =SUMPRODUCT((J273:J1772>=DATE(YEAR(EDATE(TODAY(),21)),MONTH(EDATE(TODAY(),21)),1))*(J273:J1772<DATE(YEAR(EDATE(TODAY(),22)),MONTH(EDATE(TODAY(),22)),1))*(L273:L1772)) -> 0 | F60: =E60-D60 -> 0 | G60: =G59+C60 -> 0
A61: =TEXT(EDATE(TODAY(),22),"mmm yyyy") -> Apr 2028 | B61: =SUMPRODUCT((J273:J1772>=DATE(YEAR(EDATE(TODAY(),22)),MONTH(EDATE(TODAY(),22)),1))*(J273:J1772<DATE(YEAR(EDATE(TODAY(),23)),MONTH(EDATE(TODAY(),23)),1))*1) -> 0 | C61: =IFERROR(B61/COUNTIF(E273:E1772,"Occupied*"),0) -> 0 | D61: =SUMPRODUCT((J273:J1772>=DATE(YEAR(EDATE(TODAY(),22)),MONTH(EDATE(TODAY(),22)),1))*(J273:J1772<DATE(YEAR(EDATE(TODAY(),23)),MONTH(EDATE(TODAY(),23)),1))*(N273:N1772)) -> 0 | E61: =SUMPRODUCT((J273:J1772>=DATE(YEAR(EDATE(TODAY(),22)),MONTH(EDATE(TODAY(),22)),1))*(J273:J1772<DATE(YEAR(EDATE(TODAY(),23)),MONTH(EDATE(TODAY(),23)),1))*(L273:L1772)) -> 0 | F61: =E61-D61 -> 0 | G61: =G60+C61 -> 0
