Workbook

Sheet Dashboard
O1: Care Type | P1: Property | Q1: Market
B2: ="UNDERWRITING DASHBOARD"&IF(AND(ISTEXT(Cover!B5),Cover!B5<>"")," — "&Cover!B5,"") | O2: Independent Living | P2: =IFERROR(IF('T12 Analytics'!B6>0,'T12 Analytics'!B11/'T12 Analytics'!B6,NA()),NA()) | Q2: 0.91
B3: ="Period: "&IF(AND(ISTEXT('T12 Analytics'!E2),'T12 Analytics'!E2<>""),'T12 Analytics'!E2,"T12")&" | Basis: "&IF(AND(ISTEXT('T12 Analytics'!H2),'T12 Analytics'!H2<>""),'T12 Analytics'!H2,"As-Reported")&" | Refreshed: "&TEXT(TODAY(),"mmm d, yyyy") | O3: Assisted Living | P3: =IFERROR(IF('T12 Analytics'!C6>0,'T12 Analytics'!C11/'T12 Analytics'!C6,NA()),NA()) | Q3: 0.879
O4: Memory Care | P4: =IFERROR(IF('T12 Analytics'!D6>0,'T12 Analytics'!D11/'T12 Analytics'!D6,NA()),NA()) | Q4: 0.88
B5: OCCUPANCY | E5: EBITDARM MARGIN | H5: GOING-IN CAP RATE | K5: REVPOR | O5: Blended | P5: =IFERROR('T12 Analytics'!F134,NA()) | Q5: 0.895
B6: =IFERROR(IF(ISNUMBER('T12 Analytics'!F134),TEXT('T12 Analytics'!F134,"0.0%"),"—"),"—") | E6: =IFERROR(IF(ISNUMBER('T12 Analytics'!F162),TEXT('T12 Analytics'!F162,"0.0%"),"—"),"—") | H6: =IFERROR(IF(ISNUMBER('T12 Analytics'!F118),TEXT('T12 Analytics'!F118,"0.00%"),"—"),"—") | K6: =IFERROR(IF(ISNUMBER('T12 Analytics'!F143),TEXT('T12 Analytics'!F143,"$#,##0"),"—"),"—")
B7: Normalized community occupancy | E7: Normalized (pre-mgmt fee) | H7: Normalized NOI / Purchase Price | K7: Normalized RevPOR per resident | O7: Payer | P7: Revenue
B8: =IF(ISNUMBER('T12 Analytics'!F134),IF('T12 Analytics'!F134>=0.9,"✓ At/above 90% stabilized hurdle",IF('T12 Analytics'!F134>=0.85,"⚠ Below stabilized, lease-up risk","✗ Distressed occupancy")),"— Source not populated") | E8: =IF(ISNUMBER('T12 Analytics'!F162),IF('T12 Analytics'!F162>=0.27,"✓ In-line with REIT SHOP avg ~27%",IF('T12 Analytics'!F162>=0.22,"⚠ Below institutional median","✗ Margin distressed")),"— Source not populated") | H8: =IF(ISNUMBER('T12 Analytics'!F118),IF('T12 Analytics'!F118>=0.07,"✓ Above 6.2% market avg",IF('T12 Analytics'!F118>=0.055,"⚠ At market, modest yield","✗ Below market, aggressive")),"— Source not populated") | K8: =IF(ISNUMBER('T12 Analytics'!F143),"vs blended market $5,500-$6,500","— Source not populated") | O8: Private Pay | P8: =IFERROR(IF(ISNUMBER(E43),E43,0),0)
O9: Medicaid | P9: =IFERROR(IF(ISNUMBER(E44),E44,0),0)
B10: EFFECTIVE GROSS INCOME | E10: EBITDAR | H10: PRICE / BED | O10: LTC Insurance | P10: =IFERROR(IF(ISNUMBER(E45),E45,0),0)
B11: =IFERROR(IF(ISNUMBER('T12 Analytics'!F52),TEXT('T12 Analytics'!F52,"$#,##0"),"—"),"—") | E11: =IFERROR(IF(ISNUMBER('T12 Analytics'!F163),TEXT('T12 Analytics'!F163,"$#,##0"),"—"),"—") | H11: =IFERROR(IF(AND(ISNUMBER('T12 Analytics'!F117),ISNUMBER('T12 Analytics'!E6),'T12 Analytics'!E6>0),TEXT('T12 Analytics'!F117/'T12 Analytics'!E6,"$#,##0"),"—"),"—") | O11: VA | P11: =IFERROR(IF(ISNUMBER(E46),E46,0),0)
B12: Annual revenue (T12) | E12: After mgmt fee (lender NOI) | H12: Purchase price / licensed bed | O12: Managed Care | P12: =IFERROR(IF(ISNUMBER(E47),E47,0),0)
B13: =IF(ISNUMBER('T12 Analytics'!F52),"✓ EGI captured","— Source not populated") | E13: =IFERROR(IF(ISNUMBER('T12 Analytics'!F164),"Margin: "&TEXT('T12 Analytics'!F164,"0.0%"),"— Margin n/a"),"—") | H13: =IFERROR(IF(AND(ISNUMBER('T12 Analytics'!F117),ISNUMBER('T12 Analytics'!E6),'T12 Analytics'!E6>0),"on "&TEXT('T12 Analytics'!E6,"#,##0")&" licensed beds","— Source not populated"),"—") | O13: Self-Pay | P13: =IFERROR(IF(ISNUMBER(E48),E48,0),0)
O14: Other | P14: =IFERROR(IF(ISNUMBER(E49),E49,0),0)
B15: OPERATING PERFORMANCE
B17: CAPACITY & OCCUPANCY | E17: REVENUE & RATE | H17: PROFITABILITY | K17: COST STRUCTURE & LABOR
B18: Licensed beds (total) | C18: =IFERROR(IF(ISNUMBER('T12 Analytics'!E6),'T12 Analytics'!E6,"—"),"—") | E18: Gross potential rent | F18: =IFERROR(IF(ISNUMBER('T12 Analytics'!F37),'T12 Analytics'!F37,"—"),"—") | H18: EBITDARM $ | I18: =IFERROR(IF(ISNUMBER('T12 Analytics'!F161),'T12 Analytics'!F161,"—"),"—") | K18: Total labor % EGI | L18: =IFERROR(IF(ISNUMBER('T12 Analytics'!F148),'T12 Analytics'!F148,"—"),"—")
B19: IL / AL / MC | C19: =IFERROR(IF(ISNUMBER('T12 Analytics'!B6),TEXT('T12 Analytics'!B6,"0")&" / "&TEXT('T12 Analytics'!C6,"0")&" / "&TEXT('T12 Analytics'!D6,"0"),"—"),"—") | E19: Effective gross income | F19: =IFERROR(IF(ISNUMBER('T12 Analytics'!F52),'T12 Analytics'!F52,"—"),"—") | H19: EBITDARM margin | I19: =IFERROR(IF(ISNUMBER('T12 Analytics'!F162),'T12 Analytics'!F162,"—"),"—") | K19: Direct labor % EGI | L19: =IFERROR(IF(ISNUMBER('T12 Analytics'!F149),'T12 Analytics'!F149,"—"),"—")
B20: Avg occupied beds | C20: =IFERROR(IF(ISNUMBER('T12 Analytics'!E11),'T12 Analytics'!E11,"—"),"—") | E20: Blended ADR / day | F20: =IFERROR(IF(ISNUMBER('T12 Analytics'!F140),'T12 Analytics'!F140,"—"),"—") | H20: EBITDAR $ (post mgmt fee) | I20: =IFERROR(IF(ISNUMBER('T12 Analytics'!F163),'T12 Analytics'!F163,"—"),"—") | K20: Overtime % | L20: =IFERROR(IF(ISNUMBER('T12 Analytics'!F150),'T12 Analytics'!F150,"—"),"—")
B21: Community occupancy % | C21: =IFERROR(IF(ISNUMBER('T12 Analytics'!F134),'T12 Analytics'!F134,"—"),"—") | E21: RevPOR (blended) | F21: =IFERROR(IF(ISNUMBER('T12 Analytics'!F143),'T12 Analytics'!F143,"—"),"—") | H21: EBITDAR margin | I21: =IFERROR(IF(ISNUMBER('T12 Analytics'!F164),'T12 Analytics'!F164,"—"),"—") | K21: Agency labor % | L21: =IFERROR(IF(ISNUMBER('T12 Analytics'!F152),'T12 Analytics'!F152,"—"),"—")
B22: Economic occupancy % | C22: =IFERROR(IF(ISNUMBER('Rent Roll Recon'!E13),'Rent Roll Recon'!E13,"—"),"—") | E22: RevPAB | F22: =IFERROR(IF(ISNUMBER('T12 Analytics'!F145),'T12 Analytics'!F145,"—"),"—") | H22: EGI / occupied bed | I22: =IFERROR(IF(ISNUMBER('T12 Analytics'!F144),'T12 Analytics'!F144,"—"),"—") | K22: Food PPD | L22: =IFERROR(IF(ISNUMBER('T12 Analytics'!F154),'T12 Analytics'!F154,"—"),"—")
B23: Loss to lease % | C23: =IFERROR(IF(AND(ISNUMBER('T12 Analytics'!F41),ISNUMBER('T12 Analytics'!F37),'T12 Analytics'!F37<>0),ABS('T12 Analytics'!F41)/'T12 Analytics'!F37,"—"),"—") | E23: Level of care % | F23: =IFERROR(IF(ISNUMBER('T12 Analytics'!F146),'T12 Analytics'!F146,"—"),"—") | H23: Opex / occupied bed | I23: =IFERROR(IF(ISNUMBER('T12 Analytics'!F160),'T12 Analytics'!F160,"—"),"—") | K23: Mgmt fee % | L23: =IFERROR(IF(ISNUMBER('T12 Analytics'!F157),'T12 Analytics'!F157,"—"),"—")
B24: Vacancy % | C24: =IFERROR(IF(AND(ISNUMBER('T12 Analytics'!F38),ISNUMBER('T12 Analytics'!F37),'T12 Analytics'!F37<>0),ABS('T12 Analytics'!F38)/'T12 Analytics'!F37,"—"),"—") | E24: Bad debt % | F24: =IFERROR(IF(ISNUMBER('T12 Analytics'!F158),'T12 Analytics'!F158,"—"),"—") | H24: Total opex $ | I24: =IFERROR(IF(ISNUMBER('T12 Analytics'!F105),'T12 Analytics'!F105,"—"),"—") | K24: Insurance (P&C) % | L24: =IFERROR(IF(ISNUMBER('T12 Analytics'!F159),'T12 Analytics'!F159,"—"),"—")
B26: VALUATION & MARKET BENCHMARKING
B28: DEAL ECONOMICS | H28: OCCUPANCY vs MARKET (NIC MAP Q1 2026)
B29: Metric | D29: Property | E29: Market | F29: Read
B30: Purchase price | D30: =IFERROR(IF(ISNUMBER('T12 Analytics'!F117),'T12 Analytics'!F117,"—"),"—") | E30: n/a | F30: —
B31: Price / total bed | D31: =IFERROR(IF(AND(ISNUMBER('T12 Analytics'!F117),ISNUMBER('T12 Analytics'!E6),'T12 Analytics'!E6>0),'T12 Analytics'!F117/'T12 Analytics'!E6,"—"),"—") | E31: $220-280k | F31: =IF(ISNUMBER(D31),IF(D31<=280000,"✓",IF(D31<=350000,"⚠","✗")),"—")
B32: Going-in cap rate | D32: =IFERROR(IF(ISNUMBER('T12 Analytics'!F118),'T12 Analytics'!F118,"—"),"—") | E32: 0.062 | F32: =IF(ISNUMBER(D32),IF(D32>=0.07,"✓",IF(D32>=0.055,"⚠","✗")),"—")
B33: EBITDAR cap rate | D33: =IFERROR(IF(ISNUMBER('T12 Analytics'!F120),'T12 Analytics'!F120,"—"),"—") | E33: 5.7-6.5% | F33: =IF(ISNUMBER(D33),IF(D33>=0.065,"✓",IF(D33>=0.055,"⚠","✗")),"—")
B34: EBITDARM margin | D34: =IFERROR(IF(ISNUMBER('T12 Analytics'!F162),'T12 Analytics'!F162,"—"),"—") | E34: 0.27 | F34: =IF(ISNUMBER(D34),IF(D34>=0.27,"✓",IF(D34>=0.22,"⚠","✗")),"—")
B35: Community occupancy | D35: =IFERROR(IF(ISNUMBER('T12 Analytics'!F134),'T12 Analytics'!F134,"—"),"—") | E35: 0.895 | F35: =IF(ISNUMBER(D35),IF(D35>=0.9,"✓",IF(D35>=0.85,"⚠","✗")),"—")
B36: Labor % EGI | D36: =IFERROR(IF(ISNUMBER('T12 Analytics'!F148),'T12 Analytics'!F148,"—"),"—") | E36: 43-45% | F36: =IF(ISNUMBER(D36),IF(D36<=0.45,"✓",IF(D36<=0.5,"⚠","✗")),"—")
B37: Agency labor % | D37: =IFERROR(IF(ISNUMBER('T12 Analytics'!F152),'T12 Analytics'!F152,"—"),"—") | E37: <3% | F37: =IF(ISNUMBER(D37),IF(D37<=0.03,"✓",IF(D37<=0.06,"⚠","✗")),"—")
B39: PAYER MIX
B41: Payer Mix — Revenue & Census | H41: Payer Mix — Revenue Share
B42: Payer Type | C42: Resident Count | D42: % of Census | E42: Revenue (T12) | F42: % of Revenue
B43: Private Pay | C43: =IFERROR(IF(ISNUMBER('Rent Roll Recon'!B40),'Rent Roll Recon'!B40,"—"),"—") | D43: =IFERROR(IF(ISNUMBER('Rent Roll Recon'!C40),'Rent Roll Recon'!C40,"—"),"—") | E43: =IFERROR(IF(ISNUMBER('Rent Roll Recon'!H40),'Rent Roll Recon'!H40,"—"),"—") | F43: =IFERROR(IF(ISNUMBER('Rent Roll Recon'!I40),'Rent Roll Recon'!I40,"—"),"—")
B44: Medicaid | C44: =IFERROR(IF(ISNUMBER('Rent Roll Recon'!B41),'Rent Roll Recon'!B41,"—"),"—") | D44: =IFERROR(IF(ISNUMBER('Rent Roll Recon'!C41),'Rent Roll Recon'!C41,"—"),"—") | E44: =IFERROR(IF(ISNUMBER('Rent Roll Recon'!H41),'Rent Roll Recon'!H41,"—"),"—") | F44: =IFERROR(IF(ISNUMBER('Rent Roll Recon'!I41),'Rent Roll Recon'!I41,"—"),"—")
B45: LTC Insurance | C45: =IFERROR(IF(ISNUMBER('Rent Roll Recon'!B42),'Rent Roll Recon'!B42,"—"),"—") | D45: =IFERROR(IF(ISNUMBER('Rent Roll Recon'!C42),'Rent Roll Recon'!C42,"—"),"—") | E45: =IFERROR(IF(ISNUMBER('Rent Roll Recon'!H42),'Rent Roll Recon'!H42,"—"),"—") | F45: =IFERROR(IF(ISNUMBER('Rent Roll Recon'!I42),'Rent Roll Recon'!I42,"—"),"—")
B46: VA | C46: =IFERROR(IF(ISNUMBER('Rent Roll Recon'!B43),'Rent Roll Recon'!B43,"—"),"—") | D46: =IFERROR(IF(ISNUMBER('Rent Roll Recon'!C43),'Rent Roll Recon'!C43,"—"),"—") | E46: =IFERROR(IF(ISNUMBER('Rent Roll Recon'!H43),'Rent Roll Recon'!H43,"—"),"—") | F46: =IFERROR(IF(ISNUMBER('Rent Roll Recon'!I43),'Rent Roll Recon'!I43,"—"),"—")
B47: Managed Care | C47: =IFERROR(IF(ISNUMBER('Rent Roll Recon'!B44),'Rent Roll Recon'!B44,"—"),"—") | D47: =IFERROR(IF(ISNUMBER('Rent Roll Recon'!C44),'Rent Roll Recon'!C44,"—"),"—") | E47: =IFERROR(IF(ISNUMBER('Rent Roll Recon'!H44),'Rent Roll Recon'!H44,"—"),"—") | F47: =IFERROR(IF(ISNUMBER('Rent Roll Recon'!I44),'Rent Roll Recon'!I44,"—"),"—")
B48: Self-Pay | C48: =IFERROR(IF(ISNUMBER('Rent Roll Recon'!B45),'Rent Roll Recon'!B45,"—"),"—") | D48: =IFERROR(IF(ISNUMBER('Rent Roll Recon'!C45),'Rent Roll Recon'!C45,"—"),"—") | E48: =IFERROR(IF(ISNUMBER('Rent Roll Recon'!H45),'Rent Roll Recon'!H45,"—"),"—") | F48: =IFERROR(IF(ISNUMBER('Rent Roll Recon'!I45),'Rent Roll Recon'!I45,"—"),"—")
B49: Other | C49: =IFERROR(IF(ISNUMBER('Rent Roll Recon'!B46),'Rent Roll Recon'!B46,"—"),"—") | D49: =IFERROR(IF(ISNUMBER('Rent Roll Recon'!C46),'Rent Roll Recon'!C46,"—"),"—") | E49: =IFERROR(IF(ISNUMBER('Rent Roll Recon'!H46),'Rent Roll Recon'!H46,"—"),"—") | F49: =IFERROR(IF(ISNUMBER('Rent Roll Recon'!I46),'Rent Roll Recon'!I46,"—"),"—")
B50: Total | C50: =SUM(C43:C49) | D50: 1 | E50: =SUM(E43:E49) | F50: 1
B52: RISK FLAGS & UNDERWRITING CHECKS
B54: Risk Indicator | E54: Property | F54: Threshold | G54: Flag | H54: Read
B55: Occupancy gap to market | E55: =IFERROR(IF(ISNUMBER('T12 Analytics'!F134),'T12 Analytics'!F134-0.895,"—"),"—") | F55: ≥ 0 ppt | G55: =IFERROR(IF(NOT(ISNUMBER('T12 Analytics'!F134)),"⚪",IF('T12 Analytics'!F134>=0.895,"✅",IF('T12 Analytics'!F134>=0.85,"⚠️","❌"))),"⚪") | H55: =IFERROR(IF(NOT(ISNUMBER('T12 Analytics'!F134)),"No data",IF('T12 Analytics'!F134>=0.895,"At or above NIC MAP",IF('T12 Analytics'!F134>=0.85,"Below market — lease-up risk","Significantly below market"))),"")
B56: Agency labor reliance | E56: =IFERROR(IF(ISNUMBER('T12 Analytics'!F152),'T12 Analytics'!F152,"—"),"—") | F56: < 3% of labor | G56: =IFERROR(IF(NOT(ISNUMBER('T12 Analytics'!F152)),"⚪",IF('T12 Analytics'!F152<0.03,"✅",IF('T12 Analytics'!F152<0.06,"⚠️","❌"))),"⚪") | H56: =IFERROR(IF(NOT(ISNUMBER('T12 Analytics'!F152)),"No data",IF('T12 Analytics'!F152<0.03,"Healthy in-house staffing",IF('T12 Analytics'!F152<0.06,"Moderate agency reliance","Heavy agency — staffing crisis"))),"")
B57: Overtime burden | E57: =IFERROR(IF(ISNUMBER('T12 Analytics'!F150),'T12 Analytics'!F150,"—"),"—") | F57: < 5% of labor | G57: =IFERROR(IF(NOT(ISNUMBER('T12 Analytics'!F150)),"⚪",IF('T12 Analytics'!F150<0.05,"✅",IF('T12 Analytics'!F150<0.08,"⚠️","❌"))),"⚪") | H57: =IFERROR(IF(NOT(ISNUMBER('T12 Analytics'!F150)),"No data",IF('T12 Analytics'!F150<0.05,"Schedule well-managed",IF('T12 Analytics'!F150<0.08,"Elevated OT","Severe OT — understaffed"))),"")
B58: Medicaid concentration | E58: =IFERROR(IF(ISNUMBER('Rent Roll Recon'!I41),'Rent Roll Recon'!I41,"—"),"—") | F58: < 20% of rev | G58: =IFERROR(IF(NOT(ISNUMBER('Rent Roll Recon'!I41)),"⚪",IF('Rent Roll Recon'!I41<0.2,"✅",IF('Rent Roll Recon'!I41<0.35,"⚠️","❌"))),"⚪") | H58: =IFERROR(IF(NOT(ISNUMBER('Rent Roll Recon'!I41)),"No data",IF('Rent Roll Recon'!I41<0.2,"Private-pay dominant",IF('Rent Roll Recon'!I41<0.35,"Material reimbursement risk","Heavy reimbursement exposure"))),"")
B59: Bad debt expense | E59: =IFERROR(IF(ISNUMBER('T12 Analytics'!F158),'T12 Analytics'!F158,"—"),"—") | F59: < 1% of rev | G59: =IFERROR(IF(NOT(ISNUMBER('T12 Analytics'!F158)),"⚪",IF('T12 Analytics'!F158<0.01,"✅",IF('T12 Analytics'!F158<0.025,"⚠️","❌"))),"⚪") | H59: =IFERROR(IF(NOT(ISNUMBER('T12 Analytics'!F158)),"No data",IF('T12 Analytics'!F158<0.01,"Strong collections",IF('T12 Analytics'!F158<0.025,"Watch AR aging","Collections issue"))),"")
B60: EBITDARM margin | E60: =IFERROR(IF(ISNUMBER('T12 Analytics'!F162),'T12 Analytics'!F162,"—"),"—") | F60: ≥ 25% | G60: =IFERROR(IF(NOT(ISNUMBER('T12 Analytics'!F162)),"⚪",IF('T12 Analytics'!F162>=0.25,"✅",IF('T12 Analytics'!F162>=0.18,"⚠️","❌"))),"⚪") | H60: =IFERROR(IF(NOT(ISNUMBER('T12 Analytics'!F162)),"No data",IF('T12 Analytics'!F162>=0.25,"Institutional-quality margin",IF('T12 Analytics'!F162>=0.18,"Sub-institutional margin","Significant margin compression"))),"")
B61: Going-in cap rate vs market | E61: =IFERROR(IF(ISNUMBER('T12 Analytics'!F118),'T12 Analytics'!F118,"—"),"—") | F61: ≥ 6.5% | G61: =IFERROR(IF(NOT(ISNUMBER('T12 Analytics'!F118)),"⚪",IF('T12 Analytics'!F118>=0.065,"✅",IF('T12 Analytics'!F118>=0.055,"⚠️","❌"))),"⚪") | H61: =IFERROR(IF(NOT(ISNUMBER('T12 Analytics'!F118)),"No data",IF('T12 Analytics'!F118>=0.065,"Wide of 6.2% market avg",IF('T12 Analytics'!F118>=0.055,"In line with market","Tight pricing — reaching"))),"")
B62: Loss to lease | E62: =IFERROR(IF(ISNUMBER('T12 Analytics'!F41),IFERROR('T12 Analytics'!F41/'T12 Analytics'!F37,0),"—"),"—") | F62: < 5% of GPR | G62: =IFERROR(IF(NOT(ISNUMBER('T12 Analytics'!F41)),"⚪",IF(IFERROR('T12 Analytics'!F41/'T12 Analytics'!F37,0)<0.05,"✅",IF(IFERROR('T12 Analytics'!F41/'T12 Analytics'!F37,0)<0.1,"⚠️","❌"))),"⚪") | H62: =IFERROR(IF(NOT(ISNUMBER('T12 Analytics'!F41)),"No data",IF(IFERROR('T12 Analytics'!F41/'T12 Analytics'!F37,0)<0.05,"Rate near market",IF(IFERROR('T12 Analytics'!F41/'T12 Analytics'!F37,0)<0.1,"Mark-to-market upside","Material rate compression"))),"")
B64: CAPACITY & OCCUPANCY — IL / AL / MC | H64: REVENUE QUALITY — ADR, RevPOR & ACUITY
B66: Care Type | C66: Licensed | D66: Occupied | E66: Occ % | F66: Target | H66: Metric | I66: IL | J66: AL | K66: MC | L66: Blended
B67: Independent Living | C67: =IFERROR(IF(ISNUMBER('T12 Analytics'!B6),'T12 Analytics'!B6,"—"),"—") | D67: =IFERROR(IF(ISNUMBER('T12 Analytics'!B11),'T12 Analytics'!B11,"—"),"—") | E67: =IFERROR(IF(AND(ISNUMBER(C67),ISNUMBER(D67),C67>0),D67/C67,"—"),"—") | F67: 90%+ | H67: ADR ($/bed/mo) | I67: =IFERROR(IF(AND(ISNUMBER('T12 Analytics'!B16),ISNUMBER('T12 Analytics'!B11),'T12 Analytics'!B11>0),'T12 Analytics'!B16/('T12 Analytics'!B11*12),"—"),"—") | J67: =IFERROR(IF(AND(ISNUMBER('T12 Analytics'!C16),ISNUMBER('T12 Analytics'!C11),'T12 Analytics'!C11>0),'T12 Analytics'!C16/('T12 Analytics'!C11*12),"—"),"—") | K67: =IFERROR(IF(AND(ISNUMBER('T12 Analytics'!D16),ISNUMBER('T12 Analytics'!D11),'T12 Analytics'!D11>0),'T12 Analytics'!D16/('T12 Analytics'!D11*12),"—"),"—") | L67: =IFERROR(IF(AND(ISNUMBER('T12 Analytics'!E16),ISNUMBER('T12 Analytics'!E11),'T12 Analytics'!E11>0),'T12 Analytics'!E16/('T12 Analytics'!E11*12),"—"),"—")
B68: Assisted Living | C68: =IFERROR(IF(ISNUMBER('T12 Analytics'!C6),'T12 Analytics'!C6,"—"),"—") | D68: =IFERROR(IF(ISNUMBER('T12 Analytics'!C11),'T12 Analytics'!C11,"—"),"—") | E68: =IFERROR(IF(AND(ISNUMBER(C68),ISNUMBER(D68),C68>0),D68/C68,"—"),"—") | F68: 87–92% | H68: RevPOR (base + LOC) | I68: =IFERROR(IF(AND(ISNUMBER('T12 Analytics'!B16),ISNUMBER('T12 Analytics'!B11),'T12 Analytics'!B11>0),('T12 Analytics'!B16+IFERROR('T12 Analytics'!B23,0))/('T12 Analytics'!B11*12),"—"),"—") | J68: =IFERROR(IF(AND(ISNUMBER('T12 Analytics'!C16),ISNUMBER('T12 Analytics'!C11),'T12 Analytics'!C11>0),('T12 Analytics'!C16+IFERROR('T12 Analytics'!C23,0))/('T12 Analytics'!C11*12),"—"),"—") | K68: =IFERROR(IF(AND(ISNUMBER('T12 Analytics'!D16),ISNUMBER('T12 Analytics'!D11),'T12 Analytics'!D11>0),('T12 Analytics'!D16+IFERROR('T12 Analytics'!D23,0))/('T12 Analytics'!D11*12),"—"),"—") | L68: =IFERROR(IF(AND(ISNUMBER('T12 Analytics'!E16),ISNUMBER('T12 Analytics'!E11),'T12 Analytics'!E11>0),('T12 Analytics'!E16+IFERROR('T12 Analytics'!E23,0))/('T12 Analytics'!E11*12),"—"),"—")
B69: Memory Care | C69: =IFERROR(IF(ISNUMBER('T12 Analytics'!D6),'T12 Analytics'!D6,"—"),"—") | D69: =IFERROR(IF(ISNUMBER('T12 Analytics'!D11),'T12 Analytics'!D11,"—"),"—") | E69: =IFERROR(IF(AND(ISNUMBER(C69),ISNUMBER(D69),C69>0),D69/C69,"—"),"—") | F69: 85–90% | H69: LOC as % of base rent | I69: =IFERROR(IF(AND(ISNUMBER('T12 Analytics'!B23),ISNUMBER('T12 Analytics'!B16),'T12 Analytics'!B16<>0),'T12 Analytics'!B23/'T12 Analytics'!B16,"—"),"—") | J69: =IFERROR(IF(AND(ISNUMBER('T12 Analytics'!C23),ISNUMBER('T12 Analytics'!C16),'T12 Analytics'!C16<>0),'T12 Analytics'!C23/'T12 Analytics'!C16,"—"),"—") | K69: =IFERROR(IF(AND(ISNUMBER('T12 Analytics'!D23),ISNUMBER('T12 Analytics'!D16),'T12 Analytics'!D16<>0),'T12 Analytics'!D23/'T12 Analytics'!D16,"—"),"—") | L69: =IFERROR(IF(AND(ISNUMBER('T12 Analytics'!E23),ISNUMBER('T12 Analytics'!E16),'T12 Analytics'!E16<>0),'T12 Analytics'!E23/'T12 Analytics'!E16,"—"),"—")
B70: Blended | C70: =IFERROR(IF(ISNUMBER('T12 Analytics'!E6),'T12 Analytics'!E6,"—"),"—") | D70: =IFERROR(IF(ISNUMBER('T12 Analytics'!E11),'T12 Analytics'!E11,"—"),"—") | E70: =IFERROR(IF(AND(ISNUMBER(C70),ISNUMBER(D70),C70>0),D70/C70,"—"),"—") | F70: — | H70: EGI / occupied bed / mo | I70: — | J70: — | K70: — | L70: =IFERROR(IF(AND(ISNUMBER('T12 Analytics'!F52),ISNUMBER('T12 Analytics'!E11),'T12 Analytics'!E11>0),'T12 Analytics'!F52/('T12 Analytics'!E11*12),"—"),"—")
B72: OPERATING MARGIN — T12 vs. INSTITUTIONAL BENCHMARK | H72: VALUATION — CAP RATE & PER-BED PRICING
B74: Line item | C74: T12 $ | D74: % EGI | E74: Benchmark | F74: Status | H74: Metric | I74: T12 Actual | K74: Normalized
B75: Effective Gross Income | C75: =IFERROR(IF(ISNUMBER('T12 Analytics'!F52),'T12 Analytics'!F52,"—"),"—") | D75: 1 | E75: 1 | H75: Purchase price (input) | I75: =IFERROR(IF(ISNUMBER('T12 Analytics'!F117),'T12 Analytics'!F117,"—"),"—") | K75: =IFERROR(IF(ISNUMBER('T12 Analytics'!F117),'T12 Analytics'!F117,"—"),"—")
B76: Labor & burden | C76: =IFERROR(IF(ISNUMBER('T12 Analytics'!F76),'T12 Analytics'!F76,"—"),"—") | D76: =IFERROR(IF(AND(ISNUMBER(C76),ISNUMBER($C$75),$C$75<>0),C76/$C$75,"—"),"—") | E76: 55–65% | F76: =IF(NOT(ISNUMBER(D76)),"—",IF(D76=0,"—",IF(D76>0.65,"⚠ HIGH",IF(D76<0.55,"✓ LOW","✓ OK")))) | H76: Going-in cap (EBITDARM) | I76: =IFERROR(IF(AND(ISNUMBER('T12 Analytics'!F161),ISNUMBER('T12 Analytics'!F117),'T12 Analytics'!F117<>0),'T12 Analytics'!F161/'T12 Analytics'!F117,"—"),"—") | K76: =IFERROR(IF(AND(ISNUMBER('T12 Analytics'!F161),ISNUMBER('T12 Analytics'!F117),'T12 Analytics'!F117<>0),'T12 Analytics'!F161/'T12 Analytics'!F117,"—"),"—")
B77: Non-labor opex | C77: =IFERROR(IF(ISNUMBER('T12 Analytics'!F103),'T12 Analytics'!F103,"—"),"—") | D77: =IFERROR(IF(AND(ISNUMBER(C77),ISNUMBER($C$75),$C$75<>0),C77/$C$75,"—"),"—") | E77: 25–35% | F77: =IF(NOT(ISNUMBER(D77)),"—",IF(D77=0,"—",IF(D77>0.35,"⚠ HIGH",IF(D77<0.25,"✓ LOW","✓ OK")))) | H77: Going-in cap (EBITDAR) | I77: =IFERROR(IF(AND(ISNUMBER('T12 Analytics'!F163),ISNUMBER('T12 Analytics'!F117),'T12 Analytics'!F117<>0),'T12 Analytics'!F163/'T12 Analytics'!F117,"—"),"—") | K77: =IFERROR(IF(AND(ISNUMBER('T12 Analytics'!F163),ISNUMBER('T12 Analytics'!F117),'T12 Analytics'!F117<>0),'T12 Analytics'!F163/'T12 Analytics'!F117,"—"),"—")
B78: EBITDARM (NOI) | C78: =IFERROR(IF(ISNUMBER('T12 Analytics'!F161),'T12 Analytics'!F161,"—"),"—") | D78: =IFERROR(IF(AND(ISNUMBER(C78),ISNUMBER($C$75),$C$75<>0),C78/$C$75,"—"),"—") | E78: 20–30%+ | F78: =IF(NOT(ISNUMBER(D78)),"—",IF(D78=0,"—",IF(D78<0.2,"⚠ LOW",IF(D78>0.3,"✓ STRONG","✓ OK")))) | H78: Price / licensed bed | I78: =IFERROR(IF(AND(ISNUMBER('T12 Analytics'!F117),ISNUMBER('T12 Analytics'!E6),'T12 Analytics'!E6>0),'T12 Analytics'!F117/'T12 Analytics'!E6,"—"),"—") | K78: =IFERROR(IF(AND(ISNUMBER('T12 Analytics'!F117),ISNUMBER('T12 Analytics'!E6),'T12 Analytics'!E6>0),'T12 Analytics'!F117/'T12 Analytics'!E6,"—"),"—")
B79: EBITDAR (after mgmt fee) | C79: =IFERROR(IF(ISNUMBER('T12 Analytics'!F163),'T12 Analytics'!F163,"—"),"—") | D79: =IFERROR(IF(AND(ISNUMBER(C79),ISNUMBER($C$75),$C$75<>0),C79/$C$75,"—"),"—") | E79: 15–25%+ | F79: =IF(NOT(ISNUMBER(D79)),"—",IF(D79=0,"—",IF(D79<0.15,"⚠ LOW",IF(D79>0.25,"✓ STRONG","✓ OK")))) | H79: EBITDARM multiple | I79: =IFERROR(IF(AND(ISNUMBER('T12 Analytics'!F117),ISNUMBER('T12 Analytics'!F161),'T12 Analytics'!F161<>0),'T12 Analytics'!F117/'T12 Analytics'!F161,"—"),"—") | K79: =IFERROR(IF(AND(ISNUMBER('T12 Analytics'!F117),ISNUMBER('T12 Analytics'!F161),'T12 Analytics'!F161<>0),'T12 Analytics'!F117/'T12 Analytics'!F161,"—"),"—")
B81: INSTITUTIONAL RISK CHECKLIST — ADDITIONAL CHECKS
B83: Risk factor | E83: Reading | F83: Threshold | G83: Flag
B84: RR vs T12 revenue gap | C84: Material variance between rent roll annualized revenue and T12 actual indicates restatement risk. | E84: =IFERROR(IF(AND(ISNUMBER('Rent Roll Recon'!E18),ISNUMBER('Rent Roll Recon'!E19),'Rent Roll Recon'!E19<>0),'Rent Roll Recon'!E18/'Rent Roll Recon'!E19,"—"),"—") | F84: ≤ ±3% | G84: =IF(NOT(ISNUMBER(E84)),"⚪",IF(ABS(E84)<=0.03,"✅",IF(ABS(E84)<=0.05,"⚠️","❌")))
B86: CHARTS — OCCUPANCY, MONTHLY EGI, PAYER MIX, P&L WATERFALL
B88: Chart 1 — Occupancy by Unit Type | E88: Chart 3 — Payer Mix (Revenue Share)
B89: Unit Type | C89: Occupancy | E89: Payer | F89: Share
B90: Independent Living | C90: =IFERROR(IF(AND(ISNUMBER('T12 Analytics'!B6),ISNUMBER('T12 Analytics'!B7),'T12 Analytics'!B6>0),'T12 Analytics'!B7/'T12 Analytics'!B6,0),0) | E90: Private Pay | F90: =IFERROR(IF(ISNUMBER('Rent Roll Recon'!I40),'Rent Roll Recon'!I40,0),0)
B91: Assisted Living | C91: =IFERROR(IF(AND(ISNUMBER('T12 Analytics'!C6),ISNUMBER('T12 Analytics'!C7),'T12 Analytics'!C6>0),'T12 Analytics'!C7/'T12 Analytics'!C6,0),0) | E91: Medicaid | F91: =IFERROR(IF(ISNUMBER('Rent Roll Recon'!I41),'Rent Roll Recon'!I41,0),0)
B92: Memory Care | C92: =IFERROR(IF(AND(ISNUMBER('T12 Analytics'!D6),ISNUMBER('T12 Analytics'!D7),'T12 Analytics'!D6>0),'T12 Analytics'!D7/'T12 Analytics'!D6,0),0) | E92: LTC Insurance | F92: =IFERROR(IF(ISNUMBER('Rent Roll Recon'!I42),'Rent Roll Recon'!I42,0),0)
B93: Blended | C93: =IFERROR(IF(AND(ISNUMBER('T12 Analytics'!E6),ISNUMBER('T12 Analytics'!E7),'T12 Analytics'!E6>0),'T12 Analytics'!E7/'T12 Analytics'!E6,0),0) | E93: VA | F93: =IFERROR(IF(ISNUMBER('Rent Roll Recon'!I43),'Rent Roll Recon'!I43,0),0)
E94: Managed Care | F94: =IFERROR(IF(ISNUMBER('Rent Roll Recon'!I44),'Rent Roll Recon'!I44,0),0)
B95: Chart 2 — Monthly EGI Trend | E95: Self-Pay | F95: =IFERROR(IF(ISNUMBER('Rent Roll Recon'!I45),'Rent Roll Recon'!I45,0),0)
B96: Month | C96: EGI | E96: Other | F96: =IFERROR(IF(ISNUMBER('Rent Roll Recon'!I46),'Rent Roll Recon'!I46,0),0)
B97: M01 | C97: =IFERROR('Monthly Trending'!B26,0)
B98: M02 | C98: =IFERROR('Monthly Trending'!C26,0) | E98: Chart 4 — P&L Waterfall
B99: M03 | C99: =IFERROR('Monthly Trending'!D26,0) | E99: Line | F99: T12
B100: M04 | C100: =IFERROR('Monthly Trending'!E26,0) | E100: EGI | F100: =IFERROR('T12 Analytics'!F52,0)
B101: M05 | C101: =IFERROR('Monthly Trending'!F26,0) | E101: Direct Labor | F101: =-IFERROR('T12 Analytics'!F65,0)
B102: M06 | C102: =IFERROR('Monthly Trending'!G26,0) | E102: Payroll Burden | F102: =-IFERROR('T12 Analytics'!F68+'T12 Analytics'!F69+'T12 Analytics'!F70,0)
B103: M07 | C103: =IFERROR('Monthly Trending'!H26,0) | E103: Non-Labor Opex | F103: =-IFERROR('T12 Analytics'!F103,0)
B104: M08 | C104: =IFERROR('Monthly Trending'!I26,0) | E104: Mgmt Fee | F104: =-IFERROR('T12 Analytics'!F106,0)
B105: M09 | C105: =IFERROR('Monthly Trending'!J26,0) | E105: EBITDAR | F105: =IFERROR('T12 Analytics'!F163,0)
B106: M10 | C106: =IFERROR('Monthly Trending'!K26,0)
B107: M11 | C107: =IFERROR('Monthly Trending'!L26,0)
B108: M12 | C108: =IFERROR('Monthly Trending'!M26,0)
