Workbook

Sheet Investment Dashboard
B2: SENIOR HOUSING — INVESTMENT DASHBOARD
B3: ="Property: " & 'T12 Analytics'!B2 & " | T12 Period: " & 'T12 Analytics'!E2 & " | Basis: " & 'T12 Analytics'!H2
B4: All KPIs link live to T12 Analytics and Rent Roll Recon. Update source tabs and values refresh.
B6: AT-A-GLANCE — T12 ACTUAL
B7: Total Licensed Beds | C7: Physical Occupancy | D7: Effective Gross Income | E7: EBITDARM Margin | F7: Going-In Cap (EBITDARM) | G7: Price / Licensed Bed
B8: ='T12 Analytics'!E6 | C8: ='T12 Analytics'!E8 | D8: ='T12 Analytics'!E52 | E8: ='T12 Analytics'!E162 | F8: ='T12 Analytics'!E118 | G8: ='T12 Analytics'!E123
B9: ="IL " & 'T12 Analytics'!B6 & " / AL " & 'T12 Analytics'!C6 & " / MC " & 'T12 Analytics'!D6 | C9: ="Target " & TEXT('T12 Analytics'!E10,"0%") & " | Gap " & TEXT('T12 Analytics'!E10-'T12 Analytics'!E8,"0.0%") | D9: ="Normalized: " & TEXT('T12 Analytics'!F52,"$#,##0") | E9: ="Normalized: " & TEXT('T12 Analytics'!F162,"0.0%") | F9: ="Stabilized: " & TEXT('T12 Analytics'!F118,"0.00%") | G9: ="Purchase: " & TEXT('T12 Analytics'!E117,"$#,##0,") & "K"
B11: 1. OCCUPANCY & CAPACITY
B12: Metric | C12: IL | D12: AL | E12: MC | F12: Total | G12: Target | H12: Status
B13: Licensed beds | C13: ='T12 Analytics'!B6 | D13: ='T12 Analytics'!C6 | E13: ='T12 Analytics'!D6 | F13: ='T12 Analytics'!E6
B14: Avg occupied beds (T12) | C14: ='T12 Analytics'!B7 | D14: ='T12 Analytics'!C7 | E14: ='T12 Analytics'!D7 | F14: ='T12 Analytics'!E7
B15: Physical occupancy % | C15: ='T12 Analytics'!B8 | D15: ='T12 Analytics'!C8 | E15: ='T12 Analytics'!D8 | F15: ='T12 Analytics'!E8 | G15: ='T12 Analytics'!E10 | H15: =IF(F15>=G15,"✓ At target",IF(F15>=G15-0.1,"⚠ Below","✗ Distressed"))
B16: Vacant beds | C16: ='Rent Roll Recon'!B9 | D16: ='Rent Roll Recon'!C9 | E16: ='Rent Roll Recon'!D9 | F16: ='Rent Roll Recon'!E9
B17: Beds to fill (to stabilization) | C17: =MAX(0,'T12 Analytics'!B11-'T12 Analytics'!B7) | D17: =MAX(0,'T12 Analytics'!C11-'T12 Analytics'!C7) | E17: =MAX(0,'T12 Analytics'!D11-'T12 Analytics'!D7) | F17: =SUM(C17:E17) | H17: Lease-up runway
B19: 2. REVENUE & RATE PERFORMANCE
B20: Metric | C20: IL | D20: AL | E20: MC | F20: Blended | G20: Normalized | H20: Delta
B21: ADR (base $/occ bed/mo) | C21: ='T12 Analytics'!B17 | D21: ='T12 Analytics'!C17 | E21: ='T12 Analytics'!D17 | F21: ='T12 Analytics'!E17
B22: RevPOR (base + LOC) | C22: ='T12 Analytics'!E141 | D22: ='T12 Analytics'!E142 | E22: ='T12 Analytics'!E143 | F22: ='T12 Analytics'!E144 | G22: ='T12 Analytics'!F144
B23: RevPAB ($/available bed/mo) | F23: ='T12 Analytics'!E145 | G23: ='T12 Analytics'!F145 | H23: =G23-F23
B24: LOC % of base rent (acuity) | F24: ='T12 Analytics'!E146 | G24: ='T12 Analytics'!F146
B25: T12 Base Rent ($) | C25: ='T12 Analytics'!B16 | D25: ='T12 Analytics'!C16 | E25: ='T12 Analytics'!D16 | F25: ='T12 Analytics'!E16 | G25: ='T12 Analytics'!F20 | H25: =G25-F25
B26: T12 LOC Revenue ($) | C26: ='T12 Analytics'!B23 | D26: ='T12 Analytics'!C23 | E26: ='T12 Analytics'!D23 | F26: ='T12 Analytics'!E23 | G26: ='T12 Analytics'!F27 | H26: =G26-F26
B27: Effective Gross Income (EGI) | F27: ='T12 Analytics'!E52 | G27: ='T12 Analytics'!F52 | H27: =G27-F27
B28: RR / T12 base rent gap (annualized) | F28: ='Rent Roll Recon'!E20 | G28: % of T12 | H28: =IFERROR('Rent Roll Recon'!E20/'Rent Roll Recon'!E19,"-")
B30: 3. MARGIN & COST STRUCTURE
B31: Metric | C31: T12 Actual | D31: Normalized | E31: Benchmark
B32: Total Operating Expenses (excl. mgmt) | C32: ='T12 Analytics'!E105 | D32: ='T12 Analytics'!F105
B33: Total labor & burden (% EGI) | C33: ='T12 Analytics'!E148 | D33: ='T12 Analytics'!F148 | E33: 55–65%
B34: Contract / agency labor (% direct) | C34: ='T12 Analytics'!E152 | D34: ='T12 Analytics'!F152 | E34: ≤3%
B35: Overtime (% direct wages) | C35: ='T12 Analytics'!E150 | D35: ='T12 Analytics'!F150 | E35: ≤5%
B36: Food cost (% EGI) | C36: ='T12 Analytics'!E155 | D36: ='T12 Analytics'!F155 | E36: 6–9%
B37: Food cost per patient day (PPD) | C37: ='T12 Analytics'!E154 | D37: ='T12 Analytics'!F154 | E37: $8–14
B38: P&C insurance (% EGI) | C38: ='T12 Analytics'!E159 | D38: ='T12 Analytics'!F159 | E38: 4–7%
B39: Bad debt (% gross revenue) | C39: ='T12 Analytics'!E158 | D39: ='T12 Analytics'!F158 | E39: ≤2%
B40: Mgmt fee (% revenue) | C40: ='T12 Analytics'!E157 | D40: ='T12 Analytics'!F157 | E40: 5–7%
B41: OpEx per occupied bed / month | C41: ='T12 Analytics'!E160 | D41: ='T12 Analytics'!F160
B43: EBITDARM ($) | C43: ='T12 Analytics'!E108 | D43: ='T12 Analytics'!F108 | E43: =D43-C43
B44: EBITDARM margin (%) | C44: ='T12 Analytics'!E162 | D44: ='T12 Analytics'!F162 | E44: 20–30%+
B45: EBITDAR ($, after mgmt fee) | C45: ='T12 Analytics'!E110 | D45: ='T12 Analytics'!F110 | E45: 15–25%+
B46: EBITDAR margin (%) | C46: ='T12 Analytics'!E164 | D46: ='T12 Analytics'!F164
B48: 4. VALUATION & ACQUISITION METRICS
B49: Metric | C49: T12 Actual | D49: Normalized | E49: Note
B50: Purchase price | C50: ='T12 Analytics'!E117 | D50: ='T12 Analytics'!F117 | E50: Input
B51: Going-in cap rate (EBITDARM) | C51: ='T12 Analytics'!E118 | D51: ='T12 Analytics'!F118 | E51: ="Expansion: +" & TEXT(D51-C51,"0.00%")
B52: Going-in cap rate (EBITDAR, post mgmt) | C52: ='T12 Analytics'!E120 | D52: ='T12 Analytics'!F120
B53: Price per licensed bed | C53: ='T12 Analytics'!E123
B54: Price per AL bed | C54: ='T12 Analytics'!E124
B55: Price per MC bed | C55: ='T12 Analytics'!E125
B56: Gross Revenue Multiple | C56: ='T12 Analytics'!E127 | D56: ='T12 Analytics'!F127
B57: EBITDARM multiple | C57: ='T12 Analytics'!E128 | D57: ='T12 Analytics'!F128
B59: 5. PAYER MIX & ACUITY (from Rent Roll)
B60: Payer Type | C60: Residents | D60: % Mix | E60: Monthly Rev | F60: % Revenue
B61: Private Pay | C61: ='Rent Roll Recon'!B40 | D61: ='Rent Roll Recon'!C40 | E61: ='Rent Roll Recon'!H40 | F61: ='Rent Roll Recon'!I40
B62: Medicaid | C62: ='Rent Roll Recon'!B41 | D62: ='Rent Roll Recon'!C41 | E62: ='Rent Roll Recon'!H41 | F62: ='Rent Roll Recon'!I41
B63: LTC Insurance | C63: ='Rent Roll Recon'!B42 | D63: ='Rent Roll Recon'!C42 | E63: ='Rent Roll Recon'!H42 | F63: ='Rent Roll Recon'!I42
B64: VA | C64: ='Rent Roll Recon'!B43 | D64: ='Rent Roll Recon'!C43 | E64: ='Rent Roll Recon'!H43 | F64: ='Rent Roll Recon'!I43
B65: Managed Care | C65: ='Rent Roll Recon'!B44 | D65: ='Rent Roll Recon'!C44 | E65: ='Rent Roll Recon'!H44 | F65: ='Rent Roll Recon'!I44
B66: Self-Pay | C66: ='Rent Roll Recon'!B45 | D66: ='Rent Roll Recon'!C45 | E66: ='Rent Roll Recon'!H45 | F66: ='Rent Roll Recon'!I45
B67: Other | C67: ='Rent Roll Recon'!B46 | D67: ='Rent Roll Recon'!C46 | E67: ='Rent Roll Recon'!H46 | F67: ='Rent Roll Recon'!I46
B68: Total | C68: =SUM(C61:C67) | D68: =SUM(D61:D67) | E68: =SUM(E61:E67) | F68: =SUM(F61:F67)
B70: 6 · AL CARE LEVEL DISTRIBUTION (acuity mix)
B72: Care Level | C72: Residents | D72: % Occupied | E72: Total $/mo | F72: Avg $/Res | G72: % LOC Rev
B73: Basic | C73: ='Rent Roll Recon'!B59 | D73: ='Rent Roll Recon'!C59 | E73: ='Rent Roll Recon'!D59 | F73: ='Rent Roll Recon'!E59 | G73: ='Rent Roll Recon'!G59
B74: Level 2 | C74: ='Rent Roll Recon'!B60 | D74: ='Rent Roll Recon'!C60 | E74: ='Rent Roll Recon'!D60 | F74: ='Rent Roll Recon'!E60 | G74: ='Rent Roll Recon'!G60
B75: Level 3 | C75: ='Rent Roll Recon'!B61 | D75: ='Rent Roll Recon'!C61 | E75: ='Rent Roll Recon'!D61 | F75: ='Rent Roll Recon'!E61 | G75: ='Rent Roll Recon'!G61
B76: Level 4 | C76: ='Rent Roll Recon'!B62 | D76: ='Rent Roll Recon'!C62 | E76: ='Rent Roll Recon'!D62 | F76: ='Rent Roll Recon'!E62 | G76: ='Rent Roll Recon'!G62
B77: Level 5 | C77: ='Rent Roll Recon'!B63 | D77: ='Rent Roll Recon'!C63 | E77: ='Rent Roll Recon'!D63 | F77: ='Rent Roll Recon'!E63 | G77: ='Rent Roll Recon'!G63
B78: Level 6 | C78: ='Rent Roll Recon'!B64 | D78: ='Rent Roll Recon'!C64 | E78: ='Rent Roll Recon'!D64 | F78: ='Rent Roll Recon'!E64 | G78: ='Rent Roll Recon'!G64
B79: Level 7 | C79: ='Rent Roll Recon'!B65 | D79: ='Rent Roll Recon'!C65 | E79: ='Rent Roll Recon'!D65 | F79: ='Rent Roll Recon'!E65 | G79: ='Rent Roll Recon'!G65
B80: Other | C80: ='Rent Roll Recon'!B66 | D80: ='Rent Roll Recon'!C66 | E80: ='Rent Roll Recon'!D66 | F80: ='Rent Roll Recon'!E66 | G80: ='Rent Roll Recon'!G66
B81: Total | C81: =SUM(C73:C80) | D81: =SUM(D73:D80) | E81: =SUM(E73:E80) | F81: =IFERROR(E81/C81,"-") | G81: =SUM(G73:G80)
B83: Higher acuity (L4-L7) shows greater rate uplift opportunity; Basic & L2 dominate the mix at this property.
B85: 7 · KEY RISKS & NORMALIZATION CALLOUTS
B87: Flag | C87: Observation | E87: Metric | F87: Underwriting Impact
B88: 🔴 | C88: Going-in EBITDARM cap is negative on T12 actuals | E88: ='T12 Analytics'!E118 | F88: Deal underwrites only on stabilization; no current-cash-flow support.
B89: 🔴 | C89: Physical occupancy well below stabilized target | E89: =G15-F15 | F89: ="Lease-up risk; need "&TEXT(F17,"0")&" add'l occ. beds to hit 75% stabilization."
B90: 🟠 | C90: T12 base rent below rent roll run-rate | E90: ='Rent Roll Recon'!E20 | F90: Diligence: confirm timing of rent increases vs T12 window; vacancy mix.
B91: 🟠 | C91: Single payer concentration (100% Private Pay) | E91: =F61 | F91: Insulated from Medicaid risk, but exposed to local affordability shocks.
B92: 🟢 | C92: Stabilized cap rate strong on normalized EBITDARM | E92: ='T12 Analytics'!F118 | F92: Significant cap rate expansion (Going-in → Stabilized) if lease-up executes.
B93: 🟢 | C93: Attractive price per bed vs market benchmarks | E93: ='T12 Analytics'!E123 | F93: Below typical AL/MC replacement cost; basis protection.
B94: 🟠 | C94: Acuity mix skews low (Basic + L2 = 65% of residents) | E94: =D73+D74 | F94: Opportunity to migrate residents up in care level for organic LOC revenue growth.
B96: Legend: 🔴 Critical risk · 🟠 Watch item · 🟢 Positive
B98: All figures sourced from T12 Analytics and Rent Roll Recon tabs. Normalized figures reflect stabilized occupancy / market-rate adjustments per the underlying model.
